package com.google.firebase.iid;

import android.content.Context;
import android.content.SharedPreferences;
import android.content.SharedPreferences.Editor;
import android.support.annotation.Nullable;
import android.support.annotation.WorkerThread;
import android.support.v4.content.ContextCompat;
import android.text.TextUtils;
import android.util.Base64;
import android.util.Log;
import java.io.File;
import java.io.IOException;
import java.io.UnsupportedEncodingException;
import java.nio.channels.Channels;
import java.nio.channels.FileChannel;
import java.util.Properties;

final class zzy
{
  zzy() {}
  
  /* Error */
  @Nullable
  private final zzz zza(Context paramContext, String paramString, zzz paramZzz, boolean paramBoolean)
  {
    // Byte code:
    //   0: ldc 20
    //   2: iconst_3
    //   3: invokestatic 26	android/util/Log:isLoggable	(Ljava/lang/String;I)Z
    //   6: ifeq +11 -> 17
    //   9: ldc 20
    //   11: ldc 28
    //   13: invokestatic 32	android/util/Log:d	(Ljava/lang/String;Ljava/lang/String;)I
    //   16: pop
    //   17: new 34	java/util/Properties
    //   20: dup
    //   21: invokespecial 35	java/util/Properties:<init>	()V
    //   24: astore 9
    //   26: aload 9
    //   28: ldc 37
    //   30: aload_3
    //   31: invokestatic 42	com/google/firebase/iid/zzz:zza	(Lcom/google/firebase/iid/zzz;)Ljava/lang/String;
    //   34: invokevirtual 46	java/util/Properties:setProperty	(Ljava/lang/String;Ljava/lang/String;)Ljava/lang/Object;
    //   37: pop
    //   38: aload 9
    //   40: ldc 48
    //   42: aload_3
    //   43: invokestatic 51	com/google/firebase/iid/zzz:zzb	(Lcom/google/firebase/iid/zzz;)Ljava/lang/String;
    //   46: invokevirtual 46	java/util/Properties:setProperty	(Ljava/lang/String;Ljava/lang/String;)Ljava/lang/Object;
    //   49: pop
    //   50: aload 9
    //   52: ldc 53
    //   54: aload_3
    //   55: invokestatic 57	com/google/firebase/iid/zzz:zzc	(Lcom/google/firebase/iid/zzz;)J
    //   58: invokestatic 63	java/lang/String:valueOf	(J)Ljava/lang/String;
    //   61: invokevirtual 46	java/util/Properties:setProperty	(Ljava/lang/String;Ljava/lang/String;)Ljava/lang/Object;
    //   64: pop
    //   65: aload_1
    //   66: aload_2
    //   67: invokestatic 67	com/google/firebase/iid/zzy:zzf	(Landroid/content/Context;Ljava/lang/String;)Ljava/io/File;
    //   70: astore_1
    //   71: aload_1
    //   72: invokevirtual 73	java/io/File:createNewFile	()Z
    //   75: pop
    //   76: new 75	java/io/RandomAccessFile
    //   79: dup
    //   80: aload_1
    //   81: ldc 77
    //   83: invokespecial 80	java/io/RandomAccessFile:<init>	(Ljava/io/File;Ljava/lang/String;)V
    //   86: astore 7
    //   88: aload 7
    //   90: invokevirtual 84	java/io/RandomAccessFile:getChannel	()Ljava/nio/channels/FileChannel;
    //   93: astore 8
    //   95: aload 8
    //   97: invokevirtual 90	java/nio/channels/FileChannel:lock	()Ljava/nio/channels/FileLock;
    //   100: pop
    //   101: iload 4
    //   103: ifeq +105 -> 208
    //   106: aload 8
    //   108: invokevirtual 94	java/nio/channels/FileChannel:size	()J
    //   111: lstore 5
    //   113: lload 5
    //   115: lconst_0
    //   116: lcmp
    //   117: ifle +91 -> 208
    //   120: aload 8
    //   122: lconst_0
    //   123: invokevirtual 98	java/nio/channels/FileChannel:position	(J)Ljava/nio/channels/FileChannel;
    //   126: pop
    //   127: aload 8
    //   129: invokestatic 101	com/google/firebase/iid/zzy:zza	(Ljava/nio/channels/FileChannel;)Lcom/google/firebase/iid/zzz;
    //   132: astore_1
    //   133: aload 8
    //   135: ifnull +9 -> 144
    //   138: aconst_null
    //   139: aload 8
    //   141: invokestatic 104	com/google/firebase/iid/zzy:zza	(Ljava/lang/Throwable;Ljava/nio/channels/FileChannel;)V
    //   144: aconst_null
    //   145: aload 7
    //   147: invokestatic 107	com/google/firebase/iid/zzy:zza	(Ljava/lang/Throwable;Ljava/io/RandomAccessFile;)V
    //   150: aload_1
    //   151: areturn
    //   152: astore_1
    //   153: ldc 20
    //   155: iconst_3
    //   156: invokestatic 26	android/util/Log:isLoggable	(Ljava/lang/String;I)Z
    //   159: ifeq +49 -> 208
    //   162: aload_1
    //   163: invokestatic 110	java/lang/String:valueOf	(Ljava/lang/Object;)Ljava/lang/String;
    //   166: astore_1
    //   167: new 112	java/lang/StringBuilder
    //   170: dup
    //   171: aload_1
    //   172: invokestatic 110	java/lang/String:valueOf	(Ljava/lang/Object;)Ljava/lang/String;
    //   175: invokevirtual 116	java/lang/String:length	()I
    //   178: bipush 64
    //   180: iadd
    //   181: invokespecial 119	java/lang/StringBuilder:<init>	(I)V
    //   184: astore_2
    //   185: aload_2
    //   186: ldc 121
    //   188: invokevirtual 125	java/lang/StringBuilder:append	(Ljava/lang/String;)Ljava/lang/StringBuilder;
    //   191: pop
    //   192: aload_2
    //   193: aload_1
    //   194: invokevirtual 125	java/lang/StringBuilder:append	(Ljava/lang/String;)Ljava/lang/StringBuilder;
    //   197: pop
    //   198: ldc 20
    //   200: aload_2
    //   201: invokevirtual 129	java/lang/StringBuilder:toString	()Ljava/lang/String;
    //   204: invokestatic 32	android/util/Log:d	(Ljava/lang/String;Ljava/lang/String;)I
    //   207: pop
    //   208: aload 8
    //   210: lconst_0
    //   211: invokevirtual 98	java/nio/channels/FileChannel:position	(J)Ljava/nio/channels/FileChannel;
    //   214: pop
    //   215: aload 9
    //   217: aload 8
    //   219: invokestatic 135	java/nio/channels/Channels:newOutputStream	(Ljava/nio/channels/WritableByteChannel;)Ljava/io/OutputStream;
    //   222: aconst_null
    //   223: invokevirtual 139	java/util/Properties:store	(Ljava/io/OutputStream;Ljava/lang/String;)V
    //   226: aload 8
    //   228: ifnull +9 -> 237
    //   231: aconst_null
    //   232: aload 8
    //   234: invokestatic 104	com/google/firebase/iid/zzy:zza	(Ljava/lang/Throwable;Ljava/nio/channels/FileChannel;)V
    //   237: aconst_null
    //   238: aload 7
    //   240: invokestatic 107	com/google/firebase/iid/zzy:zza	(Ljava/lang/Throwable;Ljava/io/RandomAccessFile;)V
    //   243: aload_3
    //   244: areturn
    //   245: astore_2
    //   246: aconst_null
    //   247: astore_1
    //   248: goto +7 -> 255
    //   251: astore_1
    //   252: aload_1
    //   253: athrow
    //   254: astore_2
    //   255: aload 8
    //   257: ifnull +9 -> 266
    //   260: aload_1
    //   261: aload 8
    //   263: invokestatic 104	com/google/firebase/iid/zzy:zza	(Ljava/lang/Throwable;Ljava/nio/channels/FileChannel;)V
    //   266: aload_2
    //   267: athrow
    //   268: astore_2
    //   269: aconst_null
    //   270: astore_1
    //   271: goto +7 -> 278
    //   274: astore_1
    //   275: aload_1
    //   276: athrow
    //   277: astore_2
    //   278: aload_1
    //   279: aload 7
    //   281: invokestatic 107	com/google/firebase/iid/zzy:zza	(Ljava/lang/Throwable;Ljava/io/RandomAccessFile;)V
    //   284: aload_2
    //   285: athrow
    //   286: astore_1
    //   287: aload_1
    //   288: invokestatic 110	java/lang/String:valueOf	(Ljava/lang/Object;)Ljava/lang/String;
    //   291: astore_1
    //   292: new 112	java/lang/StringBuilder
    //   295: dup
    //   296: aload_1
    //   297: invokestatic 110	java/lang/String:valueOf	(Ljava/lang/Object;)Ljava/lang/String;
    //   300: invokevirtual 116	java/lang/String:length	()I
    //   303: bipush 21
    //   305: iadd
    //   306: invokespecial 119	java/lang/StringBuilder:<init>	(I)V
    //   309: astore_2
    //   310: aload_2
    //   311: ldc -115
    //   313: invokevirtual 125	java/lang/StringBuilder:append	(Ljava/lang/String;)Ljava/lang/StringBuilder;
    //   316: pop
    //   317: aload_2
    //   318: aload_1
    //   319: invokevirtual 125	java/lang/StringBuilder:append	(Ljava/lang/String;)Ljava/lang/StringBuilder;
    //   322: pop
    //   323: ldc 20
    //   325: aload_2
    //   326: invokevirtual 129	java/lang/StringBuilder:toString	()Ljava/lang/String;
    //   329: invokestatic 144	android/util/Log:w	(Ljava/lang/String;Ljava/lang/String;)I
    //   332: pop
    //   333: aconst_null
    //   334: areturn
    // Local variable table:
    //   start	length	slot	name	signature
    //   0	335	0	this	zzy
    //   0	335	1	paramContext	Context
    //   0	335	2	paramString	String
    //   0	335	3	paramZzz	zzz
    //   0	335	4	paramBoolean	boolean
    //   111	3	5	l	long
    //   86	194	7	localRandomAccessFile	java.io.RandomAccessFile
    //   93	169	8	localFileChannel	FileChannel
    //   24	192	9	localProperties	Properties
    // Exception table:
    //   from	to	target	type
    //   120	133	152	java/io/IOException
    //   120	133	152	com/google/firebase/iid/zzaa
    //   95	101	245	finally
    //   106	113	245	finally
    //   120	133	245	finally
    //   153	208	245	finally
    //   208	226	245	finally
    //   95	101	251	java/lang/Throwable
    //   106	113	251	java/lang/Throwable
    //   120	133	251	java/lang/Throwable
    //   153	208	251	java/lang/Throwable
    //   208	226	251	java/lang/Throwable
    //   252	254	254	finally
    //   88	95	268	finally
    //   138	144	268	finally
    //   231	237	268	finally
    //   260	266	268	finally
    //   266	268	268	finally
    //   88	95	274	java/lang/Throwable
    //   138	144	274	java/lang/Throwable
    //   231	237	274	java/lang/Throwable
    //   260	266	274	java/lang/Throwable
    //   266	268	274	java/lang/Throwable
    //   275	277	277	finally
    //   71	88	286	java/io/IOException
    //   144	150	286	java/io/IOException
    //   237	243	286	java/io/IOException
    //   278	286	286	java/io/IOException
  }
  
  @Nullable
  private static zzz zza(SharedPreferences paramSharedPreferences, String paramString)
    throws zzaa
  {
    String str1 = paramSharedPreferences.getString(zzaw.zzd(paramString, "|P|"), null);
    String str2 = paramSharedPreferences.getString(zzaw.zzd(paramString, "|K|"), null);
    if (str1 != null)
    {
      if (str2 == null) {
        return null;
      }
      return new zzz(zzc(str1, str2), zzb(paramSharedPreferences, paramString));
    }
    return null;
  }
  
  /* Error */
  private final zzz zza(File paramFile)
    throws zzaa, IOException
  {
    // Byte code:
    //   0: new 174	java/io/FileInputStream
    //   3: dup
    //   4: aload_1
    //   5: invokespecial 177	java/io/FileInputStream:<init>	(Ljava/io/File;)V
    //   8: astore 5
    //   10: aconst_null
    //   11: astore 4
    //   13: aload 4
    //   15: astore_1
    //   16: aload 5
    //   18: invokevirtual 178	java/io/FileInputStream:getChannel	()Ljava/nio/channels/FileChannel;
    //   21: astore 6
    //   23: aload 6
    //   25: lconst_0
    //   26: ldc2_w 179
    //   29: iconst_1
    //   30: invokevirtual 183	java/nio/channels/FileChannel:lock	(JJZ)Ljava/nio/channels/FileLock;
    //   33: pop
    //   34: aload 6
    //   36: invokestatic 101	com/google/firebase/iid/zzy:zza	(Ljava/nio/channels/FileChannel;)Lcom/google/firebase/iid/zzz;
    //   39: astore_2
    //   40: aload 6
    //   42: ifnull +12 -> 54
    //   45: aload 4
    //   47: astore_1
    //   48: aconst_null
    //   49: aload 6
    //   51: invokestatic 104	com/google/firebase/iid/zzy:zza	(Ljava/lang/Throwable;Ljava/nio/channels/FileChannel;)V
    //   54: aconst_null
    //   55: aload 5
    //   57: invokestatic 186	com/google/firebase/iid/zzy:zza	(Ljava/lang/Throwable;Ljava/io/FileInputStream;)V
    //   60: aload_2
    //   61: areturn
    //   62: astore_2
    //   63: aconst_null
    //   64: astore_3
    //   65: goto +7 -> 72
    //   68: astore_3
    //   69: aload_3
    //   70: athrow
    //   71: astore_2
    //   72: aload 6
    //   74: ifnull +12 -> 86
    //   77: aload 4
    //   79: astore_1
    //   80: aload_3
    //   81: aload 6
    //   83: invokestatic 104	com/google/firebase/iid/zzy:zza	(Ljava/lang/Throwable;Ljava/nio/channels/FileChannel;)V
    //   86: aload 4
    //   88: astore_1
    //   89: aload_2
    //   90: athrow
    //   91: astore_2
    //   92: goto +8 -> 100
    //   95: astore_2
    //   96: aload_2
    //   97: astore_1
    //   98: aload_2
    //   99: athrow
    //   100: aload_1
    //   101: aload 5
    //   103: invokestatic 186	com/google/firebase/iid/zzy:zza	(Ljava/lang/Throwable;Ljava/io/FileInputStream;)V
    //   106: aload_2
    //   107: athrow
    // Local variable table:
    //   start	length	slot	name	signature
    //   0	108	0	this	zzy
    //   0	108	1	paramFile	File
    //   39	22	2	localZzz	zzz
    //   62	1	2	localObject1	Object
    //   71	19	2	localObject2	Object
    //   91	1	2	localObject3	Object
    //   95	12	2	localThrowable1	Throwable
    //   64	1	3	localObject4	Object
    //   68	13	3	localThrowable2	Throwable
    //   11	76	4	localObject5	Object
    //   8	94	5	localFileInputStream	java.io.FileInputStream
    //   21	61	6	localFileChannel	FileChannel
    // Exception table:
    //   from	to	target	type
    //   23	40	62	finally
    //   23	40	68	java/lang/Throwable
    //   69	71	71	finally
    //   16	23	91	finally
    //   48	54	91	finally
    //   80	86	91	finally
    //   89	91	91	finally
    //   98	100	91	finally
    //   16	23	95	java/lang/Throwable
    //   48	54	95	java/lang/Throwable
    //   80	86	95	java/lang/Throwable
    //   89	91	95	java/lang/Throwable
  }
  
  private static zzz zza(FileChannel paramFileChannel)
    throws zzaa, IOException
  {
    Properties localProperties = new Properties();
    localProperties.load(Channels.newInputStream(paramFileChannel));
    paramFileChannel = localProperties.getProperty("pub");
    String str = localProperties.getProperty("pri");
    if ((paramFileChannel != null) && (str != null))
    {
      paramFileChannel = zzc(paramFileChannel, str);
      try
      {
        long l = Long.parseLong(localProperties.getProperty("cre"));
        return new zzz(paramFileChannel, l);
      }
      catch (NumberFormatException paramFileChannel)
      {
        throw new zzaa(paramFileChannel);
      }
    }
    throw new zzaa("Invalid properties file");
  }
  
  static void zza(Context paramContext)
  {
    paramContext = zzb(paramContext).listFiles();
    int j = paramContext.length;
    int i = 0;
    while (i < j)
    {
      Object localObject = paramContext[i];
      if (localObject.getName().startsWith("com.google.InstanceId")) {
        localObject.delete();
      }
      i += 1;
    }
  }
  
  private final void zza(Context paramContext, String paramString, zzz paramZzz)
  {
    paramContext = paramContext.getSharedPreferences("com.google.android.gms.appid", 0);
    try
    {
      boolean bool = paramZzz.equals(zza(paramContext, paramString));
      if (bool) {
        return;
      }
    }
    catch (zzaa localZzaa)
    {
      for (;;) {}
    }
    if (Log.isLoggable("FirebaseInstanceId", 3)) {
      Log.d("FirebaseInstanceId", "Writing key to shared preferences");
    }
    paramContext = paramContext.edit();
    paramContext.putString(zzaw.zzd(paramString, "|P|"), zzz.zza(paramZzz));
    paramContext.putString(zzaw.zzd(paramString, "|K|"), zzz.zzb(paramZzz));
    paramContext.putString(zzaw.zzd(paramString, "cre"), String.valueOf(zzz.zzc(paramZzz)));
    paramContext.commit();
  }
  
  private static long zzb(SharedPreferences paramSharedPreferences, String paramString)
  {
    paramSharedPreferences = paramSharedPreferences.getString(zzaw.zzd(paramString, "cre"), null);
    if (paramSharedPreferences != null) {}
    try
    {
      long l = Long.parseLong(paramSharedPreferences);
      return l;
    }
    catch (NumberFormatException paramSharedPreferences)
    {
      for (;;) {}
    }
    return 0L;
  }
  
  private static File zzb(Context paramContext)
  {
    File localFile = ContextCompat.getNoBackupFilesDir(paramContext);
    if ((localFile != null) && (localFile.isDirectory())) {
      return localFile;
    }
    Log.w("FirebaseInstanceId", "noBackupFilesDir doesn't exist, using regular files directory instead");
    return paramContext.getFilesDir();
  }
  
  /* Error */
  private static java.security.KeyPair zzc(String paramString1, String paramString2)
    throws zzaa
  {
    // Byte code:
    //   0: aload_0
    //   1: bipush 8
    //   3: invokestatic 300	android/util/Base64:decode	(Ljava/lang/String;I)[B
    //   6: astore_0
    //   7: aload_1
    //   8: bipush 8
    //   10: invokestatic 300	android/util/Base64:decode	(Ljava/lang/String;I)[B
    //   13: astore_1
    //   14: ldc_w 302
    //   17: invokestatic 308	java/security/KeyFactory:getInstance	(Ljava/lang/String;)Ljava/security/KeyFactory;
    //   20: astore_2
    //   21: new 310	java/security/KeyPair
    //   24: dup
    //   25: aload_2
    //   26: new 312	java/security/spec/X509EncodedKeySpec
    //   29: dup
    //   30: aload_0
    //   31: invokespecial 315	java/security/spec/X509EncodedKeySpec:<init>	([B)V
    //   34: invokevirtual 319	java/security/KeyFactory:generatePublic	(Ljava/security/spec/KeySpec;)Ljava/security/PublicKey;
    //   37: aload_2
    //   38: new 321	java/security/spec/PKCS8EncodedKeySpec
    //   41: dup
    //   42: aload_1
    //   43: invokespecial 322	java/security/spec/PKCS8EncodedKeySpec:<init>	([B)V
    //   46: invokevirtual 326	java/security/KeyFactory:generatePrivate	(Ljava/security/spec/KeySpec;)Ljava/security/PrivateKey;
    //   49: invokespecial 329	java/security/KeyPair:<init>	(Ljava/security/PublicKey;Ljava/security/PrivateKey;)V
    //   52: astore_0
    //   53: aload_0
    //   54: areturn
    //   55: astore_0
    //   56: aload_0
    //   57: invokestatic 110	java/lang/String:valueOf	(Ljava/lang/Object;)Ljava/lang/String;
    //   60: astore_1
    //   61: new 112	java/lang/StringBuilder
    //   64: dup
    //   65: aload_1
    //   66: invokestatic 110	java/lang/String:valueOf	(Ljava/lang/Object;)Ljava/lang/String;
    //   69: invokevirtual 116	java/lang/String:length	()I
    //   72: bipush 19
    //   74: iadd
    //   75: invokespecial 119	java/lang/StringBuilder:<init>	(I)V
    //   78: astore_2
    //   79: aload_2
    //   80: ldc_w 331
    //   83: invokevirtual 125	java/lang/StringBuilder:append	(Ljava/lang/String;)Ljava/lang/StringBuilder;
    //   86: pop
    //   87: aload_2
    //   88: aload_1
    //   89: invokevirtual 125	java/lang/StringBuilder:append	(Ljava/lang/String;)Ljava/lang/StringBuilder;
    //   92: pop
    //   93: ldc 20
    //   95: aload_2
    //   96: invokevirtual 129	java/lang/StringBuilder:toString	()Ljava/lang/String;
    //   99: invokestatic 144	android/util/Log:w	(Ljava/lang/String;Ljava/lang/String;)I
    //   102: pop
    //   103: new 18	com/google/firebase/iid/zzaa
    //   106: dup
    //   107: aload_0
    //   108: invokespecial 209	com/google/firebase/iid/zzaa:<init>	(Ljava/lang/Exception;)V
    //   111: athrow
    //   112: astore_0
    //   113: new 18	com/google/firebase/iid/zzaa
    //   116: dup
    //   117: aload_0
    //   118: invokespecial 209	com/google/firebase/iid/zzaa:<init>	(Ljava/lang/Exception;)V
    //   121: athrow
    // Local variable table:
    //   start	length	slot	name	signature
    //   0	122	0	paramString1	String
    //   0	122	1	paramString2	String
    //   20	76	2	localObject	Object
    // Exception table:
    //   from	to	target	type
    //   14	53	55	java/security/spec/InvalidKeySpecException
    //   14	53	55	java/security/NoSuchAlgorithmException
    //   0	14	112	java/lang/IllegalArgumentException
  }
  
  @Nullable
  private final zzz zzd(Context paramContext, String paramString)
    throws zzaa
  {
    try
    {
      zzz localZzz1 = zze(paramContext, paramString);
      if (localZzz1 != null)
      {
        zza(paramContext, paramString, localZzz1);
        return localZzz1;
      }
      localZzz1 = null;
    }
    catch (zzaa localZzaa1) {}
    try
    {
      zzz localZzz2 = zza(paramContext.getSharedPreferences("com.google.android.gms.appid", 0), paramString);
      if (localZzz2 != null)
      {
        zza(paramContext, paramString, localZzz2, false);
        return localZzz2;
      }
    }
    catch (zzaa localZzaa2)
    {
      if (localZzaa2 == null) {
        return null;
      }
      throw localZzaa2;
    }
  }
  
  @Nullable
  private final zzz zze(Context paramContext, String paramString)
    throws zzaa
  {
    paramContext = zzf(paramContext, paramString);
    if (!paramContext.exists()) {
      return null;
    }
    try
    {
      paramString = zza(paramContext);
      return paramString;
    }
    catch (zzaa|IOException paramString)
    {
      StringBuilder localStringBuilder;
      if (Log.isLoggable("FirebaseInstanceId", 3))
      {
        paramString = String.valueOf(paramString);
        localStringBuilder = new StringBuilder(String.valueOf(paramString).length() + 40);
        localStringBuilder.append("Failed to read key from file, retrying: ");
        localStringBuilder.append(paramString);
        Log.d("FirebaseInstanceId", localStringBuilder.toString());
      }
      try
      {
        paramContext = zza(paramContext);
        return paramContext;
      }
      catch (IOException paramContext)
      {
        paramString = String.valueOf(paramContext);
        localStringBuilder = new StringBuilder(String.valueOf(paramString).length() + 45);
        localStringBuilder.append("IID file exists, but failed to read from it: ");
        localStringBuilder.append(paramString);
        Log.w("FirebaseInstanceId", localStringBuilder.toString());
        throw new zzaa(paramContext);
      }
    }
  }
  
  private static File zzf(Context paramContext, String paramString)
  {
    if (TextUtils.isEmpty(paramString)) {
      paramString = "com.google.InstanceId.properties";
    }
    try
    {
      paramString = Base64.encodeToString(paramString.getBytes("UTF-8"), 11);
      StringBuilder localStringBuilder = new StringBuilder(String.valueOf(paramString).length() + 33);
      localStringBuilder.append("com.google.InstanceId_");
      localStringBuilder.append(paramString);
      localStringBuilder.append(".properties");
      paramString = localStringBuilder.toString();
      return new File(zzb(paramContext), paramString);
    }
    catch (UnsupportedEncodingException paramContext)
    {
      throw new AssertionError(paramContext);
    }
  }
  
  @WorkerThread
  final zzz zzb(Context paramContext, String paramString)
    throws zzaa
  {
    zzz localZzz = zzd(paramContext, paramString);
    if (localZzz != null) {
      return localZzz;
    }
    return zzc(paramContext, paramString);
  }
  
  @WorkerThread
  final zzz zzc(Context paramContext, String paramString)
  {
    zzz localZzz1 = new zzz(zza.zzb(), System.currentTimeMillis());
    zzz localZzz2 = zza(paramContext, paramString, localZzz1, true);
    if ((localZzz2 != null) && (!localZzz2.equals(localZzz1)))
    {
      if (Log.isLoggable("FirebaseInstanceId", 3)) {
        Log.d("FirebaseInstanceId", "Loaded key after generating new one, using loaded one");
      }
      return localZzz2;
    }
    if (Log.isLoggable("FirebaseInstanceId", 3)) {
      Log.d("FirebaseInstanceId", "Generated new key");
    }
    zza(paramContext, paramString, localZzz1);
    return localZzz1;
  }
}
