package com.google.android.gms.dynamite;

import android.content.Context;
import android.database.Cursor;
import android.os.IBinder;
import android.os.IInterface;
import android.os.RemoteException;
import android.util.Log;
import com.google.android.gms.common.annotation.KeepForSdk;
import com.google.android.gms.common.internal.Preconditions;
import com.google.android.gms.common.util.DynamiteApi;
import com.google.android.gms.dynamic.ObjectWrapper;
import java.lang.reflect.Constructor;
import java.lang.reflect.Field;
import java.lang.reflect.InvocationTargetException;
import javax.annotation.concurrent.GuardedBy;

@KeepForSdk
public final class DynamiteModule
{
  @KeepForSdk
  public static final VersionPolicy PREFER_HIGHEST_OR_LOCAL_VERSION = new zzd();
  @KeepForSdk
  public static final VersionPolicy PREFER_HIGHEST_OR_LOCAL_VERSION_NO_FORCE_STAGING = new zze();
  @KeepForSdk
  public static final VersionPolicy PREFER_HIGHEST_OR_REMOTE_VERSION = new zzf();
  @KeepForSdk
  public static final VersionPolicy PREFER_REMOTE;
  @GuardedBy("DynamiteModule.class")
  private static Boolean zzid;
  @GuardedBy("DynamiteModule.class")
  private static zzi zzie;
  @GuardedBy("DynamiteModule.class")
  private static zzk zzif;
  @GuardedBy("DynamiteModule.class")
  private static String zzig;
  @GuardedBy("DynamiteModule.class")
  private static int zzih = -1;
  private static final ThreadLocal<zza> zzii = new ThreadLocal();
  private static final DynamiteModule.VersionPolicy.zza zzij = new zza();
  private static final VersionPolicy zzik;
  private static final VersionPolicy zzil = new zzg();
  private final Context zzim;
  
  static
  {
    PREFER_REMOTE = new zzb();
    zzik = new zzc();
  }
  
  private DynamiteModule(Context paramContext)
  {
    zzim = ((Context)Preconditions.checkNotNull(paramContext));
  }
  
  @KeepForSdk
  public static int getLocalVersion(Context paramContext, String paramString)
  {
    try
    {
      paramContext = paramContext.getApplicationContext().getClassLoader();
      Object localObject = new StringBuilder(String.valueOf(paramString).length() + 61);
      ((StringBuilder)localObject).append("com.google.android.gms.dynamite.descriptors.");
      ((StringBuilder)localObject).append(paramString);
      ((StringBuilder)localObject).append(".ModuleDescriptor");
      localObject = paramContext.loadClass(((StringBuilder)localObject).toString());
      paramContext = ((Class)localObject).getDeclaredField("MODULE_ID");
      localObject = ((Class)localObject).getDeclaredField("MODULE_VERSION");
      if (!paramContext.get(null).equals(paramString))
      {
        paramContext = String.valueOf(paramContext.get(null));
        localObject = new StringBuilder(String.valueOf(paramContext).length() + 51 + String.valueOf(paramString).length());
        ((StringBuilder)localObject).append("Module descriptor id '");
        ((StringBuilder)localObject).append(paramContext);
        ((StringBuilder)localObject).append("' didn't match expected id '");
        ((StringBuilder)localObject).append(paramString);
        ((StringBuilder)localObject).append("'");
        Log.e("DynamiteModule", ((StringBuilder)localObject).toString());
        return 0;
      }
      int i = ((Field)localObject).getInt(null);
      return i;
    }
    catch (Exception paramContext)
    {
      paramContext = String.valueOf(paramContext.getMessage());
      if (paramContext.length() != 0) {
        paramContext = "Failed to load module descriptor class: ".concat(paramContext);
      } else {
        paramContext = new String("Failed to load module descriptor class: ");
      }
      Log.e("DynamiteModule", paramContext);
      return 0;
      paramContext = new StringBuilder(String.valueOf(paramString).length() + 45);
      paramContext.append("Local module descriptor class for ");
      paramContext.append(paramString);
      paramContext.append(" not found.");
      Log.w("DynamiteModule", paramContext.toString());
      return 0;
    }
    catch (ClassNotFoundException paramContext)
    {
      for (;;) {}
    }
  }
  
  @KeepForSdk
  public static int getRemoteVersion(Context paramContext, String paramString)
  {
    return zza(paramContext, paramString, false);
  }
  
  @KeepForSdk
  public static DynamiteModule load(Context paramContext, VersionPolicy paramVersionPolicy, String paramString)
    throws DynamiteModule.LoadingException
  {
    zza localZza1 = (zza)zzii.get();
    zza localZza2 = new zza(null);
    zzii.set(localZza2);
    try
    {
      DynamiteModule.VersionPolicy.zzb localZzb = paramVersionPolicy.zza(paramContext, paramString, zzij);
      int i = zziq;
      int j = zzir;
      Object localObject = new StringBuilder(String.valueOf(paramString).length() + 68 + String.valueOf(paramString).length());
      ((StringBuilder)localObject).append("Considering local module ");
      ((StringBuilder)localObject).append(paramString);
      ((StringBuilder)localObject).append(":");
      ((StringBuilder)localObject).append(i);
      ((StringBuilder)localObject).append(" and remote module ");
      ((StringBuilder)localObject).append(paramString);
      ((StringBuilder)localObject).append(":");
      ((StringBuilder)localObject).append(j);
      Log.i("DynamiteModule", ((StringBuilder)localObject).toString());
      if ((zzis != 0) && ((zzis != -1) || (zziq != 0)) && ((zzis != 1) || (zzir != 0)))
      {
        if (zzis == -1)
        {
          paramContext = zze(paramContext, paramString);
          return paramContext;
        }
        i = zzis;
        if (i == 1) {
          try
          {
            localObject = zza(paramContext, paramString, zzir);
            return localObject;
          }
          catch (LoadingException localLoadingException)
          {
            localObject = String.valueOf(localLoadingException.getMessage());
            if (((String)localObject).length() != 0) {
              localObject = "Failed to load remote module: ".concat((String)localObject);
            } else {
              localObject = new String("Failed to load remote module: ");
            }
            Log.w("DynamiteModule", (String)localObject);
            if ((zziq != 0) && (zzazzbzziq, 0)).zzis == -1))
            {
              paramContext = zze(paramContext, paramString);
              return paramContext;
            }
            throw new LoadingException("Remote load failed. No local fallback found.", localLoadingException, null);
          }
        }
        i = zzis;
        paramContext = new StringBuilder(47);
        paramContext.append("VersionPolicy returned invalid code:");
        paramContext.append(i);
        throw new LoadingException(paramContext.toString(), null);
      }
      i = zziq;
      j = zzir;
      paramContext = new StringBuilder(91);
      paramContext.append("No acceptable module found. Local version is ");
      paramContext.append(i);
      paramContext.append(" and remote version is ");
      paramContext.append(j);
      paramContext.append(".");
      throw new LoadingException(paramContext.toString(), null);
    }
    finally
    {
      if (zzin != null) {
        zzin.close();
      }
      zzii.set(localZza1);
    }
  }
  
  /* Error */
  public static int zza(Context paramContext, String paramString, boolean paramBoolean)
  {
    // Byte code:
    //   0: ldc 2
    //   2: monitorenter
    //   3: getstatic 300	com/google/android/gms/dynamite/DynamiteModule:zzid	Ljava/lang/Boolean;
    //   6: astore 6
    //   8: aload 6
    //   10: astore 5
    //   12: aload 6
    //   14: ifnonnull +281 -> 295
    //   17: aload_0
    //   18: invokevirtual 119	android/content/Context:getApplicationContext	()Landroid/content/Context;
    //   21: invokevirtual 123	android/content/Context:getClassLoader	()Ljava/lang/ClassLoader;
    //   24: ldc 6
    //   26: invokevirtual 303	java/lang/Class:getName	()Ljava/lang/String;
    //   29: invokevirtual 156	java/lang/ClassLoader:loadClass	(Ljava/lang/String;)Ljava/lang/Class;
    //   32: astore 6
    //   34: aload 6
    //   36: ldc_w 305
    //   39: invokevirtual 164	java/lang/Class:getDeclaredField	(Ljava/lang/String;)Ljava/lang/reflect/Field;
    //   42: astore 5
    //   44: aload 6
    //   46: monitorenter
    //   47: aload 5
    //   49: aconst_null
    //   50: invokevirtual 171	java/lang/reflect/Field:get	(Ljava/lang/Object;)Ljava/lang/Object;
    //   53: checkcast 152	java/lang/ClassLoader
    //   56: astore 7
    //   58: aload 7
    //   60: ifnull +32 -> 92
    //   63: aload 7
    //   65: invokestatic 308	java/lang/ClassLoader:getSystemClassLoader	()Ljava/lang/ClassLoader;
    //   68: if_acmpne +11 -> 79
    //   71: getstatic 313	java/lang/Boolean:FALSE	Ljava/lang/Boolean;
    //   74: astore 5
    //   76: goto +138 -> 214
    //   79: aload 7
    //   81: invokestatic 316	com/google/android/gms/dynamite/DynamiteModule:zza	(Ljava/lang/ClassLoader;)V
    //   84: getstatic 319	java/lang/Boolean:TRUE	Ljava/lang/Boolean;
    //   87: astore 5
    //   89: goto +125 -> 214
    //   92: ldc_w 321
    //   95: aload_0
    //   96: invokevirtual 119	android/content/Context:getApplicationContext	()Landroid/content/Context;
    //   99: invokevirtual 324	android/content/Context:getPackageName	()Ljava/lang/String;
    //   102: invokevirtual 325	java/lang/String:equals	(Ljava/lang/Object;)Z
    //   105: ifeq +20 -> 125
    //   108: aload 5
    //   110: aconst_null
    //   111: invokestatic 308	java/lang/ClassLoader:getSystemClassLoader	()Ljava/lang/ClassLoader;
    //   114: invokevirtual 328	java/lang/reflect/Field:set	(Ljava/lang/Object;Ljava/lang/Object;)V
    //   117: getstatic 313	java/lang/Boolean:FALSE	Ljava/lang/Boolean;
    //   120: astore 5
    //   122: goto +92 -> 214
    //   125: aload_0
    //   126: aload_1
    //   127: iload_2
    //   128: invokestatic 331	com/google/android/gms/dynamite/DynamiteModule:zzc	(Landroid/content/Context;Ljava/lang/String;Z)I
    //   131: istore_3
    //   132: getstatic 333	com/google/android/gms/dynamite/DynamiteModule:zzig	Ljava/lang/String;
    //   135: ifnull +57 -> 192
    //   138: getstatic 333	com/google/android/gms/dynamite/DynamiteModule:zzig	Ljava/lang/String;
    //   141: invokevirtual 337	java/lang/String:isEmpty	()Z
    //   144: ifeq +6 -> 150
    //   147: goto +45 -> 192
    //   150: new 339	com/google/android/gms/dynamite/zzh
    //   153: dup
    //   154: getstatic 333	com/google/android/gms/dynamite/DynamiteModule:zzig	Ljava/lang/String;
    //   157: invokestatic 308	java/lang/ClassLoader:getSystemClassLoader	()Ljava/lang/ClassLoader;
    //   160: invokespecial 342	com/google/android/gms/dynamite/zzh:<init>	(Ljava/lang/String;Ljava/lang/ClassLoader;)V
    //   163: astore 7
    //   165: aload 7
    //   167: invokestatic 316	com/google/android/gms/dynamite/DynamiteModule:zza	(Ljava/lang/ClassLoader;)V
    //   170: aload 5
    //   172: aconst_null
    //   173: aload 7
    //   175: invokevirtual 328	java/lang/reflect/Field:set	(Ljava/lang/Object;Ljava/lang/Object;)V
    //   178: getstatic 319	java/lang/Boolean:TRUE	Ljava/lang/Boolean;
    //   181: putstatic 300	com/google/android/gms/dynamite/DynamiteModule:zzid	Ljava/lang/Boolean;
    //   184: aload 6
    //   186: monitorexit
    //   187: ldc 2
    //   189: monitorexit
    //   190: iload_3
    //   191: ireturn
    //   192: aload 6
    //   194: monitorexit
    //   195: ldc 2
    //   197: monitorexit
    //   198: iload_3
    //   199: ireturn
    //   200: aload 5
    //   202: aconst_null
    //   203: invokestatic 308	java/lang/ClassLoader:getSystemClassLoader	()Ljava/lang/ClassLoader;
    //   206: invokevirtual 328	java/lang/reflect/Field:set	(Ljava/lang/Object;Ljava/lang/Object;)V
    //   209: getstatic 313	java/lang/Boolean:FALSE	Ljava/lang/Boolean;
    //   212: astore 5
    //   214: aload 6
    //   216: monitorexit
    //   217: goto +73 -> 290
    //   220: astore 5
    //   222: aload 6
    //   224: monitorexit
    //   225: aload 5
    //   227: athrow
    //   228: astore 5
    //   230: aload 5
    //   232: invokestatic 131	java/lang/String:valueOf	(Ljava/lang/Object;)Ljava/lang/String;
    //   235: astore 5
    //   237: new 125	java/lang/StringBuilder
    //   240: dup
    //   241: aload 5
    //   243: invokestatic 131	java/lang/String:valueOf	(Ljava/lang/Object;)Ljava/lang/String;
    //   246: invokevirtual 135	java/lang/String:length	()I
    //   249: bipush 30
    //   251: iadd
    //   252: invokespecial 138	java/lang/StringBuilder:<init>	(I)V
    //   255: astore 6
    //   257: aload 6
    //   259: ldc_w 344
    //   262: invokevirtual 144	java/lang/StringBuilder:append	(Ljava/lang/String;)Ljava/lang/StringBuilder;
    //   265: pop
    //   266: aload 6
    //   268: aload 5
    //   270: invokevirtual 144	java/lang/StringBuilder:append	(Ljava/lang/String;)Ljava/lang/StringBuilder;
    //   273: pop
    //   274: ldc -73
    //   276: aload 6
    //   278: invokevirtual 150	java/lang/StringBuilder:toString	()Ljava/lang/String;
    //   281: invokestatic 212	android/util/Log:w	(Ljava/lang/String;Ljava/lang/String;)I
    //   284: pop
    //   285: getstatic 313	java/lang/Boolean:FALSE	Ljava/lang/Boolean;
    //   288: astore 5
    //   290: aload 5
    //   292: putstatic 300	com/google/android/gms/dynamite/DynamiteModule:zzid	Ljava/lang/Boolean;
    //   295: ldc 2
    //   297: monitorexit
    //   298: aload 5
    //   300: invokevirtual 347	java/lang/Boolean:booleanValue	()Z
    //   303: istore 4
    //   305: iload 4
    //   307: ifeq +59 -> 366
    //   310: aload_0
    //   311: aload_1
    //   312: iload_2
    //   313: invokestatic 331	com/google/android/gms/dynamite/DynamiteModule:zzc	(Landroid/content/Context;Ljava/lang/String;Z)I
    //   316: istore_3
    //   317: iload_3
    //   318: ireturn
    //   319: astore_1
    //   320: aload_1
    //   321: invokevirtual 270	com/google/android/gms/dynamite/DynamiteModule$LoadingException:getMessage	()Ljava/lang/String;
    //   324: invokestatic 131	java/lang/String:valueOf	(Ljava/lang/Object;)Ljava/lang/String;
    //   327: astore_1
    //   328: aload_1
    //   329: invokevirtual 135	java/lang/String:length	()I
    //   332: ifeq +14 -> 346
    //   335: ldc_w 349
    //   338: aload_1
    //   339: invokevirtual 202	java/lang/String:concat	(Ljava/lang/String;)Ljava/lang/String;
    //   342: astore_1
    //   343: goto +14 -> 357
    //   346: new 127	java/lang/String
    //   349: dup
    //   350: ldc_w 349
    //   353: invokespecial 205	java/lang/String:<init>	(Ljava/lang/String;)V
    //   356: astore_1
    //   357: ldc -73
    //   359: aload_1
    //   360: invokestatic 212	android/util/Log:w	(Ljava/lang/String;Ljava/lang/String;)I
    //   363: pop
    //   364: iconst_0
    //   365: ireturn
    //   366: aload_0
    //   367: aload_1
    //   368: iload_2
    //   369: invokestatic 351	com/google/android/gms/dynamite/DynamiteModule:zzb	(Landroid/content/Context;Ljava/lang/String;Z)I
    //   372: istore_3
    //   373: iload_3
    //   374: ireturn
    //   375: astore_1
    //   376: ldc 2
    //   378: monitorexit
    //   379: aload_1
    //   380: athrow
    //   381: astore_1
    //   382: aload_0
    //   383: aload_1
    //   384: invokestatic 357	com/google/android/gms/common/util/CrashUtils:addDynamiteErrorToDropBox	(Landroid/content/Context;Ljava/lang/Throwable;)Z
    //   387: pop
    //   388: aload_1
    //   389: athrow
    //   390: astore 5
    //   392: goto -308 -> 84
    //   395: astore 7
    //   397: goto -197 -> 200
    // Local variable table:
    //   start	length	slot	name	signature
    //   0	400	0	paramContext	Context
    //   0	400	1	paramString	String
    //   0	400	2	paramBoolean	boolean
    //   131	243	3	i	int
    //   303	3	4	bool	boolean
    //   10	203	5	localObject1	Object
    //   220	6	5	localObject2	Object
    //   228	3	5	localClassNotFoundException	ClassNotFoundException
    //   235	64	5	localObject3	Object
    //   390	1	5	localLoadingException1	LoadingException
    //   6	271	6	localObject4	Object
    //   56	118	7	localObject5	Object
    //   395	1	7	localLoadingException2	LoadingException
    // Exception table:
    //   from	to	target	type
    //   47	58	220	finally
    //   63	76	220	finally
    //   79	84	220	finally
    //   84	89	220	finally
    //   92	122	220	finally
    //   125	147	220	finally
    //   150	184	220	finally
    //   184	187	220	finally
    //   192	195	220	finally
    //   200	214	220	finally
    //   214	217	220	finally
    //   222	225	220	finally
    //   17	47	228	java/lang/ClassNotFoundException
    //   17	47	228	java/lang/IllegalAccessException
    //   17	47	228	java/lang/NoSuchFieldException
    //   225	228	228	java/lang/ClassNotFoundException
    //   225	228	228	java/lang/IllegalAccessException
    //   225	228	228	java/lang/NoSuchFieldException
    //   310	317	319	com/google/android/gms/dynamite/DynamiteModule$LoadingException
    //   3	8	375	finally
    //   17	47	375	finally
    //   187	190	375	finally
    //   195	198	375	finally
    //   225	228	375	finally
    //   230	290	375	finally
    //   290	295	375	finally
    //   295	298	375	finally
    //   376	379	375	finally
    //   0	3	381	java/lang/Throwable
    //   298	305	381	java/lang/Throwable
    //   310	317	381	java/lang/Throwable
    //   320	343	381	java/lang/Throwable
    //   346	357	381	java/lang/Throwable
    //   357	364	381	java/lang/Throwable
    //   366	373	381	java/lang/Throwable
    //   379	381	381	java/lang/Throwable
    //   79	84	390	com/google/android/gms/dynamite/DynamiteModule$LoadingException
    //   125	147	395	com/google/android/gms/dynamite/DynamiteModule$LoadingException
    //   150	184	395	com/google/android/gms/dynamite/DynamiteModule$LoadingException
  }
  
  private static Context zza(Context paramContext, String paramString, int paramInt, Cursor paramCursor, zzk paramZzk)
  {
    try
    {
      ObjectWrapper.wrap(null);
      if (zzai().booleanValue())
      {
        Log.v("DynamiteModule", "Dynamite loader version >= 2, using loadModule2NoCrashUtils");
        paramContext = paramZzk.zzb(ObjectWrapper.wrap(paramContext), paramString, paramInt, ObjectWrapper.wrap(paramCursor));
      }
      else
      {
        Log.w("DynamiteModule", "Dynamite loader version < 2, falling back to loadModule2");
        paramContext = paramZzk.zza(ObjectWrapper.wrap(paramContext), paramString, paramInt, ObjectWrapper.wrap(paramCursor));
      }
      paramContext = (Context)ObjectWrapper.unwrap(paramContext);
      return paramContext;
    }
    catch (Exception paramContext)
    {
      paramContext = String.valueOf(paramContext.toString());
      if (paramContext.length() != 0) {
        paramContext = "Failed to load DynamiteLoader: ".concat(paramContext);
      } else {
        paramContext = new String("Failed to load DynamiteLoader: ");
      }
      Log.e("DynamiteModule", paramContext);
    }
    return null;
  }
  
  /* Error */
  private static DynamiteModule zza(Context paramContext, String paramString, int paramInt)
    throws DynamiteModule.LoadingException
  {
    // Byte code:
    //   0: ldc 2
    //   2: monitorenter
    //   3: getstatic 300	com/google/android/gms/dynamite/DynamiteModule:zzid	Ljava/lang/Boolean;
    //   6: astore_3
    //   7: ldc 2
    //   9: monitorexit
    //   10: aload_3
    //   11: ifnull +24 -> 35
    //   14: aload_3
    //   15: invokevirtual 347	java/lang/Boolean:booleanValue	()Z
    //   18: ifeq +10 -> 28
    //   21: aload_0
    //   22: aload_1
    //   23: iload_2
    //   24: invokestatic 391	com/google/android/gms/dynamite/DynamiteModule:zzc	(Landroid/content/Context;Ljava/lang/String;I)Lcom/google/android/gms/dynamite/DynamiteModule;
    //   27: areturn
    //   28: aload_0
    //   29: aload_1
    //   30: iload_2
    //   31: invokestatic 393	com/google/android/gms/dynamite/DynamiteModule:zzb	(Landroid/content/Context;Ljava/lang/String;I)Lcom/google/android/gms/dynamite/DynamiteModule;
    //   34: areturn
    //   35: new 9	com/google/android/gms/dynamite/DynamiteModule$LoadingException
    //   38: dup
    //   39: ldc_w 395
    //   42: aconst_null
    //   43: invokespecial 285	com/google/android/gms/dynamite/DynamiteModule$LoadingException:<init>	(Ljava/lang/String;Lcom/google/android/gms/dynamite/zza;)V
    //   46: athrow
    //   47: astore_1
    //   48: ldc 2
    //   50: monitorexit
    //   51: aload_1
    //   52: athrow
    //   53: astore_1
    //   54: aload_0
    //   55: aload_1
    //   56: invokestatic 357	com/google/android/gms/common/util/CrashUtils:addDynamiteErrorToDropBox	(Landroid/content/Context;Ljava/lang/Throwable;)Z
    //   59: pop
    //   60: aload_1
    //   61: athrow
    // Local variable table:
    //   start	length	slot	name	signature
    //   0	62	0	paramContext	Context
    //   0	62	1	paramString	String
    //   0	62	2	paramInt	int
    //   6	9	3	localBoolean	Boolean
    // Exception table:
    //   from	to	target	type
    //   3	10	47	finally
    //   48	51	47	finally
    //   0	3	53	java/lang/Throwable
    //   14	28	53	java/lang/Throwable
    //   28	35	53	java/lang/Throwable
    //   35	47	53	java/lang/Throwable
    //   51	53	53	java/lang/Throwable
  }
  
  @GuardedBy("DynamiteModule.class")
  private static void zza(ClassLoader paramClassLoader)
    throws DynamiteModule.LoadingException
  {
    try
    {
      paramClassLoader = (IBinder)paramClassLoader.loadClass("com.google.android.gms.dynamiteloader.DynamiteLoaderV2").getConstructor(new Class[0]).newInstance(new Object[0]);
      if (paramClassLoader == null)
      {
        paramClassLoader = null;
      }
      else
      {
        IInterface localIInterface = paramClassLoader.queryLocalInterface("com.google.android.gms.dynamite.IDynamiteLoaderV2");
        if ((localIInterface instanceof zzk)) {
          paramClassLoader = (zzk)localIInterface;
        } else {
          paramClassLoader = new zzl(paramClassLoader);
        }
      }
      zzif = paramClassLoader;
      return;
    }
    catch (ClassNotFoundException|IllegalAccessException|InstantiationException|InvocationTargetException|NoSuchMethodException paramClassLoader)
    {
      throw new LoadingException("Failed to instantiate dynamite loader", paramClassLoader, null);
    }
  }
  
  private static Boolean zzai()
  {
    for (;;)
    {
      try
      {
        if (zzih >= 2)
        {
          bool = true;
          return Boolean.valueOf(bool);
        }
      }
      finally {}
      boolean bool = false;
    }
  }
  
  private static int zzb(Context paramContext, String paramString, boolean paramBoolean)
  {
    zzi localZzi = zzj(paramContext);
    if (localZzi == null) {
      return 0;
    }
    try
    {
      if (localZzi.zzaj() >= 2) {
        return localZzi.zzb(ObjectWrapper.wrap(paramContext), paramString, paramBoolean);
      }
      Log.w("DynamiteModule", "IDynamite loader version < 2, falling back to getModuleVersion2");
      int i = localZzi.zza(ObjectWrapper.wrap(paramContext), paramString, paramBoolean);
      return i;
    }
    catch (RemoteException paramContext)
    {
      paramContext = String.valueOf(paramContext.getMessage());
      if (paramContext.length() != 0) {
        paramContext = "Failed to retrieve remote module version: ".concat(paramContext);
      } else {
        paramContext = new String("Failed to retrieve remote module version: ");
      }
      Log.w("DynamiteModule", paramContext);
    }
    return 0;
  }
  
  private static DynamiteModule zzb(Context paramContext, String paramString, int paramInt)
    throws DynamiteModule.LoadingException
  {
    Object localObject = new StringBuilder(String.valueOf(paramString).length() + 51);
    ((StringBuilder)localObject).append("Selected remote version of ");
    ((StringBuilder)localObject).append(paramString);
    ((StringBuilder)localObject).append(", version >= ");
    ((StringBuilder)localObject).append(paramInt);
    Log.i("DynamiteModule", ((StringBuilder)localObject).toString());
    localObject = zzj(paramContext);
    if (localObject != null) {
      try
      {
        if (((zzi)localObject).zzaj() >= 2)
        {
          paramContext = ((zzi)localObject).zzb(ObjectWrapper.wrap(paramContext), paramString, paramInt);
        }
        else
        {
          Log.w("DynamiteModule", "Dynamite loader version < 2, falling back to createModuleContext");
          paramContext = ((zzi)localObject).zza(ObjectWrapper.wrap(paramContext), paramString, paramInt);
        }
        if (ObjectWrapper.unwrap(paramContext) != null) {
          return new DynamiteModule((Context)ObjectWrapper.unwrap(paramContext));
        }
        throw new LoadingException("Failed to load remote module.", null);
      }
      catch (RemoteException paramContext)
      {
        throw new LoadingException("Failed to load remote module.", paramContext, null);
      }
    }
    throw new LoadingException("Failed to create IDynamiteLoader.", null);
  }
  
  /* Error */
  private static int zzc(Context paramContext, String paramString, boolean paramBoolean)
    throws DynamiteModule.LoadingException
  {
    // Byte code:
    //   0: aconst_null
    //   1: astore 5
    //   3: aload_0
    //   4: invokevirtual 475	android/content/Context:getContentResolver	()Landroid/content/ContentResolver;
    //   7: astore 6
    //   9: iload_2
    //   10: ifeq +288 -> 298
    //   13: ldc_w 477
    //   16: astore_0
    //   17: goto +3 -> 20
    //   20: new 125	java/lang/StringBuilder
    //   23: dup
    //   24: aload_0
    //   25: invokestatic 131	java/lang/String:valueOf	(Ljava/lang/Object;)Ljava/lang/String;
    //   28: invokevirtual 135	java/lang/String:length	()I
    //   31: bipush 42
    //   33: iadd
    //   34: aload_1
    //   35: invokestatic 131	java/lang/String:valueOf	(Ljava/lang/Object;)Ljava/lang/String;
    //   38: invokevirtual 135	java/lang/String:length	()I
    //   41: iadd
    //   42: invokespecial 138	java/lang/StringBuilder:<init>	(I)V
    //   45: astore 7
    //   47: aload 7
    //   49: ldc_w 479
    //   52: invokevirtual 144	java/lang/StringBuilder:append	(Ljava/lang/String;)Ljava/lang/StringBuilder;
    //   55: pop
    //   56: aload 7
    //   58: aload_0
    //   59: invokevirtual 144	java/lang/StringBuilder:append	(Ljava/lang/String;)Ljava/lang/StringBuilder;
    //   62: pop
    //   63: aload 7
    //   65: ldc_w 481
    //   68: invokevirtual 144	java/lang/StringBuilder:append	(Ljava/lang/String;)Ljava/lang/StringBuilder;
    //   71: pop
    //   72: aload 7
    //   74: aload_1
    //   75: invokevirtual 144	java/lang/StringBuilder:append	(Ljava/lang/String;)Ljava/lang/StringBuilder;
    //   78: pop
    //   79: aload 6
    //   81: aload 7
    //   83: invokevirtual 150	java/lang/StringBuilder:toString	()Ljava/lang/String;
    //   86: invokestatic 487	android/net/Uri:parse	(Ljava/lang/String;)Landroid/net/Uri;
    //   89: aconst_null
    //   90: aconst_null
    //   91: aconst_null
    //   92: aconst_null
    //   93: invokevirtual 493	android/content/ContentResolver:query	(Landroid/net/Uri;[Ljava/lang/String;Ljava/lang/String;[Ljava/lang/String;Ljava/lang/String;)Landroid/database/Cursor;
    //   96: astore_0
    //   97: aload_0
    //   98: ifnull +134 -> 232
    //   101: aload_0
    //   102: invokeinterface 496 1 0
    //   107: ifeq +125 -> 232
    //   110: aload_0
    //   111: iconst_0
    //   112: invokeinterface 499 2 0
    //   117: istore_3
    //   118: aload_0
    //   119: astore_1
    //   120: iload_3
    //   121: ifle +91 -> 212
    //   124: ldc 2
    //   126: monitorenter
    //   127: aload_0
    //   128: iconst_2
    //   129: invokeinterface 503 2 0
    //   134: putstatic 333	com/google/android/gms/dynamite/DynamiteModule:zzig	Ljava/lang/String;
    //   137: aload_0
    //   138: ldc_w 505
    //   141: invokeinterface 509 2 0
    //   146: istore 4
    //   148: iload 4
    //   150: iflt +14 -> 164
    //   153: aload_0
    //   154: iload 4
    //   156: invokeinterface 499 2 0
    //   161: putstatic 432	com/google/android/gms/dynamite/DynamiteModule:zzih	I
    //   164: ldc 2
    //   166: monitorexit
    //   167: getstatic 61	com/google/android/gms/dynamite/DynamiteModule:zzii	Ljava/lang/ThreadLocal;
    //   170: invokevirtual 222	java/lang/ThreadLocal:get	()Ljava/lang/Object;
    //   173: checkcast 21	com/google/android/gms/dynamite/DynamiteModule$zza
    //   176: astore 5
    //   178: aload_0
    //   179: astore_1
    //   180: aload 5
    //   182: ifnull +30 -> 212
    //   185: aload_0
    //   186: astore_1
    //   187: aload 5
    //   189: getfield 261	com/google/android/gms/dynamite/DynamiteModule$zza:zzin	Landroid/database/Cursor;
    //   192: ifnonnull +20 -> 212
    //   195: aload 5
    //   197: aload_0
    //   198: putfield 261	com/google/android/gms/dynamite/DynamiteModule$zza:zzin	Landroid/database/Cursor;
    //   201: aconst_null
    //   202: astore_1
    //   203: goto +9 -> 212
    //   206: astore_1
    //   207: ldc 2
    //   209: monitorexit
    //   210: aload_1
    //   211: athrow
    //   212: aload_1
    //   213: ifnull +9 -> 222
    //   216: aload_1
    //   217: invokeinterface 266 1 0
    //   222: iload_3
    //   223: ireturn
    //   224: astore_1
    //   225: goto +61 -> 286
    //   228: astore_1
    //   229: goto +34 -> 263
    //   232: ldc -73
    //   234: ldc_w 511
    //   237: invokestatic 212	android/util/Log:w	(Ljava/lang/String;Ljava/lang/String;)I
    //   240: pop
    //   241: new 9	com/google/android/gms/dynamite/DynamiteModule$LoadingException
    //   244: dup
    //   245: ldc_w 513
    //   248: aconst_null
    //   249: invokespecial 285	com/google/android/gms/dynamite/DynamiteModule$LoadingException:<init>	(Ljava/lang/String;Lcom/google/android/gms/dynamite/zza;)V
    //   252: athrow
    //   253: astore_1
    //   254: aload 5
    //   256: astore_0
    //   257: goto +29 -> 286
    //   260: astore_1
    //   261: aconst_null
    //   262: astore_0
    //   263: aload_1
    //   264: instanceof 9
    //   267: ifeq +5 -> 272
    //   270: aload_1
    //   271: athrow
    //   272: new 9	com/google/android/gms/dynamite/DynamiteModule$LoadingException
    //   275: dup
    //   276: ldc_w 515
    //   279: aload_1
    //   280: aconst_null
    //   281: invokespecial 280	com/google/android/gms/dynamite/DynamiteModule$LoadingException:<init>	(Ljava/lang/String;Ljava/lang/Throwable;Lcom/google/android/gms/dynamite/zza;)V
    //   284: athrow
    //   285: astore_1
    //   286: aload_0
    //   287: ifnull +9 -> 296
    //   290: aload_0
    //   291: invokeinterface 266 1 0
    //   296: aload_1
    //   297: athrow
    //   298: ldc_w 517
    //   301: astore_0
    //   302: goto -282 -> 20
    // Local variable table:
    //   start	length	slot	name	signature
    //   0	305	0	paramContext	Context
    //   0	305	1	paramString	String
    //   0	305	2	paramBoolean	boolean
    //   117	106	3	i	int
    //   146	9	4	j	int
    //   1	254	5	localZza	zza
    //   7	73	6	localContentResolver	android.content.ContentResolver
    //   45	37	7	localStringBuilder	StringBuilder
    // Exception table:
    //   from	to	target	type
    //   127	148	206	finally
    //   153	164	206	finally
    //   164	167	206	finally
    //   207	210	206	finally
    //   101	118	224	finally
    //   124	127	224	finally
    //   167	178	224	finally
    //   187	201	224	finally
    //   210	212	224	finally
    //   232	253	224	finally
    //   101	118	228	java/lang/Exception
    //   124	127	228	java/lang/Exception
    //   167	178	228	java/lang/Exception
    //   187	201	228	java/lang/Exception
    //   210	212	228	java/lang/Exception
    //   232	253	228	java/lang/Exception
    //   3	9	253	finally
    //   20	97	253	finally
    //   3	9	260	java/lang/Exception
    //   20	97	260	java/lang/Exception
    //   263	272	285	finally
    //   272	285	285	finally
  }
  
  private static DynamiteModule zzc(Context paramContext, String paramString, int paramInt)
    throws DynamiteModule.LoadingException
  {
    Object localObject = new StringBuilder(String.valueOf(paramString).length() + 51);
    ((StringBuilder)localObject).append("Selected remote version of ");
    ((StringBuilder)localObject).append(paramString);
    ((StringBuilder)localObject).append(", version >= ");
    ((StringBuilder)localObject).append(paramInt);
    Log.i("DynamiteModule", ((StringBuilder)localObject).toString());
    try
    {
      localObject = zzif;
      if (localObject != null)
      {
        zza localZza = (zza)zzii.get();
        if ((localZza != null) && (zzin != null))
        {
          paramContext = zza(paramContext.getApplicationContext(), paramString, paramInt, zzin, (zzk)localObject);
          if (paramContext != null) {
            return new DynamiteModule(paramContext);
          }
          throw new LoadingException("Failed to get module context", null);
        }
        throw new LoadingException("No result cursor", null);
      }
      throw new LoadingException("DynamiteLoaderV2 was not cached.", null);
    }
    finally {}
  }
  
  private static DynamiteModule zze(Context paramContext, String paramString)
  {
    paramString = String.valueOf(paramString);
    if (paramString.length() != 0) {
      paramString = "Selected local version of ".concat(paramString);
    } else {
      paramString = new String("Selected local version of ");
    }
    Log.i("DynamiteModule", paramString);
    return new DynamiteModule(paramContext.getApplicationContext());
  }
  
  /* Error */
  private static zzi zzj(Context paramContext)
  {
    // Byte code:
    //   0: ldc 2
    //   2: monitorenter
    //   3: getstatic 529	com/google/android/gms/dynamite/DynamiteModule:zzie	Lcom/google/android/gms/dynamite/zzi;
    //   6: ifnull +12 -> 18
    //   9: getstatic 529	com/google/android/gms/dynamite/DynamiteModule:zzie	Lcom/google/android/gms/dynamite/zzi;
    //   12: astore_0
    //   13: ldc 2
    //   15: monitorexit
    //   16: aload_0
    //   17: areturn
    //   18: invokestatic 535	com/google/android/gms/common/GoogleApiAvailabilityLight:getInstance	()Lcom/google/android/gms/common/GoogleApiAvailabilityLight;
    //   21: aload_0
    //   22: invokevirtual 539	com/google/android/gms/common/GoogleApiAvailabilityLight:isGooglePlayServicesAvailable	(Landroid/content/Context;)I
    //   25: ifeq +8 -> 33
    //   28: ldc 2
    //   30: monitorexit
    //   31: aconst_null
    //   32: areturn
    //   33: aload_0
    //   34: ldc_w 321
    //   37: iconst_3
    //   38: invokevirtual 543	android/content/Context:createPackageContext	(Ljava/lang/String;I)Landroid/content/Context;
    //   41: invokevirtual 123	android/content/Context:getClassLoader	()Ljava/lang/ClassLoader;
    //   44: ldc_w 545
    //   47: invokevirtual 156	java/lang/ClassLoader:loadClass	(Ljava/lang/String;)Ljava/lang/Class;
    //   50: invokevirtual 547	java/lang/Class:newInstance	()Ljava/lang/Object;
    //   53: checkcast 415	android/os/IBinder
    //   56: astore_0
    //   57: aload_0
    //   58: ifnonnull +8 -> 66
    //   61: aconst_null
    //   62: astore_0
    //   63: goto +37 -> 100
    //   66: aload_0
    //   67: ldc_w 549
    //   70: invokeinterface 421 2 0
    //   75: astore_1
    //   76: aload_1
    //   77: instanceof 443
    //   80: ifeq +11 -> 91
    //   83: aload_1
    //   84: checkcast 443	com/google/android/gms/dynamite/zzi
    //   87: astore_0
    //   88: goto +12 -> 100
    //   91: new 551	com/google/android/gms/dynamite/zzj
    //   94: dup
    //   95: aload_0
    //   96: invokespecial 552	com/google/android/gms/dynamite/zzj:<init>	(Landroid/os/IBinder;)V
    //   99: astore_0
    //   100: aload_0
    //   101: ifnull +57 -> 158
    //   104: aload_0
    //   105: putstatic 529	com/google/android/gms/dynamite/DynamiteModule:zzie	Lcom/google/android/gms/dynamite/zzi;
    //   108: ldc 2
    //   110: monitorexit
    //   111: aload_0
    //   112: areturn
    //   113: astore_0
    //   114: aload_0
    //   115: invokevirtual 196	java/lang/Exception:getMessage	()Ljava/lang/String;
    //   118: invokestatic 131	java/lang/String:valueOf	(Ljava/lang/Object;)Ljava/lang/String;
    //   121: astore_0
    //   122: aload_0
    //   123: invokevirtual 135	java/lang/String:length	()I
    //   126: ifeq +14 -> 140
    //   129: ldc_w 554
    //   132: aload_0
    //   133: invokevirtual 202	java/lang/String:concat	(Ljava/lang/String;)Ljava/lang/String;
    //   136: astore_0
    //   137: goto +14 -> 151
    //   140: new 127	java/lang/String
    //   143: dup
    //   144: ldc_w 554
    //   147: invokespecial 205	java/lang/String:<init>	(Ljava/lang/String;)V
    //   150: astore_0
    //   151: ldc -73
    //   153: aload_0
    //   154: invokestatic 189	android/util/Log:e	(Ljava/lang/String;Ljava/lang/String;)I
    //   157: pop
    //   158: ldc 2
    //   160: monitorexit
    //   161: aconst_null
    //   162: areturn
    //   163: astore_0
    //   164: ldc 2
    //   166: monitorexit
    //   167: aload_0
    //   168: athrow
    // Local variable table:
    //   start	length	slot	name	signature
    //   0	169	0	paramContext	Context
    //   75	9	1	localIInterface	IInterface
    // Exception table:
    //   from	to	target	type
    //   33	57	113	java/lang/Exception
    //   66	88	113	java/lang/Exception
    //   91	100	113	java/lang/Exception
    //   104	108	113	java/lang/Exception
    //   3	16	163	finally
    //   18	31	163	finally
    //   33	57	163	finally
    //   66	88	163	finally
    //   91	100	163	finally
    //   104	108	163	finally
    //   108	111	163	finally
    //   114	137	163	finally
    //   140	151	163	finally
    //   151	158	163	finally
    //   158	161	163	finally
    //   164	167	163	finally
  }
  
  @KeepForSdk
  public final Context getModuleContext()
  {
    return zzim;
  }
  
  @KeepForSdk
  public final IBinder instantiate(String paramString)
    throws DynamiteModule.LoadingException
  {
    try
    {
      IBinder localIBinder = (IBinder)zzim.getClassLoader().loadClass(paramString).newInstance();
      return localIBinder;
    }
    catch (ClassNotFoundException|InstantiationException|IllegalAccessException localClassNotFoundException)
    {
      paramString = String.valueOf(paramString);
      if (paramString.length() != 0) {
        paramString = "Failed to instantiate module class: ".concat(paramString);
      } else {
        paramString = new String("Failed to instantiate module class: ");
      }
      throw new LoadingException(paramString, localClassNotFoundException, null);
    }
  }
  
  @DynamiteApi
  public static class DynamiteLoaderClassLoader
  {
    @GuardedBy("DynamiteLoaderClassLoader.class")
    public static ClassLoader sClassLoader;
    
    public DynamiteLoaderClassLoader() {}
  }
  
  @KeepForSdk
  public static class LoadingException
    extends Exception
  {
    private LoadingException(String paramString)
    {
      super();
    }
    
    private LoadingException(String paramString, Throwable paramThrowable)
    {
      super(paramThrowable);
    }
  }
  
  public static abstract interface VersionPolicy
  {
    public abstract zzb zza(Context paramContext, String paramString, zza paramZza)
      throws DynamiteModule.LoadingException;
    
    public static abstract interface zza
    {
      public abstract int getLocalVersion(Context paramContext, String paramString);
      
      public abstract int zza(Context paramContext, String paramString, boolean paramBoolean)
        throws DynamiteModule.LoadingException;
    }
    
    public static final class zzb
    {
      public int zziq = 0;
      public int zzir = 0;
      public int zzis = 0;
      
      public zzb() {}
    }
  }
  
  private static final class zza
  {
    public Cursor zzin;
    
    private zza() {}
  }
  
  private static final class zzb
    implements DynamiteModule.VersionPolicy.zza
  {
    private final int zzio;
    private final int zzip;
    
    public zzb(int paramInt1, int paramInt2)
    {
      zzio = paramInt1;
      zzip = 0;
    }
    
    public final int getLocalVersion(Context paramContext, String paramString)
    {
      return zzio;
    }
    
    public final int zza(Context paramContext, String paramString, boolean paramBoolean)
    {
      return 0;
    }
  }
}
