package android.support.v7.view;

import android.app.Activity;
import android.content.Context;
import android.content.ContextWrapper;
import android.content.res.ColorStateList;
import android.content.res.TypedArray;
import android.graphics.PorterDuff.Mode;
import android.support.annotation.RestrictTo;
import android.support.v4.view.ActionProvider;
import android.support.v4.view.MenuItemCompat;
import android.support.v7.appcompat.R.styleable;
import android.support.v7.view.menu.MenuItemImpl;
import android.support.v7.view.menu.MenuItemWrapperICS;
import android.util.AttributeSet;
import android.util.Log;
import android.view.InflateException;
import android.view.Menu;
import android.view.MenuInflater;
import android.view.MenuItem;
import android.view.MenuItem.OnMenuItemClickListener;
import android.view.SubMenu;
import android.view.View;
import java.io.IOException;
import java.lang.reflect.Constructor;
import java.lang.reflect.Method;
import org.xmlpull.v1.XmlPullParser;
import org.xmlpull.v1.XmlPullParserException;

@RestrictTo({android.support.annotation.RestrictTo.Scope.LIBRARY_GROUP})
public class SupportMenuInflater
  extends MenuInflater
{
  static final Class<?>[] ACTION_PROVIDER_CONSTRUCTOR_SIGNATURE = ACTION_VIEW_CONSTRUCTOR_SIGNATURE;
  static final Class<?>[] ACTION_VIEW_CONSTRUCTOR_SIGNATURE = { Context.class };
  static final String LOG_TAG = "SupportMenuInflater";
  static final int NO_ID = 0;
  private static final String XML_GROUP = "group";
  private static final String XML_ITEM = "item";
  private static final String XML_MENU = "menu";
  final Object[] mActionProviderConstructorArguments;
  final Object[] mActionViewConstructorArguments;
  Context mContext;
  private Object mRealOwner;
  
  public SupportMenuInflater(Context paramContext)
  {
    super(paramContext);
    mContext = paramContext;
    mActionViewConstructorArguments = new Object[] { paramContext };
    mActionProviderConstructorArguments = mActionViewConstructorArguments;
  }
  
  private Object findRealOwner(Object paramObject)
  {
    if ((paramObject instanceof Activity)) {
      return paramObject;
    }
    if ((paramObject instanceof ContextWrapper)) {
      return findRealOwner(((ContextWrapper)paramObject).getBaseContext());
    }
    return paramObject;
  }
  
  private void parseMenu(XmlPullParser paramXmlPullParser, AttributeSet paramAttributeSet, Menu paramMenu)
    throws XmlPullParserException, IOException
  {
    MenuState localMenuState = new MenuState(paramMenu);
    int i = paramXmlPullParser.getEventType();
    do
    {
      if (i == 2)
      {
        paramMenu = paramXmlPullParser.getName();
        if (paramMenu.equals("menu"))
        {
          i = paramXmlPullParser.next();
          break;
        }
        paramXmlPullParser = new StringBuilder();
        paramXmlPullParser.append("Expecting menu, got ");
        paramXmlPullParser.append(paramMenu);
        throw new RuntimeException(paramXmlPullParser.toString());
      }
      j = paramXmlPullParser.next();
      i = j;
    } while (j != 1);
    i = j;
    Object localObject = null;
    int j = 0;
    int k = 0;
    int n = i;
    while (j == 0)
    {
      int m;
      switch (n)
      {
      default: 
        i = k;
        paramMenu = (Menu)localObject;
        m = j;
        break;
      case 3: 
        String str = paramXmlPullParser.getName();
        if ((k != 0) && (str.equals(localObject)))
        {
          paramMenu = null;
          i = 0;
          m = j;
        }
        else if (str.equals("group"))
        {
          localMenuState.resetGroup();
          i = k;
          paramMenu = (Menu)localObject;
          m = j;
        }
        else if (str.equals("item"))
        {
          i = k;
          paramMenu = (Menu)localObject;
          m = j;
          if (!localMenuState.hasAddedItem()) {
            if ((itemActionProvider != null) && (itemActionProvider.hasSubMenu()))
            {
              localMenuState.addSubMenuItem();
              i = k;
              paramMenu = (Menu)localObject;
              m = j;
            }
            else
            {
              localMenuState.addItem();
              i = k;
              paramMenu = (Menu)localObject;
              m = j;
            }
          }
        }
        else
        {
          i = k;
          paramMenu = (Menu)localObject;
          m = j;
          if (str.equals("menu"))
          {
            m = 1;
            i = k;
            paramMenu = (Menu)localObject;
          }
        }
        break;
      case 2: 
        if (k != 0)
        {
          i = k;
          paramMenu = (Menu)localObject;
          m = j;
        }
        else
        {
          paramMenu = paramXmlPullParser.getName();
          if (paramMenu.equals("group"))
          {
            localMenuState.readGroup(paramAttributeSet);
            i = k;
            paramMenu = (Menu)localObject;
            m = j;
          }
          else if (paramMenu.equals("item"))
          {
            localMenuState.readItem(paramAttributeSet);
            i = k;
            paramMenu = (Menu)localObject;
            m = j;
          }
          else if (paramMenu.equals("menu"))
          {
            parseMenu(paramXmlPullParser, paramAttributeSet, localMenuState.addSubMenuItem());
            i = k;
            paramMenu = (Menu)localObject;
            m = j;
          }
          else
          {
            i = 1;
            m = j;
          }
        }
        break;
      case 1: 
        throw new RuntimeException("Unexpected end of document");
      }
      n = paramXmlPullParser.next();
      k = i;
      localObject = paramMenu;
      j = m;
    }
  }
  
  Object getRealOwner()
  {
    if (mRealOwner == null) {
      mRealOwner = findRealOwner(mContext);
    }
    return mRealOwner;
  }
  
  /* Error */
  public void inflate(@android.support.annotation.LayoutRes int paramInt, Menu paramMenu)
  {
    // Byte code:
    //   0: aload_2
    //   1: instanceof 166
    //   4: ifne +10 -> 14
    //   7: aload_0
    //   8: iload_1
    //   9: aload_2
    //   10: invokespecial 168	android/view/MenuInflater:inflate	(ILandroid/view/Menu;)V
    //   13: return
    //   14: aconst_null
    //   15: astore 5
    //   17: aconst_null
    //   18: astore 6
    //   20: aconst_null
    //   21: astore_3
    //   22: aload_0
    //   23: getfield 58	android/support/v7/view/SupportMenuInflater:mContext	Landroid/content/Context;
    //   26: invokevirtual 172	android/content/Context:getResources	()Landroid/content/res/Resources;
    //   29: iload_1
    //   30: invokevirtual 178	android/content/res/Resources:getLayout	(I)Landroid/content/res/XmlResourceParser;
    //   33: astore 4
    //   35: aload_0
    //   36: aload 4
    //   38: aload 4
    //   40: invokestatic 184	android/util/Xml:asAttributeSet	(Lorg/xmlpull/v1/XmlPullParser;)Landroid/util/AttributeSet;
    //   43: aload_2
    //   44: invokespecial 154	android/support/v7/view/SupportMenuInflater:parseMenu	(Lorg/xmlpull/v1/XmlPullParser;Landroid/util/AttributeSet;Landroid/view/Menu;)V
    //   47: aload 4
    //   49: ifnull +10 -> 59
    //   52: aload 4
    //   54: invokeinterface 189 1 0
    //   59: return
    //   60: astore_2
    //   61: aload 4
    //   63: astore_3
    //   64: goto +47 -> 111
    //   67: astore_2
    //   68: aload 4
    //   70: astore_3
    //   71: goto +18 -> 89
    //   74: astore_2
    //   75: aload 4
    //   77: astore_3
    //   78: goto +22 -> 100
    //   81: astore_2
    //   82: goto +29 -> 111
    //   85: astore_2
    //   86: aload 5
    //   88: astore_3
    //   89: new 191	android/view/InflateException
    //   92: dup
    //   93: ldc -63
    //   95: aload_2
    //   96: invokespecial 196	android/view/InflateException:<init>	(Ljava/lang/String;Ljava/lang/Throwable;)V
    //   99: athrow
    //   100: new 191	android/view/InflateException
    //   103: dup
    //   104: ldc -63
    //   106: aload_2
    //   107: invokespecial 196	android/view/InflateException:<init>	(Ljava/lang/String;Ljava/lang/Throwable;)V
    //   110: athrow
    //   111: aload_3
    //   112: ifnull +9 -> 121
    //   115: aload_3
    //   116: invokeinterface 189 1 0
    //   121: aload_2
    //   122: athrow
    //   123: astore_2
    //   124: aload 6
    //   126: astore_3
    //   127: goto -27 -> 100
    // Local variable table:
    //   start	length	slot	name	signature
    //   0	130	0	this	SupportMenuInflater
    //   0	130	1	paramInt	int
    //   0	130	2	paramMenu	Menu
    //   21	106	3	localObject1	Object
    //   33	43	4	localXmlResourceParser	android.content.res.XmlResourceParser
    //   15	72	5	localObject2	Object
    //   18	107	6	localObject3	Object
    // Exception table:
    //   from	to	target	type
    //   35	47	60	finally
    //   35	47	67	java/io/IOException
    //   35	47	74	org/xmlpull/v1/XmlPullParserException
    //   22	35	81	finally
    //   89	100	81	finally
    //   100	111	81	finally
    //   22	35	85	java/io/IOException
    //   22	35	123	org/xmlpull/v1/XmlPullParserException
  }
  
  private static class InflatedOnMenuItemClickListener
    implements MenuItem.OnMenuItemClickListener
  {
    private static final Class<?>[] PARAM_TYPES = { MenuItem.class };
    private Method mMethod;
    private Object mRealOwner;
    
    public InflatedOnMenuItemClickListener(Object paramObject, String paramString)
    {
      mRealOwner = paramObject;
      Class localClass = paramObject.getClass();
      try
      {
        mMethod = localClass.getMethod(paramString, PARAM_TYPES);
        return;
      }
      catch (Exception paramObject)
      {
        StringBuilder localStringBuilder = new StringBuilder();
        localStringBuilder.append("Couldn't resolve menu item onClick handler ");
        localStringBuilder.append(paramString);
        localStringBuilder.append(" in class ");
        localStringBuilder.append(localClass.getName());
        paramString = new InflateException(localStringBuilder.toString());
        paramString.initCause(paramObject);
        throw paramString;
      }
    }
    
    public boolean onMenuItemClick(MenuItem paramMenuItem)
    {
      try
      {
        if (mMethod.getReturnType() == Boolean.TYPE) {
          return ((Boolean)mMethod.invoke(mRealOwner, new Object[] { paramMenuItem })).booleanValue();
        }
        mMethod.invoke(mRealOwner, new Object[] { paramMenuItem });
        return true;
      }
      catch (Exception paramMenuItem)
      {
        throw new RuntimeException(paramMenuItem);
      }
    }
  }
  
  private class MenuState
  {
    private static final int defaultGroupId = 0;
    private static final int defaultItemCategory = 0;
    private static final int defaultItemCheckable = 0;
    private static final boolean defaultItemChecked = false;
    private static final boolean defaultItemEnabled = true;
    private static final int defaultItemId = 0;
    private static final int defaultItemOrder = 0;
    private static final boolean defaultItemVisible = true;
    private int groupCategory;
    private int groupCheckable;
    private boolean groupEnabled;
    private int groupId;
    private int groupOrder;
    private boolean groupVisible;
    ActionProvider itemActionProvider;
    private String itemActionProviderClassName;
    private String itemActionViewClassName;
    private int itemActionViewLayout;
    private boolean itemAdded;
    private int itemAlphabeticModifiers;
    private char itemAlphabeticShortcut;
    private int itemCategoryOrder;
    private int itemCheckable;
    private boolean itemChecked;
    private CharSequence itemContentDescription;
    private boolean itemEnabled;
    private int itemIconResId;
    private ColorStateList itemIconTintList = null;
    private PorterDuff.Mode itemIconTintMode = null;
    private int itemId;
    private String itemListenerMethodName;
    private int itemNumericModifiers;
    private char itemNumericShortcut;
    private int itemShowAsAction;
    private CharSequence itemTitle;
    private CharSequence itemTitleCondensed;
    private CharSequence itemTooltipText;
    private boolean itemVisible;
    private Menu menu;
    
    public MenuState(Menu paramMenu)
    {
      menu = paramMenu;
      resetGroup();
    }
    
    private char getShortcut(String paramString)
    {
      if (paramString == null) {
        return '\000';
      }
      return paramString.charAt(0);
    }
    
    private <T> T newInstance(String paramString, Class<?>[] paramArrayOfClass, Object[] paramArrayOfObject)
    {
      try
      {
        paramArrayOfClass = mContext.getClassLoader().loadClass(paramString).getConstructor(paramArrayOfClass);
        paramArrayOfClass.setAccessible(true);
        paramArrayOfClass = paramArrayOfClass.newInstance(paramArrayOfObject);
        return paramArrayOfClass;
      }
      catch (Exception paramArrayOfClass)
      {
        paramArrayOfObject = new StringBuilder();
        paramArrayOfObject.append("Cannot instantiate class: ");
        paramArrayOfObject.append(paramString);
        Log.w("SupportMenuInflater", paramArrayOfObject.toString(), paramArrayOfClass);
      }
      return null;
    }
    
    private void setItem(MenuItem paramMenuItem)
    {
      Object localObject = paramMenuItem.setChecked(itemChecked).setVisible(itemVisible).setEnabled(itemEnabled);
      int j = itemCheckable;
      int i = 0;
      if (j >= 1) {
        bool = true;
      } else {
        bool = false;
      }
      ((MenuItem)localObject).setCheckable(bool).setTitleCondensed(itemTitleCondensed).setIcon(itemIconResId);
      if (itemShowAsAction >= 0) {
        paramMenuItem.setShowAsAction(itemShowAsAction);
      }
      if (itemListenerMethodName != null) {
        if (!mContext.isRestricted()) {
          paramMenuItem.setOnMenuItemClickListener(new SupportMenuInflater.InflatedOnMenuItemClickListener(getRealOwner(), itemListenerMethodName));
        } else {
          throw new IllegalStateException("The android:onClick attribute cannot be used within a restricted context");
        }
      }
      boolean bool = paramMenuItem instanceof MenuItemImpl;
      if (bool) {
        localObject = (MenuItemImpl)paramMenuItem;
      }
      if (itemCheckable >= 2) {
        if (bool) {
          ((MenuItemImpl)paramMenuItem).setExclusiveCheckable(true);
        } else if ((paramMenuItem instanceof MenuItemWrapperICS)) {
          ((MenuItemWrapperICS)paramMenuItem).setExclusiveCheckable(true);
        }
      }
      if (itemActionViewClassName != null)
      {
        paramMenuItem.setActionView((View)newInstance(itemActionViewClassName, SupportMenuInflater.ACTION_VIEW_CONSTRUCTOR_SIGNATURE, mActionViewConstructorArguments));
        i = 1;
      }
      if (itemActionViewLayout > 0) {
        if (i == 0) {
          paramMenuItem.setActionView(itemActionViewLayout);
        } else {
          Log.w("SupportMenuInflater", "Ignoring attribute 'itemActionViewLayout'. Action view already specified.");
        }
      }
      if (itemActionProvider != null) {
        MenuItemCompat.setActionProvider(paramMenuItem, itemActionProvider);
      }
      MenuItemCompat.setContentDescription(paramMenuItem, itemContentDescription);
      MenuItemCompat.setTooltipText(paramMenuItem, itemTooltipText);
      MenuItemCompat.setAlphabeticShortcut(paramMenuItem, itemAlphabeticShortcut, itemAlphabeticModifiers);
      MenuItemCompat.setNumericShortcut(paramMenuItem, itemNumericShortcut, itemNumericModifiers);
      if (itemIconTintMode != null) {
        MenuItemCompat.setIconTintMode(paramMenuItem, itemIconTintMode);
      }
      if (itemIconTintList != null) {
        MenuItemCompat.setIconTintList(paramMenuItem, itemIconTintList);
      }
    }
    
    public void addItem()
    {
      itemAdded = true;
      setItem(menu.add(groupId, itemId, itemCategoryOrder, itemTitle));
    }
    
    public SubMenu addSubMenuItem()
    {
      itemAdded = true;
      SubMenu localSubMenu = menu.addSubMenu(groupId, itemId, itemCategoryOrder, itemTitle);
      setItem(localSubMenu.getItem());
      return localSubMenu;
    }
    
    public boolean hasAddedItem()
    {
      return itemAdded;
    }
    
    public void readGroup(AttributeSet paramAttributeSet)
    {
      paramAttributeSet = mContext.obtainStyledAttributes(paramAttributeSet, R.styleable.MenuGroup);
      groupId = paramAttributeSet.getResourceId(R.styleable.MenuGroup_android_id, 0);
      groupCategory = paramAttributeSet.getInt(R.styleable.MenuGroup_android_menuCategory, 0);
      groupOrder = paramAttributeSet.getInt(R.styleable.MenuGroup_android_orderInCategory, 0);
      groupCheckable = paramAttributeSet.getInt(R.styleable.MenuGroup_android_checkableBehavior, 0);
      groupVisible = paramAttributeSet.getBoolean(R.styleable.MenuGroup_android_visible, true);
      groupEnabled = paramAttributeSet.getBoolean(R.styleable.MenuGroup_android_enabled, true);
      paramAttributeSet.recycle();
    }
    
    public void readItem(AttributeSet paramAttributeSet)
    {
      throw new Runtime("d2j fail translate: java.lang.RuntimeException: can not merge I and Z\n\tat com.googlecode.dex2jar.ir.TypeClass.merge(TypeClass.java:100)\n\tat com.googlecode.dex2jar.ir.ts.TypeTransformer$TypeRef.updateTypeClass(TypeTransformer.java:174)\n\tat com.googlecode.dex2jar.ir.ts.TypeTransformer$TypeAnalyze.copyTypes(TypeTransformer.java:311)\n\tat com.googlecode.dex2jar.ir.ts.TypeTransformer$TypeAnalyze.fixTypes(TypeTransformer.java:226)\n\tat com.googlecode.dex2jar.ir.ts.TypeTransformer$TypeAnalyze.analyze(TypeTransformer.java:207)\n\tat com.googlecode.dex2jar.ir.ts.TypeTransformer.transform(TypeTransformer.java:44)\n\tat com.googlecode.d2j.dex.Dex2jar$2.optimize(Dex2jar.java:162)\n\tat com.googlecode.d2j.dex.Dex2Asm.convertCode(Dex2Asm.java:414)\n\tat com.googlecode.d2j.dex.ExDex2Asm.convertCode(ExDex2Asm.java:42)\n\tat com.googlecode.d2j.dex.Dex2jar$2.convertCode(Dex2jar.java:128)\n\tat com.googlecode.d2j.dex.Dex2Asm.convertMethod(Dex2Asm.java:509)\n\tat com.googlecode.d2j.dex.Dex2Asm.convertClass(Dex2Asm.java:406)\n\tat com.googlecode.d2j.dex.Dex2Asm.convertDex(Dex2Asm.java:422)\n\tat com.googlecode.d2j.dex.Dex2jar.doTranslate(Dex2jar.java:172)\n\tat com.googlecode.d2j.dex.Dex2jar.to(Dex2jar.java:272)\n\tat com.googlecode.dex2jar.tools.Dex2jarCmd.doCommandLine(Dex2jarCmd.java:108)\n\tat com.googlecode.dex2jar.tools.BaseCmd.doMain(BaseCmd.java:288)\n\tat com.googlecode.dex2jar.tools.Dex2jarCmd.main(Dex2jarCmd.java:32)\n");
    }
    
    public void resetGroup()
    {
      groupId = 0;
      groupCategory = 0;
      groupOrder = 0;
      groupCheckable = 0;
      groupVisible = true;
      groupEnabled = true;
    }
  }
}
