package com.google.gson;

import com.google.gson.internal.ConstructorConstructor;
import com.google.gson.internal.Excluder;
import com.google.gson.internal.Primitives;
import com.google.gson.internal.Streams;
import com.google.gson.internal.bind.ArrayTypeAdapter;
import com.google.gson.internal.bind.CollectionTypeAdapterFactory;
import com.google.gson.internal.bind.DateTypeAdapter;
import com.google.gson.internal.bind.JsonAdapterAnnotationTypeAdapterFactory;
import com.google.gson.internal.bind.JsonTreeReader;
import com.google.gson.internal.bind.JsonTreeWriter;
import com.google.gson.internal.bind.MapTypeAdapterFactory;
import com.google.gson.internal.bind.ObjectTypeAdapter;
import com.google.gson.internal.bind.ReflectiveTypeAdapterFactory;
import com.google.gson.internal.bind.SqlDateTypeAdapter;
import com.google.gson.internal.bind.TimeTypeAdapter;
import com.google.gson.internal.bind.TypeAdapters;
import com.google.gson.reflect.TypeToken;
import com.google.gson.stream.JsonReader;
import com.google.gson.stream.JsonToken;
import com.google.gson.stream.JsonWriter;
import com.google.gson.stream.MalformedJsonException;
import java.io.IOException;
import java.io.Reader;
import java.io.StringReader;
import java.io.StringWriter;
import java.io.Writer;
import java.lang.reflect.Type;
import java.math.BigDecimal;
import java.math.BigInteger;
import java.util.ArrayList;
import java.util.Collections;
import java.util.HashMap;
import java.util.Iterator;
import java.util.List;
import java.util.Map;
import java.util.concurrent.ConcurrentHashMap;
import java.util.concurrent.atomic.AtomicLong;
import java.util.concurrent.atomic.AtomicLongArray;

public final class Gson
{
  static final boolean DEFAULT_COMPLEX_MAP_KEYS = false;
  static final boolean DEFAULT_ESCAPE_HTML = true;
  static final boolean DEFAULT_JSON_NON_EXECUTABLE = false;
  static final boolean DEFAULT_LENIENT = false;
  static final boolean DEFAULT_PRETTY_PRINT = false;
  static final boolean DEFAULT_SERIALIZE_NULLS = false;
  static final boolean DEFAULT_SPECIALIZE_FLOAT_VALUES = false;
  private static final String JSON_NON_EXECUTABLE_PREFIX = ")]}'\n";
  private static final TypeToken<?> NULL_KEY_SURROGATE = TypeToken.get(Object.class);
  private final ThreadLocal<Map<TypeToken<?>, FutureTypeAdapter<?>>> calls = new ThreadLocal();
  private final ConstructorConstructor constructorConstructor;
  private final Excluder excluder;
  private final List<TypeAdapterFactory> factories;
  private final FieldNamingStrategy fieldNamingStrategy;
  private final boolean generateNonExecutableJson;
  private final boolean htmlSafe;
  private final JsonAdapterAnnotationTypeAdapterFactory jsonAdapterFactory;
  private final boolean lenient;
  private final boolean prettyPrinting;
  private final boolean serializeNulls;
  private final Map<TypeToken<?>, TypeAdapter<?>> typeTokenCache = new ConcurrentHashMap();
  
  public Gson()
  {
    this(Excluder.DEFAULT, FieldNamingPolicy.IDENTITY, Collections.emptyMap(), false, false, false, true, false, false, false, LongSerializationPolicy.DEFAULT, Collections.emptyList());
  }
  
  Gson(Excluder paramExcluder, FieldNamingStrategy paramFieldNamingStrategy, Map<Type, InstanceCreator<?>> paramMap, boolean paramBoolean1, boolean paramBoolean2, boolean paramBoolean3, boolean paramBoolean4, boolean paramBoolean5, boolean paramBoolean6, boolean paramBoolean7, LongSerializationPolicy paramLongSerializationPolicy, List<TypeAdapterFactory> paramList)
  {
    constructorConstructor = new ConstructorConstructor(paramMap);
    excluder = paramExcluder;
    fieldNamingStrategy = paramFieldNamingStrategy;
    serializeNulls = paramBoolean1;
    generateNonExecutableJson = paramBoolean3;
    htmlSafe = paramBoolean4;
    prettyPrinting = paramBoolean5;
    lenient = paramBoolean6;
    paramMap = new ArrayList();
    paramMap.add(TypeAdapters.JSON_ELEMENT_FACTORY);
    paramMap.add(ObjectTypeAdapter.FACTORY);
    paramMap.add(paramExcluder);
    paramMap.addAll(paramList);
    paramMap.add(TypeAdapters.STRING_FACTORY);
    paramMap.add(TypeAdapters.INTEGER_FACTORY);
    paramMap.add(TypeAdapters.BOOLEAN_FACTORY);
    paramMap.add(TypeAdapters.BYTE_FACTORY);
    paramMap.add(TypeAdapters.SHORT_FACTORY);
    paramLongSerializationPolicy = longAdapter(paramLongSerializationPolicy);
    paramMap.add(TypeAdapters.newFactory(Long.TYPE, Long.class, paramLongSerializationPolicy));
    paramMap.add(TypeAdapters.newFactory(Double.TYPE, Double.class, doubleAdapter(paramBoolean7)));
    paramMap.add(TypeAdapters.newFactory(Float.TYPE, Float.class, floatAdapter(paramBoolean7)));
    paramMap.add(TypeAdapters.NUMBER_FACTORY);
    paramMap.add(TypeAdapters.ATOMIC_INTEGER_FACTORY);
    paramMap.add(TypeAdapters.ATOMIC_BOOLEAN_FACTORY);
    paramMap.add(TypeAdapters.newFactory(AtomicLong.class, atomicLongAdapter(paramLongSerializationPolicy)));
    paramMap.add(TypeAdapters.newFactory(AtomicLongArray.class, atomicLongArrayAdapter(paramLongSerializationPolicy)));
    paramMap.add(TypeAdapters.ATOMIC_INTEGER_ARRAY_FACTORY);
    paramMap.add(TypeAdapters.CHARACTER_FACTORY);
    paramMap.add(TypeAdapters.STRING_BUILDER_FACTORY);
    paramMap.add(TypeAdapters.STRING_BUFFER_FACTORY);
    paramMap.add(TypeAdapters.newFactory(BigDecimal.class, TypeAdapters.BIG_DECIMAL));
    paramMap.add(TypeAdapters.newFactory(BigInteger.class, TypeAdapters.BIG_INTEGER));
    paramMap.add(TypeAdapters.URL_FACTORY);
    paramMap.add(TypeAdapters.URI_FACTORY);
    paramMap.add(TypeAdapters.UUID_FACTORY);
    paramMap.add(TypeAdapters.CURRENCY_FACTORY);
    paramMap.add(TypeAdapters.LOCALE_FACTORY);
    paramMap.add(TypeAdapters.INET_ADDRESS_FACTORY);
    paramMap.add(TypeAdapters.BIT_SET_FACTORY);
    paramMap.add(DateTypeAdapter.FACTORY);
    paramMap.add(TypeAdapters.CALENDAR_FACTORY);
    paramMap.add(TimeTypeAdapter.FACTORY);
    paramMap.add(SqlDateTypeAdapter.FACTORY);
    paramMap.add(TypeAdapters.TIMESTAMP_FACTORY);
    paramMap.add(ArrayTypeAdapter.FACTORY);
    paramMap.add(TypeAdapters.CLASS_FACTORY);
    paramMap.add(new CollectionTypeAdapterFactory(constructorConstructor));
    paramMap.add(new MapTypeAdapterFactory(constructorConstructor, paramBoolean2));
    jsonAdapterFactory = new JsonAdapterAnnotationTypeAdapterFactory(constructorConstructor);
    paramMap.add(jsonAdapterFactory);
    paramMap.add(TypeAdapters.ENUM_FACTORY);
    paramMap.add(new ReflectiveTypeAdapterFactory(constructorConstructor, paramFieldNamingStrategy, paramExcluder, jsonAdapterFactory));
    factories = Collections.unmodifiableList(paramMap);
  }
  
  private static void assertFullConsumption(Object paramObject, JsonReader paramJsonReader)
  {
    if (paramObject != null) {
      try
      {
        if (paramJsonReader.peek() == JsonToken.END_DOCUMENT) {
          return;
        }
        throw new JsonIOException("JSON document was not fully consumed.");
      }
      catch (IOException paramObject)
      {
        throw new JsonIOException(paramObject);
      }
      catch (MalformedJsonException paramObject)
      {
        throw new JsonSyntaxException(paramObject);
      }
    }
  }
  
  private static TypeAdapter<AtomicLong> atomicLongAdapter(TypeAdapter<Number> paramTypeAdapter)
  {
    new TypeAdapter()
    {
      public AtomicLong read(JsonReader paramAnonymousJsonReader)
        throws IOException
      {
        return new AtomicLong(((Number)val$longAdapter.read(paramAnonymousJsonReader)).longValue());
      }
      
      public void write(JsonWriter paramAnonymousJsonWriter, AtomicLong paramAnonymousAtomicLong)
        throws IOException
      {
        val$longAdapter.write(paramAnonymousJsonWriter, Long.valueOf(paramAnonymousAtomicLong.get()));
      }
    }.nullSafe();
  }
  
  private static TypeAdapter<AtomicLongArray> atomicLongArrayAdapter(TypeAdapter<Number> paramTypeAdapter)
  {
    new TypeAdapter()
    {
      public AtomicLongArray read(JsonReader paramAnonymousJsonReader)
        throws IOException
      {
        ArrayList localArrayList = new ArrayList();
        paramAnonymousJsonReader.beginArray();
        while (paramAnonymousJsonReader.hasNext()) {
          localArrayList.add(Long.valueOf(((Number)val$longAdapter.read(paramAnonymousJsonReader)).longValue()));
        }
        paramAnonymousJsonReader.endArray();
        int j = localArrayList.size();
        paramAnonymousJsonReader = new AtomicLongArray(j);
        int i = 0;
        while (i < j)
        {
          paramAnonymousJsonReader.set(i, ((Long)localArrayList.get(i)).longValue());
          i += 1;
        }
        return paramAnonymousJsonReader;
      }
      
      public void write(JsonWriter paramAnonymousJsonWriter, AtomicLongArray paramAnonymousAtomicLongArray)
        throws IOException
      {
        paramAnonymousJsonWriter.beginArray();
        int j = paramAnonymousAtomicLongArray.length();
        int i = 0;
        while (i < j)
        {
          val$longAdapter.write(paramAnonymousJsonWriter, Long.valueOf(paramAnonymousAtomicLongArray.get(i)));
          i += 1;
        }
        paramAnonymousJsonWriter.endArray();
      }
    }.nullSafe();
  }
  
  static void checkValidFloatingPoint(double paramDouble)
  {
    if ((!Double.isNaN(paramDouble)) && (!Double.isInfinite(paramDouble))) {
      return;
    }
    StringBuilder localStringBuilder = new StringBuilder();
    localStringBuilder.append(paramDouble);
    localStringBuilder.append(" is not a valid double value as per JSON specification. To override this behavior, use GsonBuilder.serializeSpecialFloatingPointValues() method.");
    throw new IllegalArgumentException(localStringBuilder.toString());
  }
  
  private TypeAdapter<Number> doubleAdapter(boolean paramBoolean)
  {
    if (paramBoolean) {
      return TypeAdapters.DOUBLE;
    }
    new TypeAdapter()
    {
      public Double read(JsonReader paramAnonymousJsonReader)
        throws IOException
      {
        if (paramAnonymousJsonReader.peek() == JsonToken.NULL)
        {
          paramAnonymousJsonReader.nextNull();
          return null;
        }
        return Double.valueOf(paramAnonymousJsonReader.nextDouble());
      }
      
      public void write(JsonWriter paramAnonymousJsonWriter, Number paramAnonymousNumber)
        throws IOException
      {
        if (paramAnonymousNumber == null)
        {
          paramAnonymousJsonWriter.nullValue();
          return;
        }
        Gson.checkValidFloatingPoint(paramAnonymousNumber.doubleValue());
        paramAnonymousJsonWriter.value(paramAnonymousNumber);
      }
    };
  }
  
  private TypeAdapter<Number> floatAdapter(boolean paramBoolean)
  {
    if (paramBoolean) {
      return TypeAdapters.FLOAT;
    }
    new TypeAdapter()
    {
      public Float read(JsonReader paramAnonymousJsonReader)
        throws IOException
      {
        if (paramAnonymousJsonReader.peek() == JsonToken.NULL)
        {
          paramAnonymousJsonReader.nextNull();
          return null;
        }
        return Float.valueOf((float)paramAnonymousJsonReader.nextDouble());
      }
      
      public void write(JsonWriter paramAnonymousJsonWriter, Number paramAnonymousNumber)
        throws IOException
      {
        if (paramAnonymousNumber == null)
        {
          paramAnonymousJsonWriter.nullValue();
          return;
        }
        Gson.checkValidFloatingPoint(paramAnonymousNumber.floatValue());
        paramAnonymousJsonWriter.value(paramAnonymousNumber);
      }
    };
  }
  
  private static TypeAdapter<Number> longAdapter(LongSerializationPolicy paramLongSerializationPolicy)
  {
    if (paramLongSerializationPolicy == LongSerializationPolicy.DEFAULT) {
      return TypeAdapters.LONG;
    }
    new TypeAdapter()
    {
      public Number read(JsonReader paramAnonymousJsonReader)
        throws IOException
      {
        if (paramAnonymousJsonReader.peek() == JsonToken.NULL)
        {
          paramAnonymousJsonReader.nextNull();
          return null;
        }
        return Long.valueOf(paramAnonymousJsonReader.nextLong());
      }
      
      public void write(JsonWriter paramAnonymousJsonWriter, Number paramAnonymousNumber)
        throws IOException
      {
        if (paramAnonymousNumber == null)
        {
          paramAnonymousJsonWriter.nullValue();
          return;
        }
        paramAnonymousJsonWriter.value(paramAnonymousNumber.toString());
      }
    };
  }
  
  public Excluder excluder()
  {
    return excluder;
  }
  
  public FieldNamingStrategy fieldNamingStrategy()
  {
    return fieldNamingStrategy;
  }
  
  public <T> T fromJson(JsonElement paramJsonElement, Class<T> paramClass)
    throws JsonSyntaxException
  {
    paramJsonElement = fromJson(paramJsonElement, paramClass);
    return Primitives.wrap(paramClass).cast(paramJsonElement);
  }
  
  public <T> T fromJson(JsonElement paramJsonElement, Type paramType)
    throws JsonSyntaxException
  {
    if (paramJsonElement == null) {
      return null;
    }
    return fromJson(new JsonTreeReader(paramJsonElement), paramType);
  }
  
  /* Error */
  public <T> T fromJson(JsonReader paramJsonReader, Type paramType)
    throws JsonIOException, JsonSyntaxException
  {
    // Byte code:
    //   0: aload_1
    //   1: invokevirtual 439	com/google/gson/stream/JsonReader:isLenient	()Z
    //   4: istore 4
    //   6: iconst_1
    //   7: istore_3
    //   8: aload_1
    //   9: iconst_1
    //   10: invokevirtual 443	com/google/gson/stream/JsonReader:setLenient	(Z)V
    //   13: aload_1
    //   14: invokevirtual 327	com/google/gson/stream/JsonReader:peek	()Lcom/google/gson/stream/JsonToken;
    //   17: pop
    //   18: iconst_0
    //   19: istore_3
    //   20: aload_0
    //   21: aload_2
    //   22: invokestatic 446	com/google/gson/reflect/TypeToken:get	(Ljava/lang/reflect/Type;)Lcom/google/gson/reflect/TypeToken;
    //   25: invokevirtual 450	com/google/gson/Gson:getAdapter	(Lcom/google/gson/reflect/TypeToken;)Lcom/google/gson/TypeAdapter;
    //   28: aload_1
    //   29: invokevirtual 456	com/google/gson/TypeAdapter:read	(Lcom/google/gson/stream/JsonReader;)Ljava/lang/Object;
    //   32: astore_2
    //   33: aload_1
    //   34: iload 4
    //   36: invokevirtual 443	com/google/gson/stream/JsonReader:setLenient	(Z)V
    //   39: aload_2
    //   40: areturn
    //   41: astore_2
    //   42: goto +45 -> 87
    //   45: astore_2
    //   46: new 345	com/google/gson/JsonSyntaxException
    //   49: dup
    //   50: aload_2
    //   51: invokespecial 346	com/google/gson/JsonSyntaxException:<init>	(Ljava/lang/Throwable;)V
    //   54: athrow
    //   55: astore_2
    //   56: new 345	com/google/gson/JsonSyntaxException
    //   59: dup
    //   60: aload_2
    //   61: invokespecial 346	com/google/gson/JsonSyntaxException:<init>	(Ljava/lang/Throwable;)V
    //   64: athrow
    //   65: astore_2
    //   66: iload_3
    //   67: ifeq +11 -> 78
    //   70: aload_1
    //   71: iload 4
    //   73: invokevirtual 443	com/google/gson/stream/JsonReader:setLenient	(Z)V
    //   76: aconst_null
    //   77: areturn
    //   78: new 345	com/google/gson/JsonSyntaxException
    //   81: dup
    //   82: aload_2
    //   83: invokespecial 346	com/google/gson/JsonSyntaxException:<init>	(Ljava/lang/Throwable;)V
    //   86: athrow
    //   87: aload_1
    //   88: iload 4
    //   90: invokevirtual 443	com/google/gson/stream/JsonReader:setLenient	(Z)V
    //   93: aload_2
    //   94: athrow
    // Local variable table:
    //   start	length	slot	name	signature
    //   0	95	0	this	Gson
    //   0	95	1	paramJsonReader	JsonReader
    //   0	95	2	paramType	Type
    //   7	60	3	i	int
    //   4	85	4	bool	boolean
    // Exception table:
    //   from	to	target	type
    //   13	18	41	finally
    //   20	33	41	finally
    //   46	55	41	finally
    //   56	65	41	finally
    //   78	87	41	finally
    //   13	18	45	java/io/IOException
    //   20	33	45	java/io/IOException
    //   13	18	55	java/lang/IllegalStateException
    //   20	33	55	java/lang/IllegalStateException
    //   13	18	65	java/io/EOFException
    //   20	33	65	java/io/EOFException
  }
  
  public <T> T fromJson(Reader paramReader, Class<T> paramClass)
    throws JsonSyntaxException, JsonIOException
  {
    paramReader = newJsonReader(paramReader);
    Object localObject = fromJson(paramReader, paramClass);
    assertFullConsumption(localObject, paramReader);
    return Primitives.wrap(paramClass).cast(localObject);
  }
  
  public <T> T fromJson(Reader paramReader, Type paramType)
    throws JsonIOException, JsonSyntaxException
  {
    paramReader = newJsonReader(paramReader);
    paramType = fromJson(paramReader, paramType);
    assertFullConsumption(paramType, paramReader);
    return paramType;
  }
  
  public <T> T fromJson(String paramString, Class<T> paramClass)
    throws JsonSyntaxException
  {
    paramString = fromJson(paramString, paramClass);
    return Primitives.wrap(paramClass).cast(paramString);
  }
  
  public <T> T fromJson(String paramString, Type paramType)
    throws JsonSyntaxException
  {
    if (paramString == null) {
      return null;
    }
    return fromJson(new StringReader(paramString), paramType);
  }
  
  public <T> TypeAdapter<T> getAdapter(TypeToken<T> paramTypeToken)
  {
    Object localObject2 = typeTokenCache;
    if (paramTypeToken == null) {
      localObject1 = NULL_KEY_SURROGATE;
    } else {
      localObject1 = paramTypeToken;
    }
    Object localObject1 = (TypeAdapter)((Map)localObject2).get(localObject1);
    if (localObject1 != null) {
      return localObject1;
    }
    localObject2 = (Map)calls.get();
    int i = 0;
    localObject1 = localObject2;
    if (localObject2 == null)
    {
      localObject1 = new HashMap();
      calls.set(localObject1);
      i = 1;
    }
    localObject2 = (FutureTypeAdapter)((Map)localObject1).get(paramTypeToken);
    if (localObject2 != null) {
      return localObject2;
    }
    try
    {
      localObject2 = new FutureTypeAdapter();
      ((Map)localObject1).put(paramTypeToken, localObject2);
      Iterator localIterator = factories.iterator();
      while (localIterator.hasNext())
      {
        TypeAdapter localTypeAdapter = ((TypeAdapterFactory)localIterator.next()).create(this, paramTypeToken);
        if (localTypeAdapter != null)
        {
          ((FutureTypeAdapter)localObject2).setDelegate(localTypeAdapter);
          typeTokenCache.put(paramTypeToken, localTypeAdapter);
          return localTypeAdapter;
        }
      }
      localObject2 = new StringBuilder();
      ((StringBuilder)localObject2).append("GSON cannot handle ");
      ((StringBuilder)localObject2).append(paramTypeToken);
      throw new IllegalArgumentException(((StringBuilder)localObject2).toString());
    }
    finally
    {
      ((Map)localObject1).remove(paramTypeToken);
      if (i != 0) {
        calls.remove();
      }
    }
  }
  
  public <T> TypeAdapter<T> getAdapter(Class<T> paramClass)
  {
    return getAdapter(TypeToken.get(paramClass));
  }
  
  public <T> TypeAdapter<T> getDelegateAdapter(TypeAdapterFactory paramTypeAdapterFactory, TypeToken<T> paramTypeToken)
  {
    Object localObject1 = paramTypeAdapterFactory;
    if (!factories.contains(paramTypeAdapterFactory)) {
      localObject1 = jsonAdapterFactory;
    }
    int i = 0;
    paramTypeAdapterFactory = factories.iterator();
    while (paramTypeAdapterFactory.hasNext())
    {
      Object localObject2 = (TypeAdapterFactory)paramTypeAdapterFactory.next();
      if (i == 0)
      {
        if (localObject2 == localObject1) {
          i = 1;
        }
      }
      else
      {
        localObject2 = ((TypeAdapterFactory)localObject2).create(this, paramTypeToken);
        if (localObject2 != null) {
          return localObject2;
        }
      }
    }
    paramTypeAdapterFactory = new StringBuilder();
    paramTypeAdapterFactory.append("GSON cannot serialize ");
    paramTypeAdapterFactory.append(paramTypeToken);
    throw new IllegalArgumentException(paramTypeAdapterFactory.toString());
  }
  
  public boolean htmlSafe()
  {
    return htmlSafe;
  }
  
  public JsonReader newJsonReader(Reader paramReader)
  {
    paramReader = new JsonReader(paramReader);
    paramReader.setLenient(lenient);
    return paramReader;
  }
  
  public JsonWriter newJsonWriter(Writer paramWriter)
    throws IOException
  {
    if (generateNonExecutableJson) {
      paramWriter.write(")]}'\n");
    }
    paramWriter = new JsonWriter(paramWriter);
    if (prettyPrinting) {
      paramWriter.setIndent("  ");
    }
    paramWriter.setSerializeNulls(serializeNulls);
    return paramWriter;
  }
  
  public boolean serializeNulls()
  {
    return serializeNulls;
  }
  
  public String toJson(JsonElement paramJsonElement)
  {
    StringWriter localStringWriter = new StringWriter();
    toJson(paramJsonElement, localStringWriter);
    return localStringWriter.toString();
  }
  
  public String toJson(Object paramObject)
  {
    if (paramObject == null) {
      return toJson(JsonNull.INSTANCE);
    }
    return toJson(paramObject, paramObject.getClass());
  }
  
  public String toJson(Object paramObject, Type paramType)
  {
    StringWriter localStringWriter = new StringWriter();
    toJson(paramObject, paramType, localStringWriter);
    return localStringWriter.toString();
  }
  
  /* Error */
  public void toJson(JsonElement paramJsonElement, JsonWriter paramJsonWriter)
    throws JsonIOException
  {
    // Byte code:
    //   0: aload_2
    //   1: invokevirtual 592	com/google/gson/stream/JsonWriter:isLenient	()Z
    //   4: istore_3
    //   5: aload_2
    //   6: iconst_1
    //   7: invokevirtual 593	com/google/gson/stream/JsonWriter:setLenient	(Z)V
    //   10: aload_2
    //   11: invokevirtual 596	com/google/gson/stream/JsonWriter:isHtmlSafe	()Z
    //   14: istore 4
    //   16: aload_2
    //   17: aload_0
    //   18: getfield 126	com/google/gson/Gson:htmlSafe	Z
    //   21: invokevirtual 599	com/google/gson/stream/JsonWriter:setHtmlSafe	(Z)V
    //   24: aload_2
    //   25: invokevirtual 602	com/google/gson/stream/JsonWriter:getSerializeNulls	()Z
    //   28: istore 5
    //   30: aload_2
    //   31: aload_0
    //   32: getfield 122	com/google/gson/Gson:serializeNulls	Z
    //   35: invokevirtual 562	com/google/gson/stream/JsonWriter:setSerializeNulls	(Z)V
    //   38: aload_1
    //   39: aload_2
    //   40: invokestatic 606	com/google/gson/internal/Streams:write	(Lcom/google/gson/JsonElement;Lcom/google/gson/stream/JsonWriter;)V
    //   43: aload_2
    //   44: iload_3
    //   45: invokevirtual 593	com/google/gson/stream/JsonWriter:setLenient	(Z)V
    //   48: aload_2
    //   49: iload 4
    //   51: invokevirtual 599	com/google/gson/stream/JsonWriter:setHtmlSafe	(Z)V
    //   54: aload_2
    //   55: iload 5
    //   57: invokevirtual 562	com/google/gson/stream/JsonWriter:setSerializeNulls	(Z)V
    //   60: return
    //   61: astore_1
    //   62: goto +13 -> 75
    //   65: astore_1
    //   66: new 335	com/google/gson/JsonIOException
    //   69: dup
    //   70: aload_1
    //   71: invokespecial 343	com/google/gson/JsonIOException:<init>	(Ljava/lang/Throwable;)V
    //   74: athrow
    //   75: aload_2
    //   76: iload_3
    //   77: invokevirtual 593	com/google/gson/stream/JsonWriter:setLenient	(Z)V
    //   80: aload_2
    //   81: iload 4
    //   83: invokevirtual 599	com/google/gson/stream/JsonWriter:setHtmlSafe	(Z)V
    //   86: aload_2
    //   87: iload 5
    //   89: invokevirtual 562	com/google/gson/stream/JsonWriter:setSerializeNulls	(Z)V
    //   92: aload_1
    //   93: athrow
    // Local variable table:
    //   start	length	slot	name	signature
    //   0	94	0	this	Gson
    //   0	94	1	paramJsonElement	JsonElement
    //   0	94	2	paramJsonWriter	JsonWriter
    //   4	73	3	bool1	boolean
    //   14	68	4	bool2	boolean
    //   28	60	5	bool3	boolean
    // Exception table:
    //   from	to	target	type
    //   38	43	61	finally
    //   66	75	61	finally
    //   38	43	65	java/io/IOException
  }
  
  public void toJson(JsonElement paramJsonElement, Appendable paramAppendable)
    throws JsonIOException
  {
    try
    {
      toJson(paramJsonElement, newJsonWriter(Streams.writerForAppendable(paramAppendable)));
      return;
    }
    catch (IOException paramJsonElement)
    {
      throw new JsonIOException(paramJsonElement);
    }
  }
  
  public void toJson(Object paramObject, Appendable paramAppendable)
    throws JsonIOException
  {
    if (paramObject != null)
    {
      toJson(paramObject, paramObject.getClass(), paramAppendable);
      return;
    }
    toJson(JsonNull.INSTANCE, paramAppendable);
  }
  
  /* Error */
  public void toJson(Object paramObject, Type paramType, JsonWriter paramJsonWriter)
    throws JsonIOException
  {
    // Byte code:
    //   0: aload_0
    //   1: aload_2
    //   2: invokestatic 446	com/google/gson/reflect/TypeToken:get	(Ljava/lang/reflect/Type;)Lcom/google/gson/reflect/TypeToken;
    //   5: invokevirtual 450	com/google/gson/Gson:getAdapter	(Lcom/google/gson/reflect/TypeToken;)Lcom/google/gson/TypeAdapter;
    //   8: astore_2
    //   9: aload_3
    //   10: invokevirtual 592	com/google/gson/stream/JsonWriter:isLenient	()Z
    //   13: istore 4
    //   15: aload_3
    //   16: iconst_1
    //   17: invokevirtual 593	com/google/gson/stream/JsonWriter:setLenient	(Z)V
    //   20: aload_3
    //   21: invokevirtual 596	com/google/gson/stream/JsonWriter:isHtmlSafe	()Z
    //   24: istore 5
    //   26: aload_3
    //   27: aload_0
    //   28: getfield 126	com/google/gson/Gson:htmlSafe	Z
    //   31: invokevirtual 599	com/google/gson/stream/JsonWriter:setHtmlSafe	(Z)V
    //   34: aload_3
    //   35: invokevirtual 602	com/google/gson/stream/JsonWriter:getSerializeNulls	()Z
    //   38: istore 6
    //   40: aload_3
    //   41: aload_0
    //   42: getfield 122	com/google/gson/Gson:serializeNulls	Z
    //   45: invokevirtual 562	com/google/gson/stream/JsonWriter:setSerializeNulls	(Z)V
    //   48: aload_2
    //   49: aload_3
    //   50: aload_1
    //   51: invokevirtual 619	com/google/gson/TypeAdapter:write	(Lcom/google/gson/stream/JsonWriter;Ljava/lang/Object;)V
    //   54: aload_3
    //   55: iload 4
    //   57: invokevirtual 593	com/google/gson/stream/JsonWriter:setLenient	(Z)V
    //   60: aload_3
    //   61: iload 5
    //   63: invokevirtual 599	com/google/gson/stream/JsonWriter:setHtmlSafe	(Z)V
    //   66: aload_3
    //   67: iload 6
    //   69: invokevirtual 562	com/google/gson/stream/JsonWriter:setSerializeNulls	(Z)V
    //   72: return
    //   73: astore_1
    //   74: goto +13 -> 87
    //   77: astore_1
    //   78: new 335	com/google/gson/JsonIOException
    //   81: dup
    //   82: aload_1
    //   83: invokespecial 343	com/google/gson/JsonIOException:<init>	(Ljava/lang/Throwable;)V
    //   86: athrow
    //   87: aload_3
    //   88: iload 4
    //   90: invokevirtual 593	com/google/gson/stream/JsonWriter:setLenient	(Z)V
    //   93: aload_3
    //   94: iload 5
    //   96: invokevirtual 599	com/google/gson/stream/JsonWriter:setHtmlSafe	(Z)V
    //   99: aload_3
    //   100: iload 6
    //   102: invokevirtual 562	com/google/gson/stream/JsonWriter:setSerializeNulls	(Z)V
    //   105: aload_1
    //   106: athrow
    // Local variable table:
    //   start	length	slot	name	signature
    //   0	107	0	this	Gson
    //   0	107	1	paramObject	Object
    //   0	107	2	paramType	Type
    //   0	107	3	paramJsonWriter	JsonWriter
    //   13	76	4	bool1	boolean
    //   24	71	5	bool2	boolean
    //   38	63	6	bool3	boolean
    // Exception table:
    //   from	to	target	type
    //   48	54	73	finally
    //   78	87	73	finally
    //   48	54	77	java/io/IOException
  }
  
  public void toJson(Object paramObject, Type paramType, Appendable paramAppendable)
    throws JsonIOException
  {
    try
    {
      toJson(paramObject, paramType, newJsonWriter(Streams.writerForAppendable(paramAppendable)));
      return;
    }
    catch (IOException paramObject)
    {
      throw new JsonIOException(paramObject);
    }
  }
  
  public JsonElement toJsonTree(Object paramObject)
  {
    if (paramObject == null) {
      return JsonNull.INSTANCE;
    }
    return toJsonTree(paramObject, paramObject.getClass());
  }
  
  public JsonElement toJsonTree(Object paramObject, Type paramType)
  {
    JsonTreeWriter localJsonTreeWriter = new JsonTreeWriter();
    toJson(paramObject, paramType, localJsonTreeWriter);
    return localJsonTreeWriter.get();
  }
  
  public String toString()
  {
    StringBuilder localStringBuilder = new StringBuilder("{serializeNulls:");
    localStringBuilder.append(serializeNulls);
    localStringBuilder.append(",factories:");
    localStringBuilder.append(factories);
    localStringBuilder.append(",instanceCreators:");
    localStringBuilder.append(constructorConstructor);
    localStringBuilder.append("}");
    return localStringBuilder.toString();
  }
  
  static class FutureTypeAdapter<T>
    extends TypeAdapter<T>
  {
    private TypeAdapter<T> delegate;
    
    FutureTypeAdapter() {}
    
    public T read(JsonReader paramJsonReader)
      throws IOException
    {
      if (delegate != null) {
        return delegate.read(paramJsonReader);
      }
      throw new IllegalStateException();
    }
    
    public void setDelegate(TypeAdapter<T> paramTypeAdapter)
    {
      if (delegate == null)
      {
        delegate = paramTypeAdapter;
        return;
      }
      throw new AssertionError();
    }
    
    public void write(JsonWriter paramJsonWriter, T paramT)
      throws IOException
    {
      if (delegate != null)
      {
        delegate.write(paramJsonWriter, paramT);
        return;
      }
      throw new IllegalStateException();
    }
  }
}
