package com.google.android.gms.measurement.internal;

import android.content.ContentValues;
import android.content.Context;
import android.database.Cursor;
import android.database.sqlite.SQLiteDatabase;
import android.database.sqlite.SQLiteException;
import android.support.annotation.WorkerThread;
import android.text.TextUtils;
import com.google.android.gms.common.internal.Preconditions;
import com.google.android.gms.common.util.Clock;
import com.google.android.gms.common.util.VisibleForTesting;
import com.google.android.gms.internal.measurement.zzfu;
import com.google.android.gms.internal.measurement.zzfv;
import com.google.android.gms.internal.measurement.zzfy;
import com.google.android.gms.internal.measurement.zzgf;
import com.google.android.gms.internal.measurement.zzgi;
import com.google.android.gms.internal.measurement.zzyy;
import com.google.android.gms.internal.measurement.zzzg;
import java.io.File;
import java.io.IOException;
import java.util.ArrayList;
import java.util.List;

final class zzq
  extends zzez
{
  private static final String[] zzahi = { "last_bundled_timestamp", "ALTER TABLE events ADD COLUMN last_bundled_timestamp INTEGER;", "last_bundled_day", "ALTER TABLE events ADD COLUMN last_bundled_day INTEGER;", "last_sampled_complex_event_id", "ALTER TABLE events ADD COLUMN last_sampled_complex_event_id INTEGER;", "last_sampling_rate", "ALTER TABLE events ADD COLUMN last_sampling_rate INTEGER;", "last_exempt_from_sampling", "ALTER TABLE events ADD COLUMN last_exempt_from_sampling INTEGER;" };
  private static final String[] zzahj = { "origin", "ALTER TABLE user_attributes ADD COLUMN origin TEXT;" };
  private static final String[] zzahk = { "app_version", "ALTER TABLE apps ADD COLUMN app_version TEXT;", "app_store", "ALTER TABLE apps ADD COLUMN app_store TEXT;", "gmp_version", "ALTER TABLE apps ADD COLUMN gmp_version INTEGER;", "dev_cert_hash", "ALTER TABLE apps ADD COLUMN dev_cert_hash INTEGER;", "measurement_enabled", "ALTER TABLE apps ADD COLUMN measurement_enabled INTEGER;", "last_bundle_start_timestamp", "ALTER TABLE apps ADD COLUMN last_bundle_start_timestamp INTEGER;", "day", "ALTER TABLE apps ADD COLUMN day INTEGER;", "daily_public_events_count", "ALTER TABLE apps ADD COLUMN daily_public_events_count INTEGER;", "daily_events_count", "ALTER TABLE apps ADD COLUMN daily_events_count INTEGER;", "daily_conversions_count", "ALTER TABLE apps ADD COLUMN daily_conversions_count INTEGER;", "remote_config", "ALTER TABLE apps ADD COLUMN remote_config BLOB;", "config_fetched_time", "ALTER TABLE apps ADD COLUMN config_fetched_time INTEGER;", "failed_config_fetch_time", "ALTER TABLE apps ADD COLUMN failed_config_fetch_time INTEGER;", "app_version_int", "ALTER TABLE apps ADD COLUMN app_version_int INTEGER;", "firebase_instance_id", "ALTER TABLE apps ADD COLUMN firebase_instance_id TEXT;", "daily_error_events_count", "ALTER TABLE apps ADD COLUMN daily_error_events_count INTEGER;", "daily_realtime_events_count", "ALTER TABLE apps ADD COLUMN daily_realtime_events_count INTEGER;", "health_monitor_sample", "ALTER TABLE apps ADD COLUMN health_monitor_sample TEXT;", "android_id", "ALTER TABLE apps ADD COLUMN android_id INTEGER;", "adid_reporting_enabled", "ALTER TABLE apps ADD COLUMN adid_reporting_enabled INTEGER;", "ssaid_reporting_enabled", "ALTER TABLE apps ADD COLUMN ssaid_reporting_enabled INTEGER;", "admob_app_id", "ALTER TABLE apps ADD COLUMN admob_app_id TEXT;", "linked_admob_app_id", "ALTER TABLE apps ADD COLUMN linked_admob_app_id TEXT;" };
  private static final String[] zzahl = { "realtime", "ALTER TABLE raw_events ADD COLUMN realtime INTEGER;" };
  private static final String[] zzahm = { "has_realtime", "ALTER TABLE queue ADD COLUMN has_realtime INTEGER;", "retry_count", "ALTER TABLE queue ADD COLUMN retry_count INTEGER;" };
  private static final String[] zzahn = { "previous_install_count", "ALTER TABLE app2 ADD COLUMN previous_install_count INTEGER;" };
  private final zzt zzaho = new zzt(this, getContext(), "google_app_measurement.db");
  private final zzev zzahp = new zzev(zzbx());
  
  zzq(zzfa paramZzfa)
  {
    super(paramZzfa);
  }
  
  /* Error */
  @WorkerThread
  private final long zza(String paramString, String[] paramArrayOfString)
  {
    // Byte code:
    //   0: aload_0
    //   1: invokevirtual 203	com/google/android/gms/measurement/internal/zzq:getWritableDatabase	()Landroid/database/sqlite/SQLiteDatabase;
    //   4: astore 7
    //   6: aconst_null
    //   7: astore 6
    //   9: aconst_null
    //   10: astore 5
    //   12: aload 7
    //   14: aload_1
    //   15: aload_2
    //   16: invokevirtual 209	android/database/sqlite/SQLiteDatabase:rawQuery	(Ljava/lang/String;[Ljava/lang/String;)Landroid/database/Cursor;
    //   19: astore_2
    //   20: aload_2
    //   21: invokeinterface 215 1 0
    //   26: ifeq +23 -> 49
    //   29: aload_2
    //   30: iconst_0
    //   31: invokeinterface 219 2 0
    //   36: lstore_3
    //   37: aload_2
    //   38: ifnull +9 -> 47
    //   41: aload_2
    //   42: invokeinterface 222 1 0
    //   47: lload_3
    //   48: lreturn
    //   49: new 199	android/database/sqlite/SQLiteException
    //   52: dup
    //   53: ldc -32
    //   55: invokespecial 227	android/database/sqlite/SQLiteException:<init>	(Ljava/lang/String;)V
    //   58: athrow
    //   59: astore_1
    //   60: goto +48 -> 108
    //   63: astore 6
    //   65: goto +19 -> 84
    //   68: astore_1
    //   69: aload 5
    //   71: astore_2
    //   72: goto +36 -> 108
    //   75: astore 5
    //   77: aload 6
    //   79: astore_2
    //   80: aload 5
    //   82: astore 6
    //   84: aload_2
    //   85: astore 5
    //   87: aload_0
    //   88: invokevirtual 231	com/google/android/gms/measurement/internal/zzco:zzgo	()Lcom/google/android/gms/measurement/internal/zzap;
    //   91: invokevirtual 237	com/google/android/gms/measurement/internal/zzap:zzjd	()Lcom/google/android/gms/measurement/internal/zzar;
    //   94: ldc -17
    //   96: aload_1
    //   97: aload 6
    //   99: invokevirtual 245	com/google/android/gms/measurement/internal/zzar:zze	(Ljava/lang/String;Ljava/lang/Object;Ljava/lang/Object;)V
    //   102: aload_2
    //   103: astore 5
    //   105: aload 6
    //   107: athrow
    //   108: aload_2
    //   109: ifnull +9 -> 118
    //   112: aload_2
    //   113: invokeinterface 222 1 0
    //   118: aload_1
    //   119: athrow
    // Local variable table:
    //   start	length	slot	name	signature
    //   0	120	0	this	zzq
    //   0	120	1	paramString	String
    //   0	120	2	paramArrayOfString	String[]
    //   36	12	3	l	long
    //   10	60	5	localObject1	Object
    //   75	6	5	localSQLiteException1	SQLiteException
    //   85	19	5	arrayOfString	String[]
    //   7	1	6	localObject2	Object
    //   63	15	6	localSQLiteException2	SQLiteException
    //   82	24	6	localObject3	Object
    //   4	9	7	localSQLiteDatabase	SQLiteDatabase
    // Exception table:
    //   from	to	target	type
    //   20	37	59	finally
    //   49	59	59	finally
    //   20	37	63	android/database/sqlite/SQLiteException
    //   49	59	63	android/database/sqlite/SQLiteException
    //   12	20	68	finally
    //   87	102	68	finally
    //   105	108	68	finally
    //   12	20	75	android/database/sqlite/SQLiteException
  }
  
  /* Error */
  @WorkerThread
  private final long zza(String paramString, String[] paramArrayOfString, long paramLong)
  {
    // Byte code:
    //   0: aload_0
    //   1: invokevirtual 203	com/google/android/gms/measurement/internal/zzq:getWritableDatabase	()Landroid/database/sqlite/SQLiteDatabase;
    //   4: astore 6
    //   6: aconst_null
    //   7: astore 7
    //   9: aconst_null
    //   10: astore 5
    //   12: aload 6
    //   14: aload_1
    //   15: aload_2
    //   16: invokevirtual 209	android/database/sqlite/SQLiteDatabase:rawQuery	(Ljava/lang/String;[Ljava/lang/String;)Landroid/database/Cursor;
    //   19: astore_2
    //   20: aload_2
    //   21: invokeinterface 215 1 0
    //   26: ifeq +23 -> 49
    //   29: aload_2
    //   30: iconst_0
    //   31: invokeinterface 219 2 0
    //   36: lstore_3
    //   37: aload_2
    //   38: ifnull +9 -> 47
    //   41: aload_2
    //   42: invokeinterface 222 1 0
    //   47: lload_3
    //   48: lreturn
    //   49: aload_2
    //   50: ifnull +9 -> 59
    //   53: aload_2
    //   54: invokeinterface 222 1 0
    //   59: lload_3
    //   60: lreturn
    //   61: astore_1
    //   62: aload_2
    //   63: astore 5
    //   65: goto +41 -> 106
    //   68: astore 6
    //   70: goto +12 -> 82
    //   73: astore_1
    //   74: goto +32 -> 106
    //   77: astore 6
    //   79: aload 7
    //   81: astore_2
    //   82: aload_2
    //   83: astore 5
    //   85: aload_0
    //   86: invokevirtual 231	com/google/android/gms/measurement/internal/zzco:zzgo	()Lcom/google/android/gms/measurement/internal/zzap;
    //   89: invokevirtual 237	com/google/android/gms/measurement/internal/zzap:zzjd	()Lcom/google/android/gms/measurement/internal/zzar;
    //   92: ldc -17
    //   94: aload_1
    //   95: aload 6
    //   97: invokevirtual 245	com/google/android/gms/measurement/internal/zzar:zze	(Ljava/lang/String;Ljava/lang/Object;Ljava/lang/Object;)V
    //   100: aload_2
    //   101: astore 5
    //   103: aload 6
    //   105: athrow
    //   106: aload 5
    //   108: ifnull +10 -> 118
    //   111: aload 5
    //   113: invokeinterface 222 1 0
    //   118: aload_1
    //   119: athrow
    // Local variable table:
    //   start	length	slot	name	signature
    //   0	120	0	this	zzq
    //   0	120	1	paramString	String
    //   0	120	2	paramArrayOfString	String[]
    //   0	120	3	paramLong	long
    //   10	102	5	arrayOfString	String[]
    //   4	9	6	localSQLiteDatabase	SQLiteDatabase
    //   68	1	6	localSQLiteException1	SQLiteException
    //   77	27	6	localSQLiteException2	SQLiteException
    //   7	73	7	localObject	Object
    // Exception table:
    //   from	to	target	type
    //   20	37	61	finally
    //   20	37	68	android/database/sqlite/SQLiteException
    //   12	20	73	finally
    //   85	100	73	finally
    //   103	106	73	finally
    //   12	20	77	android/database/sqlite/SQLiteException
  }
  
  @WorkerThread
  @VisibleForTesting
  private final Object zza(Cursor paramCursor, int paramInt)
  {
    int i = paramCursor.getType(paramInt);
    switch (i)
    {
    default: 
      zzgo().zzjd().zzg("Loaded invalid unknown value type, ignoring it", Integer.valueOf(i));
      return null;
    case 4: 
      zzgo().zzjd().zzbx("Loaded invalid blob type value, ignoring it");
      return null;
    case 3: 
      return paramCursor.getString(paramInt);
    case 2: 
      return Double.valueOf(paramCursor.getDouble(paramInt));
    case 1: 
      return Long.valueOf(paramCursor.getLong(paramInt));
    }
    zzgo().zzjd().zzbx("Loaded invalid null value from database");
    return null;
  }
  
  @WorkerThread
  private static void zza(ContentValues paramContentValues, String paramString, Object paramObject)
  {
    Preconditions.checkNotEmpty(paramString);
    Preconditions.checkNotNull(paramObject);
    if ((paramObject instanceof String))
    {
      paramContentValues.put(paramString, (String)paramObject);
      return;
    }
    if ((paramObject instanceof Long))
    {
      paramContentValues.put(paramString, (Long)paramObject);
      return;
    }
    if ((paramObject instanceof Double))
    {
      paramContentValues.put(paramString, (Double)paramObject);
      return;
    }
    throw new IllegalArgumentException("Invalid value type");
  }
  
  @WorkerThread
  private final boolean zza(String paramString, int paramInt, zzfv paramZzfv)
  {
    zzcl();
    zzaf();
    Preconditions.checkNotEmpty(paramString);
    Preconditions.checkNotNull(paramZzfv);
    if (TextUtils.isEmpty(zzavf))
    {
      zzgo().zzjg().zzd("Event filter had no event name. Audience definition ignored. appId, audienceId, filterId", zzap.zzbv(paramString), Integer.valueOf(paramInt), String.valueOf(zzave));
      return false;
    }
    try
    {
      byte[] arrayOfByte = new byte[paramZzfv.zzvu()];
      Object localObject = zzyy.zzk(arrayOfByte, 0, arrayOfByte.length);
      paramZzfv.zza((zzyy)localObject);
      ((zzyy)localObject).zzyt();
      localObject = new ContentValues();
      ((ContentValues)localObject).put("app_id", paramString);
      ((ContentValues)localObject).put("audience_id", Integer.valueOf(paramInt));
      ((ContentValues)localObject).put("filter_id", zzave);
      ((ContentValues)localObject).put("event_name", zzavf);
      ((ContentValues)localObject).put("data", arrayOfByte);
      try
      {
        if (getWritableDatabase().insertWithOnConflict("event_filters", null, (ContentValues)localObject, 5) == -1L) {
          zzgo().zzjd().zzg("Failed to insert event filter (got -1). appId", zzap.zzbv(paramString));
        }
        return true;
      }
      catch (SQLiteException paramZzfv)
      {
        zzgo().zzjd().zze("Error storing event filter. appId", zzap.zzbv(paramString), paramZzfv);
        return false;
      }
      return false;
    }
    catch (IOException paramZzfv)
    {
      zzgo().zzjd().zze("Configuration loss. Failed to serialize event filter. appId", zzap.zzbv(paramString), paramZzfv);
    }
  }
  
  @WorkerThread
  private final boolean zza(String paramString, int paramInt, zzfy paramZzfy)
  {
    zzcl();
    zzaf();
    Preconditions.checkNotEmpty(paramString);
    Preconditions.checkNotNull(paramZzfy);
    if (TextUtils.isEmpty(zzavu))
    {
      zzgo().zzjg().zzd("Property filter had no property name. Audience definition ignored. appId, audienceId, filterId", zzap.zzbv(paramString), Integer.valueOf(paramInt), String.valueOf(zzave));
      return false;
    }
    try
    {
      byte[] arrayOfByte = new byte[paramZzfy.zzvu()];
      Object localObject = zzyy.zzk(arrayOfByte, 0, arrayOfByte.length);
      paramZzfy.zza((zzyy)localObject);
      ((zzyy)localObject).zzyt();
      localObject = new ContentValues();
      ((ContentValues)localObject).put("app_id", paramString);
      ((ContentValues)localObject).put("audience_id", Integer.valueOf(paramInt));
      ((ContentValues)localObject).put("filter_id", zzave);
      ((ContentValues)localObject).put("property_name", zzavu);
      ((ContentValues)localObject).put("data", arrayOfByte);
      try
      {
        if (getWritableDatabase().insertWithOnConflict("property_filters", null, (ContentValues)localObject, 5) == -1L)
        {
          zzgo().zzjd().zzg("Failed to insert property filter (got -1). appId", zzap.zzbv(paramString));
          return false;
        }
        return true;
      }
      catch (SQLiteException paramZzfy)
      {
        zzgo().zzjd().zze("Error storing property filter. appId", zzap.zzbv(paramString), paramZzfy);
        return false;
      }
      return false;
    }
    catch (IOException paramZzfy)
    {
      zzgo().zzjd().zze("Configuration loss. Failed to serialize property filter. appId", zzap.zzbv(paramString), paramZzfy);
    }
  }
  
  private final boolean zza(String paramString, List<Integer> paramList)
  {
    Preconditions.checkNotEmpty(paramString);
    zzcl();
    zzaf();
    SQLiteDatabase localSQLiteDatabase = getWritableDatabase();
    try
    {
      long l = zza("select count(1) from audience_filter_values where app_id=?", new String[] { paramString });
      int j = Math.max(0, Math.min(2000, zzgq().zzb(paramString, zzaf.zzaki)));
      if (l <= j) {
        return false;
      }
      Object localObject = new ArrayList();
      int i = 0;
      while (i < paramList.size())
      {
        Integer localInteger = (Integer)paramList.get(i);
        if (localInteger != null)
        {
          if (!(localInteger instanceof Integer)) {
            return false;
          }
          ((List)localObject).add(Integer.toString(localInteger.intValue()));
          i += 1;
        }
        else
        {
          return false;
        }
      }
      paramList = TextUtils.join(",", (Iterable)localObject);
      localObject = new StringBuilder(String.valueOf(paramList).length() + 2);
      ((StringBuilder)localObject).append("(");
      ((StringBuilder)localObject).append(paramList);
      ((StringBuilder)localObject).append(")");
      paramList = ((StringBuilder)localObject).toString();
      localObject = new StringBuilder(String.valueOf(paramList).length() + 140);
      ((StringBuilder)localObject).append("audience_id in (select audience_id from audience_filter_values where app_id=? and audience_id not in ");
      ((StringBuilder)localObject).append(paramList);
      ((StringBuilder)localObject).append(" order by rowid desc limit -1 offset ?)");
      return localSQLiteDatabase.delete("audience_filter_values", ((StringBuilder)localObject).toString(), new String[] { paramString, Integer.toString(j) }) > 0;
    }
    catch (SQLiteException paramList)
    {
      zzgo().zzjd().zze("Database error querying filters. appId", zzap.zzbv(paramString), paramList);
    }
    return false;
  }
  
  private final boolean zzil()
  {
    return getContext().getDatabasePath("google_app_measurement.db").exists();
  }
  
  @WorkerThread
  public final void beginTransaction()
  {
    zzcl();
    getWritableDatabase().beginTransaction();
  }
  
  @WorkerThread
  public final void endTransaction()
  {
    zzcl();
    getWritableDatabase().endTransaction();
  }
  
  @WorkerThread
  @VisibleForTesting
  final SQLiteDatabase getWritableDatabase()
  {
    zzaf();
    try
    {
      SQLiteDatabase localSQLiteDatabase = zzaho.getWritableDatabase();
      return localSQLiteDatabase;
    }
    catch (SQLiteException localSQLiteException)
    {
      zzgo().zzjg().zzg("Error opening database", localSQLiteException);
      throw localSQLiteException;
    }
  }
  
  @WorkerThread
  public final void setTransactionSuccessful()
  {
    zzcl();
    getWritableDatabase().setTransactionSuccessful();
  }
  
  /* Error */
  public final long zza(zzgi paramZzgi)
    throws IOException
  {
    // Byte code:
    //   0: aload_0
    //   1: invokevirtual 327	com/google/android/gms/measurement/internal/zzco:zzaf	()V
    //   4: aload_0
    //   5: invokevirtual 324	com/google/android/gms/measurement/internal/zzez:zzcl	()V
    //   8: aload_1
    //   9: invokestatic 301	com/google/android/gms/common/internal/Preconditions:checkNotNull	(Ljava/lang/Object;)Ljava/lang/Object;
    //   12: pop
    //   13: aload_1
    //   14: getfield 556	com/google/android/gms/internal/measurement/zzgi:zztt	Ljava/lang/String;
    //   17: invokestatic 297	com/google/android/gms/common/internal/Preconditions:checkNotEmpty	(Ljava/lang/String;)Ljava/lang/String;
    //   20: pop
    //   21: aload_1
    //   22: invokevirtual 365	com/google/android/gms/internal/measurement/zzzg:zzvu	()I
    //   25: newarray byte
    //   27: astore 4
    //   29: aload 4
    //   31: iconst_0
    //   32: aload 4
    //   34: arraylength
    //   35: invokestatic 371	com/google/android/gms/internal/measurement/zzyy:zzk	([BII)Lcom/google/android/gms/internal/measurement/zzyy;
    //   38: astore 5
    //   40: aload_1
    //   41: aload 5
    //   43: invokevirtual 374	com/google/android/gms/internal/measurement/zzzg:zza	(Lcom/google/android/gms/internal/measurement/zzyy;)V
    //   46: aload 5
    //   48: invokevirtual 377	com/google/android/gms/internal/measurement/zzyy:zzyt	()V
    //   51: aload_0
    //   52: invokevirtual 562	com/google/android/gms/measurement/internal/zzey:zzjo	()Lcom/google/android/gms/measurement/internal/zzfg;
    //   55: astore 5
    //   57: aload 4
    //   59: invokestatic 301	com/google/android/gms/common/internal/Preconditions:checkNotNull	(Ljava/lang/Object;)Ljava/lang/Object;
    //   62: pop
    //   63: aload 5
    //   65: invokevirtual 566	com/google/android/gms/measurement/internal/zzco:zzgm	()Lcom/google/android/gms/measurement/internal/zzfk;
    //   68: invokevirtual 327	com/google/android/gms/measurement/internal/zzco:zzaf	()V
    //   71: invokestatic 572	com/google/android/gms/measurement/internal/zzfk:getMessageDigest	()Ljava/security/MessageDigest;
    //   74: astore 6
    //   76: aload 6
    //   78: ifnonnull +22 -> 100
    //   81: aload 5
    //   83: invokevirtual 231	com/google/android/gms/measurement/internal/zzco:zzgo	()Lcom/google/android/gms/measurement/internal/zzap;
    //   86: invokevirtual 237	com/google/android/gms/measurement/internal/zzap:zzjd	()Lcom/google/android/gms/measurement/internal/zzar;
    //   89: ldc_w 574
    //   92: invokevirtual 270	com/google/android/gms/measurement/internal/zzar:zzbx	(Ljava/lang/String;)V
    //   95: lconst_0
    //   96: lstore_2
    //   97: goto +14 -> 111
    //   100: aload 6
    //   102: aload 4
    //   104: invokevirtual 580	java/security/MessageDigest:digest	([B)[B
    //   107: invokestatic 584	com/google/android/gms/measurement/internal/zzfk:zzc	([B)J
    //   110: lstore_2
    //   111: new 303	android/content/ContentValues
    //   114: dup
    //   115: invokespecial 379	android/content/ContentValues:<init>	()V
    //   118: astore 5
    //   120: aload 5
    //   122: ldc_w 381
    //   125: aload_1
    //   126: getfield 556	com/google/android/gms/internal/measurement/zzgi:zztt	Ljava/lang/String;
    //   129: invokevirtual 307	android/content/ContentValues:put	(Ljava/lang/String;Ljava/lang/String;)V
    //   132: aload 5
    //   134: ldc_w 586
    //   137: lload_2
    //   138: invokestatic 288	java/lang/Long:valueOf	(J)Ljava/lang/Long;
    //   141: invokevirtual 310	android/content/ContentValues:put	(Ljava/lang/String;Ljava/lang/Long;)V
    //   144: aload 5
    //   146: ldc_w 588
    //   149: aload 4
    //   151: invokevirtual 395	android/content/ContentValues:put	(Ljava/lang/String;[B)V
    //   154: aload_0
    //   155: invokevirtual 203	com/google/android/gms/measurement/internal/zzq:getWritableDatabase	()Landroid/database/sqlite/SQLiteDatabase;
    //   158: ldc_w 590
    //   161: aconst_null
    //   162: aload 5
    //   164: iconst_4
    //   165: invokevirtual 401	android/database/sqlite/SQLiteDatabase:insertWithOnConflict	(Ljava/lang/String;Ljava/lang/String;Landroid/content/ContentValues;I)J
    //   168: pop2
    //   169: lload_2
    //   170: lreturn
    //   171: astore 4
    //   173: aload_0
    //   174: invokevirtual 231	com/google/android/gms/measurement/internal/zzco:zzgo	()Lcom/google/android/gms/measurement/internal/zzap;
    //   177: invokevirtual 237	com/google/android/gms/measurement/internal/zzap:zzjd	()Lcom/google/android/gms/measurement/internal/zzar;
    //   180: ldc_w 592
    //   183: aload_1
    //   184: getfield 556	com/google/android/gms/internal/measurement/zzgi:zztt	Ljava/lang/String;
    //   187: invokestatic 348	com/google/android/gms/measurement/internal/zzap:zzbv	(Ljava/lang/String;)Ljava/lang/Object;
    //   190: aload 4
    //   192: invokevirtual 245	com/google/android/gms/measurement/internal/zzar:zze	(Ljava/lang/String;Ljava/lang/Object;Ljava/lang/Object;)V
    //   195: aload 4
    //   197: athrow
    //   198: astore 4
    //   200: aload_0
    //   201: invokevirtual 231	com/google/android/gms/measurement/internal/zzco:zzgo	()Lcom/google/android/gms/measurement/internal/zzap;
    //   204: invokevirtual 237	com/google/android/gms/measurement/internal/zzap:zzjd	()Lcom/google/android/gms/measurement/internal/zzar;
    //   207: ldc_w 594
    //   210: aload_1
    //   211: getfield 556	com/google/android/gms/internal/measurement/zzgi:zztt	Ljava/lang/String;
    //   214: invokestatic 348	com/google/android/gms/measurement/internal/zzap:zzbv	(Ljava/lang/String;)Ljava/lang/Object;
    //   217: aload 4
    //   219: invokevirtual 245	com/google/android/gms/measurement/internal/zzar:zze	(Ljava/lang/String;Ljava/lang/Object;Ljava/lang/Object;)V
    //   222: aload 4
    //   224: athrow
    // Local variable table:
    //   start	length	slot	name	signature
    //   0	225	0	this	zzq
    //   0	225	1	paramZzgi	zzgi
    //   96	74	2	l	long
    //   27	123	4	arrayOfByte	byte[]
    //   171	25	4	localSQLiteException	SQLiteException
    //   198	25	4	localIOException	IOException
    //   38	125	5	localObject	Object
    //   74	27	6	localMessageDigest	java.security.MessageDigest
    // Exception table:
    //   from	to	target	type
    //   154	169	171	android/database/sqlite/SQLiteException
    //   21	51	198	java/io/IOException
  }
  
  /* Error */
  public final android.util.Pair<zzgf, Long> zza(String paramString, Long paramLong)
  {
    // Byte code:
    //   0: aload_0
    //   1: invokevirtual 327	com/google/android/gms/measurement/internal/zzco:zzaf	()V
    //   4: aload_0
    //   5: invokevirtual 324	com/google/android/gms/measurement/internal/zzez:zzcl	()V
    //   8: aload_0
    //   9: invokevirtual 203	com/google/android/gms/measurement/internal/zzq:getWritableDatabase	()Landroid/database/sqlite/SQLiteDatabase;
    //   12: ldc_w 598
    //   15: iconst_2
    //   16: anewarray 19	java/lang/String
    //   19: dup
    //   20: iconst_0
    //   21: aload_1
    //   22: aastore
    //   23: dup
    //   24: iconst_1
    //   25: aload_2
    //   26: invokestatic 355	java/lang/String:valueOf	(Ljava/lang/Object;)Ljava/lang/String;
    //   29: aastore
    //   30: invokevirtual 209	android/database/sqlite/SQLiteDatabase:rawQuery	(Ljava/lang/String;[Ljava/lang/String;)Landroid/database/Cursor;
    //   33: astore 6
    //   35: aload 6
    //   37: astore 5
    //   39: aload 6
    //   41: invokeinterface 215 1 0
    //   46: ifne +34 -> 80
    //   49: aload 6
    //   51: astore 5
    //   53: aload_0
    //   54: invokevirtual 231	com/google/android/gms/measurement/internal/zzco:zzgo	()Lcom/google/android/gms/measurement/internal/zzap;
    //   57: invokevirtual 601	com/google/android/gms/measurement/internal/zzap:zzjl	()Lcom/google/android/gms/measurement/internal/zzar;
    //   60: ldc_w 603
    //   63: invokevirtual 270	com/google/android/gms/measurement/internal/zzar:zzbx	(Ljava/lang/String;)V
    //   66: aload 6
    //   68: ifnull +10 -> 78
    //   71: aload 6
    //   73: invokeinterface 222 1 0
    //   78: aconst_null
    //   79: areturn
    //   80: aload 6
    //   82: astore 5
    //   84: aload 6
    //   86: iconst_0
    //   87: invokeinterface 607 2 0
    //   92: astore 7
    //   94: aload 6
    //   96: astore 5
    //   98: aload 6
    //   100: iconst_1
    //   101: invokeinterface 219 2 0
    //   106: lstore_3
    //   107: aload 6
    //   109: astore 5
    //   111: aload 7
    //   113: iconst_0
    //   114: aload 7
    //   116: arraylength
    //   117: invokestatic 613	com/google/android/gms/internal/measurement/zzyx:zzj	([BII)Lcom/google/android/gms/internal/measurement/zzyx;
    //   120: astore 7
    //   122: aload 6
    //   124: astore 5
    //   126: new 615	com/google/android/gms/internal/measurement/zzgf
    //   129: dup
    //   130: invokespecial 616	com/google/android/gms/internal/measurement/zzgf:<init>	()V
    //   133: astore 8
    //   135: aload 6
    //   137: astore 5
    //   139: aload 8
    //   141: aload 7
    //   143: invokevirtual 619	com/google/android/gms/internal/measurement/zzzg:zza	(Lcom/google/android/gms/internal/measurement/zzyx;)Lcom/google/android/gms/internal/measurement/zzzg;
    //   146: pop
    //   147: aload 6
    //   149: astore 5
    //   151: aload 8
    //   153: lload_3
    //   154: invokestatic 288	java/lang/Long:valueOf	(J)Ljava/lang/Long;
    //   157: invokestatic 625	android/util/Pair:create	(Ljava/lang/Object;Ljava/lang/Object;)Landroid/util/Pair;
    //   160: astore_1
    //   161: aload 6
    //   163: ifnull +10 -> 173
    //   166: aload 6
    //   168: invokeinterface 222 1 0
    //   173: aload_1
    //   174: areturn
    //   175: astore 7
    //   177: aload 6
    //   179: astore 5
    //   181: aload_0
    //   182: invokevirtual 231	com/google/android/gms/measurement/internal/zzco:zzgo	()Lcom/google/android/gms/measurement/internal/zzap;
    //   185: invokevirtual 237	com/google/android/gms/measurement/internal/zzap:zzjd	()Lcom/google/android/gms/measurement/internal/zzar;
    //   188: ldc_w 627
    //   191: aload_1
    //   192: invokestatic 348	com/google/android/gms/measurement/internal/zzap:zzbv	(Ljava/lang/String;)Ljava/lang/Object;
    //   195: aload_2
    //   196: aload 7
    //   198: invokevirtual 359	com/google/android/gms/measurement/internal/zzar:zzd	(Ljava/lang/String;Ljava/lang/Object;Ljava/lang/Object;Ljava/lang/Object;)V
    //   201: aload 6
    //   203: ifnull +10 -> 213
    //   206: aload 6
    //   208: invokeinterface 222 1 0
    //   213: aconst_null
    //   214: areturn
    //   215: astore_2
    //   216: aload 6
    //   218: astore_1
    //   219: goto +13 -> 232
    //   222: astore_1
    //   223: aconst_null
    //   224: astore 5
    //   226: goto +36 -> 262
    //   229: astore_2
    //   230: aconst_null
    //   231: astore_1
    //   232: aload_1
    //   233: astore 5
    //   235: aload_0
    //   236: invokevirtual 231	com/google/android/gms/measurement/internal/zzco:zzgo	()Lcom/google/android/gms/measurement/internal/zzap;
    //   239: invokevirtual 237	com/google/android/gms/measurement/internal/zzap:zzjd	()Lcom/google/android/gms/measurement/internal/zzar;
    //   242: ldc_w 629
    //   245: aload_2
    //   246: invokevirtual 266	com/google/android/gms/measurement/internal/zzar:zzg	(Ljava/lang/String;Ljava/lang/Object;)V
    //   249: aload_1
    //   250: ifnull +9 -> 259
    //   253: aload_1
    //   254: invokeinterface 222 1 0
    //   259: aconst_null
    //   260: areturn
    //   261: astore_1
    //   262: aload 5
    //   264: ifnull +10 -> 274
    //   267: aload 5
    //   269: invokeinterface 222 1 0
    //   274: aload_1
    //   275: athrow
    // Local variable table:
    //   start	length	slot	name	signature
    //   0	276	0	this	zzq
    //   0	276	1	paramString	String
    //   0	276	2	paramLong	Long
    //   106	48	3	l	long
    //   37	231	5	localObject1	Object
    //   33	184	6	localCursor	Cursor
    //   92	50	7	localObject2	Object
    //   175	22	7	localIOException	IOException
    //   133	19	8	localZzgf	zzgf
    // Exception table:
    //   from	to	target	type
    //   139	147	175	java/io/IOException
    //   39	49	215	android/database/sqlite/SQLiteException
    //   53	66	215	android/database/sqlite/SQLiteException
    //   84	94	215	android/database/sqlite/SQLiteException
    //   98	107	215	android/database/sqlite/SQLiteException
    //   111	122	215	android/database/sqlite/SQLiteException
    //   126	135	215	android/database/sqlite/SQLiteException
    //   139	147	215	android/database/sqlite/SQLiteException
    //   151	161	215	android/database/sqlite/SQLiteException
    //   181	201	215	android/database/sqlite/SQLiteException
    //   8	35	222	finally
    //   8	35	229	android/database/sqlite/SQLiteException
    //   39	49	261	finally
    //   53	66	261	finally
    //   84	94	261	finally
    //   98	107	261	finally
    //   111	122	261	finally
    //   126	135	261	finally
    //   139	147	261	finally
    //   151	161	261	finally
    //   181	201	261	finally
    //   235	249	261	finally
  }
  
  /* Error */
  @WorkerThread
  public final zzr zza(long paramLong, String paramString, boolean paramBoolean1, boolean paramBoolean2, boolean paramBoolean3, boolean paramBoolean4, boolean paramBoolean5)
  {
    // Byte code:
    //   0: aload_3
    //   1: invokestatic 297	com/google/android/gms/common/internal/Preconditions:checkNotEmpty	(Ljava/lang/String;)Ljava/lang/String;
    //   4: pop
    //   5: aload_0
    //   6: invokevirtual 327	com/google/android/gms/measurement/internal/zzco:zzaf	()V
    //   9: aload_0
    //   10: invokevirtual 324	com/google/android/gms/measurement/internal/zzez:zzcl	()V
    //   13: new 633	com/google/android/gms/measurement/internal/zzr
    //   16: dup
    //   17: invokespecial 634	com/google/android/gms/measurement/internal/zzr:<init>	()V
    //   20: astore 11
    //   22: aload_0
    //   23: invokevirtual 203	com/google/android/gms/measurement/internal/zzq:getWritableDatabase	()Landroid/database/sqlite/SQLiteDatabase;
    //   26: astore 10
    //   28: aload 10
    //   30: ldc_w 636
    //   33: bipush 6
    //   35: anewarray 19	java/lang/String
    //   38: dup
    //   39: iconst_0
    //   40: ldc 73
    //   42: aastore
    //   43: dup
    //   44: iconst_1
    //   45: ldc 81
    //   47: aastore
    //   48: dup
    //   49: iconst_2
    //   50: ldc 77
    //   52: aastore
    //   53: dup
    //   54: iconst_3
    //   55: ldc 85
    //   57: aastore
    //   58: dup
    //   59: iconst_4
    //   60: ldc 109
    //   62: aastore
    //   63: dup
    //   64: iconst_5
    //   65: ldc 113
    //   67: aastore
    //   68: ldc_w 638
    //   71: iconst_1
    //   72: anewarray 19	java/lang/String
    //   75: dup
    //   76: iconst_0
    //   77: aload_3
    //   78: aastore
    //   79: aconst_null
    //   80: aconst_null
    //   81: aconst_null
    //   82: invokevirtual 642	android/database/sqlite/SQLiteDatabase:query	(Ljava/lang/String;[Ljava/lang/String;Ljava/lang/String;[Ljava/lang/String;Ljava/lang/String;Ljava/lang/String;Ljava/lang/String;)Landroid/database/Cursor;
    //   85: astore 9
    //   87: aload 9
    //   89: invokeinterface 215 1 0
    //   94: ifne +35 -> 129
    //   97: aload_0
    //   98: invokevirtual 231	com/google/android/gms/measurement/internal/zzco:zzgo	()Lcom/google/android/gms/measurement/internal/zzap;
    //   101: invokevirtual 342	com/google/android/gms/measurement/internal/zzap:zzjg	()Lcom/google/android/gms/measurement/internal/zzar;
    //   104: ldc_w 644
    //   107: aload_3
    //   108: invokestatic 348	com/google/android/gms/measurement/internal/zzap:zzbv	(Ljava/lang/String;)Ljava/lang/Object;
    //   111: invokevirtual 266	com/google/android/gms/measurement/internal/zzar:zzg	(Ljava/lang/String;Ljava/lang/Object;)V
    //   114: aload 9
    //   116: ifnull +10 -> 126
    //   119: aload 9
    //   121: invokeinterface 222 1 0
    //   126: aload 11
    //   128: areturn
    //   129: aload 9
    //   131: iconst_0
    //   132: invokeinterface 219 2 0
    //   137: lload_1
    //   138: lcmp
    //   139: ifne +68 -> 207
    //   142: aload 11
    //   144: aload 9
    //   146: iconst_1
    //   147: invokeinterface 219 2 0
    //   152: putfield 648	com/google/android/gms/measurement/internal/zzr:zzahr	J
    //   155: aload 11
    //   157: aload 9
    //   159: iconst_2
    //   160: invokeinterface 219 2 0
    //   165: putfield 651	com/google/android/gms/measurement/internal/zzr:zzahq	J
    //   168: aload 11
    //   170: aload 9
    //   172: iconst_3
    //   173: invokeinterface 219 2 0
    //   178: putfield 654	com/google/android/gms/measurement/internal/zzr:zzahs	J
    //   181: aload 11
    //   183: aload 9
    //   185: iconst_4
    //   186: invokeinterface 219 2 0
    //   191: putfield 657	com/google/android/gms/measurement/internal/zzr:zzaht	J
    //   194: aload 11
    //   196: aload 9
    //   198: iconst_5
    //   199: invokeinterface 219 2 0
    //   204: putfield 660	com/google/android/gms/measurement/internal/zzr:zzahu	J
    //   207: iload 4
    //   209: ifeq +15 -> 224
    //   212: aload 11
    //   214: aload 11
    //   216: getfield 648	com/google/android/gms/measurement/internal/zzr:zzahr	J
    //   219: lconst_1
    //   220: ladd
    //   221: putfield 648	com/google/android/gms/measurement/internal/zzr:zzahr	J
    //   224: iload 5
    //   226: ifeq +15 -> 241
    //   229: aload 11
    //   231: aload 11
    //   233: getfield 651	com/google/android/gms/measurement/internal/zzr:zzahq	J
    //   236: lconst_1
    //   237: ladd
    //   238: putfield 651	com/google/android/gms/measurement/internal/zzr:zzahq	J
    //   241: iload 6
    //   243: ifeq +15 -> 258
    //   246: aload 11
    //   248: aload 11
    //   250: getfield 654	com/google/android/gms/measurement/internal/zzr:zzahs	J
    //   253: lconst_1
    //   254: ladd
    //   255: putfield 654	com/google/android/gms/measurement/internal/zzr:zzahs	J
    //   258: iload 7
    //   260: ifeq +15 -> 275
    //   263: aload 11
    //   265: aload 11
    //   267: getfield 657	com/google/android/gms/measurement/internal/zzr:zzaht	J
    //   270: lconst_1
    //   271: ladd
    //   272: putfield 657	com/google/android/gms/measurement/internal/zzr:zzaht	J
    //   275: iload 8
    //   277: ifeq +15 -> 292
    //   280: aload 11
    //   282: aload 11
    //   284: getfield 660	com/google/android/gms/measurement/internal/zzr:zzahu	J
    //   287: lconst_1
    //   288: ladd
    //   289: putfield 660	com/google/android/gms/measurement/internal/zzr:zzahu	J
    //   292: new 303	android/content/ContentValues
    //   295: dup
    //   296: invokespecial 379	android/content/ContentValues:<init>	()V
    //   299: astore 12
    //   301: aload 12
    //   303: ldc 73
    //   305: lload_1
    //   306: invokestatic 288	java/lang/Long:valueOf	(J)Ljava/lang/Long;
    //   309: invokevirtual 310	android/content/ContentValues:put	(Ljava/lang/String;Ljava/lang/Long;)V
    //   312: aload 12
    //   314: ldc 77
    //   316: aload 11
    //   318: getfield 651	com/google/android/gms/measurement/internal/zzr:zzahq	J
    //   321: invokestatic 288	java/lang/Long:valueOf	(J)Ljava/lang/Long;
    //   324: invokevirtual 310	android/content/ContentValues:put	(Ljava/lang/String;Ljava/lang/Long;)V
    //   327: aload 12
    //   329: ldc 81
    //   331: aload 11
    //   333: getfield 648	com/google/android/gms/measurement/internal/zzr:zzahr	J
    //   336: invokestatic 288	java/lang/Long:valueOf	(J)Ljava/lang/Long;
    //   339: invokevirtual 310	android/content/ContentValues:put	(Ljava/lang/String;Ljava/lang/Long;)V
    //   342: aload 12
    //   344: ldc 85
    //   346: aload 11
    //   348: getfield 654	com/google/android/gms/measurement/internal/zzr:zzahs	J
    //   351: invokestatic 288	java/lang/Long:valueOf	(J)Ljava/lang/Long;
    //   354: invokevirtual 310	android/content/ContentValues:put	(Ljava/lang/String;Ljava/lang/Long;)V
    //   357: aload 12
    //   359: ldc 109
    //   361: aload 11
    //   363: getfield 657	com/google/android/gms/measurement/internal/zzr:zzaht	J
    //   366: invokestatic 288	java/lang/Long:valueOf	(J)Ljava/lang/Long;
    //   369: invokevirtual 310	android/content/ContentValues:put	(Ljava/lang/String;Ljava/lang/Long;)V
    //   372: aload 12
    //   374: ldc 113
    //   376: aload 11
    //   378: getfield 660	com/google/android/gms/measurement/internal/zzr:zzahu	J
    //   381: invokestatic 288	java/lang/Long:valueOf	(J)Ljava/lang/Long;
    //   384: invokevirtual 310	android/content/ContentValues:put	(Ljava/lang/String;Ljava/lang/Long;)V
    //   387: aload 10
    //   389: ldc_w 636
    //   392: aload 12
    //   394: ldc_w 638
    //   397: iconst_1
    //   398: anewarray 19	java/lang/String
    //   401: dup
    //   402: iconst_0
    //   403: aload_3
    //   404: aastore
    //   405: invokevirtual 664	android/database/sqlite/SQLiteDatabase:update	(Ljava/lang/String;Landroid/content/ContentValues;Ljava/lang/String;[Ljava/lang/String;)I
    //   408: pop
    //   409: aload 9
    //   411: ifnull +10 -> 421
    //   414: aload 9
    //   416: invokeinterface 222 1 0
    //   421: aload 11
    //   423: areturn
    //   424: astore_3
    //   425: goto +55 -> 480
    //   428: astore 10
    //   430: goto +15 -> 445
    //   433: astore_3
    //   434: aconst_null
    //   435: astore 9
    //   437: goto +43 -> 480
    //   440: astore 10
    //   442: aconst_null
    //   443: astore 9
    //   445: aload_0
    //   446: invokevirtual 231	com/google/android/gms/measurement/internal/zzco:zzgo	()Lcom/google/android/gms/measurement/internal/zzap;
    //   449: invokevirtual 237	com/google/android/gms/measurement/internal/zzap:zzjd	()Lcom/google/android/gms/measurement/internal/zzar;
    //   452: ldc_w 666
    //   455: aload_3
    //   456: invokestatic 348	com/google/android/gms/measurement/internal/zzap:zzbv	(Ljava/lang/String;)Ljava/lang/Object;
    //   459: aload 10
    //   461: invokevirtual 245	com/google/android/gms/measurement/internal/zzar:zze	(Ljava/lang/String;Ljava/lang/Object;Ljava/lang/Object;)V
    //   464: aload 9
    //   466: ifnull +10 -> 476
    //   469: aload 9
    //   471: invokeinterface 222 1 0
    //   476: aload 11
    //   478: areturn
    //   479: astore_3
    //   480: aload 9
    //   482: ifnull +10 -> 492
    //   485: aload 9
    //   487: invokeinterface 222 1 0
    //   492: aload_3
    //   493: athrow
    // Local variable table:
    //   start	length	slot	name	signature
    //   0	494	0	this	zzq
    //   0	494	1	paramLong	long
    //   0	494	3	paramString	String
    //   0	494	4	paramBoolean1	boolean
    //   0	494	5	paramBoolean2	boolean
    //   0	494	6	paramBoolean3	boolean
    //   0	494	7	paramBoolean4	boolean
    //   0	494	8	paramBoolean5	boolean
    //   85	401	9	localCursor	Cursor
    //   26	362	10	localSQLiteDatabase	SQLiteDatabase
    //   428	1	10	localSQLiteException1	SQLiteException
    //   440	20	10	localSQLiteException2	SQLiteException
    //   20	457	11	localZzr	zzr
    //   299	94	12	localContentValues	ContentValues
    // Exception table:
    //   from	to	target	type
    //   87	114	424	finally
    //   129	207	424	finally
    //   212	224	424	finally
    //   229	241	424	finally
    //   246	258	424	finally
    //   263	275	424	finally
    //   280	292	424	finally
    //   292	409	424	finally
    //   87	114	428	android/database/sqlite/SQLiteException
    //   129	207	428	android/database/sqlite/SQLiteException
    //   212	224	428	android/database/sqlite/SQLiteException
    //   229	241	428	android/database/sqlite/SQLiteException
    //   246	258	428	android/database/sqlite/SQLiteException
    //   263	275	428	android/database/sqlite/SQLiteException
    //   280	292	428	android/database/sqlite/SQLiteException
    //   292	409	428	android/database/sqlite/SQLiteException
    //   22	87	433	finally
    //   22	87	440	android/database/sqlite/SQLiteException
    //   445	464	479	finally
  }
  
  @WorkerThread
  public final void zza(zzg paramZzg)
  {
    Preconditions.checkNotNull(paramZzg);
    zzaf();
    zzcl();
    ContentValues localContentValues = new ContentValues();
    localContentValues.put("app_id", paramZzg.zzal());
    localContentValues.put("app_instance_id", paramZzg.getAppInstanceId());
    localContentValues.put("gmp_app_id", paramZzg.getGmpAppId());
    localContentValues.put("resettable_device_id_hash", paramZzg.zzgx());
    localContentValues.put("last_bundle_index", Long.valueOf(paramZzg.zzhe()));
    localContentValues.put("last_bundle_start_timestamp", Long.valueOf(paramZzg.zzgy()));
    localContentValues.put("last_bundle_end_timestamp", Long.valueOf(paramZzg.zzgz()));
    localContentValues.put("app_version", paramZzg.zzak());
    localContentValues.put("app_store", paramZzg.zzhb());
    localContentValues.put("gmp_version", Long.valueOf(paramZzg.zzhc()));
    localContentValues.put("dev_cert_hash", Long.valueOf(paramZzg.zzhd()));
    localContentValues.put("measurement_enabled", Boolean.valueOf(paramZzg.isMeasurementEnabled()));
    localContentValues.put("day", Long.valueOf(paramZzg.zzhi()));
    localContentValues.put("daily_public_events_count", Long.valueOf(paramZzg.zzhj()));
    localContentValues.put("daily_events_count", Long.valueOf(paramZzg.zzhk()));
    localContentValues.put("daily_conversions_count", Long.valueOf(paramZzg.zzhl()));
    localContentValues.put("config_fetched_time", Long.valueOf(paramZzg.zzhf()));
    localContentValues.put("failed_config_fetch_time", Long.valueOf(paramZzg.zzhg()));
    localContentValues.put("app_version_int", Long.valueOf(paramZzg.zzha()));
    localContentValues.put("firebase_instance_id", paramZzg.getFirebaseInstanceId());
    localContentValues.put("daily_error_events_count", Long.valueOf(paramZzg.zzhn()));
    localContentValues.put("daily_realtime_events_count", Long.valueOf(paramZzg.zzhm()));
    localContentValues.put("health_monitor_sample", paramZzg.zzho());
    localContentValues.put("android_id", Long.valueOf(paramZzg.zzhq()));
    localContentValues.put("adid_reporting_enabled", Boolean.valueOf(paramZzg.zzhr()));
    localContentValues.put("ssaid_reporting_enabled", Boolean.valueOf(paramZzg.zzhs()));
    localContentValues.put("admob_app_id", paramZzg.zzgw());
    try
    {
      SQLiteDatabase localSQLiteDatabase = getWritableDatabase();
      if ((localSQLiteDatabase.update("apps", localContentValues, "app_id = ?", new String[] { paramZzg.zzal() }) == 0L) && (localSQLiteDatabase.insertWithOnConflict("apps", null, localContentValues, 5) == -1L)) {
        zzgo().zzjd().zzg("Failed to insert/update app (got -1). appId", zzap.zzbv(paramZzg.zzal()));
      }
      return;
    }
    catch (SQLiteException localSQLiteException)
    {
      zzgo().zzjd().zze("Error storing app. appId", zzap.zzbv(paramZzg.zzal()), localSQLiteException);
    }
  }
  
  @WorkerThread
  public final void zza(zzz paramZzz)
  {
    Preconditions.checkNotNull(paramZzz);
    zzaf();
    zzcl();
    ContentValues localContentValues = new ContentValues();
    localContentValues.put("app_id", zztt);
    localContentValues.put("name", name);
    localContentValues.put("lifetime_count", Long.valueOf(zzaie));
    localContentValues.put("current_bundle_count", Long.valueOf(zzaif));
    localContentValues.put("last_fire_timestamp", Long.valueOf(zzaig));
    localContentValues.put("last_bundled_timestamp", Long.valueOf(zzaih));
    localContentValues.put("last_bundled_day", zzaii);
    localContentValues.put("last_sampled_complex_event_id", zzaij);
    localContentValues.put("last_sampling_rate", zzaik);
    Long localLong;
    if ((zzail != null) && (zzail.booleanValue())) {
      localLong = Long.valueOf(1L);
    } else {
      localLong = null;
    }
    localContentValues.put("last_exempt_from_sampling", localLong);
    try
    {
      if (getWritableDatabase().insertWithOnConflict("events", null, localContentValues, 5) == -1L) {
        zzgo().zzjd().zzg("Failed to insert/update event aggregates (got -1). appId", zzap.zzbv(zztt));
      }
      return;
    }
    catch (SQLiteException localSQLiteException)
    {
      zzgo().zzjd().zze("Error storing event aggregates. appId", zzap.zzbv(zztt), localSQLiteException);
    }
  }
  
  @WorkerThread
  final void zza(String paramString, zzfu[] paramArrayOfZzfu)
  {
    zzcl();
    zzaf();
    Preconditions.checkNotEmpty(paramString);
    Preconditions.checkNotNull(paramArrayOfZzfu);
    SQLiteDatabase localSQLiteDatabase = getWritableDatabase();
    localSQLiteDatabase.beginTransaction();
    for (;;)
    {
      int j;
      int k;
      try
      {
        zzcl();
        zzaf();
        Preconditions.checkNotEmpty(paramString);
        Object localObject1 = getWritableDatabase();
        int n = 0;
        ((SQLiteDatabase)localObject1).delete("property_filters", "app_id=?", new String[] { paramString });
        ((SQLiteDatabase)localObject1).delete("event_filters", "app_id=?", new String[] { paramString });
        int i1 = paramArrayOfZzfu.length;
        j = 0;
        if (j < i1)
        {
          localObject1 = paramArrayOfZzfu[j];
          zzcl();
          zzaf();
          Preconditions.checkNotEmpty(paramString);
          Preconditions.checkNotNull(localObject1);
          Preconditions.checkNotNull(zzava);
          Preconditions.checkNotNull(zzauz);
          if (zzauy == null)
          {
            zzgo().zzjg().zzg("Audience with no ID. appId", zzap.zzbv(paramString));
            break label576;
          }
          int i2 = zzauy.intValue();
          Object localObject2 = zzava;
          k = localObject2.length;
          i = 0;
          if (i < k)
          {
            if (zzave == null)
            {
              zzgo().zzjg().zze("Event filter with no ID. Audience definition ignored. appId, audienceId", zzap.zzbv(paramString), zzauy);
              break label576;
            }
          }
          else
          {
            localObject2 = zzauz;
            k = localObject2.length;
            i = 0;
            if (i < k)
            {
              if (zzave != null) {
                break label548;
              }
              zzgo().zzjg().zze("Property filter with no ID. Audience definition ignored. appId, audienceId", zzap.zzbv(paramString), zzauy);
              break label576;
            }
            localObject2 = zzava;
            k = localObject2.length;
            i = 0;
            if (i >= k) {
              break label562;
            }
            if (zza(paramString, i2, localObject2[i])) {
              break label555;
            }
            i = 0;
            int m = i;
            if (i != 0)
            {
              localObject1 = zzauz;
              int i3 = localObject1.length;
              k = 0;
              m = i;
              if (k < i3)
              {
                if (zza(paramString, i2, localObject1[k])) {
                  break label567;
                }
                m = 0;
              }
            }
            if (m != 0) {
              break label576;
            }
            zzcl();
            zzaf();
            Preconditions.checkNotEmpty(paramString);
            localObject1 = getWritableDatabase();
            ((SQLiteDatabase)localObject1).delete("property_filters", "app_id=? and audience_id=?", new String[] { paramString, String.valueOf(i2) });
            ((SQLiteDatabase)localObject1).delete("event_filters", "app_id=? and audience_id=?", new String[] { paramString, String.valueOf(i2) });
            break label576;
          }
        }
        else
        {
          localObject1 = new ArrayList();
          j = paramArrayOfZzfu.length;
          i = n;
          if (i < j)
          {
            ((List)localObject1).add(zzauy);
            i += 1;
            continue;
          }
          zza(paramString, (List)localObject1);
          localSQLiteDatabase.setTransactionSuccessful();
          return;
        }
      }
      finally
      {
        localSQLiteDatabase.endTransaction();
      }
      i += 1;
      continue;
      label548:
      i += 1;
      continue;
      label555:
      i += 1;
      continue;
      label562:
      int i = 1;
      continue;
      label567:
      k += 1;
      continue;
      label576:
      j += 1;
    }
  }
  
  @WorkerThread
  public final boolean zza(zzgi paramZzgi, boolean paramBoolean)
  {
    throw new Runtime("d2j fail translate: java.lang.RuntimeException: can not merge I and Z\n\tat com.googlecode.dex2jar.ir.TypeClass.merge(TypeClass.java:100)\n\tat com.googlecode.dex2jar.ir.ts.TypeTransformer$TypeRef.updateTypeClass(TypeTransformer.java:174)\n\tat com.googlecode.dex2jar.ir.ts.TypeTransformer$TypeAnalyze.copyTypes(TypeTransformer.java:311)\n\tat com.googlecode.dex2jar.ir.ts.TypeTransformer$TypeAnalyze.fixTypes(TypeTransformer.java:226)\n\tat com.googlecode.dex2jar.ir.ts.TypeTransformer$TypeAnalyze.analyze(TypeTransformer.java:207)\n\tat com.googlecode.dex2jar.ir.ts.TypeTransformer.transform(TypeTransformer.java:44)\n\tat com.googlecode.d2j.dex.Dex2jar$2.optimize(Dex2jar.java:162)\n\tat com.googlecode.d2j.dex.Dex2Asm.convertCode(Dex2Asm.java:414)\n\tat com.googlecode.d2j.dex.ExDex2Asm.convertCode(ExDex2Asm.java:42)\n\tat com.googlecode.d2j.dex.Dex2jar$2.convertCode(Dex2jar.java:128)\n\tat com.googlecode.d2j.dex.Dex2Asm.convertMethod(Dex2Asm.java:509)\n\tat com.googlecode.d2j.dex.Dex2Asm.convertClass(Dex2Asm.java:406)\n\tat com.googlecode.d2j.dex.Dex2Asm.convertDex(Dex2Asm.java:422)\n\tat com.googlecode.d2j.dex.Dex2jar.doTranslate(Dex2jar.java:172)\n\tat com.googlecode.d2j.dex.Dex2jar.to(Dex2jar.java:272)\n\tat com.googlecode.dex2jar.tools.Dex2jarCmd.doCommandLine(Dex2jarCmd.java:108)\n\tat com.googlecode.dex2jar.tools.BaseCmd.doMain(BaseCmd.java:288)\n\tat com.googlecode.dex2jar.tools.Dex2jarCmd.main(Dex2jarCmd.java:32)\n");
  }
  
  @WorkerThread
  public final boolean zza(zzfj paramZzfj)
  {
    Preconditions.checkNotNull(paramZzfj);
    zzaf();
    zzcl();
    if (zzi(zztt, name) == null) {
      if (zzfk.zzcq(name))
      {
        if (zza("select count(1) from user_attributes where app_id=? and name not like '!_%' escape '!'", new String[] { zztt }) >= 25L) {
          return false;
        }
      }
      else
      {
        long l = zza("select count(1) from user_attributes where app_id=? and origin=? AND name like '!_%' escape '!'", new String[] { zztt, origin });
        if (zzgq().zze(zztt, zzaf.zzalj))
        {
          if ((!"_ap".equals(name)) && (l >= 25L)) {
            return false;
          }
        }
        else if (l >= 25L) {
          return false;
        }
      }
    }
    ContentValues localContentValues = new ContentValues();
    localContentValues.put("app_id", zztt);
    localContentValues.put("origin", origin);
    localContentValues.put("name", name);
    localContentValues.put("set_timestamp", Long.valueOf(zzaue));
    zza(localContentValues, "value", value);
    try
    {
      if (getWritableDatabase().insertWithOnConflict("user_attributes", null, localContentValues, 5) == -1L)
      {
        zzgo().zzjd().zzg("Failed to insert/update user property (got -1). appId", zzap.zzbv(zztt));
        return true;
      }
    }
    catch (SQLiteException localSQLiteException)
    {
      zzgo().zzjd().zze("Error storing user property. appId", zzap.zzbv(zztt), localSQLiteException);
    }
    return true;
  }
  
  @WorkerThread
  public final boolean zza(zzl paramZzl)
  {
    Preconditions.checkNotNull(paramZzl);
    zzaf();
    zzcl();
    if (zzi(packageName, zzahb.name) == null) {
      if (zza("SELECT COUNT(1) FROM conditional_properties WHERE app_id=?", new String[] { packageName }) >= 1000L) {
        return false;
      }
    }
    ContentValues localContentValues = new ContentValues();
    localContentValues.put("app_id", packageName);
    localContentValues.put("origin", origin);
    localContentValues.put("name", zzahb.name);
    zza(localContentValues, "value", zzahb.getValue());
    localContentValues.put("active", Boolean.valueOf(active));
    localContentValues.put("trigger_event_name", triggerEventName);
    localContentValues.put("trigger_timeout", Long.valueOf(triggerTimeout));
    zzgm();
    localContentValues.put("timed_out_event", zzfk.zza(zzahc));
    localContentValues.put("creation_timestamp", Long.valueOf(creationTimestamp));
    zzgm();
    localContentValues.put("triggered_event", zzfk.zza(zzahd));
    localContentValues.put("triggered_timestamp", Long.valueOf(zzahb.zzaue));
    localContentValues.put("time_to_live", Long.valueOf(timeToLive));
    zzgm();
    localContentValues.put("expired_event", zzfk.zza(zzahe));
    try
    {
      if (getWritableDatabase().insertWithOnConflict("conditional_properties", null, localContentValues, 5) == -1L)
      {
        zzgo().zzjd().zzg("Failed to insert/update conditional user property (got -1)", zzap.zzbv(packageName));
        return true;
      }
    }
    catch (SQLiteException localSQLiteException)
    {
      zzgo().zzjd().zze("Error storing conditional user property", zzap.zzbv(packageName), localSQLiteException);
    }
    return true;
  }
  
  public final boolean zza(zzy paramZzy, long paramLong, boolean paramBoolean)
  {
    throw new Runtime("d2j fail translate: java.lang.RuntimeException: can not merge I and Z\n\tat com.googlecode.dex2jar.ir.TypeClass.merge(TypeClass.java:100)\n\tat com.googlecode.dex2jar.ir.ts.TypeTransformer$TypeRef.updateTypeClass(TypeTransformer.java:174)\n\tat com.googlecode.dex2jar.ir.ts.TypeTransformer$TypeAnalyze.copyTypes(TypeTransformer.java:311)\n\tat com.googlecode.dex2jar.ir.ts.TypeTransformer$TypeAnalyze.fixTypes(TypeTransformer.java:226)\n\tat com.googlecode.dex2jar.ir.ts.TypeTransformer$TypeAnalyze.analyze(TypeTransformer.java:207)\n\tat com.googlecode.dex2jar.ir.ts.TypeTransformer.transform(TypeTransformer.java:44)\n\tat com.googlecode.d2j.dex.Dex2jar$2.optimize(Dex2jar.java:162)\n\tat com.googlecode.d2j.dex.Dex2Asm.convertCode(Dex2Asm.java:414)\n\tat com.googlecode.d2j.dex.ExDex2Asm.convertCode(ExDex2Asm.java:42)\n\tat com.googlecode.d2j.dex.Dex2jar$2.convertCode(Dex2jar.java:128)\n\tat com.googlecode.d2j.dex.Dex2Asm.convertMethod(Dex2Asm.java:509)\n\tat com.googlecode.d2j.dex.Dex2Asm.convertClass(Dex2Asm.java:406)\n\tat com.googlecode.d2j.dex.Dex2Asm.convertDex(Dex2Asm.java:422)\n\tat com.googlecode.d2j.dex.Dex2jar.doTranslate(Dex2jar.java:172)\n\tat com.googlecode.d2j.dex.Dex2jar.to(Dex2jar.java:272)\n\tat com.googlecode.dex2jar.tools.Dex2jarCmd.doCommandLine(Dex2jarCmd.java:108)\n\tat com.googlecode.dex2jar.tools.BaseCmd.doMain(BaseCmd.java:288)\n\tat com.googlecode.dex2jar.tools.Dex2jarCmd.main(Dex2jarCmd.java:32)\n");
  }
  
  public final boolean zza(String paramString, Long paramLong, long paramLong1, zzgf paramZzgf)
  {
    zzaf();
    zzcl();
    Preconditions.checkNotNull(paramZzgf);
    Preconditions.checkNotEmpty(paramString);
    Preconditions.checkNotNull(paramLong);
    try
    {
      byte[] arrayOfByte = new byte[paramZzgf.zzvu()];
      zzyy localZzyy = zzyy.zzk(arrayOfByte, 0, arrayOfByte.length);
      paramZzgf.zza(localZzyy);
      localZzyy.zzyt();
      zzgo().zzjl().zze("Saving complex main event, appId, data size", zzgl().zzbs(paramString), Integer.valueOf(arrayOfByte.length));
      paramZzgf = new ContentValues();
      paramZzgf.put("app_id", paramString);
      paramZzgf.put("event_id", paramLong);
      paramZzgf.put("children_to_process", Long.valueOf(paramLong1));
      paramZzgf.put("main_event", arrayOfByte);
      try
      {
        if (getWritableDatabase().insertWithOnConflict("main_event_params", null, paramZzgf, 5) == -1L)
        {
          zzgo().zzjd().zzg("Failed to insert complex main event (got -1). appId", zzap.zzbv(paramString));
          return false;
        }
        return true;
      }
      catch (SQLiteException paramLong)
      {
        zzgo().zzjd().zze("Error storing complex main event. appId", zzap.zzbv(paramString), paramLong);
        return false;
      }
      return false;
    }
    catch (IOException paramZzgf)
    {
      zzgo().zzjd().zzd("Data loss. Failed to serialize event params/data. appId, eventId", zzap.zzbv(paramString), paramLong, paramZzgf);
    }
  }
  
  /* Error */
  public final String zzah(long paramLong)
  {
    // Byte code:
    //   0: aload_0
    //   1: invokevirtual 327	com/google/android/gms/measurement/internal/zzco:zzaf	()V
    //   4: aload_0
    //   5: invokevirtual 324	com/google/android/gms/measurement/internal/zzez:zzcl	()V
    //   8: aload_0
    //   9: invokevirtual 203	com/google/android/gms/measurement/internal/zzq:getWritableDatabase	()Landroid/database/sqlite/SQLiteDatabase;
    //   12: ldc_w 1018
    //   15: iconst_1
    //   16: anewarray 19	java/lang/String
    //   19: dup
    //   20: iconst_0
    //   21: lload_1
    //   22: invokestatic 1020	java/lang/String:valueOf	(J)Ljava/lang/String;
    //   25: aastore
    //   26: invokevirtual 209	android/database/sqlite/SQLiteDatabase:rawQuery	(Ljava/lang/String;[Ljava/lang/String;)Landroid/database/Cursor;
    //   29: astore 4
    //   31: aload 4
    //   33: astore_3
    //   34: aload 4
    //   36: invokeinterface 215 1 0
    //   41: ifne +33 -> 74
    //   44: aload 4
    //   46: astore_3
    //   47: aload_0
    //   48: invokevirtual 231	com/google/android/gms/measurement/internal/zzco:zzgo	()Lcom/google/android/gms/measurement/internal/zzap;
    //   51: invokevirtual 601	com/google/android/gms/measurement/internal/zzap:zzjl	()Lcom/google/android/gms/measurement/internal/zzar;
    //   54: ldc_w 1022
    //   57: invokevirtual 270	com/google/android/gms/measurement/internal/zzar:zzbx	(Ljava/lang/String;)V
    //   60: aload 4
    //   62: ifnull +10 -> 72
    //   65: aload 4
    //   67: invokeinterface 222 1 0
    //   72: aconst_null
    //   73: areturn
    //   74: aload 4
    //   76: astore_3
    //   77: aload 4
    //   79: iconst_0
    //   80: invokeinterface 274 2 0
    //   85: astore 5
    //   87: aload 4
    //   89: ifnull +10 -> 99
    //   92: aload 4
    //   94: invokeinterface 222 1 0
    //   99: aload 5
    //   101: areturn
    //   102: astore 5
    //   104: goto +15 -> 119
    //   107: astore 4
    //   109: aconst_null
    //   110: astore_3
    //   111: goto +42 -> 153
    //   114: astore 5
    //   116: aconst_null
    //   117: astore 4
    //   119: aload 4
    //   121: astore_3
    //   122: aload_0
    //   123: invokevirtual 231	com/google/android/gms/measurement/internal/zzco:zzgo	()Lcom/google/android/gms/measurement/internal/zzap;
    //   126: invokevirtual 237	com/google/android/gms/measurement/internal/zzap:zzjd	()Lcom/google/android/gms/measurement/internal/zzar;
    //   129: ldc_w 1024
    //   132: aload 5
    //   134: invokevirtual 266	com/google/android/gms/measurement/internal/zzar:zzg	(Ljava/lang/String;Ljava/lang/Object;)V
    //   137: aload 4
    //   139: ifnull +10 -> 149
    //   142: aload 4
    //   144: invokeinterface 222 1 0
    //   149: aconst_null
    //   150: areturn
    //   151: astore 4
    //   153: aload_3
    //   154: ifnull +9 -> 163
    //   157: aload_3
    //   158: invokeinterface 222 1 0
    //   163: aload 4
    //   165: athrow
    // Local variable table:
    //   start	length	slot	name	signature
    //   0	166	0	this	zzq
    //   0	166	1	paramLong	long
    //   33	125	3	localObject1	Object
    //   29	64	4	localCursor	Cursor
    //   107	1	4	localObject2	Object
    //   117	26	4	localObject3	Object
    //   151	13	4	localObject4	Object
    //   85	15	5	str	String
    //   102	1	5	localSQLiteException1	SQLiteException
    //   114	19	5	localSQLiteException2	SQLiteException
    // Exception table:
    //   from	to	target	type
    //   34	44	102	android/database/sqlite/SQLiteException
    //   47	60	102	android/database/sqlite/SQLiteException
    //   77	87	102	android/database/sqlite/SQLiteException
    //   8	31	107	finally
    //   8	31	114	android/database/sqlite/SQLiteException
    //   34	44	151	finally
    //   47	60	151	finally
    //   77	87	151	finally
    //   122	137	151	finally
  }
  
  /* Error */
  @WorkerThread
  public final List<android.util.Pair<zzgi, Long>> zzb(String paramString, int paramInt1, int paramInt2)
  {
    // Byte code:
    //   0: aload_0
    //   1: invokevirtual 327	com/google/android/gms/measurement/internal/zzco:zzaf	()V
    //   4: aload_0
    //   5: invokevirtual 324	com/google/android/gms/measurement/internal/zzez:zzcl	()V
    //   8: iload_2
    //   9: ifle +9 -> 18
    //   12: iconst_1
    //   13: istore 5
    //   15: goto +6 -> 21
    //   18: iconst_0
    //   19: istore 5
    //   21: iload 5
    //   23: invokestatic 1029	com/google/android/gms/common/internal/Preconditions:checkArgument	(Z)V
    //   26: iload_3
    //   27: ifle +9 -> 36
    //   30: iconst_1
    //   31: istore 5
    //   33: goto +6 -> 39
    //   36: iconst_0
    //   37: istore 5
    //   39: iload 5
    //   41: invokestatic 1029	com/google/android/gms/common/internal/Preconditions:checkArgument	(Z)V
    //   44: aload_1
    //   45: invokestatic 297	com/google/android/gms/common/internal/Preconditions:checkNotEmpty	(Ljava/lang/String;)Ljava/lang/String;
    //   48: pop
    //   49: aconst_null
    //   50: astore 10
    //   52: aconst_null
    //   53: astore 8
    //   55: aload_0
    //   56: invokevirtual 203	com/google/android/gms/measurement/internal/zzq:getWritableDatabase	()Landroid/database/sqlite/SQLiteDatabase;
    //   59: ldc_w 1031
    //   62: iconst_3
    //   63: anewarray 19	java/lang/String
    //   66: dup
    //   67: iconst_0
    //   68: ldc_w 1033
    //   71: aastore
    //   72: dup
    //   73: iconst_1
    //   74: ldc_w 392
    //   77: aastore
    //   78: dup
    //   79: iconst_2
    //   80: ldc -103
    //   82: aastore
    //   83: ldc_w 638
    //   86: iconst_1
    //   87: anewarray 19	java/lang/String
    //   90: dup
    //   91: iconst_0
    //   92: aload_1
    //   93: aastore
    //   94: aconst_null
    //   95: aconst_null
    //   96: ldc_w 1033
    //   99: iload_2
    //   100: invokestatic 852	java/lang/String:valueOf	(I)Ljava/lang/String;
    //   103: invokevirtual 1036	android/database/sqlite/SQLiteDatabase:query	(Ljava/lang/String;[Ljava/lang/String;Ljava/lang/String;[Ljava/lang/String;Ljava/lang/String;Ljava/lang/String;Ljava/lang/String;Ljava/lang/String;)Landroid/database/Cursor;
    //   106: astore 9
    //   108: aload 9
    //   110: invokeinterface 215 1 0
    //   115: ifne +23 -> 138
    //   118: invokestatic 1042	java/util/Collections:emptyList	()Ljava/util/List;
    //   121: astore 8
    //   123: aload 9
    //   125: ifnull +10 -> 135
    //   128: aload 9
    //   130: invokeinterface 222 1 0
    //   135: aload 8
    //   137: areturn
    //   138: new 460	java/util/ArrayList
    //   141: dup
    //   142: invokespecial 461	java/util/ArrayList:<init>	()V
    //   145: astore 8
    //   147: iconst_0
    //   148: istore_2
    //   149: aload 9
    //   151: iconst_0
    //   152: invokeinterface 219 2 0
    //   157: lstore 6
    //   159: aload 9
    //   161: iconst_1
    //   162: invokeinterface 607 2 0
    //   167: astore 10
    //   169: aload_0
    //   170: invokevirtual 562	com/google/android/gms/measurement/internal/zzey:zzjo	()Lcom/google/android/gms/measurement/internal/zzfg;
    //   173: aload 10
    //   175: invokevirtual 1046	com/google/android/gms/measurement/internal/zzfg:zza	([B)[B
    //   178: astore 10
    //   180: aload 8
    //   182: invokeinterface 1048 1 0
    //   187: ifne +12 -> 199
    //   190: aload 10
    //   192: arraylength
    //   193: iload_2
    //   194: iadd
    //   195: iload_3
    //   196: if_icmpgt +160 -> 356
    //   199: aload 10
    //   201: iconst_0
    //   202: aload 10
    //   204: arraylength
    //   205: invokestatic 613	com/google/android/gms/internal/measurement/zzyx:zzj	([BII)Lcom/google/android/gms/internal/measurement/zzyx;
    //   208: astore 11
    //   210: new 553	com/google/android/gms/internal/measurement/zzgi
    //   213: dup
    //   214: invokespecial 1049	com/google/android/gms/internal/measurement/zzgi:<init>	()V
    //   217: astore 12
    //   219: aload 12
    //   221: aload 11
    //   223: invokevirtual 619	com/google/android/gms/internal/measurement/zzzg:zza	(Lcom/google/android/gms/internal/measurement/zzyx;)Lcom/google/android/gms/internal/measurement/zzzg;
    //   226: pop
    //   227: aload 9
    //   229: iconst_2
    //   230: invokeinterface 1053 2 0
    //   235: ifne +19 -> 254
    //   238: aload 12
    //   240: aload 9
    //   242: iconst_2
    //   243: invokeinterface 1056 2 0
    //   248: invokestatic 262	java/lang/Integer:valueOf	(I)Ljava/lang/Integer;
    //   251: putfield 1059	com/google/android/gms/internal/measurement/zzgi:zzayc	Ljava/lang/Integer;
    //   254: iload_2
    //   255: aload 10
    //   257: arraylength
    //   258: iadd
    //   259: istore 4
    //   261: aload 8
    //   263: aload 12
    //   265: lload 6
    //   267: invokestatic 288	java/lang/Long:valueOf	(J)Ljava/lang/Long;
    //   270: invokestatic 625	android/util/Pair:create	(Ljava/lang/Object;Ljava/lang/Object;)Landroid/util/Pair;
    //   273: invokeinterface 480 2 0
    //   278: pop
    //   279: goto +54 -> 333
    //   282: astore 10
    //   284: aload_0
    //   285: invokevirtual 231	com/google/android/gms/measurement/internal/zzco:zzgo	()Lcom/google/android/gms/measurement/internal/zzap;
    //   288: invokevirtual 237	com/google/android/gms/measurement/internal/zzap:zzjd	()Lcom/google/android/gms/measurement/internal/zzar;
    //   291: ldc_w 1061
    //   294: aload_1
    //   295: invokestatic 348	com/google/android/gms/measurement/internal/zzap:zzbv	(Ljava/lang/String;)Ljava/lang/Object;
    //   298: aload 10
    //   300: invokevirtual 245	com/google/android/gms/measurement/internal/zzar:zze	(Ljava/lang/String;Ljava/lang/Object;Ljava/lang/Object;)V
    //   303: iload_2
    //   304: istore 4
    //   306: goto +27 -> 333
    //   309: astore 10
    //   311: aload_0
    //   312: invokevirtual 231	com/google/android/gms/measurement/internal/zzco:zzgo	()Lcom/google/android/gms/measurement/internal/zzap;
    //   315: invokevirtual 237	com/google/android/gms/measurement/internal/zzap:zzjd	()Lcom/google/android/gms/measurement/internal/zzar;
    //   318: ldc_w 1063
    //   321: aload_1
    //   322: invokestatic 348	com/google/android/gms/measurement/internal/zzap:zzbv	(Ljava/lang/String;)Ljava/lang/Object;
    //   325: aload 10
    //   327: invokevirtual 245	com/google/android/gms/measurement/internal/zzar:zze	(Ljava/lang/String;Ljava/lang/Object;Ljava/lang/Object;)V
    //   330: iload_2
    //   331: istore 4
    //   333: aload 9
    //   335: invokeinterface 1066 1 0
    //   340: istore 5
    //   342: iload 5
    //   344: ifeq +12 -> 356
    //   347: iload 4
    //   349: istore_2
    //   350: iload 4
    //   352: iload_3
    //   353: if_icmple -204 -> 149
    //   356: aload 9
    //   358: ifnull +10 -> 368
    //   361: aload 9
    //   363: invokeinterface 222 1 0
    //   368: aload 8
    //   370: areturn
    //   371: astore_1
    //   372: aload 9
    //   374: astore 8
    //   376: goto +67 -> 443
    //   379: astore 10
    //   381: goto +17 -> 398
    //   384: astore_1
    //   385: goto +58 -> 443
    //   388: astore 8
    //   390: aload 10
    //   392: astore 9
    //   394: aload 8
    //   396: astore 10
    //   398: aload 9
    //   400: astore 8
    //   402: aload_0
    //   403: invokevirtual 231	com/google/android/gms/measurement/internal/zzco:zzgo	()Lcom/google/android/gms/measurement/internal/zzap;
    //   406: invokevirtual 237	com/google/android/gms/measurement/internal/zzap:zzjd	()Lcom/google/android/gms/measurement/internal/zzar;
    //   409: ldc_w 1068
    //   412: aload_1
    //   413: invokestatic 348	com/google/android/gms/measurement/internal/zzap:zzbv	(Ljava/lang/String;)Ljava/lang/Object;
    //   416: aload 10
    //   418: invokevirtual 245	com/google/android/gms/measurement/internal/zzar:zze	(Ljava/lang/String;Ljava/lang/Object;Ljava/lang/Object;)V
    //   421: aload 9
    //   423: astore 8
    //   425: invokestatic 1042	java/util/Collections:emptyList	()Ljava/util/List;
    //   428: astore_1
    //   429: aload 9
    //   431: ifnull +10 -> 441
    //   434: aload 9
    //   436: invokeinterface 222 1 0
    //   441: aload_1
    //   442: areturn
    //   443: aload 8
    //   445: ifnull +10 -> 455
    //   448: aload 8
    //   450: invokeinterface 222 1 0
    //   455: aload_1
    //   456: athrow
    // Local variable table:
    //   start	length	slot	name	signature
    //   0	457	0	this	zzq
    //   0	457	1	paramString	String
    //   0	457	2	paramInt1	int
    //   0	457	3	paramInt2	int
    //   259	95	4	i	int
    //   13	330	5	bool	boolean
    //   157	109	6	l	long
    //   53	322	8	localObject1	Object
    //   388	7	8	localSQLiteException1	SQLiteException
    //   400	49	8	localObject2	Object
    //   106	329	9	localObject3	Object
    //   50	206	10	arrayOfByte	byte[]
    //   282	17	10	localIOException1	IOException
    //   309	17	10	localIOException2	IOException
    //   379	12	10	localSQLiteException2	SQLiteException
    //   396	21	10	localObject4	Object
    //   208	14	11	localZzyx	com.google.android.gms.internal.measurement.zzyx
    //   217	47	12	localZzgi	zzgi
    // Exception table:
    //   from	to	target	type
    //   219	227	282	java/io/IOException
    //   159	180	309	java/io/IOException
    //   108	123	371	finally
    //   138	147	371	finally
    //   149	159	371	finally
    //   159	180	371	finally
    //   180	199	371	finally
    //   199	219	371	finally
    //   219	227	371	finally
    //   227	254	371	finally
    //   254	279	371	finally
    //   284	303	371	finally
    //   311	330	371	finally
    //   333	342	371	finally
    //   108	123	379	android/database/sqlite/SQLiteException
    //   138	147	379	android/database/sqlite/SQLiteException
    //   149	159	379	android/database/sqlite/SQLiteException
    //   159	180	379	android/database/sqlite/SQLiteException
    //   180	199	379	android/database/sqlite/SQLiteException
    //   199	219	379	android/database/sqlite/SQLiteException
    //   219	227	379	android/database/sqlite/SQLiteException
    //   227	254	379	android/database/sqlite/SQLiteException
    //   254	279	379	android/database/sqlite/SQLiteException
    //   284	303	379	android/database/sqlite/SQLiteException
    //   311	330	379	android/database/sqlite/SQLiteException
    //   333	342	379	android/database/sqlite/SQLiteException
    //   55	108	384	finally
    //   402	421	384	finally
    //   425	429	384	finally
    //   55	108	388	android/database/sqlite/SQLiteException
  }
  
  /* Error */
  @WorkerThread
  public final List<zzfj> zzb(String arg1, String arg2, String arg3)
  {
    // Byte code:
    //   0: aload_1
    //   1: invokestatic 297	com/google/android/gms/common/internal/Preconditions:checkNotEmpty	(Ljava/lang/String;)Ljava/lang/String;
    //   4: pop
    //   5: aload_0
    //   6: invokevirtual 327	com/google/android/gms/measurement/internal/zzco:zzaf	()V
    //   9: aload_0
    //   10: invokevirtual 324	com/google/android/gms/measurement/internal/zzez:zzcl	()V
    //   13: new 460	java/util/ArrayList
    //   16: dup
    //   17: invokespecial 461	java/util/ArrayList:<init>	()V
    //   20: astore 10
    //   22: aconst_null
    //   23: astore 9
    //   25: new 460	java/util/ArrayList
    //   28: dup
    //   29: iconst_3
    //   30: invokespecial 1071	java/util/ArrayList:<init>	(I)V
    //   33: astore 11
    //   35: aload 11
    //   37: aload_1
    //   38: invokeinterface 480 2 0
    //   43: pop
    //   44: new 488	java/lang/StringBuilder
    //   47: dup
    //   48: ldc_w 638
    //   51: invokespecial 1072	java/lang/StringBuilder:<init>	(Ljava/lang/String;)V
    //   54: astore 8
    //   56: aload_2
    //   57: invokestatic 339	android/text/TextUtils:isEmpty	(Ljava/lang/CharSequence;)Z
    //   60: istore 4
    //   62: iload 4
    //   64: ifne +501 -> 565
    //   67: aload 11
    //   69: aload_2
    //   70: invokeinterface 480 2 0
    //   75: pop
    //   76: aload 8
    //   78: ldc_w 1074
    //   81: invokevirtual 500	java/lang/StringBuilder:append	(Ljava/lang/String;)Ljava/lang/StringBuilder;
    //   84: pop
    //   85: goto +3 -> 88
    //   88: aload_2
    //   89: astore 7
    //   91: aload_3
    //   92: invokestatic 339	android/text/TextUtils:isEmpty	(Ljava/lang/CharSequence;)Z
    //   95: ifne +30 -> 125
    //   98: aload 11
    //   100: aload_3
    //   101: invokestatic 355	java/lang/String:valueOf	(Ljava/lang/Object;)Ljava/lang/String;
    //   104: ldc_w 1076
    //   107: invokevirtual 1079	java/lang/String:concat	(Ljava/lang/String;)Ljava/lang/String;
    //   110: invokeinterface 480 2 0
    //   115: pop
    //   116: aload 8
    //   118: ldc_w 1081
    //   121: invokevirtual 500	java/lang/StringBuilder:append	(Ljava/lang/String;)Ljava/lang/StringBuilder;
    //   124: pop
    //   125: aload 11
    //   127: aload 11
    //   129: invokeinterface 466 1 0
    //   134: anewarray 19	java/lang/String
    //   137: invokeinterface 1085 2 0
    //   142: checkcast 1086	[Ljava/lang/String;
    //   145: astore 11
    //   147: aload_0
    //   148: invokevirtual 203	com/google/android/gms/measurement/internal/zzq:getWritableDatabase	()Landroid/database/sqlite/SQLiteDatabase;
    //   151: astore 12
    //   153: aload 8
    //   155: invokevirtual 505	java/lang/StringBuilder:toString	()Ljava/lang/String;
    //   158: astore 8
    //   160: aload 12
    //   162: ldc_w 908
    //   165: iconst_4
    //   166: anewarray 19	java/lang/String
    //   169: dup
    //   170: iconst_0
    //   171: ldc_w 781
    //   174: aastore
    //   175: dup
    //   176: iconst_1
    //   177: ldc_w 896
    //   180: aastore
    //   181: dup
    //   182: iconst_2
    //   183: ldc_w 901
    //   186: aastore
    //   187: dup
    //   188: iconst_3
    //   189: ldc 43
    //   191: aastore
    //   192: aload 8
    //   194: aload 11
    //   196: aconst_null
    //   197: aconst_null
    //   198: ldc_w 1033
    //   201: ldc_w 1088
    //   204: invokevirtual 1036	android/database/sqlite/SQLiteDatabase:query	(Ljava/lang/String;[Ljava/lang/String;Ljava/lang/String;[Ljava/lang/String;Ljava/lang/String;Ljava/lang/String;Ljava/lang/String;Ljava/lang/String;)Landroid/database/Cursor;
    //   207: astore 8
    //   209: aload 7
    //   211: astore 9
    //   213: aload 8
    //   215: invokeinterface 215 1 0
    //   220: istore 4
    //   222: iload 4
    //   224: ifne +18 -> 242
    //   227: aload 8
    //   229: ifnull +10 -> 239
    //   232: aload 8
    //   234: invokeinterface 222 1 0
    //   239: aload 10
    //   241: areturn
    //   242: aload 7
    //   244: astore 9
    //   246: aload 10
    //   248: invokeinterface 466 1 0
    //   253: sipush 1000
    //   256: if_icmplt +29 -> 285
    //   259: aload 7
    //   261: astore 9
    //   263: aload_0
    //   264: invokevirtual 231	com/google/android/gms/measurement/internal/zzco:zzgo	()Lcom/google/android/gms/measurement/internal/zzap;
    //   267: invokevirtual 237	com/google/android/gms/measurement/internal/zzap:zzjd	()Lcom/google/android/gms/measurement/internal/zzar;
    //   270: ldc_w 1090
    //   273: sipush 1000
    //   276: invokestatic 262	java/lang/Integer:valueOf	(I)Ljava/lang/Integer;
    //   279: invokevirtual 266	com/google/android/gms/measurement/internal/zzar:zzg	(Ljava/lang/String;Ljava/lang/Object;)V
    //   282: goto +143 -> 425
    //   285: aload 7
    //   287: astore 9
    //   289: aload 8
    //   291: iconst_0
    //   292: invokeinterface 274 2 0
    //   297: astore 11
    //   299: aload 7
    //   301: astore 9
    //   303: aload 8
    //   305: iconst_1
    //   306: invokeinterface 219 2 0
    //   311: lstore 5
    //   313: aload 8
    //   315: astore 9
    //   317: aload_0
    //   318: aload 8
    //   320: iconst_2
    //   321: invokespecial 1092	com/google/android/gms/measurement/internal/zzq:zza	(Landroid/database/Cursor;I)Ljava/lang/Object;
    //   324: astore 12
    //   326: aload 8
    //   328: astore 9
    //   330: aload 8
    //   332: iconst_3
    //   333: invokeinterface 274 2 0
    //   338: astore_2
    //   339: aload 12
    //   341: ifnonnull +39 -> 380
    //   344: aload 8
    //   346: astore 9
    //   348: aload_0
    //   349: invokevirtual 231	com/google/android/gms/measurement/internal/zzco:zzgo	()Lcom/google/android/gms/measurement/internal/zzap;
    //   352: invokevirtual 237	com/google/android/gms/measurement/internal/zzap:zzjd	()Lcom/google/android/gms/measurement/internal/zzar;
    //   355: ldc_w 1094
    //   358: aload_1
    //   359: invokestatic 348	com/google/android/gms/measurement/internal/zzap:zzbv	(Ljava/lang/String;)Ljava/lang/Object;
    //   362: aload_2
    //   363: aload_3
    //   364: invokevirtual 359	com/google/android/gms/measurement/internal/zzar:zzd	(Ljava/lang/String;Ljava/lang/Object;Ljava/lang/Object;Ljava/lang/Object;)V
    //   367: goto +40 -> 407
    //   370: astore 7
    //   372: aload_2
    //   373: astore_3
    //   374: aload 7
    //   376: astore_2
    //   377: goto +126 -> 503
    //   380: aload 8
    //   382: astore 9
    //   384: aload 10
    //   386: new 865	com/google/android/gms/measurement/internal/zzfj
    //   389: dup
    //   390: aload_1
    //   391: aload_2
    //   392: aload 11
    //   394: lload 5
    //   396: aload 12
    //   398: invokespecial 1097	com/google/android/gms/measurement/internal/zzfj:<init>	(Ljava/lang/String;Ljava/lang/String;Ljava/lang/String;JLjava/lang/Object;)V
    //   401: invokeinterface 480 2 0
    //   406: pop
    //   407: aload 8
    //   409: astore 9
    //   411: aload 8
    //   413: invokeinterface 1066 1 0
    //   418: istore 4
    //   420: iload 4
    //   422: ifne +18 -> 440
    //   425: aload 8
    //   427: ifnull +10 -> 437
    //   430: aload 8
    //   432: invokeinterface 222 1 0
    //   437: aload 10
    //   439: areturn
    //   440: aload_2
    //   441: astore 7
    //   443: goto -201 -> 242
    //   446: astore_3
    //   447: goto +5 -> 452
    //   450: astore 7
    //   452: aload_2
    //   453: astore 7
    //   455: aload_3
    //   456: astore_2
    //   457: aload 7
    //   459: astore_3
    //   460: goto +43 -> 503
    //   463: astore_2
    //   464: aload 7
    //   466: astore_3
    //   467: goto +36 -> 503
    //   470: astore_1
    //   471: goto +74 -> 545
    //   474: astore_2
    //   475: aload 9
    //   477: astore_3
    //   478: goto +25 -> 503
    //   481: astore 7
    //   483: goto +12 -> 495
    //   486: astore_1
    //   487: aload 9
    //   489: astore_2
    //   490: goto +58 -> 548
    //   493: astore 7
    //   495: aconst_null
    //   496: astore 8
    //   498: aload_2
    //   499: astore_3
    //   500: aload 7
    //   502: astore_2
    //   503: aload 8
    //   505: astore 9
    //   507: aload_0
    //   508: invokevirtual 231	com/google/android/gms/measurement/internal/zzco:zzgo	()Lcom/google/android/gms/measurement/internal/zzap;
    //   511: invokevirtual 237	com/google/android/gms/measurement/internal/zzap:zzjd	()Lcom/google/android/gms/measurement/internal/zzar;
    //   514: ldc_w 1099
    //   517: aload_1
    //   518: invokestatic 348	com/google/android/gms/measurement/internal/zzap:zzbv	(Ljava/lang/String;)Ljava/lang/Object;
    //   521: aload_3
    //   522: aload_2
    //   523: invokevirtual 359	com/google/android/gms/measurement/internal/zzar:zzd	(Ljava/lang/String;Ljava/lang/Object;Ljava/lang/Object;Ljava/lang/Object;)V
    //   526: aload 8
    //   528: ifnull +10 -> 538
    //   531: aload 8
    //   533: invokeinterface 222 1 0
    //   538: aconst_null
    //   539: areturn
    //   540: astore_1
    //   541: aload 9
    //   543: astore 8
    //   545: aload 8
    //   547: astore_2
    //   548: aload_2
    //   549: ifnull +9 -> 558
    //   552: aload_2
    //   553: invokeinterface 222 1 0
    //   558: aload_1
    //   559: athrow
    //   560: astore 7
    //   562: goto -67 -> 495
    //   565: goto -477 -> 88
    // Exception table:
    //   from	to	target	type
    //   348	367	370	android/database/sqlite/SQLiteException
    //   384	407	446	android/database/sqlite/SQLiteException
    //   411	420	446	android/database/sqlite/SQLiteException
    //   317	326	463	android/database/sqlite/SQLiteException
    //   330	339	463	android/database/sqlite/SQLiteException
    //   213	222	470	finally
    //   246	259	470	finally
    //   263	282	470	finally
    //   289	299	470	finally
    //   303	313	470	finally
    //   213	222	474	android/database/sqlite/SQLiteException
    //   246	259	474	android/database/sqlite/SQLiteException
    //   263	282	474	android/database/sqlite/SQLiteException
    //   289	299	474	android/database/sqlite/SQLiteException
    //   303	313	474	android/database/sqlite/SQLiteException
    //   35	62	481	android/database/sqlite/SQLiteException
    //   25	35	486	finally
    //   35	62	486	finally
    //   67	85	486	finally
    //   91	125	486	finally
    //   125	209	486	finally
    //   25	35	493	android/database/sqlite/SQLiteException
    //   317	326	540	finally
    //   330	339	540	finally
    //   348	367	540	finally
    //   384	407	540	finally
    //   411	420	540	finally
    //   507	526	540	finally
    //   67	85	560	android/database/sqlite/SQLiteException
    //   91	125	560	android/database/sqlite/SQLiteException
    //   125	209	560	android/database/sqlite/SQLiteException
  }
  
  /* Error */
  public final List<zzl> zzb(String paramString, String[] paramArrayOfString)
  {
    // Byte code:
    //   0: aload_0
    //   1: invokevirtual 327	com/google/android/gms/measurement/internal/zzco:zzaf	()V
    //   4: aload_0
    //   5: invokevirtual 324	com/google/android/gms/measurement/internal/zzez:zzcl	()V
    //   8: new 460	java/util/ArrayList
    //   11: dup
    //   12: invokespecial 461	java/util/ArrayList:<init>	()V
    //   15: astore 12
    //   17: aload_0
    //   18: invokevirtual 203	com/google/android/gms/measurement/internal/zzq:getWritableDatabase	()Landroid/database/sqlite/SQLiteDatabase;
    //   21: ldc_w 983
    //   24: bipush 13
    //   26: anewarray 19	java/lang/String
    //   29: dup
    //   30: iconst_0
    //   31: ldc_w 381
    //   34: aastore
    //   35: dup
    //   36: iconst_1
    //   37: ldc 43
    //   39: aastore
    //   40: dup
    //   41: iconst_2
    //   42: ldc_w 781
    //   45: aastore
    //   46: dup
    //   47: iconst_3
    //   48: ldc_w 901
    //   51: aastore
    //   52: dup
    //   53: iconst_4
    //   54: ldc_w 936
    //   57: aastore
    //   58: dup
    //   59: iconst_5
    //   60: ldc_w 941
    //   63: aastore
    //   64: dup
    //   65: bipush 6
    //   67: ldc_w 946
    //   70: aastore
    //   71: dup
    //   72: bipush 7
    //   74: ldc_w 951
    //   77: aastore
    //   78: dup
    //   79: bipush 8
    //   81: ldc_w 960
    //   84: aastore
    //   85: dup
    //   86: bipush 9
    //   88: ldc_w 965
    //   91: aastore
    //   92: dup
    //   93: bipush 10
    //   95: ldc_w 970
    //   98: aastore
    //   99: dup
    //   100: bipush 11
    //   102: ldc_w 973
    //   105: aastore
    //   106: dup
    //   107: bipush 12
    //   109: ldc_w 978
    //   112: aastore
    //   113: aload_1
    //   114: aload_2
    //   115: aconst_null
    //   116: aconst_null
    //   117: ldc_w 1033
    //   120: ldc_w 1088
    //   123: invokevirtual 1036	android/database/sqlite/SQLiteDatabase:query	(Ljava/lang/String;[Ljava/lang/String;Ljava/lang/String;[Ljava/lang/String;Ljava/lang/String;Ljava/lang/String;Ljava/lang/String;Ljava/lang/String;)Landroid/database/Cursor;
    //   126: astore_2
    //   127: aload_2
    //   128: invokeinterface 215 1 0
    //   133: istore_3
    //   134: iload_3
    //   135: ifne +16 -> 151
    //   138: aload_2
    //   139: ifnull +9 -> 148
    //   142: aload_2
    //   143: invokeinterface 222 1 0
    //   148: aload 12
    //   150: areturn
    //   151: aload 12
    //   153: invokeinterface 466 1 0
    //   158: sipush 1000
    //   161: if_icmplt +25 -> 186
    //   164: aload_0
    //   165: invokevirtual 231	com/google/android/gms/measurement/internal/zzco:zzgo	()Lcom/google/android/gms/measurement/internal/zzap;
    //   168: invokevirtual 237	com/google/android/gms/measurement/internal/zzap:zzjd	()Lcom/google/android/gms/measurement/internal/zzar;
    //   171: ldc_w 1103
    //   174: sipush 1000
    //   177: invokestatic 262	java/lang/Integer:valueOf	(I)Ljava/lang/Integer;
    //   180: invokevirtual 266	com/google/android/gms/measurement/internal/zzar:zzg	(Ljava/lang/String;Ljava/lang/Object;)V
    //   183: goto +229 -> 412
    //   186: aload_2
    //   187: iconst_0
    //   188: invokeinterface 274 2 0
    //   193: astore_1
    //   194: aload_2
    //   195: iconst_1
    //   196: invokeinterface 274 2 0
    //   201: astore 13
    //   203: aload_2
    //   204: iconst_2
    //   205: invokeinterface 274 2 0
    //   210: astore 14
    //   212: aload_0
    //   213: aload_2
    //   214: iconst_3
    //   215: invokespecial 1092	com/google/android/gms/measurement/internal/zzq:zza	(Landroid/database/Cursor;I)Ljava/lang/Object;
    //   218: astore 15
    //   220: aload_2
    //   221: iconst_4
    //   222: invokeinterface 1056 2 0
    //   227: ifeq +273 -> 500
    //   230: iconst_1
    //   231: istore_3
    //   232: goto +3 -> 235
    //   235: aload_2
    //   236: iconst_5
    //   237: invokeinterface 274 2 0
    //   242: astore 16
    //   244: aload_2
    //   245: bipush 6
    //   247: invokeinterface 219 2 0
    //   252: lstore 4
    //   254: aload_0
    //   255: invokevirtual 562	com/google/android/gms/measurement/internal/zzey:zzjo	()Lcom/google/android/gms/measurement/internal/zzfg;
    //   258: aload_2
    //   259: bipush 7
    //   261: invokeinterface 607 2 0
    //   266: getstatic 1109	com/google/android/gms/measurement/internal/zzad:CREATOR	Landroid/os/Parcelable$Creator;
    //   269: invokevirtual 1112	com/google/android/gms/measurement/internal/zzfg:zza	([BLandroid/os/Parcelable$Creator;)Landroid/os/Parcelable;
    //   272: checkcast 1105	com/google/android/gms/measurement/internal/zzad
    //   275: astore 17
    //   277: aload_2
    //   278: bipush 8
    //   280: invokeinterface 219 2 0
    //   285: lstore 6
    //   287: aload_0
    //   288: invokevirtual 562	com/google/android/gms/measurement/internal/zzey:zzjo	()Lcom/google/android/gms/measurement/internal/zzfg;
    //   291: aload_2
    //   292: bipush 9
    //   294: invokeinterface 607 2 0
    //   299: getstatic 1109	com/google/android/gms/measurement/internal/zzad:CREATOR	Landroid/os/Parcelable$Creator;
    //   302: invokevirtual 1112	com/google/android/gms/measurement/internal/zzfg:zza	([BLandroid/os/Parcelable$Creator;)Landroid/os/Parcelable;
    //   305: checkcast 1105	com/google/android/gms/measurement/internal/zzad
    //   308: astore 18
    //   310: aload_2
    //   311: bipush 10
    //   313: invokeinterface 219 2 0
    //   318: lstore 8
    //   320: aload_2
    //   321: bipush 11
    //   323: invokeinterface 219 2 0
    //   328: lstore 10
    //   330: aload_0
    //   331: invokevirtual 562	com/google/android/gms/measurement/internal/zzey:zzjo	()Lcom/google/android/gms/measurement/internal/zzfg;
    //   334: aload_2
    //   335: bipush 12
    //   337: invokeinterface 607 2 0
    //   342: getstatic 1109	com/google/android/gms/measurement/internal/zzad:CREATOR	Landroid/os/Parcelable$Creator;
    //   345: invokevirtual 1112	com/google/android/gms/measurement/internal/zzfg:zza	([BLandroid/os/Parcelable$Creator;)Landroid/os/Parcelable;
    //   348: checkcast 1105	com/google/android/gms/measurement/internal/zzad
    //   351: astore 19
    //   353: aload 12
    //   355: new 915	com/google/android/gms/measurement/internal/zzl
    //   358: dup
    //   359: aload_1
    //   360: aload 13
    //   362: new 924	com/google/android/gms/measurement/internal/zzfh
    //   365: dup
    //   366: aload 14
    //   368: lload 8
    //   370: aload 15
    //   372: aload 13
    //   374: invokespecial 1115	com/google/android/gms/measurement/internal/zzfh:<init>	(Ljava/lang/String;JLjava/lang/Object;Ljava/lang/String;)V
    //   377: lload 6
    //   379: iload_3
    //   380: aload 16
    //   382: aload 17
    //   384: lload 4
    //   386: aload 18
    //   388: lload 10
    //   390: aload 19
    //   392: invokespecial 1118	com/google/android/gms/measurement/internal/zzl:<init>	(Ljava/lang/String;Ljava/lang/String;Lcom/google/android/gms/measurement/internal/zzfh;JZLjava/lang/String;Lcom/google/android/gms/measurement/internal/zzad;JLcom/google/android/gms/measurement/internal/zzad;JLcom/google/android/gms/measurement/internal/zzad;)V
    //   395: invokeinterface 480 2 0
    //   400: pop
    //   401: aload_2
    //   402: invokeinterface 1066 1 0
    //   407: istore_3
    //   408: iload_3
    //   409: ifne +16 -> 425
    //   412: aload_2
    //   413: ifnull +9 -> 422
    //   416: aload_2
    //   417: invokeinterface 222 1 0
    //   422: aload 12
    //   424: areturn
    //   425: goto -274 -> 151
    //   428: astore_1
    //   429: goto +59 -> 488
    //   432: astore 12
    //   434: aload_2
    //   435: astore_1
    //   436: aload 12
    //   438: astore_2
    //   439: goto +12 -> 451
    //   442: astore_1
    //   443: aconst_null
    //   444: astore_2
    //   445: goto +43 -> 488
    //   448: astore_2
    //   449: aconst_null
    //   450: astore_1
    //   451: aload_0
    //   452: invokevirtual 231	com/google/android/gms/measurement/internal/zzco:zzgo	()Lcom/google/android/gms/measurement/internal/zzap;
    //   455: invokevirtual 237	com/google/android/gms/measurement/internal/zzap:zzjd	()Lcom/google/android/gms/measurement/internal/zzar;
    //   458: ldc_w 1120
    //   461: aload_2
    //   462: invokevirtual 266	com/google/android/gms/measurement/internal/zzar:zzg	(Ljava/lang/String;Ljava/lang/Object;)V
    //   465: invokestatic 1042	java/util/Collections:emptyList	()Ljava/util/List;
    //   468: astore_2
    //   469: aload_1
    //   470: ifnull +9 -> 479
    //   473: aload_1
    //   474: invokeinterface 222 1 0
    //   479: aload_2
    //   480: areturn
    //   481: astore 12
    //   483: aload_1
    //   484: astore_2
    //   485: aload 12
    //   487: astore_1
    //   488: aload_2
    //   489: ifnull +9 -> 498
    //   492: aload_2
    //   493: invokeinterface 222 1 0
    //   498: aload_1
    //   499: athrow
    //   500: iconst_0
    //   501: istore_3
    //   502: goto -267 -> 235
    // Local variable table:
    //   start	length	slot	name	signature
    //   0	505	0	this	zzq
    //   0	505	1	paramString	String
    //   0	505	2	paramArrayOfString	String[]
    //   133	369	3	bool	boolean
    //   252	133	4	l1	long
    //   285	93	6	l2	long
    //   318	51	8	l3	long
    //   328	61	10	l4	long
    //   15	408	12	localArrayList	ArrayList
    //   432	5	12	localSQLiteException	SQLiteException
    //   481	5	12	localObject1	Object
    //   201	172	13	str1	String
    //   210	157	14	str2	String
    //   218	153	15	localObject2	Object
    //   242	139	16	str3	String
    //   275	108	17	localZzad1	zzad
    //   308	79	18	localZzad2	zzad
    //   351	40	19	localZzad3	zzad
    // Exception table:
    //   from	to	target	type
    //   127	134	428	finally
    //   151	183	428	finally
    //   186	230	428	finally
    //   235	408	428	finally
    //   127	134	432	android/database/sqlite/SQLiteException
    //   151	183	432	android/database/sqlite/SQLiteException
    //   186	230	432	android/database/sqlite/SQLiteException
    //   235	408	432	android/database/sqlite/SQLiteException
    //   17	127	442	finally
    //   17	127	448	android/database/sqlite/SQLiteException
    //   451	469	481	finally
  }
  
  /* Error */
  @WorkerThread
  public final List<zzfj> zzbk(String paramString)
  {
    // Byte code:
    //   0: aload_1
    //   1: invokestatic 297	com/google/android/gms/common/internal/Preconditions:checkNotEmpty	(Ljava/lang/String;)Ljava/lang/String;
    //   4: pop
    //   5: aload_0
    //   6: invokevirtual 327	com/google/android/gms/measurement/internal/zzco:zzaf	()V
    //   9: aload_0
    //   10: invokevirtual 324	com/google/android/gms/measurement/internal/zzez:zzcl	()V
    //   13: new 460	java/util/ArrayList
    //   16: dup
    //   17: invokespecial 461	java/util/ArrayList:<init>	()V
    //   20: astore 8
    //   22: aload_0
    //   23: invokevirtual 203	com/google/android/gms/measurement/internal/zzq:getWritableDatabase	()Landroid/database/sqlite/SQLiteDatabase;
    //   26: ldc_w 908
    //   29: iconst_4
    //   30: anewarray 19	java/lang/String
    //   33: dup
    //   34: iconst_0
    //   35: ldc_w 781
    //   38: aastore
    //   39: dup
    //   40: iconst_1
    //   41: ldc 43
    //   43: aastore
    //   44: dup
    //   45: iconst_2
    //   46: ldc_w 896
    //   49: aastore
    //   50: dup
    //   51: iconst_3
    //   52: ldc_w 901
    //   55: aastore
    //   56: ldc_w 638
    //   59: iconst_1
    //   60: anewarray 19	java/lang/String
    //   63: dup
    //   64: iconst_0
    //   65: aload_1
    //   66: aastore
    //   67: aconst_null
    //   68: aconst_null
    //   69: ldc_w 1033
    //   72: ldc_w 1125
    //   75: invokevirtual 1036	android/database/sqlite/SQLiteDatabase:query	(Ljava/lang/String;[Ljava/lang/String;Ljava/lang/String;[Ljava/lang/String;Ljava/lang/String;Ljava/lang/String;Ljava/lang/String;Ljava/lang/String;)Landroid/database/Cursor;
    //   78: astore 5
    //   80: aload 5
    //   82: invokeinterface 215 1 0
    //   87: istore_2
    //   88: iload_2
    //   89: ifne +18 -> 107
    //   92: aload 5
    //   94: ifnull +10 -> 104
    //   97: aload 5
    //   99: invokeinterface 222 1 0
    //   104: aload 8
    //   106: areturn
    //   107: aload 5
    //   109: iconst_0
    //   110: invokeinterface 274 2 0
    //   115: astore 9
    //   117: aload 5
    //   119: iconst_1
    //   120: invokeinterface 274 2 0
    //   125: astore 6
    //   127: aload 6
    //   129: astore 7
    //   131: aload 6
    //   133: ifnonnull +8 -> 141
    //   136: ldc_w 1127
    //   139: astore 7
    //   141: aload 5
    //   143: iconst_2
    //   144: invokeinterface 219 2 0
    //   149: lstore_3
    //   150: aload 5
    //   152: astore 6
    //   154: aload_0
    //   155: aload 5
    //   157: iconst_3
    //   158: invokespecial 1092	com/google/android/gms/measurement/internal/zzq:zza	(Landroid/database/Cursor;I)Ljava/lang/Object;
    //   161: astore 10
    //   163: aload 10
    //   165: ifnonnull +27 -> 192
    //   168: aload 5
    //   170: astore 6
    //   172: aload_0
    //   173: invokevirtual 231	com/google/android/gms/measurement/internal/zzco:zzgo	()Lcom/google/android/gms/measurement/internal/zzap;
    //   176: invokevirtual 237	com/google/android/gms/measurement/internal/zzap:zzjd	()Lcom/google/android/gms/measurement/internal/zzar;
    //   179: ldc_w 1129
    //   182: aload_1
    //   183: invokestatic 348	com/google/android/gms/measurement/internal/zzap:zzbv	(Ljava/lang/String;)Ljava/lang/Object;
    //   186: invokevirtual 266	com/google/android/gms/measurement/internal/zzar:zzg	(Ljava/lang/String;Ljava/lang/Object;)V
    //   189: goto +30 -> 219
    //   192: aload 5
    //   194: astore 6
    //   196: aload 8
    //   198: new 865	com/google/android/gms/measurement/internal/zzfj
    //   201: dup
    //   202: aload_1
    //   203: aload 7
    //   205: aload 9
    //   207: lload_3
    //   208: aload 10
    //   210: invokespecial 1097	com/google/android/gms/measurement/internal/zzfj:<init>	(Ljava/lang/String;Ljava/lang/String;Ljava/lang/String;JLjava/lang/Object;)V
    //   213: invokeinterface 480 2 0
    //   218: pop
    //   219: aload 5
    //   221: astore 6
    //   223: aload 5
    //   225: invokeinterface 1066 1 0
    //   230: istore_2
    //   231: iload_2
    //   232: ifne -125 -> 107
    //   235: aload 5
    //   237: ifnull +10 -> 247
    //   240: aload 5
    //   242: invokeinterface 222 1 0
    //   247: aload 8
    //   249: areturn
    //   250: astore 7
    //   252: goto +24 -> 276
    //   255: astore_1
    //   256: goto +62 -> 318
    //   259: astore 7
    //   261: goto +15 -> 276
    //   264: astore_1
    //   265: aconst_null
    //   266: astore 5
    //   268: goto +50 -> 318
    //   271: astore 7
    //   273: aconst_null
    //   274: astore 5
    //   276: aload 5
    //   278: astore 6
    //   280: aload_0
    //   281: invokevirtual 231	com/google/android/gms/measurement/internal/zzco:zzgo	()Lcom/google/android/gms/measurement/internal/zzap;
    //   284: invokevirtual 237	com/google/android/gms/measurement/internal/zzap:zzjd	()Lcom/google/android/gms/measurement/internal/zzar;
    //   287: ldc_w 1131
    //   290: aload_1
    //   291: invokestatic 348	com/google/android/gms/measurement/internal/zzap:zzbv	(Ljava/lang/String;)Ljava/lang/Object;
    //   294: aload 7
    //   296: invokevirtual 245	com/google/android/gms/measurement/internal/zzar:zze	(Ljava/lang/String;Ljava/lang/Object;Ljava/lang/Object;)V
    //   299: aload 5
    //   301: ifnull +10 -> 311
    //   304: aload 5
    //   306: invokeinterface 222 1 0
    //   311: aconst_null
    //   312: areturn
    //   313: astore_1
    //   314: aload 6
    //   316: astore 5
    //   318: aload 5
    //   320: ifnull +10 -> 330
    //   323: aload 5
    //   325: invokeinterface 222 1 0
    //   330: aload_1
    //   331: athrow
    // Local variable table:
    //   start	length	slot	name	signature
    //   0	332	0	this	zzq
    //   0	332	1	paramString	String
    //   87	145	2	bool	boolean
    //   149	59	3	l	long
    //   78	246	5	localObject1	Object
    //   125	190	6	localObject2	Object
    //   129	75	7	localObject3	Object
    //   250	1	7	localSQLiteException1	SQLiteException
    //   259	1	7	localSQLiteException2	SQLiteException
    //   271	24	7	localSQLiteException3	SQLiteException
    //   20	228	8	localArrayList	ArrayList
    //   115	91	9	str	String
    //   161	48	10	localObject4	Object
    // Exception table:
    //   from	to	target	type
    //   154	163	250	android/database/sqlite/SQLiteException
    //   172	189	250	android/database/sqlite/SQLiteException
    //   196	219	250	android/database/sqlite/SQLiteException
    //   223	231	250	android/database/sqlite/SQLiteException
    //   80	88	255	finally
    //   107	127	255	finally
    //   141	150	255	finally
    //   80	88	259	android/database/sqlite/SQLiteException
    //   107	127	259	android/database/sqlite/SQLiteException
    //   141	150	259	android/database/sqlite/SQLiteException
    //   22	80	264	finally
    //   22	80	271	android/database/sqlite/SQLiteException
    //   154	163	313	finally
    //   172	189	313	finally
    //   196	219	313	finally
    //   223	231	313	finally
    //   280	299	313	finally
  }
  
  /* Error */
  @WorkerThread
  public final zzg zzbl(String paramString)
  {
    // Byte code:
    //   0: aload_1
    //   1: invokestatic 297	com/google/android/gms/common/internal/Preconditions:checkNotEmpty	(Ljava/lang/String;)Ljava/lang/String;
    //   4: pop
    //   5: aload_0
    //   6: invokevirtual 327	com/google/android/gms/measurement/internal/zzco:zzaf	()V
    //   9: aload_0
    //   10: invokevirtual 324	com/google/android/gms/measurement/internal/zzez:zzcl	()V
    //   13: aload_0
    //   14: invokevirtual 203	com/google/android/gms/measurement/internal/zzq:getWritableDatabase	()Landroid/database/sqlite/SQLiteDatabase;
    //   17: astore 6
    //   19: iconst_0
    //   20: istore_3
    //   21: aload 6
    //   23: ldc_w 636
    //   26: bipush 26
    //   28: anewarray 19	java/lang/String
    //   31: dup
    //   32: iconst_0
    //   33: ldc_w 674
    //   36: aastore
    //   37: dup
    //   38: iconst_1
    //   39: ldc_w 679
    //   42: aastore
    //   43: dup
    //   44: iconst_2
    //   45: ldc_w 684
    //   48: aastore
    //   49: dup
    //   50: iconst_3
    //   51: ldc_w 689
    //   54: aastore
    //   55: dup
    //   56: iconst_4
    //   57: ldc 69
    //   59: aastore
    //   60: dup
    //   61: iconst_5
    //   62: ldc_w 698
    //   65: aastore
    //   66: dup
    //   67: bipush 6
    //   69: ldc 49
    //   71: aastore
    //   72: dup
    //   73: bipush 7
    //   75: ldc 53
    //   77: aastore
    //   78: dup
    //   79: bipush 8
    //   81: ldc 57
    //   83: aastore
    //   84: dup
    //   85: bipush 9
    //   87: ldc 61
    //   89: aastore
    //   90: dup
    //   91: bipush 10
    //   93: ldc 65
    //   95: aastore
    //   96: dup
    //   97: bipush 11
    //   99: ldc 73
    //   101: aastore
    //   102: dup
    //   103: bipush 12
    //   105: ldc 77
    //   107: aastore
    //   108: dup
    //   109: bipush 13
    //   111: ldc 81
    //   113: aastore
    //   114: dup
    //   115: bipush 14
    //   117: ldc 85
    //   119: aastore
    //   120: dup
    //   121: bipush 15
    //   123: ldc 93
    //   125: aastore
    //   126: dup
    //   127: bipush 16
    //   129: ldc 97
    //   131: aastore
    //   132: dup
    //   133: bipush 17
    //   135: ldc 101
    //   137: aastore
    //   138: dup
    //   139: bipush 18
    //   141: ldc 105
    //   143: aastore
    //   144: dup
    //   145: bipush 19
    //   147: ldc 109
    //   149: aastore
    //   150: dup
    //   151: bipush 20
    //   153: ldc 113
    //   155: aastore
    //   156: dup
    //   157: bipush 21
    //   159: ldc 117
    //   161: aastore
    //   162: dup
    //   163: bipush 22
    //   165: ldc 121
    //   167: aastore
    //   168: dup
    //   169: bipush 23
    //   171: ldc 125
    //   173: aastore
    //   174: dup
    //   175: bipush 24
    //   177: ldc -127
    //   179: aastore
    //   180: dup
    //   181: bipush 25
    //   183: ldc -123
    //   185: aastore
    //   186: ldc_w 638
    //   189: iconst_1
    //   190: anewarray 19	java/lang/String
    //   193: dup
    //   194: iconst_0
    //   195: aload_1
    //   196: aastore
    //   197: aconst_null
    //   198: aconst_null
    //   199: aconst_null
    //   200: invokevirtual 642	android/database/sqlite/SQLiteDatabase:query	(Ljava/lang/String;[Ljava/lang/String;Ljava/lang/String;[Ljava/lang/String;Ljava/lang/String;Ljava/lang/String;Ljava/lang/String;)Landroid/database/Cursor;
    //   203: astore 6
    //   205: aload 6
    //   207: invokeinterface 215 1 0
    //   212: istore_2
    //   213: iload_2
    //   214: ifne +17 -> 231
    //   217: aload 6
    //   219: ifnull +10 -> 229
    //   222: aload 6
    //   224: invokeinterface 222 1 0
    //   229: aconst_null
    //   230: areturn
    //   231: aload 6
    //   233: astore 7
    //   235: new 669	com/google/android/gms/measurement/internal/zzg
    //   238: dup
    //   239: aload_0
    //   240: getfield 1138	com/google/android/gms/measurement/internal/zzq:zzamz	Lcom/google/android/gms/measurement/internal/zzfa;
    //   243: invokevirtual 1144	com/google/android/gms/measurement/internal/zzfa:zzmb	()Lcom/google/android/gms/measurement/internal/zzbt;
    //   246: aload_1
    //   247: invokespecial 1147	com/google/android/gms/measurement/internal/zzg:<init>	(Lcom/google/android/gms/measurement/internal/zzbt;Ljava/lang/String;)V
    //   250: astore 8
    //   252: aload 6
    //   254: astore 7
    //   256: aload 8
    //   258: aload 6
    //   260: iconst_0
    //   261: invokeinterface 274 2 0
    //   266: invokevirtual 1150	com/google/android/gms/measurement/internal/zzg:zzam	(Ljava/lang/String;)V
    //   269: aload 6
    //   271: astore 7
    //   273: aload 8
    //   275: aload 6
    //   277: iconst_1
    //   278: invokeinterface 274 2 0
    //   283: invokevirtual 1153	com/google/android/gms/measurement/internal/zzg:zzan	(Ljava/lang/String;)V
    //   286: aload 6
    //   288: astore 7
    //   290: aload 8
    //   292: aload 6
    //   294: iconst_2
    //   295: invokeinterface 274 2 0
    //   300: invokevirtual 1156	com/google/android/gms/measurement/internal/zzg:zzap	(Ljava/lang/String;)V
    //   303: aload 6
    //   305: astore 7
    //   307: aload 8
    //   309: aload 6
    //   311: iconst_3
    //   312: invokeinterface 219 2 0
    //   317: invokevirtual 1160	com/google/android/gms/measurement/internal/zzg:zzx	(J)V
    //   320: aload 6
    //   322: astore 7
    //   324: aload 8
    //   326: aload 6
    //   328: iconst_4
    //   329: invokeinterface 219 2 0
    //   334: invokevirtual 1163	com/google/android/gms/measurement/internal/zzg:zzs	(J)V
    //   337: aload 6
    //   339: astore 7
    //   341: aload 8
    //   343: aload 6
    //   345: iconst_5
    //   346: invokeinterface 219 2 0
    //   351: invokevirtual 1166	com/google/android/gms/measurement/internal/zzg:zzt	(J)V
    //   354: aload 6
    //   356: astore 7
    //   358: aload 8
    //   360: aload 6
    //   362: bipush 6
    //   364: invokeinterface 274 2 0
    //   369: invokevirtual 1169	com/google/android/gms/measurement/internal/zzg:setAppVersion	(Ljava/lang/String;)V
    //   372: aload 6
    //   374: astore 7
    //   376: aload 8
    //   378: aload 6
    //   380: bipush 7
    //   382: invokeinterface 274 2 0
    //   387: invokevirtual 1172	com/google/android/gms/measurement/internal/zzg:zzar	(Ljava/lang/String;)V
    //   390: aload 6
    //   392: astore 7
    //   394: aload 8
    //   396: aload 6
    //   398: bipush 8
    //   400: invokeinterface 219 2 0
    //   405: invokevirtual 1175	com/google/android/gms/measurement/internal/zzg:zzv	(J)V
    //   408: aload 6
    //   410: astore 7
    //   412: aload 8
    //   414: aload 6
    //   416: bipush 9
    //   418: invokeinterface 219 2 0
    //   423: invokevirtual 1178	com/google/android/gms/measurement/internal/zzg:zzw	(J)V
    //   426: aload 6
    //   428: astore 7
    //   430: aload 6
    //   432: bipush 10
    //   434: invokeinterface 1053 2 0
    //   439: ifne +567 -> 1006
    //   442: aload 6
    //   444: astore 7
    //   446: aload 6
    //   448: bipush 10
    //   450: invokeinterface 1056 2 0
    //   455: ifeq +546 -> 1001
    //   458: goto +548 -> 1006
    //   461: aload 6
    //   463: astore 7
    //   465: aload 8
    //   467: iload_2
    //   468: invokevirtual 1181	com/google/android/gms/measurement/internal/zzg:setMeasurementEnabled	(Z)V
    //   471: aload 6
    //   473: astore 7
    //   475: aload 8
    //   477: aload 6
    //   479: bipush 11
    //   481: invokeinterface 219 2 0
    //   486: invokevirtual 1184	com/google/android/gms/measurement/internal/zzg:zzaa	(J)V
    //   489: aload 6
    //   491: astore 7
    //   493: aload 8
    //   495: aload 6
    //   497: bipush 12
    //   499: invokeinterface 219 2 0
    //   504: invokevirtual 1187	com/google/android/gms/measurement/internal/zzg:zzab	(J)V
    //   507: aload 6
    //   509: astore 7
    //   511: aload 8
    //   513: aload 6
    //   515: bipush 13
    //   517: invokeinterface 219 2 0
    //   522: invokevirtual 1190	com/google/android/gms/measurement/internal/zzg:zzac	(J)V
    //   525: aload 6
    //   527: astore 7
    //   529: aload 8
    //   531: aload 6
    //   533: bipush 14
    //   535: invokeinterface 219 2 0
    //   540: invokevirtual 1193	com/google/android/gms/measurement/internal/zzg:zzad	(J)V
    //   543: aload 6
    //   545: astore 7
    //   547: aload 8
    //   549: aload 6
    //   551: bipush 15
    //   553: invokeinterface 219 2 0
    //   558: invokevirtual 1196	com/google/android/gms/measurement/internal/zzg:zzy	(J)V
    //   561: aload 6
    //   563: astore 7
    //   565: aload 8
    //   567: aload 6
    //   569: bipush 16
    //   571: invokeinterface 219 2 0
    //   576: invokevirtual 1199	com/google/android/gms/measurement/internal/zzg:zzz	(J)V
    //   579: aload 6
    //   581: astore 7
    //   583: aload 6
    //   585: bipush 17
    //   587: invokeinterface 1053 2 0
    //   592: ifeq +11 -> 603
    //   595: ldc2_w 1200
    //   598: lstore 4
    //   600: goto +19 -> 619
    //   603: aload 6
    //   605: astore 7
    //   607: aload 6
    //   609: bipush 17
    //   611: invokeinterface 1056 2 0
    //   616: i2l
    //   617: lstore 4
    //   619: aload 6
    //   621: astore 7
    //   623: aload 8
    //   625: lload 4
    //   627: invokevirtual 1204	com/google/android/gms/measurement/internal/zzg:zzu	(J)V
    //   630: aload 6
    //   632: astore 7
    //   634: aload 8
    //   636: aload 6
    //   638: bipush 18
    //   640: invokeinterface 274 2 0
    //   645: invokevirtual 1207	com/google/android/gms/measurement/internal/zzg:zzaq	(Ljava/lang/String;)V
    //   648: aload 6
    //   650: astore 7
    //   652: aload 8
    //   654: aload 6
    //   656: bipush 19
    //   658: invokeinterface 219 2 0
    //   663: invokevirtual 1209	com/google/android/gms/measurement/internal/zzg:zzaf	(J)V
    //   666: aload 6
    //   668: astore 7
    //   670: aload 8
    //   672: aload 6
    //   674: bipush 20
    //   676: invokeinterface 219 2 0
    //   681: invokevirtual 1212	com/google/android/gms/measurement/internal/zzg:zzae	(J)V
    //   684: aload 6
    //   686: astore 7
    //   688: aload 8
    //   690: aload 6
    //   692: bipush 21
    //   694: invokeinterface 274 2 0
    //   699: invokevirtual 1215	com/google/android/gms/measurement/internal/zzg:zzas	(Ljava/lang/String;)V
    //   702: aload 6
    //   704: astore 7
    //   706: aload 6
    //   708: bipush 22
    //   710: invokeinterface 1053 2 0
    //   715: ifeq +9 -> 724
    //   718: lconst_0
    //   719: lstore 4
    //   721: goto +18 -> 739
    //   724: aload 6
    //   726: astore 7
    //   728: aload 6
    //   730: bipush 22
    //   732: invokeinterface 219 2 0
    //   737: lstore 4
    //   739: aload 6
    //   741: astore 7
    //   743: aload 8
    //   745: lload 4
    //   747: invokevirtual 1218	com/google/android/gms/measurement/internal/zzg:zzag	(J)V
    //   750: aload 6
    //   752: astore 7
    //   754: aload 6
    //   756: bipush 23
    //   758: invokeinterface 1053 2 0
    //   763: ifne +253 -> 1016
    //   766: aload 6
    //   768: astore 7
    //   770: aload 6
    //   772: bipush 23
    //   774: invokeinterface 1056 2 0
    //   779: ifeq +232 -> 1011
    //   782: goto +234 -> 1016
    //   785: aload 6
    //   787: astore 7
    //   789: aload 8
    //   791: iload_2
    //   792: invokevirtual 1220	com/google/android/gms/measurement/internal/zzg:zze	(Z)V
    //   795: aload 6
    //   797: astore 7
    //   799: aload 6
    //   801: bipush 24
    //   803: invokeinterface 1053 2 0
    //   808: ifne +213 -> 1021
    //   811: iload_3
    //   812: istore_2
    //   813: aload 6
    //   815: astore 7
    //   817: aload 6
    //   819: bipush 24
    //   821: invokeinterface 1056 2 0
    //   826: ifeq +6 -> 832
    //   829: goto +192 -> 1021
    //   832: aload 6
    //   834: astore 7
    //   836: aload 8
    //   838: iload_2
    //   839: invokevirtual 1223	com/google/android/gms/measurement/internal/zzg:zzf	(Z)V
    //   842: aload 6
    //   844: astore 7
    //   846: aload 8
    //   848: aload 6
    //   850: bipush 25
    //   852: invokeinterface 274 2 0
    //   857: invokevirtual 1226	com/google/android/gms/measurement/internal/zzg:zzao	(Ljava/lang/String;)V
    //   860: aload 6
    //   862: astore 7
    //   864: aload 8
    //   866: invokevirtual 1229	com/google/android/gms/measurement/internal/zzg:zzgv	()V
    //   869: aload 6
    //   871: astore 7
    //   873: aload 6
    //   875: invokeinterface 1066 1 0
    //   880: ifeq +24 -> 904
    //   883: aload 6
    //   885: astore 7
    //   887: aload_0
    //   888: invokevirtual 231	com/google/android/gms/measurement/internal/zzco:zzgo	()Lcom/google/android/gms/measurement/internal/zzap;
    //   891: invokevirtual 237	com/google/android/gms/measurement/internal/zzap:zzjd	()Lcom/google/android/gms/measurement/internal/zzar;
    //   894: ldc_w 1231
    //   897: aload_1
    //   898: invokestatic 348	com/google/android/gms/measurement/internal/zzap:zzbv	(Ljava/lang/String;)Ljava/lang/Object;
    //   901: invokevirtual 266	com/google/android/gms/measurement/internal/zzar:zzg	(Ljava/lang/String;Ljava/lang/Object;)V
    //   904: aload 6
    //   906: ifnull +10 -> 916
    //   909: aload 6
    //   911: invokeinterface 222 1 0
    //   916: aload 8
    //   918: areturn
    //   919: astore 8
    //   921: goto +24 -> 945
    //   924: astore_1
    //   925: goto +62 -> 987
    //   928: astore 8
    //   930: goto +15 -> 945
    //   933: astore_1
    //   934: aconst_null
    //   935: astore 6
    //   937: goto +50 -> 987
    //   940: astore 8
    //   942: aconst_null
    //   943: astore 6
    //   945: aload 6
    //   947: astore 7
    //   949: aload_0
    //   950: invokevirtual 231	com/google/android/gms/measurement/internal/zzco:zzgo	()Lcom/google/android/gms/measurement/internal/zzap;
    //   953: invokevirtual 237	com/google/android/gms/measurement/internal/zzap:zzjd	()Lcom/google/android/gms/measurement/internal/zzar;
    //   956: ldc_w 1233
    //   959: aload_1
    //   960: invokestatic 348	com/google/android/gms/measurement/internal/zzap:zzbv	(Ljava/lang/String;)Ljava/lang/Object;
    //   963: aload 8
    //   965: invokevirtual 245	com/google/android/gms/measurement/internal/zzar:zze	(Ljava/lang/String;Ljava/lang/Object;Ljava/lang/Object;)V
    //   968: aload 6
    //   970: ifnull +10 -> 980
    //   973: aload 6
    //   975: invokeinterface 222 1 0
    //   980: aconst_null
    //   981: areturn
    //   982: astore_1
    //   983: aload 7
    //   985: astore 6
    //   987: aload 6
    //   989: ifnull +10 -> 999
    //   992: aload 6
    //   994: invokeinterface 222 1 0
    //   999: aload_1
    //   1000: athrow
    //   1001: iconst_0
    //   1002: istore_2
    //   1003: goto -542 -> 461
    //   1006: iconst_1
    //   1007: istore_2
    //   1008: goto -547 -> 461
    //   1011: iconst_0
    //   1012: istore_2
    //   1013: goto -228 -> 785
    //   1016: iconst_1
    //   1017: istore_2
    //   1018: goto -233 -> 785
    //   1021: iconst_1
    //   1022: istore_2
    //   1023: goto -191 -> 832
    // Local variable table:
    //   start	length	slot	name	signature
    //   0	1026	0	this	zzq
    //   0	1026	1	paramString	String
    //   212	811	2	bool1	boolean
    //   20	792	3	bool2	boolean
    //   598	148	4	l	long
    //   17	976	6	localObject1	Object
    //   233	751	7	localObject2	Object
    //   250	667	8	localZzg	zzg
    //   919	1	8	localSQLiteException1	SQLiteException
    //   928	1	8	localSQLiteException2	SQLiteException
    //   940	24	8	localSQLiteException3	SQLiteException
    // Exception table:
    //   from	to	target	type
    //   235	252	919	android/database/sqlite/SQLiteException
    //   256	269	919	android/database/sqlite/SQLiteException
    //   273	286	919	android/database/sqlite/SQLiteException
    //   290	303	919	android/database/sqlite/SQLiteException
    //   307	320	919	android/database/sqlite/SQLiteException
    //   324	337	919	android/database/sqlite/SQLiteException
    //   341	354	919	android/database/sqlite/SQLiteException
    //   358	372	919	android/database/sqlite/SQLiteException
    //   376	390	919	android/database/sqlite/SQLiteException
    //   394	408	919	android/database/sqlite/SQLiteException
    //   412	426	919	android/database/sqlite/SQLiteException
    //   430	442	919	android/database/sqlite/SQLiteException
    //   446	458	919	android/database/sqlite/SQLiteException
    //   465	471	919	android/database/sqlite/SQLiteException
    //   475	489	919	android/database/sqlite/SQLiteException
    //   493	507	919	android/database/sqlite/SQLiteException
    //   511	525	919	android/database/sqlite/SQLiteException
    //   529	543	919	android/database/sqlite/SQLiteException
    //   547	561	919	android/database/sqlite/SQLiteException
    //   565	579	919	android/database/sqlite/SQLiteException
    //   583	595	919	android/database/sqlite/SQLiteException
    //   607	619	919	android/database/sqlite/SQLiteException
    //   623	630	919	android/database/sqlite/SQLiteException
    //   634	648	919	android/database/sqlite/SQLiteException
    //   652	666	919	android/database/sqlite/SQLiteException
    //   670	684	919	android/database/sqlite/SQLiteException
    //   688	702	919	android/database/sqlite/SQLiteException
    //   706	718	919	android/database/sqlite/SQLiteException
    //   728	739	919	android/database/sqlite/SQLiteException
    //   743	750	919	android/database/sqlite/SQLiteException
    //   754	766	919	android/database/sqlite/SQLiteException
    //   770	782	919	android/database/sqlite/SQLiteException
    //   789	795	919	android/database/sqlite/SQLiteException
    //   799	811	919	android/database/sqlite/SQLiteException
    //   817	829	919	android/database/sqlite/SQLiteException
    //   836	842	919	android/database/sqlite/SQLiteException
    //   846	860	919	android/database/sqlite/SQLiteException
    //   864	869	919	android/database/sqlite/SQLiteException
    //   873	883	919	android/database/sqlite/SQLiteException
    //   887	904	919	android/database/sqlite/SQLiteException
    //   205	213	924	finally
    //   205	213	928	android/database/sqlite/SQLiteException
    //   13	19	933	finally
    //   21	205	933	finally
    //   13	19	940	android/database/sqlite/SQLiteException
    //   21	205	940	android/database/sqlite/SQLiteException
    //   235	252	982	finally
    //   256	269	982	finally
    //   273	286	982	finally
    //   290	303	982	finally
    //   307	320	982	finally
    //   324	337	982	finally
    //   341	354	982	finally
    //   358	372	982	finally
    //   376	390	982	finally
    //   394	408	982	finally
    //   412	426	982	finally
    //   430	442	982	finally
    //   446	458	982	finally
    //   465	471	982	finally
    //   475	489	982	finally
    //   493	507	982	finally
    //   511	525	982	finally
    //   529	543	982	finally
    //   547	561	982	finally
    //   565	579	982	finally
    //   583	595	982	finally
    //   607	619	982	finally
    //   623	630	982	finally
    //   634	648	982	finally
    //   652	666	982	finally
    //   670	684	982	finally
    //   688	702	982	finally
    //   706	718	982	finally
    //   728	739	982	finally
    //   743	750	982	finally
    //   754	766	982	finally
    //   770	782	982	finally
    //   789	795	982	finally
    //   799	811	982	finally
    //   817	829	982	finally
    //   836	842	982	finally
    //   846	860	982	finally
    //   864	869	982	finally
    //   873	883	982	finally
    //   887	904	982	finally
    //   949	968	982	finally
  }
  
  public final long zzbm(String paramString)
  {
    Preconditions.checkNotEmpty(paramString);
    zzaf();
    zzcl();
    try
    {
      int i = getWritableDatabase().delete("raw_events", "rowid in (select rowid from raw_events where app_id=? order by rowid desc limit -1 offset ?)", new String[] { paramString, String.valueOf(Math.max(0, Math.min(1000000, zzgq().zzb(paramString, zzaf.zzajs)))) });
      return i;
    }
    catch (SQLiteException localSQLiteException)
    {
      zzgo().zzjd().zze("Error deleting over the limit events. appId", zzap.zzbv(paramString), localSQLiteException);
    }
    return 0L;
  }
  
  /* Error */
  @WorkerThread
  public final byte[] zzbn(String paramString)
  {
    // Byte code:
    //   0: aload_1
    //   1: invokestatic 297	com/google/android/gms/common/internal/Preconditions:checkNotEmpty	(Ljava/lang/String;)Ljava/lang/String;
    //   4: pop
    //   5: aload_0
    //   6: invokevirtual 327	com/google/android/gms/measurement/internal/zzco:zzaf	()V
    //   9: aload_0
    //   10: invokevirtual 324	com/google/android/gms/measurement/internal/zzez:zzcl	()V
    //   13: aload_0
    //   14: invokevirtual 203	com/google/android/gms/measurement/internal/zzq:getWritableDatabase	()Landroid/database/sqlite/SQLiteDatabase;
    //   17: ldc_w 636
    //   20: iconst_1
    //   21: anewarray 19	java/lang/String
    //   24: dup
    //   25: iconst_0
    //   26: ldc 89
    //   28: aastore
    //   29: ldc_w 638
    //   32: iconst_1
    //   33: anewarray 19	java/lang/String
    //   36: dup
    //   37: iconst_0
    //   38: aload_1
    //   39: aastore
    //   40: aconst_null
    //   41: aconst_null
    //   42: aconst_null
    //   43: invokevirtual 642	android/database/sqlite/SQLiteDatabase:query	(Ljava/lang/String;[Ljava/lang/String;Ljava/lang/String;[Ljava/lang/String;Ljava/lang/String;Ljava/lang/String;Ljava/lang/String;)Landroid/database/Cursor;
    //   46: astore 4
    //   48: aload 4
    //   50: astore_3
    //   51: aload 4
    //   53: invokeinterface 215 1 0
    //   58: istore_2
    //   59: iload_2
    //   60: ifne +17 -> 77
    //   63: aload 4
    //   65: ifnull +10 -> 75
    //   68: aload 4
    //   70: invokeinterface 222 1 0
    //   75: aconst_null
    //   76: areturn
    //   77: aload 4
    //   79: astore_3
    //   80: aload 4
    //   82: iconst_0
    //   83: invokeinterface 607 2 0
    //   88: astore 5
    //   90: aload 4
    //   92: astore_3
    //   93: aload 4
    //   95: invokeinterface 1066 1 0
    //   100: ifeq +23 -> 123
    //   103: aload 4
    //   105: astore_3
    //   106: aload_0
    //   107: invokevirtual 231	com/google/android/gms/measurement/internal/zzco:zzgo	()Lcom/google/android/gms/measurement/internal/zzap;
    //   110: invokevirtual 237	com/google/android/gms/measurement/internal/zzap:zzjd	()Lcom/google/android/gms/measurement/internal/zzar;
    //   113: ldc_w 1249
    //   116: aload_1
    //   117: invokestatic 348	com/google/android/gms/measurement/internal/zzap:zzbv	(Ljava/lang/String;)Ljava/lang/Object;
    //   120: invokevirtual 266	com/google/android/gms/measurement/internal/zzar:zzg	(Ljava/lang/String;Ljava/lang/Object;)V
    //   123: aload 4
    //   125: ifnull +10 -> 135
    //   128: aload 4
    //   130: invokeinterface 222 1 0
    //   135: aload 5
    //   137: areturn
    //   138: astore 5
    //   140: goto +14 -> 154
    //   143: astore_1
    //   144: aconst_null
    //   145: astore_3
    //   146: goto +45 -> 191
    //   149: astore 5
    //   151: aconst_null
    //   152: astore 4
    //   154: aload 4
    //   156: astore_3
    //   157: aload_0
    //   158: invokevirtual 231	com/google/android/gms/measurement/internal/zzco:zzgo	()Lcom/google/android/gms/measurement/internal/zzap;
    //   161: invokevirtual 237	com/google/android/gms/measurement/internal/zzap:zzjd	()Lcom/google/android/gms/measurement/internal/zzar;
    //   164: ldc_w 1251
    //   167: aload_1
    //   168: invokestatic 348	com/google/android/gms/measurement/internal/zzap:zzbv	(Ljava/lang/String;)Ljava/lang/Object;
    //   171: aload 5
    //   173: invokevirtual 245	com/google/android/gms/measurement/internal/zzar:zze	(Ljava/lang/String;Ljava/lang/Object;Ljava/lang/Object;)V
    //   176: aload 4
    //   178: ifnull +10 -> 188
    //   181: aload 4
    //   183: invokeinterface 222 1 0
    //   188: aconst_null
    //   189: areturn
    //   190: astore_1
    //   191: aload_3
    //   192: ifnull +9 -> 201
    //   195: aload_3
    //   196: invokeinterface 222 1 0
    //   201: aload_1
    //   202: athrow
    // Local variable table:
    //   start	length	slot	name	signature
    //   0	203	0	this	zzq
    //   0	203	1	paramString	String
    //   58	2	2	bool	boolean
    //   50	146	3	localCursor1	Cursor
    //   46	136	4	localCursor2	Cursor
    //   88	48	5	arrayOfByte	byte[]
    //   138	1	5	localSQLiteException1	SQLiteException
    //   149	23	5	localSQLiteException2	SQLiteException
    // Exception table:
    //   from	to	target	type
    //   51	59	138	android/database/sqlite/SQLiteException
    //   80	90	138	android/database/sqlite/SQLiteException
    //   93	103	138	android/database/sqlite/SQLiteException
    //   106	123	138	android/database/sqlite/SQLiteException
    //   13	48	143	finally
    //   13	48	149	android/database/sqlite/SQLiteException
    //   51	59	190	finally
    //   80	90	190	finally
    //   93	103	190	finally
    //   106	123	190	finally
    //   157	176	190	finally
  }
  
  /* Error */
  final java.util.Map<Integer, com.google.android.gms.internal.measurement.zzgj> zzbo(String paramString)
  {
    // Byte code:
    //   0: aload_0
    //   1: invokevirtual 324	com/google/android/gms/measurement/internal/zzez:zzcl	()V
    //   4: aload_0
    //   5: invokevirtual 327	com/google/android/gms/measurement/internal/zzco:zzaf	()V
    //   8: aload_1
    //   9: invokestatic 297	com/google/android/gms/common/internal/Preconditions:checkNotEmpty	(Ljava/lang/String;)Ljava/lang/String;
    //   12: pop
    //   13: aload_0
    //   14: invokevirtual 203	com/google/android/gms/measurement/internal/zzq:getWritableDatabase	()Landroid/database/sqlite/SQLiteDatabase;
    //   17: astore 4
    //   19: aload 4
    //   21: ldc_w 511
    //   24: iconst_2
    //   25: anewarray 19	java/lang/String
    //   28: dup
    //   29: iconst_0
    //   30: ldc_w 383
    //   33: aastore
    //   34: dup
    //   35: iconst_1
    //   36: ldc_w 1255
    //   39: aastore
    //   40: ldc_w 638
    //   43: iconst_1
    //   44: anewarray 19	java/lang/String
    //   47: dup
    //   48: iconst_0
    //   49: aload_1
    //   50: aastore
    //   51: aconst_null
    //   52: aconst_null
    //   53: aconst_null
    //   54: invokevirtual 642	android/database/sqlite/SQLiteDatabase:query	(Ljava/lang/String;[Ljava/lang/String;Ljava/lang/String;[Ljava/lang/String;Ljava/lang/String;Ljava/lang/String;Ljava/lang/String;)Landroid/database/Cursor;
    //   57: astore 5
    //   59: aload 5
    //   61: astore 4
    //   63: aload 5
    //   65: invokeinterface 215 1 0
    //   70: istore_3
    //   71: iload_3
    //   72: ifne +17 -> 89
    //   75: aload 5
    //   77: ifnull +10 -> 87
    //   80: aload 5
    //   82: invokeinterface 222 1 0
    //   87: aconst_null
    //   88: areturn
    //   89: aload 5
    //   91: astore 4
    //   93: new 1257	android/support/v4/util/ArrayMap
    //   96: dup
    //   97: invokespecial 1258	android/support/v4/util/ArrayMap:<init>	()V
    //   100: astore 6
    //   102: aload 5
    //   104: astore 4
    //   106: aload 5
    //   108: iconst_0
    //   109: invokeinterface 1056 2 0
    //   114: istore_2
    //   115: aload 5
    //   117: astore 4
    //   119: aload 5
    //   121: iconst_1
    //   122: invokeinterface 607 2 0
    //   127: astore 7
    //   129: aload 5
    //   131: astore 4
    //   133: aload 7
    //   135: iconst_0
    //   136: aload 7
    //   138: arraylength
    //   139: invokestatic 613	com/google/android/gms/internal/measurement/zzyx:zzj	([BII)Lcom/google/android/gms/internal/measurement/zzyx;
    //   142: astore 7
    //   144: aload 5
    //   146: astore 4
    //   148: new 1260	com/google/android/gms/internal/measurement/zzgj
    //   151: dup
    //   152: invokespecial 1261	com/google/android/gms/internal/measurement/zzgj:<init>	()V
    //   155: astore 8
    //   157: aload 5
    //   159: astore 4
    //   161: aload 8
    //   163: aload 7
    //   165: invokevirtual 619	com/google/android/gms/internal/measurement/zzzg:zza	(Lcom/google/android/gms/internal/measurement/zzyx;)Lcom/google/android/gms/internal/measurement/zzzg;
    //   168: pop
    //   169: aload 5
    //   171: astore 4
    //   173: aload 6
    //   175: iload_2
    //   176: invokestatic 262	java/lang/Integer:valueOf	(I)Ljava/lang/Integer;
    //   179: aload 8
    //   181: invokeinterface 1266 3 0
    //   186: pop
    //   187: goto +32 -> 219
    //   190: astore 7
    //   192: aload 5
    //   194: astore 4
    //   196: aload_0
    //   197: invokevirtual 231	com/google/android/gms/measurement/internal/zzco:zzgo	()Lcom/google/android/gms/measurement/internal/zzap;
    //   200: invokevirtual 237	com/google/android/gms/measurement/internal/zzap:zzjd	()Lcom/google/android/gms/measurement/internal/zzar;
    //   203: ldc_w 1268
    //   206: aload_1
    //   207: invokestatic 348	com/google/android/gms/measurement/internal/zzap:zzbv	(Ljava/lang/String;)Ljava/lang/Object;
    //   210: iload_2
    //   211: invokestatic 262	java/lang/Integer:valueOf	(I)Ljava/lang/Integer;
    //   214: aload 7
    //   216: invokevirtual 359	com/google/android/gms/measurement/internal/zzar:zzd	(Ljava/lang/String;Ljava/lang/Object;Ljava/lang/Object;Ljava/lang/Object;)V
    //   219: aload 5
    //   221: astore 4
    //   223: aload 5
    //   225: invokeinterface 1066 1 0
    //   230: istore_3
    //   231: iload_3
    //   232: ifne -130 -> 102
    //   235: aload 5
    //   237: ifnull +10 -> 247
    //   240: aload 5
    //   242: invokeinterface 222 1 0
    //   247: aload 6
    //   249: areturn
    //   250: astore 6
    //   252: goto +15 -> 267
    //   255: astore_1
    //   256: aconst_null
    //   257: astore 4
    //   259: goto +46 -> 305
    //   262: astore 6
    //   264: aconst_null
    //   265: astore 5
    //   267: aload 5
    //   269: astore 4
    //   271: aload_0
    //   272: invokevirtual 231	com/google/android/gms/measurement/internal/zzco:zzgo	()Lcom/google/android/gms/measurement/internal/zzap;
    //   275: invokevirtual 237	com/google/android/gms/measurement/internal/zzap:zzjd	()Lcom/google/android/gms/measurement/internal/zzar;
    //   278: ldc_w 1270
    //   281: aload_1
    //   282: invokestatic 348	com/google/android/gms/measurement/internal/zzap:zzbv	(Ljava/lang/String;)Ljava/lang/Object;
    //   285: aload 6
    //   287: invokevirtual 245	com/google/android/gms/measurement/internal/zzar:zze	(Ljava/lang/String;Ljava/lang/Object;Ljava/lang/Object;)V
    //   290: aload 5
    //   292: ifnull +10 -> 302
    //   295: aload 5
    //   297: invokeinterface 222 1 0
    //   302: aconst_null
    //   303: areturn
    //   304: astore_1
    //   305: aload 4
    //   307: ifnull +10 -> 317
    //   310: aload 4
    //   312: invokeinterface 222 1 0
    //   317: aload_1
    //   318: athrow
    // Local variable table:
    //   start	length	slot	name	signature
    //   0	319	0	this	zzq
    //   0	319	1	paramString	String
    //   114	97	2	i	int
    //   70	162	3	bool	boolean
    //   17	294	4	localObject1	Object
    //   57	239	5	localCursor	Cursor
    //   100	148	6	localArrayMap	android.support.v4.util.ArrayMap
    //   250	1	6	localSQLiteException1	SQLiteException
    //   262	24	6	localSQLiteException2	SQLiteException
    //   127	37	7	localObject2	Object
    //   190	25	7	localIOException	IOException
    //   155	25	8	localZzgj	com.google.android.gms.internal.measurement.zzgj
    // Exception table:
    //   from	to	target	type
    //   161	169	190	java/io/IOException
    //   63	71	250	android/database/sqlite/SQLiteException
    //   93	102	250	android/database/sqlite/SQLiteException
    //   106	115	250	android/database/sqlite/SQLiteException
    //   119	129	250	android/database/sqlite/SQLiteException
    //   133	144	250	android/database/sqlite/SQLiteException
    //   148	157	250	android/database/sqlite/SQLiteException
    //   161	169	250	android/database/sqlite/SQLiteException
    //   173	187	250	android/database/sqlite/SQLiteException
    //   196	219	250	android/database/sqlite/SQLiteException
    //   223	231	250	android/database/sqlite/SQLiteException
    //   19	59	255	finally
    //   19	59	262	android/database/sqlite/SQLiteException
    //   63	71	304	finally
    //   93	102	304	finally
    //   106	115	304	finally
    //   119	129	304	finally
    //   133	144	304	finally
    //   148	157	304	finally
    //   161	169	304	finally
    //   173	187	304	finally
    //   196	219	304	finally
    //   223	231	304	finally
    //   271	290	304	finally
  }
  
  public final long zzbp(String paramString)
  {
    Preconditions.checkNotEmpty(paramString);
    return zza("select count(1) from events where app_id=? and name not like '!_%' escape '!'", new String[] { paramString }, 0L);
  }
  
  @WorkerThread
  public final List<zzl> zzc(String paramString1, String paramString2, String paramString3)
  {
    Preconditions.checkNotEmpty(paramString1);
    zzaf();
    zzcl();
    ArrayList localArrayList = new ArrayList(3);
    localArrayList.add(paramString1);
    paramString1 = new StringBuilder("app_id=?");
    if (!TextUtils.isEmpty(paramString2))
    {
      localArrayList.add(paramString2);
      paramString1.append(" and origin=?");
    }
    if (!TextUtils.isEmpty(paramString3))
    {
      localArrayList.add(String.valueOf(paramString3).concat("*"));
      paramString1.append(" and name glob ?");
    }
    paramString2 = (String[])localArrayList.toArray(new String[localArrayList.size()]);
    return zzb(paramString1.toString(), paramString2);
  }
  
  @WorkerThread
  @VisibleForTesting
  final void zzc(List<Long> paramList)
  {
    zzaf();
    zzcl();
    Preconditions.checkNotNull(paramList);
    Preconditions.checkNotZero(paramList.size());
    if (!zzil()) {
      return;
    }
    paramList = TextUtils.join(",", paramList);
    Object localObject = new StringBuilder(String.valueOf(paramList).length() + 2);
    ((StringBuilder)localObject).append("(");
    ((StringBuilder)localObject).append(paramList);
    ((StringBuilder)localObject).append(")");
    paramList = ((StringBuilder)localObject).toString();
    localObject = new StringBuilder(String.valueOf(paramList).length() + 80);
    ((StringBuilder)localObject).append("SELECT COUNT(1) FROM queue WHERE rowid IN ");
    ((StringBuilder)localObject).append(paramList);
    ((StringBuilder)localObject).append(" AND retry_count =  2147483647 LIMIT 1");
    if (zza(((StringBuilder)localObject).toString(), null) > 0L) {
      zzgo().zzjg().zzbx("The number of upload retries exceeds the limit. Will remain unchanged.");
    }
    try
    {
      localObject = getWritableDatabase();
      StringBuilder localStringBuilder = new StringBuilder(String.valueOf(paramList).length() + 127);
      localStringBuilder.append("UPDATE queue SET retry_count = IFNULL(retry_count, 0) + 1 WHERE rowid IN ");
      localStringBuilder.append(paramList);
      localStringBuilder.append(" AND (retry_count IS NULL OR retry_count < 2147483647)");
      ((SQLiteDatabase)localObject).execSQL(localStringBuilder.toString());
      return;
    }
    catch (SQLiteException paramList)
    {
      zzgo().zzjd().zzg("Error incrementing retry count. error", paramList);
    }
  }
  
  /* Error */
  @WorkerThread
  public final zzz zzg(String paramString1, String paramString2)
  {
    // Byte code:
    //   0: aload_1
    //   1: invokestatic 297	com/google/android/gms/common/internal/Preconditions:checkNotEmpty	(Ljava/lang/String;)Ljava/lang/String;
    //   4: pop
    //   5: aload_2
    //   6: invokestatic 297	com/google/android/gms/common/internal/Preconditions:checkNotEmpty	(Ljava/lang/String;)Ljava/lang/String;
    //   9: pop
    //   10: aload_0
    //   11: invokevirtual 327	com/google/android/gms/measurement/internal/zzco:zzaf	()V
    //   14: aload_0
    //   15: invokevirtual 324	com/google/android/gms/measurement/internal/zzez:zzcl	()V
    //   18: aload_0
    //   19: invokevirtual 203	com/google/android/gms/measurement/internal/zzq:getWritableDatabase	()Landroid/database/sqlite/SQLiteDatabase;
    //   22: astore 13
    //   24: iconst_0
    //   25: istore_3
    //   26: aload 13
    //   28: ldc_w 820
    //   31: bipush 8
    //   33: anewarray 19	java/lang/String
    //   36: dup
    //   37: iconst_0
    //   38: ldc_w 785
    //   41: aastore
    //   42: dup
    //   43: iconst_1
    //   44: ldc_w 790
    //   47: aastore
    //   48: dup
    //   49: iconst_2
    //   50: ldc_w 795
    //   53: aastore
    //   54: dup
    //   55: iconst_3
    //   56: ldc 21
    //   58: aastore
    //   59: dup
    //   60: iconst_4
    //   61: ldc 25
    //   63: aastore
    //   64: dup
    //   65: iconst_5
    //   66: ldc 29
    //   68: aastore
    //   69: dup
    //   70: bipush 6
    //   72: ldc 33
    //   74: aastore
    //   75: dup
    //   76: bipush 7
    //   78: ldc 37
    //   80: aastore
    //   81: ldc_w 1304
    //   84: iconst_2
    //   85: anewarray 19	java/lang/String
    //   88: dup
    //   89: iconst_0
    //   90: aload_1
    //   91: aastore
    //   92: dup
    //   93: iconst_1
    //   94: aload_2
    //   95: aastore
    //   96: aconst_null
    //   97: aconst_null
    //   98: aconst_null
    //   99: invokevirtual 642	android/database/sqlite/SQLiteDatabase:query	(Ljava/lang/String;[Ljava/lang/String;Ljava/lang/String;[Ljava/lang/String;Ljava/lang/String;Ljava/lang/String;Ljava/lang/String;)Landroid/database/Cursor;
    //   102: astore 13
    //   104: aload 13
    //   106: invokeinterface 215 1 0
    //   111: istore 4
    //   113: iload 4
    //   115: ifne +17 -> 132
    //   118: aload 13
    //   120: ifnull +10 -> 130
    //   123: aload 13
    //   125: invokeinterface 222 1 0
    //   130: aconst_null
    //   131: areturn
    //   132: aload 13
    //   134: iconst_0
    //   135: invokeinterface 219 2 0
    //   140: lstore 7
    //   142: aload 13
    //   144: iconst_1
    //   145: invokeinterface 219 2 0
    //   150: lstore 9
    //   152: aload 13
    //   154: iconst_2
    //   155: invokeinterface 219 2 0
    //   160: lstore 11
    //   162: aload 13
    //   164: iconst_3
    //   165: invokeinterface 1053 2 0
    //   170: ifeq +9 -> 179
    //   173: lconst_0
    //   174: lstore 5
    //   176: goto +319 -> 495
    //   179: aload 13
    //   181: iconst_3
    //   182: invokeinterface 219 2 0
    //   187: lstore 5
    //   189: goto +306 -> 495
    //   192: aload 13
    //   194: iconst_4
    //   195: invokeinterface 1053 2 0
    //   200: ifeq +9 -> 209
    //   203: aconst_null
    //   204: astore 15
    //   206: goto +16 -> 222
    //   209: aload 13
    //   211: iconst_4
    //   212: invokeinterface 219 2 0
    //   217: invokestatic 288	java/lang/Long:valueOf	(J)Ljava/lang/Long;
    //   220: astore 15
    //   222: aload 13
    //   224: iconst_5
    //   225: invokeinterface 1053 2 0
    //   230: ifeq +9 -> 239
    //   233: aconst_null
    //   234: astore 16
    //   236: goto +16 -> 252
    //   239: aload 13
    //   241: iconst_5
    //   242: invokeinterface 219 2 0
    //   247: invokestatic 288	java/lang/Long:valueOf	(J)Ljava/lang/Long;
    //   250: astore 16
    //   252: aload 13
    //   254: bipush 6
    //   256: invokeinterface 1053 2 0
    //   261: ifeq +9 -> 270
    //   264: aconst_null
    //   265: astore 17
    //   267: goto +231 -> 498
    //   270: aload 13
    //   272: bipush 6
    //   274: invokeinterface 219 2 0
    //   279: invokestatic 288	java/lang/Long:valueOf	(J)Ljava/lang/Long;
    //   282: astore 17
    //   284: goto +214 -> 498
    //   287: aload 13
    //   289: bipush 7
    //   291: invokeinterface 1053 2 0
    //   296: ifne +205 -> 501
    //   299: aload 13
    //   301: bipush 7
    //   303: invokeinterface 219 2 0
    //   308: lconst_1
    //   309: lcmp
    //   310: ifne +5 -> 315
    //   313: iconst_1
    //   314: istore_3
    //   315: iload_3
    //   316: invokestatic 721	java/lang/Boolean:valueOf	(Z)Ljava/lang/Boolean;
    //   319: astore 18
    //   321: goto +3 -> 324
    //   324: aload 13
    //   326: astore 14
    //   328: new 778	com/google/android/gms/measurement/internal/zzz
    //   331: dup
    //   332: aload_1
    //   333: aload_2
    //   334: lload 7
    //   336: lload 9
    //   338: lload 11
    //   340: lload 5
    //   342: aload 15
    //   344: aload 16
    //   346: aload 17
    //   348: aload 18
    //   350: invokespecial 1307	com/google/android/gms/measurement/internal/zzz:<init>	(Ljava/lang/String;Ljava/lang/String;JJJJLjava/lang/Long;Ljava/lang/Long;Ljava/lang/Long;Ljava/lang/Boolean;)V
    //   353: astore 15
    //   355: aload 13
    //   357: astore 14
    //   359: aload 13
    //   361: invokeinterface 1066 1 0
    //   366: ifeq +24 -> 390
    //   369: aload 13
    //   371: astore 14
    //   373: aload_0
    //   374: invokevirtual 231	com/google/android/gms/measurement/internal/zzco:zzgo	()Lcom/google/android/gms/measurement/internal/zzap;
    //   377: invokevirtual 237	com/google/android/gms/measurement/internal/zzap:zzjd	()Lcom/google/android/gms/measurement/internal/zzar;
    //   380: ldc_w 1309
    //   383: aload_1
    //   384: invokestatic 348	com/google/android/gms/measurement/internal/zzap:zzbv	(Ljava/lang/String;)Ljava/lang/Object;
    //   387: invokevirtual 266	com/google/android/gms/measurement/internal/zzar:zzg	(Ljava/lang/String;Ljava/lang/Object;)V
    //   390: aload 13
    //   392: ifnull +10 -> 402
    //   395: aload 13
    //   397: invokeinterface 222 1 0
    //   402: aload 15
    //   404: areturn
    //   405: astore 15
    //   407: goto +28 -> 435
    //   410: astore_1
    //   411: aload 13
    //   413: astore 14
    //   415: goto +66 -> 481
    //   418: astore 15
    //   420: goto +15 -> 435
    //   423: astore_1
    //   424: aconst_null
    //   425: astore 14
    //   427: goto +54 -> 481
    //   430: astore 15
    //   432: aconst_null
    //   433: astore 13
    //   435: aload 13
    //   437: astore 14
    //   439: aload_0
    //   440: invokevirtual 231	com/google/android/gms/measurement/internal/zzco:zzgo	()Lcom/google/android/gms/measurement/internal/zzap;
    //   443: invokevirtual 237	com/google/android/gms/measurement/internal/zzap:zzjd	()Lcom/google/android/gms/measurement/internal/zzar;
    //   446: ldc_w 1311
    //   449: aload_1
    //   450: invokestatic 348	com/google/android/gms/measurement/internal/zzap:zzbv	(Ljava/lang/String;)Ljava/lang/Object;
    //   453: aload_0
    //   454: invokevirtual 995	com/google/android/gms/measurement/internal/zzco:zzgl	()Lcom/google/android/gms/measurement/internal/zzan;
    //   457: aload_2
    //   458: invokevirtual 1000	com/google/android/gms/measurement/internal/zzan:zzbs	(Ljava/lang/String;)Ljava/lang/String;
    //   461: aload 15
    //   463: invokevirtual 359	com/google/android/gms/measurement/internal/zzar:zzd	(Ljava/lang/String;Ljava/lang/Object;Ljava/lang/Object;Ljava/lang/Object;)V
    //   466: aload 13
    //   468: ifnull +10 -> 478
    //   471: aload 13
    //   473: invokeinterface 222 1 0
    //   478: aconst_null
    //   479: areturn
    //   480: astore_1
    //   481: aload 14
    //   483: ifnull +10 -> 493
    //   486: aload 14
    //   488: invokeinterface 222 1 0
    //   493: aload_1
    //   494: athrow
    //   495: goto -303 -> 192
    //   498: goto -211 -> 287
    //   501: aconst_null
    //   502: astore 18
    //   504: goto -180 -> 324
    // Local variable table:
    //   start	length	slot	name	signature
    //   0	507	0	this	zzq
    //   0	507	1	paramString1	String
    //   0	507	2	paramString2	String
    //   25	291	3	bool1	boolean
    //   111	3	4	bool2	boolean
    //   174	167	5	l1	long
    //   140	195	7	l2	long
    //   150	187	9	l3	long
    //   160	179	11	l4	long
    //   22	450	13	localObject1	Object
    //   326	161	14	localObject2	Object
    //   204	199	15	localObject3	Object
    //   405	1	15	localSQLiteException1	SQLiteException
    //   418	1	15	localSQLiteException2	SQLiteException
    //   430	32	15	localSQLiteException3	SQLiteException
    //   234	111	16	localLong1	Long
    //   265	82	17	localLong2	Long
    //   319	184	18	localBoolean	Boolean
    // Exception table:
    //   from	to	target	type
    //   328	355	405	android/database/sqlite/SQLiteException
    //   359	369	405	android/database/sqlite/SQLiteException
    //   373	390	405	android/database/sqlite/SQLiteException
    //   104	113	410	finally
    //   132	173	410	finally
    //   179	189	410	finally
    //   192	203	410	finally
    //   209	222	410	finally
    //   222	233	410	finally
    //   239	252	410	finally
    //   252	264	410	finally
    //   270	284	410	finally
    //   287	299	410	finally
    //   299	313	410	finally
    //   315	321	410	finally
    //   104	113	418	android/database/sqlite/SQLiteException
    //   132	173	418	android/database/sqlite/SQLiteException
    //   179	189	418	android/database/sqlite/SQLiteException
    //   192	203	418	android/database/sqlite/SQLiteException
    //   209	222	418	android/database/sqlite/SQLiteException
    //   222	233	418	android/database/sqlite/SQLiteException
    //   239	252	418	android/database/sqlite/SQLiteException
    //   252	264	418	android/database/sqlite/SQLiteException
    //   270	284	418	android/database/sqlite/SQLiteException
    //   287	299	418	android/database/sqlite/SQLiteException
    //   299	313	418	android/database/sqlite/SQLiteException
    //   315	321	418	android/database/sqlite/SQLiteException
    //   18	24	423	finally
    //   26	104	423	finally
    //   18	24	430	android/database/sqlite/SQLiteException
    //   26	104	430	android/database/sqlite/SQLiteException
    //   328	355	480	finally
    //   359	369	480	finally
    //   373	390	480	finally
    //   439	466	480	finally
  }
  
  protected final boolean zzgt()
  {
    return false;
  }
  
  @WorkerThread
  public final void zzh(String paramString1, String paramString2)
  {
    Preconditions.checkNotEmpty(paramString1);
    Preconditions.checkNotEmpty(paramString2);
    zzaf();
    zzcl();
    try
    {
      int i = getWritableDatabase().delete("user_attributes", "app_id=? and name=?", new String[] { paramString1, paramString2 });
      zzgo().zzjl().zzg("Deleted user attribute rows", Integer.valueOf(i));
      return;
    }
    catch (SQLiteException localSQLiteException)
    {
      zzgo().zzjd().zzd("Error deleting user attribute. appId", zzap.zzbv(paramString1), zzgl().zzbu(paramString2), localSQLiteException);
    }
  }
  
  /* Error */
  @WorkerThread
  public final zzfj zzi(String paramString1, String paramString2)
  {
    // Byte code:
    //   0: aload_1
    //   1: invokestatic 297	com/google/android/gms/common/internal/Preconditions:checkNotEmpty	(Ljava/lang/String;)Ljava/lang/String;
    //   4: pop
    //   5: aload_2
    //   6: invokestatic 297	com/google/android/gms/common/internal/Preconditions:checkNotEmpty	(Ljava/lang/String;)Ljava/lang/String;
    //   9: pop
    //   10: aload_0
    //   11: invokevirtual 327	com/google/android/gms/measurement/internal/zzco:zzaf	()V
    //   14: aload_0
    //   15: invokevirtual 324	com/google/android/gms/measurement/internal/zzez:zzcl	()V
    //   18: aload_0
    //   19: invokevirtual 203	com/google/android/gms/measurement/internal/zzq:getWritableDatabase	()Landroid/database/sqlite/SQLiteDatabase;
    //   22: ldc_w 908
    //   25: iconst_3
    //   26: anewarray 19	java/lang/String
    //   29: dup
    //   30: iconst_0
    //   31: ldc_w 896
    //   34: aastore
    //   35: dup
    //   36: iconst_1
    //   37: ldc_w 901
    //   40: aastore
    //   41: dup
    //   42: iconst_2
    //   43: ldc 43
    //   45: aastore
    //   46: ldc_w 1304
    //   49: iconst_2
    //   50: anewarray 19	java/lang/String
    //   53: dup
    //   54: iconst_0
    //   55: aload_1
    //   56: aastore
    //   57: dup
    //   58: iconst_1
    //   59: aload_2
    //   60: aastore
    //   61: aconst_null
    //   62: aconst_null
    //   63: aconst_null
    //   64: invokevirtual 642	android/database/sqlite/SQLiteDatabase:query	(Ljava/lang/String;[Ljava/lang/String;Ljava/lang/String;[Ljava/lang/String;Ljava/lang/String;Ljava/lang/String;Ljava/lang/String;)Landroid/database/Cursor;
    //   67: astore 6
    //   69: aload 6
    //   71: invokeinterface 215 1 0
    //   76: istore_3
    //   77: iload_3
    //   78: ifne +17 -> 95
    //   81: aload 6
    //   83: ifnull +10 -> 93
    //   86: aload 6
    //   88: invokeinterface 222 1 0
    //   93: aconst_null
    //   94: areturn
    //   95: aload 6
    //   97: iconst_0
    //   98: invokeinterface 219 2 0
    //   103: lstore 4
    //   105: aload 6
    //   107: astore 7
    //   109: aload_0
    //   110: aload 6
    //   112: iconst_1
    //   113: invokespecial 1092	com/google/android/gms/measurement/internal/zzq:zza	(Landroid/database/Cursor;I)Ljava/lang/Object;
    //   116: astore 8
    //   118: aload 6
    //   120: astore 7
    //   122: new 865	com/google/android/gms/measurement/internal/zzfj
    //   125: dup
    //   126: aload_1
    //   127: aload 6
    //   129: iconst_2
    //   130: invokeinterface 274 2 0
    //   135: aload_2
    //   136: lload 4
    //   138: aload 8
    //   140: invokespecial 1097	com/google/android/gms/measurement/internal/zzfj:<init>	(Ljava/lang/String;Ljava/lang/String;Ljava/lang/String;JLjava/lang/Object;)V
    //   143: astore 8
    //   145: aload 6
    //   147: astore 7
    //   149: aload 6
    //   151: invokeinterface 1066 1 0
    //   156: ifeq +24 -> 180
    //   159: aload 6
    //   161: astore 7
    //   163: aload_0
    //   164: invokevirtual 231	com/google/android/gms/measurement/internal/zzco:zzgo	()Lcom/google/android/gms/measurement/internal/zzap;
    //   167: invokevirtual 237	com/google/android/gms/measurement/internal/zzap:zzjd	()Lcom/google/android/gms/measurement/internal/zzar;
    //   170: ldc_w 1322
    //   173: aload_1
    //   174: invokestatic 348	com/google/android/gms/measurement/internal/zzap:zzbv	(Ljava/lang/String;)Ljava/lang/Object;
    //   177: invokevirtual 266	com/google/android/gms/measurement/internal/zzar:zzg	(Ljava/lang/String;Ljava/lang/Object;)V
    //   180: aload 6
    //   182: ifnull +10 -> 192
    //   185: aload 6
    //   187: invokeinterface 222 1 0
    //   192: aload 8
    //   194: areturn
    //   195: astore 8
    //   197: goto +24 -> 221
    //   200: astore_1
    //   201: goto +70 -> 271
    //   204: astore 8
    //   206: goto +15 -> 221
    //   209: astore_1
    //   210: aconst_null
    //   211: astore 6
    //   213: goto +58 -> 271
    //   216: astore 8
    //   218: aconst_null
    //   219: astore 6
    //   221: aload 6
    //   223: astore 7
    //   225: aload_0
    //   226: invokevirtual 231	com/google/android/gms/measurement/internal/zzco:zzgo	()Lcom/google/android/gms/measurement/internal/zzap;
    //   229: invokevirtual 237	com/google/android/gms/measurement/internal/zzap:zzjd	()Lcom/google/android/gms/measurement/internal/zzar;
    //   232: ldc_w 1324
    //   235: aload_1
    //   236: invokestatic 348	com/google/android/gms/measurement/internal/zzap:zzbv	(Ljava/lang/String;)Ljava/lang/Object;
    //   239: aload_0
    //   240: invokevirtual 995	com/google/android/gms/measurement/internal/zzco:zzgl	()Lcom/google/android/gms/measurement/internal/zzan;
    //   243: aload_2
    //   244: invokevirtual 1320	com/google/android/gms/measurement/internal/zzan:zzbu	(Ljava/lang/String;)Ljava/lang/String;
    //   247: aload 8
    //   249: invokevirtual 359	com/google/android/gms/measurement/internal/zzar:zzd	(Ljava/lang/String;Ljava/lang/Object;Ljava/lang/Object;Ljava/lang/Object;)V
    //   252: aload 6
    //   254: ifnull +10 -> 264
    //   257: aload 6
    //   259: invokeinterface 222 1 0
    //   264: aconst_null
    //   265: areturn
    //   266: astore_1
    //   267: aload 7
    //   269: astore 6
    //   271: aload 6
    //   273: ifnull +10 -> 283
    //   276: aload 6
    //   278: invokeinterface 222 1 0
    //   283: aload_1
    //   284: athrow
    // Local variable table:
    //   start	length	slot	name	signature
    //   0	285	0	this	zzq
    //   0	285	1	paramString1	String
    //   0	285	2	paramString2	String
    //   76	2	3	bool	boolean
    //   103	34	4	l	long
    //   67	210	6	localObject1	Object
    //   107	161	7	localObject2	Object
    //   116	77	8	localObject3	Object
    //   195	1	8	localSQLiteException1	SQLiteException
    //   204	1	8	localSQLiteException2	SQLiteException
    //   216	32	8	localSQLiteException3	SQLiteException
    // Exception table:
    //   from	to	target	type
    //   109	118	195	android/database/sqlite/SQLiteException
    //   122	145	195	android/database/sqlite/SQLiteException
    //   149	159	195	android/database/sqlite/SQLiteException
    //   163	180	195	android/database/sqlite/SQLiteException
    //   69	77	200	finally
    //   95	105	200	finally
    //   69	77	204	android/database/sqlite/SQLiteException
    //   95	105	204	android/database/sqlite/SQLiteException
    //   18	69	209	finally
    //   18	69	216	android/database/sqlite/SQLiteException
    //   109	118	266	finally
    //   122	145	266	finally
    //   149	159	266	finally
    //   163	180	266	finally
    //   225	252	266	finally
  }
  
  /* Error */
  @WorkerThread
  public final String zzid()
  {
    // Byte code:
    //   0: aload_0
    //   1: invokevirtual 203	com/google/android/gms/measurement/internal/zzq:getWritableDatabase	()Landroid/database/sqlite/SQLiteDatabase;
    //   4: astore_1
    //   5: aload_1
    //   6: ldc_w 1327
    //   9: aconst_null
    //   10: invokevirtual 209	android/database/sqlite/SQLiteDatabase:rawQuery	(Ljava/lang/String;[Ljava/lang/String;)Landroid/database/Cursor;
    //   13: astore_2
    //   14: aload_2
    //   15: astore_1
    //   16: aload_2
    //   17: invokeinterface 215 1 0
    //   22: ifeq +25 -> 47
    //   25: aload_2
    //   26: astore_1
    //   27: aload_2
    //   28: iconst_0
    //   29: invokeinterface 274 2 0
    //   34: astore_3
    //   35: aload_2
    //   36: ifnull +9 -> 45
    //   39: aload_2
    //   40: invokeinterface 222 1 0
    //   45: aload_3
    //   46: areturn
    //   47: aload_2
    //   48: ifnull +9 -> 57
    //   51: aload_2
    //   52: invokeinterface 222 1 0
    //   57: aconst_null
    //   58: areturn
    //   59: astore_3
    //   60: goto +14 -> 74
    //   63: astore_1
    //   64: aconst_null
    //   65: astore_2
    //   66: aload_1
    //   67: astore_3
    //   68: goto +37 -> 105
    //   71: astore_3
    //   72: aconst_null
    //   73: astore_2
    //   74: aload_2
    //   75: astore_1
    //   76: aload_0
    //   77: invokevirtual 231	com/google/android/gms/measurement/internal/zzco:zzgo	()Lcom/google/android/gms/measurement/internal/zzap;
    //   80: invokevirtual 237	com/google/android/gms/measurement/internal/zzap:zzjd	()Lcom/google/android/gms/measurement/internal/zzar;
    //   83: ldc_w 1329
    //   86: aload_3
    //   87: invokevirtual 266	com/google/android/gms/measurement/internal/zzar:zzg	(Ljava/lang/String;Ljava/lang/Object;)V
    //   90: aload_2
    //   91: ifnull +9 -> 100
    //   94: aload_2
    //   95: invokeinterface 222 1 0
    //   100: aconst_null
    //   101: areturn
    //   102: astore_3
    //   103: aload_1
    //   104: astore_2
    //   105: aload_2
    //   106: ifnull +9 -> 115
    //   109: aload_2
    //   110: invokeinterface 222 1 0
    //   115: aload_3
    //   116: athrow
    // Local variable table:
    //   start	length	slot	name	signature
    //   0	117	0	this	zzq
    //   4	23	1	localObject1	Object
    //   63	4	1	localObject2	Object
    //   75	29	1	localObject3	Object
    //   13	97	2	localObject4	Object
    //   34	12	3	str	String
    //   59	1	3	localSQLiteException1	SQLiteException
    //   67	1	3	localObject5	Object
    //   71	16	3	localSQLiteException2	SQLiteException
    //   102	14	3	localObject6	Object
    // Exception table:
    //   from	to	target	type
    //   16	25	59	android/database/sqlite/SQLiteException
    //   27	35	59	android/database/sqlite/SQLiteException
    //   5	14	63	finally
    //   5	14	71	android/database/sqlite/SQLiteException
    //   16	25	102	finally
    //   27	35	102	finally
    //   76	90	102	finally
  }
  
  public final boolean zzie()
  {
    return zza("select count(1) > 0 from queue where has_realtime = 1", null) != 0L;
  }
  
  @WorkerThread
  final void zzif()
  {
    zzaf();
    zzcl();
    if (!zzil()) {
      return;
    }
    long l1 = zzgpzzanh.get();
    long l2 = zzbx().elapsedRealtime();
    if (Math.abs(l2 - l1) > ((Long)zzaf.zzakb.get()).longValue())
    {
      zzgpzzanh.set(l2);
      zzaf();
      zzcl();
      if (zzil())
      {
        int i = getWritableDatabase().delete("queue", "abs(bundle_end_timestamp - ?) > cast(? as integer)", new String[] { String.valueOf(zzbx().currentTimeMillis()), String.valueOf(zzn.zzhw()) });
        if (i > 0) {
          zzgo().zzjl().zzg("Deleted stale rows. rowsDeleted", Integer.valueOf(i));
        }
      }
    }
  }
  
  @WorkerThread
  public final long zzig()
  {
    return zza("select max(bundle_end_timestamp) from queue", null, 0L);
  }
  
  @WorkerThread
  public final long zzih()
  {
    return zza("select max(timestamp) from raw_events", null, 0L);
  }
  
  public final boolean zzii()
  {
    return zza("select count(1) > 0 from raw_events", null) != 0L;
  }
  
  public final boolean zzij()
  {
    return zza("select count(1) > 0 from raw_events where realtime = 1", null) != 0L;
  }
  
  /* Error */
  public final long zzik()
  {
    // Byte code:
    //   0: aconst_null
    //   1: astore 7
    //   3: aconst_null
    //   4: astore 4
    //   6: aload_0
    //   7: invokevirtual 203	com/google/android/gms/measurement/internal/zzq:getWritableDatabase	()Landroid/database/sqlite/SQLiteDatabase;
    //   10: ldc_w 1394
    //   13: aconst_null
    //   14: invokevirtual 209	android/database/sqlite/SQLiteDatabase:rawQuery	(Ljava/lang/String;[Ljava/lang/String;)Landroid/database/Cursor;
    //   17: astore 5
    //   19: aload 5
    //   21: invokeinterface 215 1 0
    //   26: istore_1
    //   27: iload_1
    //   28: ifne +19 -> 47
    //   31: aload 5
    //   33: ifnull +10 -> 43
    //   36: aload 5
    //   38: invokeinterface 222 1 0
    //   43: ldc2_w 402
    //   46: lreturn
    //   47: aload 5
    //   49: iconst_0
    //   50: invokeinterface 219 2 0
    //   55: lstore_2
    //   56: aload 5
    //   58: ifnull +10 -> 68
    //   61: aload 5
    //   63: invokeinterface 222 1 0
    //   68: lload_2
    //   69: lreturn
    //   70: astore 6
    //   72: aload 5
    //   74: astore 4
    //   76: aload 6
    //   78: astore 5
    //   80: goto +58 -> 138
    //   83: astore 4
    //   85: aload 4
    //   87: astore 6
    //   89: goto +14 -> 103
    //   92: astore 5
    //   94: goto +44 -> 138
    //   97: astore 6
    //   99: aload 7
    //   101: astore 5
    //   103: aload 5
    //   105: astore 4
    //   107: aload_0
    //   108: invokevirtual 231	com/google/android/gms/measurement/internal/zzco:zzgo	()Lcom/google/android/gms/measurement/internal/zzap;
    //   111: invokevirtual 237	com/google/android/gms/measurement/internal/zzap:zzjd	()Lcom/google/android/gms/measurement/internal/zzar;
    //   114: ldc_w 1396
    //   117: aload 6
    //   119: invokevirtual 266	com/google/android/gms/measurement/internal/zzar:zzg	(Ljava/lang/String;Ljava/lang/Object;)V
    //   122: aload 5
    //   124: ifnull +10 -> 134
    //   127: aload 5
    //   129: invokeinterface 222 1 0
    //   134: ldc2_w 402
    //   137: lreturn
    //   138: aload 4
    //   140: ifnull +10 -> 150
    //   143: aload 4
    //   145: invokeinterface 222 1 0
    //   150: aload 5
    //   152: athrow
    // Local variable table:
    //   start	length	slot	name	signature
    //   0	153	0	this	zzq
    //   26	2	1	bool	boolean
    //   55	14	2	l	long
    //   4	71	4	localObject1	Object
    //   83	3	4	localSQLiteException1	SQLiteException
    //   105	39	4	localObject2	Object
    //   17	62	5	localObject3	Object
    //   92	1	5	localObject4	Object
    //   101	50	5	localObject5	Object
    //   70	7	6	localObject6	Object
    //   87	1	6	localSQLiteException2	SQLiteException
    //   97	21	6	localSQLiteException3	SQLiteException
    //   1	99	7	localObject7	Object
    // Exception table:
    //   from	to	target	type
    //   19	27	70	finally
    //   47	56	70	finally
    //   19	27	83	android/database/sqlite/SQLiteException
    //   47	56	83	android/database/sqlite/SQLiteException
    //   6	19	92	finally
    //   107	122	92	finally
    //   6	19	97	android/database/sqlite/SQLiteException
  }
  
  /* Error */
  @WorkerThread
  public final zzl zzj(String paramString1, String paramString2)
  {
    // Byte code:
    //   0: aload_1
    //   1: invokestatic 297	com/google/android/gms/common/internal/Preconditions:checkNotEmpty	(Ljava/lang/String;)Ljava/lang/String;
    //   4: pop
    //   5: aload_2
    //   6: invokestatic 297	com/google/android/gms/common/internal/Preconditions:checkNotEmpty	(Ljava/lang/String;)Ljava/lang/String;
    //   9: pop
    //   10: aload_0
    //   11: invokevirtual 327	com/google/android/gms/measurement/internal/zzco:zzaf	()V
    //   14: aload_0
    //   15: invokevirtual 324	com/google/android/gms/measurement/internal/zzez:zzcl	()V
    //   18: aload_0
    //   19: invokevirtual 203	com/google/android/gms/measurement/internal/zzq:getWritableDatabase	()Landroid/database/sqlite/SQLiteDatabase;
    //   22: ldc_w 983
    //   25: bipush 11
    //   27: anewarray 19	java/lang/String
    //   30: dup
    //   31: iconst_0
    //   32: ldc 43
    //   34: aastore
    //   35: dup
    //   36: iconst_1
    //   37: ldc_w 901
    //   40: aastore
    //   41: dup
    //   42: iconst_2
    //   43: ldc_w 936
    //   46: aastore
    //   47: dup
    //   48: iconst_3
    //   49: ldc_w 941
    //   52: aastore
    //   53: dup
    //   54: iconst_4
    //   55: ldc_w 946
    //   58: aastore
    //   59: dup
    //   60: iconst_5
    //   61: ldc_w 951
    //   64: aastore
    //   65: dup
    //   66: bipush 6
    //   68: ldc_w 960
    //   71: aastore
    //   72: dup
    //   73: bipush 7
    //   75: ldc_w 965
    //   78: aastore
    //   79: dup
    //   80: bipush 8
    //   82: ldc_w 970
    //   85: aastore
    //   86: dup
    //   87: bipush 9
    //   89: ldc_w 973
    //   92: aastore
    //   93: dup
    //   94: bipush 10
    //   96: ldc_w 978
    //   99: aastore
    //   100: ldc_w 1304
    //   103: iconst_2
    //   104: anewarray 19	java/lang/String
    //   107: dup
    //   108: iconst_0
    //   109: aload_1
    //   110: aastore
    //   111: dup
    //   112: iconst_1
    //   113: aload_2
    //   114: aastore
    //   115: aconst_null
    //   116: aconst_null
    //   117: aconst_null
    //   118: invokevirtual 642	android/database/sqlite/SQLiteDatabase:query	(Ljava/lang/String;[Ljava/lang/String;Ljava/lang/String;[Ljava/lang/String;Ljava/lang/String;Ljava/lang/String;Ljava/lang/String;)Landroid/database/Cursor;
    //   121: astore 12
    //   123: aload 12
    //   125: invokeinterface 215 1 0
    //   130: istore_3
    //   131: iload_3
    //   132: ifne +17 -> 149
    //   135: aload 12
    //   137: ifnull +10 -> 147
    //   140: aload 12
    //   142: invokeinterface 222 1 0
    //   147: aconst_null
    //   148: areturn
    //   149: aload 12
    //   151: iconst_0
    //   152: invokeinterface 274 2 0
    //   157: astore 14
    //   159: aload 12
    //   161: astore 13
    //   163: aload_0
    //   164: aload 12
    //   166: iconst_1
    //   167: invokespecial 1092	com/google/android/gms/measurement/internal/zzq:zza	(Landroid/database/Cursor;I)Ljava/lang/Object;
    //   170: astore 15
    //   172: aload 12
    //   174: astore 13
    //   176: aload 12
    //   178: iconst_2
    //   179: invokeinterface 1056 2 0
    //   184: ifeq +357 -> 541
    //   187: iconst_1
    //   188: istore_3
    //   189: goto +3 -> 192
    //   192: aload 12
    //   194: astore 13
    //   196: aload 12
    //   198: iconst_3
    //   199: invokeinterface 274 2 0
    //   204: astore 16
    //   206: aload 12
    //   208: astore 13
    //   210: aload 12
    //   212: iconst_4
    //   213: invokeinterface 219 2 0
    //   218: lstore 4
    //   220: aload 12
    //   222: astore 13
    //   224: aload_0
    //   225: invokevirtual 562	com/google/android/gms/measurement/internal/zzey:zzjo	()Lcom/google/android/gms/measurement/internal/zzfg;
    //   228: aload 12
    //   230: iconst_5
    //   231: invokeinterface 607 2 0
    //   236: getstatic 1109	com/google/android/gms/measurement/internal/zzad:CREATOR	Landroid/os/Parcelable$Creator;
    //   239: invokevirtual 1112	com/google/android/gms/measurement/internal/zzfg:zza	([BLandroid/os/Parcelable$Creator;)Landroid/os/Parcelable;
    //   242: checkcast 1105	com/google/android/gms/measurement/internal/zzad
    //   245: astore 17
    //   247: aload 12
    //   249: astore 13
    //   251: aload 12
    //   253: bipush 6
    //   255: invokeinterface 219 2 0
    //   260: lstore 6
    //   262: aload 12
    //   264: astore 13
    //   266: aload_0
    //   267: invokevirtual 562	com/google/android/gms/measurement/internal/zzey:zzjo	()Lcom/google/android/gms/measurement/internal/zzfg;
    //   270: aload 12
    //   272: bipush 7
    //   274: invokeinterface 607 2 0
    //   279: getstatic 1109	com/google/android/gms/measurement/internal/zzad:CREATOR	Landroid/os/Parcelable$Creator;
    //   282: invokevirtual 1112	com/google/android/gms/measurement/internal/zzfg:zza	([BLandroid/os/Parcelable$Creator;)Landroid/os/Parcelable;
    //   285: checkcast 1105	com/google/android/gms/measurement/internal/zzad
    //   288: astore 18
    //   290: aload 12
    //   292: astore 13
    //   294: aload 12
    //   296: bipush 8
    //   298: invokeinterface 219 2 0
    //   303: lstore 8
    //   305: aload 12
    //   307: astore 13
    //   309: aload 12
    //   311: bipush 9
    //   313: invokeinterface 219 2 0
    //   318: lstore 10
    //   320: aload 12
    //   322: astore 13
    //   324: aload_0
    //   325: invokevirtual 562	com/google/android/gms/measurement/internal/zzey:zzjo	()Lcom/google/android/gms/measurement/internal/zzfg;
    //   328: aload 12
    //   330: bipush 10
    //   332: invokeinterface 607 2 0
    //   337: getstatic 1109	com/google/android/gms/measurement/internal/zzad:CREATOR	Landroid/os/Parcelable$Creator;
    //   340: invokevirtual 1112	com/google/android/gms/measurement/internal/zzfg:zza	([BLandroid/os/Parcelable$Creator;)Landroid/os/Parcelable;
    //   343: checkcast 1105	com/google/android/gms/measurement/internal/zzad
    //   346: astore 19
    //   348: aload 12
    //   350: astore 13
    //   352: new 915	com/google/android/gms/measurement/internal/zzl
    //   355: dup
    //   356: aload_1
    //   357: aload 14
    //   359: new 924	com/google/android/gms/measurement/internal/zzfh
    //   362: dup
    //   363: aload_2
    //   364: lload 8
    //   366: aload 15
    //   368: aload 14
    //   370: invokespecial 1115	com/google/android/gms/measurement/internal/zzfh:<init>	(Ljava/lang/String;JLjava/lang/Object;Ljava/lang/String;)V
    //   373: lload 6
    //   375: iload_3
    //   376: aload 16
    //   378: aload 17
    //   380: lload 4
    //   382: aload 18
    //   384: lload 10
    //   386: aload 19
    //   388: invokespecial 1118	com/google/android/gms/measurement/internal/zzl:<init>	(Ljava/lang/String;Ljava/lang/String;Lcom/google/android/gms/measurement/internal/zzfh;JZLjava/lang/String;Lcom/google/android/gms/measurement/internal/zzad;JLcom/google/android/gms/measurement/internal/zzad;JLcom/google/android/gms/measurement/internal/zzad;)V
    //   391: astore 14
    //   393: aload 12
    //   395: astore 13
    //   397: aload 12
    //   399: invokeinterface 1066 1 0
    //   404: ifeq +32 -> 436
    //   407: aload 12
    //   409: astore 13
    //   411: aload_0
    //   412: invokevirtual 231	com/google/android/gms/measurement/internal/zzco:zzgo	()Lcom/google/android/gms/measurement/internal/zzap;
    //   415: invokevirtual 237	com/google/android/gms/measurement/internal/zzap:zzjd	()Lcom/google/android/gms/measurement/internal/zzar;
    //   418: ldc_w 1399
    //   421: aload_1
    //   422: invokestatic 348	com/google/android/gms/measurement/internal/zzap:zzbv	(Ljava/lang/String;)Ljava/lang/Object;
    //   425: aload_0
    //   426: invokevirtual 995	com/google/android/gms/measurement/internal/zzco:zzgl	()Lcom/google/android/gms/measurement/internal/zzan;
    //   429: aload_2
    //   430: invokevirtual 1320	com/google/android/gms/measurement/internal/zzan:zzbu	(Ljava/lang/String;)Ljava/lang/String;
    //   433: invokevirtual 245	com/google/android/gms/measurement/internal/zzar:zze	(Ljava/lang/String;Ljava/lang/Object;Ljava/lang/Object;)V
    //   436: aload 12
    //   438: ifnull +10 -> 448
    //   441: aload 12
    //   443: invokeinterface 222 1 0
    //   448: aload 14
    //   450: areturn
    //   451: astore 14
    //   453: goto +24 -> 477
    //   456: astore_1
    //   457: goto +70 -> 527
    //   460: astore 14
    //   462: goto +15 -> 477
    //   465: astore_1
    //   466: aconst_null
    //   467: astore 12
    //   469: goto +58 -> 527
    //   472: astore 14
    //   474: aconst_null
    //   475: astore 12
    //   477: aload 12
    //   479: astore 13
    //   481: aload_0
    //   482: invokevirtual 231	com/google/android/gms/measurement/internal/zzco:zzgo	()Lcom/google/android/gms/measurement/internal/zzap;
    //   485: invokevirtual 237	com/google/android/gms/measurement/internal/zzap:zzjd	()Lcom/google/android/gms/measurement/internal/zzar;
    //   488: ldc_w 1401
    //   491: aload_1
    //   492: invokestatic 348	com/google/android/gms/measurement/internal/zzap:zzbv	(Ljava/lang/String;)Ljava/lang/Object;
    //   495: aload_0
    //   496: invokevirtual 995	com/google/android/gms/measurement/internal/zzco:zzgl	()Lcom/google/android/gms/measurement/internal/zzan;
    //   499: aload_2
    //   500: invokevirtual 1320	com/google/android/gms/measurement/internal/zzan:zzbu	(Ljava/lang/String;)Ljava/lang/String;
    //   503: aload 14
    //   505: invokevirtual 359	com/google/android/gms/measurement/internal/zzar:zzd	(Ljava/lang/String;Ljava/lang/Object;Ljava/lang/Object;Ljava/lang/Object;)V
    //   508: aload 12
    //   510: ifnull +10 -> 520
    //   513: aload 12
    //   515: invokeinterface 222 1 0
    //   520: aconst_null
    //   521: areturn
    //   522: astore_1
    //   523: aload 13
    //   525: astore 12
    //   527: aload 12
    //   529: ifnull +10 -> 539
    //   532: aload 12
    //   534: invokeinterface 222 1 0
    //   539: aload_1
    //   540: athrow
    //   541: iconst_0
    //   542: istore_3
    //   543: goto -351 -> 192
    // Local variable table:
    //   start	length	slot	name	signature
    //   0	546	0	this	zzq
    //   0	546	1	paramString1	String
    //   0	546	2	paramString2	String
    //   130	413	3	bool	boolean
    //   218	163	4	l1	long
    //   260	114	6	l2	long
    //   303	62	8	l3	long
    //   318	67	10	l4	long
    //   121	412	12	localObject1	Object
    //   161	363	13	localObject2	Object
    //   157	292	14	localObject3	Object
    //   451	1	14	localSQLiteException1	SQLiteException
    //   460	1	14	localSQLiteException2	SQLiteException
    //   472	32	14	localSQLiteException3	SQLiteException
    //   170	197	15	localObject4	Object
    //   204	173	16	str	String
    //   245	134	17	localZzad1	zzad
    //   288	95	18	localZzad2	zzad
    //   346	41	19	localZzad3	zzad
    // Exception table:
    //   from	to	target	type
    //   163	172	451	android/database/sqlite/SQLiteException
    //   176	187	451	android/database/sqlite/SQLiteException
    //   196	206	451	android/database/sqlite/SQLiteException
    //   210	220	451	android/database/sqlite/SQLiteException
    //   224	247	451	android/database/sqlite/SQLiteException
    //   251	262	451	android/database/sqlite/SQLiteException
    //   266	290	451	android/database/sqlite/SQLiteException
    //   294	305	451	android/database/sqlite/SQLiteException
    //   309	320	451	android/database/sqlite/SQLiteException
    //   324	348	451	android/database/sqlite/SQLiteException
    //   352	393	451	android/database/sqlite/SQLiteException
    //   397	407	451	android/database/sqlite/SQLiteException
    //   411	436	451	android/database/sqlite/SQLiteException
    //   123	131	456	finally
    //   149	159	456	finally
    //   123	131	460	android/database/sqlite/SQLiteException
    //   149	159	460	android/database/sqlite/SQLiteException
    //   18	123	465	finally
    //   18	123	472	android/database/sqlite/SQLiteException
    //   163	172	522	finally
    //   176	187	522	finally
    //   196	206	522	finally
    //   210	220	522	finally
    //   224	247	522	finally
    //   251	262	522	finally
    //   266	290	522	finally
    //   294	305	522	finally
    //   309	320	522	finally
    //   324	348	522	finally
    //   352	393	522	finally
    //   397	407	522	finally
    //   411	436	522	finally
    //   481	508	522	finally
  }
  
  @WorkerThread
  public final int zzk(String paramString1, String paramString2)
  {
    Preconditions.checkNotEmpty(paramString1);
    Preconditions.checkNotEmpty(paramString2);
    zzaf();
    zzcl();
    try
    {
      int i = getWritableDatabase().delete("conditional_properties", "app_id=? and name=?", new String[] { paramString1, paramString2 });
      return i;
    }
    catch (SQLiteException localSQLiteException)
    {
      zzgo().zzjd().zzd("Error deleting conditional property", zzap.zzbv(paramString1), zzgl().zzbu(paramString2), localSQLiteException);
    }
    return 0;
  }
  
  /* Error */
  final java.util.Map<Integer, List<zzfv>> zzl(String paramString1, String paramString2)
  {
    // Byte code:
    //   0: aload_0
    //   1: invokevirtual 324	com/google/android/gms/measurement/internal/zzez:zzcl	()V
    //   4: aload_0
    //   5: invokevirtual 327	com/google/android/gms/measurement/internal/zzco:zzaf	()V
    //   8: aload_1
    //   9: invokestatic 297	com/google/android/gms/common/internal/Preconditions:checkNotEmpty	(Ljava/lang/String;)Ljava/lang/String;
    //   12: pop
    //   13: aload_2
    //   14: invokestatic 297	com/google/android/gms/common/internal/Preconditions:checkNotEmpty	(Ljava/lang/String;)Ljava/lang/String;
    //   17: pop
    //   18: new 1257	android/support/v4/util/ArrayMap
    //   21: dup
    //   22: invokespecial 1258	android/support/v4/util/ArrayMap:<init>	()V
    //   25: astore 8
    //   27: aload_0
    //   28: invokevirtual 203	com/google/android/gms/measurement/internal/zzq:getWritableDatabase	()Landroid/database/sqlite/SQLiteDatabase;
    //   31: astore 5
    //   33: aload 5
    //   35: ldc_w 397
    //   38: iconst_2
    //   39: anewarray 19	java/lang/String
    //   42: dup
    //   43: iconst_0
    //   44: ldc_w 383
    //   47: aastore
    //   48: dup
    //   49: iconst_1
    //   50: ldc_w 392
    //   53: aastore
    //   54: ldc_w 1408
    //   57: iconst_2
    //   58: anewarray 19	java/lang/String
    //   61: dup
    //   62: iconst_0
    //   63: aload_1
    //   64: aastore
    //   65: dup
    //   66: iconst_1
    //   67: aload_2
    //   68: aastore
    //   69: aconst_null
    //   70: aconst_null
    //   71: aconst_null
    //   72: invokevirtual 642	android/database/sqlite/SQLiteDatabase:query	(Ljava/lang/String;[Ljava/lang/String;Ljava/lang/String;[Ljava/lang/String;Ljava/lang/String;Ljava/lang/String;Ljava/lang/String;)Landroid/database/Cursor;
    //   75: astore 5
    //   77: aload 5
    //   79: astore_2
    //   80: aload 5
    //   82: invokeinterface 215 1 0
    //   87: ifne +26 -> 113
    //   90: aload 5
    //   92: astore_2
    //   93: invokestatic 1412	java/util/Collections:emptyMap	()Ljava/util/Map;
    //   96: astore 6
    //   98: aload 5
    //   100: ifnull +10 -> 110
    //   103: aload 5
    //   105: invokeinterface 222 1 0
    //   110: aload 6
    //   112: areturn
    //   113: aload 5
    //   115: astore_2
    //   116: aload 5
    //   118: iconst_1
    //   119: invokeinterface 607 2 0
    //   124: astore 6
    //   126: aload 5
    //   128: astore_2
    //   129: aload 6
    //   131: iconst_0
    //   132: aload 6
    //   134: arraylength
    //   135: invokestatic 613	com/google/android/gms/internal/measurement/zzyx:zzj	([BII)Lcom/google/android/gms/internal/measurement/zzyx;
    //   138: astore 6
    //   140: aload 5
    //   142: astore_2
    //   143: new 329	com/google/android/gms/internal/measurement/zzfv
    //   146: dup
    //   147: invokespecial 1413	com/google/android/gms/internal/measurement/zzfv:<init>	()V
    //   150: astore 9
    //   152: aload 5
    //   154: astore_2
    //   155: aload 9
    //   157: aload 6
    //   159: invokevirtual 619	com/google/android/gms/internal/measurement/zzzg:zza	(Lcom/google/android/gms/internal/measurement/zzyx;)Lcom/google/android/gms/internal/measurement/zzzg;
    //   162: pop
    //   163: aload 5
    //   165: astore_2
    //   166: aload 5
    //   168: iconst_0
    //   169: invokeinterface 1056 2 0
    //   174: istore_3
    //   175: aload 5
    //   177: astore_2
    //   178: aload 8
    //   180: iload_3
    //   181: invokestatic 262	java/lang/Integer:valueOf	(I)Ljava/lang/Integer;
    //   184: invokeinterface 1415 2 0
    //   189: checkcast 463	java/util/List
    //   192: astore 7
    //   194: aload 7
    //   196: astore 6
    //   198: aload 7
    //   200: ifnonnull +32 -> 232
    //   203: aload 5
    //   205: astore_2
    //   206: new 460	java/util/ArrayList
    //   209: dup
    //   210: invokespecial 461	java/util/ArrayList:<init>	()V
    //   213: astore 6
    //   215: aload 5
    //   217: astore_2
    //   218: aload 8
    //   220: iload_3
    //   221: invokestatic 262	java/lang/Integer:valueOf	(I)Ljava/lang/Integer;
    //   224: aload 6
    //   226: invokeinterface 1266 3 0
    //   231: pop
    //   232: aload 5
    //   234: astore_2
    //   235: aload 6
    //   237: aload 9
    //   239: invokeinterface 480 2 0
    //   244: pop
    //   245: goto +27 -> 272
    //   248: astore 6
    //   250: aload 5
    //   252: astore_2
    //   253: aload_0
    //   254: invokevirtual 231	com/google/android/gms/measurement/internal/zzco:zzgo	()Lcom/google/android/gms/measurement/internal/zzap;
    //   257: invokevirtual 237	com/google/android/gms/measurement/internal/zzap:zzjd	()Lcom/google/android/gms/measurement/internal/zzar;
    //   260: ldc_w 1417
    //   263: aload_1
    //   264: invokestatic 348	com/google/android/gms/measurement/internal/zzap:zzbv	(Ljava/lang/String;)Ljava/lang/Object;
    //   267: aload 6
    //   269: invokevirtual 245	com/google/android/gms/measurement/internal/zzar:zze	(Ljava/lang/String;Ljava/lang/Object;Ljava/lang/Object;)V
    //   272: aload 5
    //   274: astore_2
    //   275: aload 5
    //   277: invokeinterface 1066 1 0
    //   282: istore 4
    //   284: iload 4
    //   286: ifne -173 -> 113
    //   289: aload 5
    //   291: ifnull +10 -> 301
    //   294: aload 5
    //   296: invokeinterface 222 1 0
    //   301: aload 8
    //   303: areturn
    //   304: astore 6
    //   306: goto +14 -> 320
    //   309: astore_1
    //   310: aconst_null
    //   311: astore_2
    //   312: goto +45 -> 357
    //   315: astore 6
    //   317: aconst_null
    //   318: astore 5
    //   320: aload 5
    //   322: astore_2
    //   323: aload_0
    //   324: invokevirtual 231	com/google/android/gms/measurement/internal/zzco:zzgo	()Lcom/google/android/gms/measurement/internal/zzap;
    //   327: invokevirtual 237	com/google/android/gms/measurement/internal/zzap:zzjd	()Lcom/google/android/gms/measurement/internal/zzar;
    //   330: ldc_w 517
    //   333: aload_1
    //   334: invokestatic 348	com/google/android/gms/measurement/internal/zzap:zzbv	(Ljava/lang/String;)Ljava/lang/Object;
    //   337: aload 6
    //   339: invokevirtual 245	com/google/android/gms/measurement/internal/zzar:zze	(Ljava/lang/String;Ljava/lang/Object;Ljava/lang/Object;)V
    //   342: aload 5
    //   344: ifnull +10 -> 354
    //   347: aload 5
    //   349: invokeinterface 222 1 0
    //   354: aconst_null
    //   355: areturn
    //   356: astore_1
    //   357: aload_2
    //   358: ifnull +9 -> 367
    //   361: aload_2
    //   362: invokeinterface 222 1 0
    //   367: aload_1
    //   368: athrow
    // Local variable table:
    //   start	length	slot	name	signature
    //   0	369	0	this	zzq
    //   0	369	1	paramString1	String
    //   0	369	2	paramString2	String
    //   174	47	3	i	int
    //   282	3	4	bool	boolean
    //   31	317	5	localObject1	Object
    //   96	140	6	localObject2	Object
    //   248	20	6	localIOException	IOException
    //   304	1	6	localSQLiteException1	SQLiteException
    //   315	23	6	localSQLiteException2	SQLiteException
    //   192	7	7	localList	List
    //   25	277	8	localArrayMap	android.support.v4.util.ArrayMap
    //   150	88	9	localZzfv	zzfv
    // Exception table:
    //   from	to	target	type
    //   155	163	248	java/io/IOException
    //   80	90	304	android/database/sqlite/SQLiteException
    //   93	98	304	android/database/sqlite/SQLiteException
    //   116	126	304	android/database/sqlite/SQLiteException
    //   129	140	304	android/database/sqlite/SQLiteException
    //   143	152	304	android/database/sqlite/SQLiteException
    //   155	163	304	android/database/sqlite/SQLiteException
    //   166	175	304	android/database/sqlite/SQLiteException
    //   178	194	304	android/database/sqlite/SQLiteException
    //   206	215	304	android/database/sqlite/SQLiteException
    //   218	232	304	android/database/sqlite/SQLiteException
    //   235	245	304	android/database/sqlite/SQLiteException
    //   253	272	304	android/database/sqlite/SQLiteException
    //   275	284	304	android/database/sqlite/SQLiteException
    //   33	77	309	finally
    //   33	77	315	android/database/sqlite/SQLiteException
    //   80	90	356	finally
    //   93	98	356	finally
    //   116	126	356	finally
    //   129	140	356	finally
    //   143	152	356	finally
    //   155	163	356	finally
    //   166	175	356	finally
    //   178	194	356	finally
    //   206	215	356	finally
    //   218	232	356	finally
    //   235	245	356	finally
    //   253	272	356	finally
    //   275	284	356	finally
    //   323	342	356	finally
  }
  
  /* Error */
  final java.util.Map<Integer, List<zzfy>> zzm(String paramString1, String paramString2)
  {
    // Byte code:
    //   0: aload_0
    //   1: invokevirtual 324	com/google/android/gms/measurement/internal/zzez:zzcl	()V
    //   4: aload_0
    //   5: invokevirtual 327	com/google/android/gms/measurement/internal/zzco:zzaf	()V
    //   8: aload_1
    //   9: invokestatic 297	com/google/android/gms/common/internal/Preconditions:checkNotEmpty	(Ljava/lang/String;)Ljava/lang/String;
    //   12: pop
    //   13: aload_2
    //   14: invokestatic 297	com/google/android/gms/common/internal/Preconditions:checkNotEmpty	(Ljava/lang/String;)Ljava/lang/String;
    //   17: pop
    //   18: new 1257	android/support/v4/util/ArrayMap
    //   21: dup
    //   22: invokespecial 1258	android/support/v4/util/ArrayMap:<init>	()V
    //   25: astore 8
    //   27: aload_0
    //   28: invokevirtual 203	com/google/android/gms/measurement/internal/zzq:getWritableDatabase	()Landroid/database/sqlite/SQLiteDatabase;
    //   31: astore 5
    //   33: aload 5
    //   35: ldc_w 422
    //   38: iconst_2
    //   39: anewarray 19	java/lang/String
    //   42: dup
    //   43: iconst_0
    //   44: ldc_w 383
    //   47: aastore
    //   48: dup
    //   49: iconst_1
    //   50: ldc_w 392
    //   53: aastore
    //   54: ldc_w 1421
    //   57: iconst_2
    //   58: anewarray 19	java/lang/String
    //   61: dup
    //   62: iconst_0
    //   63: aload_1
    //   64: aastore
    //   65: dup
    //   66: iconst_1
    //   67: aload_2
    //   68: aastore
    //   69: aconst_null
    //   70: aconst_null
    //   71: aconst_null
    //   72: invokevirtual 642	android/database/sqlite/SQLiteDatabase:query	(Ljava/lang/String;[Ljava/lang/String;Ljava/lang/String;[Ljava/lang/String;Ljava/lang/String;Ljava/lang/String;Ljava/lang/String;)Landroid/database/Cursor;
    //   75: astore 5
    //   77: aload 5
    //   79: astore_2
    //   80: aload 5
    //   82: invokeinterface 215 1 0
    //   87: ifne +26 -> 113
    //   90: aload 5
    //   92: astore_2
    //   93: invokestatic 1412	java/util/Collections:emptyMap	()Ljava/util/Map;
    //   96: astore 6
    //   98: aload 5
    //   100: ifnull +10 -> 110
    //   103: aload 5
    //   105: invokeinterface 222 1 0
    //   110: aload 6
    //   112: areturn
    //   113: aload 5
    //   115: astore_2
    //   116: aload 5
    //   118: iconst_1
    //   119: invokeinterface 607 2 0
    //   124: astore 6
    //   126: aload 5
    //   128: astore_2
    //   129: aload 6
    //   131: iconst_0
    //   132: aload 6
    //   134: arraylength
    //   135: invokestatic 613	com/google/android/gms/internal/measurement/zzyx:zzj	([BII)Lcom/google/android/gms/internal/measurement/zzyx;
    //   138: astore 6
    //   140: aload 5
    //   142: astore_2
    //   143: new 412	com/google/android/gms/internal/measurement/zzfy
    //   146: dup
    //   147: invokespecial 1422	com/google/android/gms/internal/measurement/zzfy:<init>	()V
    //   150: astore 9
    //   152: aload 5
    //   154: astore_2
    //   155: aload 9
    //   157: aload 6
    //   159: invokevirtual 619	com/google/android/gms/internal/measurement/zzzg:zza	(Lcom/google/android/gms/internal/measurement/zzyx;)Lcom/google/android/gms/internal/measurement/zzzg;
    //   162: pop
    //   163: aload 5
    //   165: astore_2
    //   166: aload 5
    //   168: iconst_0
    //   169: invokeinterface 1056 2 0
    //   174: istore_3
    //   175: aload 5
    //   177: astore_2
    //   178: aload 8
    //   180: iload_3
    //   181: invokestatic 262	java/lang/Integer:valueOf	(I)Ljava/lang/Integer;
    //   184: invokeinterface 1415 2 0
    //   189: checkcast 463	java/util/List
    //   192: astore 7
    //   194: aload 7
    //   196: astore 6
    //   198: aload 7
    //   200: ifnonnull +32 -> 232
    //   203: aload 5
    //   205: astore_2
    //   206: new 460	java/util/ArrayList
    //   209: dup
    //   210: invokespecial 461	java/util/ArrayList:<init>	()V
    //   213: astore 6
    //   215: aload 5
    //   217: astore_2
    //   218: aload 8
    //   220: iload_3
    //   221: invokestatic 262	java/lang/Integer:valueOf	(I)Ljava/lang/Integer;
    //   224: aload 6
    //   226: invokeinterface 1266 3 0
    //   231: pop
    //   232: aload 5
    //   234: astore_2
    //   235: aload 6
    //   237: aload 9
    //   239: invokeinterface 480 2 0
    //   244: pop
    //   245: goto +27 -> 272
    //   248: astore 6
    //   250: aload 5
    //   252: astore_2
    //   253: aload_0
    //   254: invokevirtual 231	com/google/android/gms/measurement/internal/zzco:zzgo	()Lcom/google/android/gms/measurement/internal/zzap;
    //   257: invokevirtual 237	com/google/android/gms/measurement/internal/zzap:zzjd	()Lcom/google/android/gms/measurement/internal/zzar;
    //   260: ldc_w 1424
    //   263: aload_1
    //   264: invokestatic 348	com/google/android/gms/measurement/internal/zzap:zzbv	(Ljava/lang/String;)Ljava/lang/Object;
    //   267: aload 6
    //   269: invokevirtual 245	com/google/android/gms/measurement/internal/zzar:zze	(Ljava/lang/String;Ljava/lang/Object;Ljava/lang/Object;)V
    //   272: aload 5
    //   274: astore_2
    //   275: aload 5
    //   277: invokeinterface 1066 1 0
    //   282: istore 4
    //   284: iload 4
    //   286: ifne -173 -> 113
    //   289: aload 5
    //   291: ifnull +10 -> 301
    //   294: aload 5
    //   296: invokeinterface 222 1 0
    //   301: aload 8
    //   303: areturn
    //   304: astore 6
    //   306: goto +14 -> 320
    //   309: astore_1
    //   310: aconst_null
    //   311: astore_2
    //   312: goto +45 -> 357
    //   315: astore 6
    //   317: aconst_null
    //   318: astore 5
    //   320: aload 5
    //   322: astore_2
    //   323: aload_0
    //   324: invokevirtual 231	com/google/android/gms/measurement/internal/zzco:zzgo	()Lcom/google/android/gms/measurement/internal/zzap;
    //   327: invokevirtual 237	com/google/android/gms/measurement/internal/zzap:zzjd	()Lcom/google/android/gms/measurement/internal/zzar;
    //   330: ldc_w 517
    //   333: aload_1
    //   334: invokestatic 348	com/google/android/gms/measurement/internal/zzap:zzbv	(Ljava/lang/String;)Ljava/lang/Object;
    //   337: aload 6
    //   339: invokevirtual 245	com/google/android/gms/measurement/internal/zzar:zze	(Ljava/lang/String;Ljava/lang/Object;Ljava/lang/Object;)V
    //   342: aload 5
    //   344: ifnull +10 -> 354
    //   347: aload 5
    //   349: invokeinterface 222 1 0
    //   354: aconst_null
    //   355: areturn
    //   356: astore_1
    //   357: aload_2
    //   358: ifnull +9 -> 367
    //   361: aload_2
    //   362: invokeinterface 222 1 0
    //   367: aload_1
    //   368: athrow
    // Local variable table:
    //   start	length	slot	name	signature
    //   0	369	0	this	zzq
    //   0	369	1	paramString1	String
    //   0	369	2	paramString2	String
    //   174	47	3	i	int
    //   282	3	4	bool	boolean
    //   31	317	5	localObject1	Object
    //   96	140	6	localObject2	Object
    //   248	20	6	localIOException	IOException
    //   304	1	6	localSQLiteException1	SQLiteException
    //   315	23	6	localSQLiteException2	SQLiteException
    //   192	7	7	localList	List
    //   25	277	8	localArrayMap	android.support.v4.util.ArrayMap
    //   150	88	9	localZzfy	zzfy
    // Exception table:
    //   from	to	target	type
    //   155	163	248	java/io/IOException
    //   80	90	304	android/database/sqlite/SQLiteException
    //   93	98	304	android/database/sqlite/SQLiteException
    //   116	126	304	android/database/sqlite/SQLiteException
    //   129	140	304	android/database/sqlite/SQLiteException
    //   143	152	304	android/database/sqlite/SQLiteException
    //   155	163	304	android/database/sqlite/SQLiteException
    //   166	175	304	android/database/sqlite/SQLiteException
    //   178	194	304	android/database/sqlite/SQLiteException
    //   206	215	304	android/database/sqlite/SQLiteException
    //   218	232	304	android/database/sqlite/SQLiteException
    //   235	245	304	android/database/sqlite/SQLiteException
    //   253	272	304	android/database/sqlite/SQLiteException
    //   275	284	304	android/database/sqlite/SQLiteException
    //   33	77	309	finally
    //   33	77	315	android/database/sqlite/SQLiteException
    //   80	90	356	finally
    //   93	98	356	finally
    //   116	126	356	finally
    //   129	140	356	finally
    //   143	152	356	finally
    //   155	163	356	finally
    //   166	175	356	finally
    //   178	194	356	finally
    //   206	215	356	finally
    //   218	232	356	finally
    //   235	245	356	finally
    //   253	272	356	finally
    //   275	284	356	finally
    //   323	342	356	finally
  }
  
  /* Error */
  @WorkerThread
  @VisibleForTesting
  protected final long zzn(String paramString1, String paramString2)
  {
    // Byte code:
    //   0: aload_1
    //   1: invokestatic 297	com/google/android/gms/common/internal/Preconditions:checkNotEmpty	(Ljava/lang/String;)Ljava/lang/String;
    //   4: pop
    //   5: aload_2
    //   6: invokestatic 297	com/google/android/gms/common/internal/Preconditions:checkNotEmpty	(Ljava/lang/String;)Ljava/lang/String;
    //   9: pop
    //   10: aload_0
    //   11: invokevirtual 327	com/google/android/gms/measurement/internal/zzco:zzaf	()V
    //   14: aload_0
    //   15: invokevirtual 324	com/google/android/gms/measurement/internal/zzez:zzcl	()V
    //   18: aload_0
    //   19: invokevirtual 203	com/google/android/gms/measurement/internal/zzq:getWritableDatabase	()Landroid/database/sqlite/SQLiteDatabase;
    //   22: astore 8
    //   24: aload 8
    //   26: invokevirtual 541	android/database/sqlite/SQLiteDatabase:beginTransaction	()V
    //   29: new 488	java/lang/StringBuilder
    //   32: dup
    //   33: aload_2
    //   34: invokestatic 355	java/lang/String:valueOf	(Ljava/lang/Object;)Ljava/lang/String;
    //   37: invokevirtual 491	java/lang/String:length	()I
    //   40: bipush 32
    //   42: iadd
    //   43: invokespecial 494	java/lang/StringBuilder:<init>	(I)V
    //   46: astore 7
    //   48: aload 7
    //   50: ldc_w 1429
    //   53: invokevirtual 500	java/lang/StringBuilder:append	(Ljava/lang/String;)Ljava/lang/StringBuilder;
    //   56: pop
    //   57: aload 7
    //   59: aload_2
    //   60: invokevirtual 500	java/lang/StringBuilder:append	(Ljava/lang/String;)Ljava/lang/StringBuilder;
    //   63: pop
    //   64: aload 7
    //   66: ldc_w 1431
    //   69: invokevirtual 500	java/lang/StringBuilder:append	(Ljava/lang/String;)Ljava/lang/StringBuilder;
    //   72: pop
    //   73: aload_0
    //   74: aload 7
    //   76: invokevirtual 505	java/lang/StringBuilder:toString	()Ljava/lang/String;
    //   79: iconst_1
    //   80: anewarray 19	java/lang/String
    //   83: dup
    //   84: iconst_0
    //   85: aload_1
    //   86: aastore
    //   87: ldc2_w 402
    //   90: invokespecial 1276	com/google/android/gms/measurement/internal/zzq:zza	(Ljava/lang/String;[Ljava/lang/String;J)J
    //   93: lstore 5
    //   95: lload 5
    //   97: lstore_3
    //   98: lload 5
    //   100: ldc2_w 402
    //   103: lcmp
    //   104: ifne +92 -> 196
    //   107: new 303	android/content/ContentValues
    //   110: dup
    //   111: invokespecial 379	android/content/ContentValues:<init>	()V
    //   114: astore 7
    //   116: aload 7
    //   118: ldc_w 381
    //   121: aload_1
    //   122: invokevirtual 307	android/content/ContentValues:put	(Ljava/lang/String;Ljava/lang/String;)V
    //   125: aload 7
    //   127: ldc_w 1433
    //   130: iconst_0
    //   131: invokestatic 262	java/lang/Integer:valueOf	(I)Ljava/lang/Integer;
    //   134: invokevirtual 386	android/content/ContentValues:put	(Ljava/lang/String;Ljava/lang/Integer;)V
    //   137: aload 7
    //   139: ldc -97
    //   141: iconst_0
    //   142: invokestatic 262	java/lang/Integer:valueOf	(I)Ljava/lang/Integer;
    //   145: invokevirtual 386	android/content/ContentValues:put	(Ljava/lang/String;Ljava/lang/Integer;)V
    //   148: aload 8
    //   150: ldc_w 1435
    //   153: aconst_null
    //   154: aload 7
    //   156: iconst_5
    //   157: invokevirtual 401	android/database/sqlite/SQLiteDatabase:insertWithOnConflict	(Ljava/lang/String;Ljava/lang/String;Landroid/content/ContentValues;I)J
    //   160: ldc2_w 402
    //   163: lcmp
    //   164: ifne +30 -> 194
    //   167: aload_0
    //   168: invokevirtual 231	com/google/android/gms/measurement/internal/zzco:zzgo	()Lcom/google/android/gms/measurement/internal/zzap;
    //   171: invokevirtual 237	com/google/android/gms/measurement/internal/zzap:zzjd	()Lcom/google/android/gms/measurement/internal/zzar;
    //   174: ldc_w 1437
    //   177: aload_1
    //   178: invokestatic 348	com/google/android/gms/measurement/internal/zzap:zzbv	(Ljava/lang/String;)Ljava/lang/Object;
    //   181: aload_2
    //   182: invokevirtual 245	com/google/android/gms/measurement/internal/zzar:zze	(Ljava/lang/String;Ljava/lang/Object;Ljava/lang/Object;)V
    //   185: aload 8
    //   187: invokevirtual 544	android/database/sqlite/SQLiteDatabase:endTransaction	()V
    //   190: ldc2_w 402
    //   193: lreturn
    //   194: lconst_0
    //   195: lstore_3
    //   196: new 303	android/content/ContentValues
    //   199: dup
    //   200: invokespecial 379	android/content/ContentValues:<init>	()V
    //   203: astore 7
    //   205: aload 7
    //   207: ldc_w 381
    //   210: aload_1
    //   211: invokevirtual 307	android/content/ContentValues:put	(Ljava/lang/String;Ljava/lang/String;)V
    //   214: aload 7
    //   216: aload_2
    //   217: lconst_1
    //   218: lload_3
    //   219: ladd
    //   220: invokestatic 288	java/lang/Long:valueOf	(J)Ljava/lang/Long;
    //   223: invokevirtual 310	android/content/ContentValues:put	(Ljava/lang/String;Ljava/lang/Long;)V
    //   226: aload 8
    //   228: ldc_w 1435
    //   231: aload 7
    //   233: ldc_w 771
    //   236: iconst_1
    //   237: anewarray 19	java/lang/String
    //   240: dup
    //   241: iconst_0
    //   242: aload_1
    //   243: aastore
    //   244: invokevirtual 664	android/database/sqlite/SQLiteDatabase:update	(Ljava/lang/String;Landroid/content/ContentValues;Ljava/lang/String;[Ljava/lang/String;)I
    //   247: i2l
    //   248: lconst_0
    //   249: lcmp
    //   250: ifne +30 -> 280
    //   253: aload_0
    //   254: invokevirtual 231	com/google/android/gms/measurement/internal/zzco:zzgo	()Lcom/google/android/gms/measurement/internal/zzap;
    //   257: invokevirtual 237	com/google/android/gms/measurement/internal/zzap:zzjd	()Lcom/google/android/gms/measurement/internal/zzar;
    //   260: ldc_w 1439
    //   263: aload_1
    //   264: invokestatic 348	com/google/android/gms/measurement/internal/zzap:zzbv	(Ljava/lang/String;)Ljava/lang/Object;
    //   267: aload_2
    //   268: invokevirtual 245	com/google/android/gms/measurement/internal/zzar:zze	(Ljava/lang/String;Ljava/lang/Object;Ljava/lang/Object;)V
    //   271: aload 8
    //   273: invokevirtual 544	android/database/sqlite/SQLiteDatabase:endTransaction	()V
    //   276: ldc2_w 402
    //   279: lreturn
    //   280: aload 8
    //   282: invokevirtual 550	android/database/sqlite/SQLiteDatabase:setTransactionSuccessful	()V
    //   285: aload 8
    //   287: invokevirtual 544	android/database/sqlite/SQLiteDatabase:endTransaction	()V
    //   290: lload_3
    //   291: lreturn
    //   292: astore 7
    //   294: goto +11 -> 305
    //   297: astore_1
    //   298: goto +34 -> 332
    //   301: astore 7
    //   303: lconst_0
    //   304: lstore_3
    //   305: aload_0
    //   306: invokevirtual 231	com/google/android/gms/measurement/internal/zzco:zzgo	()Lcom/google/android/gms/measurement/internal/zzap;
    //   309: invokevirtual 237	com/google/android/gms/measurement/internal/zzap:zzjd	()Lcom/google/android/gms/measurement/internal/zzar;
    //   312: ldc_w 1441
    //   315: aload_1
    //   316: invokestatic 348	com/google/android/gms/measurement/internal/zzap:zzbv	(Ljava/lang/String;)Ljava/lang/Object;
    //   319: aload_2
    //   320: aload 7
    //   322: invokevirtual 359	com/google/android/gms/measurement/internal/zzar:zzd	(Ljava/lang/String;Ljava/lang/Object;Ljava/lang/Object;Ljava/lang/Object;)V
    //   325: aload 8
    //   327: invokevirtual 544	android/database/sqlite/SQLiteDatabase:endTransaction	()V
    //   330: lload_3
    //   331: lreturn
    //   332: aload 8
    //   334: invokevirtual 544	android/database/sqlite/SQLiteDatabase:endTransaction	()V
    //   337: aload_1
    //   338: athrow
    // Local variable table:
    //   start	length	slot	name	signature
    //   0	339	0	this	zzq
    //   0	339	1	paramString1	String
    //   0	339	2	paramString2	String
    //   97	234	3	l1	long
    //   93	6	5	l2	long
    //   46	186	7	localObject	Object
    //   292	1	7	localSQLiteException1	SQLiteException
    //   301	20	7	localSQLiteException2	SQLiteException
    //   22	311	8	localSQLiteDatabase	SQLiteDatabase
    // Exception table:
    //   from	to	target	type
    //   196	271	292	android/database/sqlite/SQLiteException
    //   280	285	292	android/database/sqlite/SQLiteException
    //   29	95	297	finally
    //   107	185	297	finally
    //   196	271	297	finally
    //   280	285	297	finally
    //   305	325	297	finally
    //   29	95	301	android/database/sqlite/SQLiteException
    //   107	185	301	android/database/sqlite/SQLiteException
  }
}
