package com.google.android.gms.measurement.internal;

import android.support.v4.util.ArrayMap;
import android.text.TextUtils;
import com.google.android.gms.common.internal.Preconditions;
import com.google.android.gms.common.util.VisibleForTesting;
import com.google.android.gms.internal.measurement.zzfv;
import com.google.android.gms.internal.measurement.zzfw;
import com.google.android.gms.internal.measurement.zzfx;
import com.google.android.gms.internal.measurement.zzfy;
import com.google.android.gms.internal.measurement.zzfz;
import com.google.android.gms.internal.measurement.zzge;
import com.google.android.gms.internal.measurement.zzgg;
import com.google.android.gms.internal.measurement.zzgl;
import java.math.BigDecimal;
import java.util.ArrayList;
import java.util.Arrays;
import java.util.HashSet;
import java.util.Iterator;
import java.util.List;
import java.util.Locale;
import java.util.Map;
import java.util.Set;
import java.util.regex.Matcher;
import java.util.regex.Pattern;
import java.util.regex.PatternSyntaxException;

final class zzj
  extends zzez
{
  zzj(zzfa paramZzfa)
  {
    super(paramZzfa);
  }
  
  private final Boolean zza(double paramDouble, zzfx paramZzfx)
  {
    try
    {
      paramZzfx = zza(new BigDecimal(paramDouble), paramZzfx, Math.ulp(paramDouble));
      return paramZzfx;
    }
    catch (NumberFormatException paramZzfx)
    {
      for (;;) {}
    }
    return null;
  }
  
  private final Boolean zza(long paramLong, zzfx paramZzfx)
  {
    try
    {
      paramZzfx = zza(new BigDecimal(paramLong), paramZzfx, 0.0D);
      return paramZzfx;
    }
    catch (NumberFormatException paramZzfx)
    {
      for (;;) {}
    }
    return null;
  }
  
  private final Boolean zza(zzfv paramZzfv, String paramString, zzgg[] paramArrayOfZzgg, long paramLong)
  {
    if (zzavi != null)
    {
      localObject1 = zza(paramLong, zzavi);
      if (localObject1 == null) {
        return null;
      }
      if (!((Boolean)localObject1).booleanValue()) {
        return Boolean.valueOf(false);
      }
    }
    Object localObject2 = new HashSet();
    Object localObject1 = zzavg;
    int j = localObject1.length;
    int i = 0;
    Object localObject3;
    while (i < j)
    {
      localObject3 = localObject1[i];
      if (TextUtils.isEmpty(zzavn))
      {
        zzgo().zzjg().zzg("null or empty param name in filter. event", zzgl().zzbs(paramString));
        return null;
      }
      ((Set)localObject2).add(zzavn);
      i += 1;
    }
    localObject1 = new ArrayMap();
    j = paramArrayOfZzgg.length;
    i = 0;
    while (i < j)
    {
      localObject3 = paramArrayOfZzgg[i];
      if (((Set)localObject2).contains(name)) {
        if (zzawx != null)
        {
          ((Map)localObject1).put(name, zzawx);
        }
        else if (zzauh != null)
        {
          ((Map)localObject1).put(name, zzauh);
        }
        else if (zzamp != null)
        {
          ((Map)localObject1).put(name, zzamp);
        }
        else
        {
          zzgo().zzjg().zze("Unknown value for param. event, param", zzgl().zzbs(paramString), zzgl().zzbt(name));
          return null;
        }
      }
      i += 1;
    }
    paramArrayOfZzgg = zzavg;
    j = paramArrayOfZzgg.length;
    i = 0;
    while (i < j)
    {
      paramZzfv = paramArrayOfZzgg[i];
      boolean bool = Boolean.TRUE.equals(zzavm);
      localObject2 = zzavn;
      if (TextUtils.isEmpty((CharSequence)localObject2))
      {
        zzgo().zzjg().zzg("Event has empty param name. event", zzgl().zzbs(paramString));
        return null;
      }
      localObject3 = ((Map)localObject1).get(localObject2);
      if ((localObject3 instanceof Long))
      {
        if (zzavl == null)
        {
          zzgo().zzjg().zze("No number filter for long param. event, param", zzgl().zzbs(paramString), zzgl().zzbt((String)localObject2));
          return null;
        }
        paramZzfv = zza(((Long)localObject3).longValue(), zzavl);
        if (paramZzfv == null) {
          return null;
        }
        if ((true ^ paramZzfv.booleanValue() ^ bool)) {
          return Boolean.valueOf(false);
        }
      }
      else if ((localObject3 instanceof Double))
      {
        if (zzavl == null)
        {
          zzgo().zzjg().zze("No number filter for double param. event, param", zzgl().zzbs(paramString), zzgl().zzbt((String)localObject2));
          return null;
        }
        paramZzfv = zza(((Double)localObject3).doubleValue(), zzavl);
        if (paramZzfv == null) {
          return null;
        }
        if ((true ^ paramZzfv.booleanValue() ^ bool)) {
          return Boolean.valueOf(false);
        }
      }
      else
      {
        if (!(localObject3 instanceof String)) {
          break label719;
        }
        if (zzavk != null)
        {
          paramZzfv = zza((String)localObject3, zzavk);
        }
        else
        {
          if (zzavl == null) {
            break label688;
          }
          localObject3 = (String)localObject3;
          if (!zzfg.zzcp((String)localObject3)) {
            break label657;
          }
          paramZzfv = zza((String)localObject3, zzavl);
        }
        if (paramZzfv == null) {
          return null;
        }
        if ((true ^ paramZzfv.booleanValue() ^ bool)) {
          return Boolean.valueOf(false);
        }
      }
      i += 1;
      continue;
      label657:
      zzgo().zzjg().zze("Invalid param value for number filter. event, param", zzgl().zzbs(paramString), zzgl().zzbt((String)localObject2));
      return null;
      label688:
      zzgo().zzjg().zze("No filter for String param. event, param", zzgl().zzbs(paramString), zzgl().zzbt((String)localObject2));
      return null;
      label719:
      if (localObject3 == null)
      {
        zzgo().zzjl().zze("Missing param for filter. event, param", zzgl().zzbs(paramString), zzgl().zzbt((String)localObject2));
        return Boolean.valueOf(false);
      }
      zzgo().zzjg().zze("Unknown param type. event, param", zzgl().zzbs(paramString), zzgl().zzbt((String)localObject2));
      return null;
    }
    return Boolean.valueOf(true);
  }
  
  private final Boolean zza(zzfy paramZzfy, zzgl paramZzgl)
  {
    paramZzfy = zzavv;
    if (paramZzfy == null)
    {
      zzgo().zzjg().zzg("Missing property filter. property", zzgl().zzbu(name));
      return null;
    }
    boolean bool = Boolean.TRUE.equals(zzavm);
    if (zzawx != null)
    {
      if (zzavl == null)
      {
        zzgo().zzjg().zzg("No number filter for long property. property", zzgl().zzbu(name));
        return null;
      }
      return zza(zza(zzawx.longValue(), zzavl), bool);
    }
    if (zzauh != null)
    {
      if (zzavl == null)
      {
        zzgo().zzjg().zzg("No number filter for double property. property", zzgl().zzbu(name));
        return null;
      }
      return zza(zza(zzauh.doubleValue(), zzavl), bool);
    }
    if (zzamp != null)
    {
      if (zzavk == null)
      {
        if (zzavl == null)
        {
          zzgo().zzjg().zzg("No string or number filter defined. property", zzgl().zzbu(name));
          return null;
        }
        if (zzfg.zzcp(zzamp)) {
          return zza(zza(zzamp, zzavl), bool);
        }
        zzgo().zzjg().zze("Invalid user property value for Numeric number filter. property, value", zzgl().zzbu(name), zzamp);
        return null;
      }
      return zza(zza(zzamp, zzavk), bool);
    }
    zzgo().zzjg().zzg("User property has no value, property", zzgl().zzbu(name));
    return null;
  }
  
  @VisibleForTesting
  private static Boolean zza(Boolean paramBoolean, boolean paramBoolean1)
  {
    if (paramBoolean == null) {
      return null;
    }
    return Boolean.valueOf(paramBoolean.booleanValue() ^ paramBoolean1);
  }
  
  private final Boolean zza(String paramString1, int paramInt, boolean paramBoolean, String paramString2, List<String> paramList, String paramString3)
  {
    if (paramString1 == null) {
      return null;
    }
    if (paramInt == 6)
    {
      if ((paramList == null) || (paramList.size() == 0)) {
        return null;
      }
    }
    else if (paramString2 == null) {
      return null;
    }
    String str = paramString1;
    if (!paramBoolean) {
      if (paramInt == 1) {
        str = paramString1;
      } else {
        str = paramString1.toUpperCase(Locale.ENGLISH);
      }
    }
    switch (paramInt)
    {
    default: 
      return null;
    case 6: 
      return Boolean.valueOf(paramList.contains(str));
    case 5: 
      return Boolean.valueOf(str.equals(paramString2));
    case 4: 
      return Boolean.valueOf(str.contains(paramString2));
    case 3: 
      return Boolean.valueOf(str.endsWith(paramString2));
    case 2: 
      return Boolean.valueOf(str.startsWith(paramString2));
    }
    if (paramBoolean) {
      paramInt = 0;
    } else {
      paramInt = 66;
    }
    try
    {
      paramBoolean = Pattern.compile(paramString3, paramInt).matcher(str).matches();
      return Boolean.valueOf(paramBoolean);
    }
    catch (PatternSyntaxException paramString1)
    {
      for (;;) {}
    }
    zzgo().zzjg().zzg("Invalid regular expression in REGEXP audience filter. expression", paramString3);
    return null;
  }
  
  private final Boolean zza(String paramString, zzfx paramZzfx)
  {
    if (!zzfg.zzcp(paramString)) {
      return null;
    }
    try
    {
      paramString = zza(new BigDecimal(paramString), paramZzfx, 0.0D);
      return paramString;
    }
    catch (NumberFormatException paramString) {}
    return null;
  }
  
  @VisibleForTesting
  private final Boolean zza(String paramString, zzfz paramZzfz)
  {
    Preconditions.checkNotNull(paramZzfz);
    if (paramString == null) {
      return null;
    }
    if (zzavw != null)
    {
      if (zzavw.intValue() == 0) {
        return null;
      }
      if (zzavw.intValue() == 6)
      {
        if ((zzavz == null) || (zzavz.length == 0)) {
          return null;
        }
      }
      else if (zzavx == null) {
        return null;
      }
      int j = zzavw.intValue();
      Object localObject1 = zzavy;
      int i = 0;
      boolean bool;
      if ((localObject1 != null) && (zzavy.booleanValue())) {
        bool = true;
      } else {
        bool = false;
      }
      if ((!bool) && (j != 1) && (j != 6)) {
        localObject1 = zzavx.toUpperCase(Locale.ENGLISH);
      } else {
        localObject1 = zzavx;
      }
      Object localObject2;
      if (zzavz == null)
      {
        paramZzfz = null;
      }
      else
      {
        localObject2 = zzavz;
        if (bool)
        {
          paramZzfz = Arrays.asList((Object[])localObject2);
        }
        else
        {
          paramZzfz = new ArrayList();
          int k = localObject2.length;
          while (i < k)
          {
            paramZzfz.add(localObject2[i].toUpperCase(Locale.ENGLISH));
            i += 1;
          }
        }
      }
      if (j == 1) {
        localObject2 = localObject1;
      } else {
        localObject2 = null;
      }
      return zza(paramString, j, bool, (String)localObject1, paramZzfz, (String)localObject2);
    }
    return null;
  }
  
  @VisibleForTesting
  private static Boolean zza(BigDecimal paramBigDecimal, zzfx paramZzfx, double paramDouble)
  {
    Preconditions.checkNotNull(paramZzfx);
    int i;
    if (zzavo != null)
    {
      if (zzavo.intValue() == 0) {
        return null;
      }
      if (zzavo.intValue() == 4)
      {
        if ((zzavr == null) || (zzavs == null)) {
          return null;
        }
      }
      else if (zzavq == null) {
        return null;
      }
      i = zzavo.intValue();
      if (zzavo.intValue() == 4) {
        if (zzfg.zzcp(zzavr)) {
          if (!zzfg.zzcp(zzavs)) {
            return null;
          }
        }
      }
    }
    for (;;)
    {
      try
      {
        localBigDecimal = new BigDecimal(zzavr);
        localObject = new BigDecimal(zzavs);
        paramZzfx = localBigDecimal;
        localBigDecimal = null;
        continue;
        return null;
        if (!zzfg.zzcp(zzavq)) {
          return null;
        }
      }
      catch (NumberFormatException paramBigDecimal)
      {
        BigDecimal localBigDecimal;
        Object localObject;
        boolean bool3;
        boolean bool1;
        boolean bool4;
        boolean bool5;
        boolean bool2;
        return null;
      }
      try
      {
        localBigDecimal = new BigDecimal(zzavq);
        paramZzfx = null;
        localObject = paramZzfx;
        if (i == 4)
        {
          if (paramZzfx == null) {
            return null;
          }
        }
        else {
          if (localBigDecimal == null) {
            continue;
          }
        }
        bool3 = false;
        bool1 = false;
        bool4 = false;
        bool5 = false;
        bool2 = false;
        switch (i)
        {
        default: 
          return null;
        case 4: 
          bool1 = bool2;
          if (paramBigDecimal.compareTo(paramZzfx) != -1)
          {
            bool1 = bool2;
            if (paramBigDecimal.compareTo((BigDecimal)localObject) != 1) {
              bool1 = true;
            }
          }
          return Boolean.valueOf(bool1);
        case 3: 
          if (paramDouble != 0.0D)
          {
            bool1 = bool3;
            if (paramBigDecimal.compareTo(localBigDecimal.subtract(new BigDecimal(paramDouble).multiply(new BigDecimal(2)))) == 1)
            {
              bool1 = bool3;
              if (paramBigDecimal.compareTo(localBigDecimal.add(new BigDecimal(paramDouble).multiply(new BigDecimal(2)))) == -1) {
                bool1 = true;
              }
            }
            return Boolean.valueOf(bool1);
          }
          if (paramBigDecimal.compareTo(localBigDecimal) == 0) {
            bool1 = true;
          }
          return Boolean.valueOf(bool1);
        case 2: 
          bool1 = bool4;
          if (paramBigDecimal.compareTo(localBigDecimal) == 1) {
            bool1 = true;
          }
          return Boolean.valueOf(bool1);
        }
        bool1 = bool5;
        if (paramBigDecimal.compareTo(localBigDecimal) == -1) {
          bool1 = true;
        }
        return Boolean.valueOf(bool1);
        return null;
      }
      catch (NumberFormatException paramBigDecimal) {}
    }
    return null;
    return null;
  }
  
  private static void zza(Map<Integer, Long> paramMap, int paramInt, long paramLong)
  {
    Long localLong = (Long)paramMap.get(Integer.valueOf(paramInt));
    paramLong /= 1000L;
    if ((localLong == null) || (paramLong > localLong.longValue())) {
      paramMap.put(Integer.valueOf(paramInt), Long.valueOf(paramLong));
    }
  }
  
  private static void zzb(Map<Integer, List<Long>> paramMap, int paramInt, long paramLong)
  {
    List localList = (List)paramMap.get(Integer.valueOf(paramInt));
    Object localObject = localList;
    if (localList == null)
    {
      localObject = new ArrayList();
      paramMap.put(Integer.valueOf(paramInt), localObject);
    }
    ((List)localObject).add(Long.valueOf(paramLong / 1000L));
  }
  
  private static zzge[] zzd(Map<Integer, Long> paramMap)
  {
    if (paramMap == null) {
      return null;
    }
    int i = 0;
    zzge[] arrayOfZzge = new zzge[paramMap.size()];
    Iterator localIterator = paramMap.keySet().iterator();
    while (localIterator.hasNext())
    {
      Integer localInteger = (Integer)localIterator.next();
      zzge localZzge = new zzge();
      zzawq = localInteger;
      zzawr = ((Long)paramMap.get(localInteger));
      arrayOfZzge[i] = localZzge;
      i += 1;
    }
    return arrayOfZzge;
  }
  
  /* Error */
  @android.support.annotation.WorkerThread
  final com.google.android.gms.internal.measurement.zzgd[] zza(String arg1, com.google.android.gms.internal.measurement.zzgf[] arg2, zzgl[] arg3)
  {
    // Byte code:
    //   0: aload_1
    //   1: astore 19
    //   3: aload_2
    //   4: astore 31
    //   6: aload_1
    //   7: invokestatic 413	com/google/android/gms/common/internal/Preconditions:checkNotEmpty	(Ljava/lang/String;)Ljava/lang/String;
    //   10: pop
    //   11: new 52	java/util/HashSet
    //   14: dup
    //   15: invokespecial 55	java/util/HashSet:<init>	()V
    //   18: astore 18
    //   20: new 109	android/support/v4/util/ArrayMap
    //   23: dup
    //   24: invokespecial 110	android/support/v4/util/ArrayMap:<init>	()V
    //   27: astore 23
    //   29: new 109	android/support/v4/util/ArrayMap
    //   32: dup
    //   33: invokespecial 110	android/support/v4/util/ArrayMap:<init>	()V
    //   36: astore 17
    //   38: new 109	android/support/v4/util/ArrayMap
    //   41: dup
    //   42: invokespecial 110	android/support/v4/util/ArrayMap:<init>	()V
    //   45: astore 16
    //   47: new 109	android/support/v4/util/ArrayMap
    //   50: dup
    //   51: invokespecial 110	android/support/v4/util/ArrayMap:<init>	()V
    //   54: astore 15
    //   56: new 109	android/support/v4/util/ArrayMap
    //   59: dup
    //   60: invokespecial 110	android/support/v4/util/ArrayMap:<init>	()V
    //   63: astore 30
    //   65: aload_0
    //   66: invokevirtual 417	com/google/android/gms/measurement/internal/zzco:zzgq	()Lcom/google/android/gms/measurement/internal/zzn;
    //   69: aload 19
    //   71: getstatic 423	com/google/android/gms/measurement/internal/zzaf:zzakw	Lcom/google/android/gms/measurement/internal/zzaf$zza;
    //   74: invokevirtual 428	com/google/android/gms/measurement/internal/zzn:zzd	(Ljava/lang/String;Lcom/google/android/gms/measurement/internal/zzaf$zza;)Z
    //   77: istore 10
    //   79: aload_0
    //   80: invokevirtual 434	com/google/android/gms/measurement/internal/zzey:zzjq	()Lcom/google/android/gms/measurement/internal/zzq;
    //   83: aload 19
    //   85: invokevirtual 440	com/google/android/gms/measurement/internal/zzq:zzbo	(Ljava/lang/String;)Ljava/util/Map;
    //   88: astore 25
    //   90: aload 15
    //   92: astore 22
    //   94: aload 16
    //   96: astore 21
    //   98: aload 17
    //   100: astore 20
    //   102: aload 18
    //   104: astore 19
    //   106: aload 25
    //   108: ifnull +524 -> 632
    //   111: aload 25
    //   113: invokeinterface 383 1 0
    //   118: invokeinterface 387 1 0
    //   123: astore 24
    //   125: aload 15
    //   127: astore 22
    //   129: aload 16
    //   131: astore 21
    //   133: aload 17
    //   135: astore 20
    //   137: aload 18
    //   139: astore 19
    //   141: aload 24
    //   143: invokeinterface 392 1 0
    //   148: ifeq +484 -> 632
    //   151: aload 24
    //   153: invokeinterface 396 1 0
    //   158: checkcast 307	java/lang/Integer
    //   161: invokevirtual 310	java/lang/Integer:intValue	()I
    //   164: istore 6
    //   166: aload 25
    //   168: iload 6
    //   170: invokestatic 366	java/lang/Integer:valueOf	(I)Ljava/lang/Integer;
    //   173: invokeinterface 160 2 0
    //   178: checkcast 442	com/google/android/gms/internal/measurement/zzgj
    //   181: astore 26
    //   183: aload 17
    //   185: iload 6
    //   187: invokestatic 366	java/lang/Integer:valueOf	(I)Ljava/lang/Integer;
    //   190: invokeinterface 160 2 0
    //   195: checkcast 444	java/util/BitSet
    //   198: astore 21
    //   200: aload 16
    //   202: iload 6
    //   204: invokestatic 366	java/lang/Integer:valueOf	(I)Ljava/lang/Integer;
    //   207: invokeinterface 160 2 0
    //   212: checkcast 444	java/util/BitSet
    //   215: astore 20
    //   217: iload 10
    //   219: ifeq +114 -> 333
    //   222: new 109	android/support/v4/util/ArrayMap
    //   225: dup
    //   226: invokespecial 110	android/support/v4/util/ArrayMap:<init>	()V
    //   229: astore 22
    //   231: aload 26
    //   233: ifnull +78 -> 311
    //   236: aload 26
    //   238: getfield 448	com/google/android/gms/internal/measurement/zzgj:zzayg	[Lcom/google/android/gms/internal/measurement/zzge;
    //   241: ifnonnull +6 -> 247
    //   244: goto +67 -> 311
    //   247: aload 26
    //   249: getfield 448	com/google/android/gms/internal/measurement/zzgj:zzayg	[Lcom/google/android/gms/internal/measurement/zzge;
    //   252: astore 19
    //   254: aload 19
    //   256: arraylength
    //   257: istore 4
    //   259: iconst_0
    //   260: istore 5
    //   262: iload 5
    //   264: iload 4
    //   266: if_icmpge +45 -> 311
    //   269: aload 19
    //   271: iload 5
    //   273: aaload
    //   274: astore 27
    //   276: aload 27
    //   278: getfield 400	com/google/android/gms/internal/measurement/zzge:zzawq	Ljava/lang/Integer;
    //   281: ifnull +21 -> 302
    //   284: aload 22
    //   286: aload 27
    //   288: getfield 400	com/google/android/gms/internal/measurement/zzge:zzawq	Ljava/lang/Integer;
    //   291: aload 27
    //   293: getfield 403	com/google/android/gms/internal/measurement/zzge:zzawr	Ljava/lang/Long;
    //   296: invokeinterface 128 3 0
    //   301: pop
    //   302: iload 5
    //   304: iconst_1
    //   305: iadd
    //   306: istore 5
    //   308: goto -46 -> 262
    //   311: aload 15
    //   313: iload 6
    //   315: invokestatic 366	java/lang/Integer:valueOf	(I)Ljava/lang/Integer;
    //   318: aload 22
    //   320: invokeinterface 128 3 0
    //   325: pop
    //   326: aload 22
    //   328: astore 19
    //   330: goto +6 -> 336
    //   333: aconst_null
    //   334: astore 19
    //   336: aload 21
    //   338: ifnonnull +54 -> 392
    //   341: new 444	java/util/BitSet
    //   344: dup
    //   345: invokespecial 449	java/util/BitSet:<init>	()V
    //   348: astore 21
    //   350: aload 17
    //   352: iload 6
    //   354: invokestatic 366	java/lang/Integer:valueOf	(I)Ljava/lang/Integer;
    //   357: aload 21
    //   359: invokeinterface 128 3 0
    //   364: pop
    //   365: new 444	java/util/BitSet
    //   368: dup
    //   369: invokespecial 449	java/util/BitSet:<init>	()V
    //   372: astore 20
    //   374: aload 16
    //   376: iload 6
    //   378: invokestatic 366	java/lang/Integer:valueOf	(I)Ljava/lang/Integer;
    //   381: aload 20
    //   383: invokeinterface 128 3 0
    //   388: pop
    //   389: goto +3 -> 392
    //   392: iconst_0
    //   393: istore 4
    //   395: iload 4
    //   397: aload 26
    //   399: getfield 453	com/google/android/gms/internal/measurement/zzgj:zzaye	[J
    //   402: arraylength
    //   403: bipush 6
    //   405: ishl
    //   406: if_icmpge +107 -> 513
    //   409: aload 26
    //   411: getfield 453	com/google/android/gms/internal/measurement/zzgj:zzaye	[J
    //   414: iload 4
    //   416: invokestatic 456	com/google/android/gms/measurement/internal/zzfg:zza	([JI)Z
    //   419: ifeq +59 -> 478
    //   422: aload_0
    //   423: invokevirtual 77	com/google/android/gms/measurement/internal/zzco:zzgo	()Lcom/google/android/gms/measurement/internal/zzap;
    //   426: invokevirtual 206	com/google/android/gms/measurement/internal/zzap:zzjl	()Lcom/google/android/gms/measurement/internal/zzar;
    //   429: ldc_w 458
    //   432: iload 6
    //   434: invokestatic 366	java/lang/Integer:valueOf	(I)Ljava/lang/Integer;
    //   437: iload 4
    //   439: invokestatic 366	java/lang/Integer:valueOf	(I)Ljava/lang/Integer;
    //   442: invokevirtual 144	com/google/android/gms/measurement/internal/zzar:zze	(Ljava/lang/String;Ljava/lang/Object;Ljava/lang/Object;)V
    //   445: aload 20
    //   447: iload 4
    //   449: invokevirtual 461	java/util/BitSet:set	(I)V
    //   452: aload 26
    //   454: getfield 464	com/google/android/gms/internal/measurement/zzgj:zzayf	[J
    //   457: iload 4
    //   459: invokestatic 456	com/google/android/gms/measurement/internal/zzfg:zza	([JI)Z
    //   462: ifeq +16 -> 478
    //   465: aload 21
    //   467: iload 4
    //   469: invokevirtual 461	java/util/BitSet:set	(I)V
    //   472: iconst_1
    //   473: istore 5
    //   475: goto +6 -> 481
    //   478: iconst_0
    //   479: istore 5
    //   481: aload 19
    //   483: ifnull +21 -> 504
    //   486: iload 5
    //   488: ifne +16 -> 504
    //   491: aload 19
    //   493: iload 4
    //   495: invokestatic 366	java/lang/Integer:valueOf	(I)Ljava/lang/Integer;
    //   498: invokeinterface 467 2 0
    //   503: pop
    //   504: iload 4
    //   506: iconst_1
    //   507: iadd
    //   508: istore 4
    //   510: goto -115 -> 395
    //   513: new 469	com/google/android/gms/internal/measurement/zzgd
    //   516: dup
    //   517: invokespecial 470	com/google/android/gms/internal/measurement/zzgd:<init>	()V
    //   520: astore 22
    //   522: aload 23
    //   524: iload 6
    //   526: invokestatic 366	java/lang/Integer:valueOf	(I)Ljava/lang/Integer;
    //   529: aload 22
    //   531: invokeinterface 128 3 0
    //   536: pop
    //   537: aload 22
    //   539: iconst_0
    //   540: invokestatic 50	java/lang/Boolean:valueOf	(Z)Ljava/lang/Boolean;
    //   543: putfield 473	com/google/android/gms/internal/measurement/zzgd:zzawo	Ljava/lang/Boolean;
    //   546: aload 22
    //   548: aload 26
    //   550: putfield 477	com/google/android/gms/internal/measurement/zzgd:zzawn	Lcom/google/android/gms/internal/measurement/zzgj;
    //   553: aload 22
    //   555: new 442	com/google/android/gms/internal/measurement/zzgj
    //   558: dup
    //   559: invokespecial 478	com/google/android/gms/internal/measurement/zzgj:<init>	()V
    //   562: putfield 481	com/google/android/gms/internal/measurement/zzgd:zzawm	Lcom/google/android/gms/internal/measurement/zzgj;
    //   565: aload 22
    //   567: getfield 481	com/google/android/gms/internal/measurement/zzgd:zzawm	Lcom/google/android/gms/internal/measurement/zzgj;
    //   570: aload 21
    //   572: invokestatic 484	com/google/android/gms/measurement/internal/zzfg:zza	(Ljava/util/BitSet;)[J
    //   575: putfield 464	com/google/android/gms/internal/measurement/zzgj:zzayf	[J
    //   578: aload 22
    //   580: getfield 481	com/google/android/gms/internal/measurement/zzgd:zzawm	Lcom/google/android/gms/internal/measurement/zzgj;
    //   583: aload 20
    //   585: invokestatic 484	com/google/android/gms/measurement/internal/zzfg:zza	(Ljava/util/BitSet;)[J
    //   588: putfield 453	com/google/android/gms/internal/measurement/zzgj:zzaye	[J
    //   591: iload 10
    //   593: ifeq +36 -> 629
    //   596: aload 22
    //   598: getfield 481	com/google/android/gms/internal/measurement/zzgd:zzawm	Lcom/google/android/gms/internal/measurement/zzgj;
    //   601: aload 19
    //   603: invokestatic 486	com/google/android/gms/measurement/internal/zzj:zzd	(Ljava/util/Map;)[Lcom/google/android/gms/internal/measurement/zzge;
    //   606: putfield 448	com/google/android/gms/internal/measurement/zzgj:zzayg	[Lcom/google/android/gms/internal/measurement/zzge;
    //   609: aload 30
    //   611: iload 6
    //   613: invokestatic 366	java/lang/Integer:valueOf	(I)Ljava/lang/Integer;
    //   616: new 109	android/support/v4/util/ArrayMap
    //   619: dup
    //   620: invokespecial 110	android/support/v4/util/ArrayMap:<init>	()V
    //   623: invokeinterface 128 3 0
    //   628: pop
    //   629: goto -504 -> 125
    //   632: aload 22
    //   634: astore 18
    //   636: aload 21
    //   638: astore 15
    //   640: aload 20
    //   642: astore 16
    //   644: aload 19
    //   646: astore 17
    //   648: aload 30
    //   650: astore 28
    //   652: aload 23
    //   654: astore 27
    //   656: aload 17
    //   658: astore 29
    //   660: aload 18
    //   662: astore 26
    //   664: aload 15
    //   666: astore 25
    //   668: aload 16
    //   670: astore 24
    //   672: aload 31
    //   674: ifnull +2261 -> 2935
    //   677: new 109	android/support/v4/util/ArrayMap
    //   680: dup
    //   681: invokespecial 110	android/support/v4/util/ArrayMap:<init>	()V
    //   684: astore 20
    //   686: aload 31
    //   688: arraylength
    //   689: istore 6
    //   691: lconst_0
    //   692: lstore 11
    //   694: aconst_null
    //   695: astore 22
    //   697: aconst_null
    //   698: astore 21
    //   700: iconst_0
    //   701: istore 4
    //   703: aload 23
    //   705: astore 19
    //   707: aload 20
    //   709: astore 23
    //   711: aload 30
    //   713: astore 20
    //   715: aload_1
    //   716: astore 30
    //   718: aload 20
    //   720: astore 28
    //   722: aload 19
    //   724: astore 27
    //   726: aload 17
    //   728: astore 29
    //   730: aload 18
    //   732: astore 26
    //   734: aload 15
    //   736: astore 25
    //   738: aload 16
    //   740: astore 24
    //   742: iload 4
    //   744: iload 6
    //   746: if_icmpge +2189 -> 2935
    //   749: aload_2
    //   750: iload 4
    //   752: aaload
    //   753: astore 25
    //   755: aload 25
    //   757: getfield 489	com/google/android/gms/internal/measurement/zzgf:name	Ljava/lang/String;
    //   760: astore 26
    //   762: aload 25
    //   764: getfield 493	com/google/android/gms/internal/measurement/zzgf:zzawt	[Lcom/google/android/gms/internal/measurement/zzgg;
    //   767: astore 24
    //   769: aload_0
    //   770: invokevirtual 417	com/google/android/gms/measurement/internal/zzco:zzgq	()Lcom/google/android/gms/measurement/internal/zzn;
    //   773: aload 30
    //   775: getstatic 496	com/google/android/gms/measurement/internal/zzaf:zzakq	Lcom/google/android/gms/measurement/internal/zzaf$zza;
    //   778: invokevirtual 428	com/google/android/gms/measurement/internal/zzn:zzd	(Ljava/lang/String;Lcom/google/android/gms/measurement/internal/zzaf$zza;)Z
    //   781: ifeq +741 -> 1522
    //   784: aload_0
    //   785: invokevirtual 500	com/google/android/gms/measurement/internal/zzey:zzjo	()Lcom/google/android/gms/measurement/internal/zzfg;
    //   788: pop
    //   789: aload 25
    //   791: ldc_w 502
    //   794: invokestatic 505	com/google/android/gms/measurement/internal/zzfg:zzb	(Lcom/google/android/gms/internal/measurement/zzgf;Ljava/lang/String;)Ljava/lang/Object;
    //   797: checkcast 162	java/lang/Long
    //   800: astore 29
    //   802: aload 29
    //   804: ifnull +9 -> 813
    //   807: iconst_1
    //   808: istore 7
    //   810: goto +6 -> 816
    //   813: iconst_0
    //   814: istore 7
    //   816: iload 7
    //   818: ifeq +20 -> 838
    //   821: aload 26
    //   823: ldc_w 507
    //   826: invokevirtual 264	java/lang/String:equals	(Ljava/lang/Object;)Z
    //   829: ifeq +9 -> 838
    //   832: iconst_1
    //   833: istore 5
    //   835: goto +6 -> 841
    //   838: iconst_0
    //   839: istore 5
    //   841: iload 5
    //   843: ifeq +555 -> 1398
    //   846: aload_0
    //   847: invokevirtual 500	com/google/android/gms/measurement/internal/zzey:zzjo	()Lcom/google/android/gms/measurement/internal/zzfg;
    //   850: pop
    //   851: aload 25
    //   853: ldc_w 509
    //   856: invokestatic 505	com/google/android/gms/measurement/internal/zzfg:zzb	(Lcom/google/android/gms/internal/measurement/zzgf;Ljava/lang/String;)Ljava/lang/Object;
    //   859: checkcast 183	java/lang/String
    //   862: astore 28
    //   864: aload 28
    //   866: invokestatic 71	android/text/TextUtils:isEmpty	(Ljava/lang/CharSequence;)Z
    //   869: ifeq +21 -> 890
    //   872: aload_0
    //   873: invokevirtual 77	com/google/android/gms/measurement/internal/zzco:zzgo	()Lcom/google/android/gms/measurement/internal/zzap;
    //   876: invokevirtual 512	com/google/android/gms/measurement/internal/zzap:zzjd	()Lcom/google/android/gms/measurement/internal/zzar;
    //   879: ldc_w 514
    //   882: aload 29
    //   884: invokevirtual 101	com/google/android/gms/measurement/internal/zzar:zzg	(Ljava/lang/String;Ljava/lang/Object;)V
    //   887: goto +464 -> 1351
    //   890: aload 22
    //   892: ifnull +40 -> 932
    //   895: aload 21
    //   897: ifnull +35 -> 932
    //   900: aload 29
    //   902: invokevirtual 171	java/lang/Long:longValue	()J
    //   905: aload 21
    //   907: invokevirtual 171	java/lang/Long:longValue	()J
    //   910: lcmp
    //   911: ifeq +6 -> 917
    //   914: goto +18 -> 932
    //   917: aload 21
    //   919: astore 26
    //   921: aload 22
    //   923: astore 21
    //   925: aload 26
    //   927: astore 22
    //   929: goto +73 -> 1002
    //   932: aload_0
    //   933: invokevirtual 434	com/google/android/gms/measurement/internal/zzey:zzjq	()Lcom/google/android/gms/measurement/internal/zzq;
    //   936: aload 30
    //   938: aload 29
    //   940: invokevirtual 517	com/google/android/gms/measurement/internal/zzq:zza	(Ljava/lang/String;Ljava/lang/Long;)Landroid/util/Pair;
    //   943: astore 26
    //   945: aload 26
    //   947: ifnull +387 -> 1334
    //   950: aload 26
    //   952: getfield 523	android/util/Pair:first	Ljava/lang/Object;
    //   955: ifnonnull +6 -> 961
    //   958: goto +376 -> 1334
    //   961: aload 26
    //   963: getfield 523	android/util/Pair:first	Ljava/lang/Object;
    //   966: checkcast 488	com/google/android/gms/internal/measurement/zzgf
    //   969: astore 21
    //   971: aload 26
    //   973: getfield 526	android/util/Pair:second	Ljava/lang/Object;
    //   976: checkcast 162	java/lang/Long
    //   979: invokevirtual 171	java/lang/Long:longValue	()J
    //   982: lstore 11
    //   984: aload_0
    //   985: invokevirtual 500	com/google/android/gms/measurement/internal/zzey:zzjo	()Lcom/google/android/gms/measurement/internal/zzfg;
    //   988: pop
    //   989: aload 21
    //   991: ldc_w 502
    //   994: invokestatic 505	com/google/android/gms/measurement/internal/zzfg:zzb	(Lcom/google/android/gms/internal/measurement/zzgf;Ljava/lang/String;)Ljava/lang/Object;
    //   997: checkcast 162	java/lang/Long
    //   1000: astore 22
    //   1002: lload 11
    //   1004: lconst_1
    //   1005: lsub
    //   1006: lstore 11
    //   1008: lload 11
    //   1010: lconst_0
    //   1011: lcmp
    //   1012: ifgt +87 -> 1099
    //   1015: aload_0
    //   1016: invokevirtual 434	com/google/android/gms/measurement/internal/zzey:zzjq	()Lcom/google/android/gms/measurement/internal/zzq;
    //   1019: astore 27
    //   1021: aload 27
    //   1023: invokevirtual 529	com/google/android/gms/measurement/internal/zzco:zzaf	()V
    //   1026: aload 27
    //   1028: invokevirtual 77	com/google/android/gms/measurement/internal/zzco:zzgo	()Lcom/google/android/gms/measurement/internal/zzap;
    //   1031: invokevirtual 206	com/google/android/gms/measurement/internal/zzap:zzjl	()Lcom/google/android/gms/measurement/internal/zzar;
    //   1034: ldc_w 531
    //   1037: aload 30
    //   1039: invokevirtual 101	com/google/android/gms/measurement/internal/zzar:zzg	(Ljava/lang/String;Ljava/lang/Object;)V
    //   1042: aload 27
    //   1044: invokevirtual 535	com/google/android/gms/measurement/internal/zzq:getWritableDatabase	()Landroid/database/sqlite/SQLiteDatabase;
    //   1047: astore 26
    //   1049: aload 26
    //   1051: ldc_w 537
    //   1054: iconst_1
    //   1055: anewarray 183	java/lang/String
    //   1058: dup
    //   1059: iconst_0
    //   1060: aload 30
    //   1062: aastore
    //   1063: invokevirtual 543	android/database/sqlite/SQLiteDatabase:execSQL	(Ljava/lang/String;[Ljava/lang/Object;)V
    //   1066: goto +30 -> 1096
    //   1069: astore 26
    //   1071: goto +9 -> 1080
    //   1074: astore_1
    //   1075: goto +5 -> 1080
    //   1078: astore 26
    //   1080: aload 27
    //   1082: invokevirtual 77	com/google/android/gms/measurement/internal/zzco:zzgo	()Lcom/google/android/gms/measurement/internal/zzap;
    //   1085: invokevirtual 512	com/google/android/gms/measurement/internal/zzap:zzjd	()Lcom/google/android/gms/measurement/internal/zzar;
    //   1088: ldc_w 545
    //   1091: aload 26
    //   1093: invokevirtual 101	com/google/android/gms/measurement/internal/zzar:zzg	(Ljava/lang/String;Ljava/lang/Object;)V
    //   1096: goto +18 -> 1114
    //   1099: aload_0
    //   1100: invokevirtual 434	com/google/android/gms/measurement/internal/zzey:zzjq	()Lcom/google/android/gms/measurement/internal/zzq;
    //   1103: aload_1
    //   1104: aload 29
    //   1106: lload 11
    //   1108: aload 21
    //   1110: invokevirtual 548	com/google/android/gms/measurement/internal/zzq:zza	(Ljava/lang/String;Ljava/lang/Long;JLcom/google/android/gms/internal/measurement/zzgf;)Z
    //   1113: pop
    //   1114: iload 4
    //   1116: istore 5
    //   1118: aload 21
    //   1120: getfield 493	com/google/android/gms/internal/measurement/zzgf:zzawt	[Lcom/google/android/gms/internal/measurement/zzgg;
    //   1123: arraylength
    //   1124: aload 24
    //   1126: arraylength
    //   1127: iadd
    //   1128: anewarray 112	com/google/android/gms/internal/measurement/zzgg
    //   1131: astore 27
    //   1133: aload 21
    //   1135: getfield 493	com/google/android/gms/internal/measurement/zzgf:zzawt	[Lcom/google/android/gms/internal/measurement/zzgg;
    //   1138: astore 26
    //   1140: aload 26
    //   1142: arraylength
    //   1143: istore 9
    //   1145: iconst_0
    //   1146: istore 7
    //   1148: iconst_0
    //   1149: istore 4
    //   1151: iload 7
    //   1153: iload 9
    //   1155: if_icmpge +58 -> 1213
    //   1158: aload 26
    //   1160: iload 7
    //   1162: aaload
    //   1163: astore 29
    //   1165: aload_0
    //   1166: invokevirtual 500	com/google/android/gms/measurement/internal/zzey:zzjo	()Lcom/google/android/gms/measurement/internal/zzfg;
    //   1169: pop
    //   1170: iload 4
    //   1172: istore 8
    //   1174: aload 25
    //   1176: aload 29
    //   1178: getfield 115	com/google/android/gms/internal/measurement/zzgg:name	Ljava/lang/String;
    //   1181: invokestatic 551	com/google/android/gms/measurement/internal/zzfg:zza	(Lcom/google/android/gms/internal/measurement/zzgf;Ljava/lang/String;)Lcom/google/android/gms/internal/measurement/zzgg;
    //   1184: ifnonnull +16 -> 1200
    //   1187: aload 27
    //   1189: iload 4
    //   1191: aload 29
    //   1193: aastore
    //   1194: iload 4
    //   1196: iconst_1
    //   1197: iadd
    //   1198: istore 8
    //   1200: iload 7
    //   1202: iconst_1
    //   1203: iadd
    //   1204: istore 7
    //   1206: iload 8
    //   1208: istore 4
    //   1210: goto -59 -> 1151
    //   1213: aload 21
    //   1215: astore 26
    //   1217: iload 4
    //   1219: ifle +77 -> 1296
    //   1222: aload 24
    //   1224: arraylength
    //   1225: istore 8
    //   1227: iconst_0
    //   1228: istore 7
    //   1230: iload 7
    //   1232: iload 8
    //   1234: if_icmpge +28 -> 1262
    //   1237: aload 27
    //   1239: iload 4
    //   1241: aload 24
    //   1243: iload 7
    //   1245: aaload
    //   1246: aastore
    //   1247: iload 7
    //   1249: iconst_1
    //   1250: iadd
    //   1251: istore 7
    //   1253: iload 4
    //   1255: iconst_1
    //   1256: iadd
    //   1257: istore 4
    //   1259: goto -29 -> 1230
    //   1262: iload 4
    //   1264: aload 27
    //   1266: arraylength
    //   1267: if_icmpne +10 -> 1277
    //   1270: aload 27
    //   1272: astore 21
    //   1274: goto +15 -> 1289
    //   1277: aload 27
    //   1279: iload 4
    //   1281: invokestatic 555	java/util/Arrays:copyOf	([Ljava/lang/Object;I)[Ljava/lang/Object;
    //   1284: checkcast 556	[Lcom/google/android/gms/internal/measurement/zzgg;
    //   1287: astore 21
    //   1289: aload 21
    //   1291: astore 27
    //   1293: goto +22 -> 1315
    //   1296: aload_0
    //   1297: invokevirtual 77	com/google/android/gms/measurement/internal/zzco:zzgo	()Lcom/google/android/gms/measurement/internal/zzap;
    //   1300: invokevirtual 83	com/google/android/gms/measurement/internal/zzap:zzjg	()Lcom/google/android/gms/measurement/internal/zzar;
    //   1303: ldc_w 558
    //   1306: aload 28
    //   1308: invokevirtual 101	com/google/android/gms/measurement/internal/zzar:zzg	(Ljava/lang/String;Ljava/lang/Object;)V
    //   1311: aload 24
    //   1313: astore 27
    //   1315: aload 28
    //   1317: astore 24
    //   1319: aload 22
    //   1321: astore 21
    //   1323: iload 5
    //   1325: istore 4
    //   1327: aload 26
    //   1329: astore 22
    //   1331: goto +207 -> 1538
    //   1334: aload_0
    //   1335: invokevirtual 77	com/google/android/gms/measurement/internal/zzco:zzgo	()Lcom/google/android/gms/measurement/internal/zzap;
    //   1338: invokevirtual 512	com/google/android/gms/measurement/internal/zzap:zzjd	()Lcom/google/android/gms/measurement/internal/zzar;
    //   1341: ldc_w 560
    //   1344: aload 28
    //   1346: aload 29
    //   1348: invokevirtual 144	com/google/android/gms/measurement/internal/zzar:zze	(Ljava/lang/String;Ljava/lang/Object;Ljava/lang/Object;)V
    //   1351: aload 23
    //   1353: astore 25
    //   1355: aload 19
    //   1357: astore 24
    //   1359: aload 17
    //   1361: astore 19
    //   1363: aload 15
    //   1365: astore 17
    //   1367: aload 16
    //   1369: astore 15
    //   1371: aload 20
    //   1373: astore 16
    //   1375: aload 21
    //   1377: astore 23
    //   1379: aload 19
    //   1381: astore 21
    //   1383: aload 25
    //   1385: astore 20
    //   1387: aload 16
    //   1389: astore 19
    //   1391: aload 24
    //   1393: astore 16
    //   1395: goto +1487 -> 2882
    //   1398: aload 25
    //   1400: astore 27
    //   1402: iload 4
    //   1404: istore 5
    //   1406: iload 7
    //   1408: ifeq +118 -> 1526
    //   1411: aload_0
    //   1412: invokevirtual 500	com/google/android/gms/measurement/internal/zzey:zzjo	()Lcom/google/android/gms/measurement/internal/zzfg;
    //   1415: pop
    //   1416: aload 27
    //   1418: ldc_w 562
    //   1421: invokestatic 505	com/google/android/gms/measurement/internal/zzfg:zzb	(Lcom/google/android/gms/internal/measurement/zzgf;Ljava/lang/String;)Ljava/lang/Object;
    //   1424: astore 22
    //   1426: aload 22
    //   1428: astore 21
    //   1430: aload 22
    //   1432: ifnonnull +9 -> 1441
    //   1435: lconst_0
    //   1436: invokestatic 371	java/lang/Long:valueOf	(J)Ljava/lang/Long;
    //   1439: astore 21
    //   1441: aload 21
    //   1443: checkcast 162	java/lang/Long
    //   1446: invokevirtual 171	java/lang/Long:longValue	()J
    //   1449: lstore 11
    //   1451: lload 11
    //   1453: lconst_0
    //   1454: lcmp
    //   1455: ifgt +21 -> 1476
    //   1458: aload_0
    //   1459: invokevirtual 77	com/google/android/gms/measurement/internal/zzco:zzgo	()Lcom/google/android/gms/measurement/internal/zzap;
    //   1462: invokevirtual 83	com/google/android/gms/measurement/internal/zzap:zzjg	()Lcom/google/android/gms/measurement/internal/zzar;
    //   1465: ldc_w 564
    //   1468: aload 26
    //   1470: invokevirtual 101	com/google/android/gms/measurement/internal/zzar:zzg	(Ljava/lang/String;Ljava/lang/Object;)V
    //   1473: goto +18 -> 1491
    //   1476: aload_0
    //   1477: invokevirtual 434	com/google/android/gms/measurement/internal/zzey:zzjq	()Lcom/google/android/gms/measurement/internal/zzq;
    //   1480: aload_1
    //   1481: aload 29
    //   1483: lload 11
    //   1485: aload 27
    //   1487: invokevirtual 548	com/google/android/gms/measurement/internal/zzq:zza	(Ljava/lang/String;Ljava/lang/Long;JLcom/google/android/gms/internal/measurement/zzgf;)Z
    //   1490: pop
    //   1491: aload 29
    //   1493: astore 21
    //   1495: aload 26
    //   1497: astore 28
    //   1499: aload 24
    //   1501: astore 22
    //   1503: aload 27
    //   1505: astore 26
    //   1507: aload 28
    //   1509: astore 24
    //   1511: aload 22
    //   1513: astore 27
    //   1515: aload 26
    //   1517: astore 22
    //   1519: goto +19 -> 1538
    //   1522: iload 4
    //   1524: istore 5
    //   1526: aload 24
    //   1528: astore 27
    //   1530: iload 5
    //   1532: istore 4
    //   1534: aload 26
    //   1536: astore 24
    //   1538: aload 20
    //   1540: astore 26
    //   1542: aload_0
    //   1543: invokevirtual 434	com/google/android/gms/measurement/internal/zzey:zzjq	()Lcom/google/android/gms/measurement/internal/zzq;
    //   1546: aload 30
    //   1548: aload 25
    //   1550: getfield 489	com/google/android/gms/internal/measurement/zzgf:name	Ljava/lang/String;
    //   1553: invokevirtual 567	com/google/android/gms/measurement/internal/zzq:zzg	(Ljava/lang/String;Ljava/lang/String;)Lcom/google/android/gms/measurement/internal/zzz;
    //   1556: astore 20
    //   1558: aload 20
    //   1560: ifnonnull +62 -> 1622
    //   1563: aload_0
    //   1564: invokevirtual 77	com/google/android/gms/measurement/internal/zzco:zzgo	()Lcom/google/android/gms/measurement/internal/zzap;
    //   1567: invokevirtual 83	com/google/android/gms/measurement/internal/zzap:zzjg	()Lcom/google/android/gms/measurement/internal/zzar;
    //   1570: ldc_w 569
    //   1573: aload_1
    //   1574: invokestatic 573	com/google/android/gms/measurement/internal/zzap:zzbv	(Ljava/lang/String;)Ljava/lang/Object;
    //   1577: aload_0
    //   1578: invokevirtual 89	com/google/android/gms/measurement/internal/zzco:zzgl	()Lcom/google/android/gms/measurement/internal/zzan;
    //   1581: aload 24
    //   1583: invokevirtual 95	com/google/android/gms/measurement/internal/zzan:zzbs	(Ljava/lang/String;)Ljava/lang/String;
    //   1586: invokevirtual 144	com/google/android/gms/measurement/internal/zzar:zze	(Ljava/lang/String;Ljava/lang/Object;Ljava/lang/Object;)V
    //   1589: new 575	com/google/android/gms/measurement/internal/zzz
    //   1592: dup
    //   1593: aload_1
    //   1594: aload 25
    //   1596: getfield 489	com/google/android/gms/internal/measurement/zzgf:name	Ljava/lang/String;
    //   1599: lconst_1
    //   1600: lconst_1
    //   1601: aload 25
    //   1603: getfield 578	com/google/android/gms/internal/measurement/zzgf:zzawu	Ljava/lang/Long;
    //   1606: invokevirtual 171	java/lang/Long:longValue	()J
    //   1609: lconst_0
    //   1610: aconst_null
    //   1611: aconst_null
    //   1612: aconst_null
    //   1613: aconst_null
    //   1614: invokespecial 581	com/google/android/gms/measurement/internal/zzz:<init>	(Ljava/lang/String;Ljava/lang/String;JJJJLjava/lang/Long;Ljava/lang/Long;Ljava/lang/Long;Ljava/lang/Boolean;)V
    //   1617: astore 28
    //   1619: goto +10 -> 1629
    //   1622: aload 20
    //   1624: invokevirtual 585	com/google/android/gms/measurement/internal/zzz:zziu	()Lcom/google/android/gms/measurement/internal/zzz;
    //   1627: astore 28
    //   1629: aload 17
    //   1631: astore 20
    //   1633: aload 15
    //   1635: astore 17
    //   1637: aload_0
    //   1638: invokevirtual 434	com/google/android/gms/measurement/internal/zzey:zzjq	()Lcom/google/android/gms/measurement/internal/zzq;
    //   1641: aload 28
    //   1643: invokevirtual 588	com/google/android/gms/measurement/internal/zzq:zza	(Lcom/google/android/gms/measurement/internal/zzz;)V
    //   1646: aload 28
    //   1648: getfield 592	com/google/android/gms/measurement/internal/zzz:zzaie	J
    //   1651: lstore 13
    //   1653: aload 23
    //   1655: aload 24
    //   1657: invokeinterface 160 2 0
    //   1662: checkcast 124	java/util/Map
    //   1665: astore 28
    //   1667: aload 28
    //   1669: astore 15
    //   1671: aload 28
    //   1673: ifnonnull +46 -> 1719
    //   1676: aload_0
    //   1677: invokevirtual 434	com/google/android/gms/measurement/internal/zzey:zzjq	()Lcom/google/android/gms/measurement/internal/zzq;
    //   1680: aload 30
    //   1682: aload 24
    //   1684: invokevirtual 596	com/google/android/gms/measurement/internal/zzq:zzl	(Ljava/lang/String;Ljava/lang/String;)Ljava/util/Map;
    //   1687: astore 28
    //   1689: aload 28
    //   1691: astore 15
    //   1693: aload 28
    //   1695: ifnonnull +12 -> 1707
    //   1698: new 109	android/support/v4/util/ArrayMap
    //   1701: dup
    //   1702: invokespecial 110	android/support/v4/util/ArrayMap:<init>	()V
    //   1705: astore 15
    //   1707: aload 23
    //   1709: aload 24
    //   1711: aload 15
    //   1713: invokeinterface 128 3 0
    //   1718: pop
    //   1719: aload 15
    //   1721: astore 32
    //   1723: aload 32
    //   1725: invokeinterface 383 1 0
    //   1730: invokeinterface 387 1 0
    //   1735: astore 30
    //   1737: aload 18
    //   1739: astore 15
    //   1741: aload 16
    //   1743: astore 18
    //   1745: aload 26
    //   1747: astore 16
    //   1749: aload 23
    //   1751: astore 28
    //   1753: aload 25
    //   1755: astore 23
    //   1757: aload 24
    //   1759: astore 33
    //   1761: aload 30
    //   1763: invokeinterface 392 1 0
    //   1768: ifeq +1070 -> 2838
    //   1771: aload 30
    //   1773: invokeinterface 396 1 0
    //   1778: checkcast 307	java/lang/Integer
    //   1781: invokevirtual 310	java/lang/Integer:intValue	()I
    //   1784: istore 8
    //   1786: aload 20
    //   1788: iload 8
    //   1790: invokestatic 366	java/lang/Integer:valueOf	(I)Ljava/lang/Integer;
    //   1793: invokeinterface 118 2 0
    //   1798: ifeq +24 -> 1822
    //   1801: aload_0
    //   1802: invokevirtual 77	com/google/android/gms/measurement/internal/zzco:zzgo	()Lcom/google/android/gms/measurement/internal/zzap;
    //   1805: invokevirtual 206	com/google/android/gms/measurement/internal/zzap:zzjl	()Lcom/google/android/gms/measurement/internal/zzar;
    //   1808: ldc_w 598
    //   1811: iload 8
    //   1813: invokestatic 366	java/lang/Integer:valueOf	(I)Ljava/lang/Integer;
    //   1816: invokevirtual 101	com/google/android/gms/measurement/internal/zzar:zzg	(Ljava/lang/String;Ljava/lang/Object;)V
    //   1819: goto -58 -> 1761
    //   1822: aload 19
    //   1824: astore 25
    //   1826: aload 25
    //   1828: iload 8
    //   1830: invokestatic 366	java/lang/Integer:valueOf	(I)Ljava/lang/Integer;
    //   1833: invokeinterface 160 2 0
    //   1838: checkcast 469	com/google/android/gms/internal/measurement/zzgd
    //   1841: astore 24
    //   1843: aload 18
    //   1845: astore 26
    //   1847: aload 26
    //   1849: iload 8
    //   1851: invokestatic 366	java/lang/Integer:valueOf	(I)Ljava/lang/Integer;
    //   1854: invokeinterface 160 2 0
    //   1859: checkcast 444	java/util/BitSet
    //   1862: astore 36
    //   1864: aload 23
    //   1866: astore 34
    //   1868: aload 17
    //   1870: astore 23
    //   1872: aload 23
    //   1874: iload 8
    //   1876: invokestatic 366	java/lang/Integer:valueOf	(I)Ljava/lang/Integer;
    //   1879: invokeinterface 160 2 0
    //   1884: checkcast 444	java/util/BitSet
    //   1887: astore 19
    //   1889: iload 10
    //   1891: ifeq +40 -> 1931
    //   1894: aload 15
    //   1896: iload 8
    //   1898: invokestatic 366	java/lang/Integer:valueOf	(I)Ljava/lang/Integer;
    //   1901: invokeinterface 160 2 0
    //   1906: checkcast 124	java/util/Map
    //   1909: astore 18
    //   1911: aload 16
    //   1913: iload 8
    //   1915: invokestatic 366	java/lang/Integer:valueOf	(I)Ljava/lang/Integer;
    //   1918: invokeinterface 160 2 0
    //   1923: checkcast 124	java/util/Map
    //   1926: astore 17
    //   1928: goto +9 -> 1937
    //   1931: aconst_null
    //   1932: astore 17
    //   1934: aconst_null
    //   1935: astore 18
    //   1937: aload 15
    //   1939: astore 35
    //   1941: aload 16
    //   1943: astore 31
    //   1945: aload 24
    //   1947: ifnonnull +167 -> 2114
    //   1950: new 469	com/google/android/gms/internal/measurement/zzgd
    //   1953: dup
    //   1954: invokespecial 470	com/google/android/gms/internal/measurement/zzgd:<init>	()V
    //   1957: astore 15
    //   1959: aload 25
    //   1961: iload 8
    //   1963: invokestatic 366	java/lang/Integer:valueOf	(I)Ljava/lang/Integer;
    //   1966: aload 15
    //   1968: invokeinterface 128 3 0
    //   1973: pop
    //   1974: aload 15
    //   1976: iconst_1
    //   1977: invokestatic 50	java/lang/Boolean:valueOf	(Z)Ljava/lang/Boolean;
    //   1980: putfield 473	com/google/android/gms/internal/measurement/zzgd:zzawo	Ljava/lang/Boolean;
    //   1983: new 444	java/util/BitSet
    //   1986: dup
    //   1987: invokespecial 449	java/util/BitSet:<init>	()V
    //   1990: astore 16
    //   1992: aload 26
    //   1994: iload 8
    //   1996: invokestatic 366	java/lang/Integer:valueOf	(I)Ljava/lang/Integer;
    //   1999: aload 16
    //   2001: invokeinterface 128 3 0
    //   2006: pop
    //   2007: new 444	java/util/BitSet
    //   2010: dup
    //   2011: invokespecial 449	java/util/BitSet:<init>	()V
    //   2014: astore 15
    //   2016: aload 23
    //   2018: iload 8
    //   2020: invokestatic 366	java/lang/Integer:valueOf	(I)Ljava/lang/Integer;
    //   2023: aload 15
    //   2025: invokeinterface 128 3 0
    //   2030: pop
    //   2031: iload 10
    //   2033: ifeq +62 -> 2095
    //   2036: new 109	android/support/v4/util/ArrayMap
    //   2039: dup
    //   2040: invokespecial 110	android/support/v4/util/ArrayMap:<init>	()V
    //   2043: astore 24
    //   2045: aload 35
    //   2047: iload 8
    //   2049: invokestatic 366	java/lang/Integer:valueOf	(I)Ljava/lang/Integer;
    //   2052: aload 24
    //   2054: invokeinterface 128 3 0
    //   2059: pop
    //   2060: new 109	android/support/v4/util/ArrayMap
    //   2063: dup
    //   2064: invokespecial 110	android/support/v4/util/ArrayMap:<init>	()V
    //   2067: astore 29
    //   2069: aload 31
    //   2071: iload 8
    //   2073: invokestatic 366	java/lang/Integer:valueOf	(I)Ljava/lang/Integer;
    //   2076: aload 29
    //   2078: invokeinterface 128 3 0
    //   2083: pop
    //   2084: aload 15
    //   2086: astore 19
    //   2088: aload 16
    //   2090: astore 18
    //   2092: goto +34 -> 2126
    //   2095: aload 18
    //   2097: astore 24
    //   2099: aload 15
    //   2101: astore 19
    //   2103: aload 16
    //   2105: astore 18
    //   2107: aload 17
    //   2109: astore 29
    //   2111: goto +15 -> 2126
    //   2114: aload 18
    //   2116: astore 24
    //   2118: aload 17
    //   2120: astore 29
    //   2122: aload 36
    //   2124: astore 18
    //   2126: aload 32
    //   2128: iload 8
    //   2130: invokestatic 366	java/lang/Integer:valueOf	(I)Ljava/lang/Integer;
    //   2133: invokeinterface 160 2 0
    //   2138: checkcast 248	java/util/List
    //   2141: invokeinterface 599 1 0
    //   2146: astore 38
    //   2148: aload 34
    //   2150: astore 16
    //   2152: aload 25
    //   2154: astore 15
    //   2156: aload 35
    //   2158: astore 25
    //   2160: aload 23
    //   2162: astore 17
    //   2164: aload 33
    //   2166: astore 23
    //   2168: aload 38
    //   2170: invokeinterface 392 1 0
    //   2175: ifeq +632 -> 2807
    //   2178: aload 38
    //   2180: invokeinterface 396 1 0
    //   2185: checkcast 34	com/google/android/gms/internal/measurement/zzfv
    //   2188: astore 39
    //   2190: aload_0
    //   2191: invokevirtual 77	com/google/android/gms/measurement/internal/zzco:zzgo	()Lcom/google/android/gms/measurement/internal/zzap;
    //   2194: iconst_2
    //   2195: invokevirtual 603	com/google/android/gms/measurement/internal/zzap:isLoggable	(I)Z
    //   2198: ifeq +63 -> 2261
    //   2201: aload_0
    //   2202: invokevirtual 77	com/google/android/gms/measurement/internal/zzco:zzgo	()Lcom/google/android/gms/measurement/internal/zzap;
    //   2205: invokevirtual 206	com/google/android/gms/measurement/internal/zzap:zzjl	()Lcom/google/android/gms/measurement/internal/zzar;
    //   2208: ldc_w 605
    //   2211: iload 8
    //   2213: invokestatic 366	java/lang/Integer:valueOf	(I)Ljava/lang/Integer;
    //   2216: aload 39
    //   2218: getfield 608	com/google/android/gms/internal/measurement/zzfv:zzave	Ljava/lang/Integer;
    //   2221: aload_0
    //   2222: invokevirtual 89	com/google/android/gms/measurement/internal/zzco:zzgl	()Lcom/google/android/gms/measurement/internal/zzan;
    //   2225: aload 39
    //   2227: getfield 611	com/google/android/gms/internal/measurement/zzfv:zzavf	Ljava/lang/String;
    //   2230: invokevirtual 95	com/google/android/gms/measurement/internal/zzan:zzbs	(Ljava/lang/String;)Ljava/lang/String;
    //   2233: invokevirtual 614	com/google/android/gms/measurement/internal/zzar:zzd	(Ljava/lang/String;Ljava/lang/Object;Ljava/lang/Object;Ljava/lang/Object;)V
    //   2236: aload_0
    //   2237: invokevirtual 77	com/google/android/gms/measurement/internal/zzco:zzgo	()Lcom/google/android/gms/measurement/internal/zzap;
    //   2240: invokevirtual 206	com/google/android/gms/measurement/internal/zzap:zzjl	()Lcom/google/android/gms/measurement/internal/zzar;
    //   2243: ldc_w 616
    //   2246: aload_0
    //   2247: invokevirtual 500	com/google/android/gms/measurement/internal/zzey:zzjo	()Lcom/google/android/gms/measurement/internal/zzfg;
    //   2250: aload 39
    //   2252: invokevirtual 619	com/google/android/gms/measurement/internal/zzfg:zza	(Lcom/google/android/gms/internal/measurement/zzfv;)Ljava/lang/String;
    //   2255: invokevirtual 101	com/google/android/gms/measurement/internal/zzar:zzg	(Ljava/lang/String;Ljava/lang/Object;)V
    //   2258: goto +3 -> 2261
    //   2261: aload 25
    //   2263: astore 33
    //   2265: aload 26
    //   2267: astore 25
    //   2269: aload 39
    //   2271: getfield 608	com/google/android/gms/internal/measurement/zzfv:zzave	Ljava/lang/Integer;
    //   2274: ifnull +497 -> 2771
    //   2277: aload 39
    //   2279: getfield 608	com/google/android/gms/internal/measurement/zzfv:zzave	Ljava/lang/Integer;
    //   2282: invokevirtual 310	java/lang/Integer:intValue	()I
    //   2285: sipush 256
    //   2288: if_icmple +6 -> 2294
    //   2291: goto +480 -> 2771
    //   2294: iload 10
    //   2296: ifeq +321 -> 2617
    //   2299: aload 39
    //   2301: ifnull +28 -> 2329
    //   2304: aload 39
    //   2306: getfield 622	com/google/android/gms/internal/measurement/zzfv:zzavb	Ljava/lang/Boolean;
    //   2309: ifnull +20 -> 2329
    //   2312: aload 39
    //   2314: getfield 622	com/google/android/gms/internal/measurement/zzfv:zzavb	Ljava/lang/Boolean;
    //   2317: invokevirtual 46	java/lang/Boolean:booleanValue	()Z
    //   2320: ifeq +9 -> 2329
    //   2323: iconst_1
    //   2324: istore 5
    //   2326: goto +6 -> 2332
    //   2329: iconst_0
    //   2330: istore 5
    //   2332: aload 39
    //   2334: ifnull +28 -> 2362
    //   2337: aload 39
    //   2339: getfield 625	com/google/android/gms/internal/measurement/zzfv:zzavc	Ljava/lang/Boolean;
    //   2342: ifnull +20 -> 2362
    //   2345: aload 39
    //   2347: getfield 625	com/google/android/gms/internal/measurement/zzfv:zzavc	Ljava/lang/Boolean;
    //   2350: invokevirtual 46	java/lang/Boolean:booleanValue	()Z
    //   2353: ifeq +9 -> 2362
    //   2356: iconst_1
    //   2357: istore 7
    //   2359: goto +6 -> 2365
    //   2362: iconst_0
    //   2363: istore 7
    //   2365: aload 18
    //   2367: aload 39
    //   2369: getfield 608	com/google/android/gms/internal/measurement/zzfv:zzave	Ljava/lang/Integer;
    //   2372: invokevirtual 310	java/lang/Integer:intValue	()I
    //   2375: invokevirtual 627	java/util/BitSet:get	(I)Z
    //   2378: ifeq +39 -> 2417
    //   2381: iload 5
    //   2383: ifne +34 -> 2417
    //   2386: iload 7
    //   2388: ifne +29 -> 2417
    //   2391: aload_0
    //   2392: invokevirtual 77	com/google/android/gms/measurement/internal/zzco:zzgo	()Lcom/google/android/gms/measurement/internal/zzap;
    //   2395: invokevirtual 206	com/google/android/gms/measurement/internal/zzap:zzjl	()Lcom/google/android/gms/measurement/internal/zzar;
    //   2398: ldc_w 629
    //   2401: iload 8
    //   2403: invokestatic 366	java/lang/Integer:valueOf	(I)Ljava/lang/Integer;
    //   2406: aload 39
    //   2408: getfield 608	com/google/android/gms/internal/measurement/zzfv:zzave	Ljava/lang/Integer;
    //   2411: invokevirtual 144	com/google/android/gms/measurement/internal/zzar:zze	(Ljava/lang/String;Ljava/lang/Object;Ljava/lang/Object;)V
    //   2414: goto +382 -> 2796
    //   2417: aload 19
    //   2419: astore 34
    //   2421: aload 16
    //   2423: astore 26
    //   2425: aload 18
    //   2427: astore 35
    //   2429: aload_0
    //   2430: aload 39
    //   2432: aload 23
    //   2434: aload 27
    //   2436: lload 13
    //   2438: invokespecial 631	com/google/android/gms/measurement/internal/zzj:zza	(Lcom/google/android/gms/internal/measurement/zzfv;Ljava/lang/String;[Lcom/google/android/gms/internal/measurement/zzgg;J)Ljava/lang/Boolean;
    //   2441: astore 37
    //   2443: aload_0
    //   2444: invokevirtual 77	com/google/android/gms/measurement/internal/zzco:zzgo	()Lcom/google/android/gms/measurement/internal/zzap;
    //   2447: invokevirtual 206	com/google/android/gms/measurement/internal/zzap:zzjl	()Lcom/google/android/gms/measurement/internal/zzar;
    //   2450: astore 40
    //   2452: aload 37
    //   2454: ifnonnull +11 -> 2465
    //   2457: ldc_w 633
    //   2460: astore 36
    //   2462: goto +7 -> 2469
    //   2465: aload 37
    //   2467: astore 36
    //   2469: aload 40
    //   2471: ldc_w 635
    //   2474: aload 36
    //   2476: invokevirtual 101	com/google/android/gms/measurement/internal/zzar:zzg	(Ljava/lang/String;Ljava/lang/Object;)V
    //   2479: aload 37
    //   2481: ifnonnull +31 -> 2512
    //   2484: aload 20
    //   2486: iload 8
    //   2488: invokestatic 366	java/lang/Integer:valueOf	(I)Ljava/lang/Integer;
    //   2491: invokeinterface 107 2 0
    //   2496: pop
    //   2497: aload 35
    //   2499: astore 18
    //   2501: aload 34
    //   2503: astore 19
    //   2505: aload 26
    //   2507: astore 16
    //   2509: goto +287 -> 2796
    //   2512: aload 34
    //   2514: aload 39
    //   2516: getfield 608	com/google/android/gms/internal/measurement/zzfv:zzave	Ljava/lang/Integer;
    //   2519: invokevirtual 310	java/lang/Integer:intValue	()I
    //   2522: invokevirtual 461	java/util/BitSet:set	(I)V
    //   2525: aload 37
    //   2527: invokevirtual 46	java/lang/Boolean:booleanValue	()Z
    //   2530: ifeq -33 -> 2497
    //   2533: aload 35
    //   2535: aload 39
    //   2537: getfield 608	com/google/android/gms/internal/measurement/zzfv:zzave	Ljava/lang/Integer;
    //   2540: invokevirtual 310	java/lang/Integer:intValue	()I
    //   2543: invokevirtual 461	java/util/BitSet:set	(I)V
    //   2546: iload 5
    //   2548: ifne +8 -> 2556
    //   2551: iload 7
    //   2553: ifeq -56 -> 2497
    //   2556: aload 26
    //   2558: getfield 578	com/google/android/gms/internal/measurement/zzgf:zzawu	Ljava/lang/Long;
    //   2561: ifnull -64 -> 2497
    //   2564: iload 7
    //   2566: ifeq +27 -> 2593
    //   2569: aload 29
    //   2571: aload 39
    //   2573: getfield 608	com/google/android/gms/internal/measurement/zzfv:zzave	Ljava/lang/Integer;
    //   2576: invokevirtual 310	java/lang/Integer:intValue	()I
    //   2579: aload 26
    //   2581: getfield 578	com/google/android/gms/internal/measurement/zzgf:zzawu	Ljava/lang/Long;
    //   2584: invokevirtual 171	java/lang/Long:longValue	()J
    //   2587: invokestatic 637	com/google/android/gms/measurement/internal/zzj:zzb	(Ljava/util/Map;IJ)V
    //   2590: goto -93 -> 2497
    //   2593: aload 24
    //   2595: aload 39
    //   2597: getfield 608	com/google/android/gms/internal/measurement/zzfv:zzave	Ljava/lang/Integer;
    //   2600: invokevirtual 310	java/lang/Integer:intValue	()I
    //   2603: aload 26
    //   2605: getfield 578	com/google/android/gms/internal/measurement/zzgf:zzawu	Ljava/lang/Long;
    //   2608: invokevirtual 171	java/lang/Long:longValue	()J
    //   2611: invokestatic 639	com/google/android/gms/measurement/internal/zzj:zza	(Ljava/util/Map;IJ)V
    //   2614: goto +182 -> 2796
    //   2617: aload 18
    //   2619: astore 34
    //   2621: aload 34
    //   2623: aload 39
    //   2625: getfield 608	com/google/android/gms/internal/measurement/zzfv:zzave	Ljava/lang/Integer;
    //   2628: invokevirtual 310	java/lang/Integer:intValue	()I
    //   2631: invokevirtual 627	java/util/BitSet:get	(I)Z
    //   2634: ifeq +29 -> 2663
    //   2637: aload_0
    //   2638: invokevirtual 77	com/google/android/gms/measurement/internal/zzco:zzgo	()Lcom/google/android/gms/measurement/internal/zzap;
    //   2641: invokevirtual 206	com/google/android/gms/measurement/internal/zzap:zzjl	()Lcom/google/android/gms/measurement/internal/zzar;
    //   2644: ldc_w 641
    //   2647: iload 8
    //   2649: invokestatic 366	java/lang/Integer:valueOf	(I)Ljava/lang/Integer;
    //   2652: aload 39
    //   2654: getfield 608	com/google/android/gms/internal/measurement/zzfv:zzave	Ljava/lang/Integer;
    //   2657: invokevirtual 144	com/google/android/gms/measurement/internal/zzar:zze	(Ljava/lang/String;Ljava/lang/Object;Ljava/lang/Object;)V
    //   2660: goto +136 -> 2796
    //   2663: aload_0
    //   2664: aload 39
    //   2666: aload 23
    //   2668: aload 27
    //   2670: lload 13
    //   2672: invokespecial 631	com/google/android/gms/measurement/internal/zzj:zza	(Lcom/google/android/gms/internal/measurement/zzfv;Ljava/lang/String;[Lcom/google/android/gms/internal/measurement/zzgg;J)Ljava/lang/Boolean;
    //   2675: astore 35
    //   2677: aload_0
    //   2678: invokevirtual 77	com/google/android/gms/measurement/internal/zzco:zzgo	()Lcom/google/android/gms/measurement/internal/zzap;
    //   2681: invokevirtual 206	com/google/android/gms/measurement/internal/zzap:zzjl	()Lcom/google/android/gms/measurement/internal/zzar;
    //   2684: astore 36
    //   2686: aload 35
    //   2688: ifnonnull +11 -> 2699
    //   2691: ldc_w 633
    //   2694: astore 26
    //   2696: goto +7 -> 2703
    //   2699: aload 35
    //   2701: astore 26
    //   2703: aload 36
    //   2705: ldc_w 635
    //   2708: aload 26
    //   2710: invokevirtual 101	com/google/android/gms/measurement/internal/zzar:zzg	(Ljava/lang/String;Ljava/lang/Object;)V
    //   2713: aload 35
    //   2715: ifnonnull +19 -> 2734
    //   2718: aload 20
    //   2720: iload 8
    //   2722: invokestatic 366	java/lang/Integer:valueOf	(I)Ljava/lang/Integer;
    //   2725: invokeinterface 107 2 0
    //   2730: pop
    //   2731: goto +65 -> 2796
    //   2734: aload 19
    //   2736: aload 39
    //   2738: getfield 608	com/google/android/gms/internal/measurement/zzfv:zzave	Ljava/lang/Integer;
    //   2741: invokevirtual 310	java/lang/Integer:intValue	()I
    //   2744: invokevirtual 461	java/util/BitSet:set	(I)V
    //   2747: aload 35
    //   2749: invokevirtual 46	java/lang/Boolean:booleanValue	()Z
    //   2752: ifeq +44 -> 2796
    //   2755: aload 34
    //   2757: aload 39
    //   2759: getfield 608	com/google/android/gms/internal/measurement/zzfv:zzave	Ljava/lang/Integer;
    //   2762: invokevirtual 310	java/lang/Integer:intValue	()I
    //   2765: invokevirtual 461	java/util/BitSet:set	(I)V
    //   2768: goto +28 -> 2796
    //   2771: aload_0
    //   2772: invokevirtual 77	com/google/android/gms/measurement/internal/zzco:zzgo	()Lcom/google/android/gms/measurement/internal/zzap;
    //   2775: invokevirtual 83	com/google/android/gms/measurement/internal/zzap:zzjg	()Lcom/google/android/gms/measurement/internal/zzar;
    //   2778: ldc_w 643
    //   2781: aload_1
    //   2782: invokestatic 573	com/google/android/gms/measurement/internal/zzap:zzbv	(Ljava/lang/String;)Ljava/lang/Object;
    //   2785: aload 39
    //   2787: getfield 608	com/google/android/gms/internal/measurement/zzfv:zzave	Ljava/lang/Integer;
    //   2790: invokestatic 646	java/lang/String:valueOf	(Ljava/lang/Object;)Ljava/lang/String;
    //   2793: invokevirtual 144	com/google/android/gms/measurement/internal/zzar:zze	(Ljava/lang/String;Ljava/lang/Object;Ljava/lang/Object;)V
    //   2796: aload 25
    //   2798: astore 26
    //   2800: aload 33
    //   2802: astore 25
    //   2804: goto -636 -> 2168
    //   2807: aload 26
    //   2809: astore 18
    //   2811: aload 16
    //   2813: astore 19
    //   2815: aload 31
    //   2817: astore 16
    //   2819: aload 23
    //   2821: astore 33
    //   2823: aload 19
    //   2825: astore 23
    //   2827: aload 15
    //   2829: astore 19
    //   2831: aload 25
    //   2833: astore 15
    //   2835: goto -1074 -> 1761
    //   2838: aload 16
    //   2840: astore 23
    //   2842: aload 20
    //   2844: astore 24
    //   2846: aload 19
    //   2848: astore 16
    //   2850: aload 15
    //   2852: astore 19
    //   2854: aload 21
    //   2856: astore 25
    //   2858: aload 18
    //   2860: astore 15
    //   2862: aload 19
    //   2864: astore 18
    //   2866: aload 23
    //   2868: astore 19
    //   2870: aload 28
    //   2872: astore 20
    //   2874: aload 24
    //   2876: astore 21
    //   2878: aload 25
    //   2880: astore 23
    //   2882: iload 4
    //   2884: iconst_1
    //   2885: iadd
    //   2886: istore 4
    //   2888: aload 21
    //   2890: astore 24
    //   2892: aload 20
    //   2894: astore 26
    //   2896: aload 17
    //   2898: astore 25
    //   2900: aload 16
    //   2902: astore 17
    //   2904: aload 15
    //   2906: astore 16
    //   2908: aload 23
    //   2910: astore 21
    //   2912: aload 19
    //   2914: astore 20
    //   2916: aload 26
    //   2918: astore 23
    //   2920: aload 17
    //   2922: astore 19
    //   2924: aload 24
    //   2926: astore 17
    //   2928: aload 25
    //   2930: astore 15
    //   2932: goto -2217 -> 715
    //   2935: aload 28
    //   2937: astore 15
    //   2939: aload 27
    //   2941: astore 17
    //   2943: aload 26
    //   2945: astore_2
    //   2946: aload 25
    //   2948: astore 16
    //   2950: aload 24
    //   2952: astore 18
    //   2954: aload_3
    //   2955: astore 24
    //   2957: aload 15
    //   2959: astore 23
    //   2961: aload_2
    //   2962: astore 22
    //   2964: aload 16
    //   2966: astore 21
    //   2968: aload 17
    //   2970: astore 20
    //   2972: aload 18
    //   2974: astore 19
    //   2976: aload 24
    //   2978: ifnull +1245 -> 4223
    //   2981: new 109	android/support/v4/util/ArrayMap
    //   2984: dup
    //   2985: invokespecial 110	android/support/v4/util/ArrayMap:<init>	()V
    //   2988: astore 19
    //   2990: aload 24
    //   2992: arraylength
    //   2993: istore 4
    //   2995: iconst_0
    //   2996: istore 5
    //   2998: aload 19
    //   3000: astore 24
    //   3002: aload 15
    //   3004: astore 23
    //   3006: aload_2
    //   3007: astore 22
    //   3009: aload 16
    //   3011: astore 21
    //   3013: aload 17
    //   3015: astore 20
    //   3017: aload 18
    //   3019: astore 19
    //   3021: iload 5
    //   3023: iload 4
    //   3025: if_icmpge +1198 -> 4223
    //   3028: aload_3
    //   3029: iload 5
    //   3031: aaload
    //   3032: astore 31
    //   3034: aload 24
    //   3036: aload 31
    //   3038: getfield 222	com/google/android/gms/internal/measurement/zzgl:name	Ljava/lang/String;
    //   3041: invokeinterface 160 2 0
    //   3046: checkcast 124	java/util/Map
    //   3049: astore 22
    //   3051: aload 22
    //   3053: ifnonnull +54 -> 3107
    //   3056: aload_0
    //   3057: invokevirtual 434	com/google/android/gms/measurement/internal/zzey:zzjq	()Lcom/google/android/gms/measurement/internal/zzq;
    //   3060: aload_1
    //   3061: aload 31
    //   3063: getfield 222	com/google/android/gms/internal/measurement/zzgl:name	Ljava/lang/String;
    //   3066: invokevirtual 649	com/google/android/gms/measurement/internal/zzq:zzm	(Ljava/lang/String;Ljava/lang/String;)Ljava/util/Map;
    //   3069: astore 19
    //   3071: aload 19
    //   3073: astore 22
    //   3075: aload 19
    //   3077: ifnonnull +12 -> 3089
    //   3080: new 109	android/support/v4/util/ArrayMap
    //   3083: dup
    //   3084: invokespecial 110	android/support/v4/util/ArrayMap:<init>	()V
    //   3087: astore 22
    //   3089: aload 24
    //   3091: aload 31
    //   3093: getfield 222	com/google/android/gms/internal/measurement/zzgl:name	Ljava/lang/String;
    //   3096: aload 22
    //   3098: invokeinterface 128 3 0
    //   3103: pop
    //   3104: goto +3 -> 3107
    //   3107: aload 22
    //   3109: invokeinterface 383 1 0
    //   3114: invokeinterface 387 1 0
    //   3119: astore 23
    //   3121: aload 18
    //   3123: astore 19
    //   3125: aload 17
    //   3127: astore 21
    //   3129: aload 16
    //   3131: astore 20
    //   3133: aload 23
    //   3135: astore 17
    //   3137: aload 22
    //   3139: astore 16
    //   3141: aload 24
    //   3143: astore 18
    //   3145: aload 17
    //   3147: invokeinterface 392 1 0
    //   3152: ifeq +1046 -> 4198
    //   3155: aload 17
    //   3157: invokeinterface 396 1 0
    //   3162: checkcast 307	java/lang/Integer
    //   3165: invokevirtual 310	java/lang/Integer:intValue	()I
    //   3168: istore 8
    //   3170: aload 29
    //   3172: iload 8
    //   3174: invokestatic 366	java/lang/Integer:valueOf	(I)Ljava/lang/Integer;
    //   3177: invokeinterface 118 2 0
    //   3182: ifeq +24 -> 3206
    //   3185: aload_0
    //   3186: invokevirtual 77	com/google/android/gms/measurement/internal/zzco:zzgo	()Lcom/google/android/gms/measurement/internal/zzap;
    //   3189: invokevirtual 206	com/google/android/gms/measurement/internal/zzap:zzjl	()Lcom/google/android/gms/measurement/internal/zzar;
    //   3192: ldc_w 598
    //   3195: iload 8
    //   3197: invokestatic 366	java/lang/Integer:valueOf	(I)Ljava/lang/Integer;
    //   3200: invokevirtual 101	com/google/android/gms/measurement/internal/zzar:zzg	(Ljava/lang/String;Ljava/lang/Object;)V
    //   3203: goto -58 -> 3145
    //   3206: aload 21
    //   3208: astore 26
    //   3210: aload 26
    //   3212: iload 8
    //   3214: invokestatic 366	java/lang/Integer:valueOf	(I)Ljava/lang/Integer;
    //   3217: invokeinterface 160 2 0
    //   3222: checkcast 469	com/google/android/gms/internal/measurement/zzgd
    //   3225: astore 24
    //   3227: aload 19
    //   3229: astore 27
    //   3231: aload 27
    //   3233: iload 8
    //   3235: invokestatic 366	java/lang/Integer:valueOf	(I)Ljava/lang/Integer;
    //   3238: invokeinterface 160 2 0
    //   3243: checkcast 444	java/util/BitSet
    //   3246: astore 21
    //   3248: aload 20
    //   3250: astore 28
    //   3252: aload 28
    //   3254: iload 8
    //   3256: invokestatic 366	java/lang/Integer:valueOf	(I)Ljava/lang/Integer;
    //   3259: invokeinterface 160 2 0
    //   3264: checkcast 444	java/util/BitSet
    //   3267: astore 23
    //   3269: iload 10
    //   3271: ifeq +39 -> 3310
    //   3274: aload_2
    //   3275: iload 8
    //   3277: invokestatic 366	java/lang/Integer:valueOf	(I)Ljava/lang/Integer;
    //   3280: invokeinterface 160 2 0
    //   3285: checkcast 124	java/util/Map
    //   3288: astore 19
    //   3290: aload 15
    //   3292: iload 8
    //   3294: invokestatic 366	java/lang/Integer:valueOf	(I)Ljava/lang/Integer;
    //   3297: invokeinterface 160 2 0
    //   3302: checkcast 124	java/util/Map
    //   3305: astore 20
    //   3307: goto +9 -> 3316
    //   3310: aconst_null
    //   3311: astore 20
    //   3313: aconst_null
    //   3314: astore 19
    //   3316: aload 18
    //   3318: astore 22
    //   3320: aload 15
    //   3322: astore 18
    //   3324: aload_2
    //   3325: astore 30
    //   3327: aload 21
    //   3329: astore_2
    //   3330: aload 23
    //   3332: astore 15
    //   3334: aload 24
    //   3336: ifnonnull +144 -> 3480
    //   3339: new 469	com/google/android/gms/internal/measurement/zzgd
    //   3342: dup
    //   3343: invokespecial 470	com/google/android/gms/internal/measurement/zzgd:<init>	()V
    //   3346: astore_2
    //   3347: aload 26
    //   3349: iload 8
    //   3351: invokestatic 366	java/lang/Integer:valueOf	(I)Ljava/lang/Integer;
    //   3354: aload_2
    //   3355: invokeinterface 128 3 0
    //   3360: pop
    //   3361: aload_2
    //   3362: iconst_1
    //   3363: invokestatic 50	java/lang/Boolean:valueOf	(Z)Ljava/lang/Boolean;
    //   3366: putfield 473	com/google/android/gms/internal/measurement/zzgd:zzawo	Ljava/lang/Boolean;
    //   3369: new 444	java/util/BitSet
    //   3372: dup
    //   3373: invokespecial 449	java/util/BitSet:<init>	()V
    //   3376: astore 24
    //   3378: aload 27
    //   3380: iload 8
    //   3382: invokestatic 366	java/lang/Integer:valueOf	(I)Ljava/lang/Integer;
    //   3385: aload 24
    //   3387: invokeinterface 128 3 0
    //   3392: pop
    //   3393: new 444	java/util/BitSet
    //   3396: dup
    //   3397: invokespecial 449	java/util/BitSet:<init>	()V
    //   3400: astore 25
    //   3402: aload 28
    //   3404: iload 8
    //   3406: invokestatic 366	java/lang/Integer:valueOf	(I)Ljava/lang/Integer;
    //   3409: aload 25
    //   3411: invokeinterface 128 3 0
    //   3416: pop
    //   3417: aload 24
    //   3419: astore_2
    //   3420: aload 25
    //   3422: astore 15
    //   3424: iload 10
    //   3426: ifeq +54 -> 3480
    //   3429: new 109	android/support/v4/util/ArrayMap
    //   3432: dup
    //   3433: invokespecial 110	android/support/v4/util/ArrayMap:<init>	()V
    //   3436: astore 21
    //   3438: aload 30
    //   3440: iload 8
    //   3442: invokestatic 366	java/lang/Integer:valueOf	(I)Ljava/lang/Integer;
    //   3445: aload 21
    //   3447: invokeinterface 128 3 0
    //   3452: pop
    //   3453: new 109	android/support/v4/util/ArrayMap
    //   3456: dup
    //   3457: invokespecial 110	android/support/v4/util/ArrayMap:<init>	()V
    //   3460: astore 23
    //   3462: aload 18
    //   3464: iload 8
    //   3466: invokestatic 366	java/lang/Integer:valueOf	(I)Ljava/lang/Integer;
    //   3469: aload 23
    //   3471: invokeinterface 128 3 0
    //   3476: pop
    //   3477: goto +18 -> 3495
    //   3480: aload 15
    //   3482: astore 25
    //   3484: aload_2
    //   3485: astore 24
    //   3487: aload 20
    //   3489: astore 23
    //   3491: aload 19
    //   3493: astore 21
    //   3495: aload 18
    //   3497: astore_2
    //   3498: aload 16
    //   3500: iload 8
    //   3502: invokestatic 366	java/lang/Integer:valueOf	(I)Ljava/lang/Integer;
    //   3505: invokeinterface 160 2 0
    //   3510: checkcast 248	java/util/List
    //   3513: invokeinterface 599 1 0
    //   3518: astore 19
    //   3520: aload 28
    //   3522: astore 18
    //   3524: aload 27
    //   3526: astore 15
    //   3528: aload 26
    //   3530: astore 20
    //   3532: aload 19
    //   3534: astore 26
    //   3536: aload 30
    //   3538: astore 19
    //   3540: aload 26
    //   3542: invokeinterface 392 1 0
    //   3547: ifeq +614 -> 4161
    //   3550: aload 26
    //   3552: invokeinterface 396 1 0
    //   3557: checkcast 213	com/google/android/gms/internal/measurement/zzfy
    //   3560: astore 30
    //   3562: aload_0
    //   3563: invokevirtual 77	com/google/android/gms/measurement/internal/zzco:zzgo	()Lcom/google/android/gms/measurement/internal/zzap;
    //   3566: iconst_2
    //   3567: invokevirtual 603	com/google/android/gms/measurement/internal/zzap:isLoggable	(I)Z
    //   3570: ifeq +63 -> 3633
    //   3573: aload_0
    //   3574: invokevirtual 77	com/google/android/gms/measurement/internal/zzco:zzgo	()Lcom/google/android/gms/measurement/internal/zzap;
    //   3577: invokevirtual 206	com/google/android/gms/measurement/internal/zzap:zzjl	()Lcom/google/android/gms/measurement/internal/zzar;
    //   3580: ldc_w 651
    //   3583: iload 8
    //   3585: invokestatic 366	java/lang/Integer:valueOf	(I)Ljava/lang/Integer;
    //   3588: aload 30
    //   3590: getfield 652	com/google/android/gms/internal/measurement/zzfy:zzave	Ljava/lang/Integer;
    //   3593: aload_0
    //   3594: invokevirtual 89	com/google/android/gms/measurement/internal/zzco:zzgl	()Lcom/google/android/gms/measurement/internal/zzan;
    //   3597: aload 30
    //   3599: getfield 655	com/google/android/gms/internal/measurement/zzfy:zzavu	Ljava/lang/String;
    //   3602: invokevirtual 225	com/google/android/gms/measurement/internal/zzan:zzbu	(Ljava/lang/String;)Ljava/lang/String;
    //   3605: invokevirtual 614	com/google/android/gms/measurement/internal/zzar:zzd	(Ljava/lang/String;Ljava/lang/Object;Ljava/lang/Object;Ljava/lang/Object;)V
    //   3608: aload_0
    //   3609: invokevirtual 77	com/google/android/gms/measurement/internal/zzco:zzgo	()Lcom/google/android/gms/measurement/internal/zzap;
    //   3612: invokevirtual 206	com/google/android/gms/measurement/internal/zzap:zzjl	()Lcom/google/android/gms/measurement/internal/zzar;
    //   3615: ldc_w 616
    //   3618: aload_0
    //   3619: invokevirtual 500	com/google/android/gms/measurement/internal/zzey:zzjo	()Lcom/google/android/gms/measurement/internal/zzfg;
    //   3622: aload 30
    //   3624: invokevirtual 658	com/google/android/gms/measurement/internal/zzfg:zza	(Lcom/google/android/gms/internal/measurement/zzfy;)Ljava/lang/String;
    //   3627: invokevirtual 101	com/google/android/gms/measurement/internal/zzar:zzg	(Ljava/lang/String;Ljava/lang/Object;)V
    //   3630: goto +3 -> 3633
    //   3633: aload 30
    //   3635: getfield 652	com/google/android/gms/internal/measurement/zzfy:zzave	Ljava/lang/Integer;
    //   3638: ifnull +466 -> 4104
    //   3641: aload 30
    //   3643: getfield 652	com/google/android/gms/internal/measurement/zzfy:zzave	Ljava/lang/Integer;
    //   3646: invokevirtual 310	java/lang/Integer:intValue	()I
    //   3649: sipush 256
    //   3652: if_icmple +6 -> 3658
    //   3655: goto +449 -> 4104
    //   3658: iload 10
    //   3660: ifeq +298 -> 3958
    //   3663: aload 30
    //   3665: ifnull +28 -> 3693
    //   3668: aload 30
    //   3670: getfield 659	com/google/android/gms/internal/measurement/zzfy:zzavb	Ljava/lang/Boolean;
    //   3673: ifnull +20 -> 3693
    //   3676: aload 30
    //   3678: getfield 659	com/google/android/gms/internal/measurement/zzfy:zzavb	Ljava/lang/Boolean;
    //   3681: invokevirtual 46	java/lang/Boolean:booleanValue	()Z
    //   3684: ifeq +9 -> 3693
    //   3687: iconst_1
    //   3688: istore 6
    //   3690: goto +6 -> 3696
    //   3693: iconst_0
    //   3694: istore 6
    //   3696: aload 30
    //   3698: ifnull +28 -> 3726
    //   3701: aload 30
    //   3703: getfield 660	com/google/android/gms/internal/measurement/zzfy:zzavc	Ljava/lang/Boolean;
    //   3706: ifnull +20 -> 3726
    //   3709: aload 30
    //   3711: getfield 660	com/google/android/gms/internal/measurement/zzfy:zzavc	Ljava/lang/Boolean;
    //   3714: invokevirtual 46	java/lang/Boolean:booleanValue	()Z
    //   3717: ifeq +9 -> 3726
    //   3720: iconst_1
    //   3721: istore 7
    //   3723: goto +6 -> 3729
    //   3726: iconst_0
    //   3727: istore 7
    //   3729: aload 24
    //   3731: aload 30
    //   3733: getfield 652	com/google/android/gms/internal/measurement/zzfy:zzave	Ljava/lang/Integer;
    //   3736: invokevirtual 310	java/lang/Integer:intValue	()I
    //   3739: invokevirtual 627	java/util/BitSet:get	(I)Z
    //   3742: ifeq +39 -> 3781
    //   3745: iload 6
    //   3747: ifne +34 -> 3781
    //   3750: iload 7
    //   3752: ifne +29 -> 3781
    //   3755: aload_0
    //   3756: invokevirtual 77	com/google/android/gms/measurement/internal/zzco:zzgo	()Lcom/google/android/gms/measurement/internal/zzap;
    //   3759: invokevirtual 206	com/google/android/gms/measurement/internal/zzap:zzjl	()Lcom/google/android/gms/measurement/internal/zzar;
    //   3762: ldc_w 662
    //   3765: iload 8
    //   3767: invokestatic 366	java/lang/Integer:valueOf	(I)Ljava/lang/Integer;
    //   3770: aload 30
    //   3772: getfield 652	com/google/android/gms/internal/measurement/zzfy:zzave	Ljava/lang/Integer;
    //   3775: invokevirtual 144	com/google/android/gms/measurement/internal/zzar:zze	(Ljava/lang/String;Ljava/lang/Object;Ljava/lang/Object;)V
    //   3778: goto +219 -> 3997
    //   3781: aload_0
    //   3782: aload 30
    //   3784: aload 31
    //   3786: invokespecial 664	com/google/android/gms/measurement/internal/zzj:zza	(Lcom/google/android/gms/internal/measurement/zzfy;Lcom/google/android/gms/internal/measurement/zzgl;)Ljava/lang/Boolean;
    //   3789: astore 28
    //   3791: aload_0
    //   3792: invokevirtual 77	com/google/android/gms/measurement/internal/zzco:zzgo	()Lcom/google/android/gms/measurement/internal/zzap;
    //   3795: invokevirtual 206	com/google/android/gms/measurement/internal/zzap:zzjl	()Lcom/google/android/gms/measurement/internal/zzar;
    //   3798: astore 32
    //   3800: aload 28
    //   3802: ifnonnull +11 -> 3813
    //   3805: ldc_w 633
    //   3808: astore 27
    //   3810: goto +7 -> 3817
    //   3813: aload 28
    //   3815: astore 27
    //   3817: aload 32
    //   3819: ldc_w 666
    //   3822: aload 27
    //   3824: invokevirtual 101	com/google/android/gms/measurement/internal/zzar:zzg	(Ljava/lang/String;Ljava/lang/Object;)V
    //   3827: aload 28
    //   3829: ifnonnull +19 -> 3848
    //   3832: aload 29
    //   3834: iload 8
    //   3836: invokestatic 366	java/lang/Integer:valueOf	(I)Ljava/lang/Integer;
    //   3839: invokeinterface 107 2 0
    //   3844: pop
    //   3845: goto +152 -> 3997
    //   3848: aload 25
    //   3850: aload 30
    //   3852: getfield 652	com/google/android/gms/internal/measurement/zzfy:zzave	Ljava/lang/Integer;
    //   3855: invokevirtual 310	java/lang/Integer:intValue	()I
    //   3858: invokevirtual 461	java/util/BitSet:set	(I)V
    //   3861: aload 24
    //   3863: aload 30
    //   3865: getfield 652	com/google/android/gms/internal/measurement/zzfy:zzave	Ljava/lang/Integer;
    //   3868: invokevirtual 310	java/lang/Integer:intValue	()I
    //   3871: aload 28
    //   3873: invokevirtual 46	java/lang/Boolean:booleanValue	()Z
    //   3876: invokevirtual 669	java/util/BitSet:set	(IZ)V
    //   3879: aload 28
    //   3881: invokevirtual 46	java/lang/Boolean:booleanValue	()Z
    //   3884: ifeq +113 -> 3997
    //   3887: iload 6
    //   3889: ifne +8 -> 3897
    //   3892: iload 7
    //   3894: ifeq +103 -> 3997
    //   3897: aload 31
    //   3899: getfield 672	com/google/android/gms/internal/measurement/zzgl:zzayl	Ljava/lang/Long;
    //   3902: ifnull +95 -> 3997
    //   3905: iload 7
    //   3907: ifeq +27 -> 3934
    //   3910: aload 23
    //   3912: aload 30
    //   3914: getfield 652	com/google/android/gms/internal/measurement/zzfy:zzave	Ljava/lang/Integer;
    //   3917: invokevirtual 310	java/lang/Integer:intValue	()I
    //   3920: aload 31
    //   3922: getfield 672	com/google/android/gms/internal/measurement/zzgl:zzayl	Ljava/lang/Long;
    //   3925: invokevirtual 171	java/lang/Long:longValue	()J
    //   3928: invokestatic 637	com/google/android/gms/measurement/internal/zzj:zzb	(Ljava/util/Map;IJ)V
    //   3931: goto +66 -> 3997
    //   3934: aload 21
    //   3936: aload 30
    //   3938: getfield 652	com/google/android/gms/internal/measurement/zzfy:zzave	Ljava/lang/Integer;
    //   3941: invokevirtual 310	java/lang/Integer:intValue	()I
    //   3944: aload 31
    //   3946: getfield 672	com/google/android/gms/internal/measurement/zzgl:zzayl	Ljava/lang/Long;
    //   3949: invokevirtual 171	java/lang/Long:longValue	()J
    //   3952: invokestatic 639	com/google/android/gms/measurement/internal/zzj:zza	(Ljava/util/Map;IJ)V
    //   3955: goto +42 -> 3997
    //   3958: aload 24
    //   3960: aload 30
    //   3962: getfield 652	com/google/android/gms/internal/measurement/zzfy:zzave	Ljava/lang/Integer;
    //   3965: invokevirtual 310	java/lang/Integer:intValue	()I
    //   3968: invokevirtual 627	java/util/BitSet:get	(I)Z
    //   3971: ifeq +29 -> 4000
    //   3974: aload_0
    //   3975: invokevirtual 77	com/google/android/gms/measurement/internal/zzco:zzgo	()Lcom/google/android/gms/measurement/internal/zzap;
    //   3978: invokevirtual 206	com/google/android/gms/measurement/internal/zzap:zzjl	()Lcom/google/android/gms/measurement/internal/zzar;
    //   3981: ldc_w 674
    //   3984: iload 8
    //   3986: invokestatic 366	java/lang/Integer:valueOf	(I)Ljava/lang/Integer;
    //   3989: aload 30
    //   3991: getfield 652	com/google/android/gms/internal/measurement/zzfy:zzave	Ljava/lang/Integer;
    //   3994: invokevirtual 144	com/google/android/gms/measurement/internal/zzar:zze	(Ljava/lang/String;Ljava/lang/Object;Ljava/lang/Object;)V
    //   3997: goto -457 -> 3540
    //   4000: aload_0
    //   4001: aload 30
    //   4003: aload 31
    //   4005: invokespecial 664	com/google/android/gms/measurement/internal/zzj:zza	(Lcom/google/android/gms/internal/measurement/zzfy;Lcom/google/android/gms/internal/measurement/zzgl;)Ljava/lang/Boolean;
    //   4008: astore 28
    //   4010: aload_0
    //   4011: invokevirtual 77	com/google/android/gms/measurement/internal/zzco:zzgo	()Lcom/google/android/gms/measurement/internal/zzap;
    //   4014: invokevirtual 206	com/google/android/gms/measurement/internal/zzap:zzjl	()Lcom/google/android/gms/measurement/internal/zzar;
    //   4017: astore 32
    //   4019: aload 28
    //   4021: ifnonnull +11 -> 4032
    //   4024: ldc_w 633
    //   4027: astore 27
    //   4029: goto +7 -> 4036
    //   4032: aload 28
    //   4034: astore 27
    //   4036: aload 32
    //   4038: ldc_w 666
    //   4041: aload 27
    //   4043: invokevirtual 101	com/google/android/gms/measurement/internal/zzar:zzg	(Ljava/lang/String;Ljava/lang/Object;)V
    //   4046: aload 28
    //   4048: ifnonnull +19 -> 4067
    //   4051: aload 29
    //   4053: iload 8
    //   4055: invokestatic 366	java/lang/Integer:valueOf	(I)Ljava/lang/Integer;
    //   4058: invokeinterface 107 2 0
    //   4063: pop
    //   4064: goto -67 -> 3997
    //   4067: aload 25
    //   4069: aload 30
    //   4071: getfield 652	com/google/android/gms/internal/measurement/zzfy:zzave	Ljava/lang/Integer;
    //   4074: invokevirtual 310	java/lang/Integer:intValue	()I
    //   4077: invokevirtual 461	java/util/BitSet:set	(I)V
    //   4080: aload 28
    //   4082: invokevirtual 46	java/lang/Boolean:booleanValue	()Z
    //   4085: ifeq -88 -> 3997
    //   4088: aload 24
    //   4090: aload 30
    //   4092: getfield 652	com/google/android/gms/internal/measurement/zzfy:zzave	Ljava/lang/Integer;
    //   4095: invokevirtual 310	java/lang/Integer:intValue	()I
    //   4098: invokevirtual 461	java/util/BitSet:set	(I)V
    //   4101: goto -104 -> 3997
    //   4104: aload_0
    //   4105: invokevirtual 77	com/google/android/gms/measurement/internal/zzco:zzgo	()Lcom/google/android/gms/measurement/internal/zzap;
    //   4108: invokevirtual 83	com/google/android/gms/measurement/internal/zzap:zzjg	()Lcom/google/android/gms/measurement/internal/zzar;
    //   4111: ldc_w 676
    //   4114: aload_1
    //   4115: invokestatic 573	com/google/android/gms/measurement/internal/zzap:zzbv	(Ljava/lang/String;)Ljava/lang/Object;
    //   4118: aload 30
    //   4120: getfield 652	com/google/android/gms/internal/measurement/zzfy:zzave	Ljava/lang/Integer;
    //   4123: invokestatic 646	java/lang/String:valueOf	(Ljava/lang/Object;)Ljava/lang/String;
    //   4126: invokevirtual 144	com/google/android/gms/measurement/internal/zzar:zze	(Ljava/lang/String;Ljava/lang/Object;Ljava/lang/Object;)V
    //   4129: aload 29
    //   4131: iload 8
    //   4133: invokestatic 366	java/lang/Integer:valueOf	(I)Ljava/lang/Integer;
    //   4136: invokeinterface 107 2 0
    //   4141: pop
    //   4142: aload 20
    //   4144: astore 23
    //   4146: aload 19
    //   4148: astore 21
    //   4150: aload 18
    //   4152: astore 20
    //   4154: aload 23
    //   4156: astore 19
    //   4158: goto +15 -> 4173
    //   4161: aload 19
    //   4163: astore 21
    //   4165: aload 20
    //   4167: astore 19
    //   4169: aload 18
    //   4171: astore 20
    //   4173: aload 15
    //   4175: astore 23
    //   4177: aload 22
    //   4179: astore 18
    //   4181: aload_2
    //   4182: astore 15
    //   4184: aload 21
    //   4186: astore_2
    //   4187: aload 19
    //   4189: astore 21
    //   4191: aload 23
    //   4193: astore 19
    //   4195: goto -1050 -> 3145
    //   4198: iload 5
    //   4200: iconst_1
    //   4201: iadd
    //   4202: istore 5
    //   4204: aload 18
    //   4206: astore 24
    //   4208: aload 20
    //   4210: astore 16
    //   4212: aload 21
    //   4214: astore 17
    //   4216: aload 19
    //   4218: astore 18
    //   4220: goto -1218 -> 3002
    //   4223: aload 23
    //   4225: astore 15
    //   4227: aload 22
    //   4229: astore 16
    //   4231: aload 21
    //   4233: astore 17
    //   4235: aload 20
    //   4237: astore_3
    //   4238: aload 19
    //   4240: astore 18
    //   4242: aload 18
    //   4244: invokeinterface 377 1 0
    //   4249: anewarray 469	com/google/android/gms/internal/measurement/zzgd
    //   4252: astore 22
    //   4254: aload 18
    //   4256: invokeinterface 383 1 0
    //   4261: invokeinterface 387 1 0
    //   4266: astore_2
    //   4267: iconst_0
    //   4268: istore 4
    //   4270: aload_2
    //   4271: invokeinterface 392 1 0
    //   4276: ifeq +670 -> 4946
    //   4279: aload_2
    //   4280: invokeinterface 396 1 0
    //   4285: checkcast 307	java/lang/Integer
    //   4288: invokevirtual 310	java/lang/Integer:intValue	()I
    //   4291: istore 7
    //   4293: aload 29
    //   4295: iload 7
    //   4297: invokestatic 366	java/lang/Integer:valueOf	(I)Ljava/lang/Integer;
    //   4300: invokeinterface 118 2 0
    //   4305: ifne +638 -> 4943
    //   4308: aload_3
    //   4309: iload 7
    //   4311: invokestatic 366	java/lang/Integer:valueOf	(I)Ljava/lang/Integer;
    //   4314: invokeinterface 160 2 0
    //   4319: checkcast 469	com/google/android/gms/internal/measurement/zzgd
    //   4322: astore 20
    //   4324: aload 20
    //   4326: astore 19
    //   4328: aload 20
    //   4330: ifnonnull +12 -> 4342
    //   4333: new 469	com/google/android/gms/internal/measurement/zzgd
    //   4336: dup
    //   4337: invokespecial 470	com/google/android/gms/internal/measurement/zzgd:<init>	()V
    //   4340: astore 19
    //   4342: aload 22
    //   4344: iload 4
    //   4346: aload 19
    //   4348: aastore
    //   4349: aload 19
    //   4351: iload 7
    //   4353: invokestatic 366	java/lang/Integer:valueOf	(I)Ljava/lang/Integer;
    //   4356: putfield 679	com/google/android/gms/internal/measurement/zzgd:zzauy	Ljava/lang/Integer;
    //   4359: aload 19
    //   4361: new 442	com/google/android/gms/internal/measurement/zzgj
    //   4364: dup
    //   4365: invokespecial 478	com/google/android/gms/internal/measurement/zzgj:<init>	()V
    //   4368: putfield 481	com/google/android/gms/internal/measurement/zzgd:zzawm	Lcom/google/android/gms/internal/measurement/zzgj;
    //   4371: aload 19
    //   4373: getfield 481	com/google/android/gms/internal/measurement/zzgd:zzawm	Lcom/google/android/gms/internal/measurement/zzgj;
    //   4376: aload 18
    //   4378: iload 7
    //   4380: invokestatic 366	java/lang/Integer:valueOf	(I)Ljava/lang/Integer;
    //   4383: invokeinterface 160 2 0
    //   4388: checkcast 444	java/util/BitSet
    //   4391: invokestatic 484	com/google/android/gms/measurement/internal/zzfg:zza	(Ljava/util/BitSet;)[J
    //   4394: putfield 464	com/google/android/gms/internal/measurement/zzgj:zzayf	[J
    //   4397: aload 19
    //   4399: getfield 481	com/google/android/gms/internal/measurement/zzgd:zzawm	Lcom/google/android/gms/internal/measurement/zzgj;
    //   4402: aload 17
    //   4404: iload 7
    //   4406: invokestatic 366	java/lang/Integer:valueOf	(I)Ljava/lang/Integer;
    //   4409: invokeinterface 160 2 0
    //   4414: checkcast 444	java/util/BitSet
    //   4417: invokestatic 484	com/google/android/gms/measurement/internal/zzfg:zza	(Ljava/util/BitSet;)[J
    //   4420: putfield 453	com/google/android/gms/internal/measurement/zzgj:zzaye	[J
    //   4423: iload 10
    //   4425: ifeq +270 -> 4695
    //   4428: aload 19
    //   4430: getfield 481	com/google/android/gms/internal/measurement/zzgd:zzawm	Lcom/google/android/gms/internal/measurement/zzgj;
    //   4433: aload 16
    //   4435: iload 7
    //   4437: invokestatic 366	java/lang/Integer:valueOf	(I)Ljava/lang/Integer;
    //   4440: invokeinterface 160 2 0
    //   4445: checkcast 124	java/util/Map
    //   4448: invokestatic 486	com/google/android/gms/measurement/internal/zzj:zzd	(Ljava/util/Map;)[Lcom/google/android/gms/internal/measurement/zzge;
    //   4451: putfield 448	com/google/android/gms/internal/measurement/zzgj:zzayg	[Lcom/google/android/gms/internal/measurement/zzge;
    //   4454: aload 19
    //   4456: getfield 481	com/google/android/gms/internal/measurement/zzgd:zzawm	Lcom/google/android/gms/internal/measurement/zzgj;
    //   4459: astore 23
    //   4461: aload 15
    //   4463: iload 7
    //   4465: invokestatic 366	java/lang/Integer:valueOf	(I)Ljava/lang/Integer;
    //   4468: invokeinterface 160 2 0
    //   4473: checkcast 124	java/util/Map
    //   4476: astore 20
    //   4478: aload 20
    //   4480: ifnonnull +20 -> 4500
    //   4483: aload_3
    //   4484: astore 20
    //   4486: iconst_0
    //   4487: anewarray 681	com/google/android/gms/internal/measurement/zzgk
    //   4490: astore 21
    //   4492: aload_2
    //   4493: astore_3
    //   4494: aload 20
    //   4496: astore_2
    //   4497: goto +188 -> 4685
    //   4500: aload 20
    //   4502: invokeinterface 377 1 0
    //   4507: anewarray 681	com/google/android/gms/internal/measurement/zzgk
    //   4510: astore 21
    //   4512: aload 20
    //   4514: invokeinterface 383 1 0
    //   4519: invokeinterface 387 1 0
    //   4524: astore 24
    //   4526: iconst_0
    //   4527: istore 5
    //   4529: aload 24
    //   4531: invokeinterface 392 1 0
    //   4536: ifeq +141 -> 4677
    //   4539: aload 24
    //   4541: invokeinterface 396 1 0
    //   4546: checkcast 307	java/lang/Integer
    //   4549: astore 26
    //   4551: new 681	com/google/android/gms/internal/measurement/zzgk
    //   4554: dup
    //   4555: invokespecial 682	com/google/android/gms/internal/measurement/zzgk:<init>	()V
    //   4558: astore 25
    //   4560: aload 25
    //   4562: aload 26
    //   4564: putfield 683	com/google/android/gms/internal/measurement/zzgk:zzawq	Ljava/lang/Integer;
    //   4567: aload 20
    //   4569: aload 26
    //   4571: invokeinterface 160 2 0
    //   4576: checkcast 248	java/util/List
    //   4579: astore 27
    //   4581: aload 27
    //   4583: ifnull +78 -> 4661
    //   4586: aload 27
    //   4588: invokestatic 689	java/util/Collections:sort	(Ljava/util/List;)V
    //   4591: aload 27
    //   4593: invokeinterface 252 1 0
    //   4598: newarray long
    //   4600: astore 26
    //   4602: aload 27
    //   4604: invokeinterface 599 1 0
    //   4609: astore 27
    //   4611: iconst_0
    //   4612: istore 6
    //   4614: aload 27
    //   4616: invokeinterface 392 1 0
    //   4621: ifeq +30 -> 4651
    //   4624: aload 26
    //   4626: iload 6
    //   4628: aload 27
    //   4630: invokeinterface 396 1 0
    //   4635: checkcast 162	java/lang/Long
    //   4638: invokevirtual 171	java/lang/Long:longValue	()J
    //   4641: lastore
    //   4642: iload 6
    //   4644: iconst_1
    //   4645: iadd
    //   4646: istore 6
    //   4648: goto -34 -> 4614
    //   4651: aload 25
    //   4653: aload 26
    //   4655: putfield 692	com/google/android/gms/internal/measurement/zzgk:zzayj	[J
    //   4658: goto +3 -> 4661
    //   4661: aload 21
    //   4663: iload 5
    //   4665: aload 25
    //   4667: aastore
    //   4668: iload 5
    //   4670: iconst_1
    //   4671: iadd
    //   4672: istore 5
    //   4674: goto -145 -> 4529
    //   4677: aload_2
    //   4678: astore 20
    //   4680: aload_3
    //   4681: astore_2
    //   4682: aload 20
    //   4684: astore_3
    //   4685: aload 23
    //   4687: aload 21
    //   4689: putfield 696	com/google/android/gms/internal/measurement/zzgj:zzayh	[Lcom/google/android/gms/internal/measurement/zzgk;
    //   4692: goto +11 -> 4703
    //   4695: aload_2
    //   4696: astore 20
    //   4698: aload_3
    //   4699: astore_2
    //   4700: aload 20
    //   4702: astore_3
    //   4703: aload_0
    //   4704: invokevirtual 434	com/google/android/gms/measurement/internal/zzey:zzjq	()Lcom/google/android/gms/measurement/internal/zzq;
    //   4707: astore 20
    //   4709: aload 19
    //   4711: getfield 481	com/google/android/gms/internal/measurement/zzgd:zzawm	Lcom/google/android/gms/internal/measurement/zzgj;
    //   4714: astore 21
    //   4716: aload 20
    //   4718: invokevirtual 699	com/google/android/gms/measurement/internal/zzez:zzcl	()V
    //   4721: aload 20
    //   4723: invokevirtual 529	com/google/android/gms/measurement/internal/zzco:zzaf	()V
    //   4726: aload_1
    //   4727: invokestatic 413	com/google/android/gms/common/internal/Preconditions:checkNotEmpty	(Ljava/lang/String;)Ljava/lang/String;
    //   4730: pop
    //   4731: aload 21
    //   4733: invokestatic 299	com/google/android/gms/common/internal/Preconditions:checkNotNull	(Ljava/lang/Object;)Ljava/lang/Object;
    //   4736: pop
    //   4737: aload 21
    //   4739: invokevirtual 704	com/google/android/gms/internal/measurement/zzzg:zzvu	()I
    //   4742: newarray byte
    //   4744: astore 19
    //   4746: aload 19
    //   4748: arraylength
    //   4749: istore 5
    //   4751: aload 19
    //   4753: iconst_0
    //   4754: iload 5
    //   4756: invokestatic 710	com/google/android/gms/internal/measurement/zzyy:zzk	([BII)Lcom/google/android/gms/internal/measurement/zzyy;
    //   4759: astore 23
    //   4761: aload 21
    //   4763: aload 23
    //   4765: invokevirtual 713	com/google/android/gms/internal/measurement/zzzg:zza	(Lcom/google/android/gms/internal/measurement/zzyy;)V
    //   4768: aload 23
    //   4770: invokevirtual 716	com/google/android/gms/internal/measurement/zzyy:zzyt	()V
    //   4773: new 718	android/content/ContentValues
    //   4776: dup
    //   4777: invokespecial 719	android/content/ContentValues:<init>	()V
    //   4780: astore 21
    //   4782: aload 21
    //   4784: ldc_w 721
    //   4787: aload_1
    //   4788: invokevirtual 724	android/content/ContentValues:put	(Ljava/lang/String;Ljava/lang/String;)V
    //   4791: aload 21
    //   4793: ldc_w 726
    //   4796: iload 7
    //   4798: invokestatic 366	java/lang/Integer:valueOf	(I)Ljava/lang/Integer;
    //   4801: invokevirtual 729	android/content/ContentValues:put	(Ljava/lang/String;Ljava/lang/Integer;)V
    //   4804: aload 21
    //   4806: ldc_w 731
    //   4809: aload 19
    //   4811: invokevirtual 734	android/content/ContentValues:put	(Ljava/lang/String;[B)V
    //   4814: aload 20
    //   4816: invokevirtual 535	com/google/android/gms/measurement/internal/zzq:getWritableDatabase	()Landroid/database/sqlite/SQLiteDatabase;
    //   4819: astore 19
    //   4821: aload 19
    //   4823: ldc_w 736
    //   4826: aconst_null
    //   4827: aload 21
    //   4829: iconst_5
    //   4830: invokevirtual 740	android/database/sqlite/SQLiteDatabase:insertWithOnConflict	(Ljava/lang/String;Ljava/lang/String;Landroid/content/ContentValues;I)J
    //   4833: ldc2_w 741
    //   4836: lcmp
    //   4837: ifne +81 -> 4918
    //   4840: aload 20
    //   4842: invokevirtual 77	com/google/android/gms/measurement/internal/zzco:zzgo	()Lcom/google/android/gms/measurement/internal/zzap;
    //   4845: invokevirtual 512	com/google/android/gms/measurement/internal/zzap:zzjd	()Lcom/google/android/gms/measurement/internal/zzar;
    //   4848: ldc_w 744
    //   4851: aload_1
    //   4852: invokestatic 573	com/google/android/gms/measurement/internal/zzap:zzbv	(Ljava/lang/String;)Ljava/lang/Object;
    //   4855: invokevirtual 101	com/google/android/gms/measurement/internal/zzar:zzg	(Ljava/lang/String;Ljava/lang/Object;)V
    //   4858: goto +60 -> 4918
    //   4861: astore 19
    //   4863: goto +5 -> 4868
    //   4866: astore 19
    //   4868: aload 20
    //   4870: invokevirtual 77	com/google/android/gms/measurement/internal/zzco:zzgo	()Lcom/google/android/gms/measurement/internal/zzap;
    //   4873: invokevirtual 512	com/google/android/gms/measurement/internal/zzap:zzjd	()Lcom/google/android/gms/measurement/internal/zzar;
    //   4876: ldc_w 746
    //   4879: aload_1
    //   4880: invokestatic 573	com/google/android/gms/measurement/internal/zzap:zzbv	(Ljava/lang/String;)Ljava/lang/Object;
    //   4883: aload 19
    //   4885: invokevirtual 144	com/google/android/gms/measurement/internal/zzar:zze	(Ljava/lang/String;Ljava/lang/Object;Ljava/lang/Object;)V
    //   4888: goto +30 -> 4918
    //   4891: astore 19
    //   4893: goto +5 -> 4898
    //   4896: astore 19
    //   4898: aload 20
    //   4900: invokevirtual 77	com/google/android/gms/measurement/internal/zzco:zzgo	()Lcom/google/android/gms/measurement/internal/zzap;
    //   4903: invokevirtual 512	com/google/android/gms/measurement/internal/zzap:zzjd	()Lcom/google/android/gms/measurement/internal/zzar;
    //   4906: ldc_w 748
    //   4909: aload_1
    //   4910: invokestatic 573	com/google/android/gms/measurement/internal/zzap:zzbv	(Ljava/lang/String;)Ljava/lang/Object;
    //   4913: aload 19
    //   4915: invokevirtual 144	com/google/android/gms/measurement/internal/zzar:zze	(Ljava/lang/String;Ljava/lang/Object;Ljava/lang/Object;)V
    //   4918: iload 4
    //   4920: iconst_1
    //   4921: iadd
    //   4922: istore 4
    //   4924: aload 15
    //   4926: astore 19
    //   4928: aload_3
    //   4929: astore 15
    //   4931: aload_2
    //   4932: astore_3
    //   4933: aload 15
    //   4935: astore_2
    //   4936: aload 19
    //   4938: astore 15
    //   4940: goto -670 -> 4270
    //   4943: goto -673 -> 4270
    //   4946: aload 22
    //   4948: iload 4
    //   4950: invokestatic 555	java/util/Arrays:copyOf	([Ljava/lang/Object;I)[Ljava/lang/Object;
    //   4953: checkcast 750	[Lcom/google/android/gms/internal/measurement/zzgd;
    //   4956: areturn
    // Exception table:
    //   from	to	target	type
    //   1049	1066	1069	android/database/sqlite/SQLiteException
    //   1042	1049	1078	android/database/sqlite/SQLiteException
    //   4821	4858	4861	android/database/sqlite/SQLiteException
    //   4814	4821	4866	android/database/sqlite/SQLiteException
    //   4751	4773	4891	java/io/IOException
    //   4737	4751	4896	java/io/IOException
  }
  
  protected final boolean zzgt()
  {
    return false;
  }
}
