package com.google.android.gms.measurement.internal;

import android.database.sqlite.SQLiteDatabase;
import android.database.sqlite.SQLiteException;
import android.os.Parcel;
import android.support.annotation.WorkerThread;
import com.google.android.gms.common.util.VisibleForTesting;

public final class zzal
  extends zzf
{
  private final zzam zzalq = new zzam(this, getContext(), "google_app_measurement_local.db");
  private boolean zzalr;
  
  zzal(zzbt paramZzbt)
  {
    super(paramZzbt);
  }
  
  @WorkerThread
  @VisibleForTesting
  private final SQLiteDatabase getWritableDatabase()
    throws SQLiteException
  {
    if (zzalr) {
      return null;
    }
    SQLiteDatabase localSQLiteDatabase = zzalq.getWritableDatabase();
    if (localSQLiteDatabase == null)
    {
      zzalr = true;
      return null;
    }
    return localSQLiteDatabase;
  }
  
  /* Error */
  @WorkerThread
  private final boolean zza(int paramInt, byte[] paramArrayOfByte)
  {
    // Byte code:
    //   0: aload_0
    //   1: invokevirtual 50	com/google/android/gms/measurement/internal/zzco:zzgb	()V
    //   4: aload_0
    //   5: invokevirtual 53	com/google/android/gms/measurement/internal/zzco:zzaf	()V
    //   8: aload_0
    //   9: getfield 36	com/google/android/gms/measurement/internal/zzal:zzalr	Z
    //   12: ifeq +5 -> 17
    //   15: iconst_0
    //   16: ireturn
    //   17: new 55	android/content/ContentValues
    //   20: dup
    //   21: invokespecial 57	android/content/ContentValues:<init>	()V
    //   24: astore 14
    //   26: aload 14
    //   28: ldc 59
    //   30: iload_1
    //   31: invokestatic 65	java/lang/Integer:valueOf	(I)Ljava/lang/Integer;
    //   34: invokevirtual 69	android/content/ContentValues:put	(Ljava/lang/String;Ljava/lang/Integer;)V
    //   37: aload 14
    //   39: ldc 71
    //   41: aload_2
    //   42: invokevirtual 74	android/content/ContentValues:put	(Ljava/lang/String;[B)V
    //   45: iconst_0
    //   46: istore_3
    //   47: iconst_5
    //   48: istore 4
    //   50: iload_3
    //   51: iconst_5
    //   52: if_icmpge +516 -> 568
    //   55: aconst_null
    //   56: astore 13
    //   58: aconst_null
    //   59: astore 12
    //   61: aconst_null
    //   62: astore 10
    //   64: aconst_null
    //   65: astore 9
    //   67: aload_0
    //   68: invokespecial 75	com/google/android/gms/measurement/internal/zzal:getWritableDatabase	()Landroid/database/sqlite/SQLiteDatabase;
    //   71: astore_2
    //   72: aload_2
    //   73: ifnonnull +38 -> 111
    //   76: aload 10
    //   78: astore 11
    //   80: aload_2
    //   81: astore 9
    //   83: aload_0
    //   84: iconst_1
    //   85: putfield 36	com/google/android/gms/measurement/internal/zzal:zzalr	Z
    //   88: aload_2
    //   89: ifnull +7 -> 96
    //   92: aload_2
    //   93: invokevirtual 80	android/database/sqlite/SQLiteDatabase:close	()V
    //   96: iconst_0
    //   97: ireturn
    //   98: astore 9
    //   100: aconst_null
    //   101: astore 10
    //   103: goto +231 -> 334
    //   106: astore 10
    //   108: goto +355 -> 463
    //   111: aload 10
    //   113: astore 11
    //   115: aload_2
    //   116: astore 9
    //   118: aload_2
    //   119: invokevirtual 83	android/database/sqlite/SQLiteDatabase:beginTransaction	()V
    //   122: lconst_0
    //   123: lstore 7
    //   125: aload 10
    //   127: astore 11
    //   129: aload_2
    //   130: astore 9
    //   132: aload_2
    //   133: ldc 85
    //   135: aconst_null
    //   136: invokevirtual 89	android/database/sqlite/SQLiteDatabase:rawQuery	(Ljava/lang/String;[Ljava/lang/String;)Landroid/database/Cursor;
    //   139: astore 10
    //   141: lload 7
    //   143: lstore 5
    //   145: aload 10
    //   147: ifnull +30 -> 177
    //   150: lload 7
    //   152: lstore 5
    //   154: aload 10
    //   156: invokeinterface 95 1 0
    //   161: ifeq +16 -> 177
    //   164: aload 10
    //   166: iconst_0
    //   167: invokeinterface 99 2 0
    //   172: lstore 5
    //   174: goto +3 -> 177
    //   177: lload 5
    //   179: ldc2_w 100
    //   182: lcmp
    //   183: iflt +86 -> 269
    //   186: aload_0
    //   187: invokevirtual 105	com/google/android/gms/measurement/internal/zzco:zzgo	()Lcom/google/android/gms/measurement/internal/zzap;
    //   190: invokevirtual 111	com/google/android/gms/measurement/internal/zzap:zzjd	()Lcom/google/android/gms/measurement/internal/zzar;
    //   193: ldc 113
    //   195: invokevirtual 119	com/google/android/gms/measurement/internal/zzar:zzbx	(Ljava/lang/String;)V
    //   198: ldc2_w 100
    //   201: lload 5
    //   203: lsub
    //   204: lconst_1
    //   205: ladd
    //   206: lstore 5
    //   208: aload_2
    //   209: ldc 121
    //   211: ldc 123
    //   213: iconst_1
    //   214: anewarray 125	java/lang/String
    //   217: dup
    //   218: iconst_0
    //   219: lload 5
    //   221: invokestatic 131	java/lang/Long:toString	(J)Ljava/lang/String;
    //   224: aastore
    //   225: invokevirtual 135	android/database/sqlite/SQLiteDatabase:delete	(Ljava/lang/String;Ljava/lang/String;[Ljava/lang/String;)I
    //   228: i2l
    //   229: lstore 7
    //   231: lload 7
    //   233: lload 5
    //   235: lcmp
    //   236: ifeq +33 -> 269
    //   239: aload_0
    //   240: invokevirtual 105	com/google/android/gms/measurement/internal/zzco:zzgo	()Lcom/google/android/gms/measurement/internal/zzap;
    //   243: invokevirtual 111	com/google/android/gms/measurement/internal/zzap:zzjd	()Lcom/google/android/gms/measurement/internal/zzar;
    //   246: ldc -119
    //   248: lload 5
    //   250: invokestatic 140	java/lang/Long:valueOf	(J)Ljava/lang/Long;
    //   253: lload 7
    //   255: invokestatic 140	java/lang/Long:valueOf	(J)Ljava/lang/Long;
    //   258: lload 5
    //   260: lload 7
    //   262: lsub
    //   263: invokestatic 140	java/lang/Long:valueOf	(J)Ljava/lang/Long;
    //   266: invokevirtual 144	com/google/android/gms/measurement/internal/zzar:zzd	(Ljava/lang/String;Ljava/lang/Object;Ljava/lang/Object;Ljava/lang/Object;)V
    //   269: aload_2
    //   270: ldc 121
    //   272: aconst_null
    //   273: aload 14
    //   275: invokevirtual 148	android/database/sqlite/SQLiteDatabase:insertOrThrow	(Ljava/lang/String;Ljava/lang/String;Landroid/content/ContentValues;)J
    //   278: pop2
    //   279: aload_2
    //   280: invokevirtual 151	android/database/sqlite/SQLiteDatabase:setTransactionSuccessful	()V
    //   283: aload_2
    //   284: invokevirtual 154	android/database/sqlite/SQLiteDatabase:endTransaction	()V
    //   287: aload 10
    //   289: ifnull +10 -> 299
    //   292: aload 10
    //   294: invokeinterface 155 1 0
    //   299: aload_2
    //   300: ifnull +7 -> 307
    //   303: aload_2
    //   304: invokevirtual 80	android/database/sqlite/SQLiteDatabase:close	()V
    //   307: iconst_1
    //   308: ireturn
    //   309: goto +97 -> 406
    //   312: astore 9
    //   314: aconst_null
    //   315: astore_2
    //   316: aload_2
    //   317: astore 10
    //   319: goto +226 -> 545
    //   322: astore 11
    //   324: aconst_null
    //   325: astore 10
    //   327: aload 9
    //   329: astore_2
    //   330: aload 11
    //   332: astore 9
    //   334: aload_2
    //   335: ifnull +17 -> 352
    //   338: aload_2
    //   339: invokevirtual 158	android/database/sqlite/SQLiteDatabase:inTransaction	()Z
    //   342: ifeq +10 -> 352
    //   345: aload_2
    //   346: invokevirtual 154	android/database/sqlite/SQLiteDatabase:endTransaction	()V
    //   349: goto +3 -> 352
    //   352: aload_0
    //   353: invokevirtual 105	com/google/android/gms/measurement/internal/zzco:zzgo	()Lcom/google/android/gms/measurement/internal/zzap;
    //   356: invokevirtual 111	com/google/android/gms/measurement/internal/zzap:zzjd	()Lcom/google/android/gms/measurement/internal/zzar;
    //   359: ldc -96
    //   361: aload 9
    //   363: invokevirtual 164	com/google/android/gms/measurement/internal/zzar:zzg	(Ljava/lang/String;Ljava/lang/Object;)V
    //   366: aload_0
    //   367: iconst_1
    //   368: putfield 36	com/google/android/gms/measurement/internal/zzal:zzalr	Z
    //   371: aload 10
    //   373: ifnull +10 -> 383
    //   376: aload 10
    //   378: invokeinterface 155 1 0
    //   383: iload 4
    //   385: istore_1
    //   386: aload_2
    //   387: ifnull +135 -> 522
    //   390: aload_2
    //   391: invokevirtual 80	android/database/sqlite/SQLiteDatabase:close	()V
    //   394: iload 4
    //   396: istore_1
    //   397: goto +125 -> 522
    //   400: aconst_null
    //   401: astore_2
    //   402: aload 13
    //   404: astore 10
    //   406: iload 4
    //   408: i2l
    //   409: lstore 5
    //   411: aload 10
    //   413: astore 11
    //   415: aload_2
    //   416: astore 9
    //   418: lload 5
    //   420: invokestatic 170	android/os/SystemClock:sleep	(J)V
    //   423: iload 4
    //   425: bipush 20
    //   427: iadd
    //   428: istore 4
    //   430: aload 10
    //   432: ifnull +10 -> 442
    //   435: aload 10
    //   437: invokeinterface 155 1 0
    //   442: iload 4
    //   444: istore_1
    //   445: aload_2
    //   446: ifnull +76 -> 522
    //   449: aload_2
    //   450: invokevirtual 80	android/database/sqlite/SQLiteDatabase:close	()V
    //   453: iload 4
    //   455: istore_1
    //   456: goto +66 -> 522
    //   459: astore 10
    //   461: aconst_null
    //   462: astore_2
    //   463: aload 12
    //   465: astore 11
    //   467: aload_2
    //   468: astore 9
    //   470: aload_0
    //   471: invokevirtual 105	com/google/android/gms/measurement/internal/zzco:zzgo	()Lcom/google/android/gms/measurement/internal/zzap;
    //   474: invokevirtual 111	com/google/android/gms/measurement/internal/zzap:zzjd	()Lcom/google/android/gms/measurement/internal/zzar;
    //   477: ldc -96
    //   479: aload 10
    //   481: invokevirtual 164	com/google/android/gms/measurement/internal/zzar:zzg	(Ljava/lang/String;Ljava/lang/Object;)V
    //   484: aload 12
    //   486: astore 11
    //   488: aload_2
    //   489: astore 9
    //   491: aload_0
    //   492: iconst_1
    //   493: putfield 36	com/google/android/gms/measurement/internal/zzal:zzalr	Z
    //   496: aload 12
    //   498: ifnull +10 -> 508
    //   501: aload 12
    //   503: invokeinterface 155 1 0
    //   508: iload 4
    //   510: istore_1
    //   511: aload_2
    //   512: ifnull +10 -> 522
    //   515: aload_2
    //   516: invokevirtual 80	android/database/sqlite/SQLiteDatabase:close	()V
    //   519: iload 4
    //   521: istore_1
    //   522: iload_3
    //   523: iconst_1
    //   524: iadd
    //   525: istore_3
    //   526: iload_1
    //   527: istore 4
    //   529: goto -479 -> 50
    //   532: astore 12
    //   534: aload 11
    //   536: astore 10
    //   538: aload 9
    //   540: astore_2
    //   541: aload 12
    //   543: astore 9
    //   545: aload 10
    //   547: ifnull +10 -> 557
    //   550: aload 10
    //   552: invokeinterface 155 1 0
    //   557: aload_2
    //   558: ifnull +7 -> 565
    //   561: aload_2
    //   562: invokevirtual 80	android/database/sqlite/SQLiteDatabase:close	()V
    //   565: aload 9
    //   567: athrow
    //   568: aload_0
    //   569: invokevirtual 105	com/google/android/gms/measurement/internal/zzco:zzgo	()Lcom/google/android/gms/measurement/internal/zzap;
    //   572: invokevirtual 173	com/google/android/gms/measurement/internal/zzap:zzjg	()Lcom/google/android/gms/measurement/internal/zzar;
    //   575: ldc -81
    //   577: invokevirtual 119	com/google/android/gms/measurement/internal/zzar:zzbx	(Ljava/lang/String;)V
    //   580: iconst_0
    //   581: ireturn
    //   582: astore_2
    //   583: goto -183 -> 400
    //   586: astore 9
    //   588: aload 13
    //   590: astore 10
    //   592: goto -186 -> 406
    //   595: astore 9
    //   597: goto -288 -> 309
    //   600: astore 9
    //   602: goto -57 -> 545
    //   605: astore 9
    //   607: goto -504 -> 103
    //   610: astore 9
    //   612: aload 10
    //   614: astore 12
    //   616: aload 9
    //   618: astore 10
    //   620: goto -157 -> 463
    //   623: astore 9
    //   625: goto -80 -> 545
    // Local variable table:
    //   start	length	slot	name	signature
    //   0	628	0	this	zzal
    //   0	628	1	paramInt	int
    //   0	628	2	paramArrayOfByte	byte[]
    //   46	480	3	i	int
    //   48	480	4	j	int
    //   143	276	5	l1	long
    //   123	138	7	l2	long
    //   65	17	9	arrayOfByte1	byte[]
    //   98	1	9	localSQLiteException1	SQLiteException
    //   116	15	9	arrayOfByte2	byte[]
    //   312	16	9	localObject1	Object
    //   332	234	9	localObject2	Object
    //   586	1	9	localSQLiteDatabaseLockedException1	android.database.sqlite.SQLiteDatabaseLockedException
    //   595	1	9	localSQLiteDatabaseLockedException2	android.database.sqlite.SQLiteDatabaseLockedException
    //   600	1	9	localObject3	Object
    //   605	1	9	localSQLiteException2	SQLiteException
    //   610	7	9	localSQLiteFullException1	android.database.sqlite.SQLiteFullException
    //   623	1	9	localObject4	Object
    //   62	40	10	localObject5	Object
    //   106	20	10	localSQLiteFullException2	android.database.sqlite.SQLiteFullException
    //   139	297	10	localObject6	Object
    //   459	21	10	localSQLiteFullException3	android.database.sqlite.SQLiteFullException
    //   536	83	10	localObject7	Object
    //   78	50	11	localObject8	Object
    //   322	9	11	localSQLiteException3	SQLiteException
    //   413	122	11	localObject9	Object
    //   59	443	12	localObject10	Object
    //   532	10	12	localObject11	Object
    //   614	1	12	localObject12	Object
    //   56	533	13	localObject13	Object
    //   24	250	14	localContentValues	android.content.ContentValues
    // Exception table:
    //   from	to	target	type
    //   83	88	98	android/database/sqlite/SQLiteException
    //   118	122	98	android/database/sqlite/SQLiteException
    //   132	141	98	android/database/sqlite/SQLiteException
    //   83	88	106	android/database/sqlite/SQLiteFullException
    //   118	122	106	android/database/sqlite/SQLiteFullException
    //   132	141	106	android/database/sqlite/SQLiteFullException
    //   67	72	312	finally
    //   67	72	322	android/database/sqlite/SQLiteException
    //   67	72	459	android/database/sqlite/SQLiteFullException
    //   83	88	532	finally
    //   118	122	532	finally
    //   132	141	532	finally
    //   418	423	532	finally
    //   470	484	532	finally
    //   491	496	532	finally
    //   67	72	582	android/database/sqlite/SQLiteDatabaseLockedException
    //   83	88	586	android/database/sqlite/SQLiteDatabaseLockedException
    //   118	122	586	android/database/sqlite/SQLiteDatabaseLockedException
    //   132	141	586	android/database/sqlite/SQLiteDatabaseLockedException
    //   154	174	595	android/database/sqlite/SQLiteDatabaseLockedException
    //   186	198	595	android/database/sqlite/SQLiteDatabaseLockedException
    //   208	231	595	android/database/sqlite/SQLiteDatabaseLockedException
    //   239	269	595	android/database/sqlite/SQLiteDatabaseLockedException
    //   269	287	595	android/database/sqlite/SQLiteDatabaseLockedException
    //   154	174	600	finally
    //   186	198	600	finally
    //   208	231	600	finally
    //   239	269	600	finally
    //   269	287	600	finally
    //   154	174	605	android/database/sqlite/SQLiteException
    //   186	198	605	android/database/sqlite/SQLiteException
    //   208	231	605	android/database/sqlite/SQLiteException
    //   239	269	605	android/database/sqlite/SQLiteException
    //   269	287	605	android/database/sqlite/SQLiteException
    //   154	174	610	android/database/sqlite/SQLiteFullException
    //   186	198	610	android/database/sqlite/SQLiteFullException
    //   208	231	610	android/database/sqlite/SQLiteFullException
    //   239	269	610	android/database/sqlite/SQLiteFullException
    //   269	287	610	android/database/sqlite/SQLiteFullException
    //   338	349	623	finally
    //   352	371	623	finally
  }
  
  @WorkerThread
  public final void resetAnalyticsData()
  {
    zzgb();
    zzaf();
    try
    {
      int i = getWritableDatabase().delete("messages", null, null) + 0;
      if (i > 0) {
        zzgo().zzjl().zzg("Reset local analytics data. records", Integer.valueOf(i));
      }
      return;
    }
    catch (SQLiteException localSQLiteException)
    {
      zzgo().zzjd().zzg("Error resetting local analytics data. error", localSQLiteException);
    }
  }
  
  public final boolean zza(zzad paramZzad)
  {
    Parcel localParcel = Parcel.obtain();
    paramZzad.writeToParcel(localParcel, 0);
    paramZzad = localParcel.marshall();
    localParcel.recycle();
    if (paramZzad.length > 131072)
    {
      zzgo().zzjg().zzbx("Event is too long for local database. Sending event directly to service");
      return false;
    }
    return zza(0, paramZzad);
  }
  
  public final boolean zza(zzfh paramZzfh)
  {
    Parcel localParcel = Parcel.obtain();
    paramZzfh.writeToParcel(localParcel, 0);
    paramZzfh = localParcel.marshall();
    localParcel.recycle();
    if (paramZzfh.length > 131072)
    {
      zzgo().zzjg().zzbx("User property too long for local database. Sending directly to service");
      return false;
    }
    return zza(1, paramZzfh);
  }
  
  public final boolean zzc(zzl paramZzl)
  {
    zzgm();
    paramZzl = zzfk.zza(paramZzl);
    if (paramZzl.length > 131072)
    {
      zzgo().zzjg().zzbx("Conditional user property too long for local database. Sending directly to service");
      return false;
    }
    return zza(2, paramZzl);
  }
  
  protected final boolean zzgt()
  {
    return false;
  }
  
  /* Error */
  public final java.util.List<com.google.android.gms.common.internal.safeparcel.AbstractSafeParcelable> zzr(int paramInt)
  {
    // Byte code:
    //   0: aload_0
    //   1: invokevirtual 53	com/google/android/gms/measurement/internal/zzco:zzaf	()V
    //   4: aload_0
    //   5: invokevirtual 50	com/google/android/gms/measurement/internal/zzco:zzgb	()V
    //   8: aload_0
    //   9: getfield 36	com/google/android/gms/measurement/internal/zzal:zzalr	Z
    //   12: ifeq +5 -> 17
    //   15: aconst_null
    //   16: areturn
    //   17: new 300	java/util/ArrayList
    //   20: dup
    //   21: invokespecial 301	java/util/ArrayList:<init>	()V
    //   24: astore 14
    //   26: aload_0
    //   27: invokevirtual 20	com/google/android/gms/measurement/internal/zzco:getContext	()Landroid/content/Context;
    //   30: ldc 22
    //   32: invokevirtual 307	android/content/Context:getDatabasePath	(Ljava/lang/String;)Ljava/io/File;
    //   35: invokevirtual 312	java/io/File:exists	()Z
    //   38: ifne +6 -> 44
    //   41: aload 14
    //   43: areturn
    //   44: iconst_0
    //   45: istore_1
    //   46: iconst_5
    //   47: istore_2
    //   48: aconst_null
    //   49: astore 12
    //   51: aconst_null
    //   52: astore 8
    //   54: iload_1
    //   55: iconst_5
    //   56: if_icmpge +1232 -> 1288
    //   59: aload_0
    //   60: invokespecial 75	com/google/android/gms/measurement/internal/zzal:getWritableDatabase	()Landroid/database/sqlite/SQLiteDatabase;
    //   63: astore 10
    //   65: aload 10
    //   67: astore 9
    //   69: aload 9
    //   71: ifnonnull +44 -> 115
    //   74: aload 9
    //   76: astore 11
    //   78: aload_0
    //   79: iconst_1
    //   80: putfield 36	com/google/android/gms/measurement/internal/zzal:zzalr	Z
    //   83: aload 9
    //   85: ifnull +8 -> 93
    //   88: aload 9
    //   90: invokevirtual 80	android/database/sqlite/SQLiteDatabase:close	()V
    //   93: aconst_null
    //   94: areturn
    //   95: astore 13
    //   97: aconst_null
    //   98: astore 10
    //   100: aload 9
    //   102: astore 8
    //   104: goto +906 -> 1010
    //   107: goto +838 -> 945
    //   110: astore 10
    //   112: goto +1070 -> 1182
    //   115: aload 9
    //   117: invokevirtual 83	android/database/sqlite/SQLiteDatabase:beginTransaction	()V
    //   120: bipush 100
    //   122: invokestatic 315	java/lang/Integer:toString	(I)Ljava/lang/String;
    //   125: astore 11
    //   127: aload 9
    //   129: astore 8
    //   131: aload 9
    //   133: ldc 121
    //   135: iconst_3
    //   136: anewarray 125	java/lang/String
    //   139: dup
    //   140: iconst_0
    //   141: ldc_w 317
    //   144: aastore
    //   145: dup
    //   146: iconst_1
    //   147: ldc 59
    //   149: aastore
    //   150: dup
    //   151: iconst_2
    //   152: ldc 71
    //   154: aastore
    //   155: aconst_null
    //   156: aconst_null
    //   157: aconst_null
    //   158: aconst_null
    //   159: ldc_w 319
    //   162: aload 11
    //   164: invokevirtual 323	android/database/sqlite/SQLiteDatabase:query	(Ljava/lang/String;[Ljava/lang/String;Ljava/lang/String;[Ljava/lang/String;Ljava/lang/String;Ljava/lang/String;Ljava/lang/String;Ljava/lang/String;)Landroid/database/Cursor;
    //   167: astore 9
    //   169: ldc2_w 324
    //   172: lstore 4
    //   174: aload 8
    //   176: astore 12
    //   178: aload 9
    //   180: astore 11
    //   182: aload 9
    //   184: invokeinterface 328 1 0
    //   189: ifeq +558 -> 747
    //   192: aload 8
    //   194: astore 12
    //   196: aload 9
    //   198: astore 11
    //   200: aload 9
    //   202: iconst_0
    //   203: invokeinterface 99 2 0
    //   208: lstore 6
    //   210: aload 8
    //   212: astore 12
    //   214: aload 9
    //   216: astore 11
    //   218: aload 9
    //   220: iconst_1
    //   221: invokeinterface 332 2 0
    //   226: istore_3
    //   227: aload 8
    //   229: astore 12
    //   231: aload 9
    //   233: astore 11
    //   235: aload 9
    //   237: iconst_2
    //   238: invokeinterface 336 2 0
    //   243: astore 15
    //   245: iload_3
    //   246: ifne +157 -> 403
    //   249: aload 8
    //   251: astore 12
    //   253: aload 9
    //   255: astore 11
    //   257: invokestatic 191	android/os/Parcel:obtain	()Landroid/os/Parcel;
    //   260: astore 10
    //   262: aload 10
    //   264: aload 15
    //   266: iconst_0
    //   267: aload 15
    //   269: arraylength
    //   270: invokevirtual 340	android/os/Parcel:unmarshall	([BII)V
    //   273: aload 10
    //   275: iconst_0
    //   276: invokevirtual 344	android/os/Parcel:setDataPosition	(I)V
    //   279: getstatic 348	com/google/android/gms/measurement/internal/zzad:CREATOR	Landroid/os/Parcelable$Creator;
    //   282: aload 10
    //   284: invokeinterface 354 2 0
    //   289: checkcast 193	com/google/android/gms/measurement/internal/zzad
    //   292: astore 13
    //   294: aload 8
    //   296: astore 12
    //   298: aload 9
    //   300: astore 11
    //   302: aload 10
    //   304: invokevirtual 204	android/os/Parcel:recycle	()V
    //   307: lload 6
    //   309: lstore 4
    //   311: aload 13
    //   313: ifnull -139 -> 174
    //   316: aload 8
    //   318: astore 12
    //   320: aload 9
    //   322: astore 11
    //   324: aload 14
    //   326: aload 13
    //   328: invokeinterface 360 2 0
    //   333: pop
    //   334: lload 6
    //   336: lstore 4
    //   338: goto -164 -> 174
    //   341: astore 13
    //   343: goto +36 -> 379
    //   346: aload_0
    //   347: invokevirtual 105	com/google/android/gms/measurement/internal/zzco:zzgo	()Lcom/google/android/gms/measurement/internal/zzap;
    //   350: invokevirtual 111	com/google/android/gms/measurement/internal/zzap:zzjd	()Lcom/google/android/gms/measurement/internal/zzar;
    //   353: ldc_w 362
    //   356: invokevirtual 119	com/google/android/gms/measurement/internal/zzar:zzbx	(Ljava/lang/String;)V
    //   359: aload 8
    //   361: astore 12
    //   363: aload 9
    //   365: astore 11
    //   367: aload 10
    //   369: invokevirtual 204	android/os/Parcel:recycle	()V
    //   372: lload 6
    //   374: lstore 4
    //   376: goto -202 -> 174
    //   379: aload 8
    //   381: astore 12
    //   383: aload 9
    //   385: astore 11
    //   387: aload 10
    //   389: invokevirtual 204	android/os/Parcel:recycle	()V
    //   392: aload 8
    //   394: astore 12
    //   396: aload 9
    //   398: astore 11
    //   400: aload 13
    //   402: athrow
    //   403: iload_3
    //   404: iconst_1
    //   405: if_icmpne +156 -> 561
    //   408: aload 8
    //   410: astore 12
    //   412: aload 9
    //   414: astore 11
    //   416: invokestatic 191	android/os/Parcel:obtain	()Landroid/os/Parcel;
    //   419: astore 13
    //   421: aload 13
    //   423: aload 15
    //   425: iconst_0
    //   426: aload 15
    //   428: arraylength
    //   429: invokevirtual 340	android/os/Parcel:unmarshall	([BII)V
    //   432: aload 13
    //   434: iconst_0
    //   435: invokevirtual 344	android/os/Parcel:setDataPosition	(I)V
    //   438: getstatic 363	com/google/android/gms/measurement/internal/zzfh:CREATOR	Landroid/os/Parcelable$Creator;
    //   441: aload 13
    //   443: invokeinterface 354 2 0
    //   448: checkcast 212	com/google/android/gms/measurement/internal/zzfh
    //   451: astore 10
    //   453: aload 8
    //   455: astore 12
    //   457: aload 9
    //   459: astore 11
    //   461: aload 13
    //   463: invokevirtual 204	android/os/Parcel:recycle	()V
    //   466: goto +37 -> 503
    //   469: astore 10
    //   471: goto +66 -> 537
    //   474: aload_0
    //   475: invokevirtual 105	com/google/android/gms/measurement/internal/zzco:zzgo	()Lcom/google/android/gms/measurement/internal/zzap;
    //   478: invokevirtual 111	com/google/android/gms/measurement/internal/zzap:zzjd	()Lcom/google/android/gms/measurement/internal/zzar;
    //   481: ldc_w 365
    //   484: invokevirtual 119	com/google/android/gms/measurement/internal/zzar:zzbx	(Ljava/lang/String;)V
    //   487: aload 8
    //   489: astore 12
    //   491: aload 9
    //   493: astore 11
    //   495: aload 13
    //   497: invokevirtual 204	android/os/Parcel:recycle	()V
    //   500: aconst_null
    //   501: astore 10
    //   503: lload 6
    //   505: lstore 4
    //   507: aload 10
    //   509: ifnull -335 -> 174
    //   512: aload 8
    //   514: astore 12
    //   516: aload 9
    //   518: astore 11
    //   520: aload 14
    //   522: aload 10
    //   524: invokeinterface 360 2 0
    //   529: pop
    //   530: lload 6
    //   532: lstore 4
    //   534: goto -360 -> 174
    //   537: aload 8
    //   539: astore 12
    //   541: aload 9
    //   543: astore 11
    //   545: aload 13
    //   547: invokevirtual 204	android/os/Parcel:recycle	()V
    //   550: aload 8
    //   552: astore 12
    //   554: aload 9
    //   556: astore 11
    //   558: aload 10
    //   560: athrow
    //   561: iload_3
    //   562: iconst_2
    //   563: if_icmpne +156 -> 719
    //   566: aload 8
    //   568: astore 12
    //   570: aload 9
    //   572: astore 11
    //   574: invokestatic 191	android/os/Parcel:obtain	()Landroid/os/Parcel;
    //   577: astore 13
    //   579: aload 13
    //   581: aload 15
    //   583: iconst_0
    //   584: aload 15
    //   586: arraylength
    //   587: invokevirtual 340	android/os/Parcel:unmarshall	([BII)V
    //   590: aload 13
    //   592: iconst_0
    //   593: invokevirtual 344	android/os/Parcel:setDataPosition	(I)V
    //   596: getstatic 368	com/google/android/gms/measurement/internal/zzl:CREATOR	Landroid/os/Parcelable$Creator;
    //   599: aload 13
    //   601: invokeinterface 354 2 0
    //   606: checkcast 367	com/google/android/gms/measurement/internal/zzl
    //   609: astore 10
    //   611: aload 8
    //   613: astore 12
    //   615: aload 9
    //   617: astore 11
    //   619: aload 13
    //   621: invokevirtual 204	android/os/Parcel:recycle	()V
    //   624: goto +37 -> 661
    //   627: astore 10
    //   629: goto +66 -> 695
    //   632: aload_0
    //   633: invokevirtual 105	com/google/android/gms/measurement/internal/zzco:zzgo	()Lcom/google/android/gms/measurement/internal/zzap;
    //   636: invokevirtual 111	com/google/android/gms/measurement/internal/zzap:zzjd	()Lcom/google/android/gms/measurement/internal/zzar;
    //   639: ldc_w 365
    //   642: invokevirtual 119	com/google/android/gms/measurement/internal/zzar:zzbx	(Ljava/lang/String;)V
    //   645: aload 8
    //   647: astore 12
    //   649: aload 9
    //   651: astore 11
    //   653: aload 13
    //   655: invokevirtual 204	android/os/Parcel:recycle	()V
    //   658: aconst_null
    //   659: astore 10
    //   661: lload 6
    //   663: lstore 4
    //   665: aload 10
    //   667: ifnull -493 -> 174
    //   670: aload 8
    //   672: astore 12
    //   674: aload 9
    //   676: astore 11
    //   678: aload 14
    //   680: aload 10
    //   682: invokeinterface 360 2 0
    //   687: pop
    //   688: lload 6
    //   690: lstore 4
    //   692: goto -518 -> 174
    //   695: aload 8
    //   697: astore 12
    //   699: aload 9
    //   701: astore 11
    //   703: aload 13
    //   705: invokevirtual 204	android/os/Parcel:recycle	()V
    //   708: aload 8
    //   710: astore 12
    //   712: aload 9
    //   714: astore 11
    //   716: aload 10
    //   718: athrow
    //   719: aload 8
    //   721: astore 12
    //   723: aload 9
    //   725: astore 11
    //   727: aload_0
    //   728: invokevirtual 105	com/google/android/gms/measurement/internal/zzco:zzgo	()Lcom/google/android/gms/measurement/internal/zzap;
    //   731: invokevirtual 111	com/google/android/gms/measurement/internal/zzap:zzjd	()Lcom/google/android/gms/measurement/internal/zzar;
    //   734: ldc_w 370
    //   737: invokevirtual 119	com/google/android/gms/measurement/internal/zzar:zzbx	(Ljava/lang/String;)V
    //   740: lload 6
    //   742: lstore 4
    //   744: goto -570 -> 174
    //   747: aload 8
    //   749: astore 12
    //   751: aload 9
    //   753: astore 11
    //   755: aload 8
    //   757: ldc 121
    //   759: ldc_w 372
    //   762: iconst_1
    //   763: anewarray 125	java/lang/String
    //   766: dup
    //   767: iconst_0
    //   768: lload 4
    //   770: invokestatic 131	java/lang/Long:toString	(J)Ljava/lang/String;
    //   773: aastore
    //   774: invokevirtual 135	android/database/sqlite/SQLiteDatabase:delete	(Ljava/lang/String;Ljava/lang/String;[Ljava/lang/String;)I
    //   777: aload 14
    //   779: invokeinterface 376 1 0
    //   784: if_icmpge +24 -> 808
    //   787: aload 8
    //   789: astore 12
    //   791: aload 9
    //   793: astore 11
    //   795: aload_0
    //   796: invokevirtual 105	com/google/android/gms/measurement/internal/zzco:zzgo	()Lcom/google/android/gms/measurement/internal/zzap;
    //   799: invokevirtual 111	com/google/android/gms/measurement/internal/zzap:zzjd	()Lcom/google/android/gms/measurement/internal/zzar;
    //   802: ldc_w 378
    //   805: invokevirtual 119	com/google/android/gms/measurement/internal/zzar:zzbx	(Ljava/lang/String;)V
    //   808: aload 8
    //   810: astore 12
    //   812: aload 9
    //   814: astore 11
    //   816: aload 8
    //   818: invokevirtual 151	android/database/sqlite/SQLiteDatabase:setTransactionSuccessful	()V
    //   821: aload 8
    //   823: astore 12
    //   825: aload 9
    //   827: astore 11
    //   829: aload 8
    //   831: invokevirtual 154	android/database/sqlite/SQLiteDatabase:endTransaction	()V
    //   834: aload 9
    //   836: ifnull +10 -> 846
    //   839: aload 9
    //   841: invokeinterface 155 1 0
    //   846: aload 8
    //   848: ifnull +8 -> 856
    //   851: aload 8
    //   853: invokevirtual 80	android/database/sqlite/SQLiteDatabase:close	()V
    //   856: aload 14
    //   858: areturn
    //   859: astore 13
    //   861: aload 9
    //   863: astore 10
    //   865: goto +145 -> 1010
    //   868: aload 8
    //   870: astore 10
    //   872: aload 9
    //   874: astore 8
    //   876: aload 10
    //   878: astore 9
    //   880: goto +238 -> 1118
    //   883: astore 10
    //   885: aload 8
    //   887: astore 11
    //   889: aload 9
    //   891: astore 8
    //   893: aload 11
    //   895: astore 9
    //   897: goto +285 -> 1182
    //   900: astore 9
    //   902: aload 8
    //   904: astore 10
    //   906: goto +74 -> 980
    //   909: astore 9
    //   911: goto +92 -> 1003
    //   914: astore 8
    //   916: goto +41 -> 957
    //   919: astore 8
    //   921: aload 9
    //   923: astore 10
    //   925: aload 8
    //   927: astore 9
    //   929: goto +51 -> 980
    //   932: astore 10
    //   934: aload 9
    //   936: astore 8
    //   938: aload 10
    //   940: astore 9
    //   942: goto +61 -> 1003
    //   945: aload 10
    //   947: astore 9
    //   949: aconst_null
    //   950: astore 8
    //   952: goto +166 -> 1118
    //   955: astore 8
    //   957: aload 10
    //   959: astore 9
    //   961: aconst_null
    //   962: astore 11
    //   964: aload 8
    //   966: astore 10
    //   968: aload 11
    //   970: astore 8
    //   972: goto +210 -> 1182
    //   975: astore 9
    //   977: aconst_null
    //   978: astore 10
    //   980: aconst_null
    //   981: astore 11
    //   983: aload 9
    //   985: astore 8
    //   987: aload 10
    //   989: astore 9
    //   991: aload 11
    //   993: astore 10
    //   995: goto +268 -> 1263
    //   998: astore 9
    //   1000: aconst_null
    //   1001: astore 8
    //   1003: aconst_null
    //   1004: astore 10
    //   1006: aload 9
    //   1008: astore 13
    //   1010: aload 8
    //   1012: ifnull +35 -> 1047
    //   1015: aload 8
    //   1017: astore 12
    //   1019: aload 10
    //   1021: astore 11
    //   1023: aload 8
    //   1025: invokevirtual 158	android/database/sqlite/SQLiteDatabase:inTransaction	()Z
    //   1028: ifeq +19 -> 1047
    //   1031: aload 8
    //   1033: astore 12
    //   1035: aload 10
    //   1037: astore 11
    //   1039: aload 8
    //   1041: invokevirtual 154	android/database/sqlite/SQLiteDatabase:endTransaction	()V
    //   1044: goto +3 -> 1047
    //   1047: aload 8
    //   1049: astore 12
    //   1051: aload 10
    //   1053: astore 11
    //   1055: aload_0
    //   1056: invokevirtual 105	com/google/android/gms/measurement/internal/zzco:zzgo	()Lcom/google/android/gms/measurement/internal/zzap;
    //   1059: invokevirtual 111	com/google/android/gms/measurement/internal/zzap:zzjd	()Lcom/google/android/gms/measurement/internal/zzar;
    //   1062: ldc_w 380
    //   1065: aload 13
    //   1067: invokevirtual 164	com/google/android/gms/measurement/internal/zzar:zzg	(Ljava/lang/String;Ljava/lang/Object;)V
    //   1070: aload 8
    //   1072: astore 12
    //   1074: aload 10
    //   1076: astore 11
    //   1078: aload_0
    //   1079: iconst_1
    //   1080: putfield 36	com/google/android/gms/measurement/internal/zzal:zzalr	Z
    //   1083: aload 10
    //   1085: ifnull +10 -> 1095
    //   1088: aload 10
    //   1090: invokeinterface 155 1 0
    //   1095: iload_2
    //   1096: istore_3
    //   1097: aload 8
    //   1099: ifnull +145 -> 1244
    //   1102: aload 8
    //   1104: invokevirtual 80	android/database/sqlite/SQLiteDatabase:close	()V
    //   1107: iload_2
    //   1108: istore_3
    //   1109: goto +135 -> 1244
    //   1112: aconst_null
    //   1113: astore 8
    //   1115: aconst_null
    //   1116: astore 9
    //   1118: iload_2
    //   1119: i2l
    //   1120: lstore 4
    //   1122: lload 4
    //   1124: invokestatic 170	android/os/SystemClock:sleep	(J)V
    //   1127: iload_2
    //   1128: bipush 20
    //   1130: iadd
    //   1131: istore_2
    //   1132: aload 8
    //   1134: ifnull +10 -> 1144
    //   1137: aload 8
    //   1139: invokeinterface 155 1 0
    //   1144: iload_2
    //   1145: istore_3
    //   1146: aload 9
    //   1148: ifnull +96 -> 1244
    //   1151: aload 9
    //   1153: invokevirtual 80	android/database/sqlite/SQLiteDatabase:close	()V
    //   1156: iload_2
    //   1157: istore_3
    //   1158: goto +86 -> 1244
    //   1161: astore 11
    //   1163: aload 8
    //   1165: astore 10
    //   1167: aload 11
    //   1169: astore 8
    //   1171: goto +92 -> 1263
    //   1174: astore 10
    //   1176: aconst_null
    //   1177: astore 8
    //   1179: aconst_null
    //   1180: astore 9
    //   1182: aload 8
    //   1184: astore 12
    //   1186: aload 9
    //   1188: astore 11
    //   1190: aload_0
    //   1191: invokevirtual 105	com/google/android/gms/measurement/internal/zzco:zzgo	()Lcom/google/android/gms/measurement/internal/zzap;
    //   1194: invokevirtual 111	com/google/android/gms/measurement/internal/zzap:zzjd	()Lcom/google/android/gms/measurement/internal/zzar;
    //   1197: ldc_w 380
    //   1200: aload 10
    //   1202: invokevirtual 164	com/google/android/gms/measurement/internal/zzar:zzg	(Ljava/lang/String;Ljava/lang/Object;)V
    //   1205: aload 8
    //   1207: astore 12
    //   1209: aload 9
    //   1211: astore 11
    //   1213: aload_0
    //   1214: iconst_1
    //   1215: putfield 36	com/google/android/gms/measurement/internal/zzal:zzalr	Z
    //   1218: aload 8
    //   1220: ifnull +10 -> 1230
    //   1223: aload 8
    //   1225: invokeinterface 155 1 0
    //   1230: iload_2
    //   1231: istore_3
    //   1232: aload 9
    //   1234: ifnull +10 -> 1244
    //   1237: aload 9
    //   1239: invokevirtual 80	android/database/sqlite/SQLiteDatabase:close	()V
    //   1242: iload_2
    //   1243: istore_3
    //   1244: iload_1
    //   1245: iconst_1
    //   1246: iadd
    //   1247: istore_1
    //   1248: iload_3
    //   1249: istore_2
    //   1250: goto -1202 -> 48
    //   1253: astore 8
    //   1255: aload 12
    //   1257: astore 10
    //   1259: aload 11
    //   1261: astore 9
    //   1263: aload 10
    //   1265: ifnull +10 -> 1275
    //   1268: aload 10
    //   1270: invokeinterface 155 1 0
    //   1275: aload 9
    //   1277: ifnull +8 -> 1285
    //   1280: aload 9
    //   1282: invokevirtual 80	android/database/sqlite/SQLiteDatabase:close	()V
    //   1285: aload 8
    //   1287: athrow
    //   1288: aload_0
    //   1289: invokevirtual 105	com/google/android/gms/measurement/internal/zzco:zzgo	()Lcom/google/android/gms/measurement/internal/zzap;
    //   1292: invokevirtual 173	com/google/android/gms/measurement/internal/zzap:zzjg	()Lcom/google/android/gms/measurement/internal/zzar;
    //   1295: ldc_w 382
    //   1298: invokevirtual 119	com/google/android/gms/measurement/internal/zzar:zzbx	(Ljava/lang/String;)V
    //   1301: aconst_null
    //   1302: areturn
    //   1303: astore 8
    //   1305: goto -193 -> 1112
    //   1308: astore 8
    //   1310: goto -1203 -> 107
    //   1313: astore 8
    //   1315: goto -370 -> 945
    //   1318: astore 10
    //   1320: goto -452 -> 868
    //   1323: astore 11
    //   1325: goto -979 -> 346
    //   1328: astore 10
    //   1330: goto -856 -> 474
    //   1333: astore 10
    //   1335: goto -703 -> 632
    //   1338: astore 8
    //   1340: aload 12
    //   1342: astore 9
    //   1344: aload 11
    //   1346: astore 10
    //   1348: goto -85 -> 1263
    // Local variable table:
    //   start	length	slot	name	signature
    //   0	1351	0	this	zzal
    //   0	1351	1	paramInt	int
    //   47	1203	2	i	int
    //   226	1023	3	j	int
    //   172	951	4	l1	long
    //   208	533	6	l2	long
    //   52	851	8	localObject1	Object
    //   914	1	8	localSQLiteFullException1	android.database.sqlite.SQLiteFullException
    //   919	7	8	localObject2	Object
    //   936	15	8	localObject3	Object
    //   955	10	8	localSQLiteFullException2	android.database.sqlite.SQLiteFullException
    //   970	254	8	localObject4	Object
    //   1253	33	8	localObject5	Object
    //   1303	1	8	localSQLiteDatabaseLockedException1	android.database.sqlite.SQLiteDatabaseLockedException
    //   1308	1	8	localSQLiteDatabaseLockedException2	android.database.sqlite.SQLiteDatabaseLockedException
    //   1313	1	8	localSQLiteDatabaseLockedException3	android.database.sqlite.SQLiteDatabaseLockedException
    //   1338	1	8	localObject6	Object
    //   67	829	9	localObject7	Object
    //   900	1	9	localObject8	Object
    //   909	13	9	localSQLiteException1	SQLiteException
    //   927	33	9	localObject9	Object
    //   975	9	9	localObject10	Object
    //   989	1	9	localObject11	Object
    //   998	9	9	localSQLiteException2	SQLiteException
    //   1116	227	9	localObject12	Object
    //   63	36	10	localSQLiteDatabase	SQLiteDatabase
    //   110	1	10	localSQLiteFullException3	android.database.sqlite.SQLiteFullException
    //   260	192	10	localObject13	Object
    //   469	1	10	localObject14	Object
    //   501	109	10	localObject15	Object
    //   627	1	10	localObject16	Object
    //   659	218	10	localObject17	Object
    //   883	1	10	localSQLiteFullException4	android.database.sqlite.SQLiteFullException
    //   904	20	10	localObject18	Object
    //   932	26	10	localSQLiteException3	SQLiteException
    //   966	200	10	localObject19	Object
    //   1174	27	10	localSQLiteFullException5	android.database.sqlite.SQLiteFullException
    //   1257	12	10	localObject20	Object
    //   1318	1	10	localSQLiteDatabaseLockedException4	android.database.sqlite.SQLiteDatabaseLockedException
    //   1328	1	10	localParseException1	com.google.android.gms.common.internal.safeparcel.SafeParcelReader.ParseException
    //   1333	1	10	localParseException2	com.google.android.gms.common.internal.safeparcel.SafeParcelReader.ParseException
    //   1346	1	10	localObject21	Object
    //   76	1001	11	localObject22	Object
    //   1161	7	11	localObject23	Object
    //   1188	72	11	localObject24	Object
    //   1323	22	11	localParseException3	com.google.android.gms.common.internal.safeparcel.SafeParcelReader.ParseException
    //   49	1292	12	localObject25	Object
    //   95	1	13	localSQLiteException4	SQLiteException
    //   292	35	13	localZzad	zzad
    //   341	60	13	localObject26	Object
    //   419	285	13	localParcel	Parcel
    //   859	1	13	localSQLiteException5	SQLiteException
    //   1008	58	13	localSQLiteException6	SQLiteException
    //   24	833	14	localArrayList	java.util.ArrayList
    //   243	342	15	arrayOfByte	byte[]
    // Exception table:
    //   from	to	target	type
    //   78	83	95	android/database/sqlite/SQLiteException
    //   78	83	110	android/database/sqlite/SQLiteFullException
    //   262	294	341	finally
    //   346	359	341	finally
    //   421	453	469	finally
    //   474	487	469	finally
    //   579	611	627	finally
    //   632	645	627	finally
    //   182	192	859	android/database/sqlite/SQLiteException
    //   200	210	859	android/database/sqlite/SQLiteException
    //   218	227	859	android/database/sqlite/SQLiteException
    //   235	245	859	android/database/sqlite/SQLiteException
    //   257	262	859	android/database/sqlite/SQLiteException
    //   302	307	859	android/database/sqlite/SQLiteException
    //   324	334	859	android/database/sqlite/SQLiteException
    //   367	372	859	android/database/sqlite/SQLiteException
    //   387	392	859	android/database/sqlite/SQLiteException
    //   400	403	859	android/database/sqlite/SQLiteException
    //   416	421	859	android/database/sqlite/SQLiteException
    //   461	466	859	android/database/sqlite/SQLiteException
    //   495	500	859	android/database/sqlite/SQLiteException
    //   520	530	859	android/database/sqlite/SQLiteException
    //   545	550	859	android/database/sqlite/SQLiteException
    //   558	561	859	android/database/sqlite/SQLiteException
    //   574	579	859	android/database/sqlite/SQLiteException
    //   619	624	859	android/database/sqlite/SQLiteException
    //   653	658	859	android/database/sqlite/SQLiteException
    //   678	688	859	android/database/sqlite/SQLiteException
    //   703	708	859	android/database/sqlite/SQLiteException
    //   716	719	859	android/database/sqlite/SQLiteException
    //   727	740	859	android/database/sqlite/SQLiteException
    //   755	787	859	android/database/sqlite/SQLiteException
    //   795	808	859	android/database/sqlite/SQLiteException
    //   816	821	859	android/database/sqlite/SQLiteException
    //   829	834	859	android/database/sqlite/SQLiteException
    //   182	192	883	android/database/sqlite/SQLiteFullException
    //   200	210	883	android/database/sqlite/SQLiteFullException
    //   218	227	883	android/database/sqlite/SQLiteFullException
    //   235	245	883	android/database/sqlite/SQLiteFullException
    //   257	262	883	android/database/sqlite/SQLiteFullException
    //   302	307	883	android/database/sqlite/SQLiteFullException
    //   324	334	883	android/database/sqlite/SQLiteFullException
    //   367	372	883	android/database/sqlite/SQLiteFullException
    //   387	392	883	android/database/sqlite/SQLiteFullException
    //   400	403	883	android/database/sqlite/SQLiteFullException
    //   416	421	883	android/database/sqlite/SQLiteFullException
    //   461	466	883	android/database/sqlite/SQLiteFullException
    //   495	500	883	android/database/sqlite/SQLiteFullException
    //   520	530	883	android/database/sqlite/SQLiteFullException
    //   545	550	883	android/database/sqlite/SQLiteFullException
    //   558	561	883	android/database/sqlite/SQLiteFullException
    //   574	579	883	android/database/sqlite/SQLiteFullException
    //   619	624	883	android/database/sqlite/SQLiteFullException
    //   653	658	883	android/database/sqlite/SQLiteFullException
    //   678	688	883	android/database/sqlite/SQLiteFullException
    //   703	708	883	android/database/sqlite/SQLiteFullException
    //   716	719	883	android/database/sqlite/SQLiteFullException
    //   727	740	883	android/database/sqlite/SQLiteFullException
    //   755	787	883	android/database/sqlite/SQLiteFullException
    //   795	808	883	android/database/sqlite/SQLiteFullException
    //   816	821	883	android/database/sqlite/SQLiteFullException
    //   829	834	883	android/database/sqlite/SQLiteFullException
    //   131	169	900	finally
    //   131	169	909	android/database/sqlite/SQLiteException
    //   131	169	914	android/database/sqlite/SQLiteFullException
    //   115	127	919	finally
    //   115	127	932	android/database/sqlite/SQLiteException
    //   115	127	955	android/database/sqlite/SQLiteFullException
    //   59	65	975	finally
    //   59	65	998	android/database/sqlite/SQLiteException
    //   1122	1127	1161	finally
    //   59	65	1174	android/database/sqlite/SQLiteFullException
    //   78	83	1253	finally
    //   1190	1205	1253	finally
    //   1213	1218	1253	finally
    //   59	65	1303	android/database/sqlite/SQLiteDatabaseLockedException
    //   78	83	1308	android/database/sqlite/SQLiteDatabaseLockedException
    //   115	127	1308	android/database/sqlite/SQLiteDatabaseLockedException
    //   131	169	1313	android/database/sqlite/SQLiteDatabaseLockedException
    //   182	192	1318	android/database/sqlite/SQLiteDatabaseLockedException
    //   200	210	1318	android/database/sqlite/SQLiteDatabaseLockedException
    //   218	227	1318	android/database/sqlite/SQLiteDatabaseLockedException
    //   235	245	1318	android/database/sqlite/SQLiteDatabaseLockedException
    //   257	262	1318	android/database/sqlite/SQLiteDatabaseLockedException
    //   302	307	1318	android/database/sqlite/SQLiteDatabaseLockedException
    //   324	334	1318	android/database/sqlite/SQLiteDatabaseLockedException
    //   367	372	1318	android/database/sqlite/SQLiteDatabaseLockedException
    //   387	392	1318	android/database/sqlite/SQLiteDatabaseLockedException
    //   400	403	1318	android/database/sqlite/SQLiteDatabaseLockedException
    //   416	421	1318	android/database/sqlite/SQLiteDatabaseLockedException
    //   461	466	1318	android/database/sqlite/SQLiteDatabaseLockedException
    //   495	500	1318	android/database/sqlite/SQLiteDatabaseLockedException
    //   520	530	1318	android/database/sqlite/SQLiteDatabaseLockedException
    //   545	550	1318	android/database/sqlite/SQLiteDatabaseLockedException
    //   558	561	1318	android/database/sqlite/SQLiteDatabaseLockedException
    //   574	579	1318	android/database/sqlite/SQLiteDatabaseLockedException
    //   619	624	1318	android/database/sqlite/SQLiteDatabaseLockedException
    //   653	658	1318	android/database/sqlite/SQLiteDatabaseLockedException
    //   678	688	1318	android/database/sqlite/SQLiteDatabaseLockedException
    //   703	708	1318	android/database/sqlite/SQLiteDatabaseLockedException
    //   716	719	1318	android/database/sqlite/SQLiteDatabaseLockedException
    //   727	740	1318	android/database/sqlite/SQLiteDatabaseLockedException
    //   755	787	1318	android/database/sqlite/SQLiteDatabaseLockedException
    //   795	808	1318	android/database/sqlite/SQLiteDatabaseLockedException
    //   816	821	1318	android/database/sqlite/SQLiteDatabaseLockedException
    //   829	834	1318	android/database/sqlite/SQLiteDatabaseLockedException
    //   262	294	1323	com/google/android/gms/common/internal/safeparcel/SafeParcelReader$ParseException
    //   421	453	1328	com/google/android/gms/common/internal/safeparcel/SafeParcelReader$ParseException
    //   579	611	1333	com/google/android/gms/common/internal/safeparcel/SafeParcelReader$ParseException
    //   182	192	1338	finally
    //   200	210	1338	finally
    //   218	227	1338	finally
    //   235	245	1338	finally
    //   257	262	1338	finally
    //   302	307	1338	finally
    //   324	334	1338	finally
    //   367	372	1338	finally
    //   387	392	1338	finally
    //   400	403	1338	finally
    //   416	421	1338	finally
    //   461	466	1338	finally
    //   495	500	1338	finally
    //   520	530	1338	finally
    //   545	550	1338	finally
    //   558	561	1338	finally
    //   574	579	1338	finally
    //   619	624	1338	finally
    //   653	658	1338	finally
    //   678	688	1338	finally
    //   703	708	1338	finally
    //   716	719	1338	finally
    //   727	740	1338	finally
    //   755	787	1338	finally
    //   795	808	1338	finally
    //   816	821	1338	finally
    //   829	834	1338	finally
    //   1023	1031	1338	finally
    //   1039	1044	1338	finally
    //   1055	1070	1338	finally
    //   1078	1083	1338	finally
  }
}
