package com.google.android.gms.measurement.internal;

import android.support.annotation.WorkerThread;
import com.google.android.gms.common.internal.Preconditions;
import java.net.URL;
import java.util.Map;

@WorkerThread
final class zzax
  implements Runnable
{
  private final String packageName;
  private final URL url;
  private final byte[] zzamv;
  private final zzav zzamw;
  private final Map<String, String> zzamx;
  
  public zzax(String paramString, URL paramURL, byte[] paramArrayOfByte, Map<String, String> paramMap, zzav paramZzav)
  {
    Preconditions.checkNotEmpty(paramURL);
    Preconditions.checkNotNull(paramArrayOfByte);
    Object localObject;
    Preconditions.checkNotNull(localObject);
    url = paramArrayOfByte;
    zzamv = paramMap;
    zzamw = localObject;
    packageName = paramURL;
    zzamx = paramZzav;
  }
  
  /* Error */
  public final void run()
  {
    // Byte code:
    //   0: aload_0
    //   1: getfield 24	com/google/android/gms/measurement/internal/zzax:zzamy	Lcom/google/android/gms/measurement/internal/zzat;
    //   4: invokevirtual 58	com/google/android/gms/measurement/internal/zzco:zzgc	()V
    //   7: aconst_null
    //   8: astore 4
    //   10: aconst_null
    //   11: astore 5
    //   13: aconst_null
    //   14: astore 6
    //   16: aconst_null
    //   17: astore 7
    //   19: aload_0
    //   20: getfield 24	com/google/android/gms/measurement/internal/zzax:zzamy	Lcom/google/android/gms/measurement/internal/zzat;
    //   23: aload_0
    //   24: getfield 39	com/google/android/gms/measurement/internal/zzax:url	Ljava/net/URL;
    //   27: invokevirtual 64	com/google/android/gms/measurement/internal/zzat:zzb	(Ljava/net/URL;)Ljava/net/HttpURLConnection;
    //   30: astore_2
    //   31: aload_0
    //   32: getfield 47	com/google/android/gms/measurement/internal/zzax:zzamx	Ljava/util/Map;
    //   35: ifnull +65 -> 100
    //   38: aload_0
    //   39: getfield 47	com/google/android/gms/measurement/internal/zzax:zzamx	Ljava/util/Map;
    //   42: invokeinterface 70 1 0
    //   47: invokeinterface 76 1 0
    //   52: astore_3
    //   53: aload_3
    //   54: invokeinterface 82 1 0
    //   59: ifeq +41 -> 100
    //   62: aload_3
    //   63: invokeinterface 86 1 0
    //   68: checkcast 88	java/util/Map$Entry
    //   71: astore 8
    //   73: aload_2
    //   74: aload 8
    //   76: invokeinterface 91 1 0
    //   81: checkcast 93	java/lang/String
    //   84: aload 8
    //   86: invokeinterface 96 1 0
    //   91: checkcast 93	java/lang/String
    //   94: invokevirtual 102	java/net/HttpURLConnection:addRequestProperty	(Ljava/lang/String;Ljava/lang/String;)V
    //   97: goto -44 -> 53
    //   100: aload_0
    //   101: getfield 41	com/google/android/gms/measurement/internal/zzax:zzamv	[B
    //   104: ifnull +98 -> 202
    //   107: aload_0
    //   108: getfield 24	com/google/android/gms/measurement/internal/zzax:zzamy	Lcom/google/android/gms/measurement/internal/zzat;
    //   111: invokevirtual 108	com/google/android/gms/measurement/internal/zzey:zzjo	()Lcom/google/android/gms/measurement/internal/zzfg;
    //   114: aload_0
    //   115: getfield 41	com/google/android/gms/measurement/internal/zzax:zzamv	[B
    //   118: invokevirtual 113	com/google/android/gms/measurement/internal/zzfg:zzb	([B)[B
    //   121: astore 8
    //   123: aload_0
    //   124: getfield 24	com/google/android/gms/measurement/internal/zzax:zzamy	Lcom/google/android/gms/measurement/internal/zzat;
    //   127: invokevirtual 117	com/google/android/gms/measurement/internal/zzco:zzgo	()Lcom/google/android/gms/measurement/internal/zzap;
    //   130: invokevirtual 123	com/google/android/gms/measurement/internal/zzap:zzjl	()Lcom/google/android/gms/measurement/internal/zzar;
    //   133: ldc 125
    //   135: aload 8
    //   137: arraylength
    //   138: invokestatic 131	java/lang/Integer:valueOf	(I)Ljava/lang/Integer;
    //   141: invokevirtual 137	com/google/android/gms/measurement/internal/zzar:zzg	(Ljava/lang/String;Ljava/lang/Object;)V
    //   144: aload_2
    //   145: iconst_1
    //   146: invokevirtual 141	java/net/HttpURLConnection:setDoOutput	(Z)V
    //   149: aload_2
    //   150: ldc -113
    //   152: ldc -111
    //   154: invokevirtual 102	java/net/HttpURLConnection:addRequestProperty	(Ljava/lang/String;Ljava/lang/String;)V
    //   157: aload_2
    //   158: aload 8
    //   160: arraylength
    //   161: invokevirtual 149	java/net/HttpURLConnection:setFixedLengthStreamingMode	(I)V
    //   164: aload_2
    //   165: invokevirtual 152	java/net/HttpURLConnection:connect	()V
    //   168: aload_2
    //   169: invokevirtual 156	java/net/HttpURLConnection:getOutputStream	()Ljava/io/OutputStream;
    //   172: astore_3
    //   173: aload_3
    //   174: aload 8
    //   176: invokevirtual 162	java/io/OutputStream:write	([B)V
    //   179: aload_3
    //   180: invokevirtual 165	java/io/OutputStream:close	()V
    //   183: goto +19 -> 202
    //   186: astore 5
    //   188: aload_2
    //   189: astore 4
    //   191: aload 5
    //   193: astore_2
    //   194: goto +142 -> 336
    //   197: astore 4
    //   199: goto +234 -> 433
    //   202: aload_2
    //   203: invokevirtual 169	java/net/HttpURLConnection:getResponseCode	()I
    //   206: istore_1
    //   207: aload_2
    //   208: invokevirtual 173	java/net/HttpURLConnection:getHeaderFields	()Ljava/util/Map;
    //   211: astore_3
    //   212: aload_0
    //   213: getfield 24	com/google/android/gms/measurement/internal/zzax:zzamy	Lcom/google/android/gms/measurement/internal/zzat;
    //   216: aload_2
    //   217: invokestatic 177	com/google/android/gms/measurement/internal/zzat:zza	(Lcom/google/android/gms/measurement/internal/zzat;Ljava/net/HttpURLConnection;)[B
    //   220: astore 5
    //   222: aload_2
    //   223: ifnull +7 -> 230
    //   226: aload_2
    //   227: invokevirtual 180	java/net/HttpURLConnection:disconnect	()V
    //   230: aload_0
    //   231: getfield 24	com/google/android/gms/measurement/internal/zzax:zzamy	Lcom/google/android/gms/measurement/internal/zzat;
    //   234: invokevirtual 184	com/google/android/gms/measurement/internal/zzco:zzgn	()Lcom/google/android/gms/measurement/internal/zzbo;
    //   237: new 186	com/google/android/gms/measurement/internal/zzaw
    //   240: dup
    //   241: aload_0
    //   242: getfield 45	com/google/android/gms/measurement/internal/zzax:packageName	Ljava/lang/String;
    //   245: aload_0
    //   246: getfield 43	com/google/android/gms/measurement/internal/zzax:zzamw	Lcom/google/android/gms/measurement/internal/zzav;
    //   249: iload_1
    //   250: aconst_null
    //   251: aload 5
    //   253: aload_3
    //   254: aconst_null
    //   255: invokespecial 189	com/google/android/gms/measurement/internal/zzaw:<init>	(Ljava/lang/String;Lcom/google/android/gms/measurement/internal/zzav;ILjava/lang/Throwable;[BLjava/util/Map;Lcom/google/android/gms/measurement/internal/zzau;)V
    //   258: invokevirtual 195	com/google/android/gms/measurement/internal/zzbo:zzc	(Ljava/lang/Runnable;)V
    //   261: return
    //   262: astore 5
    //   264: aload 4
    //   266: astore 6
    //   268: aload_2
    //   269: astore 4
    //   271: aload 5
    //   273: astore_2
    //   274: aload_3
    //   275: astore 5
    //   277: goto +67 -> 344
    //   280: astore 4
    //   282: goto +23 -> 305
    //   285: astore_3
    //   286: aconst_null
    //   287: astore 5
    //   289: aload 4
    //   291: astore 6
    //   293: aload_2
    //   294: astore 4
    //   296: aload_3
    //   297: astore_2
    //   298: goto +46 -> 344
    //   301: astore 4
    //   303: aconst_null
    //   304: astore_3
    //   305: aload_3
    //   306: astore 5
    //   308: goto +133 -> 441
    //   311: astore 5
    //   313: aload 7
    //   315: astore_3
    //   316: aload_2
    //   317: astore 4
    //   319: aload 5
    //   321: astore_2
    //   322: goto +14 -> 336
    //   325: astore_3
    //   326: goto +101 -> 427
    //   329: astore_2
    //   330: aconst_null
    //   331: astore 4
    //   333: aload 7
    //   335: astore_3
    //   336: aconst_null
    //   337: astore 5
    //   339: iconst_0
    //   340: istore_1
    //   341: aload_3
    //   342: astore 6
    //   344: aload 6
    //   346: ifnull +35 -> 381
    //   349: aload 6
    //   351: invokevirtual 165	java/io/OutputStream:close	()V
    //   354: goto +27 -> 381
    //   357: astore_3
    //   358: aload_0
    //   359: getfield 24	com/google/android/gms/measurement/internal/zzax:zzamy	Lcom/google/android/gms/measurement/internal/zzat;
    //   362: invokevirtual 117	com/google/android/gms/measurement/internal/zzco:zzgo	()Lcom/google/android/gms/measurement/internal/zzap;
    //   365: invokevirtual 198	com/google/android/gms/measurement/internal/zzap:zzjd	()Lcom/google/android/gms/measurement/internal/zzar;
    //   368: ldc -56
    //   370: aload_0
    //   371: getfield 45	com/google/android/gms/measurement/internal/zzax:packageName	Ljava/lang/String;
    //   374: invokestatic 204	com/google/android/gms/measurement/internal/zzap:zzbv	(Ljava/lang/String;)Ljava/lang/Object;
    //   377: aload_3
    //   378: invokevirtual 208	com/google/android/gms/measurement/internal/zzar:zze	(Ljava/lang/String;Ljava/lang/Object;Ljava/lang/Object;)V
    //   381: aload 4
    //   383: ifnull +8 -> 391
    //   386: aload 4
    //   388: invokevirtual 180	java/net/HttpURLConnection:disconnect	()V
    //   391: aload_0
    //   392: getfield 24	com/google/android/gms/measurement/internal/zzax:zzamy	Lcom/google/android/gms/measurement/internal/zzat;
    //   395: invokevirtual 184	com/google/android/gms/measurement/internal/zzco:zzgn	()Lcom/google/android/gms/measurement/internal/zzbo;
    //   398: new 186	com/google/android/gms/measurement/internal/zzaw
    //   401: dup
    //   402: aload_0
    //   403: getfield 45	com/google/android/gms/measurement/internal/zzax:packageName	Ljava/lang/String;
    //   406: aload_0
    //   407: getfield 43	com/google/android/gms/measurement/internal/zzax:zzamw	Lcom/google/android/gms/measurement/internal/zzav;
    //   410: iload_1
    //   411: aconst_null
    //   412: aconst_null
    //   413: aload 5
    //   415: aconst_null
    //   416: invokespecial 189	com/google/android/gms/measurement/internal/zzaw:<init>	(Ljava/lang/String;Lcom/google/android/gms/measurement/internal/zzav;ILjava/lang/Throwable;[BLjava/util/Map;Lcom/google/android/gms/measurement/internal/zzau;)V
    //   419: invokevirtual 195	com/google/android/gms/measurement/internal/zzbo:zzc	(Ljava/lang/Runnable;)V
    //   422: aload_2
    //   423: athrow
    //   424: astore_3
    //   425: aconst_null
    //   426: astore_2
    //   427: aload_3
    //   428: astore 4
    //   430: aload 5
    //   432: astore_3
    //   433: aconst_null
    //   434: astore 5
    //   436: iconst_0
    //   437: istore_1
    //   438: aload_3
    //   439: astore 6
    //   441: aload 6
    //   443: ifnull +35 -> 478
    //   446: aload 6
    //   448: invokevirtual 165	java/io/OutputStream:close	()V
    //   451: goto +27 -> 478
    //   454: astore_3
    //   455: aload_0
    //   456: getfield 24	com/google/android/gms/measurement/internal/zzax:zzamy	Lcom/google/android/gms/measurement/internal/zzat;
    //   459: invokevirtual 117	com/google/android/gms/measurement/internal/zzco:zzgo	()Lcom/google/android/gms/measurement/internal/zzap;
    //   462: invokevirtual 198	com/google/android/gms/measurement/internal/zzap:zzjd	()Lcom/google/android/gms/measurement/internal/zzar;
    //   465: ldc -56
    //   467: aload_0
    //   468: getfield 45	com/google/android/gms/measurement/internal/zzax:packageName	Ljava/lang/String;
    //   471: invokestatic 204	com/google/android/gms/measurement/internal/zzap:zzbv	(Ljava/lang/String;)Ljava/lang/Object;
    //   474: aload_3
    //   475: invokevirtual 208	com/google/android/gms/measurement/internal/zzar:zze	(Ljava/lang/String;Ljava/lang/Object;Ljava/lang/Object;)V
    //   478: aload_2
    //   479: ifnull +7 -> 486
    //   482: aload_2
    //   483: invokevirtual 180	java/net/HttpURLConnection:disconnect	()V
    //   486: aload_0
    //   487: getfield 24	com/google/android/gms/measurement/internal/zzax:zzamy	Lcom/google/android/gms/measurement/internal/zzat;
    //   490: invokevirtual 184	com/google/android/gms/measurement/internal/zzco:zzgn	()Lcom/google/android/gms/measurement/internal/zzbo;
    //   493: new 186	com/google/android/gms/measurement/internal/zzaw
    //   496: dup
    //   497: aload_0
    //   498: getfield 45	com/google/android/gms/measurement/internal/zzax:packageName	Ljava/lang/String;
    //   501: aload_0
    //   502: getfield 43	com/google/android/gms/measurement/internal/zzax:zzamw	Lcom/google/android/gms/measurement/internal/zzav;
    //   505: iload_1
    //   506: aload 4
    //   508: aconst_null
    //   509: aload 5
    //   511: aconst_null
    //   512: invokespecial 189	com/google/android/gms/measurement/internal/zzaw:<init>	(Ljava/lang/String;Lcom/google/android/gms/measurement/internal/zzav;ILjava/lang/Throwable;[BLjava/util/Map;Lcom/google/android/gms/measurement/internal/zzau;)V
    //   515: invokevirtual 195	com/google/android/gms/measurement/internal/zzbo:zzc	(Ljava/lang/Runnable;)V
    //   518: return
    // Local variable table:
    //   start	length	slot	name	signature
    //   0	519	0	this	zzax
    //   206	300	1	i	int
    //   30	292	2	localObject1	Object
    //   329	94	2	localObject2	Object
    //   426	57	2	localObject3	Object
    //   52	223	3	localObject4	Object
    //   285	12	3	localObject5	Object
    //   304	12	3	localObject6	Object
    //   325	1	3	localIOException1	java.io.IOException
    //   335	7	3	localObject7	Object
    //   357	21	3	localIOException2	java.io.IOException
    //   424	4	3	localIOException3	java.io.IOException
    //   432	7	3	localMap1	Map
    //   454	21	3	localIOException4	java.io.IOException
    //   8	182	4	localObject8	Object
    //   197	68	4	localIOException5	java.io.IOException
    //   269	1	4	localObject9	Object
    //   280	10	4	localIOException6	java.io.IOException
    //   294	1	4	localObject10	Object
    //   301	1	4	localIOException7	java.io.IOException
    //   317	190	4	localObject11	Object
    //   11	1	5	localObject12	Object
    //   186	6	5	localObject13	Object
    //   220	32	5	arrayOfByte	byte[]
    //   262	10	5	localObject14	Object
    //   275	32	5	localObject15	Object
    //   311	9	5	localObject16	Object
    //   337	173	5	localMap2	Map
    //   14	433	6	localObject17	Object
    //   17	317	7	localObject18	Object
    //   71	104	8	localObject19	Object
    // Exception table:
    //   from	to	target	type
    //   173	183	186	finally
    //   173	183	197	java/io/IOException
    //   212	222	262	finally
    //   212	222	280	java/io/IOException
    //   207	212	285	finally
    //   207	212	301	java/io/IOException
    //   31	53	311	finally
    //   53	97	311	finally
    //   100	173	311	finally
    //   202	207	311	finally
    //   31	53	325	java/io/IOException
    //   53	97	325	java/io/IOException
    //   100	173	325	java/io/IOException
    //   202	207	325	java/io/IOException
    //   19	31	329	finally
    //   349	354	357	java/io/IOException
    //   19	31	424	java/io/IOException
    //   446	451	454	java/io/IOException
  }
}
