package com.google.android.gms.measurement.internal;

import java.util.concurrent.atomic.AtomicReference;

final class zzct
  implements Runnable
{
  zzct(zzcs paramZzcs, AtomicReference paramAtomicReference) {}
  
  /* Error */
  public final void run()
  {
    // Byte code:
    //   0: aload_0
    //   1: getfield 16	com/google/android/gms/measurement/internal/zzct:zzarb	Ljava/util/concurrent/atomic/AtomicReference;
    //   4: astore_1
    //   5: aload_1
    //   6: monitorenter
    //   7: aload_0
    //   8: getfield 16	com/google/android/gms/measurement/internal/zzct:zzarb	Ljava/util/concurrent/atomic/AtomicReference;
    //   11: aload_0
    //   12: getfield 14	com/google/android/gms/measurement/internal/zzct:zzarc	Lcom/google/android/gms/measurement/internal/zzcs;
    //   15: invokevirtual 27	com/google/android/gms/measurement/internal/zzco:zzgq	()Lcom/google/android/gms/measurement/internal/zzn;
    //   18: aload_0
    //   19: getfield 14	com/google/android/gms/measurement/internal/zzct:zzarc	Lcom/google/android/gms/measurement/internal/zzcs;
    //   22: invokevirtual 33	com/google/android/gms/measurement/internal/zze:zzgf	()Lcom/google/android/gms/measurement/internal/zzaj;
    //   25: invokevirtual 39	com/google/android/gms/measurement/internal/zzaj:zzal	()Ljava/lang/String;
    //   28: invokevirtual 45	com/google/android/gms/measurement/internal/zzn:zzba	(Ljava/lang/String;)Z
    //   31: invokestatic 51	java/lang/Boolean:valueOf	(Z)Ljava/lang/Boolean;
    //   34: invokevirtual 57	java/util/concurrent/atomic/AtomicReference:set	(Ljava/lang/Object;)V
    //   37: aload_0
    //   38: getfield 16	com/google/android/gms/measurement/internal/zzct:zzarb	Ljava/util/concurrent/atomic/AtomicReference;
    //   41: invokevirtual 60	java/lang/Object:notify	()V
    //   44: aload_1
    //   45: monitorexit
    //   46: return
    //   47: astore_2
    //   48: aload_0
    //   49: getfield 16	com/google/android/gms/measurement/internal/zzct:zzarb	Ljava/util/concurrent/atomic/AtomicReference;
    //   52: invokevirtual 60	java/lang/Object:notify	()V
    //   55: aload_2
    //   56: athrow
    //   57: astore_2
    //   58: aload_1
    //   59: monitorexit
    //   60: aload_2
    //   61: athrow
    // Local variable table:
    //   start	length	slot	name	signature
    //   0	62	0	this	zzct
    //   4	55	1	localAtomicReference	AtomicReference
    //   47	9	2	localObject1	Object
    //   57	4	2	localObject2	Object
    // Exception table:
    //   from	to	target	type
    //   7	37	47	finally
    //   37	46	57	finally
    //   48	57	57	finally
    //   58	60	57	finally
  }
}
