package com.google.android.android.measurement.internal;

import java.util.concurrent.atomic.AtomicReference;

final class zzdd
  implements Runnable
{
  zzdd(zzcs paramZzcs, AtomicReference paramAtomicReference) {}
  
  /* Error */
  public final void run()
  {
    // Byte code:
    //   0: aload_0
    //   1: getfield 16	com/google/android/android/measurement/internal/zzdd:zzarb	Ljava/util/concurrent/atomic/AtomicReference;
    //   4: astore_1
    //   5: aload_1
    //   6: monitorenter
    //   7: aload_0
    //   8: getfield 16	com/google/android/android/measurement/internal/zzdd:zzarb	Ljava/util/concurrent/atomic/AtomicReference;
    //   11: aload_0
    //   12: getfield 14	com/google/android/android/measurement/internal/zzdd:zzarc	Lcom/google/android/android/measurement/internal/zzcs;
    //   15: invokevirtual 29	com/google/android/android/measurement/internal/zzco:zzgq	()Lcom/google/android/android/measurement/internal/class_3;
    //   18: aload_0
    //   19: getfield 14	com/google/android/android/measurement/internal/zzdd:zzarc	Lcom/google/android/android/measurement/internal/zzcs;
    //   22: invokevirtual 35	com/google/android/android/measurement/internal/class_2:zzgf	()Lcom/google/android/android/measurement/internal/zzaj;
    //   25: invokevirtual 41	com/google/android/android/measurement/internal/zzaj:zzal	()Ljava/lang/String;
    //   28: invokevirtual 47	com/google/android/android/measurement/internal/class_3:zzbb	(Ljava/lang/String;)Ljava/lang/String;
    //   31: invokevirtual 53	java/util/concurrent/atomic/AtomicReference:set	(Ljava/lang/Object;)V
    //   34: aload_0
    //   35: getfield 16	com/google/android/android/measurement/internal/zzdd:zzarb	Ljava/util/concurrent/atomic/AtomicReference;
    //   38: invokevirtual 56	java/lang/Object:notify	()V
    //   41: aload_1
    //   42: monitorexit
    //   43: return
    //   44: astore_2
    //   45: aload_0
    //   46: getfield 16	com/google/android/android/measurement/internal/zzdd:zzarb	Ljava/util/concurrent/atomic/AtomicReference;
    //   49: invokevirtual 56	java/lang/Object:notify	()V
    //   52: aload_2
    //   53: athrow
    //   54: astore_2
    //   55: aload_1
    //   56: monitorexit
    //   57: aload_2
    //   58: athrow
    // Local variable table:
    //   start	length	slot	name	signature
    //   0	59	0	this	zzdd
    //   4	52	1	localAtomicReference	AtomicReference
    //   44	9	2	localThrowable1	Throwable
    //   54	4	2	localThrowable2	Throwable
    // Exception table:
    //   from	to	target	type
    //   7	34	44	java/lang/Throwable
    //   34	43	54	java/lang/Throwable
    //   45	54	54	java/lang/Throwable
    //   55	57	54	java/lang/Throwable
  }
}
