package com.google.android.android.measurement.internal;

import java.util.concurrent.atomic.AtomicReference;

final class zzdf
  implements Runnable
{
  zzdf(zzcs paramZzcs, AtomicReference paramAtomicReference) {}
  
  /* Error */
  public final void run()
  {
    // Byte code:
    //   0: aload_0
    //   1: getfield 16	com/google/android/android/measurement/internal/zzdf:zzarb	Ljava/util/concurrent/atomic/AtomicReference;
    //   4: astore_1
    //   5: aload_1
    //   6: monitorenter
    //   7: aload_0
    //   8: getfield 16	com/google/android/android/measurement/internal/zzdf:zzarb	Ljava/util/concurrent/atomic/AtomicReference;
    //   11: aload_0
    //   12: getfield 14	com/google/android/android/measurement/internal/zzdf:zzarc	Lcom/google/android/android/measurement/internal/zzcs;
    //   15: invokevirtual 29	com/google/android/android/measurement/internal/zzco:zzgq	()Lcom/google/android/android/measurement/internal/class_3;
    //   18: aload_0
    //   19: getfield 14	com/google/android/android/measurement/internal/zzdf:zzarc	Lcom/google/android/android/measurement/internal/zzcs;
    //   22: invokevirtual 35	com/google/android/android/measurement/internal/class_2:zzgf	()Lcom/google/android/android/measurement/internal/zzaj;
    //   25: invokevirtual 41	com/google/android/android/measurement/internal/zzaj:zzal	()Ljava/lang/String;
    //   28: getstatic 47	com/google/android/android/measurement/internal/zzaf:zzakm	Lcom/google/android/android/measurement/internal/zzaf$zza;
    //   31: invokevirtual 53	com/google/android/android/measurement/internal/class_3:parseAndAdd	(Ljava/lang/String;Lcom/google/android/android/measurement/internal/zzaf$zza;)J
    //   34: invokestatic 59	java/lang/Long:valueOf	(J)Ljava/lang/Long;
    //   37: invokevirtual 65	java/util/concurrent/atomic/AtomicReference:set	(Ljava/lang/Object;)V
    //   40: aload_0
    //   41: getfield 16	com/google/android/android/measurement/internal/zzdf:zzarb	Ljava/util/concurrent/atomic/AtomicReference;
    //   44: invokevirtual 68	java/lang/Object:notify	()V
    //   47: aload_1
    //   48: monitorexit
    //   49: return
    //   50: astore_2
    //   51: aload_0
    //   52: getfield 16	com/google/android/android/measurement/internal/zzdf:zzarb	Ljava/util/concurrent/atomic/AtomicReference;
    //   55: invokevirtual 68	java/lang/Object:notify	()V
    //   58: aload_2
    //   59: athrow
    //   60: astore_2
    //   61: aload_1
    //   62: monitorexit
    //   63: aload_2
    //   64: athrow
    // Local variable table:
    //   start	length	slot	name	signature
    //   0	65	0	this	zzdf
    //   4	58	1	localAtomicReference	AtomicReference
    //   50	9	2	localThrowable1	Throwable
    //   60	4	2	localThrowable2	Throwable
    // Exception table:
    //   from	to	target	type
    //   7	40	50	java/lang/Throwable
    //   40	49	60	java/lang/Throwable
    //   51	60	60	java/lang/Throwable
    //   61	63	60	java/lang/Throwable
  }
}
