package com.google.android.gms.measurement.internal;

import java.util.concurrent.atomic.AtomicReference;

final class zzdh
  implements Runnable
{
  zzdh(zzcs paramZzcs, AtomicReference paramAtomicReference) {}
  
  /* Error */
  public final void run()
  {
    // Byte code:
    //   0: aload_0
    //   1: getfield 16	com/google/android/gms/measurement/internal/zzdh:zzarb	Ljava/util/concurrent/atomic/AtomicReference;
    //   4: astore_1
    //   5: aload_1
    //   6: monitorenter
    //   7: aload_0
    //   8: getfield 16	com/google/android/gms/measurement/internal/zzdh:zzarb	Ljava/util/concurrent/atomic/AtomicReference;
    //   11: aload_0
    //   12: getfield 14	com/google/android/gms/measurement/internal/zzdh:zzarc	Lcom/google/android/gms/measurement/internal/zzcs;
    //   15: invokevirtual 27	com/google/android/gms/measurement/internal/zzco:zzgq	()Lcom/google/android/gms/measurement/internal/zzn;
    //   18: aload_0
    //   19: getfield 14	com/google/android/gms/measurement/internal/zzdh:zzarc	Lcom/google/android/gms/measurement/internal/zzcs;
    //   22: invokevirtual 33	com/google/android/gms/measurement/internal/zze:zzgf	()Lcom/google/android/gms/measurement/internal/zzaj;
    //   25: invokevirtual 39	com/google/android/gms/measurement/internal/zzaj:zzal	()Ljava/lang/String;
    //   28: getstatic 45	com/google/android/gms/measurement/internal/zzaf:zzako	Lcom/google/android/gms/measurement/internal/zzaf$zza;
    //   31: invokevirtual 51	com/google/android/gms/measurement/internal/zzn:zzc	(Ljava/lang/String;Lcom/google/android/gms/measurement/internal/zzaf$zza;)D
    //   34: invokestatic 57	java/lang/Double:valueOf	(D)Ljava/lang/Double;
    //   37: invokevirtual 63	java/util/concurrent/atomic/AtomicReference:set	(Ljava/lang/Object;)V
    //   40: aload_0
    //   41: getfield 16	com/google/android/gms/measurement/internal/zzdh:zzarb	Ljava/util/concurrent/atomic/AtomicReference;
    //   44: invokevirtual 66	java/lang/Object:notify	()V
    //   47: aload_1
    //   48: monitorexit
    //   49: return
    //   50: astore_2
    //   51: aload_0
    //   52: getfield 16	com/google/android/gms/measurement/internal/zzdh:zzarb	Ljava/util/concurrent/atomic/AtomicReference;
    //   55: invokevirtual 66	java/lang/Object:notify	()V
    //   58: aload_2
    //   59: athrow
    //   60: astore_2
    //   61: aload_1
    //   62: monitorexit
    //   63: aload_2
    //   64: athrow
    // Local variable table:
    //   start	length	slot	name	signature
    //   0	65	0	this	zzdh
    //   4	58	1	localAtomicReference	AtomicReference
    //   50	9	2	localObject1	Object
    //   60	4	2	localObject2	Object
    // Exception table:
    //   from	to	target	type
    //   7	40	50	finally
    //   40	49	60	finally
    //   51	60	60	finally
    //   61	63	60	finally
  }
}
