package com.google.android.gms.measurement.internal;

import android.content.Context;
import android.content.pm.ApplicationInfo;
import android.content.pm.PackageInfo;
import android.content.pm.PackageManager;
import android.content.pm.PackageManager.NameNotFoundException;
import android.database.sqlite.SQLiteDatabase;
import android.database.sqlite.SQLiteException;
import android.net.Uri;
import android.net.Uri.Builder;
import android.os.Build;
import android.os.Build.VERSION;
import android.os.Bundle;
import android.support.annotation.NonNull;
import android.support.annotation.Size;
import android.support.annotation.WorkerThread;
import android.support.v4.util.ArrayMap;
import android.text.TextUtils;
import android.util.Pair;
import com.google.android.gms.common.internal.Preconditions;
import com.google.android.gms.common.util.Clock;
import com.google.android.gms.common.util.VisibleForTesting;
import com.google.android.gms.common.wrappers.PackageManagerWrapper;
import com.google.android.gms.common.wrappers.Wrappers;
import com.google.android.gms.internal.measurement.zzgd;
import com.google.android.gms.internal.measurement.zzgf;
import com.google.android.gms.internal.measurement.zzgg;
import com.google.android.gms.internal.measurement.zzgh;
import com.google.android.gms.internal.measurement.zzgi;
import com.google.android.gms.internal.measurement.zzgl;
import com.google.android.gms.internal.measurement.zzyy;
import com.google.android.gms.internal.measurement.zzzg;
import java.io.File;
import java.io.FileNotFoundException;
import java.io.IOException;
import java.io.RandomAccessFile;
import java.net.MalformedURLException;
import java.net.URL;
import java.nio.ByteBuffer;
import java.nio.channels.FileChannel;
import java.nio.channels.FileLock;
import java.security.SecureRandom;
import java.util.ArrayList;
import java.util.Arrays;
import java.util.Collections;
import java.util.Iterator;
import java.util.List;
import java.util.Locale;
import java.util.Map;
import java.util.concurrent.ExecutionException;
import java.util.concurrent.Future;
import java.util.concurrent.TimeUnit;
import java.util.concurrent.TimeoutException;

public class zzfa
  implements zzcq
{
  private static volatile zzfa zzatc;
  private final zzbt zzadj;
  private zzbn zzatd;
  private zzat zzate;
  private zzq zzatf;
  private zzay zzatg;
  private zzew zzath;
  private zzj zzati;
  private final zzfg zzatj;
  private boolean zzatk;
  @VisibleForTesting
  private long zzatl;
  private List<Runnable> zzatm;
  private int zzatn;
  private int zzato;
  private boolean zzatp;
  private boolean zzatq;
  private boolean zzatr;
  private FileLock zzats;
  private FileChannel zzatt;
  private List<Long> zzatu;
  private List<Long> zzatv;
  private long zzatw;
  private boolean zzvz = false;
  
  private zzfa(zzff paramZzff)
  {
    this(paramZzff, null);
  }
  
  private zzfa(zzff paramZzff, zzbt paramZzbt)
  {
    Preconditions.checkNotNull(paramZzff);
    zzadj = zzbt.zza(zzri, null);
    zzatw = -1L;
    paramZzbt = new zzfg(this);
    paramZzbt.zzq();
    zzatj = paramZzbt;
    paramZzbt = new zzat(this);
    paramZzbt.zzq();
    zzate = paramZzbt;
    paramZzbt = new zzbn(this);
    paramZzbt.zzq();
    zzatd = paramZzbt;
    zzadj.zzgn().zzc(new zzfb(this, paramZzff));
  }
  
  @WorkerThread
  @VisibleForTesting
  private final int zza(FileChannel paramFileChannel)
  {
    zzaf();
    if ((paramFileChannel != null) && (paramFileChannel.isOpen()))
    {
      ByteBuffer localByteBuffer = ByteBuffer.allocate(4);
      try
      {
        paramFileChannel.position(0L);
        int i = paramFileChannel.read(localByteBuffer);
        if (i != 4)
        {
          if (i == -1) {
            break label114;
          }
          zzadj.zzgo().zzjg().zzg("Unexpected data length. Bytes read", Integer.valueOf(i));
          return 0;
        }
        localByteBuffer.flip();
        i = localByteBuffer.getInt();
        return i;
      }
      catch (IOException paramFileChannel)
      {
        zzadj.zzgo().zzjd().zzg("Failed to read from channel", paramFileChannel);
        return 0;
      }
    }
    zzadj.zzgo().zzjd().zzbx("Bad channel to read from");
    return 0;
    label114:
    return 0;
  }
  
  private final zzh zza(Context paramContext, String paramString1, String paramString2, boolean paramBoolean1, boolean paramBoolean2, boolean paramBoolean3, long paramLong, String paramString3)
  {
    Object localObject2 = "Unknown";
    String str = "Unknown";
    Object localObject1 = paramContext.getPackageManager();
    if (localObject1 == null)
    {
      zzadj.zzgo().zzjd().zzbx("PackageManager is null, can not log app install information");
      return null;
    }
    try
    {
      localObject1 = ((PackageManager)localObject1).getInstallerPackageName(paramString1);
      localObject2 = localObject1;
    }
    catch (IllegalArgumentException localIllegalArgumentException)
    {
      Object localObject3;
      for (;;) {}
    }
    zzadj.zzgo().zzjd().zzg("Error retrieving installer package name. appId", zzap.zzbv(paramString1));
    if (localObject2 == null) {
      localObject1 = "manual_install";
    }
    for (;;)
    {
      break;
      localObject1 = localObject2;
      if ("com.android.vending".equals(localObject2)) {
        localObject1 = "";
      }
    }
    localObject3 = str;
    try
    {
      PackageInfo localPackageInfo = Wrappers.packageManager(paramContext).getPackageInfo(paramString1, 0);
      int i;
      if (localPackageInfo != null)
      {
        localObject3 = str;
        CharSequence localCharSequence = Wrappers.packageManager(paramContext).getApplicationLabel(paramString1);
        localObject2 = str;
        localObject3 = str;
        if (!TextUtils.isEmpty(localCharSequence))
        {
          localObject3 = str;
          localObject2 = localCharSequence.toString();
        }
        localObject3 = localObject2;
        str = versionName;
        localObject3 = localObject2;
        i = versionCode;
        localObject2 = str;
      }
      else
      {
        localObject2 = "Unknown";
        i = Integer.MIN_VALUE;
      }
      zzadj.zzgr();
      if (!zzadj.zzgq().zzbe(paramString1)) {
        paramLong = 0L;
      }
      return new zzh(paramString1, paramString2, (String)localObject2, i, (String)localObject1, zzadj.zzgq().zzhc(), zzadj.zzgm().zzd(paramContext, paramString1), null, paramBoolean1, false, "", 0L, paramLong, 0, paramBoolean2, paramBoolean3, false, paramString3);
    }
    catch (PackageManager.NameNotFoundException paramContext)
    {
      for (;;) {}
    }
    zzadj.zzgo().zzjd().zze("Error retrieving newly installed package info. appId, appName", zzap.zzbv(paramString1), localObject3);
    return null;
  }
  
  private static void zza(zzez paramZzez)
  {
    if (paramZzez != null)
    {
      if (paramZzez.isInitialized()) {
        return;
      }
      paramZzez = String.valueOf(paramZzez.getClass());
      StringBuilder localStringBuilder = new StringBuilder(String.valueOf(paramZzez).length() + 27);
      localStringBuilder.append("Component not initialized: ");
      localStringBuilder.append(paramZzez);
      throw new IllegalStateException(localStringBuilder.toString());
    }
    throw new IllegalStateException("Upload Component not created");
  }
  
  @WorkerThread
  private final void zza(zzff paramZzff)
  {
    zzadj.zzgn().zzaf();
    paramZzff = new zzq(this);
    paramZzff.zzq();
    zzatf = paramZzff;
    zzadj.zzgq().zza(zzatd);
    paramZzff = new zzj(this);
    paramZzff.zzq();
    zzati = paramZzff;
    paramZzff = new zzew(this);
    paramZzff.zzq();
    zzath = paramZzff;
    zzatg = new zzay(this);
    if (zzatn != zzato) {
      zzadj.zzgo().zzjd().zze("Not all upload components initialized", Integer.valueOf(zzatn), Integer.valueOf(zzato));
    }
    zzvz = true;
  }
  
  @WorkerThread
  @VisibleForTesting
  private final boolean zza(int paramInt, FileChannel paramFileChannel)
  {
    zzaf();
    if ((paramFileChannel != null) && (paramFileChannel.isOpen()))
    {
      ByteBuffer localByteBuffer = ByteBuffer.allocate(4);
      localByteBuffer.putInt(paramInt);
      localByteBuffer.flip();
      try
      {
        paramFileChannel.truncate(0L);
        paramFileChannel.write(localByteBuffer);
        paramFileChannel.force(true);
        if (paramFileChannel.size() != 4L) {
          zzadj.zzgo().zzjd().zzg("Error writing to channel. Bytes written", Long.valueOf(paramFileChannel.size()));
        }
        return true;
      }
      catch (IOException paramFileChannel)
      {
        zzadj.zzgo().zzjd().zzg("Failed to write to channel", paramFileChannel);
        return false;
      }
    }
    zzadj.zzgo().zzjd().zzbx("Bad channel to read from");
    return false;
  }
  
  private final boolean zza(String paramString, zzad paramZzad)
  {
    String str = zzaid.getString("currency");
    long l1;
    if ("ecommerce_purchase".equals(name))
    {
      double d2 = zzaid.zzbq("value").doubleValue() * 1000000.0D;
      double d1 = d2;
      if (d2 == 0.0D)
      {
        d1 = zzaid.getLong("value").longValue();
        Double.isNaN(d1);
        d1 *= 1000000.0D;
      }
      if ((d1 <= 9.223372036854776E18D) && (d1 >= -9.223372036854776E18D))
      {
        l1 = Math.round(d1);
      }
      else
      {
        zzadj.zzgo().zzjg().zze("Data lost. Currency value is too big. appId", zzap.zzbv(paramString), Double.valueOf(d1));
        return false;
      }
    }
    else
    {
      l1 = zzaid.getLong("value").longValue();
    }
    if (!TextUtils.isEmpty(str))
    {
      Object localObject = str.toUpperCase(Locale.US);
      if (((String)localObject).matches("[A-Z]{3}"))
      {
        str = String.valueOf("_ltv_");
        localObject = String.valueOf(localObject);
        if (((String)localObject).length() != 0) {}
        for (str = str.concat((String)localObject);; str = new String(str)) {
          break;
        }
        localObject = zzjq().zzi(paramString, str);
        if ((localObject != null) && ((value instanceof Long)))
        {
          long l2 = ((Long)value).longValue();
          paramZzad = new zzfj(paramString, origin, str, zzadj.zzbx().currentTimeMillis(), Long.valueOf(l2 + l1));
        }
        else
        {
          localObject = zzjq();
          int i = zzadj.zzgq().zzb(paramString, zzaf.zzakh);
          Preconditions.checkNotEmpty(paramString);
          ((zzco)localObject).zzaf();
          ((zzez)localObject).zzcl();
          try
          {
            ((zzq)localObject).getWritableDatabase().execSQL("delete from user_attributes where app_id=? and name in (select name from user_attributes where app_id=? and name like '_ltv_%' order by set_timestamp desc limit ?,10);", new String[] { paramString, paramString, String.valueOf(i - 1) });
          }
          catch (SQLiteException localSQLiteException)
          {
            ((zzco)localObject).zzgo().zzjd().zze("Error pruning currencies. appId", zzap.zzbv(paramString), localSQLiteException);
          }
          paramZzad = new zzfj(paramString, origin, str, zzadj.zzbx().currentTimeMillis(), Long.valueOf(l1));
        }
        if (!zzjq().zza(paramZzad))
        {
          zzadj.zzgo().zzjd().zzd("Too many unique user properties are set. Ignoring user property. appId", zzap.zzbv(paramString), zzadj.zzgl().zzbu(name), value);
          zzadj.zzgm().zza(paramString, 9, null, null, 0);
        }
      }
    }
    return true;
  }
  
  private final zzgd[] zza(String paramString, zzgl[] paramArrayOfZzgl, zzgf[] paramArrayOfZzgf)
  {
    Preconditions.checkNotEmpty(paramString);
    return zzjp().zza(paramString, paramArrayOfZzgf, paramArrayOfZzgl);
  }
  
  @VisibleForTesting
  private static zzgg[] zza(zzgg[] paramArrayOfZzgg, int paramInt)
  {
    zzgg[] arrayOfZzgg = new zzgg[paramArrayOfZzgg.length - 1];
    if (paramInt > 0) {
      System.arraycopy(paramArrayOfZzgg, 0, arrayOfZzgg, 0, paramInt);
    }
    if (paramInt < arrayOfZzgg.length) {
      System.arraycopy(paramArrayOfZzgg, paramInt + 1, arrayOfZzgg, paramInt, arrayOfZzgg.length - paramInt);
    }
    return arrayOfZzgg;
  }
  
  @VisibleForTesting
  private static zzgg[] zza(zzgg[] paramArrayOfZzgg, int paramInt, String paramString)
  {
    int i = 0;
    while (i < paramArrayOfZzgg.length)
    {
      if ("_err".equals(name)) {
        return paramArrayOfZzgg;
      }
      i += 1;
    }
    zzgg[] arrayOfZzgg = new zzgg[paramArrayOfZzgg.length + 2];
    System.arraycopy(paramArrayOfZzgg, 0, arrayOfZzgg, 0, paramArrayOfZzgg.length);
    paramArrayOfZzgg = new zzgg();
    name = "_err";
    zzawx = Long.valueOf(paramInt);
    zzgg localZzgg = new zzgg();
    name = "_ev";
    zzamp = paramString;
    arrayOfZzgg[(arrayOfZzgg.length - 2)] = paramArrayOfZzgg;
    arrayOfZzgg[(arrayOfZzgg.length - 1)] = localZzgg;
    return arrayOfZzgg;
  }
  
  @VisibleForTesting
  private static zzgg[] zza(zzgg[] paramArrayOfZzgg, @NonNull String paramString)
  {
    int i = 0;
    while (i < paramArrayOfZzgg.length)
    {
      if (paramString.equals(name)) {
        break label33;
      }
      i += 1;
    }
    i = -1;
    label33:
    if (i < 0) {
      return paramArrayOfZzgg;
    }
    return zza(paramArrayOfZzgg, i);
  }
  
  @WorkerThread
  private final void zzaf()
  {
    zzadj.zzgn().zzaf();
  }
  
  @WorkerThread
  private final void zzb(zzg paramZzg)
  {
    zzaf();
    if ((TextUtils.isEmpty(paramZzg.getGmpAppId())) && ((!zzn.zzic()) || (TextUtils.isEmpty(paramZzg.zzgw()))))
    {
      zzb(paramZzg.zzal(), 204, null, null, null);
      return;
    }
    Object localObject4 = zzadj.zzgq();
    Object localObject5 = new Uri.Builder();
    Object localObject3 = paramZzg.getGmpAppId();
    Object localObject1 = localObject3;
    if (TextUtils.isEmpty((CharSequence)localObject3))
    {
      localObject1 = localObject3;
      if (zzn.zzic()) {
        localObject1 = paramZzg.zzgw();
      }
    }
    localObject3 = ((Uri.Builder)localObject5).scheme((String)zzaf.zzajh.get()).encodedAuthority((String)zzaf.zzaji.get());
    localObject1 = String.valueOf(localObject1);
    if (((String)localObject1).length() != 0) {
      localObject1 = "config/app/".concat((String)localObject1);
    } else {
      localObject1 = new String("config/app/");
    }
    ((Uri.Builder)localObject3).path((String)localObject1).appendQueryParameter("app_instance_id", paramZzg.getAppInstanceId()).appendQueryParameter("platform", "android").appendQueryParameter("gmp_version", String.valueOf(((zzn)localObject4).zzhc()));
    localObject3 = ((Uri.Builder)localObject5).build().toString();
    try
    {
      localObject4 = new URL((String)localObject3);
      zzadj.zzgo().zzjl().zzg("Fetching remote configuration", paramZzg.zzal());
      localObject1 = zzln().zzcf(paramZzg.zzal());
      localObject5 = zzln().zzcg(paramZzg.zzal());
      if ((localObject1 == null) || (TextUtils.isEmpty((CharSequence)localObject5))) {
        break label393;
      }
      localObject1 = new ArrayMap();
      ((Map)localObject1).put("If-Modified-Since", localObject5);
    }
    catch (MalformedURLException localMalformedURLException)
    {
      for (;;)
      {
        String str;
        zzfd localZzfd;
        continue;
        Object localObject2 = null;
      }
    }
    zzatp = true;
    localObject5 = zzlo();
    str = paramZzg.zzal();
    localZzfd = new zzfd(this);
    ((zzco)localObject5).zzaf();
    ((zzez)localObject5).zzcl();
    Preconditions.checkNotNull(localObject4);
    Preconditions.checkNotNull(localZzfd);
    ((zzco)localObject5).zzgn().zzd(new zzax((zzat)localObject5, str, (URL)localObject4, null, (Map)localObject1, localZzfd));
    return;
    zzadj.zzgo().zzjd().zze("Failed to parse config URL. Not fetching. appId", zzap.zzbv(paramZzg.zzal()), localObject3);
  }
  
  @WorkerThread
  private final Boolean zzc(zzg paramZzg)
  {
    try
    {
      if (paramZzg.zzha() != -2147483648L)
      {
        int i = packageManagerzzadj.getContext()).getPackageInfo(paramZzg.zzal(), 0).versionCode;
        if (paramZzg.zzha() == i) {
          return Boolean.valueOf(true);
        }
      }
      else
      {
        String str = packageManagerzzadj.getContext()).getPackageInfo(paramZzg.zzal(), 0).versionName;
        if ((paramZzg.zzak() != null) && (paramZzg.zzak().equals(str))) {
          return Boolean.valueOf(true);
        }
      }
      return Boolean.valueOf(false);
    }
    catch (PackageManager.NameNotFoundException paramZzg)
    {
      for (;;) {}
    }
    return null;
  }
  
  @WorkerThread
  private final zzh zzco(String paramString)
  {
    zzg localZzg = zzjq().zzbl(paramString);
    if ((localZzg != null) && (!TextUtils.isEmpty(localZzg.zzak())))
    {
      Boolean localBoolean = zzc(localZzg);
      if ((localBoolean != null) && (!localBoolean.booleanValue()))
      {
        zzadj.zzgo().zzjd().zzg("App version does not match; dropping. appId", zzap.zzbv(paramString));
        return null;
      }
      return new zzh(paramString, localZzg.getGmpAppId(), localZzg.zzak(), localZzg.zzha(), localZzg.zzhb(), localZzg.zzhc(), localZzg.zzhd(), null, localZzg.isMeasurementEnabled(), false, localZzg.getFirebaseInstanceId(), localZzg.zzhq(), 0L, 0, localZzg.zzhr(), localZzg.zzhs(), false, localZzg.zzgw());
    }
    zzadj.zzgo().zzjk().zzg("No app data available; dropping", paramString);
    return null;
  }
  
  @WorkerThread
  private final void zzd(zzad paramZzad, zzh paramZzh)
  {
    throw new Runtime("d2j fail translate: java.lang.RuntimeException: fail exe a23 = a18\n\tat com.googlecode.dex2jar.ir.ts.an.BaseAnalyze.exec(BaseAnalyze.java:92)\n\tat com.googlecode.dex2jar.ir.ts.an.BaseAnalyze.exec(BaseAnalyze.java:1)\n\tat com.googlecode.dex2jar.ir.ts.Cfg.dfs(Cfg.java:255)\n\tat com.googlecode.dex2jar.ir.ts.an.BaseAnalyze.analyze0(BaseAnalyze.java:75)\n\tat com.googlecode.dex2jar.ir.ts.an.BaseAnalyze.analyze(BaseAnalyze.java:69)\n\tat com.googlecode.dex2jar.ir.ts.UnSSATransformer.transform(UnSSATransformer.java:274)\n\tat com.googlecode.d2j.dex.Dex2jar$2.optimize(Dex2jar.java:163)\n\tat com.googlecode.d2j.dex.Dex2Asm.convertCode(Dex2Asm.java:414)\n\tat com.googlecode.d2j.dex.ExDex2Asm.convertCode(ExDex2Asm.java:42)\n\tat com.googlecode.d2j.dex.Dex2jar$2.convertCode(Dex2jar.java:128)\n\tat com.googlecode.d2j.dex.Dex2Asm.convertMethod(Dex2Asm.java:509)\n\tat com.googlecode.d2j.dex.Dex2Asm.convertClass(Dex2Asm.java:406)\n\tat com.googlecode.d2j.dex.Dex2Asm.convertDex(Dex2Asm.java:422)\n\tat com.googlecode.d2j.dex.Dex2jar.doTranslate(Dex2jar.java:172)\n\tat com.googlecode.d2j.dex.Dex2jar.to(Dex2jar.java:272)\n\tat com.googlecode.dex2jar.tools.Dex2jarCmd.doCommandLine(Dex2jarCmd.java:108)\n\tat com.googlecode.dex2jar.tools.BaseCmd.doMain(BaseCmd.java:288)\n\tat com.googlecode.dex2jar.tools.Dex2jarCmd.main(Dex2jarCmd.java:32)\nCaused by: java.lang.NullPointerException\n\tat com.googlecode.dex2jar.ir.ts.UnSSATransformer$LiveA.onUseLocal(UnSSATransformer.java:552)\n\tat com.googlecode.dex2jar.ir.ts.UnSSATransformer$LiveA.onUseLocal(UnSSATransformer.java:1)\n\tat com.googlecode.dex2jar.ir.ts.an.BaseAnalyze.onUse(BaseAnalyze.java:166)\n\tat com.googlecode.dex2jar.ir.ts.an.BaseAnalyze.onUse(BaseAnalyze.java:1)\n\tat com.googlecode.dex2jar.ir.ts.Cfg.travel(Cfg.java:331)\n\tat com.googlecode.dex2jar.ir.ts.Cfg.travel(Cfg.java:387)\n\tat com.googlecode.dex2jar.ir.ts.an.BaseAnalyze.exec(BaseAnalyze.java:90)\n\t... 17 more\n");
  }
  
  /* Error */
  @WorkerThread
  private final boolean zzd(String paramString, long paramLong)
  {
    // Byte code:
    //   0: aload_0
    //   1: astore 22
    //   3: aload_0
    //   4: invokevirtual 492	com/google/android/gms/measurement/internal/zzfa:zzjq	()Lcom/google/android/gms/measurement/internal/zzq;
    //   7: invokevirtual 797	com/google/android/gms/measurement/internal/zzq:beginTransaction	()V
    //   10: aconst_null
    //   11: astore 17
    //   13: new 8	com/google/android/gms/measurement/internal/zzfa$zza
    //   16: dup
    //   17: aload 22
    //   19: aconst_null
    //   20: invokespecial 800	com/google/android/gms/measurement/internal/zzfa$zza:<init>	(Lcom/google/android/gms/measurement/internal/zzfa;Lcom/google/android/gms/measurement/internal/zzfb;)V
    //   23: astore 19
    //   25: aload_0
    //   26: invokevirtual 492	com/google/android/gms/measurement/internal/zzfa:zzjq	()Lcom/google/android/gms/measurement/internal/zzq;
    //   29: astore 24
    //   31: aload 22
    //   33: getfield 84	com/google/android/gms/measurement/internal/zzfa:zzatw	J
    //   36: lstore 11
    //   38: aload 19
    //   40: invokestatic 67	com/google/android/gms/common/internal/Preconditions:checkNotNull	(Ljava/lang/Object;)Ljava/lang/Object;
    //   43: pop
    //   44: aload 24
    //   46: invokevirtual 349	com/google/android/gms/measurement/internal/zzco:zzaf	()V
    //   49: aload 24
    //   51: invokevirtual 531	com/google/android/gms/measurement/internal/zzez:zzcl	()V
    //   54: aload 24
    //   56: invokevirtual 535	com/google/android/gms/measurement/internal/zzq:getWritableDatabase	()Landroid/database/sqlite/SQLiteDatabase;
    //   59: astore 25
    //   61: aconst_null
    //   62: invokestatic 257	android/text/TextUtils:isEmpty	(Ljava/lang/CharSequence;)Z
    //   65: istore 13
    //   67: iload 13
    //   69: ifeq +267 -> 336
    //   72: lload 11
    //   74: ldc2_w 81
    //   77: lcmp
    //   78: ifeq +67 -> 145
    //   81: aload 17
    //   83: astore_1
    //   84: iconst_2
    //   85: anewarray 229	java/lang/String
    //   88: astore 18
    //   90: aload 17
    //   92: astore_1
    //   93: aload 18
    //   95: iconst_0
    //   96: lload 11
    //   98: invokestatic 671	java/lang/String:valueOf	(J)Ljava/lang/String;
    //   101: aastore
    //   102: aload 17
    //   104: astore_1
    //   105: aload 18
    //   107: iconst_1
    //   108: lload_2
    //   109: invokestatic 671	java/lang/String:valueOf	(J)Ljava/lang/String;
    //   112: aastore
    //   113: aload 18
    //   115: astore_1
    //   116: goto +41 -> 157
    //   119: astore 18
    //   121: aload_1
    //   122: astore 17
    //   124: aload 18
    //   126: astore_1
    //   127: goto +1034 -> 1161
    //   130: astore_1
    //   131: aconst_null
    //   132: astore 17
    //   134: aload 17
    //   136: astore 18
    //   138: aload 17
    //   140: astore 20
    //   142: goto +1029 -> 1171
    //   145: iconst_1
    //   146: anewarray 229	java/lang/String
    //   149: astore_1
    //   150: aload_1
    //   151: iconst_0
    //   152: lload_2
    //   153: invokestatic 671	java/lang/String:valueOf	(J)Ljava/lang/String;
    //   156: aastore
    //   157: lload 11
    //   159: ldc2_w 81
    //   162: lcmp
    //   163: ifeq +11 -> 174
    //   166: ldc_w 802
    //   169: astore 17
    //   171: goto +7 -> 178
    //   174: ldc -21
    //   176: astore 17
    //   178: new 325	java/lang/StringBuilder
    //   181: dup
    //   182: aload 17
    //   184: invokestatic 323	java/lang/String:valueOf	(Ljava/lang/Object;)Ljava/lang/String;
    //   187: invokevirtual 328	java/lang/String:length	()I
    //   190: sipush 148
    //   193: iadd
    //   194: invokespecial 331	java/lang/StringBuilder:<init>	(I)V
    //   197: astore 18
    //   199: aload 18
    //   201: ldc_w 804
    //   204: invokevirtual 337	java/lang/StringBuilder:append	(Ljava/lang/String;)Ljava/lang/StringBuilder;
    //   207: pop
    //   208: aload 18
    //   210: aload 17
    //   212: invokevirtual 337	java/lang/StringBuilder:append	(Ljava/lang/String;)Ljava/lang/StringBuilder;
    //   215: pop
    //   216: aload 18
    //   218: ldc_w 806
    //   221: invokevirtual 337	java/lang/StringBuilder:append	(Ljava/lang/String;)Ljava/lang/StringBuilder;
    //   224: pop
    //   225: aload 25
    //   227: aload 18
    //   229: invokevirtual 340	java/lang/StringBuilder:toString	()Ljava/lang/String;
    //   232: aload_1
    //   233: invokevirtual 810	android/database/sqlite/SQLiteDatabase:rawQuery	(Ljava/lang/String;[Ljava/lang/String;)Landroid/database/Cursor;
    //   236: astore 17
    //   238: aload 17
    //   240: astore_1
    //   241: aload 17
    //   243: astore 18
    //   245: aload 17
    //   247: invokeinterface 815 1 0
    //   252: istore 13
    //   254: iload 13
    //   256: ifne +18 -> 274
    //   259: aload 17
    //   261: ifnull +946 -> 1207
    //   264: aload 17
    //   266: invokeinterface 818 1 0
    //   271: goto +936 -> 1207
    //   274: aload 17
    //   276: astore_1
    //   277: aload 17
    //   279: astore 18
    //   281: aload 17
    //   283: iconst_0
    //   284: invokeinterface 820 2 0
    //   289: astore 20
    //   291: aload 17
    //   293: astore_1
    //   294: aload 17
    //   296: iconst_1
    //   297: invokeinterface 820 2 0
    //   302: astore 18
    //   304: aload 17
    //   306: astore_1
    //   307: aload 17
    //   309: invokeinterface 818 1 0
    //   314: aload 20
    //   316: astore_1
    //   317: aload 18
    //   319: astore 20
    //   321: goto +184 -> 505
    //   324: astore_1
    //   325: aload 17
    //   327: astore 18
    //   329: aload 20
    //   331: astore 17
    //   333: goto -195 -> 138
    //   336: lload 11
    //   338: ldc2_w 81
    //   341: lcmp
    //   342: ifeq +23 -> 365
    //   345: iconst_2
    //   346: anewarray 229	java/lang/String
    //   349: astore_1
    //   350: aload_1
    //   351: iconst_0
    //   352: aconst_null
    //   353: aastore
    //   354: aload_1
    //   355: iconst_1
    //   356: lload 11
    //   358: invokestatic 671	java/lang/String:valueOf	(J)Ljava/lang/String;
    //   361: aastore
    //   362: goto +4844 -> 5206
    //   365: iconst_1
    //   366: anewarray 229	java/lang/String
    //   369: astore_1
    //   370: aload_1
    //   371: iconst_0
    //   372: aconst_null
    //   373: aastore
    //   374: goto +4832 -> 5206
    //   377: new 325	java/lang/StringBuilder
    //   380: dup
    //   381: aload 17
    //   383: invokestatic 323	java/lang/String:valueOf	(Ljava/lang/Object;)Ljava/lang/String;
    //   386: invokevirtual 328	java/lang/String:length	()I
    //   389: bipush 84
    //   391: iadd
    //   392: invokespecial 331	java/lang/StringBuilder:<init>	(I)V
    //   395: astore 18
    //   397: aload 18
    //   399: ldc_w 822
    //   402: invokevirtual 337	java/lang/StringBuilder:append	(Ljava/lang/String;)Ljava/lang/StringBuilder;
    //   405: pop
    //   406: aload 18
    //   408: aload 17
    //   410: invokevirtual 337	java/lang/StringBuilder:append	(Ljava/lang/String;)Ljava/lang/StringBuilder;
    //   413: pop
    //   414: aload 18
    //   416: ldc_w 824
    //   419: invokevirtual 337	java/lang/StringBuilder:append	(Ljava/lang/String;)Ljava/lang/StringBuilder;
    //   422: pop
    //   423: aload 25
    //   425: aload 18
    //   427: invokevirtual 340	java/lang/StringBuilder:toString	()Ljava/lang/String;
    //   430: aload_1
    //   431: invokevirtual 810	android/database/sqlite/SQLiteDatabase:rawQuery	(Ljava/lang/String;[Ljava/lang/String;)Landroid/database/Cursor;
    //   434: astore 17
    //   436: aload 17
    //   438: astore_1
    //   439: aload 17
    //   441: astore 18
    //   443: aload 17
    //   445: invokeinterface 815 1 0
    //   450: istore 13
    //   452: iload 13
    //   454: ifne +18 -> 472
    //   457: aload 17
    //   459: ifnull +748 -> 1207
    //   462: aload 17
    //   464: invokeinterface 818 1 0
    //   469: goto +738 -> 1207
    //   472: aload 17
    //   474: astore_1
    //   475: aload 17
    //   477: astore 18
    //   479: aload 17
    //   481: iconst_0
    //   482: invokeinterface 820 2 0
    //   487: astore 20
    //   489: aload 17
    //   491: astore_1
    //   492: aload 17
    //   494: astore 18
    //   496: aload 17
    //   498: invokeinterface 818 1 0
    //   503: aconst_null
    //   504: astore_1
    //   505: aload 25
    //   507: ldc_w 826
    //   510: iconst_1
    //   511: anewarray 229	java/lang/String
    //   514: dup
    //   515: iconst_0
    //   516: ldc_w 828
    //   519: aastore
    //   520: ldc_w 830
    //   523: iconst_2
    //   524: anewarray 229	java/lang/String
    //   527: dup
    //   528: iconst_0
    //   529: aload_1
    //   530: aastore
    //   531: dup
    //   532: iconst_1
    //   533: aload 20
    //   535: aastore
    //   536: aconst_null
    //   537: aconst_null
    //   538: ldc_w 832
    //   541: ldc_w 834
    //   544: invokevirtual 838	android/database/sqlite/SQLiteDatabase:query	(Ljava/lang/String;[Ljava/lang/String;Ljava/lang/String;[Ljava/lang/String;Ljava/lang/String;Ljava/lang/String;Ljava/lang/String;Ljava/lang/String;)Landroid/database/Cursor;
    //   547: astore 18
    //   549: aload 18
    //   551: astore 17
    //   553: aload 18
    //   555: invokeinterface 815 1 0
    //   560: ifne +40 -> 600
    //   563: aload 18
    //   565: astore 17
    //   567: aload 24
    //   569: invokevirtual 547	com/google/android/gms/measurement/internal/zzco:zzgo	()Lcom/google/android/gms/measurement/internal/zzap;
    //   572: invokevirtual 183	com/google/android/gms/measurement/internal/zzap:zzjd	()Lcom/google/android/gms/measurement/internal/zzar;
    //   575: ldc_w 840
    //   578: aload_1
    //   579: invokestatic 223	com/google/android/gms/measurement/internal/zzap:zzbv	(Ljava/lang/String;)Ljava/lang/Object;
    //   582: invokevirtual 172	com/google/android/gms/measurement/internal/zzar:zzg	(Ljava/lang/String;Ljava/lang/Object;)V
    //   585: aload 18
    //   587: ifnull +620 -> 1207
    //   590: aload 18
    //   592: invokeinterface 818 1 0
    //   597: goto +610 -> 1207
    //   600: aload 18
    //   602: astore 17
    //   604: aload 18
    //   606: iconst_0
    //   607: invokeinterface 844 2 0
    //   612: astore 21
    //   614: aload 18
    //   616: astore 17
    //   618: aload 21
    //   620: iconst_0
    //   621: aload 21
    //   623: arraylength
    //   624: invokestatic 850	com/google/android/gms/internal/measurement/zzyx:zzj	([BII)Lcom/google/android/gms/internal/measurement/zzyx;
    //   627: astore 21
    //   629: aload 18
    //   631: astore 17
    //   633: new 852	com/google/android/gms/internal/measurement/zzgi
    //   636: dup
    //   637: invokespecial 853	com/google/android/gms/internal/measurement/zzgi:<init>	()V
    //   640: astore 23
    //   642: aload 18
    //   644: astore 17
    //   646: aload 23
    //   648: aload 21
    //   650: invokevirtual 858	com/google/android/gms/internal/measurement/zzzg:zza	(Lcom/google/android/gms/internal/measurement/zzyx;)Lcom/google/android/gms/internal/measurement/zzzg;
    //   653: pop
    //   654: aload 18
    //   656: astore 17
    //   658: aload 18
    //   660: invokeinterface 861 1 0
    //   665: ifeq +25 -> 690
    //   668: aload 18
    //   670: astore 17
    //   672: aload 24
    //   674: invokevirtual 547	com/google/android/gms/measurement/internal/zzco:zzgo	()Lcom/google/android/gms/measurement/internal/zzap;
    //   677: invokevirtual 158	com/google/android/gms/measurement/internal/zzap:zzjg	()Lcom/google/android/gms/measurement/internal/zzar;
    //   680: ldc_w 863
    //   683: aload_1
    //   684: invokestatic 223	com/google/android/gms/measurement/internal/zzap:zzbv	(Ljava/lang/String;)Ljava/lang/Object;
    //   687: invokevirtual 172	com/google/android/gms/measurement/internal/zzar:zzg	(Ljava/lang/String;Ljava/lang/Object;)V
    //   690: aload 18
    //   692: astore 17
    //   694: aload 18
    //   696: invokeinterface 818 1 0
    //   701: aload 18
    //   703: astore 17
    //   705: aload 19
    //   707: aload 23
    //   709: invokeinterface 868 2 0
    //   714: lload 11
    //   716: ldc2_w 81
    //   719: lcmp
    //   720: ifeq +46 -> 766
    //   723: ldc_w 870
    //   726: astore 21
    //   728: aload 18
    //   730: astore 17
    //   732: iconst_3
    //   733: anewarray 229	java/lang/String
    //   736: dup
    //   737: iconst_0
    //   738: aload_1
    //   739: aastore
    //   740: dup
    //   741: iconst_1
    //   742: aload 20
    //   744: aastore
    //   745: dup
    //   746: iconst_2
    //   747: lload 11
    //   749: invokestatic 671	java/lang/String:valueOf	(J)Ljava/lang/String;
    //   752: aastore
    //   753: astore 23
    //   755: aload 21
    //   757: astore 20
    //   759: aload 23
    //   761: astore 21
    //   763: goto +31 -> 794
    //   766: ldc_w 830
    //   769: astore 23
    //   771: aload 18
    //   773: astore 17
    //   775: iconst_2
    //   776: anewarray 229	java/lang/String
    //   779: dup
    //   780: iconst_0
    //   781: aload_1
    //   782: aastore
    //   783: dup
    //   784: iconst_1
    //   785: aload 20
    //   787: aastore
    //   788: astore 21
    //   790: aload 23
    //   792: astore 20
    //   794: aload 18
    //   796: astore 17
    //   798: aload 25
    //   800: ldc_w 872
    //   803: iconst_4
    //   804: anewarray 229	java/lang/String
    //   807: dup
    //   808: iconst_0
    //   809: ldc_w 832
    //   812: aastore
    //   813: dup
    //   814: iconst_1
    //   815: ldc_w 873
    //   818: aastore
    //   819: dup
    //   820: iconst_2
    //   821: ldc_w 875
    //   824: aastore
    //   825: dup
    //   826: iconst_3
    //   827: ldc_w 877
    //   830: aastore
    //   831: aload 20
    //   833: aload 21
    //   835: aconst_null
    //   836: aconst_null
    //   837: ldc_w 832
    //   840: aconst_null
    //   841: invokevirtual 838	android/database/sqlite/SQLiteDatabase:query	(Ljava/lang/String;[Ljava/lang/String;Ljava/lang/String;[Ljava/lang/String;Ljava/lang/String;Ljava/lang/String;Ljava/lang/String;Ljava/lang/String;)Landroid/database/Cursor;
    //   844: astore 20
    //   846: aload 20
    //   848: invokeinterface 815 1 0
    //   853: ifne +36 -> 889
    //   856: aload 24
    //   858: invokevirtual 547	com/google/android/gms/measurement/internal/zzco:zzgo	()Lcom/google/android/gms/measurement/internal/zzap;
    //   861: invokevirtual 158	com/google/android/gms/measurement/internal/zzap:zzjg	()Lcom/google/android/gms/measurement/internal/zzar;
    //   864: ldc_w 879
    //   867: aload_1
    //   868: invokestatic 223	com/google/android/gms/measurement/internal/zzap:zzbv	(Ljava/lang/String;)Ljava/lang/Object;
    //   871: invokevirtual 172	com/google/android/gms/measurement/internal/zzar:zzg	(Ljava/lang/String;Ljava/lang/Object;)V
    //   874: aload 20
    //   876: ifnull +331 -> 1207
    //   879: aload 20
    //   881: invokeinterface 818 1 0
    //   886: goto +321 -> 1207
    //   889: aload 20
    //   891: iconst_0
    //   892: invokeinterface 882 2 0
    //   897: lstore_2
    //   898: aload 20
    //   900: iconst_3
    //   901: invokeinterface 844 2 0
    //   906: astore 17
    //   908: aload 17
    //   910: iconst_0
    //   911: aload 17
    //   913: arraylength
    //   914: invokestatic 850	com/google/android/gms/internal/measurement/zzyx:zzj	([BII)Lcom/google/android/gms/internal/measurement/zzyx;
    //   917: astore 17
    //   919: new 884	com/google/android/gms/internal/measurement/zzgf
    //   922: dup
    //   923: invokespecial 885	com/google/android/gms/internal/measurement/zzgf:<init>	()V
    //   926: astore 18
    //   928: aload 18
    //   930: aload 17
    //   932: invokevirtual 858	com/google/android/gms/internal/measurement/zzzg:zza	(Lcom/google/android/gms/internal/measurement/zzyx;)Lcom/google/android/gms/internal/measurement/zzzg;
    //   935: pop
    //   936: aload 18
    //   938: aload 20
    //   940: iconst_1
    //   941: invokeinterface 820 2 0
    //   946: putfield 886	com/google/android/gms/internal/measurement/zzgf:name	Ljava/lang/String;
    //   949: aload 18
    //   951: aload 20
    //   953: iconst_2
    //   954: invokeinterface 882 2 0
    //   959: invokestatic 404	java/lang/Long:valueOf	(J)Ljava/lang/Long;
    //   962: putfield 889	com/google/android/gms/internal/measurement/zzgf:zzawu	Ljava/lang/Long;
    //   965: aload 19
    //   967: lload_2
    //   968: aload 18
    //   970: invokeinterface 892 4 0
    //   975: istore 13
    //   977: iload 13
    //   979: ifne +40 -> 1019
    //   982: aload 20
    //   984: ifnull +223 -> 1207
    //   987: aload 20
    //   989: invokeinterface 818 1 0
    //   994: goto +213 -> 1207
    //   997: astore 17
    //   999: aload 24
    //   1001: invokevirtual 547	com/google/android/gms/measurement/internal/zzco:zzgo	()Lcom/google/android/gms/measurement/internal/zzap;
    //   1004: invokevirtual 183	com/google/android/gms/measurement/internal/zzap:zzjd	()Lcom/google/android/gms/measurement/internal/zzar;
    //   1007: ldc_w 894
    //   1010: aload_1
    //   1011: invokestatic 223	com/google/android/gms/measurement/internal/zzap:zzbv	(Ljava/lang/String;)Ljava/lang/Object;
    //   1014: aload 17
    //   1016: invokevirtual 312	com/google/android/gms/measurement/internal/zzar:zze	(Ljava/lang/String;Ljava/lang/Object;Ljava/lang/Object;)V
    //   1019: aload 20
    //   1021: invokeinterface 861 1 0
    //   1026: istore 13
    //   1028: iload 13
    //   1030: ifne -141 -> 889
    //   1033: aload 20
    //   1035: ifnull +172 -> 1207
    //   1038: aload 20
    //   1040: invokeinterface 818 1 0
    //   1045: goto +162 -> 1207
    //   1048: astore_1
    //   1049: aload 20
    //   1051: astore 17
    //   1053: goto +4123 -> 5176
    //   1056: astore 21
    //   1058: aload_1
    //   1059: astore 17
    //   1061: aload 20
    //   1063: astore 18
    //   1065: aload 21
    //   1067: astore_1
    //   1068: goto -930 -> 138
    //   1071: astore 20
    //   1073: aload 18
    //   1075: astore 17
    //   1077: aload 24
    //   1079: invokevirtual 547	com/google/android/gms/measurement/internal/zzco:zzgo	()Lcom/google/android/gms/measurement/internal/zzap;
    //   1082: invokevirtual 183	com/google/android/gms/measurement/internal/zzap:zzjd	()Lcom/google/android/gms/measurement/internal/zzar;
    //   1085: ldc_w 896
    //   1088: aload_1
    //   1089: invokestatic 223	com/google/android/gms/measurement/internal/zzap:zzbv	(Ljava/lang/String;)Ljava/lang/Object;
    //   1092: aload 20
    //   1094: invokevirtual 312	com/google/android/gms/measurement/internal/zzar:zze	(Ljava/lang/String;Ljava/lang/Object;Ljava/lang/Object;)V
    //   1097: aload 18
    //   1099: ifnull +108 -> 1207
    //   1102: aload 18
    //   1104: invokeinterface 818 1 0
    //   1109: goto +98 -> 1207
    //   1112: astore 20
    //   1114: aload_1
    //   1115: astore 17
    //   1117: aload 20
    //   1119: astore_1
    //   1120: goto -982 -> 138
    //   1123: astore_1
    //   1124: goto +37 -> 1161
    //   1127: astore 21
    //   1129: aload_1
    //   1130: astore 18
    //   1132: aload 17
    //   1134: astore 20
    //   1136: aload 21
    //   1138: astore_1
    //   1139: aload 18
    //   1141: astore 17
    //   1143: aload 20
    //   1145: astore 18
    //   1147: goto -1009 -> 138
    //   1150: astore_1
    //   1151: aconst_null
    //   1152: astore 17
    //   1154: goto -1016 -> 138
    //   1157: astore_1
    //   1158: aconst_null
    //   1159: astore 17
    //   1161: goto +4018 -> 5179
    //   1164: astore_1
    //   1165: aconst_null
    //   1166: astore 20
    //   1168: aconst_null
    //   1169: astore 18
    //   1171: aload 18
    //   1173: astore 17
    //   1175: aload 24
    //   1177: invokevirtual 547	com/google/android/gms/measurement/internal/zzco:zzgo	()Lcom/google/android/gms/measurement/internal/zzap;
    //   1180: invokevirtual 183	com/google/android/gms/measurement/internal/zzap:zzjd	()Lcom/google/android/gms/measurement/internal/zzar;
    //   1183: ldc_w 898
    //   1186: aload 20
    //   1188: invokestatic 223	com/google/android/gms/measurement/internal/zzap:zzbv	(Ljava/lang/String;)Ljava/lang/Object;
    //   1191: aload_1
    //   1192: invokevirtual 312	com/google/android/gms/measurement/internal/zzar:zze	(Ljava/lang/String;Ljava/lang/Object;Ljava/lang/Object;)V
    //   1195: aload 18
    //   1197: ifnull +10 -> 1207
    //   1200: aload 18
    //   1202: invokeinterface 818 1 0
    //   1207: aload 19
    //   1209: getfield 901	com/google/android/gms/measurement/internal/zzfa$zza:zzauc	Ljava/util/List;
    //   1212: ifnull +4024 -> 5236
    //   1215: aload 19
    //   1217: getfield 901	com/google/android/gms/measurement/internal/zzfa$zza:zzauc	Ljava/util/List;
    //   1220: invokeinterface 905 1 0
    //   1225: ifeq +4005 -> 5230
    //   1228: goto +4008 -> 5236
    //   1231: iload 4
    //   1233: ifne +3926 -> 5159
    //   1236: aload 19
    //   1238: getfield 909	com/google/android/gms/measurement/internal/zzfa$zza:zzaua	Lcom/google/android/gms/internal/measurement/zzgi;
    //   1241: astore 17
    //   1243: aload 17
    //   1245: aload 19
    //   1247: getfield 901	com/google/android/gms/measurement/internal/zzfa$zza:zzauc	Ljava/util/List;
    //   1250: invokeinterface 911 1 0
    //   1255: anewarray 884	com/google/android/gms/internal/measurement/zzgf
    //   1258: putfield 915	com/google/android/gms/internal/measurement/zzgi:zzaxb	[Lcom/google/android/gms/internal/measurement/zzgf;
    //   1261: aload 22
    //   1263: getfield 80	com/google/android/gms/measurement/internal/zzfa:zzadj	Lcom/google/android/gms/measurement/internal/zzbt;
    //   1266: invokevirtual 281	com/google/android/gms/measurement/internal/zzbt:zzgq	()Lcom/google/android/gms/measurement/internal/zzn;
    //   1269: aload 17
    //   1271: getfield 918	com/google/android/gms/internal/measurement/zzgi:zztt	Ljava/lang/String;
    //   1274: invokevirtual 921	com/google/android/gms/measurement/internal/zzn:zzax	(Ljava/lang/String;)Z
    //   1277: istore 15
    //   1279: iconst_0
    //   1280: istore 5
    //   1282: iconst_0
    //   1283: istore 13
    //   1285: iconst_0
    //   1286: istore 6
    //   1288: lconst_0
    //   1289: lstore_2
    //   1290: iload 5
    //   1292: aload 19
    //   1294: getfield 901	com/google/android/gms/measurement/internal/zzfa$zza:zzauc	Ljava/util/List;
    //   1297: invokeinterface 911 1 0
    //   1302: if_icmpge +1530 -> 2832
    //   1305: aload 19
    //   1307: getfield 901	com/google/android/gms/measurement/internal/zzfa$zza:zzauc	Ljava/util/List;
    //   1310: iload 5
    //   1312: invokeinterface 924 2 0
    //   1317: checkcast 884	com/google/android/gms/internal/measurement/zzgf
    //   1320: astore 23
    //   1322: aload_0
    //   1323: invokespecial 690	com/google/android/gms/measurement/internal/zzfa:zzln	()Lcom/google/android/gms/measurement/internal/zzbn;
    //   1326: aload 19
    //   1328: getfield 909	com/google/android/gms/measurement/internal/zzfa$zza:zzaua	Lcom/google/android/gms/internal/measurement/zzgi;
    //   1331: getfield 918	com/google/android/gms/internal/measurement/zzgi:zztt	Ljava/lang/String;
    //   1334: aload 23
    //   1336: getfield 886	com/google/android/gms/internal/measurement/zzgf:name	Ljava/lang/String;
    //   1339: invokevirtual 928	com/google/android/gms/measurement/internal/zzbn:zzo	(Ljava/lang/String;Ljava/lang/String;)Z
    //   1342: ifeq +138 -> 1480
    //   1345: aload 22
    //   1347: getfield 80	com/google/android/gms/measurement/internal/zzfa:zzadj	Lcom/google/android/gms/measurement/internal/zzbt;
    //   1350: invokevirtual 152	com/google/android/gms/measurement/internal/zzbt:zzgo	()Lcom/google/android/gms/measurement/internal/zzap;
    //   1353: invokevirtual 158	com/google/android/gms/measurement/internal/zzap:zzjg	()Lcom/google/android/gms/measurement/internal/zzar;
    //   1356: ldc_w 930
    //   1359: aload 19
    //   1361: getfield 909	com/google/android/gms/measurement/internal/zzfa$zza:zzaua	Lcom/google/android/gms/internal/measurement/zzgi;
    //   1364: getfield 918	com/google/android/gms/internal/measurement/zzgi:zztt	Ljava/lang/String;
    //   1367: invokestatic 223	com/google/android/gms/measurement/internal/zzap:zzbv	(Ljava/lang/String;)Ljava/lang/Object;
    //   1370: aload 22
    //   1372: getfield 80	com/google/android/gms/measurement/internal/zzfa:zzadj	Lcom/google/android/gms/measurement/internal/zzbt;
    //   1375: invokevirtual 558	com/google/android/gms/measurement/internal/zzbt:zzgl	()Lcom/google/android/gms/measurement/internal/zzan;
    //   1378: aload 23
    //   1380: getfield 886	com/google/android/gms/internal/measurement/zzgf:name	Ljava/lang/String;
    //   1383: invokevirtual 933	com/google/android/gms/measurement/internal/zzan:zzbs	(Ljava/lang/String;)Ljava/lang/String;
    //   1386: invokevirtual 312	com/google/android/gms/measurement/internal/zzar:zze	(Ljava/lang/String;Ljava/lang/Object;Ljava/lang/Object;)V
    //   1389: aload_0
    //   1390: invokespecial 690	com/google/android/gms/measurement/internal/zzfa:zzln	()Lcom/google/android/gms/measurement/internal/zzbn;
    //   1393: aload 19
    //   1395: getfield 909	com/google/android/gms/measurement/internal/zzfa$zza:zzaua	Lcom/google/android/gms/internal/measurement/zzgi;
    //   1398: getfield 918	com/google/android/gms/internal/measurement/zzgi:zztt	Ljava/lang/String;
    //   1401: invokevirtual 936	com/google/android/gms/measurement/internal/zzbn:zzck	(Ljava/lang/String;)Z
    //   1404: ifne +3844 -> 5248
    //   1407: aload_0
    //   1408: invokespecial 690	com/google/android/gms/measurement/internal/zzfa:zzln	()Lcom/google/android/gms/measurement/internal/zzbn;
    //   1411: aload 19
    //   1413: getfield 909	com/google/android/gms/measurement/internal/zzfa$zza:zzaua	Lcom/google/android/gms/internal/measurement/zzgi;
    //   1416: getfield 918	com/google/android/gms/internal/measurement/zzgi:zztt	Ljava/lang/String;
    //   1419: invokevirtual 938	com/google/android/gms/measurement/internal/zzbn:zzcl	(Ljava/lang/String;)Z
    //   1422: ifeq +3820 -> 5242
    //   1425: goto +3823 -> 5248
    //   1428: iload 4
    //   1430: ifne +3824 -> 5254
    //   1433: ldc_w 590
    //   1436: aload 23
    //   1438: getfield 886	com/google/android/gms/internal/measurement/zzgf:name	Ljava/lang/String;
    //   1441: invokevirtual 233	java/lang/String:equals	(Ljava/lang/Object;)Z
    //   1444: ifne +3810 -> 5254
    //   1447: aload 22
    //   1449: getfield 80	com/google/android/gms/measurement/internal/zzfa:zzadj	Lcom/google/android/gms/measurement/internal/zzbt;
    //   1452: invokevirtual 297	com/google/android/gms/measurement/internal/zzbt:zzgm	()Lcom/google/android/gms/measurement/internal/zzfk;
    //   1455: aload 19
    //   1457: getfield 909	com/google/android/gms/measurement/internal/zzfa$zza:zzaua	Lcom/google/android/gms/internal/measurement/zzgi;
    //   1460: getfield 918	com/google/android/gms/internal/measurement/zzgi:zztt	Ljava/lang/String;
    //   1463: bipush 11
    //   1465: ldc_w 598
    //   1468: aload 23
    //   1470: getfield 886	com/google/android/gms/internal/measurement/zzgf:name	Ljava/lang/String;
    //   1473: iconst_0
    //   1474: invokevirtual 570	com/google/android/gms/measurement/internal/zzfk:zza	(Ljava/lang/String;ILjava/lang/String;Ljava/lang/String;I)V
    //   1477: goto +3777 -> 5254
    //   1480: aload_0
    //   1481: invokespecial 690	com/google/android/gms/measurement/internal/zzfa:zzln	()Lcom/google/android/gms/measurement/internal/zzbn;
    //   1484: aload 19
    //   1486: getfield 909	com/google/android/gms/measurement/internal/zzfa$zza:zzaua	Lcom/google/android/gms/internal/measurement/zzgi;
    //   1489: getfield 918	com/google/android/gms/internal/measurement/zzgi:zztt	Ljava/lang/String;
    //   1492: aload 23
    //   1494: getfield 886	com/google/android/gms/internal/measurement/zzgf:name	Ljava/lang/String;
    //   1497: invokevirtual 941	com/google/android/gms/measurement/internal/zzbn:zzp	(Ljava/lang/String;Ljava/lang/String;)Z
    //   1500: istore 16
    //   1502: iload 16
    //   1504: ifne +100 -> 1604
    //   1507: aload_0
    //   1508: invokevirtual 945	com/google/android/gms/measurement/internal/zzfa:zzjo	()Lcom/google/android/gms/measurement/internal/zzfg;
    //   1511: pop
    //   1512: aload 23
    //   1514: getfield 886	com/google/android/gms/internal/measurement/zzgf:name	Ljava/lang/String;
    //   1517: astore_1
    //   1518: aload_1
    //   1519: invokestatic 528	com/google/android/gms/common/internal/Preconditions:checkNotEmpty	(Ljava/lang/String;)Ljava/lang/String;
    //   1522: pop
    //   1523: aload_1
    //   1524: invokevirtual 948	java/lang/String:hashCode	()I
    //   1527: istore 4
    //   1529: iload 4
    //   1531: ldc_w 949
    //   1534: if_icmpeq +54 -> 1588
    //   1537: iload 4
    //   1539: ldc_w 950
    //   1542: if_icmpeq +30 -> 1572
    //   1545: iload 4
    //   1547: ldc_w 951
    //   1550: if_icmpeq +6 -> 1556
    //   1553: goto +3704 -> 5257
    //   1556: aload_1
    //   1557: ldc_w 953
    //   1560: invokevirtual 233	java/lang/String:equals	(Ljava/lang/Object;)Z
    //   1563: ifeq +3694 -> 5257
    //   1566: iconst_1
    //   1567: istore 4
    //   1569: goto +3691 -> 5260
    //   1572: aload_1
    //   1573: ldc_w 955
    //   1576: invokevirtual 233	java/lang/String:equals	(Ljava/lang/Object;)Z
    //   1579: ifeq +3678 -> 5257
    //   1582: iconst_2
    //   1583: istore 4
    //   1585: goto +3675 -> 5260
    //   1588: aload_1
    //   1589: ldc_w 957
    //   1592: invokevirtual 233	java/lang/String:equals	(Ljava/lang/Object;)Z
    //   1595: ifeq +3662 -> 5257
    //   1598: iconst_0
    //   1599: istore 4
    //   1601: goto +3659 -> 5260
    //   1604: aload 23
    //   1606: getfield 961	com/google/android/gms/internal/measurement/zzgf:zzawt	[Lcom/google/android/gms/internal/measurement/zzgg;
    //   1609: ifnonnull +12 -> 1621
    //   1612: aload 23
    //   1614: iconst_0
    //   1615: anewarray 581	com/google/android/gms/internal/measurement/zzgg
    //   1618: putfield 961	com/google/android/gms/internal/measurement/zzgf:zzawt	[Lcom/google/android/gms/internal/measurement/zzgg;
    //   1621: aload 23
    //   1623: getfield 961	com/google/android/gms/internal/measurement/zzgf:zzawt	[Lcom/google/android/gms/internal/measurement/zzgg;
    //   1626: astore_1
    //   1627: aload_1
    //   1628: arraylength
    //   1629: istore 4
    //   1631: iconst_0
    //   1632: istore 7
    //   1634: iconst_0
    //   1635: istore 8
    //   1637: iconst_0
    //   1638: istore 9
    //   1640: iload 7
    //   1642: iload 4
    //   1644: if_icmpge +75 -> 1719
    //   1647: aload_1
    //   1648: iload 7
    //   1650: aaload
    //   1651: astore 18
    //   1653: ldc_w 963
    //   1656: aload 18
    //   1658: getfield 591	com/google/android/gms/internal/measurement/zzgg:name	Ljava/lang/String;
    //   1661: invokevirtual 233	java/lang/String:equals	(Ljava/lang/Object;)Z
    //   1664: ifeq +18 -> 1682
    //   1667: aload 18
    //   1669: lconst_1
    //   1670: invokestatic 404	java/lang/Long:valueOf	(J)Ljava/lang/Long;
    //   1673: putfield 596	com/google/android/gms/internal/measurement/zzgg:zzawx	Ljava/lang/Long;
    //   1676: iconst_1
    //   1677: istore 10
    //   1679: goto +3629 -> 5308
    //   1682: iload 8
    //   1684: istore 10
    //   1686: ldc_w 965
    //   1689: aload 18
    //   1691: getfield 591	com/google/android/gms/internal/measurement/zzgg:name	Ljava/lang/String;
    //   1694: invokevirtual 233	java/lang/String:equals	(Ljava/lang/Object;)Z
    //   1697: ifeq +3611 -> 5308
    //   1700: aload 18
    //   1702: lconst_1
    //   1703: invokestatic 404	java/lang/Long:valueOf	(J)Ljava/lang/Long;
    //   1706: putfield 596	com/google/android/gms/internal/measurement/zzgg:zzawx	Ljava/lang/Long;
    //   1709: iconst_1
    //   1710: istore 9
    //   1712: iload 8
    //   1714: istore 10
    //   1716: goto +3592 -> 5308
    //   1719: iload 8
    //   1721: ifne +101 -> 1822
    //   1724: iload 16
    //   1726: ifeq +96 -> 1822
    //   1729: aload 22
    //   1731: getfield 80	com/google/android/gms/measurement/internal/zzfa:zzadj	Lcom/google/android/gms/measurement/internal/zzbt;
    //   1734: invokevirtual 152	com/google/android/gms/measurement/internal/zzbt:zzgo	()Lcom/google/android/gms/measurement/internal/zzap;
    //   1737: invokevirtual 684	com/google/android/gms/measurement/internal/zzap:zzjl	()Lcom/google/android/gms/measurement/internal/zzar;
    //   1740: ldc_w 967
    //   1743: aload 22
    //   1745: getfield 80	com/google/android/gms/measurement/internal/zzfa:zzadj	Lcom/google/android/gms/measurement/internal/zzbt;
    //   1748: invokevirtual 558	com/google/android/gms/measurement/internal/zzbt:zzgl	()Lcom/google/android/gms/measurement/internal/zzan;
    //   1751: aload 23
    //   1753: getfield 886	com/google/android/gms/internal/measurement/zzgf:name	Ljava/lang/String;
    //   1756: invokevirtual 933	com/google/android/gms/measurement/internal/zzan:zzbs	(Ljava/lang/String;)Ljava/lang/String;
    //   1759: invokevirtual 172	com/google/android/gms/measurement/internal/zzar:zzg	(Ljava/lang/String;Ljava/lang/Object;)V
    //   1762: aload 23
    //   1764: getfield 961	com/google/android/gms/internal/measurement/zzgf:zzawt	[Lcom/google/android/gms/internal/measurement/zzgg;
    //   1767: aload 23
    //   1769: getfield 961	com/google/android/gms/internal/measurement/zzgf:zzawt	[Lcom/google/android/gms/internal/measurement/zzgg;
    //   1772: arraylength
    //   1773: iconst_1
    //   1774: iadd
    //   1775: invokestatic 973	java/util/Arrays:copyOf	([Ljava/lang/Object;I)[Ljava/lang/Object;
    //   1778: checkcast 974	[Lcom/google/android/gms/internal/measurement/zzgg;
    //   1781: astore_1
    //   1782: new 581	com/google/android/gms/internal/measurement/zzgg
    //   1785: dup
    //   1786: invokespecial 592	com/google/android/gms/internal/measurement/zzgg:<init>	()V
    //   1789: astore 18
    //   1791: aload 18
    //   1793: ldc_w 963
    //   1796: putfield 591	com/google/android/gms/internal/measurement/zzgg:name	Ljava/lang/String;
    //   1799: aload 18
    //   1801: lconst_1
    //   1802: invokestatic 404	java/lang/Long:valueOf	(J)Ljava/lang/Long;
    //   1805: putfield 596	com/google/android/gms/internal/measurement/zzgg:zzawx	Ljava/lang/Long;
    //   1808: aload_1
    //   1809: aload_1
    //   1810: arraylength
    //   1811: iconst_1
    //   1812: isub
    //   1813: aload 18
    //   1815: aastore
    //   1816: aload 23
    //   1818: aload_1
    //   1819: putfield 961	com/google/android/gms/internal/measurement/zzgf:zzawt	[Lcom/google/android/gms/internal/measurement/zzgg;
    //   1822: iload 9
    //   1824: ifne +96 -> 1920
    //   1827: aload 22
    //   1829: getfield 80	com/google/android/gms/measurement/internal/zzfa:zzadj	Lcom/google/android/gms/measurement/internal/zzbt;
    //   1832: invokevirtual 152	com/google/android/gms/measurement/internal/zzbt:zzgo	()Lcom/google/android/gms/measurement/internal/zzap;
    //   1835: invokevirtual 684	com/google/android/gms/measurement/internal/zzap:zzjl	()Lcom/google/android/gms/measurement/internal/zzar;
    //   1838: ldc_w 976
    //   1841: aload 22
    //   1843: getfield 80	com/google/android/gms/measurement/internal/zzfa:zzadj	Lcom/google/android/gms/measurement/internal/zzbt;
    //   1846: invokevirtual 558	com/google/android/gms/measurement/internal/zzbt:zzgl	()Lcom/google/android/gms/measurement/internal/zzan;
    //   1849: aload 23
    //   1851: getfield 886	com/google/android/gms/internal/measurement/zzgf:name	Ljava/lang/String;
    //   1854: invokevirtual 933	com/google/android/gms/measurement/internal/zzan:zzbs	(Ljava/lang/String;)Ljava/lang/String;
    //   1857: invokevirtual 172	com/google/android/gms/measurement/internal/zzar:zzg	(Ljava/lang/String;Ljava/lang/Object;)V
    //   1860: aload 23
    //   1862: getfield 961	com/google/android/gms/internal/measurement/zzgf:zzawt	[Lcom/google/android/gms/internal/measurement/zzgg;
    //   1865: aload 23
    //   1867: getfield 961	com/google/android/gms/internal/measurement/zzgf:zzawt	[Lcom/google/android/gms/internal/measurement/zzgg;
    //   1870: arraylength
    //   1871: iconst_1
    //   1872: iadd
    //   1873: invokestatic 973	java/util/Arrays:copyOf	([Ljava/lang/Object;I)[Ljava/lang/Object;
    //   1876: checkcast 974	[Lcom/google/android/gms/internal/measurement/zzgg;
    //   1879: astore_1
    //   1880: new 581	com/google/android/gms/internal/measurement/zzgg
    //   1883: dup
    //   1884: invokespecial 592	com/google/android/gms/internal/measurement/zzgg:<init>	()V
    //   1887: astore 18
    //   1889: aload 18
    //   1891: ldc_w 965
    //   1894: putfield 591	com/google/android/gms/internal/measurement/zzgg:name	Ljava/lang/String;
    //   1897: aload 18
    //   1899: lconst_1
    //   1900: invokestatic 404	java/lang/Long:valueOf	(J)Ljava/lang/Long;
    //   1903: putfield 596	com/google/android/gms/internal/measurement/zzgg:zzawx	Ljava/lang/Long;
    //   1906: aload_1
    //   1907: aload_1
    //   1908: arraylength
    //   1909: iconst_1
    //   1910: isub
    //   1911: aload 18
    //   1913: aastore
    //   1914: aload 23
    //   1916: aload_1
    //   1917: putfield 961	com/google/android/gms/internal/measurement/zzgf:zzawt	[Lcom/google/android/gms/internal/measurement/zzgg;
    //   1920: aload_0
    //   1921: invokevirtual 492	com/google/android/gms/measurement/internal/zzfa:zzjq	()Lcom/google/android/gms/measurement/internal/zzq;
    //   1924: aload_0
    //   1925: invokespecial 979	com/google/android/gms/measurement/internal/zzfa:zzls	()J
    //   1928: aload 19
    //   1930: getfield 909	com/google/android/gms/measurement/internal/zzfa$zza:zzaua	Lcom/google/android/gms/internal/measurement/zzgi;
    //   1933: getfield 918	com/google/android/gms/internal/measurement/zzgi:zztt	Ljava/lang/String;
    //   1936: iconst_0
    //   1937: iconst_0
    //   1938: iconst_0
    //   1939: iconst_0
    //   1940: iconst_1
    //   1941: invokevirtual 982	com/google/android/gms/measurement/internal/zzq:zza	(JLjava/lang/String;ZZZZZ)Lcom/google/android/gms/measurement/internal/zzr;
    //   1944: getfield 987	com/google/android/gms/measurement/internal/zzr:zzahu	J
    //   1947: aload 22
    //   1949: getfield 80	com/google/android/gms/measurement/internal/zzfa:zzadj	Lcom/google/android/gms/measurement/internal/zzbt;
    //   1952: invokevirtual 281	com/google/android/gms/measurement/internal/zzbt:zzgq	()Lcom/google/android/gms/measurement/internal/zzn;
    //   1955: aload 19
    //   1957: getfield 909	com/google/android/gms/measurement/internal/zzfa$zza:zzaua	Lcom/google/android/gms/internal/measurement/zzgi;
    //   1960: getfield 918	com/google/android/gms/internal/measurement/zzgi:zztt	Ljava/lang/String;
    //   1963: invokevirtual 991	com/google/android/gms/measurement/internal/zzn:zzat	(Ljava/lang/String;)I
    //   1966: i2l
    //   1967: lcmp
    //   1968: ifle +3362 -> 5330
    //   1971: iconst_0
    //   1972: istore 4
    //   1974: iload 13
    //   1976: istore 14
    //   1978: iload 4
    //   1980: aload 23
    //   1982: getfield 961	com/google/android/gms/internal/measurement/zzgf:zzawt	[Lcom/google/android/gms/internal/measurement/zzgg;
    //   1985: arraylength
    //   1986: if_icmpge +93 -> 2079
    //   1989: ldc_w 965
    //   1992: aload 23
    //   1994: getfield 961	com/google/android/gms/internal/measurement/zzgf:zzawt	[Lcom/google/android/gms/internal/measurement/zzgg;
    //   1997: iload 4
    //   1999: aaload
    //   2000: getfield 591	com/google/android/gms/internal/measurement/zzgg:name	Ljava/lang/String;
    //   2003: invokevirtual 233	java/lang/String:equals	(Ljava/lang/Object;)Z
    //   2006: ifeq +3315 -> 5321
    //   2009: aload 23
    //   2011: getfield 961	com/google/android/gms/internal/measurement/zzgf:zzawt	[Lcom/google/android/gms/internal/measurement/zzgg;
    //   2014: arraylength
    //   2015: iconst_1
    //   2016: isub
    //   2017: anewarray 581	com/google/android/gms/internal/measurement/zzgg
    //   2020: astore_1
    //   2021: iload 4
    //   2023: ifle +16 -> 2039
    //   2026: aload 23
    //   2028: getfield 961	com/google/android/gms/internal/measurement/zzgf:zzawt	[Lcom/google/android/gms/internal/measurement/zzgg;
    //   2031: iconst_0
    //   2032: aload_1
    //   2033: iconst_0
    //   2034: iload 4
    //   2036: invokestatic 587	java/lang/System:arraycopy	(Ljava/lang/Object;ILjava/lang/Object;II)V
    //   2039: iload 4
    //   2041: aload_1
    //   2042: arraylength
    //   2043: if_icmpge +23 -> 2066
    //   2046: aload 23
    //   2048: getfield 961	com/google/android/gms/internal/measurement/zzgf:zzawt	[Lcom/google/android/gms/internal/measurement/zzgg;
    //   2051: iload 4
    //   2053: iconst_1
    //   2054: iadd
    //   2055: aload_1
    //   2056: iload 4
    //   2058: aload_1
    //   2059: arraylength
    //   2060: iload 4
    //   2062: isub
    //   2063: invokestatic 587	java/lang/System:arraycopy	(Ljava/lang/Object;ILjava/lang/Object;II)V
    //   2066: aload 23
    //   2068: aload_1
    //   2069: putfield 961	com/google/android/gms/internal/measurement/zzgf:zzawt	[Lcom/google/android/gms/internal/measurement/zzgg;
    //   2072: iload 13
    //   2074: istore 14
    //   2076: goto +3 -> 2079
    //   2079: iload 14
    //   2081: istore 13
    //   2083: aload 23
    //   2085: getfield 886	com/google/android/gms/internal/measurement/zzgf:name	Ljava/lang/String;
    //   2088: invokestatic 994	com/google/android/gms/measurement/internal/zzfk:zzcq	(Ljava/lang/String;)Z
    //   2091: ifeq +3214 -> 5305
    //   2094: iload 14
    //   2096: istore 13
    //   2098: iload 16
    //   2100: ifeq +3205 -> 5305
    //   2103: iload 14
    //   2105: istore 13
    //   2107: aload_0
    //   2108: invokevirtual 492	com/google/android/gms/measurement/internal/zzfa:zzjq	()Lcom/google/android/gms/measurement/internal/zzq;
    //   2111: aload_0
    //   2112: invokespecial 979	com/google/android/gms/measurement/internal/zzfa:zzls	()J
    //   2115: aload 19
    //   2117: getfield 909	com/google/android/gms/measurement/internal/zzfa$zza:zzaua	Lcom/google/android/gms/internal/measurement/zzgi;
    //   2120: getfield 918	com/google/android/gms/internal/measurement/zzgi:zztt	Ljava/lang/String;
    //   2123: iconst_0
    //   2124: iconst_0
    //   2125: iconst_1
    //   2126: iconst_0
    //   2127: iconst_0
    //   2128: invokevirtual 982	com/google/android/gms/measurement/internal/zzq:zza	(JLjava/lang/String;ZZZZZ)Lcom/google/android/gms/measurement/internal/zzr;
    //   2131: getfield 997	com/google/android/gms/measurement/internal/zzr:zzahs	J
    //   2134: aload 22
    //   2136: getfield 80	com/google/android/gms/measurement/internal/zzfa:zzadj	Lcom/google/android/gms/measurement/internal/zzbt;
    //   2139: invokevirtual 281	com/google/android/gms/measurement/internal/zzbt:zzgq	()Lcom/google/android/gms/measurement/internal/zzn;
    //   2142: aload 19
    //   2144: getfield 909	com/google/android/gms/measurement/internal/zzfa$zza:zzaua	Lcom/google/android/gms/internal/measurement/zzgi;
    //   2147: getfield 918	com/google/android/gms/internal/measurement/zzgi:zztt	Ljava/lang/String;
    //   2150: getstatic 1000	com/google/android/gms/measurement/internal/zzaf:zzajq	Lcom/google/android/gms/measurement/internal/zzaf$zza;
    //   2153: invokevirtual 525	com/google/android/gms/measurement/internal/zzn:zzb	(Ljava/lang/String;Lcom/google/android/gms/measurement/internal/zzaf$zza;)I
    //   2156: i2l
    //   2157: lcmp
    //   2158: ifle +3147 -> 5305
    //   2161: aload 22
    //   2163: getfield 80	com/google/android/gms/measurement/internal/zzfa:zzadj	Lcom/google/android/gms/measurement/internal/zzbt;
    //   2166: invokevirtual 152	com/google/android/gms/measurement/internal/zzbt:zzgo	()Lcom/google/android/gms/measurement/internal/zzap;
    //   2169: invokevirtual 158	com/google/android/gms/measurement/internal/zzap:zzjg	()Lcom/google/android/gms/measurement/internal/zzar;
    //   2172: ldc_w 1002
    //   2175: aload 19
    //   2177: getfield 909	com/google/android/gms/measurement/internal/zzfa$zza:zzaua	Lcom/google/android/gms/internal/measurement/zzgi;
    //   2180: getfield 918	com/google/android/gms/internal/measurement/zzgi:zztt	Ljava/lang/String;
    //   2183: invokestatic 223	com/google/android/gms/measurement/internal/zzap:zzbv	(Ljava/lang/String;)Ljava/lang/Object;
    //   2186: invokevirtual 172	com/google/android/gms/measurement/internal/zzar:zzg	(Ljava/lang/String;Ljava/lang/Object;)V
    //   2189: aload 23
    //   2191: getfield 961	com/google/android/gms/internal/measurement/zzgf:zzawt	[Lcom/google/android/gms/internal/measurement/zzgg;
    //   2194: astore_1
    //   2195: aload_1
    //   2196: arraylength
    //   2197: istore 4
    //   2199: iconst_0
    //   2200: istore 7
    //   2202: iconst_0
    //   2203: istore 8
    //   2205: aconst_null
    //   2206: astore 18
    //   2208: iload 7
    //   2210: iload 4
    //   2212: if_icmpge +58 -> 2270
    //   2215: aload_1
    //   2216: iload 7
    //   2218: aaload
    //   2219: astore 21
    //   2221: ldc_w 963
    //   2224: aload 21
    //   2226: getfield 591	com/google/android/gms/internal/measurement/zzgg:name	Ljava/lang/String;
    //   2229: invokevirtual 233	java/lang/String:equals	(Ljava/lang/Object;)Z
    //   2232: ifeq +10 -> 2242
    //   2235: aload 21
    //   2237: astore 20
    //   2239: goto +3097 -> 5336
    //   2242: aload 18
    //   2244: astore 20
    //   2246: ldc_w 590
    //   2249: aload 21
    //   2251: getfield 591	com/google/android/gms/internal/measurement/zzgg:name	Ljava/lang/String;
    //   2254: invokevirtual 233	java/lang/String:equals	(Ljava/lang/Object;)Z
    //   2257: ifeq +3079 -> 5336
    //   2260: iconst_1
    //   2261: istore 8
    //   2263: aload 18
    //   2265: astore 20
    //   2267: goto +3069 -> 5336
    //   2270: iload 14
    //   2272: istore 13
    //   2274: iload 8
    //   2276: ifeq +36 -> 2312
    //   2279: aload 18
    //   2281: ifnull +31 -> 2312
    //   2284: aload 23
    //   2286: aload 23
    //   2288: getfield 961	com/google/android/gms/internal/measurement/zzgf:zzawt	[Lcom/google/android/gms/internal/measurement/zzgg;
    //   2291: iconst_1
    //   2292: anewarray 581	com/google/android/gms/internal/measurement/zzgg
    //   2295: dup
    //   2296: iconst_0
    //   2297: aload 18
    //   2299: aastore
    //   2300: invokestatic 1008	com/google/android/gms/common/util/ArrayUtils:removeAll	([Ljava/lang/Object;[Ljava/lang/Object;)[Ljava/lang/Object;
    //   2303: checkcast 974	[Lcom/google/android/gms/internal/measurement/zzgg;
    //   2306: putfield 961	com/google/android/gms/internal/measurement/zzgf:zzawt	[Lcom/google/android/gms/internal/measurement/zzgg;
    //   2309: goto +58 -> 2367
    //   2312: aload 18
    //   2314: ifnull +25 -> 2339
    //   2317: aload 18
    //   2319: ldc_w 590
    //   2322: putfield 591	com/google/android/gms/internal/measurement/zzgg:name	Ljava/lang/String;
    //   2325: aload 18
    //   2327: ldc2_w 1009
    //   2330: invokestatic 404	java/lang/Long:valueOf	(J)Ljava/lang/Long;
    //   2333: putfield 596	com/google/android/gms/internal/measurement/zzgg:zzawx	Ljava/lang/Long;
    //   2336: goto +31 -> 2367
    //   2339: aload 22
    //   2341: getfield 80	com/google/android/gms/measurement/internal/zzfa:zzadj	Lcom/google/android/gms/measurement/internal/zzbt;
    //   2344: invokevirtual 152	com/google/android/gms/measurement/internal/zzbt:zzgo	()Lcom/google/android/gms/measurement/internal/zzap;
    //   2347: invokevirtual 183	com/google/android/gms/measurement/internal/zzap:zzjd	()Lcom/google/android/gms/measurement/internal/zzar;
    //   2350: ldc_w 1012
    //   2353: aload 19
    //   2355: getfield 909	com/google/android/gms/measurement/internal/zzfa$zza:zzaua	Lcom/google/android/gms/internal/measurement/zzgi;
    //   2358: getfield 918	com/google/android/gms/internal/measurement/zzgi:zztt	Ljava/lang/String;
    //   2361: invokestatic 223	com/google/android/gms/measurement/internal/zzap:zzbv	(Ljava/lang/String;)Ljava/lang/Object;
    //   2364: invokevirtual 172	com/google/android/gms/measurement/internal/zzar:zzg	(Ljava/lang/String;Ljava/lang/Object;)V
    //   2367: aload 22
    //   2369: getfield 80	com/google/android/gms/measurement/internal/zzfa:zzadj	Lcom/google/android/gms/measurement/internal/zzbt;
    //   2372: invokevirtual 281	com/google/android/gms/measurement/internal/zzbt:zzgq	()Lcom/google/android/gms/measurement/internal/zzn;
    //   2375: aload 19
    //   2377: getfield 909	com/google/android/gms/measurement/internal/zzfa$zza:zzaua	Lcom/google/android/gms/internal/measurement/zzgi;
    //   2380: getfield 918	com/google/android/gms/internal/measurement/zzgi:zztt	Ljava/lang/String;
    //   2383: invokevirtual 1015	com/google/android/gms/measurement/internal/zzn:zzbf	(Ljava/lang/String;)Z
    //   2386: ifeq +3009 -> 5395
    //   2389: iload 16
    //   2391: ifeq +3004 -> 5395
    //   2394: aload 23
    //   2396: getfield 961	com/google/android/gms/internal/measurement/zzgf:zzawt	[Lcom/google/android/gms/internal/measurement/zzgg;
    //   2399: astore 18
    //   2401: iconst_0
    //   2402: istore 4
    //   2404: iconst_m1
    //   2405: istore 7
    //   2407: iconst_m1
    //   2408: istore 8
    //   2410: iload 4
    //   2412: aload 18
    //   2414: arraylength
    //   2415: if_icmpge +59 -> 2474
    //   2418: ldc_w 429
    //   2421: aload 18
    //   2423: iload 4
    //   2425: aaload
    //   2426: getfield 591	com/google/android/gms/internal/measurement/zzgg:name	Ljava/lang/String;
    //   2429: invokevirtual 233	java/lang/String:equals	(Ljava/lang/Object;)Z
    //   2432: ifeq +10 -> 2442
    //   2435: iload 4
    //   2437: istore 9
    //   2439: goto +2910 -> 5349
    //   2442: iload 7
    //   2444: istore 9
    //   2446: ldc_w 417
    //   2449: aload 18
    //   2451: iload 4
    //   2453: aaload
    //   2454: getfield 591	com/google/android/gms/internal/measurement/zzgg:name	Ljava/lang/String;
    //   2457: invokevirtual 233	java/lang/String:equals	(Ljava/lang/Object;)Z
    //   2460: ifeq +2889 -> 5349
    //   2463: iload 4
    //   2465: istore 8
    //   2467: iload 7
    //   2469: istore 9
    //   2471: goto +2878 -> 5349
    //   2474: aload 18
    //   2476: astore_1
    //   2477: iload 7
    //   2479: iconst_m1
    //   2480: if_icmpeq +2882 -> 5362
    //   2483: aload 18
    //   2485: iload 7
    //   2487: aaload
    //   2488: getfield 596	com/google/android/gms/internal/measurement/zzgg:zzawx	Ljava/lang/Long;
    //   2491: ifnonnull +2874 -> 5365
    //   2494: aload 18
    //   2496: iload 7
    //   2498: aaload
    //   2499: getfield 1019	com/google/android/gms/internal/measurement/zzgg:zzauh	Ljava/lang/Double;
    //   2502: ifnonnull +2863 -> 5365
    //   2505: aload 22
    //   2507: getfield 80	com/google/android/gms/measurement/internal/zzfa:zzadj	Lcom/google/android/gms/measurement/internal/zzbt;
    //   2510: invokevirtual 152	com/google/android/gms/measurement/internal/zzbt:zzgo	()Lcom/google/android/gms/measurement/internal/zzap;
    //   2513: invokevirtual 1022	com/google/android/gms/measurement/internal/zzap:zzji	()Lcom/google/android/gms/measurement/internal/zzar;
    //   2516: ldc_w 1024
    //   2519: invokevirtual 191	com/google/android/gms/measurement/internal/zzar:zzbx	(Ljava/lang/String;)V
    //   2522: aload 18
    //   2524: iload 7
    //   2526: invokestatic 605	com/google/android/gms/measurement/internal/zzfa:zza	([Lcom/google/android/gms/internal/measurement/zzgg;I)[Lcom/google/android/gms/internal/measurement/zzgg;
    //   2529: ldc_w 963
    //   2532: invokestatic 1026	com/google/android/gms/measurement/internal/zzfa:zza	([Lcom/google/android/gms/internal/measurement/zzgg;Ljava/lang/String;)[Lcom/google/android/gms/internal/measurement/zzgg;
    //   2535: bipush 18
    //   2537: ldc_w 429
    //   2540: invokestatic 1028	com/google/android/gms/measurement/internal/zzfa:zza	([Lcom/google/android/gms/internal/measurement/zzgg;ILjava/lang/String;)[Lcom/google/android/gms/internal/measurement/zzgg;
    //   2543: astore_1
    //   2544: goto +2818 -> 5362
    //   2547: aload 18
    //   2549: iload 8
    //   2551: aaload
    //   2552: getfield 601	com/google/android/gms/internal/measurement/zzgg:zzamp	Ljava/lang/String;
    //   2555: astore_1
    //   2556: aload_1
    //   2557: ifnull +2832 -> 5389
    //   2560: aload_1
    //   2561: invokevirtual 328	java/lang/String:length	()I
    //   2564: iconst_3
    //   2565: if_icmpeq +2812 -> 5377
    //   2568: goto +2821 -> 5389
    //   2571: iload 4
    //   2573: aload_1
    //   2574: invokevirtual 328	java/lang/String:length	()I
    //   2577: if_icmpge +2806 -> 5383
    //   2580: aload_1
    //   2581: iload 4
    //   2583: invokevirtual 1032	java/lang/String:codePointAt	(I)I
    //   2586: istore 8
    //   2588: iload 8
    //   2590: invokestatic 1038	java/lang/Character:isLetter	(I)Z
    //   2593: ifne +6 -> 2599
    //   2596: goto +2793 -> 5389
    //   2599: iload 4
    //   2601: iload 8
    //   2603: invokestatic 1041	java/lang/Character:charCount	(I)I
    //   2606: iadd
    //   2607: istore 4
    //   2609: goto -38 -> 2571
    //   2612: aload 18
    //   2614: astore_1
    //   2615: iload 4
    //   2617: ifeq +42 -> 2659
    //   2620: aload 22
    //   2622: getfield 80	com/google/android/gms/measurement/internal/zzfa:zzadj	Lcom/google/android/gms/measurement/internal/zzbt;
    //   2625: invokevirtual 152	com/google/android/gms/measurement/internal/zzbt:zzgo	()Lcom/google/android/gms/measurement/internal/zzap;
    //   2628: invokevirtual 1022	com/google/android/gms/measurement/internal/zzap:zzji	()Lcom/google/android/gms/measurement/internal/zzar;
    //   2631: ldc_w 1043
    //   2634: invokevirtual 191	com/google/android/gms/measurement/internal/zzar:zzbx	(Ljava/lang/String;)V
    //   2637: aload 18
    //   2639: iload 7
    //   2641: invokestatic 605	com/google/android/gms/measurement/internal/zzfa:zza	([Lcom/google/android/gms/internal/measurement/zzgg;I)[Lcom/google/android/gms/internal/measurement/zzgg;
    //   2644: ldc_w 963
    //   2647: invokestatic 1026	com/google/android/gms/measurement/internal/zzfa:zza	([Lcom/google/android/gms/internal/measurement/zzgg;Ljava/lang/String;)[Lcom/google/android/gms/internal/measurement/zzgg;
    //   2650: bipush 19
    //   2652: ldc_w 417
    //   2655: invokestatic 1028	com/google/android/gms/measurement/internal/zzfa:zza	([Lcom/google/android/gms/internal/measurement/zzgg;ILjava/lang/String;)[Lcom/google/android/gms/internal/measurement/zzgg;
    //   2658: astore_1
    //   2659: aload 23
    //   2661: aload_1
    //   2662: putfield 961	com/google/android/gms/internal/measurement/zzgf:zzawt	[Lcom/google/android/gms/internal/measurement/zzgg;
    //   2665: goto +3 -> 2668
    //   2668: lload_2
    //   2669: lstore 11
    //   2671: iload 15
    //   2673: ifeq +137 -> 2810
    //   2676: lload_2
    //   2677: lstore 11
    //   2679: ldc_w 1045
    //   2682: aload 23
    //   2684: getfield 886	com/google/android/gms/internal/measurement/zzgf:name	Ljava/lang/String;
    //   2687: invokevirtual 233	java/lang/String:equals	(Ljava/lang/Object;)Z
    //   2690: ifeq +120 -> 2810
    //   2693: aload 23
    //   2695: getfield 961	com/google/android/gms/internal/measurement/zzgf:zzawt	[Lcom/google/android/gms/internal/measurement/zzgg;
    //   2698: ifnull +81 -> 2779
    //   2701: aload 23
    //   2703: getfield 961	com/google/android/gms/internal/measurement/zzgf:zzawt	[Lcom/google/android/gms/internal/measurement/zzgg;
    //   2706: arraylength
    //   2707: ifne +6 -> 2713
    //   2710: goto +69 -> 2779
    //   2713: aload_0
    //   2714: invokevirtual 945	com/google/android/gms/measurement/internal/zzfa:zzjo	()Lcom/google/android/gms/measurement/internal/zzfg;
    //   2717: pop
    //   2718: aload 23
    //   2720: ldc_w 1047
    //   2723: invokestatic 1050	com/google/android/gms/measurement/internal/zzfg:zzb	(Lcom/google/android/gms/internal/measurement/zzgf;Ljava/lang/String;)Ljava/lang/Object;
    //   2726: checkcast 401	java/lang/Long
    //   2729: astore_1
    //   2730: aload_1
    //   2731: ifnonnull +37 -> 2768
    //   2734: aload 22
    //   2736: getfield 80	com/google/android/gms/measurement/internal/zzfa:zzadj	Lcom/google/android/gms/measurement/internal/zzbt;
    //   2739: invokevirtual 152	com/google/android/gms/measurement/internal/zzbt:zzgo	()Lcom/google/android/gms/measurement/internal/zzap;
    //   2742: invokevirtual 158	com/google/android/gms/measurement/internal/zzap:zzjg	()Lcom/google/android/gms/measurement/internal/zzar;
    //   2745: ldc_w 1052
    //   2748: aload 19
    //   2750: getfield 909	com/google/android/gms/measurement/internal/zzfa$zza:zzaua	Lcom/google/android/gms/internal/measurement/zzgi;
    //   2753: getfield 918	com/google/android/gms/internal/measurement/zzgi:zztt	Ljava/lang/String;
    //   2756: invokestatic 223	com/google/android/gms/measurement/internal/zzap:zzbv	(Ljava/lang/String;)Ljava/lang/Object;
    //   2759: invokevirtual 172	com/google/android/gms/measurement/internal/zzar:zzg	(Ljava/lang/String;Ljava/lang/Object;)V
    //   2762: lload_2
    //   2763: lstore 11
    //   2765: goto +45 -> 2810
    //   2768: lload_2
    //   2769: aload_1
    //   2770: invokevirtual 448	java/lang/Long:longValue	()J
    //   2773: ladd
    //   2774: lstore 11
    //   2776: goto +34 -> 2810
    //   2779: aload 22
    //   2781: getfield 80	com/google/android/gms/measurement/internal/zzfa:zzadj	Lcom/google/android/gms/measurement/internal/zzbt;
    //   2784: invokevirtual 152	com/google/android/gms/measurement/internal/zzbt:zzgo	()Lcom/google/android/gms/measurement/internal/zzap;
    //   2787: invokevirtual 158	com/google/android/gms/measurement/internal/zzap:zzjg	()Lcom/google/android/gms/measurement/internal/zzar;
    //   2790: ldc_w 1054
    //   2793: aload 19
    //   2795: getfield 909	com/google/android/gms/measurement/internal/zzfa$zza:zzaua	Lcom/google/android/gms/internal/measurement/zzgi;
    //   2798: getfield 918	com/google/android/gms/internal/measurement/zzgi:zztt	Ljava/lang/String;
    //   2801: invokestatic 223	com/google/android/gms/measurement/internal/zzap:zzbv	(Ljava/lang/String;)Ljava/lang/Object;
    //   2804: invokevirtual 172	com/google/android/gms/measurement/internal/zzar:zzg	(Ljava/lang/String;Ljava/lang/Object;)V
    //   2807: lload_2
    //   2808: lstore 11
    //   2810: aload 17
    //   2812: getfield 915	com/google/android/gms/internal/measurement/zzgi:zzaxb	[Lcom/google/android/gms/internal/measurement/zzgf;
    //   2815: iload 6
    //   2817: aload 23
    //   2819: aastore
    //   2820: iload 6
    //   2822: iconst_1
    //   2823: iadd
    //   2824: istore 6
    //   2826: lload 11
    //   2828: lstore_2
    //   2829: goto +2569 -> 5398
    //   2832: iload 6
    //   2834: aload 19
    //   2836: getfield 901	com/google/android/gms/measurement/internal/zzfa$zza:zzauc	Ljava/util/List;
    //   2839: invokeinterface 911 1 0
    //   2844: if_icmpge +21 -> 2865
    //   2847: aload 17
    //   2849: aload 17
    //   2851: getfield 915	com/google/android/gms/internal/measurement/zzgi:zzaxb	[Lcom/google/android/gms/internal/measurement/zzgf;
    //   2854: iload 6
    //   2856: invokestatic 973	java/util/Arrays:copyOf	([Ljava/lang/Object;I)[Ljava/lang/Object;
    //   2859: checkcast 1055	[Lcom/google/android/gms/internal/measurement/zzgf;
    //   2862: putfield 915	com/google/android/gms/internal/measurement/zzgi:zzaxb	[Lcom/google/android/gms/internal/measurement/zzgf;
    //   2865: iload 15
    //   2867: ifeq +303 -> 3170
    //   2870: aload_0
    //   2871: invokevirtual 492	com/google/android/gms/measurement/internal/zzfa:zzjq	()Lcom/google/android/gms/measurement/internal/zzq;
    //   2874: aload 17
    //   2876: getfield 918	com/google/android/gms/internal/measurement/zzgi:zztt	Ljava/lang/String;
    //   2879: ldc_w 1057
    //   2882: invokevirtual 496	com/google/android/gms/measurement/internal/zzq:zzi	(Ljava/lang/String;Ljava/lang/String;)Lcom/google/android/gms/measurement/internal/zzfj;
    //   2885: astore_1
    //   2886: aload_1
    //   2887: ifnull +63 -> 2950
    //   2890: aload_1
    //   2891: getfield 501	com/google/android/gms/measurement/internal/zzfj:value	Ljava/lang/Object;
    //   2894: ifnonnull +6 -> 2900
    //   2897: goto +53 -> 2950
    //   2900: new 498	com/google/android/gms/measurement/internal/zzfj
    //   2903: dup
    //   2904: aload 17
    //   2906: getfield 918	com/google/android/gms/internal/measurement/zzgi:zztt	Ljava/lang/String;
    //   2909: ldc_w 1059
    //   2912: ldc_w 1057
    //   2915: aload 22
    //   2917: getfield 80	com/google/android/gms/measurement/internal/zzfa:zzadj	Lcom/google/android/gms/measurement/internal/zzbt;
    //   2920: invokevirtual 507	com/google/android/gms/measurement/internal/zzbt:zzbx	()Lcom/google/android/gms/common/util/Clock;
    //   2923: invokeinterface 512 1 0
    //   2928: aload_1
    //   2929: getfield 501	com/google/android/gms/measurement/internal/zzfj:value	Ljava/lang/Object;
    //   2932: checkcast 401	java/lang/Long
    //   2935: invokevirtual 448	java/lang/Long:longValue	()J
    //   2938: lload_2
    //   2939: ladd
    //   2940: invokestatic 404	java/lang/Long:valueOf	(J)Ljava/lang/Long;
    //   2943: invokespecial 515	com/google/android/gms/measurement/internal/zzfj:<init>	(Ljava/lang/String;Ljava/lang/String;Ljava/lang/String;JLjava/lang/Object;)V
    //   2946: astore_1
    //   2947: goto +39 -> 2986
    //   2950: new 498	com/google/android/gms/measurement/internal/zzfj
    //   2953: dup
    //   2954: aload 17
    //   2956: getfield 918	com/google/android/gms/internal/measurement/zzgi:zztt	Ljava/lang/String;
    //   2959: ldc_w 1059
    //   2962: ldc_w 1057
    //   2965: aload 22
    //   2967: getfield 80	com/google/android/gms/measurement/internal/zzfa:zzadj	Lcom/google/android/gms/measurement/internal/zzbt;
    //   2970: invokevirtual 507	com/google/android/gms/measurement/internal/zzbt:zzbx	()Lcom/google/android/gms/common/util/Clock;
    //   2973: invokeinterface 512 1 0
    //   2978: lload_2
    //   2979: invokestatic 404	java/lang/Long:valueOf	(J)Ljava/lang/Long;
    //   2982: invokespecial 515	com/google/android/gms/measurement/internal/zzfj:<init>	(Ljava/lang/String;Ljava/lang/String;Ljava/lang/String;JLjava/lang/Object;)V
    //   2985: astore_1
    //   2986: new 1061	com/google/android/gms/internal/measurement/zzgl
    //   2989: dup
    //   2990: invokespecial 1062	com/google/android/gms/internal/measurement/zzgl:<init>	()V
    //   2993: astore 18
    //   2995: aload 18
    //   2997: ldc_w 1057
    //   3000: putfield 1063	com/google/android/gms/internal/measurement/zzgl:name	Ljava/lang/String;
    //   3003: aload 18
    //   3005: aload 22
    //   3007: getfield 80	com/google/android/gms/measurement/internal/zzfa:zzadj	Lcom/google/android/gms/measurement/internal/zzbt;
    //   3010: invokevirtual 507	com/google/android/gms/measurement/internal/zzbt:zzbx	()Lcom/google/android/gms/common/util/Clock;
    //   3013: invokeinterface 512 1 0
    //   3018: invokestatic 404	java/lang/Long:valueOf	(J)Ljava/lang/Long;
    //   3021: putfield 1066	com/google/android/gms/internal/measurement/zzgl:zzayl	Ljava/lang/Long;
    //   3024: aload 18
    //   3026: aload_1
    //   3027: getfield 501	com/google/android/gms/measurement/internal/zzfj:value	Ljava/lang/Object;
    //   3030: checkcast 401	java/lang/Long
    //   3033: putfield 1067	com/google/android/gms/internal/measurement/zzgl:zzawx	Ljava/lang/Long;
    //   3036: iconst_0
    //   3037: istore 4
    //   3039: iload 4
    //   3041: aload 17
    //   3043: getfield 1071	com/google/android/gms/internal/measurement/zzgi:zzaxc	[Lcom/google/android/gms/internal/measurement/zzgl;
    //   3046: arraylength
    //   3047: if_icmpge +2369 -> 5416
    //   3050: ldc_w 1057
    //   3053: aload 17
    //   3055: getfield 1071	com/google/android/gms/internal/measurement/zzgi:zzaxc	[Lcom/google/android/gms/internal/measurement/zzgl;
    //   3058: iload 4
    //   3060: aaload
    //   3061: getfield 1063	com/google/android/gms/internal/measurement/zzgl:name	Ljava/lang/String;
    //   3064: invokevirtual 233	java/lang/String:equals	(Ljava/lang/Object;)Z
    //   3067: ifeq +2340 -> 5407
    //   3070: aload 17
    //   3072: getfield 1071	com/google/android/gms/internal/measurement/zzgi:zzaxc	[Lcom/google/android/gms/internal/measurement/zzgl;
    //   3075: iload 4
    //   3077: aload 18
    //   3079: aastore
    //   3080: iconst_1
    //   3081: istore 4
    //   3083: goto +3 -> 3086
    //   3086: iload 4
    //   3088: ifne +46 -> 3134
    //   3091: aload 17
    //   3093: aload 17
    //   3095: getfield 1071	com/google/android/gms/internal/measurement/zzgi:zzaxc	[Lcom/google/android/gms/internal/measurement/zzgl;
    //   3098: aload 17
    //   3100: getfield 1071	com/google/android/gms/internal/measurement/zzgi:zzaxc	[Lcom/google/android/gms/internal/measurement/zzgl;
    //   3103: arraylength
    //   3104: iconst_1
    //   3105: iadd
    //   3106: invokestatic 973	java/util/Arrays:copyOf	([Ljava/lang/Object;I)[Ljava/lang/Object;
    //   3109: checkcast 1072	[Lcom/google/android/gms/internal/measurement/zzgl;
    //   3112: putfield 1071	com/google/android/gms/internal/measurement/zzgi:zzaxc	[Lcom/google/android/gms/internal/measurement/zzgl;
    //   3115: aload 17
    //   3117: getfield 1071	com/google/android/gms/internal/measurement/zzgi:zzaxc	[Lcom/google/android/gms/internal/measurement/zzgl;
    //   3120: aload 19
    //   3122: getfield 909	com/google/android/gms/measurement/internal/zzfa$zza:zzaua	Lcom/google/android/gms/internal/measurement/zzgi;
    //   3125: getfield 1071	com/google/android/gms/internal/measurement/zzgi:zzaxc	[Lcom/google/android/gms/internal/measurement/zzgl;
    //   3128: arraylength
    //   3129: iconst_1
    //   3130: isub
    //   3131: aload 18
    //   3133: aastore
    //   3134: lload_2
    //   3135: lconst_0
    //   3136: lcmp
    //   3137: ifle +33 -> 3170
    //   3140: aload_0
    //   3141: invokevirtual 492	com/google/android/gms/measurement/internal/zzfa:zzjq	()Lcom/google/android/gms/measurement/internal/zzq;
    //   3144: aload_1
    //   3145: invokevirtual 552	com/google/android/gms/measurement/internal/zzq:zza	(Lcom/google/android/gms/measurement/internal/zzfj;)Z
    //   3148: pop
    //   3149: aload 22
    //   3151: getfield 80	com/google/android/gms/measurement/internal/zzfa:zzadj	Lcom/google/android/gms/measurement/internal/zzbt;
    //   3154: invokevirtual 152	com/google/android/gms/measurement/internal/zzbt:zzgo	()Lcom/google/android/gms/measurement/internal/zzap;
    //   3157: invokevirtual 783	com/google/android/gms/measurement/internal/zzap:zzjk	()Lcom/google/android/gms/measurement/internal/zzar;
    //   3160: ldc_w 1074
    //   3163: aload_1
    //   3164: getfield 501	com/google/android/gms/measurement/internal/zzfj:value	Ljava/lang/Object;
    //   3167: invokevirtual 172	com/google/android/gms/measurement/internal/zzar:zzg	(Ljava/lang/String;Ljava/lang/Object;)V
    //   3170: aload 17
    //   3172: aload 22
    //   3174: aload 17
    //   3176: getfield 918	com/google/android/gms/internal/measurement/zzgi:zztt	Ljava/lang/String;
    //   3179: aload 17
    //   3181: getfield 1071	com/google/android/gms/internal/measurement/zzgi:zzaxc	[Lcom/google/android/gms/internal/measurement/zzgl;
    //   3184: aload 17
    //   3186: getfield 915	com/google/android/gms/internal/measurement/zzgi:zzaxb	[Lcom/google/android/gms/internal/measurement/zzgf;
    //   3189: invokespecial 1076	com/google/android/gms/measurement/internal/zzfa:zza	(Ljava/lang/String;[Lcom/google/android/gms/internal/measurement/zzgl;[Lcom/google/android/gms/internal/measurement/zzgf;)[Lcom/google/android/gms/internal/measurement/zzgd;
    //   3192: putfield 1080	com/google/android/gms/internal/measurement/zzgi:zzaxt	[Lcom/google/android/gms/internal/measurement/zzgd;
    //   3195: aload 22
    //   3197: getfield 80	com/google/android/gms/measurement/internal/zzfa:zzadj	Lcom/google/android/gms/measurement/internal/zzbt;
    //   3200: invokevirtual 281	com/google/android/gms/measurement/internal/zzbt:zzgq	()Lcom/google/android/gms/measurement/internal/zzn;
    //   3203: aload 19
    //   3205: getfield 909	com/google/android/gms/measurement/internal/zzfa$zza:zzaua	Lcom/google/android/gms/internal/measurement/zzgi;
    //   3208: getfield 918	com/google/android/gms/internal/measurement/zzgi:zztt	Ljava/lang/String;
    //   3211: invokevirtual 1083	com/google/android/gms/measurement/internal/zzn:zzaw	(Ljava/lang/String;)Z
    //   3214: istore 14
    //   3216: iload 14
    //   3218: ifeq +1249 -> 4467
    //   3221: new 1085	java/util/HashMap
    //   3224: dup
    //   3225: invokespecial 1086	java/util/HashMap:<init>	()V
    //   3228: astore 23
    //   3230: aload 17
    //   3232: getfield 915	com/google/android/gms/internal/measurement/zzgi:zzaxb	[Lcom/google/android/gms/internal/measurement/zzgf;
    //   3235: arraylength
    //   3236: anewarray 884	com/google/android/gms/internal/measurement/zzgf
    //   3239: astore 24
    //   3241: aload 22
    //   3243: getfield 80	com/google/android/gms/measurement/internal/zzfa:zzadj	Lcom/google/android/gms/measurement/internal/zzbt;
    //   3246: invokevirtual 297	com/google/android/gms/measurement/internal/zzbt:zzgm	()Lcom/google/android/gms/measurement/internal/zzfk;
    //   3249: invokevirtual 1090	com/google/android/gms/measurement/internal/zzfk:zzmd	()Ljava/security/SecureRandom;
    //   3252: astore 22
    //   3254: aload 17
    //   3256: getfield 915	com/google/android/gms/internal/measurement/zzgi:zzaxb	[Lcom/google/android/gms/internal/measurement/zzgf;
    //   3259: astore 20
    //   3261: aload 20
    //   3263: arraylength
    //   3264: istore 6
    //   3266: iconst_0
    //   3267: istore 7
    //   3269: iconst_0
    //   3270: istore 5
    //   3272: aload 19
    //   3274: astore 18
    //   3276: aload_0
    //   3277: astore 19
    //   3279: iload 7
    //   3281: iload 6
    //   3283: if_icmpge +1085 -> 4368
    //   3286: aload 20
    //   3288: iload 7
    //   3290: aaload
    //   3291: astore 25
    //   3293: aload 25
    //   3295: getfield 886	com/google/android/gms/internal/measurement/zzgf:name	Ljava/lang/String;
    //   3298: ldc_w 1092
    //   3301: invokevirtual 233	java/lang/String:equals	(Ljava/lang/Object;)Z
    //   3304: istore 14
    //   3306: iload 14
    //   3308: ifeq +184 -> 3492
    //   3311: aload_0
    //   3312: invokevirtual 945	com/google/android/gms/measurement/internal/zzfa:zzjo	()Lcom/google/android/gms/measurement/internal/zzfg;
    //   3315: pop
    //   3316: aload 25
    //   3318: ldc_w 1094
    //   3321: invokestatic 1050	com/google/android/gms/measurement/internal/zzfg:zzb	(Lcom/google/android/gms/internal/measurement/zzgf;Ljava/lang/String;)Ljava/lang/Object;
    //   3324: checkcast 229	java/lang/String
    //   3327: astore 21
    //   3329: aload 23
    //   3331: aload 21
    //   3333: invokeinterface 1096 2 0
    //   3338: checkcast 1098	com/google/android/gms/measurement/internal/zzz
    //   3341: astore 19
    //   3343: aload 19
    //   3345: astore_1
    //   3346: aload 19
    //   3348: ifnonnull +32 -> 3380
    //   3351: aload_0
    //   3352: invokevirtual 492	com/google/android/gms/measurement/internal/zzfa:zzjq	()Lcom/google/android/gms/measurement/internal/zzq;
    //   3355: aload 18
    //   3357: getfield 909	com/google/android/gms/measurement/internal/zzfa$zza:zzaua	Lcom/google/android/gms/internal/measurement/zzgi;
    //   3360: getfield 918	com/google/android/gms/internal/measurement/zzgi:zztt	Ljava/lang/String;
    //   3363: aload 21
    //   3365: invokevirtual 1101	com/google/android/gms/measurement/internal/zzq:zzg	(Ljava/lang/String;Ljava/lang/String;)Lcom/google/android/gms/measurement/internal/zzz;
    //   3368: astore_1
    //   3369: aload 23
    //   3371: aload 21
    //   3373: aload_1
    //   3374: invokeinterface 708 3 0
    //   3379: pop
    //   3380: aload_1
    //   3381: getfield 1104	com/google/android/gms/measurement/internal/zzz:zzaij	Ljava/lang/Long;
    //   3384: ifnonnull +101 -> 3485
    //   3387: aload_1
    //   3388: getfield 1107	com/google/android/gms/measurement/internal/zzz:zzaik	Ljava/lang/Long;
    //   3391: invokevirtual 448	java/lang/Long:longValue	()J
    //   3394: lconst_1
    //   3395: lcmp
    //   3396: ifle +2026 -> 5422
    //   3399: aload_0
    //   3400: invokevirtual 945	com/google/android/gms/measurement/internal/zzfa:zzjo	()Lcom/google/android/gms/measurement/internal/zzfg;
    //   3403: pop
    //   3404: aload 25
    //   3406: aload 25
    //   3408: getfield 961	com/google/android/gms/internal/measurement/zzgf:zzawt	[Lcom/google/android/gms/internal/measurement/zzgg;
    //   3411: ldc_w 1109
    //   3414: aload_1
    //   3415: getfield 1107	com/google/android/gms/measurement/internal/zzz:zzaik	Ljava/lang/Long;
    //   3418: invokestatic 1112	com/google/android/gms/measurement/internal/zzfg:zza	([Lcom/google/android/gms/internal/measurement/zzgg;Ljava/lang/String;Ljava/lang/Object;)[Lcom/google/android/gms/internal/measurement/zzgg;
    //   3421: putfield 961	com/google/android/gms/internal/measurement/zzgf:zzawt	[Lcom/google/android/gms/internal/measurement/zzgg;
    //   3424: goto +3 -> 3427
    //   3427: aload_1
    //   3428: getfield 1116	com/google/android/gms/measurement/internal/zzz:zzail	Ljava/lang/Boolean;
    //   3431: ifnull +38 -> 3469
    //   3434: aload_1
    //   3435: getfield 1116	com/google/android/gms/measurement/internal/zzz:zzail	Ljava/lang/Boolean;
    //   3438: invokevirtual 756	java/lang/Boolean:booleanValue	()Z
    //   3441: ifeq +28 -> 3469
    //   3444: aload_0
    //   3445: invokevirtual 945	com/google/android/gms/measurement/internal/zzfa:zzjo	()Lcom/google/android/gms/measurement/internal/zzfg;
    //   3448: pop
    //   3449: aload 25
    //   3451: aload 25
    //   3453: getfield 961	com/google/android/gms/internal/measurement/zzgf:zzawt	[Lcom/google/android/gms/internal/measurement/zzgg;
    //   3456: ldc_w 1118
    //   3459: lconst_1
    //   3460: invokestatic 404	java/lang/Long:valueOf	(J)Ljava/lang/Long;
    //   3463: invokestatic 1112	com/google/android/gms/measurement/internal/zzfg:zza	([Lcom/google/android/gms/internal/measurement/zzgg;Ljava/lang/String;Ljava/lang/Object;)[Lcom/google/android/gms/internal/measurement/zzgg;
    //   3466: putfield 961	com/google/android/gms/internal/measurement/zzgf:zzawt	[Lcom/google/android/gms/internal/measurement/zzgg;
    //   3469: aload 24
    //   3471: iload 5
    //   3473: aload 25
    //   3475: aastore
    //   3476: iload 5
    //   3478: iconst_1
    //   3479: iadd
    //   3480: istore 4
    //   3482: goto +1995 -> 5477
    //   3485: iload 5
    //   3487: istore 4
    //   3489: goto -7 -> 3482
    //   3492: aload_0
    //   3493: invokespecial 690	com/google/android/gms/measurement/internal/zzfa:zzln	()Lcom/google/android/gms/measurement/internal/zzbn;
    //   3496: aload 18
    //   3498: getfield 909	com/google/android/gms/measurement/internal/zzfa$zza:zzaua	Lcom/google/android/gms/internal/measurement/zzgi;
    //   3501: getfield 918	com/google/android/gms/internal/measurement/zzgi:zztt	Ljava/lang/String;
    //   3504: invokevirtual 1122	com/google/android/gms/measurement/internal/zzbn:zzcj	(Ljava/lang/String;)J
    //   3507: lstore_2
    //   3508: aload 19
    //   3510: getfield 80	com/google/android/gms/measurement/internal/zzfa:zzadj	Lcom/google/android/gms/measurement/internal/zzbt;
    //   3513: invokevirtual 297	com/google/android/gms/measurement/internal/zzbt:zzgm	()Lcom/google/android/gms/measurement/internal/zzfk;
    //   3516: pop
    //   3517: aload 25
    //   3519: getfield 889	com/google/android/gms/internal/measurement/zzgf:zzawu	Ljava/lang/Long;
    //   3522: invokevirtual 448	java/lang/Long:longValue	()J
    //   3525: lload_2
    //   3526: invokestatic 1125	com/google/android/gms/measurement/internal/zzfk:zzc	(JJ)J
    //   3529: lstore 11
    //   3531: lconst_1
    //   3532: invokestatic 404	java/lang/Long:valueOf	(J)Ljava/lang/Long;
    //   3535: astore 21
    //   3537: ldc_w 1127
    //   3540: invokestatic 257	android/text/TextUtils:isEmpty	(Ljava/lang/CharSequence;)Z
    //   3543: istore 14
    //   3545: iload 14
    //   3547: ifne +1893 -> 5440
    //   3550: aload 21
    //   3552: ifnonnull +6 -> 3558
    //   3555: goto +1885 -> 5440
    //   3558: aload 25
    //   3560: getfield 961	com/google/android/gms/internal/measurement/zzgf:zzawt	[Lcom/google/android/gms/internal/measurement/zzgg;
    //   3563: astore_1
    //   3564: aload_1
    //   3565: arraylength
    //   3566: istore 8
    //   3568: iconst_0
    //   3569: istore 4
    //   3571: iload 4
    //   3573: iload 8
    //   3575: if_icmpge +1865 -> 5440
    //   3578: aload_1
    //   3579: iload 4
    //   3581: aaload
    //   3582: astore 26
    //   3584: ldc_w 1127
    //   3587: aload 26
    //   3589: getfield 591	com/google/android/gms/internal/measurement/zzgg:name	Ljava/lang/String;
    //   3592: invokevirtual 233	java/lang/String:equals	(Ljava/lang/Object;)Z
    //   3595: ifeq +1836 -> 5431
    //   3598: aload 21
    //   3600: instanceof 401
    //   3603: ifeq +16 -> 3619
    //   3606: aload 21
    //   3608: aload 26
    //   3610: getfield 596	com/google/android/gms/internal/measurement/zzgg:zzawx	Ljava/lang/Long;
    //   3613: invokevirtual 1128	java/lang/Object:equals	(Ljava/lang/Object;)Z
    //   3616: ifne +1809 -> 5425
    //   3619: aload 21
    //   3621: instanceof 229
    //   3624: ifeq +16 -> 3640
    //   3627: aload 21
    //   3629: aload 26
    //   3631: getfield 601	com/google/android/gms/internal/measurement/zzgg:zzamp	Ljava/lang/String;
    //   3634: invokevirtual 1128	java/lang/Object:equals	(Ljava/lang/Object;)Z
    //   3637: ifne +1788 -> 5425
    //   3640: aload 21
    //   3642: instanceof 435
    //   3645: ifeq +1795 -> 5440
    //   3648: aload 21
    //   3650: aload 26
    //   3652: getfield 1019	com/google/android/gms/internal/measurement/zzgg:zzauh	Ljava/lang/Double;
    //   3655: invokevirtual 1128	java/lang/Object:equals	(Ljava/lang/Object;)Z
    //   3658: ifeq +1782 -> 5440
    //   3661: goto +1764 -> 5425
    //   3664: iload 4
    //   3666: ifne +1780 -> 5446
    //   3669: aload_0
    //   3670: invokespecial 690	com/google/android/gms/measurement/internal/zzfa:zzln	()Lcom/google/android/gms/measurement/internal/zzbn;
    //   3673: aload 18
    //   3675: getfield 909	com/google/android/gms/measurement/internal/zzfa$zza:zzaua	Lcom/google/android/gms/internal/measurement/zzgi;
    //   3678: getfield 918	com/google/android/gms/internal/measurement/zzgi:zztt	Ljava/lang/String;
    //   3681: aload 25
    //   3683: getfield 886	com/google/android/gms/internal/measurement/zzgf:name	Ljava/lang/String;
    //   3686: invokevirtual 1131	com/google/android/gms/measurement/internal/zzbn:zzq	(Ljava/lang/String;Ljava/lang/String;)I
    //   3689: istore 4
    //   3691: goto +3 -> 3694
    //   3694: iload 4
    //   3696: ifgt +46 -> 3742
    //   3699: aload 19
    //   3701: getfield 80	com/google/android/gms/measurement/internal/zzfa:zzadj	Lcom/google/android/gms/measurement/internal/zzbt;
    //   3704: invokevirtual 152	com/google/android/gms/measurement/internal/zzbt:zzgo	()Lcom/google/android/gms/measurement/internal/zzap;
    //   3707: invokevirtual 158	com/google/android/gms/measurement/internal/zzap:zzjg	()Lcom/google/android/gms/measurement/internal/zzar;
    //   3710: ldc_w 1133
    //   3713: aload 25
    //   3715: getfield 886	com/google/android/gms/internal/measurement/zzgf:name	Ljava/lang/String;
    //   3718: iload 4
    //   3720: invokestatic 166	java/lang/Integer:valueOf	(I)Ljava/lang/Integer;
    //   3723: invokevirtual 312	com/google/android/gms/measurement/internal/zzar:zze	(Ljava/lang/String;Ljava/lang/Object;Ljava/lang/Object;)V
    //   3726: iload 5
    //   3728: iconst_1
    //   3729: iadd
    //   3730: istore 4
    //   3732: aload 24
    //   3734: iload 5
    //   3736: aload 25
    //   3738: aastore
    //   3739: goto +1738 -> 5477
    //   3742: aload 23
    //   3744: aload 25
    //   3746: getfield 886	com/google/android/gms/internal/measurement/zzgf:name	Ljava/lang/String;
    //   3749: invokeinterface 1096 2 0
    //   3754: checkcast 1098	com/google/android/gms/measurement/internal/zzz
    //   3757: astore 21
    //   3759: aload 21
    //   3761: astore_1
    //   3762: aload 21
    //   3764: ifnonnull +99 -> 3863
    //   3767: aload_0
    //   3768: invokevirtual 492	com/google/android/gms/measurement/internal/zzfa:zzjq	()Lcom/google/android/gms/measurement/internal/zzq;
    //   3771: aload 18
    //   3773: getfield 909	com/google/android/gms/measurement/internal/zzfa$zza:zzaua	Lcom/google/android/gms/internal/measurement/zzgi;
    //   3776: getfield 918	com/google/android/gms/internal/measurement/zzgi:zztt	Ljava/lang/String;
    //   3779: aload 25
    //   3781: getfield 886	com/google/android/gms/internal/measurement/zzgf:name	Ljava/lang/String;
    //   3784: invokevirtual 1101	com/google/android/gms/measurement/internal/zzq:zzg	(Ljava/lang/String;Ljava/lang/String;)Lcom/google/android/gms/measurement/internal/zzz;
    //   3787: astore 21
    //   3789: aload 21
    //   3791: astore_1
    //   3792: aload 21
    //   3794: ifnonnull +69 -> 3863
    //   3797: aload 19
    //   3799: getfield 80	com/google/android/gms/measurement/internal/zzfa:zzadj	Lcom/google/android/gms/measurement/internal/zzbt;
    //   3802: invokevirtual 152	com/google/android/gms/measurement/internal/zzbt:zzgo	()Lcom/google/android/gms/measurement/internal/zzap;
    //   3805: invokevirtual 158	com/google/android/gms/measurement/internal/zzap:zzjg	()Lcom/google/android/gms/measurement/internal/zzar;
    //   3808: ldc_w 1135
    //   3811: aload 18
    //   3813: getfield 909	com/google/android/gms/measurement/internal/zzfa$zza:zzaua	Lcom/google/android/gms/internal/measurement/zzgi;
    //   3816: getfield 918	com/google/android/gms/internal/measurement/zzgi:zztt	Ljava/lang/String;
    //   3819: aload 25
    //   3821: getfield 886	com/google/android/gms/internal/measurement/zzgf:name	Ljava/lang/String;
    //   3824: invokevirtual 312	com/google/android/gms/measurement/internal/zzar:zze	(Ljava/lang/String;Ljava/lang/Object;Ljava/lang/Object;)V
    //   3827: new 1098	com/google/android/gms/measurement/internal/zzz
    //   3830: dup
    //   3831: aload 18
    //   3833: getfield 909	com/google/android/gms/measurement/internal/zzfa$zza:zzaua	Lcom/google/android/gms/internal/measurement/zzgi;
    //   3836: getfield 918	com/google/android/gms/internal/measurement/zzgi:zztt	Ljava/lang/String;
    //   3839: aload 25
    //   3841: getfield 886	com/google/android/gms/internal/measurement/zzgf:name	Ljava/lang/String;
    //   3844: lconst_1
    //   3845: lconst_1
    //   3846: aload 25
    //   3848: getfield 889	com/google/android/gms/internal/measurement/zzgf:zzawu	Ljava/lang/Long;
    //   3851: invokevirtual 448	java/lang/Long:longValue	()J
    //   3854: lconst_0
    //   3855: aconst_null
    //   3856: aconst_null
    //   3857: aconst_null
    //   3858: aconst_null
    //   3859: invokespecial 1138	com/google/android/gms/measurement/internal/zzz:<init>	(Ljava/lang/String;Ljava/lang/String;JJJJLjava/lang/Long;Ljava/lang/Long;Ljava/lang/Long;Ljava/lang/Boolean;)V
    //   3862: astore_1
    //   3863: aload_0
    //   3864: invokevirtual 945	com/google/android/gms/measurement/internal/zzfa:zzjo	()Lcom/google/android/gms/measurement/internal/zzfg;
    //   3867: pop
    //   3868: aload 25
    //   3870: ldc_w 1140
    //   3873: invokestatic 1050	com/google/android/gms/measurement/internal/zzfg:zzb	(Lcom/google/android/gms/internal/measurement/zzgf;Ljava/lang/String;)Ljava/lang/Object;
    //   3876: checkcast 401	java/lang/Long
    //   3879: astore 26
    //   3881: aload 26
    //   3883: ifnull +1569 -> 5452
    //   3886: iconst_1
    //   3887: istore 14
    //   3889: goto +3 -> 3892
    //   3892: iload 14
    //   3894: invokestatic 742	java/lang/Boolean:valueOf	(Z)Ljava/lang/Boolean;
    //   3897: astore 21
    //   3899: iload 4
    //   3901: iconst_1
    //   3902: if_icmpne +82 -> 3984
    //   3905: iload 5
    //   3907: iconst_1
    //   3908: iadd
    //   3909: istore 8
    //   3911: aload 24
    //   3913: iload 5
    //   3915: aload 25
    //   3917: aastore
    //   3918: iload 8
    //   3920: istore 4
    //   3922: aload 21
    //   3924: invokevirtual 756	java/lang/Boolean:booleanValue	()Z
    //   3927: ifeq -188 -> 3739
    //   3930: aload_1
    //   3931: getfield 1104	com/google/android/gms/measurement/internal/zzz:zzaij	Ljava/lang/Long;
    //   3934: ifnonnull +21 -> 3955
    //   3937: aload_1
    //   3938: getfield 1107	com/google/android/gms/measurement/internal/zzz:zzaik	Ljava/lang/Long;
    //   3941: ifnonnull +14 -> 3955
    //   3944: iload 8
    //   3946: istore 4
    //   3948: aload_1
    //   3949: getfield 1116	com/google/android/gms/measurement/internal/zzz:zzail	Ljava/lang/Boolean;
    //   3952: ifnull -213 -> 3739
    //   3955: aload_1
    //   3956: aconst_null
    //   3957: aconst_null
    //   3958: aconst_null
    //   3959: invokevirtual 1143	com/google/android/gms/measurement/internal/zzz:zza	(Ljava/lang/Long;Ljava/lang/Long;Ljava/lang/Boolean;)Lcom/google/android/gms/measurement/internal/zzz;
    //   3962: astore_1
    //   3963: aload 23
    //   3965: aload 25
    //   3967: getfield 886	com/google/android/gms/internal/measurement/zzgf:name	Ljava/lang/String;
    //   3970: aload_1
    //   3971: invokeinterface 708 3 0
    //   3976: pop
    //   3977: iload 8
    //   3979: istore 4
    //   3981: goto -242 -> 3739
    //   3984: aload 22
    //   3986: iload 4
    //   3988: invokevirtual 1148	java/security/SecureRandom:nextInt	(I)I
    //   3991: istore 8
    //   3993: iload 8
    //   3995: ifne +103 -> 4098
    //   3998: aload_0
    //   3999: invokevirtual 945	com/google/android/gms/measurement/internal/zzfa:zzjo	()Lcom/google/android/gms/measurement/internal/zzfg;
    //   4002: pop
    //   4003: aload 25
    //   4005: getfield 961	com/google/android/gms/internal/measurement/zzgf:zzawt	[Lcom/google/android/gms/internal/measurement/zzgg;
    //   4008: astore 19
    //   4010: iload 4
    //   4012: i2l
    //   4013: lstore_2
    //   4014: aload 25
    //   4016: aload 19
    //   4018: ldc_w 1109
    //   4021: lload_2
    //   4022: invokestatic 404	java/lang/Long:valueOf	(J)Ljava/lang/Long;
    //   4025: invokestatic 1112	com/google/android/gms/measurement/internal/zzfg:zza	([Lcom/google/android/gms/internal/measurement/zzgg;Ljava/lang/String;Ljava/lang/Object;)[Lcom/google/android/gms/internal/measurement/zzgg;
    //   4028: putfield 961	com/google/android/gms/internal/measurement/zzgf:zzawt	[Lcom/google/android/gms/internal/measurement/zzgg;
    //   4031: aload 24
    //   4033: iload 5
    //   4035: aload 25
    //   4037: aastore
    //   4038: aload_1
    //   4039: astore 19
    //   4041: aload 21
    //   4043: invokevirtual 756	java/lang/Boolean:booleanValue	()Z
    //   4046: ifeq +15 -> 4061
    //   4049: aload_1
    //   4050: aconst_null
    //   4051: lload_2
    //   4052: invokestatic 404	java/lang/Long:valueOf	(J)Ljava/lang/Long;
    //   4055: aconst_null
    //   4056: invokevirtual 1143	com/google/android/gms/measurement/internal/zzz:zza	(Ljava/lang/Long;Ljava/lang/Long;Ljava/lang/Boolean;)Lcom/google/android/gms/measurement/internal/zzz;
    //   4059: astore 19
    //   4061: aload 23
    //   4063: aload 25
    //   4065: getfield 886	com/google/android/gms/internal/measurement/zzgf:name	Ljava/lang/String;
    //   4068: aload 19
    //   4070: aload 25
    //   4072: getfield 889	com/google/android/gms/internal/measurement/zzgf:zzawu	Ljava/lang/Long;
    //   4075: invokevirtual 448	java/lang/Long:longValue	()J
    //   4078: lload 11
    //   4080: invokevirtual 1151	com/google/android/gms/measurement/internal/zzz:zza	(JJ)Lcom/google/android/gms/measurement/internal/zzz;
    //   4083: invokeinterface 708 3 0
    //   4088: pop
    //   4089: iload 5
    //   4091: iconst_1
    //   4092: iadd
    //   4093: istore 4
    //   4095: goto +1382 -> 5477
    //   4098: aload 19
    //   4100: getfield 80	com/google/android/gms/measurement/internal/zzfa:zzadj	Lcom/google/android/gms/measurement/internal/zzbt;
    //   4103: invokevirtual 281	com/google/android/gms/measurement/internal/zzbt:zzgq	()Lcom/google/android/gms/measurement/internal/zzn;
    //   4106: aload 18
    //   4108: getfield 909	com/google/android/gms/measurement/internal/zzfa$zza:zzaua	Lcom/google/android/gms/internal/measurement/zzgi;
    //   4111: getfield 918	com/google/android/gms/internal/measurement/zzgi:zztt	Ljava/lang/String;
    //   4114: invokevirtual 1154	com/google/android/gms/measurement/internal/zzn:zzbh	(Ljava/lang/String;)Z
    //   4117: ifeq +50 -> 4167
    //   4120: aload_1
    //   4121: getfield 1157	com/google/android/gms/measurement/internal/zzz:zzaii	Ljava/lang/Long;
    //   4124: astore 27
    //   4126: aload 27
    //   4128: ifnull +14 -> 4142
    //   4131: aload_1
    //   4132: getfield 1157	com/google/android/gms/measurement/internal/zzz:zzaii	Ljava/lang/Long;
    //   4135: invokevirtual 448	java/lang/Long:longValue	()J
    //   4138: lstore_2
    //   4139: goto +1319 -> 5458
    //   4142: aload 19
    //   4144: getfield 80	com/google/android/gms/measurement/internal/zzfa:zzadj	Lcom/google/android/gms/measurement/internal/zzbt;
    //   4147: invokevirtual 297	com/google/android/gms/measurement/internal/zzbt:zzgm	()Lcom/google/android/gms/measurement/internal/zzfk;
    //   4150: pop
    //   4151: aload 25
    //   4153: getfield 1160	com/google/android/gms/internal/measurement/zzgf:zzawv	Ljava/lang/Long;
    //   4156: invokevirtual 448	java/lang/Long:longValue	()J
    //   4159: lload_2
    //   4160: invokestatic 1125	com/google/android/gms/measurement/internal/zzfk:zzc	(JJ)J
    //   4163: lstore_2
    //   4164: goto +1294 -> 5458
    //   4167: aload_1
    //   4168: getfield 1163	com/google/android/gms/measurement/internal/zzz:zzaih	J
    //   4171: lstore_2
    //   4172: aload 25
    //   4174: getfield 889	com/google/android/gms/internal/measurement/zzgf:zzawu	Ljava/lang/Long;
    //   4177: invokevirtual 448	java/lang/Long:longValue	()J
    //   4180: lload_2
    //   4181: lsub
    //   4182: invokestatic 1167	java/lang/Math:abs	(J)J
    //   4185: ldc2_w 1168
    //   4188: lcmp
    //   4189: iflt +1282 -> 5471
    //   4192: goto +1273 -> 5465
    //   4195: iload 8
    //   4197: ifeq +131 -> 4328
    //   4200: aload_0
    //   4201: invokevirtual 945	com/google/android/gms/measurement/internal/zzfa:zzjo	()Lcom/google/android/gms/measurement/internal/zzfg;
    //   4204: pop
    //   4205: aload 25
    //   4207: aload 25
    //   4209: getfield 961	com/google/android/gms/internal/measurement/zzgf:zzawt	[Lcom/google/android/gms/internal/measurement/zzgg;
    //   4212: ldc_w 1118
    //   4215: lconst_1
    //   4216: invokestatic 404	java/lang/Long:valueOf	(J)Ljava/lang/Long;
    //   4219: invokestatic 1112	com/google/android/gms/measurement/internal/zzfg:zza	([Lcom/google/android/gms/internal/measurement/zzgg;Ljava/lang/String;Ljava/lang/Object;)[Lcom/google/android/gms/internal/measurement/zzgg;
    //   4222: putfield 961	com/google/android/gms/internal/measurement/zzgf:zzawt	[Lcom/google/android/gms/internal/measurement/zzgg;
    //   4225: aload_0
    //   4226: invokevirtual 945	com/google/android/gms/measurement/internal/zzfa:zzjo	()Lcom/google/android/gms/measurement/internal/zzfg;
    //   4229: pop
    //   4230: aload 25
    //   4232: getfield 961	com/google/android/gms/internal/measurement/zzgf:zzawt	[Lcom/google/android/gms/internal/measurement/zzgg;
    //   4235: astore 19
    //   4237: iload 4
    //   4239: i2l
    //   4240: lstore_2
    //   4241: aload 25
    //   4243: aload 19
    //   4245: ldc_w 1109
    //   4248: lload_2
    //   4249: invokestatic 404	java/lang/Long:valueOf	(J)Ljava/lang/Long;
    //   4252: invokestatic 1112	com/google/android/gms/measurement/internal/zzfg:zza	([Lcom/google/android/gms/internal/measurement/zzgg;Ljava/lang/String;Ljava/lang/Object;)[Lcom/google/android/gms/internal/measurement/zzgg;
    //   4255: putfield 961	com/google/android/gms/internal/measurement/zzgf:zzawt	[Lcom/google/android/gms/internal/measurement/zzgg;
    //   4258: aload 24
    //   4260: iload 5
    //   4262: aload 25
    //   4264: aastore
    //   4265: aload_1
    //   4266: astore 19
    //   4268: aload 21
    //   4270: invokevirtual 756	java/lang/Boolean:booleanValue	()Z
    //   4273: ifeq +18 -> 4291
    //   4276: aload_1
    //   4277: aconst_null
    //   4278: lload_2
    //   4279: invokestatic 404	java/lang/Long:valueOf	(J)Ljava/lang/Long;
    //   4282: iconst_1
    //   4283: invokestatic 742	java/lang/Boolean:valueOf	(Z)Ljava/lang/Boolean;
    //   4286: invokevirtual 1143	com/google/android/gms/measurement/internal/zzz:zza	(Ljava/lang/Long;Ljava/lang/Long;Ljava/lang/Boolean;)Lcom/google/android/gms/measurement/internal/zzz;
    //   4289: astore 19
    //   4291: aload 23
    //   4293: aload 25
    //   4295: getfield 886	com/google/android/gms/internal/measurement/zzgf:name	Ljava/lang/String;
    //   4298: aload 19
    //   4300: aload 25
    //   4302: getfield 889	com/google/android/gms/internal/measurement/zzgf:zzawu	Ljava/lang/Long;
    //   4305: invokevirtual 448	java/lang/Long:longValue	()J
    //   4308: lload 11
    //   4310: invokevirtual 1151	com/google/android/gms/measurement/internal/zzz:zza	(JJ)Lcom/google/android/gms/measurement/internal/zzz;
    //   4313: invokeinterface 708 3 0
    //   4318: pop
    //   4319: iload 5
    //   4321: iconst_1
    //   4322: iadd
    //   4323: istore 4
    //   4325: goto +1152 -> 5477
    //   4328: iload 5
    //   4330: istore 4
    //   4332: aload 21
    //   4334: invokevirtual 756	java/lang/Boolean:booleanValue	()Z
    //   4337: ifeq +1140 -> 5477
    //   4340: aload 23
    //   4342: aload 25
    //   4344: getfield 886	com/google/android/gms/internal/measurement/zzgf:name	Ljava/lang/String;
    //   4347: aload_1
    //   4348: aload 26
    //   4350: aconst_null
    //   4351: aconst_null
    //   4352: invokevirtual 1143	com/google/android/gms/measurement/internal/zzz:zza	(Ljava/lang/Long;Ljava/lang/Long;Ljava/lang/Boolean;)Lcom/google/android/gms/measurement/internal/zzz;
    //   4355: invokeinterface 708 3 0
    //   4360: pop
    //   4361: iload 5
    //   4363: istore 4
    //   4365: goto +1112 -> 5477
    //   4368: aload 17
    //   4370: astore 19
    //   4372: iload 5
    //   4374: aload 19
    //   4376: getfield 915	com/google/android/gms/internal/measurement/zzgi:zzaxb	[Lcom/google/android/gms/internal/measurement/zzgf;
    //   4379: arraylength
    //   4380: if_icmpge +18 -> 4398
    //   4383: aload 19
    //   4385: aload 24
    //   4387: iload 5
    //   4389: invokestatic 973	java/util/Arrays:copyOf	([Ljava/lang/Object;I)[Ljava/lang/Object;
    //   4392: checkcast 1055	[Lcom/google/android/gms/internal/measurement/zzgf;
    //   4395: putfield 915	com/google/android/gms/internal/measurement/zzgi:zzaxb	[Lcom/google/android/gms/internal/measurement/zzgf;
    //   4398: aload 23
    //   4400: invokeinterface 1173 1 0
    //   4405: invokeinterface 1179 1 0
    //   4410: astore 20
    //   4412: aload 19
    //   4414: astore 17
    //   4416: iload 13
    //   4418: istore 14
    //   4420: aload 18
    //   4422: astore_1
    //   4423: aload 20
    //   4425: invokeinterface 1184 1 0
    //   4430: ifeq +44 -> 4474
    //   4433: aload 20
    //   4435: invokeinterface 1187 1 0
    //   4440: checkcast 1189	java/util/Map$Entry
    //   4443: astore_1
    //   4444: aload_0
    //   4445: invokevirtual 492	com/google/android/gms/measurement/internal/zzfa:zzjq	()Lcom/google/android/gms/measurement/internal/zzq;
    //   4448: aload_1
    //   4449: invokeinterface 1192 1 0
    //   4454: checkcast 1098	com/google/android/gms/measurement/internal/zzz
    //   4457: invokevirtual 1195	com/google/android/gms/measurement/internal/zzq:zza	(Lcom/google/android/gms/measurement/internal/zzz;)V
    //   4460: goto -48 -> 4412
    //   4463: astore_1
    //   4464: goto +733 -> 5197
    //   4467: aload 19
    //   4469: astore_1
    //   4470: iload 13
    //   4472: istore 14
    //   4474: aload 17
    //   4476: ldc2_w 1196
    //   4479: invokestatic 404	java/lang/Long:valueOf	(J)Ljava/lang/Long;
    //   4482: putfield 1200	com/google/android/gms/internal/measurement/zzgi:zzaxe	Ljava/lang/Long;
    //   4485: aload 17
    //   4487: ldc2_w 1201
    //   4490: invokestatic 404	java/lang/Long:valueOf	(J)Ljava/lang/Long;
    //   4493: putfield 1205	com/google/android/gms/internal/measurement/zzgi:zzaxf	Ljava/lang/Long;
    //   4496: iconst_0
    //   4497: istore 4
    //   4499: aload 17
    //   4501: getfield 915	com/google/android/gms/internal/measurement/zzgi:zzaxb	[Lcom/google/android/gms/internal/measurement/zzgf;
    //   4504: arraylength
    //   4505: istore 5
    //   4507: iload 4
    //   4509: iload 5
    //   4511: if_icmpge +82 -> 4593
    //   4514: aload 17
    //   4516: getfield 915	com/google/android/gms/internal/measurement/zzgi:zzaxb	[Lcom/google/android/gms/internal/measurement/zzgf;
    //   4519: iload 4
    //   4521: aaload
    //   4522: astore 18
    //   4524: aload 18
    //   4526: getfield 889	com/google/android/gms/internal/measurement/zzgf:zzawu	Ljava/lang/Long;
    //   4529: invokevirtual 448	java/lang/Long:longValue	()J
    //   4532: aload 17
    //   4534: getfield 1200	com/google/android/gms/internal/measurement/zzgi:zzaxe	Ljava/lang/Long;
    //   4537: invokevirtual 448	java/lang/Long:longValue	()J
    //   4540: lcmp
    //   4541: ifge +13 -> 4554
    //   4544: aload 17
    //   4546: aload 18
    //   4548: getfield 889	com/google/android/gms/internal/measurement/zzgf:zzawu	Ljava/lang/Long;
    //   4551: putfield 1200	com/google/android/gms/internal/measurement/zzgi:zzaxe	Ljava/lang/Long;
    //   4554: aload 18
    //   4556: getfield 889	com/google/android/gms/internal/measurement/zzgf:zzawu	Ljava/lang/Long;
    //   4559: invokevirtual 448	java/lang/Long:longValue	()J
    //   4562: aload 17
    //   4564: getfield 1205	com/google/android/gms/internal/measurement/zzgi:zzaxf	Ljava/lang/Long;
    //   4567: invokevirtual 448	java/lang/Long:longValue	()J
    //   4570: lcmp
    //   4571: ifle +13 -> 4584
    //   4574: aload 17
    //   4576: aload 18
    //   4578: getfield 889	com/google/android/gms/internal/measurement/zzgf:zzawu	Ljava/lang/Long;
    //   4581: putfield 1205	com/google/android/gms/internal/measurement/zzgi:zzaxf	Ljava/lang/Long;
    //   4584: iload 4
    //   4586: iconst_1
    //   4587: iadd
    //   4588: istore 4
    //   4590: goto -91 -> 4499
    //   4593: aload_1
    //   4594: getfield 909	com/google/android/gms/measurement/internal/zzfa$zza:zzaua	Lcom/google/android/gms/internal/measurement/zzgi;
    //   4597: getfield 918	com/google/android/gms/internal/measurement/zzgi:zztt	Ljava/lang/String;
    //   4600: astore 19
    //   4602: aload_0
    //   4603: invokevirtual 492	com/google/android/gms/measurement/internal/zzfa:zzjq	()Lcom/google/android/gms/measurement/internal/zzq;
    //   4606: aload 19
    //   4608: invokevirtual 751	com/google/android/gms/measurement/internal/zzq:zzbl	(Ljava/lang/String;)Lcom/google/android/gms/measurement/internal/zzg;
    //   4611: astore 20
    //   4613: aload 20
    //   4615: ifnonnull +32 -> 4647
    //   4618: aload_0
    //   4619: getfield 80	com/google/android/gms/measurement/internal/zzfa:zzadj	Lcom/google/android/gms/measurement/internal/zzbt;
    //   4622: invokevirtual 152	com/google/android/gms/measurement/internal/zzbt:zzgo	()Lcom/google/android/gms/measurement/internal/zzap;
    //   4625: invokevirtual 183	com/google/android/gms/measurement/internal/zzap:zzjd	()Lcom/google/android/gms/measurement/internal/zzar;
    //   4628: ldc_w 1207
    //   4631: aload_1
    //   4632: getfield 909	com/google/android/gms/measurement/internal/zzfa$zza:zzaua	Lcom/google/android/gms/internal/measurement/zzgi;
    //   4635: getfield 918	com/google/android/gms/internal/measurement/zzgi:zztt	Ljava/lang/String;
    //   4638: invokestatic 223	com/google/android/gms/measurement/internal/zzap:zzbv	(Ljava/lang/String;)Ljava/lang/Object;
    //   4641: invokevirtual 172	com/google/android/gms/measurement/internal/zzar:zzg	(Ljava/lang/String;Ljava/lang/Object;)V
    //   4644: goto +143 -> 4787
    //   4647: aload 17
    //   4649: getfield 915	com/google/android/gms/internal/measurement/zzgi:zzaxb	[Lcom/google/android/gms/internal/measurement/zzgf;
    //   4652: arraylength
    //   4653: ifle +134 -> 4787
    //   4656: aload 20
    //   4658: invokevirtual 1210	com/google/android/gms/measurement/internal/zzg:zzgz	()J
    //   4661: lstore_2
    //   4662: lload_2
    //   4663: lconst_0
    //   4664: lcmp
    //   4665: ifeq +825 -> 5490
    //   4668: lload_2
    //   4669: invokestatic 404	java/lang/Long:valueOf	(J)Ljava/lang/Long;
    //   4672: astore 18
    //   4674: goto +3 -> 4677
    //   4677: aload 17
    //   4679: aload 18
    //   4681: putfield 1213	com/google/android/gms/internal/measurement/zzgi:zzaxh	Ljava/lang/Long;
    //   4684: aload 20
    //   4686: invokevirtual 1216	com/google/android/gms/measurement/internal/zzg:zzgy	()J
    //   4689: lstore 11
    //   4691: lload 11
    //   4693: lconst_0
    //   4694: lcmp
    //   4695: ifne +801 -> 5496
    //   4698: goto +3 -> 4701
    //   4701: lload_2
    //   4702: lconst_0
    //   4703: lcmp
    //   4704: ifeq +798 -> 5502
    //   4707: lload_2
    //   4708: invokestatic 404	java/lang/Long:valueOf	(J)Ljava/lang/Long;
    //   4711: astore 18
    //   4713: goto +3 -> 4716
    //   4716: aload 17
    //   4718: aload 18
    //   4720: putfield 1219	com/google/android/gms/internal/measurement/zzgi:zzaxg	Ljava/lang/Long;
    //   4723: aload 20
    //   4725: invokevirtual 1222	com/google/android/gms/measurement/internal/zzg:zzhh	()V
    //   4728: aload 17
    //   4730: aload 20
    //   4732: invokevirtual 1225	com/google/android/gms/measurement/internal/zzg:zzhe	()J
    //   4735: l2i
    //   4736: invokestatic 166	java/lang/Integer:valueOf	(I)Ljava/lang/Integer;
    //   4739: putfield 1229	com/google/android/gms/internal/measurement/zzgi:zzaxr	Ljava/lang/Integer;
    //   4742: aload 20
    //   4744: aload 17
    //   4746: getfield 1200	com/google/android/gms/internal/measurement/zzgi:zzaxe	Ljava/lang/Long;
    //   4749: invokevirtual 448	java/lang/Long:longValue	()J
    //   4752: invokevirtual 1233	com/google/android/gms/measurement/internal/zzg:zzs	(J)V
    //   4755: aload 20
    //   4757: aload 17
    //   4759: getfield 1205	com/google/android/gms/internal/measurement/zzgi:zzaxf	Ljava/lang/Long;
    //   4762: invokevirtual 448	java/lang/Long:longValue	()J
    //   4765: invokevirtual 1236	com/google/android/gms/measurement/internal/zzg:zzt	(J)V
    //   4768: aload 17
    //   4770: aload 20
    //   4772: invokevirtual 1239	com/google/android/gms/measurement/internal/zzg:zzhp	()Ljava/lang/String;
    //   4775: putfield 1242	com/google/android/gms/internal/measurement/zzgi:zzagv	Ljava/lang/String;
    //   4778: aload_0
    //   4779: invokevirtual 492	com/google/android/gms/measurement/internal/zzfa:zzjq	()Lcom/google/android/gms/measurement/internal/zzq;
    //   4782: aload 20
    //   4784: invokevirtual 1244	com/google/android/gms/measurement/internal/zzq:zza	(Lcom/google/android/gms/measurement/internal/zzg;)V
    //   4787: aload_0
    //   4788: astore 18
    //   4790: aload 17
    //   4792: getfield 915	com/google/android/gms/internal/measurement/zzgi:zzaxb	[Lcom/google/android/gms/internal/measurement/zzgf;
    //   4795: arraylength
    //   4796: ifle +123 -> 4919
    //   4799: aload 18
    //   4801: getfield 80	com/google/android/gms/measurement/internal/zzfa:zzadj	Lcom/google/android/gms/measurement/internal/zzbt;
    //   4804: invokevirtual 277	com/google/android/gms/measurement/internal/zzbt:zzgr	()Lcom/google/android/gms/measurement/internal/zzk;
    //   4807: pop
    //   4808: aload_0
    //   4809: invokespecial 690	com/google/android/gms/measurement/internal/zzfa:zzln	()Lcom/google/android/gms/measurement/internal/zzbn;
    //   4812: aload_1
    //   4813: getfield 909	com/google/android/gms/measurement/internal/zzfa$zza:zzaua	Lcom/google/android/gms/internal/measurement/zzgi;
    //   4816: getfield 918	com/google/android/gms/internal/measurement/zzgi:zztt	Ljava/lang/String;
    //   4819: invokevirtual 694	com/google/android/gms/measurement/internal/zzbn:zzcf	(Ljava/lang/String;)Lcom/google/android/gms/internal/measurement/zzgb;
    //   4822: astore 20
    //   4824: aload 20
    //   4826: ifnull +27 -> 4853
    //   4829: aload 20
    //   4831: getfield 1249	com/google/android/gms/internal/measurement/zzgb:zzawe	Ljava/lang/Long;
    //   4834: ifnonnull +6 -> 4840
    //   4837: goto +16 -> 4853
    //   4840: aload 17
    //   4842: aload 20
    //   4844: getfield 1249	com/google/android/gms/internal/measurement/zzgb:zzawe	Ljava/lang/Long;
    //   4847: putfield 1252	com/google/android/gms/internal/measurement/zzgi:zzaxy	Ljava/lang/Long;
    //   4850: goto +57 -> 4907
    //   4853: aload_1
    //   4854: getfield 909	com/google/android/gms/measurement/internal/zzfa$zza:zzaua	Lcom/google/android/gms/internal/measurement/zzgi;
    //   4857: getfield 1255	com/google/android/gms/internal/measurement/zzgi:zzafx	Ljava/lang/String;
    //   4860: invokestatic 257	android/text/TextUtils:isEmpty	(Ljava/lang/CharSequence;)Z
    //   4863: ifeq +17 -> 4880
    //   4866: aload 17
    //   4868: ldc2_w 81
    //   4871: invokestatic 404	java/lang/Long:valueOf	(J)Ljava/lang/Long;
    //   4874: putfield 1252	com/google/android/gms/internal/measurement/zzgi:zzaxy	Ljava/lang/Long;
    //   4877: goto +30 -> 4907
    //   4880: aload 18
    //   4882: getfield 80	com/google/android/gms/measurement/internal/zzfa:zzadj	Lcom/google/android/gms/measurement/internal/zzbt;
    //   4885: invokevirtual 152	com/google/android/gms/measurement/internal/zzbt:zzgo	()Lcom/google/android/gms/measurement/internal/zzap;
    //   4888: invokevirtual 158	com/google/android/gms/measurement/internal/zzap:zzjg	()Lcom/google/android/gms/measurement/internal/zzar;
    //   4891: ldc_w 1257
    //   4894: aload_1
    //   4895: getfield 909	com/google/android/gms/measurement/internal/zzfa$zza:zzaua	Lcom/google/android/gms/internal/measurement/zzgi;
    //   4898: getfield 918	com/google/android/gms/internal/measurement/zzgi:zztt	Ljava/lang/String;
    //   4901: invokestatic 223	com/google/android/gms/measurement/internal/zzap:zzbv	(Ljava/lang/String;)Ljava/lang/Object;
    //   4904: invokevirtual 172	com/google/android/gms/measurement/internal/zzar:zzg	(Ljava/lang/String;Ljava/lang/Object;)V
    //   4907: aload_0
    //   4908: invokevirtual 492	com/google/android/gms/measurement/internal/zzfa:zzjq	()Lcom/google/android/gms/measurement/internal/zzq;
    //   4911: aload 17
    //   4913: iload 14
    //   4915: invokevirtual 1260	com/google/android/gms/measurement/internal/zzq:zza	(Lcom/google/android/gms/internal/measurement/zzgi;Z)Z
    //   4918: pop
    //   4919: aload_0
    //   4920: invokevirtual 492	com/google/android/gms/measurement/internal/zzfa:zzjq	()Lcom/google/android/gms/measurement/internal/zzq;
    //   4923: astore 17
    //   4925: aload_1
    //   4926: getfield 1263	com/google/android/gms/measurement/internal/zzfa$zza:zzaub	Ljava/util/List;
    //   4929: astore_1
    //   4930: aload_1
    //   4931: invokestatic 67	com/google/android/gms/common/internal/Preconditions:checkNotNull	(Ljava/lang/Object;)Ljava/lang/Object;
    //   4934: pop
    //   4935: aload 17
    //   4937: invokevirtual 349	com/google/android/gms/measurement/internal/zzco:zzaf	()V
    //   4940: aload 17
    //   4942: invokevirtual 531	com/google/android/gms/measurement/internal/zzez:zzcl	()V
    //   4945: new 325	java/lang/StringBuilder
    //   4948: dup
    //   4949: ldc_w 1265
    //   4952: invokespecial 1266	java/lang/StringBuilder:<init>	(Ljava/lang/String;)V
    //   4955: astore 18
    //   4957: iconst_0
    //   4958: istore 4
    //   4960: iload 4
    //   4962: aload_1
    //   4963: invokeinterface 911 1 0
    //   4968: if_icmpge +46 -> 5014
    //   4971: iload 4
    //   4973: ifeq +12 -> 4985
    //   4976: aload 18
    //   4978: ldc_w 1268
    //   4981: invokevirtual 337	java/lang/StringBuilder:append	(Ljava/lang/String;)Ljava/lang/StringBuilder;
    //   4984: pop
    //   4985: aload 18
    //   4987: aload_1
    //   4988: iload 4
    //   4990: invokeinterface 924 2 0
    //   4995: checkcast 401	java/lang/Long
    //   4998: invokevirtual 448	java/lang/Long:longValue	()J
    //   5001: invokevirtual 1271	java/lang/StringBuilder:append	(J)Ljava/lang/StringBuilder;
    //   5004: pop
    //   5005: iload 4
    //   5007: iconst_1
    //   5008: iadd
    //   5009: istore 4
    //   5011: goto -51 -> 4960
    //   5014: aload 18
    //   5016: ldc_w 1273
    //   5019: invokevirtual 337	java/lang/StringBuilder:append	(Ljava/lang/String;)Ljava/lang/StringBuilder;
    //   5022: pop
    //   5023: aload 17
    //   5025: invokevirtual 535	com/google/android/gms/measurement/internal/zzq:getWritableDatabase	()Landroid/database/sqlite/SQLiteDatabase;
    //   5028: ldc_w 872
    //   5031: aload 18
    //   5033: invokevirtual 340	java/lang/StringBuilder:toString	()Ljava/lang/String;
    //   5036: aconst_null
    //   5037: invokevirtual 1277	android/database/sqlite/SQLiteDatabase:delete	(Ljava/lang/String;Ljava/lang/String;[Ljava/lang/String;)I
    //   5040: istore 4
    //   5042: iload 4
    //   5044: aload_1
    //   5045: invokeinterface 911 1 0
    //   5050: if_icmpeq +31 -> 5081
    //   5053: aload 17
    //   5055: invokevirtual 547	com/google/android/gms/measurement/internal/zzco:zzgo	()Lcom/google/android/gms/measurement/internal/zzap;
    //   5058: invokevirtual 183	com/google/android/gms/measurement/internal/zzap:zzjd	()Lcom/google/android/gms/measurement/internal/zzar;
    //   5061: ldc_w 1279
    //   5064: iload 4
    //   5066: invokestatic 166	java/lang/Integer:valueOf	(I)Ljava/lang/Integer;
    //   5069: aload_1
    //   5070: invokeinterface 911 1 0
    //   5075: invokestatic 166	java/lang/Integer:valueOf	(I)Ljava/lang/Integer;
    //   5078: invokevirtual 312	com/google/android/gms/measurement/internal/zzar:zze	(Ljava/lang/String;Ljava/lang/Object;Ljava/lang/Object;)V
    //   5081: aload_0
    //   5082: invokevirtual 492	com/google/android/gms/measurement/internal/zzfa:zzjq	()Lcom/google/android/gms/measurement/internal/zzq;
    //   5085: astore_1
    //   5086: aload_1
    //   5087: invokevirtual 535	com/google/android/gms/measurement/internal/zzq:getWritableDatabase	()Landroid/database/sqlite/SQLiteDatabase;
    //   5090: astore 17
    //   5092: aload 17
    //   5094: ldc_w 1281
    //   5097: iconst_2
    //   5098: anewarray 229	java/lang/String
    //   5101: dup
    //   5102: iconst_0
    //   5103: aload 19
    //   5105: aastore
    //   5106: dup
    //   5107: iconst_1
    //   5108: aload 19
    //   5110: aastore
    //   5111: invokevirtual 546	android/database/sqlite/SQLiteDatabase:execSQL	(Ljava/lang/String;[Ljava/lang/Object;)V
    //   5114: goto +25 -> 5139
    //   5117: astore 17
    //   5119: aload_1
    //   5120: invokevirtual 547	com/google/android/gms/measurement/internal/zzco:zzgo	()Lcom/google/android/gms/measurement/internal/zzap;
    //   5123: invokevirtual 183	com/google/android/gms/measurement/internal/zzap:zzjd	()Lcom/google/android/gms/measurement/internal/zzar;
    //   5126: ldc_w 1283
    //   5129: aload 19
    //   5131: invokestatic 223	com/google/android/gms/measurement/internal/zzap:zzbv	(Ljava/lang/String;)Ljava/lang/Object;
    //   5134: aload 17
    //   5136: invokevirtual 312	com/google/android/gms/measurement/internal/zzar:zze	(Ljava/lang/String;Ljava/lang/Object;Ljava/lang/Object;)V
    //   5139: aload_0
    //   5140: invokevirtual 492	com/google/android/gms/measurement/internal/zzfa:zzjq	()Lcom/google/android/gms/measurement/internal/zzq;
    //   5143: invokevirtual 1286	com/google/android/gms/measurement/internal/zzq:setTransactionSuccessful	()V
    //   5146: aload_0
    //   5147: invokevirtual 492	com/google/android/gms/measurement/internal/zzfa:zzjq	()Lcom/google/android/gms/measurement/internal/zzq;
    //   5150: invokevirtual 1289	com/google/android/gms/measurement/internal/zzq:endTransaction	()V
    //   5153: iconst_1
    //   5154: ireturn
    //   5155: astore_1
    //   5156: goto +41 -> 5197
    //   5159: aload_0
    //   5160: invokevirtual 492	com/google/android/gms/measurement/internal/zzfa:zzjq	()Lcom/google/android/gms/measurement/internal/zzq;
    //   5163: invokevirtual 1286	com/google/android/gms/measurement/internal/zzq:setTransactionSuccessful	()V
    //   5166: aload_0
    //   5167: invokevirtual 492	com/google/android/gms/measurement/internal/zzfa:zzjq	()Lcom/google/android/gms/measurement/internal/zzq;
    //   5170: invokevirtual 1289	com/google/android/gms/measurement/internal/zzq:endTransaction	()V
    //   5173: iconst_0
    //   5174: ireturn
    //   5175: astore_1
    //   5176: goto -4015 -> 1161
    //   5179: aload 17
    //   5181: ifnull +13 -> 5194
    //   5184: aload 17
    //   5186: invokeinterface 818 1 0
    //   5191: goto +3 -> 5194
    //   5194: aload_1
    //   5195: athrow
    //   5196: astore_1
    //   5197: aload_0
    //   5198: invokevirtual 492	com/google/android/gms/measurement/internal/zzfa:zzjq	()Lcom/google/android/gms/measurement/internal/zzq;
    //   5201: invokevirtual 1289	com/google/android/gms/measurement/internal/zzq:endTransaction	()V
    //   5204: aload_1
    //   5205: athrow
    //   5206: lload 11
    //   5208: ldc2_w 81
    //   5211: lcmp
    //   5212: ifeq +11 -> 5223
    //   5215: ldc_w 1291
    //   5218: astore 17
    //   5220: goto -4843 -> 377
    //   5223: ldc -21
    //   5225: astore 17
    //   5227: goto -4850 -> 377
    //   5230: iconst_0
    //   5231: istore 4
    //   5233: goto -4002 -> 1231
    //   5236: iconst_1
    //   5237: istore 4
    //   5239: goto -4008 -> 1231
    //   5242: iconst_0
    //   5243: istore 4
    //   5245: goto -3817 -> 1428
    //   5248: iconst_1
    //   5249: istore 4
    //   5251: goto -3823 -> 1428
    //   5254: goto +144 -> 5398
    //   5257: iconst_m1
    //   5258: istore 4
    //   5260: iload 4
    //   5262: tableswitch	default:+26->5288, 0:+32->5294, 1:+32->5294, 2:+32->5294
    //   5288: iconst_0
    //   5289: istore 4
    //   5291: goto +6 -> 5297
    //   5294: iconst_1
    //   5295: istore 4
    //   5297: iload 4
    //   5299: ifeq +6 -> 5305
    //   5302: goto -3698 -> 1604
    //   5305: goto -2938 -> 2367
    //   5308: iload 7
    //   5310: iconst_1
    //   5311: iadd
    //   5312: istore 7
    //   5314: iload 10
    //   5316: istore 8
    //   5318: goto -3678 -> 1640
    //   5321: iload 4
    //   5323: iconst_1
    //   5324: iadd
    //   5325: istore 4
    //   5327: goto -3353 -> 1974
    //   5330: iconst_1
    //   5331: istore 14
    //   5333: goto -3254 -> 2079
    //   5336: iload 7
    //   5338: iconst_1
    //   5339: iadd
    //   5340: istore 7
    //   5342: aload 20
    //   5344: astore 18
    //   5346: goto -3138 -> 2208
    //   5349: iload 4
    //   5351: iconst_1
    //   5352: iadd
    //   5353: istore 4
    //   5355: iload 9
    //   5357: istore 7
    //   5359: goto -2949 -> 2410
    //   5362: goto -2703 -> 2659
    //   5365: iload 8
    //   5367: iconst_m1
    //   5368: if_icmpne -2821 -> 2547
    //   5371: iconst_1
    //   5372: istore 4
    //   5374: goto -2762 -> 2612
    //   5377: iconst_0
    //   5378: istore 4
    //   5380: goto -2809 -> 2571
    //   5383: iconst_0
    //   5384: istore 4
    //   5386: goto -2774 -> 2612
    //   5389: iconst_1
    //   5390: istore 4
    //   5392: goto -2780 -> 2612
    //   5395: goto -2727 -> 2668
    //   5398: iload 5
    //   5400: iconst_1
    //   5401: iadd
    //   5402: istore 5
    //   5404: goto -4114 -> 1290
    //   5407: iload 4
    //   5409: iconst_1
    //   5410: iadd
    //   5411: istore 4
    //   5413: goto -2374 -> 3039
    //   5416: iconst_0
    //   5417: istore 4
    //   5419: goto -2333 -> 3086
    //   5422: goto -1995 -> 3427
    //   5425: iconst_1
    //   5426: istore 4
    //   5428: goto -1764 -> 3664
    //   5431: iload 4
    //   5433: iconst_1
    //   5434: iadd
    //   5435: istore 4
    //   5437: goto -1866 -> 3571
    //   5440: iconst_0
    //   5441: istore 4
    //   5443: goto -1779 -> 3664
    //   5446: iconst_1
    //   5447: istore 4
    //   5449: goto -1755 -> 3694
    //   5452: iconst_0
    //   5453: istore 14
    //   5455: goto -1563 -> 3892
    //   5458: lload_2
    //   5459: lload 11
    //   5461: lcmp
    //   5462: ifeq +9 -> 5471
    //   5465: iconst_1
    //   5466: istore 8
    //   5468: goto -1273 -> 4195
    //   5471: iconst_0
    //   5472: istore 8
    //   5474: goto -1279 -> 4195
    //   5477: iload 7
    //   5479: iconst_1
    //   5480: iadd
    //   5481: istore 7
    //   5483: iload 4
    //   5485: istore 5
    //   5487: goto -2211 -> 3276
    //   5490: aconst_null
    //   5491: astore 18
    //   5493: goto -816 -> 4677
    //   5496: lload 11
    //   5498: lstore_2
    //   5499: goto -798 -> 4701
    //   5502: aconst_null
    //   5503: astore 18
    //   5505: goto -789 -> 4716
    //   5508: astore_1
    //   5509: goto -312 -> 5197
    // Local variable table:
    //   start	length	slot	name	signature
    //   0	5512	0	this	zzfa
    //   0	5512	1	paramString	String
    //   0	5512	2	paramLong	long
    //   1231	4253	4	i	int
    //   1280	4206	5	j	int
    //   1286	1998	6	k	int
    //   1632	3850	7	m	int
    //   1635	3838	8	n	int
    //   1638	3718	9	i1	int
    //   1677	3638	10	i2	int
    //   36	5461	11	l	long
    //   65	4406	13	bool1	boolean
    //   1976	3478	14	bool2	boolean
    //   1277	1589	15	bool3	boolean
    //   1500	890	16	bool4	boolean
    //   11	920	17	localObject1	Object
    //   997	18	17	localIOException1	IOException
    //   1051	4042	17	localObject2	Object
    //   5117	68	17	localSQLiteException1	SQLiteException
    //   5218	8	17	str	String
    //   88	26	18	arrayOfString	String[]
    //   119	6	18	localObject3	Object
    //   136	5368	18	localObject4	Object
    //   23	5107	19	localObject5	Object
    //   140	922	20	localObject6	Object
    //   1071	22	20	localIOException2	IOException
    //   1112	6	20	localSQLiteException2	SQLiteException
    //   1134	4209	20	localObject7	Object
    //   612	222	21	localObject8	Object
    //   1056	10	21	localSQLiteException3	SQLiteException
    //   1127	10	21	localSQLiteException4	SQLiteException
    //   2219	2114	21	localObject9	Object
    //   1	3984	22	localObject10	Object
    //   640	3759	23	localObject11	Object
    //   29	4357	24	localObject12	Object
    //   59	4284	25	localSQLiteDatabase	SQLiteDatabase
    //   3582	767	26	localLong1	Long
    //   4124	3	27	localLong2	Long
    // Exception table:
    //   from	to	target	type
    //   84	90	119	finally
    //   93	102	119	finally
    //   105	113	119	finally
    //   245	254	119	finally
    //   281	291	119	finally
    //   294	304	119	finally
    //   307	314	119	finally
    //   443	452	119	finally
    //   479	489	119	finally
    //   496	503	119	finally
    //   84	90	130	android/database/sqlite/SQLiteException
    //   93	102	130	android/database/sqlite/SQLiteException
    //   105	113	130	android/database/sqlite/SQLiteException
    //   294	304	324	android/database/sqlite/SQLiteException
    //   307	314	324	android/database/sqlite/SQLiteException
    //   928	936	997	java/io/IOException
    //   846	874	1048	finally
    //   889	928	1048	finally
    //   928	936	1048	finally
    //   936	977	1048	finally
    //   999	1019	1048	finally
    //   1019	1028	1048	finally
    //   846	874	1056	android/database/sqlite/SQLiteException
    //   889	928	1056	android/database/sqlite/SQLiteException
    //   928	936	1056	android/database/sqlite/SQLiteException
    //   936	977	1056	android/database/sqlite/SQLiteException
    //   999	1019	1056	android/database/sqlite/SQLiteException
    //   1019	1028	1056	android/database/sqlite/SQLiteException
    //   646	654	1071	java/io/IOException
    //   553	563	1112	android/database/sqlite/SQLiteException
    //   567	585	1112	android/database/sqlite/SQLiteException
    //   604	614	1112	android/database/sqlite/SQLiteException
    //   618	629	1112	android/database/sqlite/SQLiteException
    //   633	642	1112	android/database/sqlite/SQLiteException
    //   646	654	1112	android/database/sqlite/SQLiteException
    //   658	668	1112	android/database/sqlite/SQLiteException
    //   672	690	1112	android/database/sqlite/SQLiteException
    //   694	701	1112	android/database/sqlite/SQLiteException
    //   705	714	1112	android/database/sqlite/SQLiteException
    //   732	755	1112	android/database/sqlite/SQLiteException
    //   775	790	1112	android/database/sqlite/SQLiteException
    //   798	846	1112	android/database/sqlite/SQLiteException
    //   1077	1097	1112	android/database/sqlite/SQLiteException
    //   505	549	1123	finally
    //   505	549	1127	android/database/sqlite/SQLiteException
    //   245	254	1150	android/database/sqlite/SQLiteException
    //   281	291	1150	android/database/sqlite/SQLiteException
    //   443	452	1150	android/database/sqlite/SQLiteException
    //   479	489	1150	android/database/sqlite/SQLiteException
    //   496	503	1150	android/database/sqlite/SQLiteException
    //   54	67	1157	finally
    //   145	157	1157	finally
    //   178	238	1157	finally
    //   345	350	1157	finally
    //   354	362	1157	finally
    //   365	370	1157	finally
    //   377	436	1157	finally
    //   54	67	1164	android/database/sqlite/SQLiteException
    //   145	157	1164	android/database/sqlite/SQLiteException
    //   178	238	1164	android/database/sqlite/SQLiteException
    //   345	350	1164	android/database/sqlite/SQLiteException
    //   354	362	1164	android/database/sqlite/SQLiteException
    //   365	370	1164	android/database/sqlite/SQLiteException
    //   377	436	1164	android/database/sqlite/SQLiteException
    //   3221	3266	4463	finally
    //   3293	3306	4463	finally
    //   3492	3545	4463	finally
    //   3742	3759	4463	finally
    //   3863	3881	4463	finally
    //   3892	3899	4463	finally
    //   3984	3993	4463	finally
    //   4098	4126	4463	finally
    //   4142	4164	4463	finally
    //   4167	4192	4463	finally
    //   4200	4237	4463	finally
    //   4241	4258	4463	finally
    //   4268	4291	4463	finally
    //   4291	4319	4463	finally
    //   4332	4361	4463	finally
    //   4372	4398	4463	finally
    //   4398	4412	4463	finally
    //   4423	4460	4463	finally
    //   4514	4554	4463	finally
    //   4554	4584	4463	finally
    //   5092	5114	5117	android/database/sqlite/SQLiteException
    //   4474	4496	5155	finally
    //   4499	4507	5155	finally
    //   4593	4613	5155	finally
    //   553	563	5175	finally
    //   567	585	5175	finally
    //   604	614	5175	finally
    //   618	629	5175	finally
    //   633	642	5175	finally
    //   646	654	5175	finally
    //   658	668	5175	finally
    //   672	690	5175	finally
    //   694	701	5175	finally
    //   705	714	5175	finally
    //   732	755	5175	finally
    //   775	790	5175	finally
    //   798	846	5175	finally
    //   1077	1097	5175	finally
    //   1175	1195	5175	finally
    //   13	54	5196	finally
    //   264	271	5196	finally
    //   462	469	5196	finally
    //   590	597	5196	finally
    //   879	886	5196	finally
    //   987	994	5196	finally
    //   1038	1045	5196	finally
    //   1102	1109	5196	finally
    //   1200	1207	5196	finally
    //   1207	1228	5196	finally
    //   1236	1279	5196	finally
    //   1290	1425	5196	finally
    //   1433	1477	5196	finally
    //   1480	1502	5196	finally
    //   1507	1529	5196	finally
    //   1556	1566	5196	finally
    //   1572	1582	5196	finally
    //   1588	1598	5196	finally
    //   1604	1621	5196	finally
    //   1621	1631	5196	finally
    //   1653	1676	5196	finally
    //   1686	1709	5196	finally
    //   1729	1822	5196	finally
    //   1827	1920	5196	finally
    //   1920	1971	5196	finally
    //   1978	2021	5196	finally
    //   2026	2039	5196	finally
    //   2039	2066	5196	finally
    //   2066	2072	5196	finally
    //   2083	2094	5196	finally
    //   2107	2199	5196	finally
    //   2221	2235	5196	finally
    //   2246	2260	5196	finally
    //   2284	2309	5196	finally
    //   2317	2336	5196	finally
    //   2339	2367	5196	finally
    //   2367	2389	5196	finally
    //   2394	2401	5196	finally
    //   2410	2435	5196	finally
    //   2446	2463	5196	finally
    //   2483	2544	5196	finally
    //   2547	2556	5196	finally
    //   2560	2568	5196	finally
    //   2571	2596	5196	finally
    //   2599	2609	5196	finally
    //   2620	2659	5196	finally
    //   2659	2665	5196	finally
    //   2679	2710	5196	finally
    //   2713	2730	5196	finally
    //   2734	2762	5196	finally
    //   2768	2776	5196	finally
    //   2779	2807	5196	finally
    //   2810	2820	5196	finally
    //   2832	2865	5196	finally
    //   2870	2886	5196	finally
    //   2890	2897	5196	finally
    //   2900	2947	5196	finally
    //   2950	2986	5196	finally
    //   2986	3036	5196	finally
    //   3039	3080	5196	finally
    //   3091	3134	5196	finally
    //   3140	3170	5196	finally
    //   3170	3216	5196	finally
    //   3311	3343	5196	finally
    //   3351	3380	5196	finally
    //   3380	3424	5196	finally
    //   3427	3469	5196	finally
    //   3558	3568	5196	finally
    //   3584	3619	5196	finally
    //   3619	3640	5196	finally
    //   3640	3661	5196	finally
    //   3669	3691	5196	finally
    //   3699	3726	5196	finally
    //   3767	3789	5196	finally
    //   3797	3863	5196	finally
    //   3922	3944	5196	finally
    //   3948	3955	5196	finally
    //   3955	3977	5196	finally
    //   3998	4010	5196	finally
    //   4014	4031	5196	finally
    //   4041	4061	5196	finally
    //   4061	4089	5196	finally
    //   4131	4139	5196	finally
    //   4618	4644	5508	finally
    //   4647	4662	5508	finally
    //   4668	4674	5508	finally
    //   4677	4691	5508	finally
    //   4707	4713	5508	finally
    //   4716	4787	5508	finally
    //   4790	4824	5508	finally
    //   4829	4837	5508	finally
    //   4840	4850	5508	finally
    //   4853	4877	5508	finally
    //   4880	4907	5508	finally
    //   4907	4919	5508	finally
    //   4919	4957	5508	finally
    //   4960	4971	5508	finally
    //   4976	4985	5508	finally
    //   4985	5005	5508	finally
    //   5014	5081	5508	finally
    //   5081	5092	5508	finally
    //   5092	5114	5508	finally
    //   5119	5139	5508	finally
    //   5139	5146	5508	finally
    //   5159	5166	5508	finally
    //   5184	5191	5508	finally
    //   5194	5196	5508	finally
  }
  
  @WorkerThread
  private final zzg zzg(zzh paramZzh)
  {
    zzaf();
    zzlr();
    Preconditions.checkNotNull(paramZzh);
    Preconditions.checkNotEmpty(packageName);
    zzg localZzg = zzjq().zzbl(packageName);
    String str = zzadj.zzgp().zzbz(packageName);
    if (localZzg == null)
    {
      localZzg = new zzg(zzadj, packageName);
      localZzg.zzam(zzadj.zzgm().zzmf());
      localZzg.zzap(str);
    }
    for (;;)
    {
      i = 1;
      break label139;
      if (str.equals(localZzg.zzgx())) {
        break;
      }
      localZzg.zzap(str);
      localZzg.zzam(zzadj.zzgm().zzmf());
    }
    int i = 0;
    label139:
    if (!TextUtils.equals(zzafx, localZzg.getGmpAppId()))
    {
      localZzg.zzan(zzafx);
      i = 1;
    }
    int j = i;
    if (!TextUtils.equals(zzagk, localZzg.zzgw()))
    {
      localZzg.zzao(zzagk);
      j = 1;
    }
    i = j;
    if (!TextUtils.isEmpty(zzafz))
    {
      i = j;
      if (!zzafz.equals(localZzg.getFirebaseInstanceId()))
      {
        localZzg.zzaq(zzafz);
        i = 1;
      }
    }
    j = i;
    if (zzadt != 0L)
    {
      j = i;
      if (zzadt != localZzg.zzhc())
      {
        localZzg.zzv(zzadt);
        j = 1;
      }
    }
    i = j;
    if (!TextUtils.isEmpty(zzts))
    {
      i = j;
      if (!zzts.equals(localZzg.zzak()))
      {
        localZzg.setAppVersion(zzts);
        i = 1;
      }
    }
    if (zzagd != localZzg.zzha())
    {
      localZzg.zzu(zzagd);
      i = 1;
    }
    j = i;
    if (zzage != null)
    {
      j = i;
      if (!zzage.equals(localZzg.zzhb()))
      {
        localZzg.zzar(zzage);
        j = 1;
      }
    }
    i = j;
    if (zzagf != localZzg.zzhd())
    {
      localZzg.zzw(zzagf);
      i = 1;
    }
    if (zzagg != localZzg.isMeasurementEnabled())
    {
      localZzg.setMeasurementEnabled(zzagg);
      i = 1;
    }
    j = i;
    if (!TextUtils.isEmpty(zzagv))
    {
      j = i;
      if (!zzagv.equals(localZzg.zzho()))
      {
        localZzg.zzas(zzagv);
        j = 1;
      }
    }
    if (zzagh != localZzg.zzhq())
    {
      localZzg.zzag(zzagh);
      j = 1;
    }
    if (zzagi != localZzg.zzhr())
    {
      localZzg.zze(zzagi);
      j = 1;
    }
    if (zzagj != localZzg.zzhs())
    {
      localZzg.zzf(zzagj);
      j = 1;
    }
    if (j != 0) {
      zzjq().zza(localZzg);
    }
    return localZzg;
  }
  
  private final zzbn zzln()
  {
    zza(zzatd);
    return zzatd;
  }
  
  private final zzay zzlp()
  {
    if (zzatg != null) {
      return zzatg;
    }
    throw new IllegalStateException("Network broadcast receiver not created");
  }
  
  private final zzew zzlq()
  {
    zza(zzath);
    return zzath;
  }
  
  private final long zzls()
  {
    long l3 = zzadj.zzbx().currentTimeMillis();
    zzba localZzba = zzadj.zzgp();
    localZzba.zzcl();
    localZzba.zzaf();
    long l2 = zzani.get();
    long l1 = l2;
    if (l2 == 0L)
    {
      l1 = 1L + localZzba.zzgm().zzmd().nextInt(86400000);
      zzani.set(l1);
    }
    return (l3 + l1) / 1000L / 60L / 60L / 24L;
  }
  
  private final boolean zzlu()
  {
    zzaf();
    zzlr();
    return (zzjq().zzii()) || (!TextUtils.isEmpty(zzjq().zzid()));
  }
  
  @WorkerThread
  private final void zzlv()
  {
    zzaf();
    zzlr();
    if (!zzlz()) {
      return;
    }
    long l1;
    if (zzatl > 0L)
    {
      l1 = 3600000L - Math.abs(zzadj.zzbx().elapsedRealtime() - zzatl);
      if (l1 > 0L)
      {
        zzadj.zzgo().zzjl().zzg("Upload has been suspended. Will update scheduling later in approximately ms", Long.valueOf(l1));
        zzlp().unregister();
        zzlq().cancel();
        return;
      }
      zzatl = 0L;
    }
    if ((zzadj.zzkr()) && (zzlu()))
    {
      long l3 = zzadj.zzbx().currentTimeMillis();
      long l2 = Math.max(0L, ((Long)zzaf.zzakd.get()).longValue());
      int i;
      if ((!zzjq().zzij()) && (!zzjq().zzie())) {
        i = 0;
      } else {
        i = 1;
      }
      if (i != 0)
      {
        String str = zzadj.zzgq().zzhy();
        if ((!TextUtils.isEmpty(str)) && (!".none.".equals(str))) {
          l1 = Math.max(0L, ((Long)zzaf.zzajy.get()).longValue());
        } else {
          l1 = Math.max(0L, ((Long)zzaf.zzajx.get()).longValue());
        }
      }
      else
      {
        l1 = Math.max(0L, ((Long)zzaf.zzajw.get()).longValue());
      }
      long l6 = zzadj.zzgp().zzane.get();
      long l5 = zzadj.zzgp().zzanf.get();
      long l4 = Math.max(zzjq().zzig(), zzjq().zzih());
      if (l4 == 0L) {}
      for (;;)
      {
        l1 = 0L;
        break;
        l4 = l3 - Math.abs(l4 - l3);
        l6 = Math.abs(l6 - l3);
        l5 = l3 - Math.abs(l5 - l3);
        l6 = Math.max(l3 - l6, l5);
        l3 = l4 + l2;
        l2 = l3;
        if (i != 0)
        {
          l2 = l3;
          if (l6 > 0L) {
            l2 = Math.min(l4, l6) + l1;
          }
        }
        if (!zzjo().zzb(l6, l1)) {
          l2 = l6 + l1;
        }
        l1 = l2;
        if (l5 == 0L) {
          break;
        }
        l1 = l2;
        if (l5 < l4) {
          break;
        }
        i = 0;
        while (i < Math.min(20, Math.max(0, ((Integer)zzaf.zzakf.get()).intValue())))
        {
          l1 = l2 + Math.max(0L, ((Long)zzaf.zzake.get()).longValue()) * (1L << i);
          if (l1 > l5) {
            break label530;
          }
          i += 1;
          l2 = l1;
        }
      }
      label530:
      if (l1 == 0L)
      {
        zzadj.zzgo().zzjl().zzbx("Next upload time is 0");
        zzlp().unregister();
        zzlq().cancel();
        return;
      }
      if (!zzlo().zzfb())
      {
        zzadj.zzgo().zzjl().zzbx("No network");
        zzlp().zzey();
        zzlq().cancel();
        return;
      }
      l3 = zzadj.zzgp().zzang.get();
      l4 = Math.max(0L, ((Long)zzaf.zzaju.get()).longValue());
      l2 = l1;
      if (!zzjo().zzb(l3, l4)) {
        l2 = Math.max(l1, l3 + l4);
      }
      zzlp().unregister();
      l2 -= zzadj.zzbx().currentTimeMillis();
      l1 = l2;
      if (l2 <= 0L)
      {
        l1 = Math.max(0L, ((Long)zzaf.zzajz.get()).longValue());
        zzadj.zzgp().zzane.set(zzadj.zzbx().currentTimeMillis());
      }
      zzadj.zzgo().zzjl().zzg("Upload scheduled in approximately ms", Long.valueOf(l1));
      zzlq().zzh(l1);
      return;
    }
    zzadj.zzgo().zzjl().zzbx("Nothing to upload or uploading impossible");
    zzlp().unregister();
    zzlq().cancel();
  }
  
  @WorkerThread
  private final void zzlw()
  {
    zzaf();
    if ((!zzatp) && (!zzatq) && (!zzatr))
    {
      zzadj.zzgo().zzjl().zzbx("Stopping uploading service(s)");
      if (zzatm == null) {
        return;
      }
      Iterator localIterator = zzatm.iterator();
      while (localIterator.hasNext()) {
        ((Runnable)localIterator.next()).run();
      }
      zzatm.clear();
      return;
    }
    zzadj.zzgo().zzjl().zzd("Not stopping services. fetch, network, upload", Boolean.valueOf(zzatp), Boolean.valueOf(zzatq), Boolean.valueOf(zzatr));
  }
  
  @WorkerThread
  @VisibleForTesting
  private final boolean zzlx()
  {
    zzaf();
    File localFile = new File(zzadj.getContext().getFilesDir(), "google_app_measurement.db");
    try
    {
      zzatt = new RandomAccessFile(localFile, "rw").getChannel();
      zzats = zzatt.tryLock();
      if (zzats != null)
      {
        zzadj.zzgo().zzjl().zzbx("Storage concurrent access okay");
        return true;
      }
      zzadj.zzgo().zzjd().zzbx("Storage concurrent data access panic");
    }
    catch (IOException localIOException)
    {
      zzadj.zzgo().zzjd().zzg("Failed to access storage lock file", localIOException);
    }
    catch (FileNotFoundException localFileNotFoundException)
    {
      zzadj.zzgo().zzjd().zzg("Failed to acquire storage lock", localFileNotFoundException);
    }
    return false;
  }
  
  @WorkerThread
  private final boolean zzlz()
  {
    zzaf();
    zzlr();
    return zzatk;
  }
  
  public static zzfa zzm(Context paramContext)
  {
    Preconditions.checkNotNull(paramContext);
    Preconditions.checkNotNull(paramContext.getApplicationContext());
    if (zzatc == null) {
      try
      {
        if (zzatc == null) {
          zzatc = new zzfa(new zzff(paramContext));
        }
      }
      finally {}
    }
    return zzatc;
  }
  
  public final Context getContext()
  {
    return zzadj.getContext();
  }
  
  @WorkerThread
  protected final void start()
  {
    zzadj.zzgn().zzaf();
    zzjq().zzif();
    if (zzadj.zzgp().zzane.get() == 0L) {
      zzadj.zzgp().zzane.set(zzadj.zzbx().currentTimeMillis());
    }
    zzlv();
  }
  
  @WorkerThread
  @VisibleForTesting
  final void zza(int paramInt, Throwable paramThrowable, byte[] paramArrayOfByte, String paramString)
  {
    zzaf();
    zzlr();
    Object localObject = paramArrayOfByte;
    if (paramArrayOfByte == null) {}
    try
    {
      localObject = new byte[0];
      paramArrayOfByte = zzatu;
      zzatu = null;
      int j = 1;
      if (((paramInt == 200) || (paramInt == 204)) && (paramThrowable == null)) {
        try
        {
          zzadj.zzgp().zzane.set(zzadj.zzbx().currentTimeMillis());
          zzadj.zzgp().zzanf.set(0L);
          zzlv();
          zzadj.zzgo().zzjl().zze("Successful upload. Got network response. code, size", Integer.valueOf(paramInt), Integer.valueOf(localObject.length));
          zzjq().beginTransaction();
          try
          {
            paramThrowable = paramArrayOfByte.iterator();
            while (paramThrowable.hasNext())
            {
              paramArrayOfByte = (Long)paramThrowable.next();
              try
              {
                paramString = zzjq();
                long l = paramArrayOfByte.longValue();
                paramString.zzaf();
                paramString.zzcl();
                localObject = paramString.getWritableDatabase();
                try
                {
                  if (((SQLiteDatabase)localObject).delete("queue", "rowid=?", new String[] { String.valueOf(l) }) == 1) {
                    continue;
                  }
                  throw new SQLiteException("Deleted fewer rows from queue than expected");
                }
                catch (SQLiteException localSQLiteException)
                {
                  paramString.zzgo().zzjd().zzg("Failed to delete a bundle in a queue table", localSQLiteException);
                  throw localSQLiteException;
                }
                if (zzatv == null) {
                  break label272;
                }
              }
              catch (SQLiteException paramString) {}
              if (!zzatv.contains(paramArrayOfByte)) {
                label272:
                throw paramString;
              }
            }
            zzjq().setTransactionSuccessful();
            zzjq().endTransaction();
            zzatv = null;
            if ((zzlo().zzfb()) && (zzlu()))
            {
              zzlt();
            }
            else
            {
              zzatw = -1L;
              zzlv();
            }
            zzatl = 0L;
          }
          finally
          {
            zzjq().endTransaction();
          }
          zzadj.zzgo().zzjl().zze("Network upload failed. Will retry later. code, error", Integer.valueOf(paramInt), paramThrowable);
        }
        catch (SQLiteException paramThrowable)
        {
          zzadj.zzgo().zzjd().zzg("Database error while trying to delete uploaded bundles", paramThrowable);
          zzatl = zzadj.zzbx().elapsedRealtime();
          zzadj.zzgo().zzjl().zzg("Disable upload, time", Long.valueOf(zzatl));
        }
      }
      zzadj.zzgp().zzanf.set(zzadj.zzbx().currentTimeMillis());
      i = j;
      if (paramInt != 503)
      {
        if (paramInt != 429) {
          break label560;
        }
        i = j;
      }
    }
    finally
    {
      for (;;)
      {
        continue;
        int i = 0;
      }
    }
    if (i != 0) {
      zzadj.zzgp().zzang.set(zzadj.zzbx().currentTimeMillis());
    }
    if (zzadj.zzgq().zzaz(paramString)) {
      zzjq().zzc(paramArrayOfByte);
    }
    zzlv();
    zzatq = false;
    zzlw();
    return;
    zzatq = false;
    zzlw();
    throw paramThrowable;
  }
  
  @WorkerThread
  public final byte[] zza(@NonNull zzad paramZzad, @Size(min=1L) String paramString)
  {
    zzlr();
    zzaf();
    zzadj.zzga();
    Preconditions.checkNotNull(paramZzad);
    Preconditions.checkNotEmpty(paramString);
    zzgh localZzgh = new zzgh();
    zzjq().beginTransaction();
    Object localObject1;
    long l1;
    Object localObject3;
    int i;
    Object localObject4;
    label1119:
    label1606:
    long l2;
    try
    {
      localZzg = zzjq().zzbl(paramString);
      if (localZzg == null)
      {
        zzadj.zzgo().zzjk().zzg("Log and bundle not available. package_name", paramString);
        return new byte[0];
      }
      if (!localZzg.isMeasurementEnabled())
      {
        zzadj.zzgo().zzjk().zzg("Log and bundle disabled. package_name", paramString);
        return new byte[0];
      }
      if ((("_iap".equals(name)) || ("ecommerce_purchase".equals(name))) && (!zza(paramString, paramZzad))) {
        zzadj.zzgo().zzjg().zzg("Failed to handle purchase event at single event bundle creation. appId", zzap.zzbv(paramString));
      }
      bool = zzadj.zzgq().zzax(paramString);
      localObject1 = Long.valueOf(0L);
      localObject2 = localObject1;
      if (bool)
      {
        localObject2 = localObject1;
        if ("_e".equals(name)) {
          if ((zzaid != null) && (zzaid.size() != 0))
          {
            if (zzaid.getLong("_et") == null)
            {
              zzadj.zzgo().zzjg().zzg("The engagement event does not include duration. appId", zzap.zzbv(paramString));
              localObject2 = localObject1;
            }
            else
            {
              localObject2 = zzaid.getLong("_et");
            }
          }
          else
          {
            zzadj.zzgo().zzjg().zzg("The engagement event does not contain any parameters. appId", zzap.zzbv(paramString));
            localObject2 = localObject1;
          }
        }
      }
      localZzgi = new zzgi();
      zzawy = new zzgi[] { localZzgi };
      zzaxa = Integer.valueOf(1);
      zzaxi = "android";
      zztt = localZzg.zzal();
      zzage = localZzg.zzhb();
      zzts = localZzg.zzak();
      l1 = localZzg.zzha();
      if (l1 == -2147483648L) {
        localObject1 = null;
      } else {
        localObject1 = Integer.valueOf((int)l1);
      }
      zzaxu = ((Integer)localObject1);
      zzaxm = Long.valueOf(localZzg.zzhc());
      zzafx = localZzg.getGmpAppId();
      if (TextUtils.isEmpty(zzafx)) {
        zzawj = localZzg.zzgw();
      }
      zzaxq = Long.valueOf(localZzg.zzhd());
      if ((zzadj.isEnabled()) && (zzn.zzhz()) && (zzadj.zzgq().zzav(zztt))) {
        zzaya = null;
      }
      localObject1 = zzadj.zzgp().zzby(localZzg.zzal());
      if ((localZzg.zzhr()) && (localObject1 != null) && (!TextUtils.isEmpty((CharSequence)first)))
      {
        zzaxo = ((String)first);
        zzaxp = ((Boolean)second);
      }
      zzadj.zzgk().zzcl();
      zzaxk = Build.MODEL;
      zzadj.zzgk().zzcl();
      zzaxj = Build.VERSION.RELEASE;
      zzaxl = Integer.valueOf((int)zzadj.zzgk().zzis());
      zzaia = zzadj.zzgk().zzit();
      zzafw = localZzg.getAppInstanceId();
      zzafz = localZzg.getFirebaseInstanceId();
      localList = zzjq().zzbk(localZzg.zzal());
      zzaxc = new zzgl[localList.size()];
      if (!bool) {
        break label1839;
      }
      localObject3 = zzjq().zzi(zztt, "_lte");
      if ((localObject3 != null) && (value != null))
      {
        localObject1 = localObject3;
        if (((Long)localObject2).longValue() > 0L) {
          localObject1 = new zzfj(zztt, "auto", "_lte", zzadj.zzbx().currentTimeMillis(), Long.valueOf(((Long)value).longValue() + ((Long)localObject2).longValue()));
        }
      }
      else
      {
        localObject1 = new zzfj(zztt, "auto", "_lte", zzadj.zzbx().currentTimeMillis(), localObject2);
      }
    }
    finally
    {
      zzg localZzg;
      boolean bool;
      Object localObject2;
      zzgi localZzgi;
      List localList;
      zzgl localZzgl;
      label1629:
      zzjq().endTransaction();
    }
    if (i < localList.size())
    {
      localZzgl = new zzgl();
      zzaxc[i] = localZzgl;
      name = getname;
      zzayl = Long.valueOf(getzzaue);
      zzjo().zza(localZzgl, getvalue);
      localObject4 = localObject3;
      if (bool)
      {
        localObject4 = localObject3;
        if ("_lte".equals(name))
        {
          zzawx = ((Long)value);
          zzayl = Long.valueOf(zzadj.zzbx().currentTimeMillis());
          localObject4 = localZzgl;
        }
      }
    }
    else
    {
      if ((!bool) || (localObject3 != null)) {
        break label1861;
      }
      localObject3 = new zzgl();
      name = "_lte";
      zzayl = Long.valueOf(zzadj.zzbx().currentTimeMillis());
      zzawx = ((Long)value);
      zzaxc = ((zzgl[])Arrays.copyOf(zzaxc, zzaxc.length + 1));
      zzaxc[(zzaxc.length - 1)] = localObject3;
      if (((Long)localObject2).longValue() > 0L) {
        zzjq().zza((zzfj)localObject1);
      }
      localObject1 = zzaid.zziv();
      if ("_iap".equals(name))
      {
        ((Bundle)localObject1).putLong("_c", 1L);
        zzadj.zzgo().zzjk().zzbx("Marking in-app purchase as real-time");
        ((Bundle)localObject1).putLong("_r", 1L);
      }
      ((Bundle)localObject1).putString("_o", origin);
      if (zzadj.zzgm().zzcw(zztt))
      {
        zzadj.zzgm().zza((Bundle)localObject1, "_dbg", Long.valueOf(1L));
        zzadj.zzgm().zza((Bundle)localObject1, "_r", Long.valueOf(1L));
      }
      localObject2 = zzjq().zzg(paramString, name);
      if (localObject2 == null)
      {
        localObject2 = new zzz(paramString, name, 1L, 0L, zzaip, 0L, null, null, null, null);
        zzjq().zza((zzz)localObject2);
        l1 = 0L;
      }
      else
      {
        l1 = zzaig;
        localObject2 = ((zzz)localObject2).zzai(zzaip).zziu();
        zzjq().zza((zzz)localObject2);
      }
      paramZzad = new zzy(zzadj, origin, paramString, name, zzaip, l1, (Bundle)localObject1);
      localObject1 = new zzgf();
      zzaxb = new zzgf[] { localObject1 };
      zzawu = Long.valueOf(timestamp);
      name = name;
      zzawv = Long.valueOf(zzaic);
      zzawt = new zzgg[zzaid.size()];
      localObject2 = zzaid.iterator();
      i = 0;
      while (((Iterator)localObject2).hasNext())
      {
        localObject4 = (String)((Iterator)localObject2).next();
        localObject3 = new zzgg();
        zzawt[i] = localObject3;
        name = ((String)localObject4);
        localObject4 = zzaid.get((String)localObject4);
        zzjo().zza((zzgg)localObject3, localObject4);
        i += 1;
      }
      zzaxt = zza(localZzg.zzal(), zzaxc, zzaxb);
      zzaxe = zzawu;
      zzaxf = zzawu;
      l1 = localZzg.zzgz();
      if (l1 == 0L) {
        break label1864;
      }
      paramZzad = Long.valueOf(l1);
      zzaxh = paramZzad;
      l2 = localZzg.zzgy();
      if (l2 != 0L) {
        break label1869;
      }
      if (l1 == 0L) {
        break label1876;
      }
      paramZzad = Long.valueOf(l1);
    }
    for (;;)
    {
      zzaxg = paramZzad;
      localZzg.zzhh();
      zzaxr = Integer.valueOf((int)localZzg.zzhe());
      zzaxn = Long.valueOf(zzadj.zzgq().zzhc());
      zzaxd = Long.valueOf(zzadj.zzbx().currentTimeMillis());
      zzaxs = Boolean.TRUE;
      localZzg.zzs(zzaxe.longValue());
      localZzg.zzt(zzaxf.longValue());
      zzjq().zza(localZzg);
      zzjq().setTransactionSuccessful();
      zzjq().endTransaction();
      try
      {
        paramZzad = new byte[localZzgh.zzvu()];
        localObject1 = zzyy.zzk(paramZzad, 0, paramZzad.length);
        localZzgh.zza((zzyy)localObject1);
        ((zzyy)localObject1).zzyt();
        paramZzad = zzjo().zzb(paramZzad);
        return paramZzad;
      }
      catch (IOException paramZzad)
      {
        zzadj.zzgo().zzjd().zze("Data loss. Failed to bundle and serialize. appId", zzap.zzbv(paramString), paramZzad);
        return null;
      }
      label1839:
      localObject1 = null;
      localObject3 = null;
      i = 0;
      break;
      i += 1;
      localObject3 = localObject4;
      break;
      label1861:
      break label1119;
      label1864:
      paramZzad = null;
      break label1606;
      label1869:
      l1 = l2;
      break label1629;
      label1876:
      paramZzad = null;
    }
  }
  
  final void zzb(zzez paramZzez)
  {
    zzatn += 1;
  }
  
  @WorkerThread
  final void zzb(zzfh paramZzfh, zzh paramZzh)
  {
    zzaf();
    zzlr();
    if ((TextUtils.isEmpty(zzafx)) && (TextUtils.isEmpty(zzagk))) {
      return;
    }
    if (!zzagg)
    {
      zzg(paramZzh);
      return;
    }
    if ((zzadj.zzgq().zze(packageName, zzaf.zzalj)) && ("_ap".equals(name)))
    {
      localObject = zzjq().zzi(packageName, "_ap");
      if ((localObject != null) && ("auto".equals(origin)) && (!"auto".equals(origin)))
      {
        zzadj.zzgo().zzjk().zzbx("Not setting lower priority ad personalization property");
        return;
      }
    }
    int j = zzadj.zzgm().zzcs(name);
    int i;
    if (j != 0)
    {
      zzadj.zzgm();
      localObject = zzfk.zza(name, 24, true);
      if (name != null) {
        i = name.length();
      } else {
        i = 0;
      }
      zzadj.zzgm().zza(packageName, j, "_ev", (String)localObject, i);
      return;
    }
    j = zzadj.zzgm().zzi(name, paramZzfh.getValue());
    if (j != 0)
    {
      zzadj.zzgm();
      localObject = zzfk.zza(name, 24, true);
      paramZzfh = paramZzfh.getValue();
      if ((paramZzfh != null) && (((paramZzfh instanceof String)) || ((paramZzfh instanceof CharSequence)))) {
        i = String.valueOf(paramZzfh).length();
      } else {
        i = 0;
      }
      zzadj.zzgm().zza(packageName, j, "_ev", (String)localObject, i);
      return;
    }
    Object localObject = zzadj.zzgm().zzj(name, paramZzfh.getValue());
    if (localObject == null) {
      return;
    }
    paramZzfh = new zzfj(packageName, origin, name, zzaue, localObject);
    zzadj.zzgo().zzjk().zze("Setting user property", zzadj.zzgl().zzbu(name), localObject);
    zzjq().beginTransaction();
    try
    {
      zzg(paramZzh);
      boolean bool = zzjq().zza(paramZzfh);
      zzjq().setTransactionSuccessful();
      if (bool)
      {
        zzadj.zzgo().zzjk().zze("User property set", zzadj.zzgl().zzbu(name), value);
      }
      else
      {
        zzadj.zzgo().zzjd().zze("Too many unique user properties are set. Ignoring user property", zzadj.zzgl().zzbu(name), value);
        zzadj.zzgm().zza(packageName, 9, null, null, 0);
      }
      return;
    }
    finally
    {
      zzjq().endTransaction();
    }
  }
  
  @WorkerThread
  final void zzb(zzl paramZzl, zzh paramZzh)
  {
    Preconditions.checkNotNull(paramZzl);
    Preconditions.checkNotEmpty(packageName);
    Preconditions.checkNotNull(origin);
    Preconditions.checkNotNull(zzahb);
    Preconditions.checkNotEmpty(zzahb.name);
    zzaf();
    zzlr();
    if ((TextUtils.isEmpty(zzafx)) && (TextUtils.isEmpty(zzagk))) {
      return;
    }
    if (!zzagg)
    {
      zzg(paramZzh);
      return;
    }
    paramZzl = new zzl(paramZzl);
    int i = 0;
    active = false;
    zzjq().beginTransaction();
    try
    {
      Object localObject = zzjq().zzj(packageName, zzahb.name);
      if ((localObject != null) && (!origin.equals(origin))) {
        zzadj.zzgo().zzjg().zzd("Updating a conditional user property with different origin. name, origin, origin (from DB)", zzadj.zzgl().zzbu(zzahb.name), origin, origin);
      }
      if ((localObject != null) && (active))
      {
        origin = origin;
        creationTimestamp = creationTimestamp;
        triggerTimeout = triggerTimeout;
        triggerEventName = triggerEventName;
        zzahd = zzahd;
        active = active;
        zzahb = new zzfh(zzahb.name, zzahb.zzaue, zzahb.getValue(), zzahb.origin);
      }
      else if (TextUtils.isEmpty(triggerEventName))
      {
        zzahb = new zzfh(zzahb.name, creationTimestamp, zzahb.getValue(), zzahb.origin);
        active = true;
        i = 1;
      }
      if (active)
      {
        localObject = zzahb;
        localObject = new zzfj(packageName, origin, name, zzaue, ((zzfh)localObject).getValue());
        if (zzjq().zza((zzfj)localObject)) {
          zzadj.zzgo().zzjk().zzd("User property updated immediately", packageName, zzadj.zzgl().zzbu(name), value);
        } else {
          zzadj.zzgo().zzjd().zzd("(2)Too many active user properties, ignoring", zzap.zzbv(packageName), zzadj.zzgl().zzbu(name), value);
        }
        if ((i != 0) && (zzahd != null)) {
          zzd(new zzad(zzahd, creationTimestamp), paramZzh);
        }
      }
      if (zzjq().zza(paramZzl)) {
        zzadj.zzgo().zzjk().zzd("Conditional property added", packageName, zzadj.zzgl().zzbu(zzahb.name), zzahb.getValue());
      } else {
        zzadj.zzgo().zzjd().zzd("Too many conditional properties, ignoring", zzap.zzbv(packageName), zzadj.zzgl().zzbu(zzahb.name), zzahb.getValue());
      }
      zzjq().setTransactionSuccessful();
      return;
    }
    finally
    {
      zzjq().endTransaction();
    }
  }
  
  @WorkerThread
  @VisibleForTesting
  final void zzb(String paramString, int paramInt, Throwable paramThrowable, byte[] paramArrayOfByte, Map<String, List<String>> paramMap)
  {
    zzaf();
    zzlr();
    Preconditions.checkNotEmpty(paramString);
    byte[] arrayOfByte = paramArrayOfByte;
    if (paramArrayOfByte == null) {}
    for (;;)
    {
      try
      {
        arrayOfByte = new byte[0];
        zzadj.zzgo().zzjl().zzg("onConfigFetched. Response size", Integer.valueOf(arrayOfByte.length));
        zzjq().beginTransaction();
      }
      finally
      {
        int j;
        boolean bool;
        label502:
        continue;
        if (paramThrowable != null) {
          continue;
        }
        int i = 1;
        continue;
        i = 0;
        continue;
        if (i != 0) {
          continue;
        }
        if (paramInt != 404) {
          continue;
        }
        continue;
        i = 0;
        continue;
        paramThrowable = null;
        continue;
        paramThrowable = null;
        if (paramInt == 404) {
          continue;
        }
        if (paramInt != 304) {
          continue;
        }
        continue;
      }
      try
      {
        paramArrayOfByte = zzjq().zzbl(paramString);
        j = 1;
        if ((paramInt == 200) || (paramInt == 204)) {
          continue;
        }
        if (paramInt != 304) {
          continue;
        }
      }
      finally
      {
        zzjq().endTransaction();
      }
    }
    if (paramArrayOfByte == null)
    {
      zzadj.zzgo().zzjg().zzg("App does not exist in onConfigFetched. appId", zzap.zzbv(paramString));
      break label502;
      paramArrayOfByte.zzz(zzadj.zzbx().currentTimeMillis());
      zzjq().zza(paramArrayOfByte);
      zzadj.zzgo().zzjl().zze("Fetching config failed. code, error", Integer.valueOf(paramInt), paramThrowable);
      zzln().zzch(paramString);
      zzadj.zzgp().zzanf.set(zzadj.zzbx().currentTimeMillis());
      i = j;
      if (paramInt != 503)
      {
        if (paramInt != 429) {
          break label582;
        }
        i = j;
      }
      if (i != 0) {
        zzadj.zzgp().zzang.set(zzadj.zzbx().currentTimeMillis());
      }
      zzlv();
      break label502;
      if (paramMap == null) {
        break label588;
      }
      paramThrowable = (List)paramMap.get("Last-Modified");
      if ((paramThrowable == null) || (paramThrowable.size() <= 0)) {
        break label593;
      }
      paramThrowable = (String)paramThrowable.get(0);
      break label595;
      bool = zzln().zza(paramString, arrayOfByte, paramThrowable);
      if (!bool)
      {
        zzjq().endTransaction();
        zzatp = false;
        zzlw();
        return;
        if (zzln().zzcf(paramString) == null)
        {
          bool = zzln().zza(paramString, null, null);
          if (!bool)
          {
            zzjq().endTransaction();
            zzatp = false;
            zzlw();
            return;
          }
        }
      }
      paramArrayOfByte.zzy(zzadj.zzbx().currentTimeMillis());
      zzjq().zza(paramArrayOfByte);
      if (paramInt == 404) {
        zzadj.zzgo().zzji().zzg("Config not found. Using empty config. appId", paramString);
      } else {
        zzadj.zzgo().zzjl().zze("Successfully fetched config. Got network response. code, size", Integer.valueOf(paramInt), Integer.valueOf(arrayOfByte.length));
      }
      if ((zzlo().zzfb()) && (zzlu())) {
        zzlt();
      } else {
        zzlv();
      }
      zzjq().setTransactionSuccessful();
      zzjq().endTransaction();
      zzatp = false;
      zzlw();
      return;
      zzatp = false;
      zzlw();
      throw paramString;
    }
  }
  
  public final Clock zzbx()
  {
    return zzadj.zzbx();
  }
  
  @WorkerThread
  final void zzc(zzad paramZzad, zzh paramZzh)
  {
    Preconditions.checkNotNull(paramZzh);
    Preconditions.checkNotEmpty(packageName);
    zzaf();
    zzlr();
    Object localObject2 = packageName;
    long l = zzaip;
    if (!zzjo().zze(paramZzad, paramZzh)) {
      return;
    }
    if (!zzagg)
    {
      zzg(paramZzh);
      return;
    }
    zzjq().beginTransaction();
    try
    {
      Object localObject1 = zzjq();
      Preconditions.checkNotEmpty((String)localObject2);
      ((zzco)localObject1).zzaf();
      ((zzez)localObject1).zzcl();
      if (l < 0L)
      {
        ((zzco)localObject1).zzgo().zzjg().zze("Invalid time querying timed out conditional properties", zzap.zzbv((String)localObject2), Long.valueOf(l));
        localObject1 = Collections.emptyList();
      }
      else
      {
        localObject1 = ((zzq)localObject1).zzb("active=0 and app_id=? and abs(? - creation_timestamp) > trigger_timeout", new String[] { localObject2, String.valueOf(l) });
      }
      localObject1 = ((List)localObject1).iterator();
      while (((Iterator)localObject1).hasNext())
      {
        localObject3 = (zzl)((Iterator)localObject1).next();
        if (localObject3 != null)
        {
          zzadj.zzgo().zzjk().zzd("User property timed out", packageName, zzadj.zzgl().zzbu(zzahb.name), zzahb.getValue());
          if (zzahc != null) {
            zzd(new zzad(zzahc, l), paramZzh);
          }
          zzjq().zzk((String)localObject2, zzahb.name);
        }
      }
      localObject1 = zzjq();
      Preconditions.checkNotEmpty((String)localObject2);
      ((zzco)localObject1).zzaf();
      ((zzez)localObject1).zzcl();
      if (l < 0L)
      {
        ((zzco)localObject1).zzgo().zzjg().zze("Invalid time querying expired conditional properties", zzap.zzbv((String)localObject2), Long.valueOf(l));
        localObject1 = Collections.emptyList();
      }
      else
      {
        localObject1 = ((zzq)localObject1).zzb("active<>0 and app_id=? and abs(? - triggered_timestamp) > time_to_live", new String[] { localObject2, String.valueOf(l) });
      }
      Object localObject3 = new ArrayList(((List)localObject1).size());
      localObject1 = ((List)localObject1).iterator();
      Object localObject4;
      while (((Iterator)localObject1).hasNext())
      {
        localObject4 = (zzl)((Iterator)localObject1).next();
        if (localObject4 != null)
        {
          zzadj.zzgo().zzjk().zzd("User property expired", packageName, zzadj.zzgl().zzbu(zzahb.name), zzahb.getValue());
          zzjq().zzh((String)localObject2, zzahb.name);
          if (zzahe != null) {
            ((List)localObject3).add(zzahe);
          }
          zzjq().zzk((String)localObject2, zzahb.name);
        }
      }
      localObject1 = (ArrayList)localObject3;
      int j = ((ArrayList)localObject1).size();
      int i = 0;
      while (i < j)
      {
        localObject3 = ((ArrayList)localObject1).get(i);
        i += 1;
        zzd(new zzad((zzad)localObject3, l), paramZzh);
      }
      localObject1 = zzjq();
      localObject3 = name;
      Preconditions.checkNotEmpty((String)localObject2);
      Preconditions.checkNotEmpty((String)localObject3);
      ((zzco)localObject1).zzaf();
      ((zzez)localObject1).zzcl();
      if (l < 0L)
      {
        ((zzco)localObject1).zzgo().zzjg().zzd("Invalid time querying triggered conditional properties", zzap.zzbv((String)localObject2), ((zzco)localObject1).zzgl().zzbs((String)localObject3), Long.valueOf(l));
        localObject1 = Collections.emptyList();
      }
      else
      {
        localObject1 = ((zzq)localObject1).zzb("active=0 and app_id=? and trigger_event_name=? and abs(? - creation_timestamp) <= trigger_timeout", new String[] { localObject2, localObject3, String.valueOf(l) });
      }
      localObject2 = new ArrayList(((List)localObject1).size());
      localObject1 = ((List)localObject1).iterator();
      while (((Iterator)localObject1).hasNext())
      {
        localObject3 = (zzl)((Iterator)localObject1).next();
        if (localObject3 != null)
        {
          localObject4 = zzahb;
          localObject4 = new zzfj(packageName, origin, name, l, ((zzfh)localObject4).getValue());
          if (zzjq().zza((zzfj)localObject4)) {
            zzadj.zzgo().zzjk().zzd("User property triggered", packageName, zzadj.zzgl().zzbu(name), value);
          } else {
            zzadj.zzgo().zzjd().zzd("Too many active user properties, ignoring", zzap.zzbv(packageName), zzadj.zzgl().zzbu(name), value);
          }
          if (zzahd != null) {
            ((List)localObject2).add(zzahd);
          }
          zzahb = new zzfh((zzfj)localObject4);
          active = true;
          zzjq().zza((zzl)localObject3);
        }
      }
      zzd(paramZzad, paramZzh);
      paramZzad = (ArrayList)localObject2;
      j = paramZzad.size();
      i = 0;
      while (i < j)
      {
        localObject1 = paramZzad.get(i);
        i += 1;
        zzd(new zzad((zzad)localObject1, l), paramZzh);
      }
      zzjq().setTransactionSuccessful();
      return;
    }
    finally
    {
      zzjq().endTransaction();
    }
  }
  
  @WorkerThread
  final void zzc(zzad paramZzad, String paramString)
  {
    zzg localZzg = zzjq().zzbl(paramString);
    if ((localZzg != null) && (!TextUtils.isEmpty(localZzg.zzak())))
    {
      Boolean localBoolean = zzc(localZzg);
      if (localBoolean == null)
      {
        if (!"_ui".equals(name)) {
          zzadj.zzgo().zzjg().zzg("Could not find package. appId", zzap.zzbv(paramString));
        }
      }
      else if (!localBoolean.booleanValue())
      {
        zzadj.zzgo().zzjd().zzg("App version does not match; dropping event. appId", zzap.zzbv(paramString));
        return;
      }
      zzc(paramZzad, new zzh(paramString, localZzg.getGmpAppId(), localZzg.zzak(), localZzg.zzha(), localZzg.zzhb(), localZzg.zzhc(), localZzg.zzhd(), null, localZzg.isMeasurementEnabled(), false, localZzg.getFirebaseInstanceId(), localZzg.zzhq(), 0L, 0, localZzg.zzhr(), localZzg.zzhs(), false, localZzg.zzgw()));
      return;
    }
    zzadj.zzgo().zzjk().zzg("No app data available; dropping event", paramString);
  }
  
  @WorkerThread
  final void zzc(zzfh paramZzfh, zzh paramZzh)
  {
    zzaf();
    zzlr();
    if ((TextUtils.isEmpty(zzafx)) && (TextUtils.isEmpty(zzagk))) {
      return;
    }
    if (!zzagg)
    {
      zzg(paramZzh);
      return;
    }
    if ((zzadj.zzgq().zze(packageName, zzaf.zzalj)) && ("_ap".equals(name)))
    {
      zzfj localZzfj = zzjq().zzi(packageName, "_ap");
      if ((localZzfj != null) && ("auto".equals(origin)) && (!"auto".equals(origin)))
      {
        zzadj.zzgo().zzjk().zzbx("Not removing higher priority ad personalization property");
        return;
      }
    }
    zzadj.zzgo().zzjk().zzg("Removing user property", zzadj.zzgl().zzbu(name));
    zzjq().beginTransaction();
    try
    {
      zzg(paramZzh);
      zzjq().zzh(packageName, name);
      zzjq().setTransactionSuccessful();
      zzadj.zzgo().zzjk().zzg("User property removed", zzadj.zzgl().zzbu(name));
      return;
    }
    finally
    {
      zzjq().endTransaction();
    }
  }
  
  @WorkerThread
  final void zzc(zzl paramZzl, zzh paramZzh)
  {
    Preconditions.checkNotNull(paramZzl);
    Preconditions.checkNotEmpty(packageName);
    Preconditions.checkNotNull(zzahb);
    Preconditions.checkNotEmpty(zzahb.name);
    zzaf();
    zzlr();
    if ((TextUtils.isEmpty(zzafx)) && (TextUtils.isEmpty(zzagk))) {
      return;
    }
    if (!zzagg)
    {
      zzg(paramZzh);
      return;
    }
    zzjq().beginTransaction();
    try
    {
      zzg(paramZzh);
      zzl localZzl = zzjq().zzj(packageName, zzahb.name);
      if (localZzl != null)
      {
        zzadj.zzgo().zzjk().zze("Removing conditional user property", packageName, zzadj.zzgl().zzbu(zzahb.name));
        zzjq().zzk(packageName, zzahb.name);
        if (active) {
          zzjq().zzh(packageName, zzahb.name);
        }
        if (zzahe != null)
        {
          Bundle localBundle = null;
          if (zzahe.zzaid != null) {
            localBundle = zzahe.zzaid.zziv();
          }
          zzd(zzadj.zzgm().zza(packageName, zzahe.name, localBundle, origin, zzahe.zzaip, true, false), paramZzh);
        }
      }
      else
      {
        zzadj.zzgo().zzjg().zze("Conditional user property doesn't exist", zzap.zzbv(packageName), zzadj.zzgl().zzbu(zzahb.name));
      }
      zzjq().setTransactionSuccessful();
      return;
    }
    finally
    {
      zzjq().endTransaction();
    }
  }
  
  @WorkerThread
  @VisibleForTesting
  final void zzd(zzh paramZzh)
  {
    if (zzatu != null)
    {
      zzatv = new ArrayList();
      zzatv.addAll(zzatu);
    }
    Object localObject = zzjq();
    String str = packageName;
    Preconditions.checkNotEmpty(str);
    ((zzco)localObject).zzaf();
    ((zzez)localObject).zzcl();
    try
    {
      SQLiteDatabase localSQLiteDatabase = ((zzq)localObject).getWritableDatabase();
      String[] arrayOfString = new String[1];
      arrayOfString[0] = str;
      int i = localSQLiteDatabase.delete("apps", "app_id=?", arrayOfString) + 0 + localSQLiteDatabase.delete("events", "app_id=?", arrayOfString) + localSQLiteDatabase.delete("user_attributes", "app_id=?", arrayOfString) + localSQLiteDatabase.delete("conditional_properties", "app_id=?", arrayOfString) + localSQLiteDatabase.delete("raw_events", "app_id=?", arrayOfString) + localSQLiteDatabase.delete("raw_events_metadata", "app_id=?", arrayOfString) + localSQLiteDatabase.delete("queue", "app_id=?", arrayOfString) + localSQLiteDatabase.delete("audience_filter_values", "app_id=?", arrayOfString) + localSQLiteDatabase.delete("main_event_params", "app_id=?", arrayOfString);
      if (i > 0) {
        ((zzco)localObject).zzgo().zzjl().zze("Reset analytics data. app, records", str, Integer.valueOf(i));
      }
    }
    catch (SQLiteException localSQLiteException)
    {
      ((zzco)localObject).zzgo().zzjd().zze("Error resetting analytics data. appId, error", zzap.zzbv(str), localSQLiteException);
    }
    localObject = zza(zzadj.getContext(), packageName, zzafx, zzagg, zzagi, zzagj, zzagx, zzagk);
    if ((!zzadj.zzgq().zzbd(packageName)) || (zzagg)) {
      zzf((zzh)localObject);
    }
  }
  
  final void zze(zzh paramZzh)
  {
    zzaf();
    zzlr();
    Preconditions.checkNotEmpty(packageName);
    zzg(paramZzh);
  }
  
  @WorkerThread
  final void zze(zzl paramZzl)
  {
    zzh localZzh = zzco(packageName);
    if (localZzh != null) {
      zzb(paramZzl, localZzh);
    }
  }
  
  @WorkerThread
  final void zzf(zzh paramZzh)
  {
    zzaf();
    zzlr();
    Preconditions.checkNotNull(paramZzh);
    Preconditions.checkNotEmpty(packageName);
    if ((TextUtils.isEmpty(zzafx)) && (TextUtils.isEmpty(zzagk))) {
      return;
    }
    Object localObject1 = zzjq().zzbl(packageName);
    if ((localObject1 != null) && (TextUtils.isEmpty(((zzg)localObject1).getGmpAppId())) && (!TextUtils.isEmpty(zzafx)))
    {
      ((zzg)localObject1).zzy(0L);
      zzjq().zza((zzg)localObject1);
      zzln().zzci(packageName);
    }
    if (!zzagg)
    {
      zzg(paramZzh);
      return;
    }
    long l2 = zzagx;
    long l1 = l2;
    if (l2 == 0L) {
      l1 = zzadj.zzbx().currentTimeMillis();
    }
    int i = zzagy;
    if ((i != 0) && (i != 1))
    {
      zzadj.zzgo().zzjg().zze("Incorrect app type, assuming installed app. appId, appType", zzap.zzbv(packageName), Integer.valueOf(i));
      i = 0;
    }
    zzjq().beginTransaction();
    for (;;)
    {
      try
      {
        Object localObject3 = zzjq().zzbl(packageName);
        localObject1 = localObject3;
        if (localObject3 != null)
        {
          zzadj.zzgm();
          localObject1 = localObject3;
          if (zzfk.zza(zzafx, ((zzg)localObject3).getGmpAppId(), zzagk, ((zzg)localObject3).zzgw()))
          {
            zzadj.zzgo().zzjg().zzg("New GMP App Id passed in. Removing cached database data. appId", zzap.zzbv(((zzg)localObject3).zzal()));
            localObject1 = zzjq();
            localObject3 = ((zzg)localObject3).zzal();
            ((zzez)localObject1).zzcl();
            ((zzco)localObject1).zzaf();
            Preconditions.checkNotEmpty((String)localObject3);
            try
            {
              SQLiteDatabase localSQLiteDatabase = ((zzq)localObject1).getWritableDatabase();
              String[] arrayOfString = new String[1];
              arrayOfString[0] = localObject3;
              int j = localSQLiteDatabase.delete("events", "app_id=?", arrayOfString) + 0 + localSQLiteDatabase.delete("user_attributes", "app_id=?", arrayOfString) + localSQLiteDatabase.delete("conditional_properties", "app_id=?", arrayOfString) + localSQLiteDatabase.delete("apps", "app_id=?", arrayOfString) + localSQLiteDatabase.delete("raw_events", "app_id=?", arrayOfString) + localSQLiteDatabase.delete("raw_events_metadata", "app_id=?", arrayOfString) + localSQLiteDatabase.delete("event_filters", "app_id=?", arrayOfString) + localSQLiteDatabase.delete("property_filters", "app_id=?", arrayOfString) + localSQLiteDatabase.delete("audience_filter_values", "app_id=?", arrayOfString);
              if (j <= 0) {
                break label1530;
              }
              ((zzco)localObject1).zzgo().zzjl().zze("Deleted application data. app, records", localObject3, Integer.valueOf(j));
            }
            catch (SQLiteException localSQLiteException)
            {
              ((zzco)localObject1).zzgo().zzjd().zze("Error deleting application data. appId, error", zzap.zzbv((String)localObject3), localSQLiteException);
            }
          }
        }
        if (localObject1 != null) {
          if (((zzg)localObject1).zzha() != -2147483648L)
          {
            if (((zzg)localObject1).zzha() != zzagd)
            {
              localObject3 = new Bundle();
              ((Bundle)localObject3).putString("_pv", ((zzg)localObject1).zzak());
              zzc(new zzad("_au", new zzaa((Bundle)localObject3), "auto", l1), paramZzh);
            }
          }
          else if ((((zzg)localObject1).zzak() != null) && (!((zzg)localObject1).zzak().equals(zzts)))
          {
            localObject3 = new Bundle();
            ((Bundle)localObject3).putString("_pv", ((zzg)localObject1).zzak());
            zzc(new zzad("_au", new zzaa((Bundle)localObject3), "auto", l1), paramZzh);
          }
        }
        zzg(paramZzh);
        if (i == 0)
        {
          localObject1 = zzjq().zzg(packageName, "_f");
        }
        else
        {
          if (i != 1) {
            break label1536;
          }
          localObject1 = zzjq().zzg(packageName, "_v");
        }
        if (localObject1 == null)
        {
          l2 = (l1 / 3600000L + 1L) * 3600000L;
          long l3;
          if (i == 0)
          {
            l3 = 1L;
            zzb(new zzfh("_fot", l1, Long.valueOf(l2), "auto"), paramZzh);
            if (zzadj.zzgq().zzbg(zzafx))
            {
              zzaf();
              zzadj.zzkg().zzcd(packageName);
            }
            zzaf();
            zzlr();
            localObject3 = new Bundle();
            ((Bundle)localObject3).putLong("_c", l3);
            ((Bundle)localObject3).putLong("_r", l3);
            ((Bundle)localObject3).putLong("_uwa", 0L);
            ((Bundle)localObject3).putLong("_pfo", 0L);
            ((Bundle)localObject3).putLong("_sys", 0L);
            ((Bundle)localObject3).putLong("_sysu", 0L);
            if ((zzadj.zzgq().zzbd(packageName)) && (zzagz)) {
              ((Bundle)localObject3).putLong("_dac", l3);
            }
            if (zzadj.getContext().getPackageManager() == null)
            {
              zzadj.zzgo().zzjd().zzg("PackageManager is null, first open report might be inaccurate. appId", zzap.zzbv(packageName));
            }
            else
            {
              ApplicationInfo localApplicationInfo;
              try
              {
                localObject1 = Wrappers.packageManager(zzadj.getContext()).getPackageInfo(packageName, 0);
              }
              catch (PackageManager.NameNotFoundException localNameNotFoundException1)
              {
                zzadj.zzgo().zzjd().zze("Package info is null, first open report might be inaccurate. appId", zzap.zzbv(packageName), localNameNotFoundException1);
                localApplicationInfo = null;
              }
              if ((localApplicationInfo != null) && (firstInstallTime != 0L))
              {
                if (firstInstallTime == lastUpdateTime) {
                  break label1542;
                }
                ((Bundle)localObject3).putLong("_uwa", l3);
                i = 0;
                if (i == 0) {
                  break label1547;
                }
                l2 = l3;
                zzb(new zzfh("_fi", l1, Long.valueOf(l2), "auto"), paramZzh);
              }
              try
              {
                localApplicationInfo = Wrappers.packageManager(zzadj.getContext()).getApplicationInfo(packageName, 0);
              }
              catch (PackageManager.NameNotFoundException localNameNotFoundException2)
              {
                zzadj.zzgo().zzjd().zze("Application info is null, first open report might be inaccurate. appId", zzap.zzbv(packageName), localNameNotFoundException2);
                localObject2 = null;
              }
              if (localObject2 != null)
              {
                if ((flags & 0x1) != 0) {
                  ((Bundle)localObject3).putLong("_sys", l3);
                }
                if ((flags & 0x80) != 0) {
                  ((Bundle)localObject3).putLong("_sysu", l3);
                }
              }
            }
            localObject2 = zzjq();
            String str = packageName;
            Preconditions.checkNotEmpty(str);
            ((zzco)localObject2).zzaf();
            ((zzez)localObject2).zzcl();
            l2 = ((zzq)localObject2).zzn(str, "first_open_count");
            if (l2 >= 0L) {
              ((Bundle)localObject3).putLong("_pfo", l2);
            }
            zzc(new zzad("_f", new zzaa((Bundle)localObject3), "auto", l1), paramZzh);
          }
          else
          {
            l3 = 1L;
            if (i == 1)
            {
              zzb(new zzfh("_fvt", l1, Long.valueOf(l2), "auto"), paramZzh);
              zzaf();
              zzlr();
              localObject2 = new Bundle();
              ((Bundle)localObject2).putLong("_c", l3);
              ((Bundle)localObject2).putLong("_r", l3);
              if ((zzadj.zzgq().zzbd(packageName)) && (zzagz)) {
                ((Bundle)localObject2).putLong("_dac", l3);
              }
              zzc(new zzad("_v", new zzaa((Bundle)localObject2), "auto", l1), paramZzh);
            }
          }
          localObject2 = new Bundle();
          ((Bundle)localObject2).putLong("_et", 1L);
          zzc(new zzad("_e", new zzaa((Bundle)localObject2), "auto", l1), paramZzh);
        }
        else if (zzagw)
        {
          zzc(new zzad("_cd", new zzaa(new Bundle()), "auto", l1), paramZzh);
        }
        zzjq().setTransactionSuccessful();
        return;
      }
      finally
      {
        zzjq().endTransaction();
      }
      label1530:
      Object localObject2 = null;
      continue;
      label1536:
      localObject2 = null;
      continue;
      label1542:
      i = 1;
      continue;
      label1547:
      l2 = 0L;
    }
  }
  
  @WorkerThread
  final void zzf(zzl paramZzl)
  {
    zzh localZzh = zzco(packageName);
    if (localZzh != null) {
      zzc(paramZzl, localZzh);
    }
  }
  
  @WorkerThread
  final void zzg(Runnable paramRunnable)
  {
    zzaf();
    if (zzatm == null) {
      zzatm = new ArrayList();
    }
    zzatm.add(paramRunnable);
  }
  
  public final zzan zzgl()
  {
    return zzadj.zzgl();
  }
  
  public final zzfk zzgm()
  {
    return zzadj.zzgm();
  }
  
  public final zzbo zzgn()
  {
    return zzadj.zzgn();
  }
  
  public final zzap zzgo()
  {
    return zzadj.zzgo();
  }
  
  public final zzn zzgq()
  {
    return zzadj.zzgq();
  }
  
  public final zzk zzgr()
  {
    return zzadj.zzgr();
  }
  
  final String zzh(zzh paramZzh)
  {
    Object localObject = zzadj.zzgn().zzb(new zzfe(this, paramZzh));
    try
    {
      localObject = (String)((Future)localObject).get(30000L, TimeUnit.MILLISECONDS);
      return localObject;
    }
    catch (TimeoutException|InterruptedException|ExecutionException localTimeoutException)
    {
      zzadj.zzgo().zzjd().zze("Failed to get app instance id. appId", zzap.zzbv(packageName), localTimeoutException);
    }
    return null;
  }
  
  public final zzfg zzjo()
  {
    zza(zzatj);
    return zzatj;
  }
  
  public final zzj zzjp()
  {
    zza(zzati);
    return zzati;
  }
  
  public final zzq zzjq()
  {
    zza(zzatf);
    return zzatf;
  }
  
  public final zzat zzlo()
  {
    zza(zzate);
    return zzate;
  }
  
  final void zzlr()
  {
    if (zzvz) {
      return;
    }
    throw new IllegalStateException("UploadController is not initialized");
  }
  
  /* Error */
  @WorkerThread
  final void zzlt()
  {
    // Byte code:
    //   0: aload_0
    //   1: invokespecial 128	com/google/android/gms/measurement/internal/zzfa:zzaf	()V
    //   4: aload_0
    //   5: invokevirtual 1294	com/google/android/gms/measurement/internal/zzfa:zzlr	()V
    //   8: aload_0
    //   9: iconst_1
    //   10: putfield 1554	com/google/android/gms/measurement/internal/zzfa:zzatr	Z
    //   13: aload_0
    //   14: getfield 80	com/google/android/gms/measurement/internal/zzfa:zzadj	Lcom/google/android/gms/measurement/internal/zzbt;
    //   17: invokevirtual 277	com/google/android/gms/measurement/internal/zzbt:zzgr	()Lcom/google/android/gms/measurement/internal/zzk;
    //   20: pop
    //   21: aload_0
    //   22: getfield 80	com/google/android/gms/measurement/internal/zzfa:zzadj	Lcom/google/android/gms/measurement/internal/zzbt;
    //   25: invokevirtual 2246	com/google/android/gms/measurement/internal/zzbt:zzgg	()Lcom/google/android/gms/measurement/internal/zzdr;
    //   28: invokevirtual 2252	com/google/android/gms/measurement/internal/zzdr:zzle	()Ljava/lang/Boolean;
    //   31: astore 7
    //   33: aload 7
    //   35: ifnonnull +29 -> 64
    //   38: aload_0
    //   39: getfield 80	com/google/android/gms/measurement/internal/zzfa:zzadj	Lcom/google/android/gms/measurement/internal/zzbt;
    //   42: invokevirtual 152	com/google/android/gms/measurement/internal/zzbt:zzgo	()Lcom/google/android/gms/measurement/internal/zzap;
    //   45: invokevirtual 158	com/google/android/gms/measurement/internal/zzap:zzjg	()Lcom/google/android/gms/measurement/internal/zzar;
    //   48: ldc_w 2254
    //   51: invokevirtual 191	com/google/android/gms/measurement/internal/zzar:zzbx	(Ljava/lang/String;)V
    //   54: aload_0
    //   55: iconst_0
    //   56: putfield 1554	com/google/android/gms/measurement/internal/zzfa:zzatr	Z
    //   59: aload_0
    //   60: invokespecial 1664	com/google/android/gms/measurement/internal/zzfa:zzlw	()V
    //   63: return
    //   64: aload 7
    //   66: invokevirtual 756	java/lang/Boolean:booleanValue	()Z
    //   69: ifeq +29 -> 98
    //   72: aload_0
    //   73: getfield 80	com/google/android/gms/measurement/internal/zzfa:zzadj	Lcom/google/android/gms/measurement/internal/zzbt;
    //   76: invokevirtual 152	com/google/android/gms/measurement/internal/zzbt:zzgo	()Lcom/google/android/gms/measurement/internal/zzap;
    //   79: invokevirtual 183	com/google/android/gms/measurement/internal/zzap:zzjd	()Lcom/google/android/gms/measurement/internal/zzar;
    //   82: ldc_w 2256
    //   85: invokevirtual 191	com/google/android/gms/measurement/internal/zzar:zzbx	(Ljava/lang/String;)V
    //   88: aload_0
    //   89: iconst_0
    //   90: putfield 1554	com/google/android/gms/measurement/internal/zzfa:zzatr	Z
    //   93: aload_0
    //   94: invokespecial 1664	com/google/android/gms/measurement/internal/zzfa:zzlw	()V
    //   97: return
    //   98: aload_0
    //   99: getfield 1443	com/google/android/gms/measurement/internal/zzfa:zzatl	J
    //   102: lconst_0
    //   103: lcmp
    //   104: ifle +17 -> 121
    //   107: aload_0
    //   108: invokespecial 1628	com/google/android/gms/measurement/internal/zzfa:zzlv	()V
    //   111: aload_0
    //   112: iconst_0
    //   113: putfield 1554	com/google/android/gms/measurement/internal/zzfa:zzatr	Z
    //   116: aload_0
    //   117: invokespecial 1664	com/google/android/gms/measurement/internal/zzfa:zzlw	()V
    //   120: return
    //   121: aload_0
    //   122: invokespecial 128	com/google/android/gms/measurement/internal/zzfa:zzaf	()V
    //   125: aload_0
    //   126: getfield 1631	com/google/android/gms/measurement/internal/zzfa:zzatu	Ljava/util/List;
    //   129: ifnull +956 -> 1085
    //   132: iconst_1
    //   133: istore_1
    //   134: goto +3 -> 137
    //   137: iload_1
    //   138: ifeq +29 -> 167
    //   141: aload_0
    //   142: getfield 80	com/google/android/gms/measurement/internal/zzfa:zzadj	Lcom/google/android/gms/measurement/internal/zzbt;
    //   145: invokevirtual 152	com/google/android/gms/measurement/internal/zzbt:zzgo	()Lcom/google/android/gms/measurement/internal/zzap;
    //   148: invokevirtual 684	com/google/android/gms/measurement/internal/zzap:zzjl	()Lcom/google/android/gms/measurement/internal/zzar;
    //   151: ldc_w 2258
    //   154: invokevirtual 191	com/google/android/gms/measurement/internal/zzar:zzbx	(Ljava/lang/String;)V
    //   157: aload_0
    //   158: iconst_0
    //   159: putfield 1554	com/google/android/gms/measurement/internal/zzfa:zzatr	Z
    //   162: aload_0
    //   163: invokespecial 1664	com/google/android/gms/measurement/internal/zzfa:zzlw	()V
    //   166: return
    //   167: aload_0
    //   168: invokevirtual 714	com/google/android/gms/measurement/internal/zzfa:zzlo	()Lcom/google/android/gms/measurement/internal/zzat;
    //   171: invokevirtual 1528	com/google/android/gms/measurement/internal/zzat:zzfb	()Z
    //   174: ifne +33 -> 207
    //   177: aload_0
    //   178: getfield 80	com/google/android/gms/measurement/internal/zzfa:zzadj	Lcom/google/android/gms/measurement/internal/zzbt;
    //   181: invokevirtual 152	com/google/android/gms/measurement/internal/zzbt:zzgo	()Lcom/google/android/gms/measurement/internal/zzap;
    //   184: invokevirtual 684	com/google/android/gms/measurement/internal/zzap:zzjl	()Lcom/google/android/gms/measurement/internal/zzar;
    //   187: ldc_w 2260
    //   190: invokevirtual 191	com/google/android/gms/measurement/internal/zzar:zzbx	(Ljava/lang/String;)V
    //   193: aload_0
    //   194: invokespecial 1628	com/google/android/gms/measurement/internal/zzfa:zzlv	()V
    //   197: aload_0
    //   198: iconst_0
    //   199: putfield 1554	com/google/android/gms/measurement/internal/zzfa:zzatr	Z
    //   202: aload_0
    //   203: invokespecial 1664	com/google/android/gms/measurement/internal/zzfa:zzlw	()V
    //   206: return
    //   207: aload_0
    //   208: getfield 80	com/google/android/gms/measurement/internal/zzfa:zzadj	Lcom/google/android/gms/measurement/internal/zzbt;
    //   211: invokevirtual 507	com/google/android/gms/measurement/internal/zzbt:zzbx	()Lcom/google/android/gms/common/util/Clock;
    //   214: invokeinterface 512 1 0
    //   219: lstore_3
    //   220: invokestatic 2263	com/google/android/gms/measurement/internal/zzn:zzhx	()J
    //   223: lstore 5
    //   225: aconst_null
    //   226: astore 9
    //   228: aload_0
    //   229: aconst_null
    //   230: lload_3
    //   231: lload 5
    //   233: lsub
    //   234: invokespecial 2265	com/google/android/gms/measurement/internal/zzfa:zzd	(Ljava/lang/String;J)Z
    //   237: pop
    //   238: aload_0
    //   239: getfield 80	com/google/android/gms/measurement/internal/zzfa:zzadj	Lcom/google/android/gms/measurement/internal/zzbt;
    //   242: invokevirtual 1301	com/google/android/gms/measurement/internal/zzbt:zzgp	()Lcom/google/android/gms/measurement/internal/zzba;
    //   245: getfield 1494	com/google/android/gms/measurement/internal/zzba:zzane	Lcom/google/android/gms/measurement/internal/zzbd;
    //   248: invokevirtual 1419	com/google/android/gms/measurement/internal/zzbd:get	()J
    //   251: lstore 5
    //   253: lload 5
    //   255: lconst_0
    //   256: lcmp
    //   257: ifeq +29 -> 286
    //   260: aload_0
    //   261: getfield 80	com/google/android/gms/measurement/internal/zzfa:zzadj	Lcom/google/android/gms/measurement/internal/zzbt;
    //   264: invokevirtual 152	com/google/android/gms/measurement/internal/zzbt:zzgo	()Lcom/google/android/gms/measurement/internal/zzap;
    //   267: invokevirtual 783	com/google/android/gms/measurement/internal/zzap:zzjk	()Lcom/google/android/gms/measurement/internal/zzar;
    //   270: ldc_w 2267
    //   273: lload_3
    //   274: lload 5
    //   276: lsub
    //   277: invokestatic 1167	java/lang/Math:abs	(J)J
    //   280: invokestatic 404	java/lang/Long:valueOf	(J)Ljava/lang/Long;
    //   283: invokevirtual 172	com/google/android/gms/measurement/internal/zzar:zzg	(Ljava/lang/String;Ljava/lang/Object;)V
    //   286: aload_0
    //   287: invokevirtual 492	com/google/android/gms/measurement/internal/zzfa:zzjq	()Lcom/google/android/gms/measurement/internal/zzq;
    //   290: invokevirtual 1437	com/google/android/gms/measurement/internal/zzq:zzid	()Ljava/lang/String;
    //   293: astore 11
    //   295: aload 11
    //   297: invokestatic 257	android/text/TextUtils:isEmpty	(Ljava/lang/CharSequence;)Z
    //   300: ifne +705 -> 1005
    //   303: aload_0
    //   304: getfield 84	com/google/android/gms/measurement/internal/zzfa:zzatw	J
    //   307: ldc2_w 81
    //   310: lcmp
    //   311: ifne +14 -> 325
    //   314: aload_0
    //   315: aload_0
    //   316: invokevirtual 492	com/google/android/gms/measurement/internal/zzfa:zzjq	()Lcom/google/android/gms/measurement/internal/zzq;
    //   319: invokevirtual 2270	com/google/android/gms/measurement/internal/zzq:zzik	()J
    //   322: putfield 84	com/google/android/gms/measurement/internal/zzfa:zzatw	J
    //   325: aload_0
    //   326: getfield 80	com/google/android/gms/measurement/internal/zzfa:zzadj	Lcom/google/android/gms/measurement/internal/zzbt;
    //   329: invokevirtual 281	com/google/android/gms/measurement/internal/zzbt:zzgq	()Lcom/google/android/gms/measurement/internal/zzn;
    //   332: aload 11
    //   334: getstatic 2273	com/google/android/gms/measurement/internal/zzaf:zzajj	Lcom/google/android/gms/measurement/internal/zzaf$zza;
    //   337: invokevirtual 525	com/google/android/gms/measurement/internal/zzn:zzb	(Ljava/lang/String;Lcom/google/android/gms/measurement/internal/zzaf$zza;)I
    //   340: istore_1
    //   341: iconst_0
    //   342: aload_0
    //   343: getfield 80	com/google/android/gms/measurement/internal/zzfa:zzadj	Lcom/google/android/gms/measurement/internal/zzbt;
    //   346: invokevirtual 281	com/google/android/gms/measurement/internal/zzbt:zzgq	()Lcom/google/android/gms/measurement/internal/zzn;
    //   349: aload 11
    //   351: getstatic 2276	com/google/android/gms/measurement/internal/zzaf:zzajk	Lcom/google/android/gms/measurement/internal/zzaf$zza;
    //   354: invokevirtual 525	com/google/android/gms/measurement/internal/zzn:zzb	(Ljava/lang/String;Lcom/google/android/gms/measurement/internal/zzaf$zza;)I
    //   357: invokestatic 1518	java/lang/Math:max	(II)I
    //   360: istore_2
    //   361: aload_0
    //   362: invokevirtual 492	com/google/android/gms/measurement/internal/zzfa:zzjq	()Lcom/google/android/gms/measurement/internal/zzq;
    //   365: aload 11
    //   367: iload_1
    //   368: iload_2
    //   369: invokevirtual 2279	com/google/android/gms/measurement/internal/zzq:zzb	(Ljava/lang/String;II)Ljava/util/List;
    //   372: astore 10
    //   374: aload 10
    //   376: invokeinterface 905 1 0
    //   381: ifne +675 -> 1056
    //   384: aload 10
    //   386: invokeinterface 1559 1 0
    //   391: astore 7
    //   393: aload 7
    //   395: invokeinterface 1184 1 0
    //   400: ifeq +690 -> 1090
    //   403: aload 7
    //   405: invokeinterface 1187 1 0
    //   410: checkcast 1731	android/util/Pair
    //   413: getfield 1734	android/util/Pair:first	Ljava/lang/Object;
    //   416: checkcast 852	com/google/android/gms/internal/measurement/zzgi
    //   419: astore 8
    //   421: aload 8
    //   423: getfield 1737	com/google/android/gms/internal/measurement/zzgi:zzaxo	Ljava/lang/String;
    //   426: invokestatic 257	android/text/TextUtils:isEmpty	(Ljava/lang/CharSequence;)Z
    //   429: ifne -36 -> 393
    //   432: aload 8
    //   434: getfield 1737	com/google/android/gms/internal/measurement/zzgi:zzaxo	Ljava/lang/String;
    //   437: astore 8
    //   439: goto +654 -> 1093
    //   442: aload 10
    //   444: astore 7
    //   446: iload_1
    //   447: aload 10
    //   449: invokeinterface 911 1 0
    //   454: if_icmpge +60 -> 514
    //   457: aload 10
    //   459: iload_1
    //   460: invokeinterface 924 2 0
    //   465: checkcast 1731	android/util/Pair
    //   468: getfield 1734	android/util/Pair:first	Ljava/lang/Object;
    //   471: checkcast 852	com/google/android/gms/internal/measurement/zzgi
    //   474: astore 7
    //   476: aload 7
    //   478: getfield 1737	com/google/android/gms/internal/measurement/zzgi:zzaxo	Ljava/lang/String;
    //   481: invokestatic 257	android/text/TextUtils:isEmpty	(Ljava/lang/CharSequence;)Z
    //   484: ifne +623 -> 1107
    //   487: aload 7
    //   489: getfield 1737	com/google/android/gms/internal/measurement/zzgi:zzaxo	Ljava/lang/String;
    //   492: aload 8
    //   494: invokevirtual 233	java/lang/String:equals	(Ljava/lang/Object;)Z
    //   497: ifne +610 -> 1107
    //   500: aload 10
    //   502: iconst_0
    //   503: iload_1
    //   504: invokeinterface 2283 3 0
    //   509: astore 7
    //   511: goto +3 -> 514
    //   514: new 1673	com/google/android/gms/internal/measurement/zzgh
    //   517: dup
    //   518: invokespecial 1674	com/google/android/gms/internal/measurement/zzgh:<init>	()V
    //   521: astore 10
    //   523: aload 10
    //   525: aload 7
    //   527: invokeinterface 911 1 0
    //   532: anewarray 852	com/google/android/gms/internal/measurement/zzgi
    //   535: putfield 1693	com/google/android/gms/internal/measurement/zzgh:zzawy	[Lcom/google/android/gms/internal/measurement/zzgi;
    //   538: new 2022	java/util/ArrayList
    //   541: dup
    //   542: aload 7
    //   544: invokeinterface 911 1 0
    //   549: invokespecial 2023	java/util/ArrayList:<init>	(I)V
    //   552: astore 8
    //   554: invokestatic 1719	com/google/android/gms/measurement/internal/zzn:zzhz	()Z
    //   557: ifeq +557 -> 1114
    //   560: aload_0
    //   561: getfield 80	com/google/android/gms/measurement/internal/zzfa:zzadj	Lcom/google/android/gms/measurement/internal/zzbt;
    //   564: invokevirtual 281	com/google/android/gms/measurement/internal/zzbt:zzgq	()Lcom/google/android/gms/measurement/internal/zzn;
    //   567: aload 11
    //   569: invokevirtual 1722	com/google/android/gms/measurement/internal/zzn:zzav	(Ljava/lang/String;)Z
    //   572: ifeq +542 -> 1114
    //   575: iconst_1
    //   576: istore_1
    //   577: goto +539 -> 1116
    //   580: iload_2
    //   581: aload 10
    //   583: getfield 1693	com/google/android/gms/internal/measurement/zzgh:zzawy	[Lcom/google/android/gms/internal/measurement/zzgi;
    //   586: arraylength
    //   587: if_icmpge +133 -> 720
    //   590: aload 10
    //   592: getfield 1693	com/google/android/gms/internal/measurement/zzgh:zzawy	[Lcom/google/android/gms/internal/measurement/zzgi;
    //   595: iload_2
    //   596: aload 7
    //   598: iload_2
    //   599: invokeinterface 924 2 0
    //   604: checkcast 1731	android/util/Pair
    //   607: getfield 1734	android/util/Pair:first	Ljava/lang/Object;
    //   610: checkcast 852	com/google/android/gms/internal/measurement/zzgi
    //   613: aastore
    //   614: aload 8
    //   616: aload 7
    //   618: iload_2
    //   619: invokeinterface 924 2 0
    //   624: checkcast 1731	android/util/Pair
    //   627: getfield 1740	android/util/Pair:second	Ljava/lang/Object;
    //   630: checkcast 401	java/lang/Long
    //   633: invokeinterface 2033 2 0
    //   638: pop
    //   639: aload 10
    //   641: getfield 1693	com/google/android/gms/internal/measurement/zzgh:zzawy	[Lcom/google/android/gms/internal/measurement/zzgi;
    //   644: iload_2
    //   645: aaload
    //   646: aload_0
    //   647: getfield 80	com/google/android/gms/measurement/internal/zzfa:zzadj	Lcom/google/android/gms/measurement/internal/zzbt;
    //   650: invokevirtual 281	com/google/android/gms/measurement/internal/zzbt:zzgq	()Lcom/google/android/gms/measurement/internal/zzn;
    //   653: invokevirtual 293	com/google/android/gms/measurement/internal/zzn:zzhc	()J
    //   656: invokestatic 404	java/lang/Long:valueOf	(J)Ljava/lang/Long;
    //   659: putfield 1850	com/google/android/gms/internal/measurement/zzgi:zzaxn	Ljava/lang/Long;
    //   662: aload 10
    //   664: getfield 1693	com/google/android/gms/internal/measurement/zzgh:zzawy	[Lcom/google/android/gms/internal/measurement/zzgi;
    //   667: iload_2
    //   668: aaload
    //   669: lload_3
    //   670: invokestatic 404	java/lang/Long:valueOf	(J)Ljava/lang/Long;
    //   673: putfield 1853	com/google/android/gms/internal/measurement/zzgi:zzaxd	Ljava/lang/Long;
    //   676: aload 10
    //   678: getfield 1693	com/google/android/gms/internal/measurement/zzgh:zzawy	[Lcom/google/android/gms/internal/measurement/zzgi;
    //   681: iload_2
    //   682: aaload
    //   683: astore 12
    //   685: aload_0
    //   686: getfield 80	com/google/android/gms/measurement/internal/zzfa:zzadj	Lcom/google/android/gms/measurement/internal/zzbt;
    //   689: invokevirtual 277	com/google/android/gms/measurement/internal/zzbt:zzgr	()Lcom/google/android/gms/measurement/internal/zzk;
    //   692: pop
    //   693: aload 12
    //   695: iconst_0
    //   696: invokestatic 742	java/lang/Boolean:valueOf	(Z)Ljava/lang/Boolean;
    //   699: putfield 1859	com/google/android/gms/internal/measurement/zzgi:zzaxs	Ljava/lang/Boolean;
    //   702: iload_1
    //   703: ifne +418 -> 1121
    //   706: aload 10
    //   708: getfield 1693	com/google/android/gms/internal/measurement/zzgh:zzawy	[Lcom/google/android/gms/internal/measurement/zzgi;
    //   711: iload_2
    //   712: aaload
    //   713: aconst_null
    //   714: putfield 1725	com/google/android/gms/internal/measurement/zzgi:zzaya	Ljava/lang/String;
    //   717: goto +404 -> 1121
    //   720: aload 9
    //   722: astore 7
    //   724: aload_0
    //   725: getfield 80	com/google/android/gms/measurement/internal/zzfa:zzadj	Lcom/google/android/gms/measurement/internal/zzbt;
    //   728: invokevirtual 152	com/google/android/gms/measurement/internal/zzbt:zzgo	()Lcom/google/android/gms/measurement/internal/zzap;
    //   731: iconst_2
    //   732: invokevirtual 2286	com/google/android/gms/measurement/internal/zzap:isLoggable	(I)Z
    //   735: ifeq +14 -> 749
    //   738: aload_0
    //   739: invokevirtual 945	com/google/android/gms/measurement/internal/zzfa:zzjo	()Lcom/google/android/gms/measurement/internal/zzfg;
    //   742: aload 10
    //   744: invokevirtual 2289	com/google/android/gms/measurement/internal/zzfg:zzb	(Lcom/google/android/gms/internal/measurement/zzgh;)Ljava/lang/String;
    //   747: astore 7
    //   749: aload_0
    //   750: invokevirtual 945	com/google/android/gms/measurement/internal/zzfa:zzjo	()Lcom/google/android/gms/measurement/internal/zzfg;
    //   753: aload 10
    //   755: invokevirtual 2292	com/google/android/gms/measurement/internal/zzfg:zza	(Lcom/google/android/gms/internal/measurement/zzgh;)[B
    //   758: astore 12
    //   760: getstatic 2295	com/google/android/gms/measurement/internal/zzaf:zzajt	Lcom/google/android/gms/measurement/internal/zzaf$zza;
    //   763: invokevirtual 638	com/google/android/gms/measurement/internal/zzaf$zza:get	()Ljava/lang/Object;
    //   766: checkcast 229	java/lang/String
    //   769: astore 9
    //   771: new 680	java/net/URL
    //   774: dup
    //   775: aload 9
    //   777: invokespecial 681	java/net/URL:<init>	(Ljava/lang/String;)V
    //   780: astore 13
    //   782: aload 8
    //   784: invokeinterface 905 1 0
    //   789: iconst_1
    //   790: ixor
    //   791: invokestatic 2298	com/google/android/gms/common/internal/Preconditions:checkArgument	(Z)V
    //   794: aload_0
    //   795: getfield 1631	com/google/android/gms/measurement/internal/zzfa:zzatu	Ljava/util/List;
    //   798: ifnull +22 -> 820
    //   801: aload_0
    //   802: getfield 80	com/google/android/gms/measurement/internal/zzfa:zzadj	Lcom/google/android/gms/measurement/internal/zzbt;
    //   805: invokevirtual 152	com/google/android/gms/measurement/internal/zzbt:zzgo	()Lcom/google/android/gms/measurement/internal/zzap;
    //   808: invokevirtual 183	com/google/android/gms/measurement/internal/zzap:zzjd	()Lcom/google/android/gms/measurement/internal/zzar;
    //   811: ldc_w 2300
    //   814: invokevirtual 191	com/google/android/gms/measurement/internal/zzar:zzbx	(Ljava/lang/String;)V
    //   817: goto +16 -> 833
    //   820: aload_0
    //   821: new 2022	java/util/ArrayList
    //   824: dup
    //   825: aload 8
    //   827: invokespecial 2303	java/util/ArrayList:<init>	(Ljava/util/Collection;)V
    //   830: putfield 1631	com/google/android/gms/measurement/internal/zzfa:zzatu	Ljava/util/List;
    //   833: aload_0
    //   834: getfield 80	com/google/android/gms/measurement/internal/zzfa:zzadj	Lcom/google/android/gms/measurement/internal/zzbt;
    //   837: invokevirtual 1301	com/google/android/gms/measurement/internal/zzbt:zzgp	()Lcom/google/android/gms/measurement/internal/zzba;
    //   840: getfield 1497	com/google/android/gms/measurement/internal/zzba:zzanf	Lcom/google/android/gms/measurement/internal/zzbd;
    //   843: lload_3
    //   844: invokevirtual 1424	com/google/android/gms/measurement/internal/zzbd:set	(J)V
    //   847: ldc_w 2305
    //   850: astore 8
    //   852: aload 10
    //   854: getfield 1693	com/google/android/gms/internal/measurement/zzgh:zzawy	[Lcom/google/android/gms/internal/measurement/zzgi;
    //   857: arraylength
    //   858: ifle +15 -> 873
    //   861: aload 10
    //   863: getfield 1693	com/google/android/gms/internal/measurement/zzgh:zzawy	[Lcom/google/android/gms/internal/measurement/zzgi;
    //   866: iconst_0
    //   867: aaload
    //   868: getfield 918	com/google/android/gms/internal/measurement/zzgi:zztt	Ljava/lang/String;
    //   871: astore 8
    //   873: aload_0
    //   874: getfield 80	com/google/android/gms/measurement/internal/zzfa:zzadj	Lcom/google/android/gms/measurement/internal/zzbt;
    //   877: invokevirtual 152	com/google/android/gms/measurement/internal/zzbt:zzgo	()Lcom/google/android/gms/measurement/internal/zzap;
    //   880: invokevirtual 684	com/google/android/gms/measurement/internal/zzap:zzjl	()Lcom/google/android/gms/measurement/internal/zzar;
    //   883: ldc_w 2307
    //   886: aload 8
    //   888: aload 12
    //   890: arraylength
    //   891: invokestatic 166	java/lang/Integer:valueOf	(I)Ljava/lang/Integer;
    //   894: aload 7
    //   896: invokevirtual 567	com/google/android/gms/measurement/internal/zzar:zzd	(Ljava/lang/String;Ljava/lang/Object;Ljava/lang/Object;Ljava/lang/Object;)V
    //   899: aload_0
    //   900: iconst_1
    //   901: putfield 1552	com/google/android/gms/measurement/internal/zzfa:zzatq	Z
    //   904: aload_0
    //   905: invokevirtual 714	com/google/android/gms/measurement/internal/zzfa:zzlo	()Lcom/google/android/gms/measurement/internal/zzat;
    //   908: astore 7
    //   910: new 2309	com/google/android/gms/measurement/internal/zzfc
    //   913: dup
    //   914: aload_0
    //   915: aload 11
    //   917: invokespecial 2312	com/google/android/gms/measurement/internal/zzfc:<init>	(Lcom/google/android/gms/measurement/internal/zzfa;Ljava/lang/String;)V
    //   920: astore 8
    //   922: aload 7
    //   924: invokevirtual 349	com/google/android/gms/measurement/internal/zzco:zzaf	()V
    //   927: aload 7
    //   929: invokevirtual 531	com/google/android/gms/measurement/internal/zzez:zzcl	()V
    //   932: aload 13
    //   934: invokestatic 67	com/google/android/gms/common/internal/Preconditions:checkNotNull	(Ljava/lang/Object;)Ljava/lang/Object;
    //   937: pop
    //   938: aload 12
    //   940: invokestatic 67	com/google/android/gms/common/internal/Preconditions:checkNotNull	(Ljava/lang/Object;)Ljava/lang/Object;
    //   943: pop
    //   944: aload 8
    //   946: invokestatic 67	com/google/android/gms/common/internal/Preconditions:checkNotNull	(Ljava/lang/Object;)Ljava/lang/Object;
    //   949: pop
    //   950: aload 7
    //   952: invokevirtual 718	com/google/android/gms/measurement/internal/zzco:zzgn	()Lcom/google/android/gms/measurement/internal/zzbo;
    //   955: new 720	com/google/android/gms/measurement/internal/zzax
    //   958: dup
    //   959: aload 7
    //   961: aload 11
    //   963: aload 13
    //   965: aload 12
    //   967: aconst_null
    //   968: aload 8
    //   970: invokespecial 723	com/google/android/gms/measurement/internal/zzax:<init>	(Lcom/google/android/gms/measurement/internal/zzat;Ljava/lang/String;Ljava/net/URL;[BLjava/util/Map;Lcom/google/android/gms/measurement/internal/zzav;)V
    //   973: invokevirtual 725	com/google/android/gms/measurement/internal/zzbo:zzd	(Ljava/lang/Runnable;)V
    //   976: goto +80 -> 1056
    //   979: aload_0
    //   980: getfield 80	com/google/android/gms/measurement/internal/zzfa:zzadj	Lcom/google/android/gms/measurement/internal/zzbt;
    //   983: invokevirtual 152	com/google/android/gms/measurement/internal/zzbt:zzgo	()Lcom/google/android/gms/measurement/internal/zzap;
    //   986: invokevirtual 183	com/google/android/gms/measurement/internal/zzap:zzjd	()Lcom/google/android/gms/measurement/internal/zzar;
    //   989: ldc_w 2314
    //   992: aload 11
    //   994: invokestatic 223	com/google/android/gms/measurement/internal/zzap:zzbv	(Ljava/lang/String;)Ljava/lang/Object;
    //   997: aload 9
    //   999: invokevirtual 312	com/google/android/gms/measurement/internal/zzar:zze	(Ljava/lang/String;Ljava/lang/Object;Ljava/lang/Object;)V
    //   1002: goto +54 -> 1056
    //   1005: aload_0
    //   1006: ldc2_w 81
    //   1009: putfield 84	com/google/android/gms/measurement/internal/zzfa:zzatw	J
    //   1012: aload_0
    //   1013: invokevirtual 492	com/google/android/gms/measurement/internal/zzfa:zzjq	()Lcom/google/android/gms/measurement/internal/zzq;
    //   1016: lload_3
    //   1017: invokestatic 2263	com/google/android/gms/measurement/internal/zzn:zzhx	()J
    //   1020: lsub
    //   1021: invokevirtual 2317	com/google/android/gms/measurement/internal/zzq:zzah	(J)Ljava/lang/String;
    //   1024: astore 7
    //   1026: aload 7
    //   1028: invokestatic 257	android/text/TextUtils:isEmpty	(Ljava/lang/CharSequence;)Z
    //   1031: ifne +25 -> 1056
    //   1034: aload_0
    //   1035: invokevirtual 492	com/google/android/gms/measurement/internal/zzfa:zzjq	()Lcom/google/android/gms/measurement/internal/zzq;
    //   1038: aload 7
    //   1040: invokevirtual 751	com/google/android/gms/measurement/internal/zzq:zzbl	(Ljava/lang/String;)Lcom/google/android/gms/measurement/internal/zzg;
    //   1043: astore 7
    //   1045: aload 7
    //   1047: ifnull +9 -> 1056
    //   1050: aload_0
    //   1051: aload 7
    //   1053: invokespecial 2319	com/google/android/gms/measurement/internal/zzfa:zzb	(Lcom/google/android/gms/measurement/internal/zzg;)V
    //   1056: aload_0
    //   1057: iconst_0
    //   1058: putfield 1554	com/google/android/gms/measurement/internal/zzfa:zzatr	Z
    //   1061: aload_0
    //   1062: invokespecial 1664	com/google/android/gms/measurement/internal/zzfa:zzlw	()V
    //   1065: return
    //   1066: astore 7
    //   1068: aload_0
    //   1069: iconst_0
    //   1070: putfield 1554	com/google/android/gms/measurement/internal/zzfa:zzatr	Z
    //   1073: aload_0
    //   1074: invokespecial 1664	com/google/android/gms/measurement/internal/zzfa:zzlw	()V
    //   1077: aload 7
    //   1079: athrow
    //   1080: astore 7
    //   1082: goto -103 -> 979
    //   1085: iconst_0
    //   1086: istore_1
    //   1087: goto -950 -> 137
    //   1090: aconst_null
    //   1091: astore 8
    //   1093: aload 10
    //   1095: astore 7
    //   1097: aload 8
    //   1099: ifnull -585 -> 514
    //   1102: iconst_0
    //   1103: istore_1
    //   1104: goto -662 -> 442
    //   1107: iload_1
    //   1108: iconst_1
    //   1109: iadd
    //   1110: istore_1
    //   1111: goto -669 -> 442
    //   1114: iconst_0
    //   1115: istore_1
    //   1116: iconst_0
    //   1117: istore_2
    //   1118: goto -538 -> 580
    //   1121: iload_2
    //   1122: iconst_1
    //   1123: iadd
    //   1124: istore_2
    //   1125: goto -545 -> 580
    // Local variable table:
    //   start	length	slot	name	signature
    //   0	1128	0	this	zzfa
    //   133	983	1	i	int
    //   360	765	2	j	int
    //   219	798	3	l1	long
    //   223	52	5	l2	long
    //   31	1021	7	localObject1	Object
    //   1066	12	7	localObject2	Object
    //   1080	1	7	localMalformedURLException	MalformedURLException
    //   1095	1	7	localObject3	Object
    //   419	679	8	localObject4	Object
    //   226	772	9	str1	String
    //   372	722	10	localObject5	Object
    //   293	700	11	str2	String
    //   683	283	12	localObject6	Object
    //   780	184	13	localURL	URL
    // Exception table:
    //   from	to	target	type
    //   13	33	1066	finally
    //   38	54	1066	finally
    //   64	88	1066	finally
    //   98	111	1066	finally
    //   121	132	1066	finally
    //   141	157	1066	finally
    //   167	197	1066	finally
    //   207	225	1066	finally
    //   228	253	1066	finally
    //   260	286	1066	finally
    //   286	325	1066	finally
    //   325	393	1066	finally
    //   393	439	1066	finally
    //   446	511	1066	finally
    //   514	575	1066	finally
    //   580	702	1066	finally
    //   706	717	1066	finally
    //   724	749	1066	finally
    //   749	771	1066	finally
    //   771	817	1066	finally
    //   820	833	1066	finally
    //   833	847	1066	finally
    //   852	873	1066	finally
    //   873	976	1066	finally
    //   979	1002	1066	finally
    //   1005	1045	1066	finally
    //   1050	1056	1066	finally
    //   771	817	1080	java/net/MalformedURLException
    //   820	833	1080	java/net/MalformedURLException
    //   833	847	1080	java/net/MalformedURLException
    //   852	873	1080	java/net/MalformedURLException
    //   873	976	1080	java/net/MalformedURLException
  }
  
  @WorkerThread
  final void zzly()
  {
    zzaf();
    zzlr();
    if (!zzatk)
    {
      zzadj.zzgo().zzjj().zzbx("This instance being marked as an uploader");
      zzaf();
      zzlr();
      if ((zzlz()) && (zzlx()))
      {
        int i = zza(zzatt);
        int j = zzadj.zzgf().zzja();
        zzaf();
        if (i > j) {
          zzadj.zzgo().zzjd().zze("Panic: can't downgrade version. Previous, current version", Integer.valueOf(i), Integer.valueOf(j));
        } else if (i < j) {
          if (zza(j, zzatt)) {
            zzadj.zzgo().zzjl().zze("Storage version upgraded. Previous, current version", Integer.valueOf(i), Integer.valueOf(j));
          } else {
            zzadj.zzgo().zzjd().zze("Storage version upgrade failed. Previous, current version", Integer.valueOf(i), Integer.valueOf(j));
          }
        }
      }
      zzatk = true;
      zzlv();
    }
  }
  
  final void zzma()
  {
    zzato += 1;
  }
  
  final zzbt zzmb()
  {
    return zzadj;
  }
  
  final void zzo(boolean paramBoolean)
  {
    zzlv();
  }
  
  final class zza
    implements zzs
  {
    zzgi zzaua;
    List<Long> zzaub;
    List<zzgf> zzauc;
    private long zzaud;
    
    private zza() {}
    
    private static long zza(zzgf paramZzgf)
    {
      return zzawu.longValue() / 1000L / 60L / 60L;
    }
    
    public final boolean zza(long paramLong, zzgf paramZzgf)
    {
      Preconditions.checkNotNull(paramZzgf);
      if (zzauc == null) {
        zzauc = new ArrayList();
      }
      if (zzaub == null) {
        zzaub = new ArrayList();
      }
      if ((zzauc.size() > 0) && (zza((zzgf)zzauc.get(0)) != zza(paramZzgf))) {
        return false;
      }
      long l = zzaud + paramZzgf.zzvu();
      if (l >= Math.max(0, ((Integer)zzaf.zzajl.get()).intValue())) {
        return false;
      }
      zzaud = l;
      zzauc.add(paramZzgf);
      zzaub.add(Long.valueOf(paramLong));
      return zzauc.size() < Math.max(1, ((Integer)zzaf.zzajm.get()).intValue());
    }
    
    public final void zzb(zzgi paramZzgi)
    {
      Preconditions.checkNotNull(paramZzgi);
      zzaua = paramZzgi;
    }
  }
}
