package com.google.android.gms.common.internal;

import android.accounts.Account;

public class AccountAccessor
  extends IAccountAccessor.Stub
{
  /* Error */
  @com.google.android.gms.common.annotation.KeepForSdk
  public static Account getAccountBinderSafe(IAccountAccessor paramIAccountAccessor)
  {
    // Byte code:
    //   0: aload_0
    //   1: ifnull +45 -> 46
    //   4: invokestatic 15	android/os/Binder:clearCallingIdentity	()J
    //   7: lstore_1
    //   8: aload_0
    //   9: invokeinterface 21 1 0
    //   14: astore_0
    //   15: lload_1
    //   16: invokestatic 25	android/os/Binder:restoreCallingIdentity	(J)V
    //   19: aload_0
    //   20: areturn
    //   21: astore_0
    //   22: goto +18 -> 40
    //   25: ldc 27
    //   27: ldc 29
    //   29: invokestatic 35	android/util/Log:w	(Ljava/lang/String;Ljava/lang/String;)I
    //   32: pop
    //   33: lload_1
    //   34: invokestatic 25	android/os/Binder:restoreCallingIdentity	(J)V
    //   37: goto +9 -> 46
    //   40: lload_1
    //   41: invokestatic 25	android/os/Binder:restoreCallingIdentity	(J)V
    //   44: aload_0
    //   45: athrow
    //   46: aconst_null
    //   47: areturn
    //   48: astore_0
    //   49: goto -24 -> 25
    // Local variable table:
    //   start	length	slot	name	signature
    //   0	52	0	paramIAccountAccessor	IAccountAccessor
    //   7	34	1	l	long
    // Exception table:
    //   from	to	target	type
    //   8	15	21	finally
    //   25	33	21	finally
    //   8	15	48	android/os/RemoteException
  }
  
  public boolean equals(Object paramObject)
  {
    throw new NoSuchMethodError();
  }
  
  public final Account getAccount()
  {
    throw new NoSuchMethodError();
  }
}
