package com.google.android.gms.internal.measurement;

import java.io.IOException;
import java.lang.reflect.Field;
import java.util.Arrays;
import java.util.Collection;
import java.util.Iterator;
import java.util.List;
import java.util.Map;
import java.util.Map.Entry;
import java.util.Set;
import sun.misc.Unsafe;

final class zzwx<T>
  implements zzxj<T>
{
  private static final int[] zzcax = new int[0];
  private static final Unsafe zzcay = zzyh.zzyk();
  private final int[] zzcaz;
  private final Object[] zzcba;
  private final int zzcbb;
  private final int zzcbc;
  private final zzwt zzcbd;
  private final boolean zzcbe;
  private final boolean zzcbf;
  private final boolean zzcbg;
  private final boolean zzcbh;
  private final int[] zzcbi;
  private final int zzcbj;
  private final int zzcbk;
  private final zzxa zzcbl;
  private final zzwd zzcbm;
  private final zzyb<?, ?> zzcbn;
  private final zzva<?> zzcbo;
  private final zzwo zzcbp;
  
  private zzwx(int[] paramArrayOfInt1, Object[] paramArrayOfObject, int paramInt1, int paramInt2, zzwt paramZzwt, boolean paramBoolean1, boolean paramBoolean2, int[] paramArrayOfInt2, int paramInt3, int paramInt4, zzxa paramZzxa, zzwd paramZzwd, zzyb<?, ?> paramZzyb, zzva<?> paramZzva, zzwo paramZzwo)
  {
    zzcaz = paramArrayOfInt1;
    zzcba = paramArrayOfObject;
    zzcbb = paramInt1;
    zzcbc = paramInt2;
    zzcbf = (paramZzwt instanceof zzvm);
    zzcbg = paramBoolean1;
    if ((paramZzva != null) && (paramZzva.zze(paramZzwt))) {
      paramBoolean1 = true;
    } else {
      paramBoolean1 = false;
    }
    zzcbe = paramBoolean1;
    zzcbh = false;
    zzcbi = paramArrayOfInt2;
    zzcbj = paramInt3;
    zzcbk = paramInt4;
    zzcbl = paramZzxa;
    zzcbm = paramZzwd;
    zzcbn = paramZzyb;
    zzcbo = paramZzva;
    zzcbd = paramZzwt;
    zzcbp = paramZzwo;
  }
  
  private static <UT, UB> int zza(zzyb<UT, UB> paramZzyb, T paramT)
  {
    return paramZzyb.zzae(paramZzyb.zzah(paramT));
  }
  
  static <T> zzwx<T> zza(Class<T> paramClass, zzwr paramZzwr, zzxa paramZzxa, zzwd paramZzwd, zzyb<?, ?> paramZzyb, zzva<?> paramZzva, zzwo paramZzwo)
  {
    if ((paramZzwr instanceof zzxh))
    {
      zzxh localZzxh = (zzxh)paramZzwr;
      int i = localZzxh.zzxg();
      int j = zzvm.zze.zzbzc;
      int n = 0;
      boolean bool;
      if (i == j) {
        bool = true;
      } else {
        bool = false;
      }
      String str = localZzxh.zzxp();
      int i8 = str.length();
      int i4 = str.charAt(0);
      if (i4 >= 55296)
      {
        k = i4 & 0x1FFF;
        m = 1;
        j = 13;
        for (;;)
        {
          i = m + 1;
          m = str.charAt(m);
          if (m < 55296) {
            break;
          }
          k |= (m & 0x1FFF) << j;
          j += 13;
          m = i;
        }
        i4 = m << j | k;
      }
      else
      {
        i = 1;
      }
      j = i + 1;
      i = str.charAt(i);
      if (i >= 55296)
      {
        k = i & 0x1FFF;
        i = 13;
        for (m = j;; m = j)
        {
          j = m + 1;
          m = str.charAt(m);
          if (m < 55296) {
            break;
          }
          k |= (m & 0x1FFF) << i;
          i += 13;
        }
        i = k | m << i;
      }
      int i5;
      int i1;
      if (i == 0)
      {
        paramClass = zzcax;
        i2 = 0;
        i5 = 0;
        k = 0;
        i1 = 0;
        m = 0;
        i3 = 0;
        i = n;
        n = i2;
      }
      else
      {
        k = j + 1;
        i = str.charAt(j);
        if (i >= 55296)
        {
          m = i & 0x1FFF;
          i = 13;
          for (;;)
          {
            j = k + 1;
            k = str.charAt(k);
            if (k < 55296) {
              break;
            }
            m |= (k & 0x1FFF) << i;
            i += 13;
            k = j;
          }
          i = k << i | m;
          k = j;
        }
        j = k + 1;
        i3 = str.charAt(k);
        if (i3 >= 55296)
        {
          m = i3 & 0x1FFF;
          k = 13;
          for (n = j;; n = j)
          {
            j = n + 1;
            n = str.charAt(n);
            if (n < 55296) {
              break;
            }
            m |= (n & 0x1FFF) << k;
            k += 13;
          }
          i3 = m | n << k;
        }
        k = j + 1;
        j = str.charAt(j);
        if (j >= 55296)
        {
          m = j & 0x1FFF;
          j = 13;
          for (n = k;; n = k)
          {
            k = n + 1;
            n = str.charAt(n);
            if (n < 55296) {
              break;
            }
            m |= (n & 0x1FFF) << j;
            j += 13;
          }
          j = n << j | m;
        }
        m = k + 1;
        k = str.charAt(k);
        if (k >= 55296)
        {
          n = k & 0x1FFF;
          k = 13;
          for (i1 = m;; i1 = m)
          {
            m = i1 + 1;
            i1 = str.charAt(i1);
            if (i1 < 55296) {
              break;
            }
            n |= (i1 & 0x1FFF) << k;
            k += 13;
          }
          k = i1 << k | n;
        }
        n = m + 1;
        i1 = str.charAt(m);
        i2 = n;
        m = i1;
        if (i1 >= 55296)
        {
          i1 &= 0x1FFF;
          m = 13;
          for (i2 = n;; i2 = n)
          {
            n = i2 + 1;
            i2 = str.charAt(i2);
            if (i2 < 55296) {
              break;
            }
            i1 |= (i2 & 0x1FFF) << m;
            m += 13;
          }
          m = i2 << m | i1;
          i2 = n;
        }
        i1 = i2 + 1;
        i5 = str.charAt(i2);
        n = i5;
        i2 = i1;
        if (i5 >= 55296)
        {
          i2 = i5 & 0x1FFF;
          n = 13;
          for (i5 = i1;; i5 = i1)
          {
            i1 = i5 + 1;
            i5 = str.charAt(i5);
            if (i5 < 55296) {
              break;
            }
            i2 |= (i5 & 0x1FFF) << n;
            n += 13;
          }
          n = i2 | i5 << n;
          i2 = i1;
        }
        i1 = i2 + 1;
        i5 = str.charAt(i2);
        if (i5 >= 55296)
        {
          i2 = 13;
          i5 &= 0x1FFF;
          i6 = i1;
          i1 = i2;
          for (;;)
          {
            i2 = i6 + 1;
            i6 = str.charAt(i6);
            if (i6 < 55296) {
              break;
            }
            i5 |= (i6 & 0x1FFF) << i1;
            i1 += 13;
            i6 = i2;
          }
          i5 |= i6 << i1;
          i1 = i2;
        }
        i6 = i1 + 1;
        i7 = str.charAt(i1);
        i2 = i7;
        i1 = i6;
        if (i7 >= 55296)
        {
          i1 = 13;
          i2 = i7 & 0x1FFF;
          i7 = i6;
          i6 = i2;
          for (;;)
          {
            i2 = i7 + 1;
            i7 = str.charAt(i7);
            if (i7 < 55296) {
              break;
            }
            i6 |= (i7 & 0x1FFF) << i1;
            i1 += 13;
            i7 = i2;
          }
          i6 |= i7 << i1;
          i1 = i2;
          i2 = i6;
        }
        paramClass = new int[i2 + n + i5];
        i3 = (i << 1) + i3;
        i5 = j;
        j = i1;
        i1 = k;
        k = i5;
        i5 = i;
        i = i2;
      }
      Unsafe localUnsafe = zzcay;
      Object[] arrayOfObject = localZzxh.zzxq();
      Class localClass = localZzxh.zzxi().getClass();
      int[] arrayOfInt = new int[m * 3];
      paramZzwr = new Object[m << 1];
      int i15 = i + n;
      n = i;
      int m = i3;
      int i2 = j;
      int i3 = 0;
      int i9 = 0;
      int i10 = i15;
      j = n;
      n = i3;
      i3 = i1;
      int i6 = k;
      int k = i2;
      int i7 = i;
      while (k < i8)
      {
        i = k + 1;
        int i11 = str.charAt(k);
        if (i11 >= 55296)
        {
          k = 13;
          i1 = i11 & 0x1FFF;
          i2 = i;
          i = k;
          for (;;)
          {
            k = i2 + 1;
            i2 = str.charAt(i2);
            if (i2 < 55296) {
              break;
            }
            i1 |= (i2 & 0x1FFF) << i;
            i += 13;
            i2 = k;
          }
          i11 = i1 | i2 << i;
        }
        else
        {
          k = i;
        }
        i = k + 1;
        int i12 = str.charAt(k);
        if (i12 >= 55296)
        {
          k = 13;
          i1 = i12 & 0x1FFF;
          i2 = i;
          i = k;
          for (;;)
          {
            k = i2 + 1;
            i2 = str.charAt(i2);
            if (i2 < 55296) {
              break;
            }
            i1 |= (i2 & 0x1FFF) << i;
            i += 13;
            i2 = k;
          }
          i12 = i1 | i2 << i;
          i1 = k;
        }
        else
        {
          i1 = i;
        }
        int i16 = i12 & 0xFF;
        k = n;
        if ((i12 & 0x400) != 0)
        {
          paramClass[n] = i9;
          k = n + 1;
        }
        Object localObject;
        int i14;
        int i13;
        if (i16 > zzvg.zzbxs.id())
        {
          i = i1 + 1;
          n = str.charAt(i1);
          if (n >= 55296)
          {
            n &= 0x1FFF;
            i1 = i;
            i = 13;
            for (;;)
            {
              i2 = i1 + 1;
              i1 = str.charAt(i1);
              if (i1 < 55296) {
                break;
              }
              n |= (i1 & 0x1FFF) << i;
              i += 13;
              i1 = i2;
            }
            n |= i1 << i;
          }
          else
          {
            i2 = i;
          }
          if ((i16 != zzvg.zzbwd.id() + 51) && (i16 != zzvg.zzbwl.id() + 51))
          {
            if ((i16 == zzvg.zzbwg.id() + 51) && ((i4 & 0x1) == 1))
            {
              paramZzwr[((i9 / 3 << 1) + 1)] = arrayOfObject[m];
              i = m + 1;
            }
            else
            {
              i = m;
            }
          }
          else
          {
            i1 = i9 / 3;
            i = m + 1;
            paramZzwr[((i1 << 1) + 1)] = arrayOfObject[m];
          }
          m = n << 1;
          localObject = arrayOfObject[m];
          if ((localObject instanceof Field)) {
            localObject = (Field)localObject;
          }
          for (;;)
          {
            break;
            localObject = zza(localClass, (String)localObject);
            arrayOfObject[m] = localObject;
          }
          i14 = (int)localUnsafe.objectFieldOffset((Field)localObject);
          m += 1;
          localObject = arrayOfObject[m];
          if ((localObject instanceof Field)) {
            localObject = (Field)localObject;
          }
          for (;;)
          {
            break;
            localObject = zza(localClass, (String)localObject);
            arrayOfObject[m] = localObject;
          }
          i1 = (int)localUnsafe.objectFieldOffset((Field)localObject);
          n = 0;
          i13 = j;
          j = i2;
        }
        else
        {
          i = m + 1;
          localObject = zza(localClass, (String)arrayOfObject[m]);
          if ((i16 != zzvg.zzbwd.id()) && (i16 != zzvg.zzbwl.id()))
          {
            if ((i16 != zzvg.zzbwv.id()) && (i16 != zzvg.zzbxr.id()))
            {
              if ((i16 != zzvg.zzbwg.id()) && (i16 != zzvg.zzbwy.id()) && (i16 != zzvg.zzbxm.id()))
              {
                if (i16 == zzvg.zzbxs.id())
                {
                  paramClass[j] = i9;
                  n = i9 / 3 << 1;
                  m = i + 1;
                  paramZzwr[n] = arrayOfObject[i];
                  if ((i12 & 0x800) != 0)
                  {
                    i = m + 1;
                    paramZzwr[(n + 1)] = arrayOfObject[m];
                  }
                  else
                  {
                    i = m;
                  }
                  m = j + 1;
                  break label2193;
                }
                break label2189;
              }
              if ((i4 & 0x1) != 1) {
                break label2189;
              }
              n = i9 / 3;
              m = i + 1;
              paramZzwr[((n << 1) + 1)] = arrayOfObject[i];
              i = m;
            }
            else
            {
              n = i9 / 3;
              m = i + 1;
              paramZzwr[((n << 1) + 1)] = arrayOfObject[i];
              i = m;
            }
            m = j;
            break label2193;
          }
          else
          {
            paramZzwr[((i9 / 3 << 1) + 1)] = ((Field)localObject).getType();
          }
          label2189:
          m = j;
          label2193:
          i14 = (int)localUnsafe.objectFieldOffset((Field)localObject);
          if (((i4 & 0x1) == 1) && (i16 <= zzvg.zzbwl.id()))
          {
            n = i1 + 1;
            i2 = str.charAt(i1);
            i1 = i2;
            j = n;
            if (i2 >= 55296)
            {
              i1 = i2 & 0x1FFF;
              j = 13;
              for (i2 = n;; i2 = n)
              {
                n = i2 + 1;
                i2 = str.charAt(i2);
                if (i2 < 55296) {
                  break;
                }
                i1 |= (i2 & 0x1FFF) << j;
                j += 13;
              }
              i1 |= i2 << j;
              j = n;
            }
            n = (i5 << 1) + i1 / 32;
            localObject = arrayOfObject[n];
            if ((localObject instanceof Field))
            {
              localObject = (Field)localObject;
            }
            else
            {
              localObject = zza(localClass, (String)localObject);
              arrayOfObject[n] = localObject;
            }
            i2 = (int)localUnsafe.objectFieldOffset((Field)localObject);
            n = i1 % 32;
            i1 = i2;
            i13 = m;
          }
          else
          {
            j = i1;
            n = 0;
            i1 = 0;
            i13 = m;
          }
        }
        i2 = i10;
        if (i16 >= 18)
        {
          i2 = i10;
          if (i16 <= 49)
          {
            paramClass[i10] = i14;
            i2 = i10 + 1;
          }
        }
        i10 = i9 + 1;
        arrayOfInt[i9] = i11;
        i11 = i10 + 1;
        if ((i12 & 0x200) != 0) {
          m = 536870912;
        } else {
          m = 0;
        }
        if ((i12 & 0x100) != 0) {
          i9 = 268435456;
        } else {
          i9 = 0;
        }
        arrayOfInt[i10] = (i16 << 20 | i9 | m | i14);
        i9 = i11 + 1;
        arrayOfInt[i11] = (n << 20 | i1);
        n = k;
        k = j;
        m = i;
        i10 = i2;
        j = i13;
      }
      return new zzwx(arrayOfInt, paramZzwr, i6, i3, localZzxh.zzxi(), bool, false, paramClass, i7, i15, paramZzxa, paramZzwd, paramZzyb, paramZzva, paramZzwo);
    }
    ((zzxw)paramZzwr).zzxg();
    throw new NoSuchMethodError();
  }
  
  private final <K, V, UT, UB> UB zza(int paramInt1, int paramInt2, Map<K, V> paramMap, zzvr paramZzvr, UB paramUB, zzyb<UT, UB> paramZzyb)
  {
    zzwm localZzwm = zzcbp.zzad(zzbo(paramInt1));
    Iterator localIterator = paramMap.entrySet().iterator();
    while (localIterator.hasNext())
    {
      Map.Entry localEntry = (Map.Entry)localIterator.next();
      if (!paramZzvr.zzb(((Integer)localEntry.getValue()).intValue()))
      {
        paramMap = paramUB;
        if (paramUB == null) {
          paramMap = paramZzyb.zzye();
        }
        paramUB = zzud.zzam(zzwl.zza(localZzwm, localEntry.getKey(), localEntry.getValue()));
        zzut localZzut = paramUB.zzuf();
        try
        {
          zzwl.zza(localZzut, localZzwm, localEntry.getKey(), localEntry.getValue());
          paramZzyb.zza(paramMap, paramInt2, paramUB.zzue());
          localIterator.remove();
          paramUB = paramMap;
        }
        catch (IOException paramMap)
        {
          throw new RuntimeException(paramMap);
        }
      }
    }
    return paramUB;
  }
  
  private final <UT, UB> UB zza(Object paramObject, int paramInt, UB paramUB, zzyb<UT, UB> paramZzyb)
  {
    int i = zzcaz[paramInt];
    paramObject = zzyh.zzp(paramObject, zzbq(paramInt) & 0xFFFFF);
    if (paramObject == null) {
      return paramUB;
    }
    zzvr localZzvr = zzbp(paramInt);
    if (localZzvr == null) {
      return paramUB;
    }
    return zza(paramInt, i, zzcbp.zzy(paramObject), localZzvr, paramUB, paramZzyb);
  }
  
  private static Field zza(Class<?> paramClass, String paramString)
  {
    try
    {
      localObject1 = paramClass.getDeclaredField(paramString);
      return localObject1;
    }
    catch (NoSuchFieldException localNoSuchFieldException)
    {
      Object localObject1;
      int j;
      int i;
      Object localObject2;
      for (;;) {}
    }
    localObject1 = paramClass.getDeclaredFields();
    j = localObject1.length;
    i = 0;
    while (i < j)
    {
      localObject2 = localObject1[i];
      if (paramString.equals(((Field)localObject2).getName())) {
        return localObject2;
      }
      i += 1;
    }
    paramClass = paramClass.getName();
    localObject1 = Arrays.toString((Object[])localObject1);
    localObject2 = new StringBuilder(String.valueOf(paramString).length() + 40 + String.valueOf(paramClass).length() + String.valueOf(localObject1).length());
    ((StringBuilder)localObject2).append("Field ");
    ((StringBuilder)localObject2).append(paramString);
    ((StringBuilder)localObject2).append(" for ");
    ((StringBuilder)localObject2).append(paramClass);
    ((StringBuilder)localObject2).append(" not found. Known fields are ");
    ((StringBuilder)localObject2).append((String)localObject1);
    throw new RuntimeException(((StringBuilder)localObject2).toString());
  }
  
  private static void zza(int paramInt, Object paramObject, zzyw paramZzyw)
    throws IOException
  {
    if ((paramObject instanceof String))
    {
      paramZzyw.zzb(paramInt, (String)paramObject);
      return;
    }
    paramZzyw.zza(paramInt, (zzud)paramObject);
  }
  
  private static <UT, UB> void zza(zzyb<UT, UB> paramZzyb, T paramT, zzyw paramZzyw)
    throws IOException
  {
    paramZzyb.zza(paramZzyb.zzah(paramT), paramZzyw);
  }
  
  private final <K, V> void zza(zzyw paramZzyw, int paramInt1, Object paramObject, int paramInt2)
    throws IOException
  {
    if (paramObject != null) {
      paramZzyw.zza(paramInt1, zzcbp.zzad(zzbo(paramInt2)), zzcbp.zzz(paramObject));
    }
  }
  
  private final void zza(Object paramObject, int paramInt, zzxi paramZzxi)
    throws IOException
  {
    if (zzbs(paramInt))
    {
      zzyh.zza(paramObject, paramInt & 0xFFFFF, paramZzxi.zzun());
      return;
    }
    if (zzcbf)
    {
      zzyh.zza(paramObject, paramInt & 0xFFFFF, paramZzxi.readString());
      return;
    }
    zzyh.zza(paramObject, paramInt & 0xFFFFF, paramZzxi.zzuo());
  }
  
  private final void zza(T paramT1, T paramT2, int paramInt)
  {
    long l = zzbq(paramInt) & 0xFFFFF;
    if (!zzb(paramT2, paramInt)) {
      return;
    }
    Object localObject = zzyh.zzp(paramT1, l);
    paramT2 = zzyh.zzp(paramT2, l);
    if ((localObject != null) && (paramT2 != null))
    {
      zzyh.zza(paramT1, l, zzvo.zzb(localObject, paramT2));
      zzc(paramT1, paramInt);
      return;
    }
    if (paramT2 != null)
    {
      zzyh.zza(paramT1, l, paramT2);
      zzc(paramT1, paramInt);
    }
  }
  
  private final boolean zza(T paramT, int paramInt1, int paramInt2)
  {
    return zzyh.zzk(paramT, zzbr(paramInt2) & 0xFFFFF) == paramInt1;
  }
  
  private final boolean zza(T paramT, int paramInt1, int paramInt2, int paramInt3)
  {
    if (zzcbg) {
      return zzb(paramT, paramInt1);
    }
    return (paramInt2 & paramInt3) != 0;
  }
  
  private static boolean zza(Object paramObject, int paramInt, zzxj paramZzxj)
  {
    return paramZzxj.zzaf(zzyh.zzp(paramObject, paramInt & 0xFFFFF));
  }
  
  private final void zzb(T paramT, int paramInt1, int paramInt2)
  {
    zzyh.zzb(paramT, zzbr(paramInt2) & 0xFFFFF, paramInt1);
  }
  
  private final void zzb(T paramT, zzyw paramZzyw)
    throws IOException
  {
    if (zzcbe)
    {
      localObject1 = zzcbo.zzs(paramT);
      if (!((zzvd)localObject1).isEmpty())
      {
        localIterator = ((zzvd)localObject1).iterator();
        localObject1 = (Map.Entry)localIterator.next();
        break label53;
      }
    }
    Iterator localIterator = null;
    Object localObject1 = null;
    label53:
    int i = -1;
    int i1 = zzcaz.length;
    Unsafe localUnsafe = zzcay;
    int j = 0;
    int k = 0;
    Object localObject2;
    for (;;)
    {
      localObject2 = localObject1;
      if (j >= i1) {
        break;
      }
      int i3 = zzbq(j);
      int i2 = zzcaz[j];
      int i4 = (0xFF00000 & i3) >>> 20;
      int n;
      int m;
      if ((!zzcbg) && (i4 <= 17))
      {
        n = zzcaz[(j + 2)];
        m = n & 0xFFFFF;
        if (m != i)
        {
          k = localUnsafe.getInt(paramT, m);
          i = m;
        }
        n = 1 << (n >>> 20);
        m = i;
      }
      else
      {
        n = 0;
        m = i;
      }
      for (;;)
      {
        i = j;
        if ((localObject1 == null) || (zzcbo.zzb((Map.Entry)localObject1) > i2)) {
          break;
        }
        zzcbo.zza(paramZzyw, (Map.Entry)localObject1);
        if (localIterator.hasNext()) {
          localObject1 = (Map.Entry)localIterator.next();
        } else {
          localObject1 = null;
        }
      }
      long l = i3 & 0xFFFFF;
      switch (i4)
      {
      }
      for (;;)
      {
        break;
        j = i;
        if (zza(paramT, i2, j))
        {
          paramZzyw.zzb(i2, localUnsafe.getObject(paramT, l), zzbn(j));
          continue;
          if (zza(paramT, i2, i))
          {
            paramZzyw.zzb(i2, zzi(paramT, l));
            continue;
            if (zza(paramT, i2, i))
            {
              paramZzyw.zzf(i2, zzh(paramT, l));
              continue;
              if (zza(paramT, i2, i))
              {
                paramZzyw.zzj(i2, zzi(paramT, l));
                continue;
                if (zza(paramT, i2, i))
                {
                  paramZzyw.zzn(i2, zzh(paramT, l));
                  continue;
                  if (zza(paramT, i2, i))
                  {
                    paramZzyw.zzo(i2, zzh(paramT, l));
                    continue;
                    if (zza(paramT, i2, i))
                    {
                      paramZzyw.zze(i2, zzh(paramT, l));
                      continue;
                      if (zza(paramT, i2, i))
                      {
                        paramZzyw.zza(i2, (zzud)localUnsafe.getObject(paramT, l));
                        continue;
                        j = i;
                        if (zza(paramT, i2, j))
                        {
                          paramZzyw.zza(i2, localUnsafe.getObject(paramT, l), zzbn(j));
                          continue;
                          if (zza(paramT, i2, i))
                          {
                            zza(i2, localUnsafe.getObject(paramT, l), paramZzyw);
                            continue;
                            if (zza(paramT, i2, i))
                            {
                              paramZzyw.zzb(i2, zzj(paramT, l));
                              continue;
                              if (zza(paramT, i2, i))
                              {
                                paramZzyw.zzg(i2, zzh(paramT, l));
                                continue;
                                if (zza(paramT, i2, i))
                                {
                                  paramZzyw.zzc(i2, zzi(paramT, l));
                                  continue;
                                  if (zza(paramT, i2, i))
                                  {
                                    paramZzyw.zzd(i2, zzh(paramT, l));
                                    continue;
                                    if (zza(paramT, i2, i))
                                    {
                                      paramZzyw.zza(i2, zzi(paramT, l));
                                      continue;
                                      if (zza(paramT, i2, i))
                                      {
                                        paramZzyw.zzi(i2, zzi(paramT, l));
                                        continue;
                                        if (zza(paramT, i2, i))
                                        {
                                          paramZzyw.zza(i2, zzg(paramT, l));
                                          continue;
                                          if (zza(paramT, i2, i))
                                          {
                                            paramZzyw.zza(i2, zzf(paramT, l));
                                            continue;
                                            zza(paramZzyw, i2, localUnsafe.getObject(paramT, l), i);
                                            continue;
                                            j = i;
                                            zzxl.zzb(zzcaz[j], (List)localUnsafe.getObject(paramT, l), paramZzyw, zzbn(j));
                                            continue;
                                            zzxl.zze(zzcaz[i], (List)localUnsafe.getObject(paramT, l), paramZzyw, true);
                                            continue;
                                            zzxl.zzj(zzcaz[i], (List)localUnsafe.getObject(paramT, l), paramZzyw, true);
                                            continue;
                                            zzxl.zzg(zzcaz[i], (List)localUnsafe.getObject(paramT, l), paramZzyw, true);
                                            continue;
                                            zzxl.zzl(zzcaz[i], (List)localUnsafe.getObject(paramT, l), paramZzyw, true);
                                            continue;
                                            zzxl.zzm(zzcaz[i], (List)localUnsafe.getObject(paramT, l), paramZzyw, true);
                                            continue;
                                            zzxl.zzi(zzcaz[i], (List)localUnsafe.getObject(paramT, l), paramZzyw, true);
                                            continue;
                                            zzxl.zzn(zzcaz[i], (List)localUnsafe.getObject(paramT, l), paramZzyw, true);
                                            continue;
                                            zzxl.zzk(zzcaz[i], (List)localUnsafe.getObject(paramT, l), paramZzyw, true);
                                            continue;
                                            zzxl.zzf(zzcaz[i], (List)localUnsafe.getObject(paramT, l), paramZzyw, true);
                                            continue;
                                            zzxl.zzh(zzcaz[i], (List)localUnsafe.getObject(paramT, l), paramZzyw, true);
                                            continue;
                                            zzxl.zzd(zzcaz[i], (List)localUnsafe.getObject(paramT, l), paramZzyw, true);
                                            continue;
                                            zzxl.zzc(zzcaz[i], (List)localUnsafe.getObject(paramT, l), paramZzyw, true);
                                            continue;
                                            zzxl.zzb(zzcaz[i], (List)localUnsafe.getObject(paramT, l), paramZzyw, true);
                                            continue;
                                            zzxl.zza(zzcaz[i], (List)localUnsafe.getObject(paramT, l), paramZzyw, true);
                                            continue;
                                            zzxl.zze(zzcaz[i], (List)localUnsafe.getObject(paramT, l), paramZzyw, false);
                                            continue;
                                            zzxl.zzj(zzcaz[i], (List)localUnsafe.getObject(paramT, l), paramZzyw, false);
                                            continue;
                                            zzxl.zzg(zzcaz[i], (List)localUnsafe.getObject(paramT, l), paramZzyw, false);
                                            continue;
                                            zzxl.zzl(zzcaz[i], (List)localUnsafe.getObject(paramT, l), paramZzyw, false);
                                            continue;
                                            zzxl.zzm(zzcaz[i], (List)localUnsafe.getObject(paramT, l), paramZzyw, false);
                                            continue;
                                            zzxl.zzi(zzcaz[i], (List)localUnsafe.getObject(paramT, l), paramZzyw, false);
                                            continue;
                                            zzxl.zzb(zzcaz[i], (List)localUnsafe.getObject(paramT, l), paramZzyw);
                                            continue;
                                            j = i;
                                            zzxl.zza(zzcaz[j], (List)localUnsafe.getObject(paramT, l), paramZzyw, zzbn(j));
                                            continue;
                                            zzxl.zza(zzcaz[i], (List)localUnsafe.getObject(paramT, l), paramZzyw);
                                            continue;
                                            zzxl.zzn(zzcaz[i], (List)localUnsafe.getObject(paramT, l), paramZzyw, false);
                                            break;
                                            zzxl.zzk(zzcaz[i], (List)localUnsafe.getObject(paramT, l), paramZzyw, false);
                                            break;
                                            zzxl.zzf(zzcaz[i], (List)localUnsafe.getObject(paramT, l), paramZzyw, false);
                                            break;
                                            zzxl.zzh(zzcaz[i], (List)localUnsafe.getObject(paramT, l), paramZzyw, false);
                                            break;
                                            zzxl.zzd(zzcaz[i], (List)localUnsafe.getObject(paramT, l), paramZzyw, false);
                                            break;
                                            zzxl.zzc(zzcaz[i], (List)localUnsafe.getObject(paramT, l), paramZzyw, false);
                                            break;
                                            zzxl.zzb(zzcaz[i], (List)localUnsafe.getObject(paramT, l), paramZzyw, false);
                                            break;
                                            zzxl.zza(zzcaz[i], (List)localUnsafe.getObject(paramT, l), paramZzyw, false);
                                            break;
                                            if ((n & k) != 0)
                                            {
                                              paramZzyw.zzb(i2, localUnsafe.getObject(paramT, l), zzbn(i));
                                              break;
                                              if ((n & k) != 0)
                                              {
                                                paramZzyw.zzb(i2, localUnsafe.getLong(paramT, l));
                                                break;
                                                if ((n & k) != 0)
                                                {
                                                  paramZzyw.zzf(i2, localUnsafe.getInt(paramT, l));
                                                  break;
                                                  if ((n & k) != 0)
                                                  {
                                                    paramZzyw.zzj(i2, localUnsafe.getLong(paramT, l));
                                                    break;
                                                    if ((n & k) != 0)
                                                    {
                                                      paramZzyw.zzn(i2, localUnsafe.getInt(paramT, l));
                                                      break;
                                                      if ((n & k) != 0)
                                                      {
                                                        paramZzyw.zzo(i2, localUnsafe.getInt(paramT, l));
                                                        break;
                                                        if ((n & k) != 0)
                                                        {
                                                          paramZzyw.zze(i2, localUnsafe.getInt(paramT, l));
                                                          break;
                                                          if ((n & k) != 0)
                                                          {
                                                            paramZzyw.zza(i2, (zzud)localUnsafe.getObject(paramT, l));
                                                            break;
                                                            if ((n & k) != 0)
                                                            {
                                                              paramZzyw.zza(i2, localUnsafe.getObject(paramT, l), zzbn(i));
                                                              break;
                                                              if ((n & k) != 0)
                                                              {
                                                                zza(i2, localUnsafe.getObject(paramT, l), paramZzyw);
                                                                break;
                                                                if ((n & k) != 0)
                                                                {
                                                                  paramZzyw.zzb(i2, zzyh.zzm(paramT, l));
                                                                  break;
                                                                  if ((n & k) != 0)
                                                                  {
                                                                    paramZzyw.zzg(i2, localUnsafe.getInt(paramT, l));
                                                                    break;
                                                                    if ((n & k) != 0)
                                                                    {
                                                                      paramZzyw.zzc(i2, localUnsafe.getLong(paramT, l));
                                                                      break;
                                                                      if ((n & k) != 0)
                                                                      {
                                                                        paramZzyw.zzd(i2, localUnsafe.getInt(paramT, l));
                                                                        break;
                                                                        if ((n & k) != 0)
                                                                        {
                                                                          paramZzyw.zza(i2, localUnsafe.getLong(paramT, l));
                                                                          break;
                                                                          if ((n & k) != 0)
                                                                          {
                                                                            paramZzyw.zzi(i2, localUnsafe.getLong(paramT, l));
                                                                            break;
                                                                            if ((n & k) != 0)
                                                                            {
                                                                              paramZzyw.zza(i2, zzyh.zzn(paramT, l));
                                                                              break;
                                                                              if ((n & k) != 0) {
                                                                                paramZzyw.zza(i2, zzyh.zzo(paramT, l));
                                                                              }
                                                                            }
                                                                          }
                                                                        }
                                                                      }
                                                                    }
                                                                  }
                                                                }
                                                              }
                                                            }
                                                          }
                                                        }
                                                      }
                                                    }
                                                  }
                                                }
                                              }
                                            }
                                          }
                                        }
                                      }
                                    }
                                  }
                                }
                              }
                            }
                          }
                        }
                      }
                    }
                  }
                }
              }
            }
          }
        }
      }
      j = i + 3;
      i = m;
    }
    while (localObject2 != null)
    {
      zzcbo.zza(paramZzyw, (Map.Entry)localObject2);
      if (localIterator.hasNext()) {
        localObject2 = (Map.Entry)localIterator.next();
      } else {
        localObject2 = null;
      }
    }
    zza(zzcbn, paramT, paramZzyw);
  }
  
  private final void zzb(T paramT1, T paramT2, int paramInt)
  {
    int i = zzbq(paramInt);
    int j = zzcaz[paramInt];
    long l = i & 0xFFFFF;
    if (!zza(paramT2, j, paramInt)) {
      return;
    }
    Object localObject = zzyh.zzp(paramT1, l);
    paramT2 = zzyh.zzp(paramT2, l);
    if ((localObject != null) && (paramT2 != null))
    {
      zzyh.zza(paramT1, l, zzvo.zzb(localObject, paramT2));
      zzb(paramT1, j, paramInt);
      return;
    }
    if (paramT2 != null)
    {
      zzyh.zza(paramT1, l, paramT2);
      zzb(paramT1, j, paramInt);
    }
  }
  
  private final boolean zzb(T paramT, int paramInt)
  {
    if (zzcbg)
    {
      paramInt = zzbq(paramInt);
      long l = paramInt & 0xFFFFF;
      switch ((paramInt & 0xFF00000) >>> 20)
      {
      default: 
        throw new IllegalArgumentException();
      case 17: 
        return zzyh.zzp(paramT, l) != null;
      case 16: 
        return zzyh.zzl(paramT, l) != 0L;
      case 15: 
        return zzyh.zzk(paramT, l) != 0;
      case 14: 
        return zzyh.zzl(paramT, l) != 0L;
      case 13: 
        return zzyh.zzk(paramT, l) != 0;
      case 12: 
        return zzyh.zzk(paramT, l) != 0;
      case 11: 
        return zzyh.zzk(paramT, l) != 0;
      case 10: 
        return !zzud.zzbtz.equals(zzyh.zzp(paramT, l));
      case 9: 
        return zzyh.zzp(paramT, l) != null;
      case 8: 
        paramT = zzyh.zzp(paramT, l);
        if ((paramT instanceof String)) {
          return !((String)paramT).isEmpty();
        }
        if ((paramT instanceof zzud)) {
          return !zzud.zzbtz.equals(paramT);
        }
        throw new IllegalArgumentException();
      case 7: 
        return zzyh.zzm(paramT, l);
      case 6: 
        return zzyh.zzk(paramT, l) != 0;
      case 5: 
        return zzyh.zzl(paramT, l) != 0L;
      case 4: 
        return zzyh.zzk(paramT, l) != 0;
      case 3: 
        return zzyh.zzl(paramT, l) != 0L;
      case 2: 
        return zzyh.zzl(paramT, l) != 0L;
      case 1: 
        return zzyh.zzn(paramT, l) != 0.0F;
      }
      return zzyh.zzo(paramT, l) != 0.0D;
    }
    paramInt = zzbr(paramInt);
    return (zzyh.zzk(paramT, paramInt & 0xFFFFF) & 1 << (paramInt >>> 20)) != 0;
  }
  
  private final zzxj zzbn(int paramInt)
  {
    paramInt = paramInt / 3 << 1;
    zzxj localZzxj = (zzxj)zzcba[paramInt];
    if (localZzxj != null) {
      return localZzxj;
    }
    localZzxj = zzxf.zzxn().zzi((Class)zzcba[(paramInt + 1)]);
    zzcba[paramInt] = localZzxj;
    return localZzxj;
  }
  
  private final Object zzbo(int paramInt)
  {
    return zzcba[(paramInt / 3 << 1)];
  }
  
  private final zzvr zzbp(int paramInt)
  {
    return (zzvr)zzcba[((paramInt / 3 << 1) + 1)];
  }
  
  private final int zzbq(int paramInt)
  {
    return zzcaz[(paramInt + 1)];
  }
  
  private final int zzbr(int paramInt)
  {
    return zzcaz[(paramInt + 2)];
  }
  
  private static boolean zzbs(int paramInt)
  {
    return (paramInt & 0x20000000) != 0;
  }
  
  private final void zzc(T paramT, int paramInt)
  {
    if (zzcbg) {
      return;
    }
    paramInt = zzbr(paramInt);
    long l = paramInt & 0xFFFFF;
    zzyh.zzb(paramT, l, zzyh.zzk(paramT, l) | 1 << (paramInt >>> 20));
  }
  
  private final boolean zzc(T paramT1, T paramT2, int paramInt)
  {
    return zzb(paramT1, paramInt) == zzb(paramT2, paramInt);
  }
  
  private static <E> List<E> zze(Object paramObject, long paramLong)
  {
    return (List)zzyh.zzp(paramObject, paramLong);
  }
  
  private static <T> double zzf(T paramT, long paramLong)
  {
    return ((Double)zzyh.zzp(paramT, paramLong)).doubleValue();
  }
  
  private static <T> float zzg(T paramT, long paramLong)
  {
    return ((Float)zzyh.zzp(paramT, paramLong)).floatValue();
  }
  
  private static <T> int zzh(T paramT, long paramLong)
  {
    return ((Integer)zzyh.zzp(paramT, paramLong)).intValue();
  }
  
  private static <T> long zzi(T paramT, long paramLong)
  {
    return ((Long)zzyh.zzp(paramT, paramLong)).longValue();
  }
  
  private static <T> boolean zzj(T paramT, long paramLong)
  {
    return ((Boolean)zzyh.zzp(paramT, paramLong)).booleanValue();
  }
  
  /* Error */
  public final boolean equals(T paramT1, T paramT2)
  {
    // Byte code:
    //   0: aload_0
    //   1: getfield 58	com/google/android/gms/internal/measurement/zzwx:zzcaz	[I
    //   4: arraylength
    //   5: istore 4
    //   7: iconst_0
    //   8: istore_3
    //   9: iconst_1
    //   10: istore 6
    //   12: iload_3
    //   13: iload 4
    //   15: if_icmpge +944 -> 959
    //   18: aload_0
    //   19: iload_3
    //   20: invokespecial 304	com/google/android/gms/internal/measurement/zzwx:zzbq	(I)I
    //   23: istore 5
    //   25: iload 5
    //   27: ldc_w 305
    //   30: iand
    //   31: i2l
    //   32: lstore 7
    //   34: iload 5
    //   36: ldc_w 457
    //   39: iand
    //   40: bipush 20
    //   42: iushr
    //   43: tableswitch	default:+289->332, 0:+873->916, 1:+845->888, 2:+816->859, 3:+787->830, 4:+759->802, 5:+730->773, 6:+702->745, 7:+674->717, 8:+643->686, 9:+612->655, 10:+581->624, 11:+553->596, 12:+525->568, 13:+497->540, 14:+468->511, 15:+440->483, 16:+411->454, 17:+380->423, 18:+360->403, 19:+360->403, 20:+360->403, 21:+360->403, 22:+360->403, 23:+360->403, 24:+360->403, 25:+360->403, 26:+360->403, 27:+360->403, 28:+360->403, 29:+360->403, 30:+360->403, 31:+360->403, 32:+360->403, 33:+360->403, 34:+360->403, 35:+360->403, 36:+360->403, 37:+360->403, 38:+360->403, 39:+360->403, 40:+360->403, 41:+360->403, 42:+360->403, 43:+360->403, 44:+360->403, 45:+360->403, 46:+360->403, 47:+360->403, 48:+360->403, 49:+360->403, 50:+340->383, 51:+292->335, 52:+292->335, 53:+292->335, 54:+292->335, 55:+292->335, 56:+292->335, 57:+292->335, 58:+292->335, 59:+292->335, 60:+292->335, 61:+292->335, 62:+292->335, 63:+292->335, 64:+292->335, 65:+292->335, 66:+292->335, 67:+292->335, 68:+292->335
    //   332: goto +613 -> 945
    //   335: aload_0
    //   336: iload_3
    //   337: invokespecial 430	com/google/android/gms/internal/measurement/zzwx:zzbr	(I)I
    //   340: ldc_w 305
    //   343: iand
    //   344: i2l
    //   345: lstore 9
    //   347: aload_1
    //   348: lload 9
    //   350: invokestatic 434	com/google/android/gms/internal/measurement/zzyh:zzk	(Ljava/lang/Object;J)I
    //   353: aload_2
    //   354: lload 9
    //   356: invokestatic 434	com/google/android/gms/internal/measurement/zzyh:zzk	(Ljava/lang/Object;J)I
    //   359: if_icmpne +583 -> 942
    //   362: aload_1
    //   363: lload 7
    //   365: invokestatic 309	com/google/android/gms/internal/measurement/zzyh:zzp	(Ljava/lang/Object;J)Ljava/lang/Object;
    //   368: aload_2
    //   369: lload 7
    //   371: invokestatic 309	com/google/android/gms/internal/measurement/zzyh:zzp	(Ljava/lang/Object;J)Ljava/lang/Object;
    //   374: invokestatic 655	com/google/android/gms/internal/measurement/zzxl:zze	(Ljava/lang/Object;Ljava/lang/Object;)Z
    //   377: ifne +568 -> 945
    //   380: goto +562 -> 942
    //   383: aload_1
    //   384: lload 7
    //   386: invokestatic 309	com/google/android/gms/internal/measurement/zzyh:zzp	(Ljava/lang/Object;J)Ljava/lang/Object;
    //   389: aload_2
    //   390: lload 7
    //   392: invokestatic 309	com/google/android/gms/internal/measurement/zzyh:zzp	(Ljava/lang/Object;J)Ljava/lang/Object;
    //   395: invokestatic 655	com/google/android/gms/internal/measurement/zzxl:zze	(Ljava/lang/Object;Ljava/lang/Object;)Z
    //   398: istore 6
    //   400: goto +545 -> 945
    //   403: aload_1
    //   404: lload 7
    //   406: invokestatic 309	com/google/android/gms/internal/measurement/zzyh:zzp	(Ljava/lang/Object;J)Ljava/lang/Object;
    //   409: aload_2
    //   410: lload 7
    //   412: invokestatic 309	com/google/android/gms/internal/measurement/zzyh:zzp	(Ljava/lang/Object;J)Ljava/lang/Object;
    //   415: invokestatic 655	com/google/android/gms/internal/measurement/zzxl:zze	(Ljava/lang/Object;Ljava/lang/Object;)Z
    //   418: istore 6
    //   420: goto +525 -> 945
    //   423: aload_0
    //   424: aload_1
    //   425: aload_2
    //   426: iload_3
    //   427: invokespecial 657	com/google/android/gms/internal/measurement/zzwx:zzc	(Ljava/lang/Object;Ljava/lang/Object;I)Z
    //   430: ifeq +512 -> 942
    //   433: aload_1
    //   434: lload 7
    //   436: invokestatic 309	com/google/android/gms/internal/measurement/zzyh:zzp	(Ljava/lang/Object;J)Ljava/lang/Object;
    //   439: aload_2
    //   440: lload 7
    //   442: invokestatic 309	com/google/android/gms/internal/measurement/zzyh:zzp	(Ljava/lang/Object;J)Ljava/lang/Object;
    //   445: invokestatic 655	com/google/android/gms/internal/measurement/zzxl:zze	(Ljava/lang/Object;Ljava/lang/Object;)Z
    //   448: ifne +497 -> 945
    //   451: goto +491 -> 942
    //   454: aload_0
    //   455: aload_1
    //   456: aload_2
    //   457: iload_3
    //   458: invokespecial 657	com/google/android/gms/internal/measurement/zzwx:zzc	(Ljava/lang/Object;Ljava/lang/Object;I)Z
    //   461: ifeq +481 -> 942
    //   464: aload_1
    //   465: lload 7
    //   467: invokestatic 603	com/google/android/gms/internal/measurement/zzyh:zzl	(Ljava/lang/Object;J)J
    //   470: aload_2
    //   471: lload 7
    //   473: invokestatic 603	com/google/android/gms/internal/measurement/zzyh:zzl	(Ljava/lang/Object;J)J
    //   476: lcmp
    //   477: ifeq +468 -> 945
    //   480: goto +462 -> 942
    //   483: aload_0
    //   484: aload_1
    //   485: aload_2
    //   486: iload_3
    //   487: invokespecial 657	com/google/android/gms/internal/measurement/zzwx:zzc	(Ljava/lang/Object;Ljava/lang/Object;I)Z
    //   490: ifeq +452 -> 942
    //   493: aload_1
    //   494: lload 7
    //   496: invokestatic 434	com/google/android/gms/internal/measurement/zzyh:zzk	(Ljava/lang/Object;J)I
    //   499: aload_2
    //   500: lload 7
    //   502: invokestatic 434	com/google/android/gms/internal/measurement/zzyh:zzk	(Ljava/lang/Object;J)I
    //   505: if_icmpeq +440 -> 945
    //   508: goto +434 -> 942
    //   511: aload_0
    //   512: aload_1
    //   513: aload_2
    //   514: iload_3
    //   515: invokespecial 657	com/google/android/gms/internal/measurement/zzwx:zzc	(Ljava/lang/Object;Ljava/lang/Object;I)Z
    //   518: ifeq +424 -> 942
    //   521: aload_1
    //   522: lload 7
    //   524: invokestatic 603	com/google/android/gms/internal/measurement/zzyh:zzl	(Ljava/lang/Object;J)J
    //   527: aload_2
    //   528: lload 7
    //   530: invokestatic 603	com/google/android/gms/internal/measurement/zzyh:zzl	(Ljava/lang/Object;J)J
    //   533: lcmp
    //   534: ifeq +411 -> 945
    //   537: goto +405 -> 942
    //   540: aload_0
    //   541: aload_1
    //   542: aload_2
    //   543: iload_3
    //   544: invokespecial 657	com/google/android/gms/internal/measurement/zzwx:zzc	(Ljava/lang/Object;Ljava/lang/Object;I)Z
    //   547: ifeq +395 -> 942
    //   550: aload_1
    //   551: lload 7
    //   553: invokestatic 434	com/google/android/gms/internal/measurement/zzyh:zzk	(Ljava/lang/Object;J)I
    //   556: aload_2
    //   557: lload 7
    //   559: invokestatic 434	com/google/android/gms/internal/measurement/zzyh:zzk	(Ljava/lang/Object;J)I
    //   562: if_icmpeq +383 -> 945
    //   565: goto +377 -> 942
    //   568: aload_0
    //   569: aload_1
    //   570: aload_2
    //   571: iload_3
    //   572: invokespecial 657	com/google/android/gms/internal/measurement/zzwx:zzc	(Ljava/lang/Object;Ljava/lang/Object;I)Z
    //   575: ifeq +367 -> 942
    //   578: aload_1
    //   579: lload 7
    //   581: invokestatic 434	com/google/android/gms/internal/measurement/zzyh:zzk	(Ljava/lang/Object;J)I
    //   584: aload_2
    //   585: lload 7
    //   587: invokestatic 434	com/google/android/gms/internal/measurement/zzyh:zzk	(Ljava/lang/Object;J)I
    //   590: if_icmpeq +355 -> 945
    //   593: goto +349 -> 942
    //   596: aload_0
    //   597: aload_1
    //   598: aload_2
    //   599: iload_3
    //   600: invokespecial 657	com/google/android/gms/internal/measurement/zzwx:zzc	(Ljava/lang/Object;Ljava/lang/Object;I)Z
    //   603: ifeq +339 -> 942
    //   606: aload_1
    //   607: lload 7
    //   609: invokestatic 434	com/google/android/gms/internal/measurement/zzyh:zzk	(Ljava/lang/Object;J)I
    //   612: aload_2
    //   613: lload 7
    //   615: invokestatic 434	com/google/android/gms/internal/measurement/zzyh:zzk	(Ljava/lang/Object;J)I
    //   618: if_icmpeq +327 -> 945
    //   621: goto +321 -> 942
    //   624: aload_0
    //   625: aload_1
    //   626: aload_2
    //   627: iload_3
    //   628: invokespecial 657	com/google/android/gms/internal/measurement/zzwx:zzc	(Ljava/lang/Object;Ljava/lang/Object;I)Z
    //   631: ifeq +311 -> 942
    //   634: aload_1
    //   635: lload 7
    //   637: invokestatic 309	com/google/android/gms/internal/measurement/zzyh:zzp	(Ljava/lang/Object;J)Ljava/lang/Object;
    //   640: aload_2
    //   641: lload 7
    //   643: invokestatic 309	com/google/android/gms/internal/measurement/zzyh:zzp	(Ljava/lang/Object;J)Ljava/lang/Object;
    //   646: invokestatic 655	com/google/android/gms/internal/measurement/zzxl:zze	(Ljava/lang/Object;Ljava/lang/Object;)Z
    //   649: ifne +296 -> 945
    //   652: goto +290 -> 942
    //   655: aload_0
    //   656: aload_1
    //   657: aload_2
    //   658: iload_3
    //   659: invokespecial 657	com/google/android/gms/internal/measurement/zzwx:zzc	(Ljava/lang/Object;Ljava/lang/Object;I)Z
    //   662: ifeq +280 -> 942
    //   665: aload_1
    //   666: lload 7
    //   668: invokestatic 309	com/google/android/gms/internal/measurement/zzyh:zzp	(Ljava/lang/Object;J)Ljava/lang/Object;
    //   671: aload_2
    //   672: lload 7
    //   674: invokestatic 309	com/google/android/gms/internal/measurement/zzyh:zzp	(Ljava/lang/Object;J)Ljava/lang/Object;
    //   677: invokestatic 655	com/google/android/gms/internal/measurement/zzxl:zze	(Ljava/lang/Object;Ljava/lang/Object;)Z
    //   680: ifne +265 -> 945
    //   683: goto +259 -> 942
    //   686: aload_0
    //   687: aload_1
    //   688: aload_2
    //   689: iload_3
    //   690: invokespecial 657	com/google/android/gms/internal/measurement/zzwx:zzc	(Ljava/lang/Object;Ljava/lang/Object;I)Z
    //   693: ifeq +249 -> 942
    //   696: aload_1
    //   697: lload 7
    //   699: invokestatic 309	com/google/android/gms/internal/measurement/zzyh:zzp	(Ljava/lang/Object;J)Ljava/lang/Object;
    //   702: aload_2
    //   703: lload 7
    //   705: invokestatic 309	com/google/android/gms/internal/measurement/zzyh:zzp	(Ljava/lang/Object;J)Ljava/lang/Object;
    //   708: invokestatic 655	com/google/android/gms/internal/measurement/zzxl:zze	(Ljava/lang/Object;Ljava/lang/Object;)Z
    //   711: ifne +234 -> 945
    //   714: goto +228 -> 942
    //   717: aload_0
    //   718: aload_1
    //   719: aload_2
    //   720: iload_3
    //   721: invokespecial 657	com/google/android/gms/internal/measurement/zzwx:zzc	(Ljava/lang/Object;Ljava/lang/Object;I)Z
    //   724: ifeq +218 -> 942
    //   727: aload_1
    //   728: lload 7
    //   730: invokestatic 589	com/google/android/gms/internal/measurement/zzyh:zzm	(Ljava/lang/Object;J)Z
    //   733: aload_2
    //   734: lload 7
    //   736: invokestatic 589	com/google/android/gms/internal/measurement/zzyh:zzm	(Ljava/lang/Object;J)Z
    //   739: if_icmpeq +206 -> 945
    //   742: goto +200 -> 942
    //   745: aload_0
    //   746: aload_1
    //   747: aload_2
    //   748: iload_3
    //   749: invokespecial 657	com/google/android/gms/internal/measurement/zzwx:zzc	(Ljava/lang/Object;Ljava/lang/Object;I)Z
    //   752: ifeq +190 -> 942
    //   755: aload_1
    //   756: lload 7
    //   758: invokestatic 434	com/google/android/gms/internal/measurement/zzyh:zzk	(Ljava/lang/Object;J)I
    //   761: aload_2
    //   762: lload 7
    //   764: invokestatic 434	com/google/android/gms/internal/measurement/zzyh:zzk	(Ljava/lang/Object;J)I
    //   767: if_icmpeq +178 -> 945
    //   770: goto +172 -> 942
    //   773: aload_0
    //   774: aload_1
    //   775: aload_2
    //   776: iload_3
    //   777: invokespecial 657	com/google/android/gms/internal/measurement/zzwx:zzc	(Ljava/lang/Object;Ljava/lang/Object;I)Z
    //   780: ifeq +162 -> 942
    //   783: aload_1
    //   784: lload 7
    //   786: invokestatic 603	com/google/android/gms/internal/measurement/zzyh:zzl	(Ljava/lang/Object;J)J
    //   789: aload_2
    //   790: lload 7
    //   792: invokestatic 603	com/google/android/gms/internal/measurement/zzyh:zzl	(Ljava/lang/Object;J)J
    //   795: lcmp
    //   796: ifeq +149 -> 945
    //   799: goto +143 -> 942
    //   802: aload_0
    //   803: aload_1
    //   804: aload_2
    //   805: iload_3
    //   806: invokespecial 657	com/google/android/gms/internal/measurement/zzwx:zzc	(Ljava/lang/Object;Ljava/lang/Object;I)Z
    //   809: ifeq +133 -> 942
    //   812: aload_1
    //   813: lload 7
    //   815: invokestatic 434	com/google/android/gms/internal/measurement/zzyh:zzk	(Ljava/lang/Object;J)I
    //   818: aload_2
    //   819: lload 7
    //   821: invokestatic 434	com/google/android/gms/internal/measurement/zzyh:zzk	(Ljava/lang/Object;J)I
    //   824: if_icmpeq +121 -> 945
    //   827: goto +115 -> 942
    //   830: aload_0
    //   831: aload_1
    //   832: aload_2
    //   833: iload_3
    //   834: invokespecial 657	com/google/android/gms/internal/measurement/zzwx:zzc	(Ljava/lang/Object;Ljava/lang/Object;I)Z
    //   837: ifeq +105 -> 942
    //   840: aload_1
    //   841: lload 7
    //   843: invokestatic 603	com/google/android/gms/internal/measurement/zzyh:zzl	(Ljava/lang/Object;J)J
    //   846: aload_2
    //   847: lload 7
    //   849: invokestatic 603	com/google/android/gms/internal/measurement/zzyh:zzl	(Ljava/lang/Object;J)J
    //   852: lcmp
    //   853: ifeq +92 -> 945
    //   856: goto +86 -> 942
    //   859: aload_0
    //   860: aload_1
    //   861: aload_2
    //   862: iload_3
    //   863: invokespecial 657	com/google/android/gms/internal/measurement/zzwx:zzc	(Ljava/lang/Object;Ljava/lang/Object;I)Z
    //   866: ifeq +76 -> 942
    //   869: aload_1
    //   870: lload 7
    //   872: invokestatic 603	com/google/android/gms/internal/measurement/zzyh:zzl	(Ljava/lang/Object;J)J
    //   875: aload_2
    //   876: lload 7
    //   878: invokestatic 603	com/google/android/gms/internal/measurement/zzyh:zzl	(Ljava/lang/Object;J)J
    //   881: lcmp
    //   882: ifeq +63 -> 945
    //   885: goto +57 -> 942
    //   888: aload_0
    //   889: aload_1
    //   890: aload_2
    //   891: iload_3
    //   892: invokespecial 657	com/google/android/gms/internal/measurement/zzwx:zzc	(Ljava/lang/Object;Ljava/lang/Object;I)Z
    //   895: ifeq +47 -> 942
    //   898: aload_1
    //   899: lload 7
    //   901: invokestatic 434	com/google/android/gms/internal/measurement/zzyh:zzk	(Ljava/lang/Object;J)I
    //   904: aload_2
    //   905: lload 7
    //   907: invokestatic 434	com/google/android/gms/internal/measurement/zzyh:zzk	(Ljava/lang/Object;J)I
    //   910: if_icmpeq +35 -> 945
    //   913: goto +29 -> 942
    //   916: aload_0
    //   917: aload_1
    //   918: aload_2
    //   919: iload_3
    //   920: invokespecial 657	com/google/android/gms/internal/measurement/zzwx:zzc	(Ljava/lang/Object;Ljava/lang/Object;I)Z
    //   923: ifeq +19 -> 942
    //   926: aload_1
    //   927: lload 7
    //   929: invokestatic 603	com/google/android/gms/internal/measurement/zzyh:zzl	(Ljava/lang/Object;J)J
    //   932: aload_2
    //   933: lload 7
    //   935: invokestatic 603	com/google/android/gms/internal/measurement/zzyh:zzl	(Ljava/lang/Object;J)J
    //   938: lcmp
    //   939: ifeq +6 -> 945
    //   942: iconst_0
    //   943: istore 6
    //   945: iload 6
    //   947: ifne +5 -> 952
    //   950: iconst_0
    //   951: ireturn
    //   952: iload_3
    //   953: iconst_3
    //   954: iadd
    //   955: istore_3
    //   956: goto -947 -> 9
    //   959: aload_0
    //   960: getfield 92	com/google/android/gms/internal/measurement/zzwx:zzcbn	Lcom/google/android/gms/internal/measurement/zzyb;
    //   963: aload_1
    //   964: invokevirtual 108	com/google/android/gms/internal/measurement/zzyb:zzah	(Ljava/lang/Object;)Ljava/lang/Object;
    //   967: aload_0
    //   968: getfield 92	com/google/android/gms/internal/measurement/zzwx:zzcbn	Lcom/google/android/gms/internal/measurement/zzyb;
    //   971: aload_2
    //   972: invokevirtual 108	com/google/android/gms/internal/measurement/zzyb:zzah	(Ljava/lang/Object;)Ljava/lang/Object;
    //   975: invokevirtual 658	java/lang/Object:equals	(Ljava/lang/Object;)Z
    //   978: ifne +5 -> 983
    //   981: iconst_0
    //   982: ireturn
    //   983: aload_0
    //   984: getfield 78	com/google/android/gms/internal/measurement/zzwx:zzcbe	Z
    //   987: ifeq +23 -> 1010
    //   990: aload_0
    //   991: getfield 94	com/google/android/gms/internal/measurement/zzwx:zzcbo	Lcom/google/android/gms/internal/measurement/zzva;
    //   994: aload_1
    //   995: invokevirtual 450	com/google/android/gms/internal/measurement/zzva:zzs	(Ljava/lang/Object;)Lcom/google/android/gms/internal/measurement/zzvd;
    //   998: aload_0
    //   999: getfield 94	com/google/android/gms/internal/measurement/zzwx:zzcbo	Lcom/google/android/gms/internal/measurement/zzva;
    //   1002: aload_2
    //   1003: invokevirtual 450	com/google/android/gms/internal/measurement/zzva:zzs	(Ljava/lang/Object;)Lcom/google/android/gms/internal/measurement/zzvd;
    //   1006: invokevirtual 659	com/google/android/gms/internal/measurement/zzvd:equals	(Ljava/lang/Object;)Z
    //   1009: ireturn
    //   1010: iconst_1
    //   1011: ireturn
    // Local variable table:
    //   start	length	slot	name	signature
    //   0	1012	0	this	zzwx
    //   0	1012	1	paramT1	T
    //   0	1012	2	paramT2	T
    //   8	948	3	i	int
    //   5	11	4	j	int
    //   23	17	5	k	int
    //   10	936	6	bool	boolean
    //   32	902	7	l1	long
    //   345	10	9	l2	long
  }
  
  public final int hashCode(T paramT)
  {
    int m = zzcaz.length;
    int j = 0;
    for (int k = 0; j < m; k = i)
    {
      int i1 = zzbq(j);
      int n = zzcaz[j];
      long l = 0xFFFFF & i1;
      i = 37;
      Object localObject;
      switch ((i1 & 0xFF00000) >>> 20)
      {
      default: 
        i = k;
        break;
      case 68: 
        i = k;
        if (zza(paramT, n, j)) {
          i = k * 53 + zzyh.zzp(paramT, l).hashCode();
        }
        break;
      case 67: 
        i = k;
        if (zza(paramT, n, j)) {
          i = k * 53 + zzvo.zzbf(zzi(paramT, l));
        }
        break;
      case 66: 
        i = k;
        if (zza(paramT, n, j)) {
          i = k * 53 + zzh(paramT, l);
        }
        break;
      case 65: 
        i = k;
        if (zza(paramT, n, j)) {
          i = k * 53 + zzvo.zzbf(zzi(paramT, l));
        }
        break;
      case 64: 
        i = k;
        if (zza(paramT, n, j)) {
          i = k * 53 + zzh(paramT, l);
        }
        break;
      case 63: 
        i = k;
        if (zza(paramT, n, j)) {
          i = k * 53 + zzh(paramT, l);
        }
        break;
      case 62: 
        i = k;
        if (zza(paramT, n, j)) {
          i = k * 53 + zzh(paramT, l);
        }
        break;
      case 61: 
        i = k;
        if (zza(paramT, n, j)) {
          i = k * 53 + zzyh.zzp(paramT, l).hashCode();
        }
        break;
      case 60: 
        i = k;
        if (zza(paramT, n, j)) {
          i = k * 53 + zzyh.zzp(paramT, l).hashCode();
        }
        break;
      case 59: 
        i = k;
        if (zza(paramT, n, j)) {
          i = k * 53 + ((String)zzyh.zzp(paramT, l)).hashCode();
        }
        break;
      case 58: 
        i = k;
        if (zza(paramT, n, j)) {
          i = k * 53 + zzvo.zzw(zzj(paramT, l));
        }
        break;
      case 57: 
        i = k;
        if (zza(paramT, n, j)) {
          i = k * 53 + zzh(paramT, l);
        }
        break;
      case 56: 
        i = k;
        if (zza(paramT, n, j)) {
          i = k * 53 + zzvo.zzbf(zzi(paramT, l));
        }
        break;
      case 55: 
        i = k;
        if (zza(paramT, n, j)) {
          i = k * 53 + zzh(paramT, l);
        }
        break;
      case 54: 
        i = k;
        if (zza(paramT, n, j)) {
          i = k * 53 + zzvo.zzbf(zzi(paramT, l));
        }
        break;
      case 53: 
        i = k;
        if (zza(paramT, n, j)) {
          i = k * 53 + zzvo.zzbf(zzi(paramT, l));
        }
        break;
      case 52: 
        i = k;
        if (zza(paramT, n, j)) {
          i = k * 53 + Float.floatToIntBits(zzg(paramT, l));
        }
        break;
      case 51: 
        i = k;
        if (zza(paramT, n, j)) {
          i = k * 53 + zzvo.zzbf(Double.doubleToLongBits(zzf(paramT, l)));
        }
        break;
      case 50: 
        i = k * 53 + zzyh.zzp(paramT, l).hashCode();
        break;
      case 18: 
      case 19: 
      case 20: 
      case 21: 
      case 22: 
      case 23: 
      case 24: 
      case 25: 
      case 26: 
      case 27: 
      case 28: 
      case 29: 
      case 30: 
      case 31: 
      case 32: 
      case 33: 
      case 34: 
      case 35: 
      case 36: 
      case 37: 
      case 38: 
      case 39: 
      case 40: 
      case 41: 
      case 42: 
      case 43: 
      case 44: 
      case 45: 
      case 46: 
      case 47: 
      case 48: 
      case 49: 
        i = k * 53 + zzyh.zzp(paramT, l).hashCode();
        break;
      case 17: 
        localObject = zzyh.zzp(paramT, l);
        if (localObject != null) {
          i = localObject.hashCode();
        }
        i = k * 53 + i;
        break;
      case 16: 
        i = k * 53 + zzvo.zzbf(zzyh.zzl(paramT, l));
        break;
      case 15: 
        i = k * 53 + zzyh.zzk(paramT, l);
        break;
      case 14: 
        i = k * 53 + zzvo.zzbf(zzyh.zzl(paramT, l));
        break;
      case 13: 
        i = k * 53 + zzyh.zzk(paramT, l);
        break;
      case 12: 
        i = k * 53 + zzyh.zzk(paramT, l);
        break;
      case 11: 
        i = k * 53 + zzyh.zzk(paramT, l);
        break;
      case 10: 
        i = k * 53 + zzyh.zzp(paramT, l).hashCode();
        break;
      case 9: 
        localObject = zzyh.zzp(paramT, l);
        if (localObject != null) {
          i = localObject.hashCode();
        }
        i = k * 53 + i;
        break;
      case 8: 
        i = k * 53 + ((String)zzyh.zzp(paramT, l)).hashCode();
        break;
      case 7: 
        i = k * 53 + zzvo.zzw(zzyh.zzm(paramT, l));
        break;
      case 6: 
        i = k * 53 + zzyh.zzk(paramT, l);
        break;
      case 5: 
        i = k * 53 + zzvo.zzbf(zzyh.zzl(paramT, l));
        break;
      case 4: 
        i = k * 53 + zzyh.zzk(paramT, l);
        break;
      case 3: 
        i = k * 53 + zzvo.zzbf(zzyh.zzl(paramT, l));
        break;
      case 2: 
        i = k * 53 + zzvo.zzbf(zzyh.zzl(paramT, l));
        break;
      case 1: 
        i = k * 53 + Float.floatToIntBits(zzyh.zzn(paramT, l));
        break;
      case 0: 
        i = k * 53 + zzvo.zzbf(Double.doubleToLongBits(zzyh.zzo(paramT, l)));
      }
      j += 3;
    }
    j = k * 53 + zzcbn.zzah(paramT).hashCode();
    int i = j;
    if (zzcbe) {
      i = j * 53 + zzcbo.zzs(paramT).hashCode();
    }
    return i;
  }
  
  public final T newInstance()
  {
    return zzcbl.newInstance(zzcbd);
  }
  
  public final void zza(T paramT, zzxi paramZzxi, zzuz paramZzuz)
    throws IOException
  {
    zzyb localZzyb;
    Object localObject1;
    Object localObject2;
    if (paramZzuz != null)
    {
      localZzyb = zzcbn;
      zzva localZzva = zzcbo;
      Object localObject5 = null;
      localObject1 = localObject5;
      for (;;)
      {
        localObject2 = localObject1;
        try
        {
          n = paramZzxi.zzve();
          localObject2 = localObject1;
          i = zzcbb;
          int m = -1;
          k = m;
          if (n >= i)
          {
            k = m;
            localObject2 = localObject1;
            if (n <= zzcbc)
            {
              j = 0;
              localObject2 = localObject1;
              i = zzcaz.length / 3 - 1;
              for (;;)
              {
                k = m;
                if (j > i) {
                  break;
                }
                int i1 = i + j >>> 1;
                k = i1 * 3;
                localObject2 = localObject1;
                int i2 = zzcaz[k];
                if (n == i2) {
                  break;
                }
                if (n < i2) {
                  i = i1 - 1;
                } else {
                  j = i1 + 1;
                }
              }
            }
          }
          if (k < 0)
          {
            if (n == Integer.MAX_VALUE) {
              return;
            }
            localObject2 = localObject1;
            if (!zzcbe)
            {
              localObject4 = null;
            }
            else
            {
              localObject2 = localObject1;
              localObject4 = localZzva.zza(paramZzuz, zzcbd, n);
            }
            if (localObject4 != null)
            {
              localObject3 = localObject5;
              if (localObject5 == null)
              {
                localObject2 = localObject1;
                localObject3 = localZzva.zzt(paramT);
              }
              localObject2 = localObject1;
              localObject1 = localZzva.zza(paramZzxi, localObject4, paramZzuz, (zzvd)localObject3, localObject1, localZzyb);
              localObject5 = localObject3;
              continue;
            }
            localObject2 = localObject1;
            localZzyb.zza(paramZzxi);
            localObject3 = localObject1;
            if (localObject1 == null)
            {
              localObject2 = localObject1;
              localObject3 = localZzyb.zzai(paramT);
            }
            localObject2 = localObject3;
            bool = localZzyb.zza(localObject3, paramZzxi);
            localObject1 = localObject3;
            if (bool) {
              continue;
            }
            return;
          }
          localObject2 = localObject1;
          i = zzbq(k);
          switch ((0xFF00000 & i) >>> 20)
          {
          default: 
            localObject3 = localObject1;
            if (localObject1 == null)
            {
              localObject2 = localObject1;
              localObject4 = localObject1;
            }
            break;
          }
        }
        finally
        {
          int n;
          int k;
          int j;
          Object localObject4;
          Object localObject3;
          boolean bool;
          long l;
          Object localObject7;
          Object localObject6;
          int i = zzcbj;
          while (i < zzcbk)
          {
            localObject2 = zza(paramT, zzcbi[i], localObject2, localZzyb);
            i += 1;
          }
          if (localObject2 != null) {
            localZzyb.zzg(paramT, localObject2);
          }
        }
        try
        {
          localObject3 = localZzyb.zzye();
        }
        catch (zzvu localZzvu)
        {
          break label4288;
        }
        localObject2 = localObject1;
        localObject4 = localObject1;
        zzyh.zza(paramT, i & 0xFFFFF, paramZzxi.zzb(zzbn(k), paramZzuz));
        localObject2 = localObject1;
        localObject4 = localObject1;
        zzb(paramT, n, k);
        continue;
        localObject2 = localObject1;
        localObject4 = localObject1;
        zzyh.zza(paramT, i & 0xFFFFF, Long.valueOf(paramZzxi.zzuu()));
        localObject2 = localObject1;
        localObject4 = localObject1;
        zzb(paramT, n, k);
        continue;
        localObject2 = localObject1;
        localObject4 = localObject1;
        zzyh.zza(paramT, i & 0xFFFFF, Integer.valueOf(paramZzxi.zzut()));
        localObject2 = localObject1;
        localObject4 = localObject1;
        zzb(paramT, n, k);
        continue;
        localObject2 = localObject1;
        localObject4 = localObject1;
        zzyh.zza(paramT, i & 0xFFFFF, Long.valueOf(paramZzxi.zzus()));
        localObject2 = localObject1;
        localObject4 = localObject1;
        zzb(paramT, n, k);
        continue;
        localObject2 = localObject1;
        localObject4 = localObject1;
        zzyh.zza(paramT, i & 0xFFFFF, Integer.valueOf(paramZzxi.zzur()));
        localObject2 = localObject1;
        localObject4 = localObject1;
        zzb(paramT, n, k);
        continue;
        localObject2 = localObject1;
        localObject4 = localObject1;
        j = paramZzxi.zzuq();
        localObject2 = localObject1;
        localObject4 = localObject1;
        localObject3 = zzbp(k);
        if (localObject3 != null)
        {
          localObject2 = localObject1;
          localObject4 = localObject1;
          if (!((zzvr)localObject3).zzb(j))
          {
            localObject2 = localObject1;
            localObject4 = localObject1;
            localObject1 = zzxl.zza(n, j, localObject1, localZzyb);
            break label4470;
          }
        }
        localObject2 = localObject1;
        localObject4 = localObject1;
        zzyh.zza(paramT, i & 0xFFFFF, Integer.valueOf(j));
        localObject2 = localObject1;
        localObject4 = localObject1;
        zzb(paramT, n, k);
        continue;
        localObject2 = localObject1;
        localObject4 = localObject1;
        zzyh.zza(paramT, i & 0xFFFFF, Integer.valueOf(paramZzxi.zzup()));
        localObject2 = localObject1;
        localObject4 = localObject1;
        zzb(paramT, n, k);
        continue;
        localObject2 = localObject1;
        localObject4 = localObject1;
        zzyh.zza(paramT, i & 0xFFFFF, paramZzxi.zzuo());
        localObject2 = localObject1;
        localObject4 = localObject1;
        zzb(paramT, n, k);
        continue;
        localObject2 = localObject1;
        localObject4 = localObject1;
        if (zza(paramT, n, k))
        {
          l = i & 0xFFFFF;
          localObject2 = localObject1;
          localObject4 = localObject1;
          zzyh.zza(paramT, l, zzvo.zzb(zzyh.zzp(paramT, l), paramZzxi.zza(zzbn(k), paramZzuz)));
        }
        else
        {
          localObject2 = localObject1;
          localObject4 = localObject1;
          zzyh.zza(paramT, i & 0xFFFFF, paramZzxi.zza(zzbn(k), paramZzuz));
          localObject2 = localObject1;
          localObject4 = localObject1;
          zzc(paramT, k);
        }
        localObject2 = localObject1;
        localObject4 = localObject1;
        zzb(paramT, n, k);
        continue;
        localObject2 = localObject1;
        localObject4 = localObject1;
        zza(paramT, i, paramZzxi);
        localObject2 = localObject1;
        localObject4 = localObject1;
        zzb(paramT, n, k);
        continue;
        localObject2 = localObject1;
        localObject4 = localObject1;
        zzyh.zza(paramT, i & 0xFFFFF, Boolean.valueOf(paramZzxi.zzum()));
        localObject2 = localObject1;
        localObject4 = localObject1;
        zzb(paramT, n, k);
        continue;
        localObject2 = localObject1;
        localObject4 = localObject1;
        zzyh.zza(paramT, i & 0xFFFFF, Integer.valueOf(paramZzxi.zzul()));
        localObject2 = localObject1;
        localObject4 = localObject1;
        zzb(paramT, n, k);
        continue;
        localObject2 = localObject1;
        localObject4 = localObject1;
        zzyh.zza(paramT, i & 0xFFFFF, Long.valueOf(paramZzxi.zzuk()));
        localObject2 = localObject1;
        localObject4 = localObject1;
        zzb(paramT, n, k);
        continue;
        localObject2 = localObject1;
        localObject4 = localObject1;
        zzyh.zza(paramT, i & 0xFFFFF, Integer.valueOf(paramZzxi.zzuj()));
        localObject2 = localObject1;
        localObject4 = localObject1;
        zzb(paramT, n, k);
        continue;
        localObject2 = localObject1;
        localObject4 = localObject1;
        zzyh.zza(paramT, i & 0xFFFFF, Long.valueOf(paramZzxi.zzuh()));
        localObject2 = localObject1;
        localObject4 = localObject1;
        zzb(paramT, n, k);
        continue;
        localObject2 = localObject1;
        localObject4 = localObject1;
        zzyh.zza(paramT, i & 0xFFFFF, Long.valueOf(paramZzxi.zzui()));
        localObject2 = localObject1;
        localObject4 = localObject1;
        zzb(paramT, n, k);
        continue;
        localObject2 = localObject1;
        localObject4 = localObject1;
        zzyh.zza(paramT, i & 0xFFFFF, Float.valueOf(paramZzxi.readFloat()));
        localObject2 = localObject1;
        localObject4 = localObject1;
        zzb(paramT, n, k);
        continue;
        localObject2 = localObject1;
        localObject4 = localObject1;
        zzyh.zza(paramT, i & 0xFFFFF, Double.valueOf(paramZzxi.readDouble()));
        localObject2 = localObject1;
        localObject4 = localObject1;
        zzb(paramT, n, k);
        continue;
        localObject2 = localObject1;
        localObject4 = localObject1;
        localObject7 = zzbo(k);
        localObject2 = localObject1;
        localObject4 = localObject1;
        l = zzbq(k) & 0xFFFFF;
        localObject2 = localObject1;
        localObject4 = localObject1;
        localObject6 = zzyh.zzp(paramT, l);
        if (localObject6 == null)
        {
          localObject2 = localObject1;
          localObject4 = localObject1;
          localObject3 = zzcbp.zzac(localObject7);
          localObject2 = localObject1;
          localObject4 = localObject1;
          zzyh.zza(paramT, l, localObject3);
        }
        else
        {
          localObject3 = localObject6;
          localObject2 = localObject1;
          localObject4 = localObject1;
          if (zzcbp.zzaa(localObject6))
          {
            localObject2 = localObject1;
            localObject4 = localObject1;
            localObject3 = zzcbp.zzac(localObject7);
            localObject2 = localObject1;
            localObject4 = localObject1;
            zzcbp.zzc(localObject3, localObject6);
            localObject2 = localObject1;
            localObject4 = localObject1;
            zzyh.zza(paramT, l, localObject3);
          }
        }
        localObject2 = localObject1;
        localObject4 = localObject1;
        paramZzxi.zza(zzcbp.zzy(localObject3), zzcbp.zzad(localObject7), paramZzuz);
        continue;
        l = i & 0xFFFFF;
        localObject2 = localObject1;
        localObject4 = localObject1;
        localObject3 = zzbn(k);
        localObject2 = localObject1;
        localObject4 = localObject1;
        paramZzxi.zzb(zzcbm.zza(paramT, l), (zzxj)localObject3, paramZzuz);
        continue;
        localObject2 = localObject1;
        localObject4 = localObject1;
        paramZzxi.zzw(zzcbm.zza(paramT, i & 0xFFFFF));
        continue;
        localObject2 = localObject1;
        localObject4 = localObject1;
        paramZzxi.zzv(zzcbm.zza(paramT, i & 0xFFFFF));
        continue;
        localObject2 = localObject1;
        localObject4 = localObject1;
        paramZzxi.zzu(zzcbm.zza(paramT, i & 0xFFFFF));
        continue;
        localObject2 = localObject1;
        localObject4 = localObject1;
        paramZzxi.zzt(zzcbm.zza(paramT, i & 0xFFFFF));
        continue;
        localObject2 = localObject1;
        localObject4 = localObject1;
        localObject3 = zzcbm.zza(paramT, i & 0xFFFFF);
        localObject2 = localObject1;
        localObject4 = localObject1;
        paramZzxi.zzs((List)localObject3);
        localObject2 = localObject1;
        localObject4 = localObject1;
        localObject1 = zzxl.zza(n, (List)localObject3, zzbp(k), localObject1, localZzyb);
        break label4470;
        localObject2 = localObject1;
        localObject4 = localObject1;
        paramZzxi.zzr(zzcbm.zza(paramT, i & 0xFFFFF));
        continue;
        localObject2 = localObject1;
        localObject4 = localObject1;
        paramZzxi.zzo(zzcbm.zza(paramT, i & 0xFFFFF));
        continue;
        localObject2 = localObject1;
        localObject4 = localObject1;
        paramZzxi.zzn(zzcbm.zza(paramT, i & 0xFFFFF));
        continue;
        localObject2 = localObject1;
        localObject4 = localObject1;
        paramZzxi.zzm(zzcbm.zza(paramT, i & 0xFFFFF));
        continue;
        localObject2 = localObject1;
        localObject4 = localObject1;
        paramZzxi.zzl(zzcbm.zza(paramT, i & 0xFFFFF));
        continue;
        localObject2 = localObject1;
        localObject4 = localObject1;
        paramZzxi.zzj(zzcbm.zza(paramT, i & 0xFFFFF));
        continue;
        localObject2 = localObject1;
        localObject4 = localObject1;
        paramZzxi.zzk(zzcbm.zza(paramT, i & 0xFFFFF));
        continue;
        localObject2 = localObject1;
        localObject4 = localObject1;
        paramZzxi.zzi(zzcbm.zza(paramT, i & 0xFFFFF));
        continue;
        localObject2 = localObject1;
        localObject4 = localObject1;
        paramZzxi.zzh(zzcbm.zza(paramT, i & 0xFFFFF));
        continue;
        localObject2 = localObject1;
        localObject4 = localObject1;
        paramZzxi.zzw(zzcbm.zza(paramT, i & 0xFFFFF));
        continue;
        localObject2 = localObject1;
        localObject4 = localObject1;
        paramZzxi.zzv(zzcbm.zza(paramT, i & 0xFFFFF));
        continue;
        localObject2 = localObject1;
        localObject4 = localObject1;
        paramZzxi.zzu(zzcbm.zza(paramT, i & 0xFFFFF));
        continue;
        localObject2 = localObject1;
        localObject4 = localObject1;
        paramZzxi.zzt(zzcbm.zza(paramT, i & 0xFFFFF));
        continue;
        localObject2 = localObject1;
        localObject4 = localObject1;
        localObject3 = zzcbm.zza(paramT, i & 0xFFFFF);
        localObject2 = localObject1;
        localObject4 = localObject1;
        paramZzxi.zzs((List)localObject3);
        localObject2 = localObject1;
        localObject4 = localObject1;
        localObject1 = zzxl.zza(n, (List)localObject3, zzbp(k), localObject1, localZzyb);
        break label4470;
        localObject2 = localObject1;
        localObject4 = localObject1;
        paramZzxi.zzr(zzcbm.zza(paramT, i & 0xFFFFF));
        continue;
        localObject2 = localObject1;
        localObject4 = localObject1;
        paramZzxi.zzq(zzcbm.zza(paramT, i & 0xFFFFF));
        continue;
        localObject2 = localObject1;
        localObject4 = localObject1;
        localObject3 = zzbn(k);
        l = i & 0xFFFFF;
        localObject2 = localObject1;
        localObject4 = localObject1;
        paramZzxi.zza(zzcbm.zza(paramT, l), (zzxj)localObject3, paramZzuz);
        continue;
        localObject2 = localObject1;
        localObject4 = localObject1;
        if (zzbs(i))
        {
          localObject2 = localObject1;
          localObject4 = localObject1;
          paramZzxi.zzp(zzcbm.zza(paramT, i & 0xFFFFF));
        }
        else
        {
          localObject2 = localObject1;
          localObject4 = localObject1;
          paramZzxi.readStringList(zzcbm.zza(paramT, i & 0xFFFFF));
          continue;
          localObject2 = localObject1;
          localObject4 = localObject1;
          paramZzxi.zzo(zzcbm.zza(paramT, i & 0xFFFFF));
          continue;
          localObject2 = localObject1;
          localObject4 = localObject1;
          paramZzxi.zzn(zzcbm.zza(paramT, i & 0xFFFFF));
          continue;
          localObject2 = localObject1;
          localObject4 = localObject1;
          paramZzxi.zzm(zzcbm.zza(paramT, i & 0xFFFFF));
          continue;
          localObject2 = localObject1;
          localObject4 = localObject1;
          paramZzxi.zzl(zzcbm.zza(paramT, i & 0xFFFFF));
          continue;
          localObject2 = localObject1;
          localObject4 = localObject1;
          paramZzxi.zzj(zzcbm.zza(paramT, i & 0xFFFFF));
          continue;
          localObject2 = localObject1;
          localObject4 = localObject1;
          paramZzxi.zzk(zzcbm.zza(paramT, i & 0xFFFFF));
          continue;
          localObject2 = localObject1;
          localObject4 = localObject1;
          paramZzxi.zzi(zzcbm.zza(paramT, i & 0xFFFFF));
          continue;
          localObject2 = localObject1;
          localObject4 = localObject1;
          paramZzxi.zzh(zzcbm.zza(paramT, i & 0xFFFFF));
          continue;
          localObject2 = localObject1;
          localObject4 = localObject1;
          if (zzb(paramT, k))
          {
            l = i & 0xFFFFF;
            localObject2 = localObject1;
            localObject4 = localObject1;
            zzyh.zza(paramT, l, zzvo.zzb(zzyh.zzp(paramT, l), paramZzxi.zzb(zzbn(k), paramZzuz)));
          }
          else
          {
            localObject2 = localObject1;
            localObject4 = localObject1;
            zzyh.zza(paramT, i & 0xFFFFF, paramZzxi.zzb(zzbn(k), paramZzuz));
            localObject2 = localObject1;
            localObject4 = localObject1;
            zzc(paramT, k);
            continue;
            localObject2 = localObject1;
            localObject4 = localObject1;
            zzyh.zza(paramT, i & 0xFFFFF, paramZzxi.zzuu());
            localObject2 = localObject1;
            localObject4 = localObject1;
            zzc(paramT, k);
            continue;
            localObject2 = localObject1;
            localObject4 = localObject1;
            zzyh.zzb(paramT, i & 0xFFFFF, paramZzxi.zzut());
            localObject2 = localObject1;
            localObject4 = localObject1;
            zzc(paramT, k);
            continue;
            localObject2 = localObject1;
            localObject4 = localObject1;
            zzyh.zza(paramT, i & 0xFFFFF, paramZzxi.zzus());
            localObject2 = localObject1;
            localObject4 = localObject1;
            zzc(paramT, k);
            continue;
            localObject2 = localObject1;
            localObject4 = localObject1;
            zzyh.zzb(paramT, i & 0xFFFFF, paramZzxi.zzur());
            localObject2 = localObject1;
            localObject4 = localObject1;
            zzc(paramT, k);
            continue;
            localObject2 = localObject1;
            localObject4 = localObject1;
            j = paramZzxi.zzuq();
            localObject2 = localObject1;
            localObject4 = localObject1;
            localObject3 = zzbp(k);
            if (localObject3 != null)
            {
              localObject2 = localObject1;
              localObject4 = localObject1;
              if (!((zzvr)localObject3).zzb(j))
              {
                localObject2 = localObject1;
                localObject4 = localObject1;
                localObject1 = zzxl.zza(n, j, localObject1, localZzyb);
                break label4470;
              }
            }
            localObject2 = localObject1;
            localObject4 = localObject1;
            zzyh.zzb(paramT, i & 0xFFFFF, j);
            localObject2 = localObject1;
            localObject4 = localObject1;
            zzc(paramT, k);
            continue;
            localObject2 = localObject1;
            localObject4 = localObject1;
            zzyh.zzb(paramT, i & 0xFFFFF, paramZzxi.zzup());
            localObject2 = localObject1;
            localObject4 = localObject1;
            zzc(paramT, k);
            continue;
            localObject2 = localObject1;
            localObject4 = localObject1;
            zzyh.zza(paramT, i & 0xFFFFF, paramZzxi.zzuo());
            localObject2 = localObject1;
            localObject4 = localObject1;
            zzc(paramT, k);
            continue;
            localObject2 = localObject1;
            localObject4 = localObject1;
            if (zzb(paramT, k))
            {
              l = i & 0xFFFFF;
              localObject2 = localObject1;
              localObject4 = localObject1;
              zzyh.zza(paramT, l, zzvo.zzb(zzyh.zzp(paramT, l), paramZzxi.zza(zzbn(k), paramZzuz)));
            }
            else
            {
              localObject2 = localObject1;
              localObject4 = localObject1;
              zzyh.zza(paramT, i & 0xFFFFF, paramZzxi.zza(zzbn(k), paramZzuz));
              localObject2 = localObject1;
              localObject4 = localObject1;
              zzc(paramT, k);
              continue;
              localObject2 = localObject1;
              localObject4 = localObject1;
              zza(paramT, i, paramZzxi);
              localObject2 = localObject1;
              localObject4 = localObject1;
              zzc(paramT, k);
              continue;
              localObject2 = localObject1;
              localObject4 = localObject1;
              zzyh.zza(paramT, i & 0xFFFFF, paramZzxi.zzum());
              localObject2 = localObject1;
              localObject4 = localObject1;
              zzc(paramT, k);
              continue;
              localObject2 = localObject1;
              localObject4 = localObject1;
              zzyh.zzb(paramT, i & 0xFFFFF, paramZzxi.zzul());
              localObject2 = localObject1;
              localObject4 = localObject1;
              zzc(paramT, k);
              continue;
              localObject2 = localObject1;
              localObject4 = localObject1;
              zzyh.zza(paramT, i & 0xFFFFF, paramZzxi.zzuk());
              localObject2 = localObject1;
              localObject4 = localObject1;
              zzc(paramT, k);
              continue;
              localObject2 = localObject1;
              localObject4 = localObject1;
              zzyh.zzb(paramT, i & 0xFFFFF, paramZzxi.zzuj());
              localObject2 = localObject1;
              localObject4 = localObject1;
              zzc(paramT, k);
              continue;
              localObject2 = localObject1;
              localObject4 = localObject1;
              zzyh.zza(paramT, i & 0xFFFFF, paramZzxi.zzuh());
              localObject2 = localObject1;
              localObject4 = localObject1;
              zzc(paramT, k);
              continue;
              localObject2 = localObject1;
              localObject4 = localObject1;
              zzyh.zza(paramT, i & 0xFFFFF, paramZzxi.zzui());
              localObject2 = localObject1;
              localObject4 = localObject1;
              zzc(paramT, k);
              continue;
              localObject2 = localObject1;
              localObject4 = localObject1;
              zzyh.zza(paramT, i & 0xFFFFF, paramZzxi.readFloat());
              localObject2 = localObject1;
              localObject4 = localObject1;
              zzc(paramT, k);
              continue;
              localObject2 = localObject1;
              localObject4 = localObject1;
              zzyh.zza(paramT, i & 0xFFFFF, paramZzxi.readDouble());
              localObject2 = localObject1;
              localObject4 = localObject1;
              zzc(paramT, k);
            }
          }
        }
      }
    }
    for (;;)
    {
      localObject2 = localObject3;
      localObject4 = localObject3;
      bool = localZzyb.zza(localObject3, paramZzxi);
      localObject1 = localObject3;
      if (bool) {
        break;
      }
      i = zzcbj;
      while (i < zzcbk)
      {
        localObject3 = zza(paramT, zzcbi[i], localObject3, localZzyb);
        i += 1;
      }
      if (localObject3 != null) {
        localZzyb.zzg(paramT, localObject3);
      }
      return;
      label4288:
      localObject2 = localObject4;
      localZzyb.zza(paramZzxi);
      localObject3 = localObject4;
      if (localObject4 == null)
      {
        localObject2 = localObject4;
        localObject3 = localZzyb.zzai(paramT);
      }
      localObject2 = localObject3;
      bool = localZzyb.zza(localObject3, paramZzxi);
      localObject1 = localObject3;
      if (bool) {
        break;
      }
      i = zzcbj;
      while (i < zzcbk)
      {
        localObject3 = zza(paramT, zzcbi[i], localObject3, localZzyb);
        i += 1;
      }
      if (localObject3 != null) {
        localZzyb.zzg(paramT, localObject3);
      }
      return;
      throw new NullPointerException();
      label4470:
      break;
    }
  }
  
  public final void zza(T paramT, zzyw paramZzyw)
    throws IOException
  {
    Object localObject1;
    Iterator localIterator;
    label75:
    int i;
    Object localObject2;
    int j;
    int k;
    if (paramZzyw.zzvj() == zzvm.zze.zzbzf)
    {
      zza(zzcbn, paramT, paramZzyw);
      if (zzcbe)
      {
        localObject1 = zzcbo.zzs(paramT);
        if (!((zzvd)localObject1).isEmpty())
        {
          localIterator = ((zzvd)localObject1).descendingIterator();
          localObject1 = (Map.Entry)localIterator.next();
          break label75;
        }
      }
      localIterator = null;
      localObject1 = localIterator;
      i = zzcaz.length - 3;
      for (;;)
      {
        localObject2 = localObject1;
        if (i < 0) {
          break;
        }
        j = zzbq(i);
        k = zzcaz[i];
        while ((localObject1 != null) && (zzcbo.zzb((Map.Entry)localObject1) > k))
        {
          zzcbo.zza(paramZzyw, (Map.Entry)localObject1);
          if (localIterator.hasNext()) {
            localObject1 = (Map.Entry)localIterator.next();
          } else {
            localObject1 = null;
          }
        }
        switch ((j & 0xFF00000) >>> 20)
        {
        default: 
          break;
        case 68: 
          if (zza(paramT, k, i)) {
            paramZzyw.zzb(k, zzyh.zzp(paramT, j & 0xFFFFF), zzbn(i));
          }
          break;
        case 67: 
          if (zza(paramT, k, i)) {
            paramZzyw.zzb(k, zzi(paramT, j & 0xFFFFF));
          }
          break;
        case 66: 
          if (zza(paramT, k, i)) {
            paramZzyw.zzf(k, zzh(paramT, j & 0xFFFFF));
          }
          break;
        case 65: 
          if (zza(paramT, k, i)) {
            paramZzyw.zzj(k, zzi(paramT, j & 0xFFFFF));
          }
          break;
        case 64: 
          if (zza(paramT, k, i)) {
            paramZzyw.zzn(k, zzh(paramT, j & 0xFFFFF));
          }
          break;
        case 63: 
          if (zza(paramT, k, i)) {
            paramZzyw.zzo(k, zzh(paramT, j & 0xFFFFF));
          }
          break;
        case 62: 
          if (zza(paramT, k, i)) {
            paramZzyw.zze(k, zzh(paramT, j & 0xFFFFF));
          }
          break;
        case 61: 
          if (zza(paramT, k, i)) {
            paramZzyw.zza(k, (zzud)zzyh.zzp(paramT, j & 0xFFFFF));
          }
          break;
        case 60: 
          if (zza(paramT, k, i)) {
            paramZzyw.zza(k, zzyh.zzp(paramT, j & 0xFFFFF), zzbn(i));
          }
          break;
        case 59: 
          if (zza(paramT, k, i)) {
            zza(k, zzyh.zzp(paramT, j & 0xFFFFF), paramZzyw);
          }
          break;
        case 58: 
          if (zza(paramT, k, i)) {
            paramZzyw.zzb(k, zzj(paramT, j & 0xFFFFF));
          }
          break;
        case 57: 
          if (zza(paramT, k, i)) {
            paramZzyw.zzg(k, zzh(paramT, j & 0xFFFFF));
          }
          break;
        case 56: 
          if (zza(paramT, k, i)) {
            paramZzyw.zzc(k, zzi(paramT, j & 0xFFFFF));
          }
          break;
        case 55: 
          if (zza(paramT, k, i)) {
            paramZzyw.zzd(k, zzh(paramT, j & 0xFFFFF));
          }
          break;
        case 54: 
          if (zza(paramT, k, i)) {
            paramZzyw.zza(k, zzi(paramT, j & 0xFFFFF));
          }
          break;
        case 53: 
          if (zza(paramT, k, i)) {
            paramZzyw.zzi(k, zzi(paramT, j & 0xFFFFF));
          }
          break;
        case 52: 
          if (zza(paramT, k, i)) {
            paramZzyw.zza(k, zzg(paramT, j & 0xFFFFF));
          }
          break;
        case 51: 
          if (zza(paramT, k, i)) {
            paramZzyw.zza(k, zzf(paramT, j & 0xFFFFF));
          }
          break;
        case 50: 
          zza(paramZzyw, k, zzyh.zzp(paramT, j & 0xFFFFF), i);
          break;
        case 49: 
          zzxl.zzb(zzcaz[i], (List)zzyh.zzp(paramT, j & 0xFFFFF), paramZzyw, zzbn(i));
          break;
        case 48: 
          zzxl.zze(zzcaz[i], (List)zzyh.zzp(paramT, j & 0xFFFFF), paramZzyw, true);
          break;
        case 47: 
          zzxl.zzj(zzcaz[i], (List)zzyh.zzp(paramT, j & 0xFFFFF), paramZzyw, true);
          break;
        case 46: 
          zzxl.zzg(zzcaz[i], (List)zzyh.zzp(paramT, j & 0xFFFFF), paramZzyw, true);
          break;
        case 45: 
          zzxl.zzl(zzcaz[i], (List)zzyh.zzp(paramT, j & 0xFFFFF), paramZzyw, true);
          break;
        case 44: 
          zzxl.zzm(zzcaz[i], (List)zzyh.zzp(paramT, j & 0xFFFFF), paramZzyw, true);
          break;
        case 43: 
          zzxl.zzi(zzcaz[i], (List)zzyh.zzp(paramT, j & 0xFFFFF), paramZzyw, true);
          break;
        case 42: 
          zzxl.zzn(zzcaz[i], (List)zzyh.zzp(paramT, j & 0xFFFFF), paramZzyw, true);
          break;
        case 41: 
          zzxl.zzk(zzcaz[i], (List)zzyh.zzp(paramT, j & 0xFFFFF), paramZzyw, true);
          break;
        case 40: 
          zzxl.zzf(zzcaz[i], (List)zzyh.zzp(paramT, j & 0xFFFFF), paramZzyw, true);
          break;
        case 39: 
          zzxl.zzh(zzcaz[i], (List)zzyh.zzp(paramT, j & 0xFFFFF), paramZzyw, true);
          break;
        case 38: 
          zzxl.zzd(zzcaz[i], (List)zzyh.zzp(paramT, j & 0xFFFFF), paramZzyw, true);
          break;
        case 37: 
          zzxl.zzc(zzcaz[i], (List)zzyh.zzp(paramT, j & 0xFFFFF), paramZzyw, true);
          break;
        case 36: 
          zzxl.zzb(zzcaz[i], (List)zzyh.zzp(paramT, j & 0xFFFFF), paramZzyw, true);
          break;
        case 35: 
          zzxl.zza(zzcaz[i], (List)zzyh.zzp(paramT, j & 0xFFFFF), paramZzyw, true);
          break;
        case 34: 
          zzxl.zze(zzcaz[i], (List)zzyh.zzp(paramT, j & 0xFFFFF), paramZzyw, false);
          break;
        case 33: 
          zzxl.zzj(zzcaz[i], (List)zzyh.zzp(paramT, j & 0xFFFFF), paramZzyw, false);
          break;
        case 32: 
          zzxl.zzg(zzcaz[i], (List)zzyh.zzp(paramT, j & 0xFFFFF), paramZzyw, false);
          break;
        case 31: 
          zzxl.zzl(zzcaz[i], (List)zzyh.zzp(paramT, j & 0xFFFFF), paramZzyw, false);
          break;
        case 30: 
          zzxl.zzm(zzcaz[i], (List)zzyh.zzp(paramT, j & 0xFFFFF), paramZzyw, false);
          break;
        case 29: 
          zzxl.zzi(zzcaz[i], (List)zzyh.zzp(paramT, j & 0xFFFFF), paramZzyw, false);
          break;
        case 28: 
          zzxl.zzb(zzcaz[i], (List)zzyh.zzp(paramT, j & 0xFFFFF), paramZzyw);
          break;
        case 27: 
          zzxl.zza(zzcaz[i], (List)zzyh.zzp(paramT, j & 0xFFFFF), paramZzyw, zzbn(i));
          break;
        case 26: 
          zzxl.zza(zzcaz[i], (List)zzyh.zzp(paramT, j & 0xFFFFF), paramZzyw);
          break;
        case 25: 
          zzxl.zzn(zzcaz[i], (List)zzyh.zzp(paramT, j & 0xFFFFF), paramZzyw, false);
          break;
        case 24: 
          zzxl.zzk(zzcaz[i], (List)zzyh.zzp(paramT, j & 0xFFFFF), paramZzyw, false);
          break;
        case 23: 
          zzxl.zzf(zzcaz[i], (List)zzyh.zzp(paramT, j & 0xFFFFF), paramZzyw, false);
          break;
        case 22: 
          zzxl.zzh(zzcaz[i], (List)zzyh.zzp(paramT, j & 0xFFFFF), paramZzyw, false);
          break;
        case 21: 
          zzxl.zzd(zzcaz[i], (List)zzyh.zzp(paramT, j & 0xFFFFF), paramZzyw, false);
          break;
        case 20: 
          zzxl.zzc(zzcaz[i], (List)zzyh.zzp(paramT, j & 0xFFFFF), paramZzyw, false);
          break;
        case 19: 
          zzxl.zzb(zzcaz[i], (List)zzyh.zzp(paramT, j & 0xFFFFF), paramZzyw, false);
          break;
        case 18: 
          zzxl.zza(zzcaz[i], (List)zzyh.zzp(paramT, j & 0xFFFFF), paramZzyw, false);
          break;
        case 17: 
          if (zzb(paramT, i)) {
            paramZzyw.zzb(k, zzyh.zzp(paramT, j & 0xFFFFF), zzbn(i));
          }
          break;
        case 16: 
          if (zzb(paramT, i)) {
            paramZzyw.zzb(k, zzyh.zzl(paramT, j & 0xFFFFF));
          }
          break;
        case 15: 
          if (zzb(paramT, i)) {
            paramZzyw.zzf(k, zzyh.zzk(paramT, j & 0xFFFFF));
          }
          break;
        case 14: 
          if (zzb(paramT, i)) {
            paramZzyw.zzj(k, zzyh.zzl(paramT, j & 0xFFFFF));
          }
          break;
        case 13: 
          if (zzb(paramT, i)) {
            paramZzyw.zzn(k, zzyh.zzk(paramT, j & 0xFFFFF));
          }
          break;
        case 12: 
          if (zzb(paramT, i)) {
            paramZzyw.zzo(k, zzyh.zzk(paramT, j & 0xFFFFF));
          }
          break;
        case 11: 
          if (zzb(paramT, i)) {
            paramZzyw.zze(k, zzyh.zzk(paramT, j & 0xFFFFF));
          }
          break;
        case 10: 
          if (zzb(paramT, i)) {
            paramZzyw.zza(k, (zzud)zzyh.zzp(paramT, j & 0xFFFFF));
          }
          break;
        case 9: 
          if (zzb(paramT, i)) {
            paramZzyw.zza(k, zzyh.zzp(paramT, j & 0xFFFFF), zzbn(i));
          }
          break;
        case 8: 
          if (zzb(paramT, i)) {
            zza(k, zzyh.zzp(paramT, j & 0xFFFFF), paramZzyw);
          }
          break;
        case 7: 
          if (zzb(paramT, i)) {
            paramZzyw.zzb(k, zzyh.zzm(paramT, j & 0xFFFFF));
          }
          break;
        case 6: 
          if (zzb(paramT, i)) {
            paramZzyw.zzg(k, zzyh.zzk(paramT, j & 0xFFFFF));
          }
          break;
        case 5: 
          if (zzb(paramT, i)) {
            paramZzyw.zzc(k, zzyh.zzl(paramT, j & 0xFFFFF));
          }
          break;
        case 4: 
          if (zzb(paramT, i)) {
            paramZzyw.zzd(k, zzyh.zzk(paramT, j & 0xFFFFF));
          }
          break;
        case 3: 
          if (zzb(paramT, i)) {
            paramZzyw.zza(k, zzyh.zzl(paramT, j & 0xFFFFF));
          }
          break;
        case 2: 
          if (zzb(paramT, i)) {
            paramZzyw.zzi(k, zzyh.zzl(paramT, j & 0xFFFFF));
          }
          break;
        case 1: 
          if (zzb(paramT, i)) {
            paramZzyw.zza(k, zzyh.zzn(paramT, j & 0xFFFFF));
          }
          break;
        case 0: 
          if (zzb(paramT, i)) {
            paramZzyw.zza(k, zzyh.zzo(paramT, j & 0xFFFFF));
          }
          break;
        }
        i -= 3;
      }
      while (localObject2 != null)
      {
        zzcbo.zza(paramZzyw, (Map.Entry)localObject2);
        if (localIterator.hasNext()) {
          localObject2 = (Map.Entry)localIterator.next();
        } else {
          localObject2 = null;
        }
      }
      return;
    }
    if (zzcbg)
    {
      if (zzcbe)
      {
        localObject1 = zzcbo.zzs(paramT);
        if (!((zzvd)localObject1).isEmpty())
        {
          localIterator = ((zzvd)localObject1).iterator();
          localObject1 = (Map.Entry)localIterator.next();
          break label2677;
        }
      }
      localIterator = null;
      localObject1 = localIterator;
      label2677:
      j = zzcaz.length;
      i = 0;
      for (;;)
      {
        localObject2 = localObject1;
        if (i >= j) {
          break;
        }
        k = zzbq(i);
        int m = zzcaz[i];
        while ((localObject1 != null) && (zzcbo.zzb((Map.Entry)localObject1) <= m))
        {
          zzcbo.zza(paramZzyw, (Map.Entry)localObject1);
          if (localIterator.hasNext()) {
            localObject1 = (Map.Entry)localIterator.next();
          } else {
            localObject1 = null;
          }
        }
        switch ((k & 0xFF00000) >>> 20)
        {
        default: 
          break;
        case 68: 
          if (zza(paramT, m, i)) {
            paramZzyw.zzb(m, zzyh.zzp(paramT, k & 0xFFFFF), zzbn(i));
          }
          break;
        case 67: 
          if (zza(paramT, m, i)) {
            paramZzyw.zzb(m, zzi(paramT, k & 0xFFFFF));
          }
          break;
        case 66: 
          if (zza(paramT, m, i)) {
            paramZzyw.zzf(m, zzh(paramT, k & 0xFFFFF));
          }
          break;
        case 65: 
          if (zza(paramT, m, i)) {
            paramZzyw.zzj(m, zzi(paramT, k & 0xFFFFF));
          }
          break;
        case 64: 
          if (zza(paramT, m, i)) {
            paramZzyw.zzn(m, zzh(paramT, k & 0xFFFFF));
          }
          break;
        case 63: 
          if (zza(paramT, m, i)) {
            paramZzyw.zzo(m, zzh(paramT, k & 0xFFFFF));
          }
          break;
        case 62: 
          if (zza(paramT, m, i)) {
            paramZzyw.zze(m, zzh(paramT, k & 0xFFFFF));
          }
          break;
        case 61: 
          if (zza(paramT, m, i)) {
            paramZzyw.zza(m, (zzud)zzyh.zzp(paramT, k & 0xFFFFF));
          }
          break;
        case 60: 
          if (zza(paramT, m, i)) {
            paramZzyw.zza(m, zzyh.zzp(paramT, k & 0xFFFFF), zzbn(i));
          }
          break;
        case 59: 
          if (zza(paramT, m, i)) {
            zza(m, zzyh.zzp(paramT, k & 0xFFFFF), paramZzyw);
          }
          break;
        case 58: 
          if (zza(paramT, m, i)) {
            paramZzyw.zzb(m, zzj(paramT, k & 0xFFFFF));
          }
          break;
        case 57: 
          if (zza(paramT, m, i)) {
            paramZzyw.zzg(m, zzh(paramT, k & 0xFFFFF));
          }
          break;
        case 56: 
          if (zza(paramT, m, i)) {
            paramZzyw.zzc(m, zzi(paramT, k & 0xFFFFF));
          }
          break;
        case 55: 
          if (zza(paramT, m, i)) {
            paramZzyw.zzd(m, zzh(paramT, k & 0xFFFFF));
          }
          break;
        case 54: 
          if (zza(paramT, m, i)) {
            paramZzyw.zza(m, zzi(paramT, k & 0xFFFFF));
          }
          break;
        case 53: 
          if (zza(paramT, m, i)) {
            paramZzyw.zzi(m, zzi(paramT, k & 0xFFFFF));
          }
          break;
        case 52: 
          if (zza(paramT, m, i)) {
            paramZzyw.zza(m, zzg(paramT, k & 0xFFFFF));
          }
          break;
        case 51: 
          if (zza(paramT, m, i)) {
            paramZzyw.zza(m, zzf(paramT, k & 0xFFFFF));
          }
          break;
        case 50: 
          zza(paramZzyw, m, zzyh.zzp(paramT, k & 0xFFFFF), i);
          break;
        case 49: 
          zzxl.zzb(zzcaz[i], (List)zzyh.zzp(paramT, k & 0xFFFFF), paramZzyw, zzbn(i));
          break;
        case 48: 
          zzxl.zze(zzcaz[i], (List)zzyh.zzp(paramT, k & 0xFFFFF), paramZzyw, true);
          break;
        case 47: 
          zzxl.zzj(zzcaz[i], (List)zzyh.zzp(paramT, k & 0xFFFFF), paramZzyw, true);
          break;
        case 46: 
          zzxl.zzg(zzcaz[i], (List)zzyh.zzp(paramT, k & 0xFFFFF), paramZzyw, true);
          break;
        case 45: 
          zzxl.zzl(zzcaz[i], (List)zzyh.zzp(paramT, k & 0xFFFFF), paramZzyw, true);
          break;
        case 44: 
          zzxl.zzm(zzcaz[i], (List)zzyh.zzp(paramT, k & 0xFFFFF), paramZzyw, true);
          break;
        case 43: 
          zzxl.zzi(zzcaz[i], (List)zzyh.zzp(paramT, k & 0xFFFFF), paramZzyw, true);
          break;
        case 42: 
          zzxl.zzn(zzcaz[i], (List)zzyh.zzp(paramT, k & 0xFFFFF), paramZzyw, true);
          break;
        case 41: 
          zzxl.zzk(zzcaz[i], (List)zzyh.zzp(paramT, k & 0xFFFFF), paramZzyw, true);
          break;
        case 40: 
          zzxl.zzf(zzcaz[i], (List)zzyh.zzp(paramT, k & 0xFFFFF), paramZzyw, true);
          break;
        case 39: 
          zzxl.zzh(zzcaz[i], (List)zzyh.zzp(paramT, k & 0xFFFFF), paramZzyw, true);
          break;
        case 38: 
          zzxl.zzd(zzcaz[i], (List)zzyh.zzp(paramT, k & 0xFFFFF), paramZzyw, true);
          break;
        case 37: 
          zzxl.zzc(zzcaz[i], (List)zzyh.zzp(paramT, k & 0xFFFFF), paramZzyw, true);
          break;
        case 36: 
          zzxl.zzb(zzcaz[i], (List)zzyh.zzp(paramT, k & 0xFFFFF), paramZzyw, true);
          break;
        case 35: 
          zzxl.zza(zzcaz[i], (List)zzyh.zzp(paramT, k & 0xFFFFF), paramZzyw, true);
          break;
        case 34: 
          zzxl.zze(zzcaz[i], (List)zzyh.zzp(paramT, k & 0xFFFFF), paramZzyw, false);
          break;
        case 33: 
          zzxl.zzj(zzcaz[i], (List)zzyh.zzp(paramT, k & 0xFFFFF), paramZzyw, false);
          break;
        case 32: 
          zzxl.zzg(zzcaz[i], (List)zzyh.zzp(paramT, k & 0xFFFFF), paramZzyw, false);
          break;
        case 31: 
          zzxl.zzl(zzcaz[i], (List)zzyh.zzp(paramT, k & 0xFFFFF), paramZzyw, false);
          break;
        case 30: 
          zzxl.zzm(zzcaz[i], (List)zzyh.zzp(paramT, k & 0xFFFFF), paramZzyw, false);
          break;
        case 29: 
          zzxl.zzi(zzcaz[i], (List)zzyh.zzp(paramT, k & 0xFFFFF), paramZzyw, false);
          break;
        case 28: 
          zzxl.zzb(zzcaz[i], (List)zzyh.zzp(paramT, k & 0xFFFFF), paramZzyw);
          break;
        case 27: 
          zzxl.zza(zzcaz[i], (List)zzyh.zzp(paramT, k & 0xFFFFF), paramZzyw, zzbn(i));
          break;
        case 26: 
          zzxl.zza(zzcaz[i], (List)zzyh.zzp(paramT, k & 0xFFFFF), paramZzyw);
          break;
        case 25: 
          zzxl.zzn(zzcaz[i], (List)zzyh.zzp(paramT, k & 0xFFFFF), paramZzyw, false);
          break;
        case 24: 
          zzxl.zzk(zzcaz[i], (List)zzyh.zzp(paramT, k & 0xFFFFF), paramZzyw, false);
          break;
        case 23: 
          zzxl.zzf(zzcaz[i], (List)zzyh.zzp(paramT, k & 0xFFFFF), paramZzyw, false);
          break;
        case 22: 
          zzxl.zzh(zzcaz[i], (List)zzyh.zzp(paramT, k & 0xFFFFF), paramZzyw, false);
          break;
        case 21: 
          zzxl.zzd(zzcaz[i], (List)zzyh.zzp(paramT, k & 0xFFFFF), paramZzyw, false);
          break;
        case 20: 
          zzxl.zzc(zzcaz[i], (List)zzyh.zzp(paramT, k & 0xFFFFF), paramZzyw, false);
          break;
        case 19: 
          zzxl.zzb(zzcaz[i], (List)zzyh.zzp(paramT, k & 0xFFFFF), paramZzyw, false);
          break;
        case 18: 
          zzxl.zza(zzcaz[i], (List)zzyh.zzp(paramT, k & 0xFFFFF), paramZzyw, false);
          break;
        case 17: 
          if (zzb(paramT, i)) {
            paramZzyw.zzb(m, zzyh.zzp(paramT, k & 0xFFFFF), zzbn(i));
          }
          break;
        case 16: 
          if (zzb(paramT, i)) {
            paramZzyw.zzb(m, zzyh.zzl(paramT, k & 0xFFFFF));
          }
          break;
        case 15: 
          if (zzb(paramT, i)) {
            paramZzyw.zzf(m, zzyh.zzk(paramT, k & 0xFFFFF));
          }
          break;
        case 14: 
          if (zzb(paramT, i)) {
            paramZzyw.zzj(m, zzyh.zzl(paramT, k & 0xFFFFF));
          }
          break;
        case 13: 
          if (zzb(paramT, i)) {
            paramZzyw.zzn(m, zzyh.zzk(paramT, k & 0xFFFFF));
          }
          break;
        case 12: 
          if (zzb(paramT, i)) {
            paramZzyw.zzo(m, zzyh.zzk(paramT, k & 0xFFFFF));
          }
          break;
        case 11: 
          if (zzb(paramT, i)) {
            paramZzyw.zze(m, zzyh.zzk(paramT, k & 0xFFFFF));
          }
          break;
        case 10: 
          if (zzb(paramT, i)) {
            paramZzyw.zza(m, (zzud)zzyh.zzp(paramT, k & 0xFFFFF));
          }
          break;
        case 9: 
          if (zzb(paramT, i)) {
            paramZzyw.zza(m, zzyh.zzp(paramT, k & 0xFFFFF), zzbn(i));
          }
          break;
        case 8: 
          if (zzb(paramT, i)) {
            zza(m, zzyh.zzp(paramT, k & 0xFFFFF), paramZzyw);
          }
          break;
        case 7: 
          if (zzb(paramT, i)) {
            paramZzyw.zzb(m, zzyh.zzm(paramT, k & 0xFFFFF));
          }
          break;
        case 6: 
          if (zzb(paramT, i)) {
            paramZzyw.zzg(m, zzyh.zzk(paramT, k & 0xFFFFF));
          }
          break;
        case 5: 
          if (zzb(paramT, i)) {
            paramZzyw.zzc(m, zzyh.zzl(paramT, k & 0xFFFFF));
          }
          break;
        case 4: 
          if (zzb(paramT, i)) {
            paramZzyw.zzd(m, zzyh.zzk(paramT, k & 0xFFFFF));
          }
          break;
        case 3: 
          if (zzb(paramT, i)) {
            paramZzyw.zza(m, zzyh.zzl(paramT, k & 0xFFFFF));
          }
          break;
        case 2: 
          if (zzb(paramT, i)) {
            paramZzyw.zzi(m, zzyh.zzl(paramT, k & 0xFFFFF));
          }
          break;
        case 1: 
          if (zzb(paramT, i)) {
            paramZzyw.zza(m, zzyh.zzn(paramT, k & 0xFFFFF));
          }
          break;
        case 0: 
          if (zzb(paramT, i)) {
            paramZzyw.zza(m, zzyh.zzo(paramT, k & 0xFFFFF));
          }
          break;
        }
        i += 3;
      }
      while (localObject2 != null)
      {
        zzcbo.zza(paramZzyw, (Map.Entry)localObject2);
        if (localIterator.hasNext()) {
          localObject2 = (Map.Entry)localIterator.next();
        } else {
          localObject2 = null;
        }
      }
      zza(zzcbn, paramT, paramZzyw);
      return;
    }
    zzb(paramT, paramZzyw);
  }
  
  public final int zzae(T paramT)
  {
    int m;
    long l;
    Object localObject;
    int i1;
    if (zzcbg)
    {
      localUnsafe = zzcay;
      j = 0;
      for (k = 0; j < zzcaz.length; k = i)
      {
        m = zzbq(j);
        i = (m & 0xFF00000) >>> 20;
        n = zzcaz[j];
        l = m & 0xFFFFF;
        if ((i >= zzvg.zzbxd.id()) && (i <= zzvg.zzbxq.id())) {
          m = zzcaz[(j + 2)] & 0xFFFFF;
        } else {
          m = 0;
        }
        switch (i)
        {
        default: 
          i = k;
          break;
        case 68: 
          i = k;
          if (zza(paramT, n, j)) {
            i = k + zzut.zzc(n, (zzwt)zzyh.zzp(paramT, l), zzbn(j));
          }
          break;
        case 67: 
          i = k;
          if (zza(paramT, n, j)) {
            i = k + zzut.zzf(n, zzi(paramT, l));
          }
          break;
        case 66: 
          i = k;
          if (zza(paramT, n, j)) {
            i = k + zzut.zzj(n, zzh(paramT, l));
          }
          break;
        case 65: 
          i = k;
          if (zza(paramT, n, j)) {
            i = k + zzut.zzh(n, 0L);
          }
          break;
        case 64: 
          i = k;
          if (zza(paramT, n, j)) {
            i = k + zzut.zzl(n, 0);
          }
          break;
        case 63: 
          i = k;
          if (zza(paramT, n, j)) {
            i = k + zzut.zzm(n, zzh(paramT, l));
          }
          break;
        case 62: 
          i = k;
          if (zza(paramT, n, j)) {
            i = k + zzut.zzi(n, zzh(paramT, l));
          }
          break;
        case 61: 
          i = k;
          if (zza(paramT, n, j)) {
            i = k + zzut.zzc(n, (zzud)zzyh.zzp(paramT, l));
          }
          break;
        case 60: 
          i = k;
          if (zza(paramT, n, j)) {
            i = k + zzxl.zzc(n, zzyh.zzp(paramT, l), zzbn(j));
          }
          break;
        case 59: 
          i = k;
          if (zza(paramT, n, j))
          {
            localObject = zzyh.zzp(paramT, l);
            if ((localObject instanceof zzud)) {
              i = k + zzut.zzc(n, (zzud)localObject);
            } else {
              i = k + zzut.zzc(n, (String)localObject);
            }
          }
          break;
        case 58: 
          i = k;
          if (zza(paramT, n, j)) {
            i = k + zzut.zzc(n, true);
          }
          break;
        case 57: 
          i = k;
          if (zza(paramT, n, j)) {
            i = k + zzut.zzk(n, 0);
          }
          break;
        case 56: 
          i = k;
          if (zza(paramT, n, j)) {
            i = k + zzut.zzg(n, 0L);
          }
          break;
        case 55: 
          i = k;
          if (zza(paramT, n, j)) {
            i = k + zzut.zzh(n, zzh(paramT, l));
          }
          break;
        case 54: 
          i = k;
          if (zza(paramT, n, j)) {
            i = k + zzut.zze(n, zzi(paramT, l));
          }
          break;
        case 53: 
          i = k;
          if (zza(paramT, n, j)) {
            i = k + zzut.zzd(n, zzi(paramT, l));
          }
          break;
        case 52: 
          i = k;
          if (zza(paramT, n, j)) {
            i = k + zzut.zzb(n, 0.0F);
          }
          break;
        case 51: 
          i = k;
          if (zza(paramT, n, j)) {
            i = k + zzut.zzb(n, 0.0D);
          }
          break;
        case 50: 
          i = k + zzcbp.zzb(n, zzyh.zzp(paramT, l), zzbo(j));
          break;
        case 49: 
          i = k + zzxl.zzd(n, zze(paramT, l), zzbn(j));
          break;
        case 48: 
          i1 = zzxl.zzz((List)localUnsafe.getObject(paramT, l));
          i = k;
          if (i1 > 0)
          {
            if (zzcbh) {
              localUnsafe.putInt(paramT, m, i1);
            }
            i = k + (zzut.zzbb(n) + zzut.zzbd(i1) + i1);
          }
          break;
        case 47: 
          i1 = zzxl.zzad((List)localUnsafe.getObject(paramT, l));
          i = k;
          if (i1 > 0)
          {
            if (zzcbh) {
              localUnsafe.putInt(paramT, m, i1);
            }
            i = k + (zzut.zzbb(n) + zzut.zzbd(i1) + i1);
          }
          break;
        case 46: 
          i1 = zzxl.zzaf((List)localUnsafe.getObject(paramT, l));
          i = k;
          if (i1 > 0)
          {
            if (zzcbh) {
              localUnsafe.putInt(paramT, m, i1);
            }
            i = k + (zzut.zzbb(n) + zzut.zzbd(i1) + i1);
          }
          break;
        case 45: 
          i1 = zzxl.zzae((List)localUnsafe.getObject(paramT, l));
          i = k;
          if (i1 > 0)
          {
            if (zzcbh) {
              localUnsafe.putInt(paramT, m, i1);
            }
            i = k + (zzut.zzbb(n) + zzut.zzbd(i1) + i1);
          }
          break;
        case 44: 
          i1 = zzxl.zzaa((List)localUnsafe.getObject(paramT, l));
          i = k;
          if (i1 > 0)
          {
            if (zzcbh) {
              localUnsafe.putInt(paramT, m, i1);
            }
            i = k + (zzut.zzbb(n) + zzut.zzbd(i1) + i1);
          }
          break;
        case 43: 
          i1 = zzxl.zzac((List)localUnsafe.getObject(paramT, l));
          i = k;
          if (i1 > 0)
          {
            if (zzcbh) {
              localUnsafe.putInt(paramT, m, i1);
            }
            i = k + (zzut.zzbb(n) + zzut.zzbd(i1) + i1);
          }
          break;
        case 42: 
          i1 = zzxl.zzag((List)localUnsafe.getObject(paramT, l));
          i = k;
          if (i1 > 0)
          {
            if (zzcbh) {
              localUnsafe.putInt(paramT, m, i1);
            }
            i = k + (zzut.zzbb(n) + zzut.zzbd(i1) + i1);
          }
          break;
        case 41: 
          i1 = zzxl.zzae((List)localUnsafe.getObject(paramT, l));
          i = k;
          if (i1 > 0)
          {
            if (zzcbh) {
              localUnsafe.putInt(paramT, m, i1);
            }
            i = k + (zzut.zzbb(n) + zzut.zzbd(i1) + i1);
          }
          break;
        case 40: 
          i1 = zzxl.zzaf((List)localUnsafe.getObject(paramT, l));
          i = k;
          if (i1 > 0)
          {
            if (zzcbh) {
              localUnsafe.putInt(paramT, m, i1);
            }
            i = k + (zzut.zzbb(n) + zzut.zzbd(i1) + i1);
          }
          break;
        case 39: 
          i1 = zzxl.zzab((List)localUnsafe.getObject(paramT, l));
          i = k;
          if (i1 > 0)
          {
            if (zzcbh) {
              localUnsafe.putInt(paramT, m, i1);
            }
            i = k + (zzut.zzbb(n) + zzut.zzbd(i1) + i1);
          }
          break;
        case 38: 
          i1 = zzxl.zzy((List)localUnsafe.getObject(paramT, l));
          i = k;
          if (i1 > 0)
          {
            if (zzcbh) {
              localUnsafe.putInt(paramT, m, i1);
            }
            i = k + (zzut.zzbb(n) + zzut.zzbd(i1) + i1);
          }
          break;
        case 37: 
          i1 = zzxl.zzx((List)localUnsafe.getObject(paramT, l));
          i = k;
          if (i1 > 0)
          {
            if (zzcbh) {
              localUnsafe.putInt(paramT, m, i1);
            }
            i = k + (zzut.zzbb(n) + zzut.zzbd(i1) + i1);
          }
          break;
        case 36: 
          i1 = zzxl.zzae((List)localUnsafe.getObject(paramT, l));
          i = k;
          if (i1 > 0)
          {
            if (zzcbh) {
              localUnsafe.putInt(paramT, m, i1);
            }
            i = k + (zzut.zzbb(n) + zzut.zzbd(i1) + i1);
          }
          break;
        case 35: 
          i1 = zzxl.zzaf((List)localUnsafe.getObject(paramT, l));
          i = k;
          if (i1 > 0)
          {
            if (zzcbh) {
              localUnsafe.putInt(paramT, m, i1);
            }
            i = k + (zzut.zzbb(n) + zzut.zzbd(i1) + i1);
          }
          break;
        case 34: 
          i = k + zzxl.zzq(n, zze(paramT, l), false);
          break;
        case 33: 
          i = k + zzxl.zzu(n, zze(paramT, l), false);
          break;
        case 32: 
          i = k + zzxl.zzw(n, zze(paramT, l), false);
          break;
        case 31: 
          i = k + zzxl.zzv(n, zze(paramT, l), false);
          break;
        case 30: 
          i = k + zzxl.zzr(n, zze(paramT, l), false);
          break;
        case 29: 
          i = k + zzxl.zzt(n, zze(paramT, l), false);
          break;
        case 28: 
          i = k + zzxl.zzd(n, zze(paramT, l));
          break;
        case 27: 
          i = k + zzxl.zzc(n, zze(paramT, l), zzbn(j));
          break;
        case 26: 
          i = k + zzxl.zzc(n, zze(paramT, l));
          break;
        case 25: 
          i = k + zzxl.zzx(n, zze(paramT, l), false);
          break;
        case 24: 
          i = k + zzxl.zzv(n, zze(paramT, l), false);
          break;
        case 23: 
          i = k + zzxl.zzw(n, zze(paramT, l), false);
          break;
        case 22: 
          i = k + zzxl.zzs(n, zze(paramT, l), false);
          break;
        case 21: 
          i = k + zzxl.zzp(n, zze(paramT, l), false);
          break;
        case 20: 
          i = k + zzxl.zzo(n, zze(paramT, l), false);
          break;
        case 19: 
          i = k + zzxl.zzv(n, zze(paramT, l), false);
          break;
        case 18: 
          i = k + zzxl.zzw(n, zze(paramT, l), false);
          break;
        case 17: 
          i = k;
          if (zzb(paramT, j)) {
            i = k + zzut.zzc(n, (zzwt)zzyh.zzp(paramT, l), zzbn(j));
          }
          break;
        case 16: 
          i = k;
          if (zzb(paramT, j)) {
            i = k + zzut.zzf(n, zzyh.zzl(paramT, l));
          }
          break;
        case 15: 
          i = k;
          if (zzb(paramT, j)) {
            i = k + zzut.zzj(n, zzyh.zzk(paramT, l));
          }
          break;
        case 14: 
          i = k;
          if (zzb(paramT, j)) {
            i = k + zzut.zzh(n, 0L);
          }
          break;
        case 13: 
          i = k;
          if (zzb(paramT, j)) {
            i = k + zzut.zzl(n, 0);
          }
          break;
        case 12: 
          i = k;
          if (zzb(paramT, j)) {
            i = k + zzut.zzm(n, zzyh.zzk(paramT, l));
          }
          break;
        case 11: 
          i = k;
          if (zzb(paramT, j)) {
            i = k + zzut.zzi(n, zzyh.zzk(paramT, l));
          }
          break;
        case 10: 
          i = k;
          if (zzb(paramT, j)) {
            i = k + zzut.zzc(n, (zzud)zzyh.zzp(paramT, l));
          }
          break;
        case 9: 
          i = k;
          if (zzb(paramT, j)) {
            i = k + zzxl.zzc(n, zzyh.zzp(paramT, l), zzbn(j));
          }
          break;
        case 8: 
          i = k;
          if (zzb(paramT, j))
          {
            localObject = zzyh.zzp(paramT, l);
            if ((localObject instanceof zzud)) {
              i = k + zzut.zzc(n, (zzud)localObject);
            } else {
              i = k + zzut.zzc(n, (String)localObject);
            }
          }
          break;
        case 7: 
          i = k;
          if (zzb(paramT, j)) {
            i = k + zzut.zzc(n, true);
          }
          break;
        case 6: 
          i = k;
          if (zzb(paramT, j)) {
            i = k + zzut.zzk(n, 0);
          }
          break;
        case 5: 
          i = k;
          if (zzb(paramT, j)) {
            i = k + zzut.zzg(n, 0L);
          }
          break;
        case 4: 
          i = k;
          if (zzb(paramT, j)) {
            i = k + zzut.zzh(n, zzyh.zzk(paramT, l));
          }
          break;
        case 3: 
          i = k;
          if (zzb(paramT, j)) {
            i = k + zzut.zze(n, zzyh.zzl(paramT, l));
          }
          break;
        case 2: 
          i = k;
          if (zzb(paramT, j)) {
            i = k + zzut.zzd(n, zzyh.zzl(paramT, l));
          }
          break;
        case 1: 
          i = k;
          if (zzb(paramT, j)) {
            i = k + zzut.zzb(n, 0.0F);
          }
          break;
        case 0: 
          i = k;
          if (zzb(paramT, j)) {
            i = k + zzut.zzb(n, 0.0D);
          }
          break;
        }
        j += 3;
      }
      return k + zza(zzcbn, paramT);
    }
    Unsafe localUnsafe = zzcay;
    int k = 0;
    int j = 0;
    int i2 = -1;
    int n = 0;
    while (k < zzcaz.length)
    {
      int i7 = zzbq(k);
      int i6 = zzcaz[k];
      int i8 = (i7 & 0xFF00000) >>> 20;
      int i3;
      if (i8 <= 17)
      {
        i = zzcaz[(k + 2)];
        int i5 = i & 0xFFFFF;
        int i4 = 1 << (i >>> 20);
        i1 = i;
        m = i2;
        i3 = i4;
        if (i5 != i2)
        {
          n = localUnsafe.getInt(paramT, i5);
          m = i5;
          i1 = i;
          i3 = i4;
        }
      }
      else
      {
        if ((zzcbh) && (i8 >= zzvg.zzbxd.id()) && (i8 <= zzvg.zzbxq.id())) {
          i = zzcaz[(k + 2)] & 0xFFFFF;
        } else {
          i = 0;
        }
        i3 = 0;
        m = i2;
        i1 = i;
      }
      l = i7 & 0xFFFFF;
      switch (i8)
      {
      default: 
        i = j;
        break;
      case 68: 
        i = j;
        if (zza(paramT, i6, k)) {
          i = j + zzut.zzc(i6, (zzwt)localUnsafe.getObject(paramT, l), zzbn(k));
        }
        break;
      case 67: 
        i = j;
        if (zza(paramT, i6, k)) {
          i = j + zzut.zzf(i6, zzi(paramT, l));
        }
        break;
      case 66: 
        i = j;
        if (zza(paramT, i6, k)) {
          i = j + zzut.zzj(i6, zzh(paramT, l));
        }
        break;
      case 65: 
        i = j;
        if (zza(paramT, i6, k)) {
          i = j + zzut.zzh(i6, 0L);
        }
        break;
      case 64: 
        i = j;
        if (zza(paramT, i6, k)) {
          i = j + zzut.zzl(i6, 0);
        }
        break;
      case 63: 
        i = j;
        if (zza(paramT, i6, k)) {
          i = j + zzut.zzm(i6, zzh(paramT, l));
        }
        break;
      case 62: 
        i = j;
        if (zza(paramT, i6, k)) {
          i = j + zzut.zzi(i6, zzh(paramT, l));
        }
        break;
      case 61: 
        i = j;
        if (zza(paramT, i6, k)) {
          i = j + zzut.zzc(i6, (zzud)localUnsafe.getObject(paramT, l));
        }
        break;
      case 60: 
        i = j;
        if (zza(paramT, i6, k)) {
          i = j + zzxl.zzc(i6, localUnsafe.getObject(paramT, l), zzbn(k));
        }
        break;
      case 59: 
        i = j;
        if (zza(paramT, i6, k))
        {
          localObject = localUnsafe.getObject(paramT, l);
          if ((localObject instanceof zzud)) {
            i = j + zzut.zzc(i6, (zzud)localObject);
          } else {
            i = j + zzut.zzc(i6, (String)localObject);
          }
        }
        break;
      case 58: 
        i = j;
        if (zza(paramT, i6, k)) {
          i = j + zzut.zzc(i6, true);
        }
        break;
      case 57: 
        i = j;
        if (zza(paramT, i6, k)) {
          i = j + zzut.zzk(i6, 0);
        }
        break;
      case 56: 
        i = j;
        if (zza(paramT, i6, k)) {
          i = j + zzut.zzg(i6, 0L);
        }
        break;
      case 55: 
        i = j;
        if (zza(paramT, i6, k)) {
          i = j + zzut.zzh(i6, zzh(paramT, l));
        }
        break;
      case 54: 
        i = j;
        if (zza(paramT, i6, k)) {
          i = j + zzut.zze(i6, zzi(paramT, l));
        }
        break;
      case 53: 
        i = j;
        if (zza(paramT, i6, k)) {
          i = j + zzut.zzd(i6, zzi(paramT, l));
        }
        break;
      case 52: 
        i = j;
        if (zza(paramT, i6, k)) {
          i = j + zzut.zzb(i6, 0.0F);
        }
        break;
      case 51: 
        i = j;
        if (zza(paramT, i6, k)) {
          i = j + zzut.zzb(i6, 0.0D);
        }
        break;
      case 50: 
        i = j + zzcbp.zzb(i6, localUnsafe.getObject(paramT, l), zzbo(k));
        break;
      case 49: 
        i = j + zzxl.zzd(i6, (List)localUnsafe.getObject(paramT, l), zzbn(k));
        break;
      case 48: 
        i2 = zzxl.zzz((List)localUnsafe.getObject(paramT, l));
        i = j;
        if (i2 > 0)
        {
          if (zzcbh) {
            localUnsafe.putInt(paramT, i1, i2);
          }
          i = j + (zzut.zzbb(i6) + zzut.zzbd(i2) + i2);
        }
        break;
      case 47: 
        i2 = zzxl.zzad((List)localUnsafe.getObject(paramT, l));
        i = j;
        if (i2 > 0)
        {
          if (zzcbh) {
            localUnsafe.putInt(paramT, i1, i2);
          }
          i = j + (zzut.zzbb(i6) + zzut.zzbd(i2) + i2);
        }
        break;
      case 46: 
        i2 = zzxl.zzaf((List)localUnsafe.getObject(paramT, l));
        i = j;
        if (i2 > 0)
        {
          if (zzcbh) {
            localUnsafe.putInt(paramT, i1, i2);
          }
          i = j + (zzut.zzbb(i6) + zzut.zzbd(i2) + i2);
        }
        break;
      case 45: 
        i2 = zzxl.zzae((List)localUnsafe.getObject(paramT, l));
        i = j;
        if (i2 > 0)
        {
          if (zzcbh) {
            localUnsafe.putInt(paramT, i1, i2);
          }
          i = j + (zzut.zzbb(i6) + zzut.zzbd(i2) + i2);
        }
        break;
      case 44: 
        i2 = zzxl.zzaa((List)localUnsafe.getObject(paramT, l));
        i = j;
        if (i2 > 0)
        {
          if (zzcbh) {
            localUnsafe.putInt(paramT, i1, i2);
          }
          i = j + (zzut.zzbb(i6) + zzut.zzbd(i2) + i2);
        }
        break;
      case 43: 
        i2 = zzxl.zzac((List)localUnsafe.getObject(paramT, l));
        i = j;
        if (i2 > 0)
        {
          if (zzcbh) {
            localUnsafe.putInt(paramT, i1, i2);
          }
          i = j + (zzut.zzbb(i6) + zzut.zzbd(i2) + i2);
        }
        break;
      case 42: 
        i2 = zzxl.zzag((List)localUnsafe.getObject(paramT, l));
        i = j;
        if (i2 > 0)
        {
          if (zzcbh) {
            localUnsafe.putInt(paramT, i1, i2);
          }
          i = j + (zzut.zzbb(i6) + zzut.zzbd(i2) + i2);
        }
        break;
      case 41: 
        i2 = zzxl.zzae((List)localUnsafe.getObject(paramT, l));
        i = j;
        if (i2 > 0)
        {
          if (zzcbh) {
            localUnsafe.putInt(paramT, i1, i2);
          }
          i = j + (zzut.zzbb(i6) + zzut.zzbd(i2) + i2);
        }
        break;
      case 40: 
        i2 = zzxl.zzaf((List)localUnsafe.getObject(paramT, l));
        i = j;
        if (i2 > 0)
        {
          if (zzcbh) {
            localUnsafe.putInt(paramT, i1, i2);
          }
          i = j + (zzut.zzbb(i6) + zzut.zzbd(i2) + i2);
        }
        break;
      case 39: 
        i2 = zzxl.zzab((List)localUnsafe.getObject(paramT, l));
        i = j;
        if (i2 > 0)
        {
          if (zzcbh) {
            localUnsafe.putInt(paramT, i1, i2);
          }
          i = j + (zzut.zzbb(i6) + zzut.zzbd(i2) + i2);
        }
        break;
      case 38: 
        i2 = zzxl.zzy((List)localUnsafe.getObject(paramT, l));
        i = j;
        if (i2 > 0)
        {
          if (zzcbh) {
            localUnsafe.putInt(paramT, i1, i2);
          }
          i = j + (zzut.zzbb(i6) + zzut.zzbd(i2) + i2);
        }
        break;
      case 37: 
        i2 = zzxl.zzx((List)localUnsafe.getObject(paramT, l));
        i = j;
        if (i2 > 0)
        {
          if (zzcbh) {
            localUnsafe.putInt(paramT, i1, i2);
          }
          i = j + (zzut.zzbb(i6) + zzut.zzbd(i2) + i2);
        }
        break;
      case 36: 
        i2 = zzxl.zzae((List)localUnsafe.getObject(paramT, l));
        i = j;
        if (i2 > 0)
        {
          if (zzcbh) {
            localUnsafe.putInt(paramT, i1, i2);
          }
          i = j + (zzut.zzbb(i6) + zzut.zzbd(i2) + i2);
        }
        break;
      case 35: 
        i2 = zzxl.zzaf((List)localUnsafe.getObject(paramT, l));
        i = j;
        if (i2 > 0)
        {
          if (zzcbh) {
            localUnsafe.putInt(paramT, i1, i2);
          }
          i = j + (zzut.zzbb(i6) + zzut.zzbd(i2) + i2);
        }
        break;
      case 34: 
        i = j + zzxl.zzq(i6, (List)localUnsafe.getObject(paramT, l), false);
        break;
      case 33: 
        i = j + zzxl.zzu(i6, (List)localUnsafe.getObject(paramT, l), false);
        break;
      case 32: 
        i = j + zzxl.zzw(i6, (List)localUnsafe.getObject(paramT, l), false);
        break;
      case 31: 
        i = j + zzxl.zzv(i6, (List)localUnsafe.getObject(paramT, l), false);
        break;
      case 30: 
        i = j + zzxl.zzr(i6, (List)localUnsafe.getObject(paramT, l), false);
        break;
      case 29: 
        i = j + zzxl.zzt(i6, (List)localUnsafe.getObject(paramT, l), false);
        break;
      case 28: 
        i = j + zzxl.zzd(i6, (List)localUnsafe.getObject(paramT, l));
        break;
      case 27: 
        i = j + zzxl.zzc(i6, (List)localUnsafe.getObject(paramT, l), zzbn(k));
        break;
      case 26: 
        i = j + zzxl.zzc(i6, (List)localUnsafe.getObject(paramT, l));
        break;
      case 25: 
        i = j + zzxl.zzx(i6, (List)localUnsafe.getObject(paramT, l), false);
        break;
      case 24: 
        i = j + zzxl.zzv(i6, (List)localUnsafe.getObject(paramT, l), false);
        break;
      case 23: 
        i = j + zzxl.zzw(i6, (List)localUnsafe.getObject(paramT, l), false);
        break;
      case 22: 
        i = j + zzxl.zzs(i6, (List)localUnsafe.getObject(paramT, l), false);
        break;
      case 21: 
        i = j + zzxl.zzp(i6, (List)localUnsafe.getObject(paramT, l), false);
        break;
      case 20: 
        i = j + zzxl.zzo(i6, (List)localUnsafe.getObject(paramT, l), false);
        break;
      case 19: 
        i = j + zzxl.zzv(i6, (List)localUnsafe.getObject(paramT, l), false);
        break;
      case 18: 
        i = j + zzxl.zzw(i6, (List)localUnsafe.getObject(paramT, l), false);
      }
      for (;;)
      {
        break;
        i = j;
        if ((n & i3) != 0)
        {
          i = j + zzut.zzc(i6, (zzwt)localUnsafe.getObject(paramT, l), zzbn(k));
          continue;
          i = j;
          if ((n & i3) != 0)
          {
            i = j + zzut.zzf(i6, localUnsafe.getLong(paramT, l));
            continue;
            i = j;
            if ((n & i3) != 0)
            {
              i = j + zzut.zzj(i6, localUnsafe.getInt(paramT, l));
              continue;
              i = j;
              if ((n & i3) != 0)
              {
                i = j + zzut.zzh(i6, 0L);
                continue;
                i = j;
                if ((n & i3) != 0)
                {
                  i = j + zzut.zzl(i6, 0);
                  continue;
                  i = j;
                  if ((n & i3) != 0)
                  {
                    i = j + zzut.zzm(i6, localUnsafe.getInt(paramT, l));
                    continue;
                    i = j;
                    if ((n & i3) != 0)
                    {
                      i = j + zzut.zzi(i6, localUnsafe.getInt(paramT, l));
                      continue;
                      i = j;
                      if ((n & i3) != 0)
                      {
                        i = j + zzut.zzc(i6, (zzud)localUnsafe.getObject(paramT, l));
                        continue;
                        i = j;
                        if ((n & i3) != 0)
                        {
                          i = j + zzxl.zzc(i6, localUnsafe.getObject(paramT, l), zzbn(k));
                          continue;
                          i = j;
                          if ((n & i3) != 0)
                          {
                            localObject = localUnsafe.getObject(paramT, l);
                            if ((localObject instanceof zzud))
                            {
                              i = j + zzut.zzc(i6, (zzud)localObject);
                            }
                            else
                            {
                              i = j + zzut.zzc(i6, (String)localObject);
                              continue;
                              i = j;
                              if ((n & i3) != 0)
                              {
                                i = j + zzut.zzc(i6, true);
                                continue;
                                i = j;
                                if ((n & i3) != 0)
                                {
                                  i = j + zzut.zzk(i6, 0);
                                  continue;
                                  i = j;
                                  if ((n & i3) != 0)
                                  {
                                    i = j + zzut.zzg(i6, 0L);
                                    break label5675;
                                    i = j;
                                    if ((n & i3) != 0)
                                    {
                                      i = j + zzut.zzh(i6, localUnsafe.getInt(paramT, l));
                                      break label5675;
                                      i = j;
                                      if ((n & i3) != 0)
                                      {
                                        i = j + zzut.zze(i6, localUnsafe.getLong(paramT, l));
                                        break label5675;
                                        i = j;
                                        if ((n & i3) != 0) {
                                          i = j + zzut.zzd(i6, localUnsafe.getLong(paramT, l));
                                        }
                                      }
                                    }
                                    for (;;)
                                    {
                                      label5675:
                                      break;
                                      i = j;
                                      if ((n & i3) != 0) {
                                        i = j + zzut.zzb(i6, 0.0F);
                                      }
                                    }
                                    for (;;)
                                    {
                                      break;
                                      i = j;
                                      if ((n & i3) != 0) {
                                        i = j + zzut.zzb(i6, 0.0D);
                                      }
                                    }
                                  }
                                }
                              }
                            }
                          }
                        }
                      }
                    }
                  }
                }
              }
            }
          }
        }
      }
      k += 3;
      j = i;
      i2 = m;
    }
    j += zza(zzcbn, paramT);
    int i = j;
    if (zzcbe) {
      i = j + zzcbo.zzs(paramT).zzvu();
    }
    return i;
  }
  
  public final boolean zzaf(T paramT)
  {
    int i = 0;
    int m = -1;
    int k = 0;
    for (;;)
    {
      int j = zzcbj;
      int i1 = 1;
      int i2 = 1;
      if (i >= j) {
        break;
      }
      int i5 = zzcbi[i];
      int i6 = zzcaz[i5];
      int i7 = zzbq(i5);
      int n;
      if (!zzcbg)
      {
        j = zzcaz[(i5 + 2)];
        int i3 = j & 0xFFFFF;
        int i4 = 1 << (j >>> 20);
        j = m;
        n = i4;
        if (i3 != m)
        {
          k = zzcay.getInt(paramT, i3);
          j = i3;
          n = i4;
        }
      }
      else
      {
        n = 0;
        j = m;
      }
      if ((0x10000000 & i7) != 0) {
        m = 1;
      } else {
        m = 0;
      }
      if ((m != 0) && (!zza(paramT, i5, k, n))) {
        return false;
      }
      m = (0xFF00000 & i7) >>> 20;
      if ((m != 9) && (m != 17))
      {
        Object localObject2;
        Object localObject1;
        if (m != 27)
        {
          if ((m != 60) && (m != 68)) {}
          switch (m)
          {
          default: 
            break;
          case 50: 
            localObject2 = zzcbp.zzz(zzyh.zzp(paramT, i7 & 0xFFFFF));
            m = i2;
            if (!((Map)localObject2).isEmpty())
            {
              localObject1 = zzbo(i5);
              m = i2;
              if (zzcbp.zzad(localObject1).zzcat.zzyp() == zzyv.zzcet)
              {
                localObject1 = null;
                Iterator localIterator = ((Map)localObject2).values().iterator();
                Object localObject3;
                do
                {
                  m = i2;
                  if (!localIterator.hasNext()) {
                    break;
                  }
                  localObject3 = localIterator.next();
                  localObject2 = localObject1;
                  if (localObject1 == null) {
                    localObject2 = zzxf.zzxn().zzi(localObject3.getClass());
                  }
                  localObject1 = localObject2;
                } while (((zzxj)localObject2).zzaf(localObject3));
                m = 0;
              }
            }
            if (m != 0) {
              break;
            }
            return false;
            if ((!zza(paramT, i6, i5)) || (zza(paramT, i7, zzbn(i5)))) {
              break;
            }
            return false;
          }
        }
        else
        {
          localObject1 = (List)zzyh.zzp(paramT, i7 & 0xFFFFF);
          m = i1;
          if (!((List)localObject1).isEmpty())
          {
            localObject2 = zzbn(i5);
            n = 0;
            for (;;)
            {
              m = i1;
              if (n >= ((List)localObject1).size()) {
                break;
              }
              if (!((zzxj)localObject2).zzaf(((List)localObject1).get(n)))
              {
                m = 0;
                break;
              }
              n += 1;
            }
          }
          if (m == 0) {
            return false;
          }
        }
      }
      else if ((zza(paramT, i5, k, n)) && (!zza(paramT, i7, zzbn(i5))))
      {
        return false;
      }
      i += 1;
      m = j;
    }
    return (!zzcbe) || (zzcbo.zzs(paramT).isInitialized());
  }
  
  public final void zzd(T paramT1, T paramT2)
  {
    if (paramT2 != null)
    {
      int i = 0;
      while (i < zzcaz.length)
      {
        int j = zzbq(i);
        long l = 0xFFFFF & j;
        int k = zzcaz[i];
        switch ((j & 0xFF00000) >>> 20)
        {
        default: 
          break;
        case 68: 
          zzb(paramT1, paramT2, i);
          break;
        case 61: 
        case 62: 
        case 63: 
        case 64: 
        case 65: 
        case 66: 
        case 67: 
          if (zza(paramT2, k, i))
          {
            zzyh.zza(paramT1, l, zzyh.zzp(paramT2, l));
            zzb(paramT1, k, i);
          }
          break;
        case 60: 
          zzb(paramT1, paramT2, i);
          break;
        case 51: 
        case 52: 
        case 53: 
        case 54: 
        case 55: 
        case 56: 
        case 57: 
        case 58: 
        case 59: 
          if (zza(paramT2, k, i))
          {
            zzyh.zza(paramT1, l, zzyh.zzp(paramT2, l));
            zzb(paramT1, k, i);
          }
          break;
        case 50: 
          zzxl.zza(zzcbp, paramT1, paramT2, l);
          break;
        case 18: 
        case 19: 
        case 20: 
        case 21: 
        case 22: 
        case 23: 
        case 24: 
        case 25: 
        case 26: 
        case 27: 
        case 28: 
        case 29: 
        case 30: 
        case 31: 
        case 32: 
        case 33: 
        case 34: 
        case 35: 
        case 36: 
        case 37: 
        case 38: 
        case 39: 
        case 40: 
        case 41: 
        case 42: 
        case 43: 
        case 44: 
        case 45: 
        case 46: 
        case 47: 
        case 48: 
        case 49: 
          zzcbm.zza(paramT1, paramT2, l);
          break;
        case 17: 
          zza(paramT1, paramT2, i);
          break;
        case 16: 
          if (zzb(paramT2, i))
          {
            zzyh.zza(paramT1, l, zzyh.zzl(paramT2, l));
            zzc(paramT1, i);
          }
          break;
        case 15: 
          if (zzb(paramT2, i))
          {
            zzyh.zzb(paramT1, l, zzyh.zzk(paramT2, l));
            zzc(paramT1, i);
          }
          break;
        case 14: 
          if (zzb(paramT2, i))
          {
            zzyh.zza(paramT1, l, zzyh.zzl(paramT2, l));
            zzc(paramT1, i);
          }
          break;
        case 13: 
          if (zzb(paramT2, i))
          {
            zzyh.zzb(paramT1, l, zzyh.zzk(paramT2, l));
            zzc(paramT1, i);
          }
          break;
        case 12: 
          if (zzb(paramT2, i))
          {
            zzyh.zzb(paramT1, l, zzyh.zzk(paramT2, l));
            zzc(paramT1, i);
          }
          break;
        case 11: 
          if (zzb(paramT2, i))
          {
            zzyh.zzb(paramT1, l, zzyh.zzk(paramT2, l));
            zzc(paramT1, i);
          }
          break;
        case 10: 
          if (zzb(paramT2, i))
          {
            zzyh.zza(paramT1, l, zzyh.zzp(paramT2, l));
            zzc(paramT1, i);
          }
          break;
        case 9: 
          zza(paramT1, paramT2, i);
          break;
        case 8: 
          if (zzb(paramT2, i))
          {
            zzyh.zza(paramT1, l, zzyh.zzp(paramT2, l));
            zzc(paramT1, i);
          }
          break;
        case 7: 
          if (zzb(paramT2, i))
          {
            zzyh.zza(paramT1, l, zzyh.zzm(paramT2, l));
            zzc(paramT1, i);
          }
          break;
        case 6: 
          if (zzb(paramT2, i))
          {
            zzyh.zzb(paramT1, l, zzyh.zzk(paramT2, l));
            zzc(paramT1, i);
          }
          break;
        case 5: 
          if (zzb(paramT2, i))
          {
            zzyh.zza(paramT1, l, zzyh.zzl(paramT2, l));
            zzc(paramT1, i);
          }
          break;
        case 4: 
          if (zzb(paramT2, i))
          {
            zzyh.zzb(paramT1, l, zzyh.zzk(paramT2, l));
            zzc(paramT1, i);
          }
          break;
        case 3: 
          if (zzb(paramT2, i))
          {
            zzyh.zza(paramT1, l, zzyh.zzl(paramT2, l));
            zzc(paramT1, i);
          }
          break;
        case 2: 
          if (zzb(paramT2, i))
          {
            zzyh.zza(paramT1, l, zzyh.zzl(paramT2, l));
            zzc(paramT1, i);
          }
          break;
        case 1: 
          if (zzb(paramT2, i))
          {
            zzyh.zza(paramT1, l, zzyh.zzn(paramT2, l));
            zzc(paramT1, i);
          }
          break;
        case 0: 
          if (zzb(paramT2, i))
          {
            zzyh.zza(paramT1, l, zzyh.zzo(paramT2, l));
            zzc(paramT1, i);
          }
          break;
        }
        i += 3;
      }
      if (!zzcbg)
      {
        zzxl.zza(zzcbn, paramT1, paramT2);
        if (zzcbe) {
          zzxl.zza(zzcbo, paramT1, paramT2);
        }
      }
      return;
    }
    throw new NullPointerException();
  }
  
  public final void zzu(T paramT)
  {
    int i = zzcbj;
    while (i < zzcbk)
    {
      long l = zzbq(zzcbi[i]) & 0xFFFFF;
      Object localObject = zzyh.zzp(paramT, l);
      if (localObject != null) {
        zzyh.zza(paramT, l, zzcbp.zzab(localObject));
      }
      i += 1;
    }
    int j = zzcbi.length;
    i = zzcbk;
    while (i < j)
    {
      zzcbm.zzb(paramT, zzcbi[i]);
      i += 1;
    }
    zzcbn.zzu(paramT);
    if (zzcbe) {
      zzcbo.zzu(paramT);
    }
  }
}
