package com.google.android.gms.common.api.internal;

import android.support.annotation.WorkerThread;

abstract class zaau
  implements Runnable
{
  private zaau(zaak paramZaak) {}
  
  /* Error */
  @WorkerThread
  public void run()
  {
    // Byte code:
    //   0: aload_0
    //   1: getfield 12	com/google/android/gms/common/api/internal/zaau:zagi	Lcom/google/android/gms/common/api/internal/zaak;
    //   4: invokestatic 29	com/google/android/gms/common/api/internal/zaak:zac	(Lcom/google/android/gms/common/api/internal/zaak;)Ljava/util/concurrent/locks/Lock;
    //   7: invokeinterface 34 1 0
    //   12: invokestatic 40	java/lang/Thread:interrupted	()Z
    //   15: istore_1
    //   16: iload_1
    //   17: ifeq +16 -> 33
    //   20: aload_0
    //   21: getfield 12	com/google/android/gms/common/api/internal/zaau:zagi	Lcom/google/android/gms/common/api/internal/zaak;
    //   24: invokestatic 29	com/google/android/gms/common/api/internal/zaak:zac	(Lcom/google/android/gms/common/api/internal/zaak;)Ljava/util/concurrent/locks/Lock;
    //   27: invokeinterface 43 1 0
    //   32: return
    //   33: aload_0
    //   34: invokevirtual 46	com/google/android/gms/common/api/internal/zaau:zaan	()V
    //   37: aload_0
    //   38: getfield 12	com/google/android/gms/common/api/internal/zaau:zagi	Lcom/google/android/gms/common/api/internal/zaak;
    //   41: invokestatic 29	com/google/android/gms/common/api/internal/zaak:zac	(Lcom/google/android/gms/common/api/internal/zaak;)Ljava/util/concurrent/locks/Lock;
    //   44: invokeinterface 43 1 0
    //   49: return
    //   50: astore_2
    //   51: goto +28 -> 79
    //   54: astore_2
    //   55: aload_0
    //   56: getfield 12	com/google/android/gms/common/api/internal/zaau:zagi	Lcom/google/android/gms/common/api/internal/zaak;
    //   59: invokestatic 50	com/google/android/gms/common/api/internal/zaak:zad	(Lcom/google/android/gms/common/api/internal/zaak;)Lcom/google/android/gms/common/api/internal/zabe;
    //   62: aload_2
    //   63: invokevirtual 56	com/google/android/gms/common/api/internal/zabe:zab	(Ljava/lang/RuntimeException;)V
    //   66: aload_0
    //   67: getfield 12	com/google/android/gms/common/api/internal/zaau:zagi	Lcom/google/android/gms/common/api/internal/zaak;
    //   70: invokestatic 29	com/google/android/gms/common/api/internal/zaak:zac	(Lcom/google/android/gms/common/api/internal/zaak;)Ljava/util/concurrent/locks/Lock;
    //   73: invokeinterface 43 1 0
    //   78: return
    //   79: aload_0
    //   80: getfield 12	com/google/android/gms/common/api/internal/zaau:zagi	Lcom/google/android/gms/common/api/internal/zaak;
    //   83: invokestatic 29	com/google/android/gms/common/api/internal/zaak:zac	(Lcom/google/android/gms/common/api/internal/zaak;)Ljava/util/concurrent/locks/Lock;
    //   86: invokeinterface 43 1 0
    //   91: aload_2
    //   92: athrow
    // Local variable table:
    //   start	length	slot	name	signature
    //   0	93	0	this	zaau
    //   15	2	1	bool	boolean
    //   50	1	2	localObject	Object
    //   54	38	2	localRuntimeException	RuntimeException
    // Exception table:
    //   from	to	target	type
    //   12	16	50	finally
    //   33	37	50	finally
    //   55	66	50	finally
    //   12	16	54	java/lang/RuntimeException
    //   33	37	54	java/lang/RuntimeException
  }
  
  @WorkerThread
  protected abstract void zaan();
}
